Workbook

Sheet Key
A1: Guide to interpreting this cost-effectiveness analysis
A2: Sheet descriptions
E4: Main CEA | F4: This sheet contains the primary calculations that result in final cost-effectiveness estimates. This sheet draws on inputs from the "Inputs" sheet and inputs calculated in the other supplemental sheets listed below.
E5: Effective coverage | F5: This sheet contains our calculations of how much protection nets distributed in grantee programs provide compared to the protection provided by nets distributed in the trials that inform our treatment effect estimates.
E6: Counterfactual malaria | F6: This sheet contains our calculations of how high malaria mortality and prevalence rates would be in the absence of net distributions.
E7: Insecticide resistance | F7: This sheet contains our calculations of how much the protective effect of nets is reduced by insecticide resistance among malaria-transmitting mosquitos.
E8: Leverage/Funging | F8: This sheet contains our calculations of the impact that crowding in and crowding out funding by other contributors has on the benefits of the program.
E9: Inputs | F9: This sheet contains all of the manually entered input values informing the CEA, along with the sources and reasoning supporting them. This sheet also contains inputs sourced from the "GBD estimates" sheet.
E10: Net decay model | F10: This sheet contains our models of physical net decay over time, which inform calculations on the "Effective coverage" sheet.
E11: GBD estimates | F11: This sheet contains disease burden and population datasets downloaded from the Institute of Health Metrics (IHME)'s Global Burden of Disease (GBD) project.
E12: Simple CEA | F12: This sheet contains a simplified version of the CEA that is designed to be comparable to our CEAs of other programs.
E13: Confidence intervals | F13: This sheet contains our best guesses of the 25th and 75th percentile values for each of the parameters of our simple CEA.
E14: Sensitivity analysis | F14: This sheet contains the outputs of our sensitivity analysis that tests the cost-effectiveness ranges that would result from updating certain inputs to their 25th or 75th percentile values.
A16: Terminology key
C18: Terms specific to this CEA
E19: ITN | F19: Insecticide-treated nets (ITNs) are mosquito nets have have been treated with insecticidal chemicals designed to kill and/or repel mosquitoes. ITNs are an umbrella category of nets that include conventionally treated nets (CTNs), long-lasting insecticide-treated nets (LLINs), and newer types of nets like PBO and chlorfenapyr nets.
E20: LLIN | F20: Long-lasting insecticide-treated nets (LLINs) are mosquito nets that have been treated with insecticides using a method that extends the effectiveness of the insecticide for multiple years without retreatment. Some of the nets (which we sometimes refer to as "standard nets") distributed in programs we consider funding are LLINs.
E21: Pyrethroid | F21: A class of insecticides commonly used to treat LLINs. The pyrethroid compounds most commonly used to treat LLINs are permethrin, alpha-cypermethrin, and deltamethrin.
E22: CTN | F22: Conventionally treated nets (CTNs) are mosquito nets that must be re-treated with insecticide periodically to retain their effectiveness. The nets distributed in the trials informing our treatment effect estimates were CTNs.
E23: Dual AI nets | F23: Dual active ingredient (Dual AI) nets are LLINs that are treated with multiple insecticidal chemicals that have different mechanisms of action. These nets are typically treated with a pyrethroid plus another insecticide and are designed to combat pyrethroid-resistant mosquitoes.
E24: PBO | F24: Piperonyl butoxide (PBO) is a chemical used alongside pyrethroid insecticides to treat some types of LLINs ("PBO nets") to enhance their effectiveness against insecticide-resistant mosquitos. PBO is not itself an insecticidal chemical but acts as a "synergist" that inhibits the metabolic enzymes that grant mosquitoes immunity to pyrethroids.
E25: Chlorfenapyr | F25: The rate of new cases in a given unit of time.
E26: Incidence
E27: Prevalence | F27: The proportion of people with a disease or condition at or during a particular time period (regardless of when they first contracted it).
E28: Indirect malaria deaths | F28: Deaths in which malaria plays a causal role, but are attributed to another cause. For example, malaria may increase the likelihood of death from malnutrition or other infectious diseases. Malaria control interventions often have a larger effect on all-cause mortality than would be expected exclusively from declines in malaria-specific mortality, which we interpret as evidence that averting malaria may also avert deaths attributed to other causes.
E29: Insecticide resistance | F29: Immunity among mosquito populations to the insecticidal chemicals commonly used to treat LLINs. Insecticide resistance can inhibit the protective effect of nets against malaria transmission.
E30: Bioassay | F30: An insecticide resistance test that involves exposing mosquitos to an insecticidal chemical and measuring the proportion of mosquitos that are killed.
E31: Person-year of effective coverage | F31: We use "effective coverage" to refer to a level of protection against malaria equivalent to the protection provided by the nets distributed in the mortality studies we rely on. A "person-year" refers to the equivalent of one person receiving one year of effective coverage. This unit is a simplification. For example, because nets typically remain effective longer than a year, two person-years of coverage could actually reflect one person receiving effective coverage for two years.
C33: Terms used across GiveWell's CEAs
E34: Internal validity | F34: Describes an adjustment we make to the treatment effect of an intervention to account for the possibility that the treatment effects found in studies may not represent the true effect the intervention had on the populations studied.
E35: External validity | F35: Describes an adjustment we make to the treatment effect of an intervention to account for differences in the program implementation or populations treated in studies from the program implementation or populations treated by grantee programs.
E36: Leverage | F36: Describes a situation where a grantee's spending on a program causes other organizations or governments to contribute more to the program than they otherwise would have. In most cases, accounting for leverage increases cost-effectiveness
E37: Funging | F37: Describes a situation where a grantee's spending on a program causes other organizations or governments to contribute less to the program than they otherwise would have. In most cases, accounting for funging decreases cost-effectiveness.
E38: In-kind contributions | F38: Describes non-financial (e.g., staff time, office space) contributions to a program that might otherwise have been used for other activities or programs.
E39: Counterfactual | F39: In most cases, describes the state of the world that would exist if we did not provide funding to a grantee for a program. When discussing the "counterfactual value of other actors' spending," we are referring to how much benefit another organization's or government's spending would generate if it were spent on something other than the grantee program.
E40: Moral weights | F40: To compare cost-effectiveness across different programs, we use ‘moral weights’ to quantify the benefits of different program impacts (e.g. increased income vs reduced deaths). We benchmark the value of each benefit to a value of 1, which we define as the value of doubling someone’s consumption for one year.
E41: Philanthropic actors | F41: Non-governmental organizations (NGOs) providing funding to philanthropic programs.
A43: Unit and source key
C45: Unit labels used in the CEA
E46: # | F46: Number
E47: per 1k | F47: Rate per 1,000
E48: per 100k | F48: Rate per 100,000
E49: $ | F49: U.S. dollars
E50: ln($) | F50: The natural logarithm of a monetary value
E51: % | F51: Percentage
E52: ppt | F52: Percentage points
E53: UoV | F53: Units of value: an arbitrary unit GiveWell uses to compare the moral value of different types of outcomes, such as saving lives or increasing income
E54: xbenchmark | F54: Cost-effectiveness in terms of multiples of GiveWell's benchmark
C56: Source labels used in the CEA
E58: Input | F58: A value pulled from the "Inputs" sheet
E59: Calc | F59: A value calculated using other values in the same sheet
E60: Supp | F60: A value pulled from one of the sheets hosting supplemental calculations
E61: Main | F61: A value pulled from the "Main CEA" sheet
E62: Feed | F62: A value pulled from an earlier section within the same sheet
A64: GiveWell analyses informing this model
C66: Analyses specific to this CEA
E67: GW's model of LLIN coverage years compared to CTNs
E68: GW's insecticide resistance analysis
E69: GW's analysis of counterfactual scenarios on pre-existing nets
E70: GW's subnational counterfactual mortality calculations
E71: Updated GiveWell summary of ITN RCTs
E72: GW's analysis of the number of people covered per net
E73: GW's analysis of AMF net purchases by net type
E74: GW's analysis of Nigerian state-level population estimates
E75: GW's analysis of DRC net durability
E76: GW's analysis of malaria development effects size
C78: Analyses referenced across GiveWell's CEAs
E79: GW's moral weights and discount rate
E80: GW's analysis on estimating multiplier for benefits experienced by other household members
E81: GW's supplemental intervention-level adjustments
E82: GWs benchmark for evaluating cost effectiveness
E83: GW's analysis of the counterfactual value of other actors' spending
E84: GW's analysis of the counterfactual value of Global Fund spending

Sheet Main CEA
I1: Against Malaria Foundation
I2: Chad | J2: DRC | K2: Guinea | L2: Nigeria | M2: Nigeria | N2: South Sudan | O2: Togo | P2: Uganda
A3: Main calculations | F3: unit | G3: type | H3: Overall | L3: GF states | M3: PMI states
E4: Final cost-effectiveness estimate (pulled from below for visibility) | F4: =F203 -> xbenchmark | G4: main | H4: =H203 -> - | I4: =I203 -> 4.8202994 | J4: =J203 -> 14.629025 | K4: =K203 -> 22.79223 | L4: =L203 -> 16.778736 | M4: =M203 -> 13.250427 | N4: =N203 -> 7.1630004 | O4: =O203 -> 8.8061654 | P4: =P203 -> 15.60304
A5: Costs
C7: GiveWell costs
E8: Grant size | F8: =Inputs!F8 -> $ | G8: input | H8: =Inputs!H8 -> 1000000 | I8: =Inputs!I8 -> - | J8: =Inputs!J8 -> - | K8: =Inputs!K8 -> - | L8: =Inputs!L8 -> - | M8: =Inputs!M8 -> - | N8: =Inputs!N8 -> - | O8: =Inputs!O8 -> - | P8: =Inputs!P8 -> -
C10: Cost breakdown
E11: Percentage of total costs covered by the grantee | F11: =Inputs!F11 -> % | G11: input | H11: =Inputs!H11 -> - | I11: =Inputs!I11 -> 0.9562847 | J11: =Inputs!J11 -> 0.9449092 | K11: =Inputs!K11 -> 0.9562847 | L11: =Inputs!L11 -> 0.9613383 | M11: =Inputs!M11 -> 0.9613383 | N11: =Inputs!N11 -> 0.936798 | O11: =Inputs!O11 -> 0.9595745 | P11: =Inputs!P11 -> 0.9553321
E12: Percentage of total costs covered by other philanthropic actors | F12: =Inputs!F12 -> % | G12: input | H12: =Inputs!H12 -> - | I12: =Inputs!I12 -> 0 | J12: =Inputs!J12 -> 0 | K12: =Inputs!K12 -> 0 | L12: =Inputs!L12 -> 0 | M12: =Inputs!M12 -> 0 | N12: =Inputs!N12 -> 0 | O12: =Inputs!O12 -> 0 | P12: =Inputs!P12 -> 0
E13: Percentage of total costs covered by domestic governments | F13: =Inputs!F13 -> % | G13: input | H13: =Inputs!H13 -> - | I13: =Inputs!I13 -> 0.0437153 | J13: =Inputs!J13 -> 0.0550908 | K13: =Inputs!K13 -> 0.0437153 | L13: =Inputs!L13 -> 0.0386617 | M13: =Inputs!M13 -> 0.0386617 | N13: =Inputs!N13 -> 0.0632021 | O13: =Inputs!O13 -> 0.0404255 | P13: =Inputs!P13 -> 0.0446679
C15: Total costs
E16: Total spending by all contributors | F16: $ | G16: calc | H16: - | I16: =IF(I8="-",$H8/I11,I8/I11) -> 1045713.7 | J16: =IF(J8="-",$H8/J11,J8/J11) -> 1058302.7 | K16: =IF(K8="-",$H8/K11,K8/K11) -> 1045713.7 | L16: =IF(L8="-",$H8/L11,L8/L11) -> 1040216.5 | M16: =IF(M8="-",$H8/M11,M8/M11) -> 1040216.5 | N16: =IF(N8="-",$H8/N11,N8/N11) -> 1067466 | O16: =IF(O8="-",$H8/O11,O8/O11) -> 1042128.6 | P16: =IF(P8="-",$H8/P11,P8/P11) -> 1046756.4
C18: Total spending attributable to different actors
E19: Total spending contributed by grantee | F19: $ | G19: calc | H19: - | I19: =I11*I$16 -> 1000000 | J19: =J11*J$16 -> 1000000 | K19: =K11*K$16 -> 1000000 | L19: =L11*L$16 -> 1000000 | M19: =M11*M$16 -> 1000000 | N19: =N11*N$16 -> 1000000 | O19: =O11*O$16 -> 1000000 | P19: =P11*P$16 -> 1000000
E20: Total spending contributed by other philanthropic actors | F20: $ | G20: calc | H20: - | I20: =I12*I$16 -> 0 | J20: =J12*J$16 -> 0 | K20: =K12*K$16 -> 0 | L20: =L12*L$16 -> 0 | M20: =M12*M$16 -> 0 | N20: =N12*N$16 -> 0 | O20: =O12*O$16 -> 0 | P20: =P12*P$16 -> 0
E21: Total spending contributed by domestic governments | F21: $ | G21: calc | H21: - | I21: =I13*I$16 -> 45713.688 | J21: =J13*J$16 -> 58302.745 | K21: =K13*K$16 -> 45713.688 | L21: =L13*L$16 -> 40216.54 | M21: =M13*M$16 -> 40216.54 | N21: =N13*N$16 -> 67466.092 | O21: =O13*O$16 -> 42128.568 | P21: =P13*P$16 -> 46756.411
C23: Upstream / downstream spending
E24: Total spending causally upstream of donations to grantee | F24: $ | G24: calc | H24: - | I24: =SUM(I19:I20) -> 1000000 | J24: =SUM(J19:J20) -> 1000000 | K24: =SUM(K19:K20) -> 1000000 | L24: =SUM(L19:L20) -> 1000000 | M24: =SUM(M19:M20) -> 1000000 | N24: =SUM(N19:N20) -> 1000000 | O24: =SUM(O19:O20) -> 1000000 | P24: =SUM(P19:P20) -> 1000000
E25: Total spending causally downstream of donations to grantee | F25: $ | G25: calc | H25: - | I25: =I21 -> 45713.688 | J25: =J21 -> 58302.745 | K25: =K21 -> 45713.688 | L25: =L21 -> 40216.54 | M25: =M21 -> 40216.54 | N25: =N21 -> 67466.092 | O25: =O21 -> 42128.568 | P25: =P21 -> 46756.411
C27: Cost per net
E28: Total cost per insecticide-treated net (ITN) distributed | F28: =Inputs!F16 -> $ | G28: input | H28: =Inputs!H16 -> - | I28: =Inputs!I16 -> 3.93785 | J28: =Inputs!J16 -> 5.85033 | K28: =Inputs!K16 -> 3.93785 | L28: =Inputs!L16 -> 4.34117 | M28: =Inputs!M16 -> 4.34117 | N28: =Inputs!N16 -> 5.32824 | O28: =Inputs!O16 -> 3.66624 | P28: =Inputs!P16 -> 4.44504
E29: Upstream costs per ITN distributed | F29: $ | G29: calc | H29: - | I29: =(I24/I16)*I28 -> 3.7657057 | J29: =(J24/J16)*J28 -> 5.5280306 | K29: =(K24/K16)*K28 -> 3.7657057 | L29: =(L24/L16)*L28 -> 4.173333 | M29: =(M24/M16)*M28 -> 4.173333 | N29: =(N24/N16)*N28 -> 4.9914846 | O29: =(O24/O16)*O28 -> 3.5180304 | P29: =(P24/P16)*P28 -> 4.2464894
A31: Outputs
C33: Net usage
E34: Number of nets distributed | F34: # | G34: calc | H34: - | I34: =I19/I29 -> 265554.47 | J34: =J19/J29 -> 180896.25 | K34: =K19/K29 -> 265554.47 | L34: =L19/L29 -> 239616.63 | M34: =M19/M29 -> 239616.63 | N34: =N19/N29 -> 200341.2 | O34: =O19/O29 -> 284249.96 | P34: =P19/P29 -> 235488.64
E35: Proportion of distributed nets that were used in trials from the Pryce et al. 2018 meta-analysis | F35: =Inputs!F21 -> % | G35: input | H35: =Inputs!H21 -> 0.7 | I35: =Inputs!I21 -> - | J35: =Inputs!J21 -> - | K35: =Inputs!K21 -> - | L35: =Inputs!L21 -> - | M35: =Inputs!M21 -> - | N35: =Inputs!N21 -> - | O35: =Inputs!O21 -> - | P35: =Inputs!P21 -> -
E36: Adjustment for net usage in program contexts | F36: =Inputs!F22 -> % | G36: input | H36: =Inputs!H22 -> -0.1 | I36: =Inputs!I22 -> - | J36: =Inputs!J22 -> - | K36: =Inputs!K22 -> - | L36: =Inputs!L22 -> - | M36: =Inputs!M22 -> - | N36: =Inputs!N22 -> - | O36: =Inputs!O22 -> - | P36: =Inputs!P22 -> -
E37: Proportion of distributed nets that are used in program contexts | F37: % | G37: calc | H37: =H35*(1+H36) -> 0.63 | I37: - | J37: - | K37: - | L37: - | M37: - | N37: - | O37: - | P37: -
E38: Number of nets used | F38: # | G38: calc | H38: - | I38: =I34*$H37 -> 167299.32 | J38: =J34*$H37 -> 113964.64 | K38: =K34*$H37 -> 167299.32 | L38: =L34*$H37 -> 150958.48 | M38: =M34*$H37 -> 150958.48 | N38: =N34*$H37 -> 126214.95 | O38: =O34*$H37 -> 179077.47 | P38: =P34*$H37 -> 148357.84
C40: Net coverage
E41: Number of people sleeping under each used net | F41: =Inputs!F25 -> # | G41: input | H41: =Inputs!H25 -> - | I41: =Inputs!I25 -> 1.93645 | J41: =Inputs!J25 -> 2.15114 | K41: =Inputs!K25 -> 1.99095 | L41: =Inputs!L25 -> 1.93645 | M41: =Inputs!M25 -> 1.93645 | N41: =Inputs!N25 -> 1.93645 | O41: =Inputs!O25 -> 1.72163 | P41: =Inputs!P25 -> 1.76505
E42: Total people sleeping under distributed nets | F42: # | G42: calc | H42: - | I42: =I38*I41 -> 323966.77 | J42: =J38*J41 -> 245153.89 | K42: =K38*K41 -> 333084.58 | L42: =L38*L41 -> 292323.55 | M42: =M38*M41 -> 292323.55 | N42: =N38*N41 -> 244408.95 | O42: =O38*O41 -> 308305.15 | P42: =P38*P41 -> 261859.01
E43: Effective coverage years provided per net | F43: ='Effective coverage'!F145 -> # | G43: supp | H43: ='Effective coverage'!H145 -> - | I43: ='Effective coverage'!I145 -> 1.9656086 | J43: ='Effective coverage'!J145 -> 1.1925167 | K43: ='Effective coverage'!K145 -> 1.9656086 | L43: ='Effective coverage'!L145 -> 1.9656086 | M43: ='Effective coverage'!M145 -> 1.317121 | N43: ='Effective coverage'!N145 -> 1.269016 | O43: ='Effective coverage'!O145 -> 1.9656086 | P43: ='Effective coverage'!P145 -> 1.9656086
E44: Total person-years of effective coverage provided | F44: # | G44: calc | H44: - | I44: =I42*I43 -> 636791.87 | J44: =J42*J43 -> 292350.09 | K44: =K42*K43 -> 654713.92 | L44: =L42*L43 -> 574593.68 | M44: =M42*M43 -> 385025.49 | N44: =N42*N43 -> 310158.86 | O44: =O42*O43 -> 606007.26 | P44: =P42*P43 -> 514712.32
C46: Age distribution of population
E47: Total national population | F47: =Inputs!F28 -> # | G47: =Inputs!G28 -> input | H47: =Inputs!H28 -> - | I47: =Inputs!I28 -> 16398860 | J47: =Inputs!J28 -> 87670444 | K47: =Inputs!K28 -> 12643149 | L47: =Inputs!L28 -> 2.1482379e+08 | M47: =Inputs!M28 -> 2.1482379e+08 | ... P47: =Inputs!P28 -> 41117856
E48: National population under age 5 | F48: =Inputs!F29 -> # | G48: =Inputs!G29 -> input | H48: =Inputs!H29 -> - | I48: =Inputs!I29 -> 3332666.6 | J48: =Inputs!J29 -> 13629465 | K48: =Inputs!K29 -> 2143394.9 | L48: =Inputs!L29 -> 33521638 | M48: =Inputs!M29 -> 33521638 | ... P48: =Inputs!P29 -> 7089749.8
E49: National population age 5-14 | F49: =Inputs!F30 -> # | G49: =Inputs!G30 -> input | H49: =Inputs!H30 -> - | I49: =Inputs!I30 -> 4977421 | J49: =Inputs!J30 -> 24065680 | K49: =Inputs!K30 -> 3569794.5 | L49: =Inputs!L30 -> 60226437 | M49: =Inputs!M30 -> 60226437 | ... P49: =Inputs!P30 -> 11987722
E50: Proportion of population under age 5 | F50: # | G50: calc | H50: - | I50: =I48/I47 -> 0.20322551 | J50: =J48/J47 -> 0.15546249 | K50: =K48/K47 -> 0.16953015 | L50: =L48/L47 -> 0.15604249 | M50: =M48/M47 -> 0.15604249 | N50: =N48/N47 -> 0.16335034 | O50: =O48/O47 -> 0.14073742 | P50: =P48/P47 -> 0.17242508
E51: Proportion of population age 5-14 | F51: # | G51: calc | H51: - | I51: =I49/I47 -> 0.30352238 | J51: =J49/J47 -> 0.27450164 | K51: =K49/K47 -> 0.28235011 | L51: =L49/L47 -> 0.28035274 | M51: =M49/M47 -> 0.28035274 | N51: =N49/N47 -> 0.28569842 | O51: =O49/O47 -> 0.25661478 | P51: =P49/P47 -> 0.29154541
E52: Proportion of population over age 14 | F52: # | G52: calc | H52: - | I52: =1-SUM(I50:I51) -> 0.49325211 | J52: =1-SUM(J50:J51) -> 0.57003588 | K52: =1-SUM(K50:K51) -> 0.54811974 | L52: =1-SUM(L50:L51) -> 0.56360477 | M52: =1-SUM(M50:M51) -> 0.56360477 | N52: =1-SUM(N50:N51) -> 0.55095124 | O52: =1-SUM(O50:O51) -> 0.6026478 | P52: =1-SUM(P50:P51) -> 0.53602951
C54: Net coverage by age group
E55: Person-years of net coverage provided among people under age 5 | F55: # | G55: calc | H55: - | I55: =I$44*I50 -> 129412.35 | J55: =J$44*J50 -> 45449.472 | K55: =K$44*K50 -> 110993.75 | L55: =L$44*L50 -> 89661.027 | M55: =M$44*M50 -> 60080.335 | N55: =N$44*N50 -> 50664.555 | O55: =O$44*O50 -> 85287.898 | P55: =P$44*P50 -> 88749.315
E56: Person-years of net coverage provided among people age 5-14 | F56: # | G56: calc | H56: - | I56: =I$44*I51 -> 193280.59 | J56: =J$44*J51 -> 80250.579 | K56: =K$44*K51 -> 184858.55 | L56: =L$44*L51 -> 161088.91 | M56: =M$44*M51 -> 107942.95 | N56: =N$44*N51 -> 88611.898 | O56: =O$44*O51 -> 155510.42 | P56: =P$44*P51 -> 150062.01
E57: Person-years of net coverage provided among people over age 14 | F57: # | G57: calc | H57: - | I57: =I$44*I52 -> 314098.93 | J57: =J$44*J52 -> 166650.04 | K57: =K$44*K52 -> 358861.63 | L57: =L$44*L52 -> 323843.74 | M57: =M$44*M52 -> 217002.2 | N57: =N$44*N52 -> 170882.41 | O57: =O$44*O52 -> 365208.95 | P57: =P$44*P52 -> 275900.99
A59: Outcomes
C61: Mortality reduction among people under age 5
E62: Reduction in malaria incidence for children under age 5 receiving nets found in the Pryce et al. 2018 meta-analysis | F62: =Inputs!F132 -> % | G62: =Inputs!G132 -> input | H62: =Inputs!H132 -> 0.45 | I62: =Inputs!I132 -> - | J62: =Inputs!J132 -> - | K62: =Inputs!K132 -> - | L62: =Inputs!L132 -> - | M62: =Inputs!M132 -> - | ... P62: =Inputs!P132 -> -
E63: Implied reduction in malaria incidence for people under age 5 sleeping under nets | F63: % | G63: calc | H63: =H62/H35 -> 0.64285714 | I63: - | J63: - | K63: - | L63: - | M63: - | N63: - | O63: - | P63: -
E64: Internal validity adjustment | F64: =Inputs!F133 -> % | G64: =Inputs!G133 -> input | H64: =Inputs!H133 -> -0.05 | I64: =Inputs!I133 -> - | J64: =Inputs!J133 -> - | K64: =Inputs!K133 -> - | L64: =Inputs!L133 -> - | M64: =Inputs!M133 -> - | ... P64: =Inputs!P133 -> -
E65: External validity adjustment | F65: =Inputs!F134 -> % | G65: =Inputs!G134 -> input | H65: =Inputs!H134 -> -0.05 | I65: =Inputs!I134 -> - | J65: =Inputs!J134 -> - | K65: =Inputs!K134 -> - | L65: =Inputs!L134 -> - | M65: =Inputs!M134 -> - | ... P65: =Inputs!P134 -> -
E66: Adjustment for insecticide resistance | F66: ='Insecticide resistance'!F66 -> % | G66: supp | H66: ='Insecticide resistance'!H66 -> - | I66: ='Insecticide resistance'!I66 -> -0.58597602 | J66: ='Insecticide resistance'!J66 -> -0.03767824 | K66: ='Insecticide resistance'!K66 -> -0.20702271 | L66: ='Insecticide resistance'!L66 -> -0.1353111 | M66: ='Insecticide resistance'!M66 -> -0.1353111 | N66: ='Insecticide resistance'!N66 -> -0.30730661 | O66: ='Insecticide resistance'!O66 -> -0.32905969 | P66: ='Insecticide resistance'!P66 -> -0.11498383
E67: Expected reduction in malaria incidence among people under age 5 sleeping under nets | F67: % | G67: calc | H67: - | I67: =$H63*(1+$H64)*(1+$H65)*(1+I66) -> 0.24020784 | J67: =$H63*(1+$H64)*(1+$H65)*(1+J66) -> 0.55831846 | K67: =$H63*(1+$H64)*(1+$H65)*(1+K66) -> 0.46006843 | L67: =$H63*(1+$H64)*(1+$H65)*(1+L66) -> 0.50167397 | M67: =$H63*(1+$H64)*(1+$H65)*(1+M66) -> 0.50167397 | N67: =$H63*(1+$H64)*(1+$H65)*(1+N66) -> 0.40188586 | O67: =$H63*(1+$H64)*(1+$H65)*(1+O66) -> 0.38926519 | P67: =$H63*(1+$H64)*(1+$H65)*(1+P66) -> 0.51346742
E68: Ratio of the reduction in malaria mortality to the reduction in malaria incidence | F68: =Inputs!F135 -> % | G68: input | H68: =Inputs!H135 -> 1 | I68: =Inputs!I135 -> - | J68: =Inputs!J135 -> - | K68: =Inputs!K135 -> - | L68: =Inputs!L135 -> - | M68: =Inputs!M135 -> - | N68: =Inputs!N135 -> - | O68: =Inputs!O135 -> - | P68: =Inputs!P135 -> -
E69: Expected reduction in malaria mortality among people under age 5 sleeping under nets | F69: % | G69: calc | H69: - | I69: =I67*$H68 -> 0.24020784 | J69: =J67*$H68 -> 0.55831846 | K69: =K67*$H68 -> 0.46006843 | L69: =L67*$H68 -> 0.50167397 | M69: =M67*$H68 -> 0.50167397 | N69: =N67*$H68 -> 0.40188586 | O69: =O67*$H68 -> 0.38926519 | P69: =P67*$H68 -> 0.51346742
E70: Annual malaria mortality rate among 1-59-month-olds (2019) | F70: ='Counterfactual malaria'!F15 -> % | G70: supp | H70: ='Counterfactual malaria'!H15 -> - | I70: ='Counterfactual malaria'!I15 -> 0.0013189977 | J70: ='Counterfactual malaria'!J15 -> 0.0030564473 | K70: ='Counterfactual malaria'!K15 -> 0.0036739114 | L70: ='Counterfactual malaria'!L15 -> 0.0027048043 | M70: ='Counterfactual malaria'!M15 -> 0.0029065506 | N70: ='Counterfactual malaria'!N15 -> 0.0025161796 | O70: ='Counterfactual malaria'!O15 -> 0.0016391362 | P70: ='Counterfactual malaria'!P15 -> 0.0023504822
E71: Indirect malaria deaths per direct malaria death | F71: =Inputs!F136 -> # | G71: =Inputs!G136 -> input | H71: =Inputs!H136 -> 0.75 | I71: =Inputs!I136 -> - | J71: =Inputs!J136 -> - | K71: =Inputs!K136 -> - | L71: =Inputs!L136 -> - | M71: =Inputs!M136 -> - | ... P71: =Inputs!P136 -> -
E72: Total malaria-attributable mortality rate (including direct and indirect malaria deaths) | F72: % | G72: calc | H72: - | I72: =I70*(1+$H71) -> 0.002308246 | J72: =J70*(1+$H71) -> 0.0053487828 | K72: =K70*(1+$H71) -> 0.0064293449 | L72: =L70*(1+$H71) -> 0.0047334075 | M72: =M70*(1+$H71) -> 0.0050864635 | N72: =N70*(1+$H71) -> 0.0044033142 | O72: =O70*(1+$H71) -> 0.0028684883 | P72: =P70*(1+$H71) -> 0.0041133439
E73: Malaria-attributable mortality reduction as a result of seasonal malaria chemoprevention (SMC) | F73: ='Counterfactual malaria'!F26 -> ppt | G73: supp | H73: ='Counterfactual malaria'!H26 -> - | I73: ='Counterfactual malaria'!I26 -> 0.00091339 | J73: ='Counterfactual malaria'!J26 -> 0 | K73: ='Counterfactual malaria'!K26 -> 0 | L73: ='Counterfactual malaria'!L26 -> 0.00063457383 | M73: ='Counterfactual malaria'!M26 -> 0.001422762 | N73: ='Counterfactual malaria'!N26 -> 0.000434442 | O73: ='Counterfactual malaria'!O26 -> 0.00071024897 | P73: ='Counterfactual malaria'!P26 -> 0
E74: Total malaria-attributable mortality rate among 1-59-month-olds (adjusted for SMC) | F74: % | G74: calc | H74: - | I74: =I72-I73 -> 0.001394856 | J74: =J72-J73 -> 0.0053487828 | K74: =K72-K73 -> 0.0064293449 | L74: =L72-L73 -> 0.0040988337 | M74: =M72-M73 -> 0.0036637015 | N74: =N72-N73 -> 0.0039688722 | O74: =O72-O73 -> 0.0021582393 | P74: =P72-P73 -> 0.0041133439
E75: Baseline proportion of 1-59-month-old children sleeping under nets | F75: =Inputs!F137 -> % | G75: =Inputs!G137 -> input | H75: =Inputs!H137 -> - | I75: =Inputs!I137 -> 0.313 | J75: =Inputs!J137 -> 0.591 | K75: =Inputs!K137 -> 0.586 | L75: =Inputs!L137 -> 0.51 | M75: =Inputs!M137 -> 0.471 | ... P75: =Inputs!P137 -> 0.704
E76: Total malaria-attributable mortality rate among 1-59-month-olds in the absence of nets | F76: % | G76: calc | H76: - | I76: =I74/((1-I69)*I75+(1-I75)) -> 0.0015082541 | J76: =J74/((1-J69)*J75+(1-J75)) -> 0.0079828554 | K76: =K74/((1-K69)*K75+(1-K75)) -> 0.0088024997 | L76: =L74/((1-L69)*L75+(1-L75)) -> 0.0055081021 | M76: =M74/((1-M69)*M75+(1-M75)) -> 0.0047972319 | N76: =N74/((1-N69)*N75+(1-N75)) -> 0.004952001 | O76: =O74/((1-O69)*O75+(1-O75)) -> 0.0031254634 | P76: =P74/((1-P69)*P75+(1-P75)) -> 0.0064420077
E77: Total deaths averted among people under age 5 | F77: # | G77: calc | H77: - | I77: =I55*I76*I69 -> 46.885378 | J77: =J55*J76*J69 -> 202.56719 | K77: =K55*K76*K69 -> 449.49717 | L77: =L55*L76*L69 -> 247.75776 | M77: =M55*M76*M69 -> 144.59212 | N77: =N55*N76*N69 -> 100.82952 | O77: =O55*O76*O69 -> 103.76417 | P77: =P55*P76*P69 -> 293.56153
C79: Mortality reduction among people age 5 and older
E80: Malaria deaths among people under age 5 per year | F80: =Inputs!F140 -> # | G80: =Inputs!G140 -> input | H80: =Inputs!H140 -> - | I80: =Inputs!I140 -> 4525.7324 | J80: =Inputs!J140 -> 44077.948 | K80: =Inputs!K140 -> 8181.1025 | L80: =Inputs!L140 -> 44919.36 | M80: =Inputs!M140 -> 30014.76 | ... P80: =Inputs!P140 -> 17385.765
E81: Total malaria deaths per year across all age groups | F81: =Inputs!F141 -> # | G81: =Inputs!G141 -> input | H81: =Inputs!H141 -> - | I81: =Inputs!I141 -> 7194.1994 | J81: =Inputs!J141 -> 57160.155 | K81: =Inputs!K141 -> 11336.501 | L81: =Inputs!L141 -> 77647.61 | M81: =Inputs!M141 -> 55752.71 | ... P81: =Inputs!P141 -> 22586.593
E82: Malaria deaths among people age 5 and older | F82: # | G82: calc | H82: - | I82: =I81-I80 -> 2668.467 | J82: =J81-J80 -> 13082.206 | K82: =K81-K80 -> 3155.3986 | L82: =L81-L80 -> 32728.25 | M82: =M81-M80 -> 25737.95 | N82: =N81-N80 -> 1099.0096 | O82: =O81-O80 -> 3555.7799 | P82: =P81-P80 -> 5200.8271
E83: Number of malaria deaths among people age 5 and older per malaria death among people under age 5 | F83: % | G83: calc | H83: - | I83: =I82/I80 -> 0.58962102 | J83: =J82/J80 -> 0.29679708 | K83: =K82/K80 -> 0.38569356 | L83: =L82/L80 -> 0.7286001 | M83: =M82/M80 -> 0.85750977 | N83: =N82/N80 -> 0.27404647 | O83: =O82/O80 -> 1.890962 | P83: =P82/P80 -> 0.29914283
E84: Relative efficacy of ITNs for reducing mortality of people age 5 and older | F84: =Inputs!F142 -> % | G84: =Inputs!G142 -> input | H84: =Inputs!H142 -> 0.8 | I84: =Inputs!I142 -> - | J84: =Inputs!J142 -> - | K84: =Inputs!K142 -> - | L84: =Inputs!L142 -> - | M84: =Inputs!M142 -> - | ... P84: =Inputs!P142 -> -
E85: Total deaths averted among people age 5 and older | F85: # | G85: calc | H85: - | I85: =I77*I83*$H84 -> 22.115683 | J85: =J77*J83*$H84 -> 48.097081 | K85: =K77*K83*$H84 -> 138.69453 | L85: =L77*L83*$H84 -> 144.41306 | M85: =M77*M83*$H84 -> 99.191326 | N85: =N77*N83*$H84 -> 22.105579 | O85: =O77*O83*$H84 -> 156.97127 | P85: =P77*P83*$H84 -> 70.253462
C87: Malaria incidence reduction among people under age 15
E88: Malaria incidence among people under age 5 in the absence of a distribution | F88: ='Counterfactual malaria'!F36 -> % | G88: supp | H88: ='Counterfactual malaria'!H36 -> - | I88: ='Counterfactual malaria'!I36 -> 0.23896348 | J88: ='Counterfactual malaria'!J36 -> 1.3120882 | K88: ='Counterfactual malaria'!K36 -> 0.9790565 | L88: ='Counterfactual malaria'!L36 -> 0.83002573 | M88: ='Counterfactual malaria'!M36 -> 0.98734218 | N88: ='Counterfactual malaria'!N36 -> 0.73521426 | O88: ='Counterfactual malaria'!O36 -> 1.0648694 | P88: ='Counterfactual malaria'!P36 -> 1.0262111
E89: Malaria incidence among people age 5 to 14 in the absence of a distribution | F89: ='Counterfactual malaria'!F37 -> % | G89: supp | H89: ='Counterfactual malaria'!H37 -> - | I89: ='Counterfactual malaria'!I37 -> 0.23896348 | J89: ='Counterfactual malaria'!J37 -> 0.53498743 | K89: ='Counterfactual malaria'!K37 -> 0.40853064 | L89: ='Counterfactual malaria'!L37 -> 0.3611327 | M89: ='Counterfactual malaria'!M37 -> 0.42005795 | N89: ='Counterfactual malaria'!N37 -> 0.31164979 | O89: ='Counterfactual malaria'!O37 -> 0.44668425 | P89: ='Counterfactual malaria'!P37 -> 0.42903972
E90: Reduction in malaria incidence among people under age 5 sleeping under nets | F90: ppt | G90: calc | H90: - | I90: =I$67*I88 -> 0.057400901 | J90: =J$67*J88 -> 0.73256304 | K90: =K$67*K88 -> 0.45043298 | L90: =L$67*L88 -> 0.4164023 | M90: =M$67*M88 -> 0.49532387 | N90: =N$67*N88 -> 0.29547221 | O90: =O$67*O88 -> 0.41451657 | P90: =P$67*P88 -> 0.52692597
E91: Reduction in malaria incidence among people age 5 to 14 sleeping under nets | F91: ppt | G91: calc | H91: - | I91: =I$67*I89 -> 0.057400901 | J91: =J$67*J89 -> 0.29869336 | K91: =K$67*K89 -> 0.18795205 | L91: =L$67*L89 -> 0.18117087 | M91: =M$67*M89 -> 0.21073214 | N91: =N$67*N89 -> 0.12524764 | O91: =O$67*O89 -> 0.17387863 | P91: =P$67*P89 -> 0.22029792
E92: Malaria cases averted among people under age 5 | F92: # | G92: calc | H92: - | I92: =I90*I55 -> 7428.3855 | J92: =J90*J55 -> 33294.604 | K92: =K90*K55 -> 49995.244 | L92: =L90*L55 -> 37335.058 | M92: =M90*M55 -> 29759.224 | N92: =N90*N55 -> 14969.968 | O92: =O90*O55 -> 35353.247 | P92: =P90*P55 -> 46764.319
E93: Malaria cases averted among people age 5 to 14 | F93: # | G93: calc | H93: - | I93: =I91*I56 -> 11094.48 | J93: =J91*J56 -> 23970.315 | K93: =K91*K56 -> 34744.543 | L93: =L91*L56 -> 29184.619 | M93: =M91*M56 -> 22747.049 | N93: =N91*N56 -> 11098.431 | O93: =O91*O56 -> 27039.939 | P93: =P91*P56 -> 33058.349
C95: Long-term income increases for people under age 15
E96: Increase in annual income per malaria case averted among people under age 15 | F96: =Inputs!F145 -> % | G96: =Inputs!G145 -> input | H96: =Inputs!H145 -> 0.0058088 | I96: =Inputs!I145 -> - | J96: =Inputs!J145 -> - | K96: =Inputs!K145 -> - | L96: =Inputs!L145 -> - | M96: =Inputs!M145 -> - | ... P96: =Inputs!P145 -> -
E97: Adjusted increase in ln(income) per malaria case averted among people under age 15 | F97: ln($) | G97: calc | H97: =(ln(1+H96)-ln(1)) -> 0.005791994 | I97: - | J97: - | K97: - | L97: - | M97: - | N97: - | O97: - | P97: -
E98: Average number of years between nets being distributed and the beginning of long term benefits | F98: =Inputs!F146 -> # | G98: =Inputs!G146 -> input | H98: =Inputs!H146 -> 10 | I98: =Inputs!I146 -> - | J98: =Inputs!J146 -> - | K98: =Inputs!K146 -> - | L98: =Inputs!L146 -> - | M98: =Inputs!M146 -> - | ... P98: =Inputs!P146 -> -
E99: Discount rate for future benefits | F99: =Inputs!F147 -> % | G99: =Inputs!G147 -> input | H99: =Inputs!H147 -> 0.04 | I99: =Inputs!I147 -> - | J99: =Inputs!J147 -> - | K99: =Inputs!K147 -> - | L99: =Inputs!L147 -> - | M99: =Inputs!M147 -> - | ... P99: =Inputs!P147 -> -
E100: Discounted increase in ln(income) per malaria case averted among people under age 15 | F100: ln($) | G100: calc | H100: =H97/(1+H99)^H98 -> 0.0039128636 | I100: - | J100: - | K100: - | L100: - | M100: - | N100: - | O100: - | P100: -
E101: Expected number of years the long-term benefits of receiving nets will last | F101: =Inputs!F148 -> # | G101: =Inputs!G148 -> input | H101: =Inputs!H148 -> 40 | I101: =Inputs!I148 -> - | J101: =Inputs!J148 -> - | K101: =Inputs!K148 -> - | L101: =Inputs!L148 -> - | M101: =Inputs!M148 -> - | ... P101: =Inputs!P148 -> -
E102: Present value of individual lifetime benefits per malaria case averted among people under age 15 | F102: ln($) | G102: calc | H102: =pv(H99,H101,-H100,,1) -> 0.080544281 | I102: - | J102: - | K102: - | L102: - | M102: - | N102: - | O102: - | P102: -
E103: Multiplier for resource sharing within households | F103: =Inputs!F149 -> # | G103: =Inputs!G149 -> input | H103: =Inputs!H149 -> 2 | I103: =Inputs!I149 -> - | J103: =Inputs!J149 -> - | K103: =Inputs!K149 -> - | L103: =Inputs!L149 -> - | M103: =Inputs!M149 -> - | ... P103: =Inputs!P149 -> -
E104: Present value of total lifetime benefits per malaria case averted among people under age 15 | F104: ln($) | G104: calc | H104: =H102*H103 -> 0.16108856 | I104: - | J104: - | K104: - | L104: - | M104: - | N104: - | O104: - | P104: -
E105: Present value of increase in units of annual ln(income) among people under age 5 | F105: ln($) | G105: calc | H105: - | I105: =I92*$H104 -> 1196.6279 | J105: =J92*$H104 -> 5363.3799 | K105: =K92*$H104 -> 8053.662 | L105: =L92*$H104 -> 6014.2509 | M105: =M92*$H104 -> 4793.8706 | N105: =N92*$H104 -> 2411.4907 | O105: =O92*$H104 -> 5695.0037 | P105: =P92*$H104 -> 7533.197
E106: Present value of increase in units of annual ln(income) among people age 5 to 14 | F106: ln($) | G106: calc | H106: - | I106: =I93*$H104 -> 1787.1938 | J106: =J93*$H104 -> 3861.3436 | K106: =K93*$H104 -> 5596.9484 | L106: =L93*$H104 -> 4701.3083 | M106: =M93*$H104 -> 3664.2894 | N106: =N93*$H104 -> 1787.8303 | O106: =O93*$H104 -> 4355.8248 | P106: =P93*$H104 -> 5325.3219
E107: Total present value of units of increase in units of annual ln(income) among people under age 15 | F107: ln($) | G107: calc | H107: - | I107: =SUM(I105:I106) -> 2983.8218 | J107: =SUM(J105:J106) -> 9224.7235 | K107: =SUM(K105:K106) -> 13650.61 | L107: =SUM(L105:L106) -> 10715.559 | M107: =SUM(M105:M106) -> 8458.1601 | N107: =SUM(N105:N106) -> 4199.321 | O107: =SUM(O105:O106) -> 10050.829 | P107: =SUM(P105:P106) -> 12858.519
A109: Value of outcomes
C111: Units of value from mortality reduction among people under age 5
E112: Value assigned to averting a malaria-attributable death of a person under age 5 | F112: =Inputs!F154 -> UoV | G112: =Inputs!G154 -> input | H112: =Inputs!H154 -> 116.25262 | I112: =Inputs!I154 -> - | J112: =Inputs!J154 -> - | K112: =Inputs!K154 -> - | L112: =Inputs!L154 -> - | M112: =Inputs!M154 -> - | ... P112: =Inputs!P154 -> -
E113: Units of value from under-5 deaths averted (before accounting for leverage and funging) | F113: UoV | G113: calc | H113: - | I113: =I77*$H112 -> 5450.548 | J113: =J77*$H112 -> 23548.966 | K113: =K77*$H112 -> 52255.223 | L113: =L77*$H112 -> 28802.488 | M113: =M77*$H112 -> 16809.213 | N113: =N77*$H112 -> 11721.695 | O113: =O77*$H112 -> 12062.856 | P113: =P77*$H112 -> 34127.297
C115: Units of value from mortality reduction among people age 5 and older
E116: Value assigned to averting a malaria-attributable death of a person age 5 or older | F116: =Inputs!F155 -> UoV | G116: =Inputs!G155 -> input | H116: =Inputs!H155 -> 73.1914 | I116: =Inputs!I155 -> - | J116: =Inputs!J155 -> - | K116: =Inputs!K155 -> - | L116: =Inputs!L155 -> - | M116: =Inputs!M155 -> - | ... P116: =Inputs!P155 -> -
E117: Units of value from 5-and-over deaths averted (before accounting for leverage and funging) | F117: UoV | G117: calc | H117: - | I117: =I85*$H116 -> 1618.6778 | J117: =J85*$H116 -> 3520.2927 | K117: =K85*$H116 -> 10151.247 | L117: =L85*$H116 -> 10569.794 | M117: =M85*$H116 -> 7259.952 | N117: =N85*$H116 -> 1617.9383 | O117: =O85*$H116 -> 11488.947 | P117: =P85*$H116 -> 5141.9492
C119: Units of value from long-term income increases for people under age 15
E120: Value assigned to increasing ln(consumption) by one unit for one person for one year | F120: =Inputs!F157 -> UoV | G120: =Inputs!G157 -> input | H120: =Inputs!H157 -> 1.442695 | I120: =Inputs!I157 -> - | J120: =Inputs!J157 -> - | K120: =Inputs!K157 -> - | L120: =Inputs!L157 -> - | M120: =Inputs!M157 -> - | ... P120: =Inputs!P157 -> -
...

Sheet Effective coverage
I1: Against Malaria Foundation
I2: Chad | J2: DRC | K2: Guinea | L2: Nigeria | M2: Nigeria | N2: South Sudan | O2: Togo | P2: Uganda
A3: Supplemental calculations for effective coverage years provided per net | F3: unit | G3: type | H3: Overall | L3: GF states | M3: PMI states
E4: Final cost-effectiveness estimate (pulled from "Main calcs" sheet for visibility) | F4: ='Main CEA'!F203 -> xbenchmark | G4: main | H4: ='Main CEA'!H203 -> - | I4: ='Main CEA'!I203 -> 4.8202994 | J4: ='Main CEA'!J203 -> 14.629025 | K4: ='Main CEA'!K203 -> 22.79223 | L4: ='Main CEA'!L203 -> 16.778736 | M4: ='Main CEA'!M203 -> 13.250427 | N4: ='Main CEA'!N203 -> 7.1630004 | O4: ='Main CEA'!O203 -> 8.8061654 | P4: ='Main CEA'!P203 -> 15.60304
A5: Net survival
C7: Net coverage years lost to attrition
E8: Percentage of nets remaining in use two years after the CTN distributions in trials from the Pryce et al. 2018 meta-analysis | F8: =Inputs!F35 -> % | G8: =Inputs!G35 -> input | H8: =Inputs!H35 -> 1 | I8: =Inputs!I35 -> - | J8: =Inputs!J35 -> - | K8: =Inputs!K35 -> - | L8: =Inputs!L35 -> - | M8: =Inputs!M35 -> - | ... P8: =Inputs!P35 -> -
E9: Average percentage of nets remaining in use during the 1st year after an ITN distribution | F9: =Inputs!F36 -> % | G9: =Inputs!G36 -> input | H9: =Inputs!H36 -> 0.9539455 | I9: =Inputs!I36 -> - | J9: =Inputs!J36 -> - | K9: =Inputs!K36 -> - | L9: =Inputs!L36 -> - | M9: =Inputs!M36 -> - | ... P9: =Inputs!P36 -> -
E10: Average percentage of nets remaining in use during the 2nd year after an ITN distribution | F10: =Inputs!F37 -> % | G10: =Inputs!G37 -> input | H10: =Inputs!H37 -> 0.8345774 | I10: =Inputs!I37 -> - | J10: =Inputs!J37 -> - | K10: =Inputs!K37 -> - | L10: =Inputs!L37 -> - | M10: =Inputs!M37 -> - | ... P10: =Inputs!P37 -> -
E11: =Inputs!E38 -> Average percentage of nets remaining in use during the 3rd year after an ITN distribution | F11: =Inputs!F38 -> % | G11: =Inputs!G38 -> input | H11: =Inputs!H38 -> 0.6935533 | I11: =Inputs!I38 -> - | J11: =Inputs!J38 -> - | K11: =Inputs!K38 -> - | L11: =Inputs!L38 -> - | ... P11: =Inputs!P38 -> -
C13: Net coverage years lost due to physical decay
E14: Percentage of remaining nets lost due to physical damage at the midpoint of the 1st year after an ITN distribution | F14: =Inputs!F41 -> % | G14: =Inputs!G41 -> input | H14: =Inputs!H41 -> 0.0346098 | I14: =Inputs!I41 -> - | J14: =Inputs!J41 -> - | K14: =Inputs!K41 -> - | L14: =Inputs!L41 -> - | M14: =Inputs!M41 -> - | ... P14: =Inputs!P41 -> -
E15: Percentage of remaining nets lost due to physical damage at the midpoint of the 2nd year after an ITN distribution | F15: =Inputs!F42 -> % | G15: =Inputs!G42 -> input | H15: =Inputs!H42 -> 0.1536925 | I15: =Inputs!I42 -> - | J15: =Inputs!J42 -> - | K15: =Inputs!K42 -> - | L15: =Inputs!L42 -> - | M15: =Inputs!M42 -> - | ... P15: =Inputs!P42 -> -
E16: Percentage of remaining nets lost due to physical damage at the midpoint of the 3rd year after an ITN distribution | F16: =Inputs!F43 -> % | G16: =Inputs!G43 -> input | H16: =Inputs!H43 -> 0.3453212 | I16: =Inputs!I43 -> - | J16: =Inputs!J43 -> - | K16: =Inputs!K43 -> - | L16: =Inputs!L43 -> - | M16: =Inputs!M43 -> - | ... P16: =Inputs!P43 -> -
E17: Ratio of physical net decay in trials of CTN distributions from the Pryce et al. 2018 meta-analysis compared to physical net decay from grantee ITN distributions | F17: =Inputs!F44 -> % | G17: =Inputs!G44 -> input | H17: =Inputs!H44 -> 0.33 | I17: =Inputs!I44 -> - | J17: =Inputs!J44 -> - | K17: =Inputs!K44 -> - | L17: =Inputs!L44 -> - | M17: =Inputs!M44 -> - | ... P17: =Inputs!P44 -> -
E18: Percentage of remaining nets lost due to physical damage at the midpoint of the 1st year after a CTN distribution from the Pryce et al. 2018 meta-analysis | F18: % | G18: calc | H18: =H14*(1-H$17) -> 0.023188566 | I18: - | J18: - | K18: - | L18: - | M18: - | N18: - | O18: - | P18: -
E19: Percentage of remaining nets lost due to physical damage at the midpoint of the 2nd year after a CTN distribution from the Pryce et al. 2018 meta-analysis | F19: % | G19: calc | H19: =H15*(1-H$17) -> 0.10297397 | I19: - | J19: - | K19: - | L19: - | M19: - | N19: - | O19: - | P19: -
E20: Average percentage of remaining nets lost due to physical damage over the two-year period following a CTN distribution from the Pryce et al. 2018 meta-analysis | F20: % | G20: calc | H20: =AVERAGE(H18:H19) -> 0.06308127 | I20: - | J20: - | K20: - | L20: - | M20: - | N20: - | O20: - | P20: -
C22: Net coverage years lost due to insecticide decay
E23: Proportion of net coverage lost due to insecticide decay for CTNs distributed in trials from the Pryce et al. 2018 meta-analysis | F23: =Inputs!F47 -> % | G23: =Inputs!G47 -> input | H23: =Inputs!H47 -> 0 | I23: =Inputs!I47 -> - | J23: =Inputs!J47 -> - | K23: =Inputs!K47 -> - | L23: =Inputs!L47 -> - | M23: =Inputs!M47 -> - | ... P23: =Inputs!P47 -> -
E24: Proportion of net coverage lost due to insecticide decay for ITNs distributed in grantee distributions | F24: =Inputs!F48 -> % | G24: =Inputs!G48 -> input | H24: =Inputs!H48 -> 0 | I24: =Inputs!I48 -> - | J24: =Inputs!J48 -> - | K24: =Inputs!K48 -> - | L24: =Inputs!L48 -> - | M24: =Inputs!M48 -> - | ... P24: =Inputs!P48 -> -
C26: Total net coverage years lost
E27: Coverage years lost per year for CTNs distributed in trials from the Pryce et al. 2018 meta-analysis | F27: # | G27: calc | H27: =(1-H8)+(H8*H20)+(H8*H20*H23) -> 0.06308127 | I27: - | J27: - | K27: - | L27: - | M27: - | N27: - | O27: - | P27: -
E28: Coverage years lost during the 1st year after a grantee ITN distribution | F28: # | G28: calc | H28: =(1-H9)+(H9*H14)+(H9*H14*H$24) -> 0.079070363 | I28: - | J28: - | K28: - | L28: - | M28: - | N28: - | O28: - | P28: -
E29: Coverage years lost during the 2nd year after a grantee ITN distribution | F29: # | G29: calc | H29: =(1-H10)+(H10*H15)+(H10*H15*H$24) -> 0.29369089 | I29: - | J29: - | K29: - | L29: - | M29: - | N29: - | O29: - | P29: -
E30: Coverage years lost during the 3rd year after a grantee ITN distribution | F30: # | G30: calc | H30: =(1-H11)+(H11*H16)+(H11*H16*H$24) -> 0.54594536 | I30: - | J30: - | K30: - | L30: - | M30: - | N30: - | O30: - | P30: -
C32: Trial-equivalent coverage years provided per distributed net
E33: Effective net coverage years provided by a CTN distributed in a trial from the Pryce et al. 2018 meta-analysis (reference value) | F33: =Inputs!F51 -> # | G33: =Inputs!G51 -> input | H33: =Inputs!H51 -> 1 | I33: =Inputs!I51 -> - | J33: =Inputs!J51 -> - | K33: =Inputs!K51 -> - | L33: =Inputs!L51 -> - | M33: =Inputs!M51 -> - | ... P33: =Inputs!P51 -> -
E34: Effective coverage years provided per net in the 1st year after a grantee ITN distribution | F34: # | G34: calc | H34: =H$33-(H28-H$27) -> 0.98401091 | I34: - | J34: - | K34: - | L34: - | M34: - | N34: - | O34: - | P34: -
E35: Effective coverage years provided per net in the 2nd year after a grantee ITN distribution | F35: # | G35: calc | H35: =H$33-(H29-H$27) -> 0.76939038 | I35: - | J35: - | K35: - | L35: - | M35: - | N35: - | O35: - | P35: -
E36: Effective coverage years provided per net in the 3rd year after a grantee ITN distribution | F36: # | G36: calc | H36: =H$33-(H30-H$27) -> 0.51713591 | I36: - | J36: - | K36: - | L36: - | M36: - | N36: - | O36: - | P36: -
E37: Total effective coverage years provided per net over the three-year period following a grantee ITN distribution for reference ITNs | F37: # | G37: calc | H37: =SUM(H34:H36) -> 2.2705372 | I37: - | J37: - | K37: - | L37: - | M37: - | N37: - | O37: - | P37: -
C39: Adjustment for generic ITNs
E40: Total effective coverage years provided per net over the three-year period following a grantee ITN distribution of reference ITNs | F40: # | G40: calc | H40: =H37 -> 2.2705372 | I40: - | J40: - | K40: - | L40: - | M40: - | N40: - | O40: - | P40: -
E41: Adjustment for reduced net coverage provided by generic ITNs | F41: =Inputs!F54 -> % | G41: =Inputs!G54 -> input | H41: =Inputs!H54 -> -0.15 | I41: =Inputs!I54 -> - | J41: =Inputs!J54 -> - | K41: =Inputs!K54 -> - | L41: =Inputs!L54 -> - | M41: =Inputs!M54 -> - | ... P41: =Inputs!P54 -> -
E42: Total effective coverage years provided per net over the three-year period following a grantee ITN distribution for generic ITNs | F42: # | G42: calc | H42: =H37*(1+H41) -> 1.9299566 | I42: - | J42: - | K42: - | L42: - | M42: - | N42: - | O42: - | P42: -
C44: Breakdown of net types purchased for distributions
E45: Expected proportion of ITNs purchased that are generic ITNs | F45: =Inputs!F57 -> % | G45: =Inputs!G57 -> input | H45: =Inputs!H57 -> 0.465547 | I45: =Inputs!I57 -> - | J45: =Inputs!J57 -> - | K45: =Inputs!K57 -> - | L45: =Inputs!L57 -> - | M45: =Inputs!M57 -> - | ... P45: =Inputs!P57 -> -
C47: Effective coverage years per net, incorporating generic ITNs
E48: Overall effective coverage years provided per net over the three-year period following a grantee ITN distribution, before adjusting for lower net durability in DRC | F48: # | G48: calc | H48: =H40*(1-H45)+(H42*H45) -> 2.1119809 | I48: - | J48: - | K48: - | L48: - | M48: - | N48: - | O48: - | P48: -
C50: Adjustment for lower net durability in DRC
E51: Adjustment for lower net durability in DRC than in other countries | F51: =Inputs!F60 -> % | G51: =Inputs!G60 -> input | H51: =Inputs!H60 -> - | I51: =Inputs!I60 -> - | J51: =Inputs!J60 -> -0.1737044 | K51: =Inputs!K60 -> - | L51: =Inputs!L60 -> - | M51: =Inputs!M60 -> - | ... P51: =Inputs!P60 -> -
E52: Overall effective coverage years provided per net over the three-year period following a grantee ITN distribution, after adjusting for lower net durability in DRC | F52: # | G52: calc | H52: - | I52: =$H48*IF(I51<>"-",(1+I51),1) -> 2.1119809 | J52: =$H48*IF(J51<>"-",(1+J51),1) -> 1.7451206 | K52: =$H48*IF(K51<>"-",(1+K51),1) -> 2.1119809 | L52: =$H48*IF(L51<>"-",(1+L51),1) -> 2.1119809 | M52: =$H48*IF(M51<>"-",(1+M51),1) -> 2.1119809 | N52: =$H48*IF(N51<>"-",(1+N51),1) -> 2.1119809 | O52: =$H48*IF(O51<>"-",(1+O51),1) -> 2.1119809 | P52: =$H48*IF(P51<>"-",(1+P51),1) -> 2.1119809
A54: Net decay rates
C56: Extrapolated net decay rate over a six-year period
E57: Effective coverage years provided per net in the 1st year after a grantee ITN distribution | F57: =F34 -> # | G57: feed | H57: =H34 -> 0.98401091 | I57: =I34 -> - | J57: =J34 -> - | K57: =K34 -> - | L57: =L34 -> - | M57: =M34 -> - | N57: =N34 -> - | O57: =O34 -> - | P57: =P34 -> -
E58: Effective coverage years provided per net in the 2nd year after a grantee ITN distribution | F58: =F35 -> # | G58: feed | H58: =H35 -> 0.76939038 | I58: =I35 -> - | J58: =J35 -> - | K58: =K35 -> - | L58: =L35 -> - | M58: =M35 -> - | N58: =N35 -> - | O58: =O35 -> - | P58: =P35 -> -
E59: Effective coverage years provided per net in the 3rd year after a grantee ITN distribution | F59: =F36 -> # | G59: feed | H59: =H36 -> 0.51713591 | I59: =I36 -> - | J59: =J36 -> - | K59: =K36 -> - | L59: =L36 -> - | M59: =M36 -> - | N59: =N36 -> - | O59: =O36 -> - | P59: =P36 -> -
E60: Effective coverage years provided per net in the 4th year after a grantee ITN distribution | F60: =Inputs!F63 -> # | G60: =Inputs!G63 -> input | H60: =Inputs!H63 -> 0.218549 | I60: =Inputs!I63 -> - | J60: =Inputs!J63 -> - | K60: =Inputs!K63 -> - | L60: =Inputs!L63 -> - | M60: =Inputs!M63 -> - | ... P60: =Inputs!P63 -> -
E61: Effective coverage years provided per net in the 5th year after a grantee ITN distribution | F61: =Inputs!F64 -> # | G61: =Inputs!G64 -> input | H61: =Inputs!H64 -> 0.065935 | I61: =Inputs!I64 -> - | J61: =Inputs!J64 -> - | K61: =Inputs!K64 -> - | L61: =Inputs!L64 -> - | M61: =Inputs!M64 -> - | ... P61: =Inputs!P64 -> -
E62: Effective coverage years provided per net in the 6th year after a grantee ITN distribution | F62: =Inputs!F65 -> # | G62: =Inputs!G65 -> input | H62: =Inputs!H65 -> 0.010989 | I62: =Inputs!I65 -> - | J62: =Inputs!J65 -> - | K62: =Inputs!K65 -> - | L62: =Inputs!L65 -> - | M62: =Inputs!M65 -> - | ... P62: =Inputs!P65 -> -
C64: Extrapolated net decay rate, adjusted for the inclusion of generic ITNs
E65: Overall adjustment for reduced net coverage provided by generic ITNs | F65: % | G65: calc | H65: =(H48-H40)/H40 -> -0.06983205 | I65: - | J65: - | K65: - | L65: - | M65: - | N65: - | O65: - | P65: -
E66: Adjusted effective coverage years provided per net in the 1st year after a grantee ITN distribution | F66: # | G66: calc | H66: =H57*(1+H$65) -> 0.91529541 | I66: - | J66: - | K66: - | L66: - | M66: - | N66: - | O66: - | P66: -
E67: Adjusted effective coverage years provided per net in the 2nd year after a grantee ITN distribution | F67: # | G67: calc | H67: =H58*(1+H$65) -> 0.71566228 | I67: - | J67: - | K67: - | L67: - | M67: - | N67: - | O67: - | P67: -
E68: Adjusted effective coverage years provided per net in the 3rd year after a grantee ITN distribution | F68: # | G68: calc | H68: =H59*(1+H$65) -> 0.48102325 | I68: - | J68: - | K68: - | L68: - | M68: - | N68: - | O68: - | P68: -
E69: Adjusted effective coverage years provided per net in the 4th year after a grantee ITN distribution | F69: # | G69: calc | H69: =H60*(1+H$65) -> 0.20328728 | I69: - | J69: - | K69: - | L69: - | M69: - | N69: - | O69: - | P69: -
E70: Adjusted effective coverage years provided per net in the 5th year after a grantee ITN distribution | F70: # | G70: calc | H70: =H61*(1+H$65) -> 0.061330624 | I70: - | J70: - | K70: - | L70: - | M70: - | N70: - | O70: - | P70: -
E71: Adjusted effective coverage years provided per net in the 6th year after a grantee ITN distribution | F71: # | G71: calc | H71: =H62*(1+H$65) -> 0.010221616 | I71: - | J71: - | K71: - | L71: - | M71: - | N71: - | O71: - | P71: -
C73: Adjusted net decay rate adjusted for lower net durability in DRC
E74: Adjustment for lower effective coverage years provided in the 1st year after a grantee ITN distribution in DRC | F74: =Inputs!F68 -> % | G74: =Inputs!G68 -> input | H74: =Inputs!H68 -> - | I74: =Inputs!I68 -> - | J74: =Inputs!J68 -> -0.1165152 | K74: =Inputs!K68 -> - | L74: =Inputs!L68 -> - | M74: =Inputs!M68 -> - | ... P74: =Inputs!P68 -> -
E75: Adjustment for lower effective coverage years provided in the 2nd year after a grantee ITN distribution in DRC | F75: =Inputs!F69 -> % | G75: =Inputs!G69 -> input | H75: =Inputs!H69 -> - | I75: =Inputs!I69 -> - | J75: =Inputs!J69 -> -0.1609735 | K75: =Inputs!K69 -> - | L75: =Inputs!L69 -> - | M75: =Inputs!M69 -> - | ... P75: =Inputs!P69 -> -
E76: Adjustment for lower effective coverage years provided in the 3rd year after a grantee ITN distribution in DRC | F76: =Inputs!F70 -> % | G76: =Inputs!G70 -> input | H76: =Inputs!H70 -> - | I76: =Inputs!I70 -> - | J76: =Inputs!J70 -> -0.3246594 | K76: =Inputs!K70 -> - | L76: =Inputs!L70 -> - | M76: =Inputs!M70 -> - | ... P76: =Inputs!P70 -> -
E77: Adjustment for lower effective coverage years provided in the 4th year after a grantee ITN distribution in DRC | F77: % | G77: calc | H77: - | I77: - | J77: =MAX(-1,(J76+((J76-J75)/J75)*J76)) -> -0.6547893 | K77: - | L77: - | M77: - | N77: - | O77: - | P77: -
E78: Adjustment for lower effective coverage years provided in the 5th year after a grantee ITN distribution in DRC | F78: % | G78: calc | H78: - | I78: - | J78: =MAX(-1,(J77+((J77-J76)/J76)*J77)) -> -1 | K78: - | L78: - | M78: - | N78: - | O78: - | P78: -
E79: Adjustment for lower effective coverage years provided in the 6th year after a grantee ITN distribution in DRC | F79: % | G79: calc | H79: - | I79: - | J79: =MAX(-1,(J78+((J78-J77)/J77)*J78)) -> -1 | K79: - | L79: - | M79: - | N79: - | O79: - | P79: -
C81: Final extrapolated net decay rate, after all adjustments
E82: Final effective coverage years provided per net in the 1st year after a grantee ITN distribution | F82: # | G82: calc | H82: - | I82: =IF(I74<>"-",$H66*(1+I74),$H66) -> 0.91529541 | J82: =IF(J74<>"-",$H66*(1+J74),$H66) -> 0.80864958 | K82: =IF(K74<>"-",$H66*(1+K74),$H66) -> 0.91529541 | L82: =IF(L74<>"-",$H66*(1+L74),$H66) -> 0.91529541 | M82: =IF(M74<>"-",$H66*(1+M74),$H66) -> 0.91529541 | N82: =IF(N74<>"-",$H66*(1+N74),$H66) -> 0.91529541 | O82: =IF(O74<>"-",$H66*(1+O74),$H66) -> 0.91529541 | P82: =IF(P74<>"-",$H66*(1+P74),$H66) -> 0.91529541
E83: Final effective coverage years provided per net in the 2nd year after a grantee ITN distribution | F83: # | G83: calc | H83: - | I83: =IF(I75<>"-",$H67*(1+I75),$H67) -> 0.71566228 | J83: =IF(J75<>"-",$H67*(1+J75),$H67) -> 0.60045961 | K83: =IF(K75<>"-",$H67*(1+K75),$H67) -> 0.71566228 | L83: =IF(L75<>"-",$H67*(1+L75),$H67) -> 0.71566228 | M83: =IF(M75<>"-",$H67*(1+M75),$H67) -> 0.71566228 | N83: =IF(N75<>"-",$H67*(1+N75),$H67) -> 0.71566228 | O83: =IF(O75<>"-",$H67*(1+O75),$H67) -> 0.71566228 | P83: =IF(P75<>"-",$H67*(1+P75),$H67) -> 0.71566228
E84: Final effective coverage years provided per net in the 3rd year after a grantee ITN distribution | F84: # | G84: calc | H84: - | I84: =IF(I76<>"-",$H68*(1+I76),$H68) -> 0.48102325 | J84: =IF(J76<>"-",$H68*(1+J76),$H68) -> 0.32485453 | K84: =IF(K76<>"-",$H68*(1+K76),$H68) -> 0.48102325 | L84: =IF(L76<>"-",$H68*(1+L76),$H68) -> 0.48102325 | M84: =IF(M76<>"-",$H68*(1+M76),$H68) -> 0.48102325 | N84: =IF(N76<>"-",$H68*(1+N76),$H68) -> 0.48102325 | O84: =IF(O76<>"-",$H68*(1+O76),$H68) -> 0.48102325 | P84: =IF(P76<>"-",$H68*(1+P76),$H68) -> 0.48102325
E85: Final effective coverage years provided per net in the 4th year after a grantee ITN distribution | F85: # | G85: calc | H85: - | I85: =IF(I77<>"-",$H69*(1+I77),$H69) -> 0.20328728 | J85: =IF(J77<>"-",$H69*(1+J77),$H69) -> 0.070176942 | K85: =IF(K77<>"-",$H69*(1+K77),$H69) -> 0.20328728 | L85: =IF(L77<>"-",$H69*(1+L77),$H69) -> 0.20328728 | M85: =IF(M77<>"-",$H69*(1+M77),$H69) -> 0.20328728 | N85: =IF(N77<>"-",$H69*(1+N77),$H69) -> 0.20328728 | O85: =IF(O77<>"-",$H69*(1+O77),$H69) -> 0.20328728 | P85: =IF(P77<>"-",$H69*(1+P77),$H69) -> 0.20328728
E86: Final effective coverage years provided per net in the 5th year after a grantee ITN distribution | F86: # | G86: calc | H86: - | I86: =IF(I78<>"-",$H70*(1+I78),$H70) -> 0.061330624 | J86: =IF(J78<>"-",$H70*(1+J78),$H70) -> 0 | K86: =IF(K78<>"-",$H70*(1+K78),$H70) -> 0.061330624 | L86: =IF(L78<>"-",$H70*(1+L78),$H70) -> 0.061330624 | M86: =IF(M78<>"-",$H70*(1+M78),$H70) -> 0.061330624 | N86: =IF(N78<>"-",$H70*(1+N78),$H70) -> 0.061330624 | O86: =IF(O78<>"-",$H70*(1+O78),$H70) -> 0.061330624 | P86: =IF(P78<>"-",$H70*(1+P78),$H70) -> 0.061330624
E87: Final effective coverage years provided per net in the 6th year after a grantee ITN distribution | F87: # | G87: calc | H87: - | I87: =IF(I79<>"-",$H71*(1+I79),$H71) -> 0.010221616 | J87: =IF(J79<>"-",$H71*(1+J79),$H71) -> 0 | K87: =IF(K79<>"-",$H71*(1+K79),$H71) -> 0.010221616 | L87: =IF(L79<>"-",$H71*(1+L79),$H71) -> 0.010221616 | M87: =IF(M79<>"-",$H71*(1+M79),$H71) -> 0.010221616 | N87: =IF(N79<>"-",$H71*(1+N79),$H71) -> 0.010221616 | O87: =IF(O79<>"-",$H71*(1+O79),$H71) -> 0.010221616 | P87: =IF(P79<>"-",$H71*(1+P79),$H71) -> 0.010221616
A89: Changes in net distribution intervals
C91: Time intervals between distributions in different scenarios
E92: Standard number of months between ITN distributions as modeled in this CEA | F92: =Inputs!F73 -> # | G92: =Inputs!G73 -> input | H92: =Inputs!H73 -> 36 | I92: =Inputs!I73 -> - | J92: =Inputs!J73 -> - | K92: =Inputs!K73 -> - | L92: =Inputs!L73 -> - | M92: =Inputs!M73 -> - | ... P92: =Inputs!P73 -> -
E93: Expected number of months between the previous net distribution and the upcoming distribution in the absence of a grant | F93: =Inputs!F74 -> # | G93: =Inputs!G74 -> input | H93: =Inputs!H74 -> - | I93: =Inputs!I74 -> - | J93: =Inputs!J74 -> 42 | K93: =Inputs!K74 -> - | L93: =Inputs!L74 -> - | M93: =Inputs!M74 -> 45 | ... P93: =Inputs!P74 -> -
E94: Expected number of months between the previous net distribution and the upcoming distribution if a grant is made | F94: =Inputs!F75 -> # | G94: =Inputs!G75 -> input | H94: =Inputs!H75 -> - | I94: =Inputs!I75 -> - | J94: =Inputs!J75 -> 33 | K94: =Inputs!K75 -> - | L94: =Inputs!L75 -> - | M94: =Inputs!M75 -> 36 | ... P94: =Inputs!P75 -> -
E95: Expected reduction in number of months between the previous net distribution and the upcoming distribution if a grant is made | F95: # | G95: calc | H95: - | I95: =IF(I93<>"-",I93-I94,"-") -> - | J95: =IF(J93<>"-",J93-J94,"-") -> 9 | K95: =IF(K93<>"-",K93-K94,"-") -> - | L95: =IF(L93<>"-",L93-L94,"-") -> - | M95: =IF(M93<>"-",M93-M94,"-") -> 9 | N95: =IF(N93<>"-",N93-N94,"-") -> 10 | O95: =IF(O93<>"-",O93-O94,"-") -> - | P95: =IF(P93<>"-",P93-P94,"-") -> -
C97: Costs per distributed net per year for different distribution intervals
E98: Total cost per insecticide-treated net (ITN) distributed | F98: =IF(F93<>"-",Inputs!F16,"-") -> $ | G98: =IF(G93<>"-",Inputs!G16,"-") -> input | H98: =IF(H93<>"-",Inputs!H16,"-") -> - | I98: =IF(I93<>"-",Inputs!I16,"-") -> - | J98: =IF(J93<>"-",Inputs!J16,"-") -> 5.85033 | K98: =IF(K93<>"-",Inputs!K16,"-") -> - | L98: =IF(L93<>"-",Inputs!L16,"-") -> - | M98: =IF(M93<>"-",Inputs!M16,"-") -> 4.34117 | ... P98: =IF(P93<>"-",Inputs!P16,"-") -> -
E99: Cost per net distributed per year for a standard 36-month distribution interval | F99: $ | G99: calc | H99: - | I99: =IF(I93<>"-",I98/($H92/12),"-") -> - | J99: =IF(J93<>"-",J98/($H92/12),"-") -> 1.95011 | K99: =IF(K93<>"-",K98/($H92/12),"-") -> - | L99: =IF(L93<>"-",L98/($H92/12),"-") -> - | M99: =IF(M93<>"-",M98/($H92/12),"-") -> 1.4470567 | N99: =IF(N93<>"-",N98/($H92/12),"-") -> 1.77608 | O99: =IF(O93<>"-",O98/($H92/12),"-") -> - | P99: =IF(P93<>"-",P98/($H92/12),"-") -> -
E100: Cost per net distributed per year in the absence of a grant | F100: $ | G100: calc | H100: - | I100: =IF(I93<>"-",I98/(I93/12),"-") -> - | J100: =IF(J93<>"-",J98/(J93/12),"-") -> 1.6715229 | K100: =IF(K93<>"-",K98/(K93/12),"-") -> - | L100: =IF(L93<>"-",L98/(L93/12),"-") -> - | M100: =IF(M93<>"-",M98/(M93/12),"-") -> 1.1576453 | N100: =IF(N93<>"-",N98/(N93/12),"-") -> 1.420864 | O100: =IF(O93<>"-",O98/(O93/12),"-") -> - | P100: =IF(P93<>"-",P98/(P93/12),"-") -> -
E101: Cost per net distributed per year if a grant is made | F101: $ | G101: calc | H101: - | I101: =IF(I93<>"-",I98/(I94/12),"-") -> - | J101: =IF(J93<>"-",J98/(J94/12),"-") -> 2.1273927 | K101: =IF(K93<>"-",K98/(K94/12),"-") -> - | L101: =IF(L93<>"-",L98/(L94/12),"-") -> - | M101: =IF(M93<>"-",M98/(M94/12),"-") -> 1.4470567 | N101: =IF(N93<>"-",N98/(N94/12),"-") -> 1.8268251 | O101: =IF(O93<>"-",O98/(O94/12),"-") -> - | P101: =IF(P93<>"-",P98/(P94/12),"-") -> -
E102: Change in cost per net distributed per year as a result of a grant shortening the time interval between distributions | F102: $ | G102: calc | H102: - | I102: =IF(I93<>"-",I101-I100,"-") -> - | J102: =IF(J93<>"-",J101-J100,"-") -> 0.45586987 | K102: =IF(K93<>"-",K101-K100,"-") -> - | L102: =IF(L93<>"-",L101-L100,"-") -> - | M102: =IF(M93<>"-",M101-M100,"-") -> 0.28941133 | N102: =IF(N93<>"-",N101-N100,"-") -> 0.40596114 | O102: =IF(O93<>"-",O101-O100,"-") -> - | P102: =IF(P93<>"-",P101-P100,"-") -> -
C104: Coverage years provided per year for different distribution intervals
E105: Average coverage years provided per net for a standard 36-month distribution interval | F105: # | G105: supp | H105: - | I105: {=IF(I93<>"-",INDEX('Net decay model'!$I$17:$I$71,MATCH($H92,'Net decay model'!$G$17:$G$71)),"-")} -> - | J105: {=IF(J93<>"-",INDEX('Net decay model'!$D$17:$D$71,MATCH($H92,'Net decay model'!$B$17:$B$71)),"-")} -> 0.58373939 | K105: {=IF(K93<>"-",INDEX('Net decay model'!$I$17:$I$71,MATCH($H92,'Net decay model'!$G$17:$G$71)),"-")} -> - | L105: {=IF(L93<>"-",INDEX('Net decay model'!$I$17:$I$71,MATCH($H92,'Net decay model'!$G$17:$G$71)),"-")} -> - | M105: {=IF(M93<>"-",INDEX('Net decay model'!$I$17:$I$71,MATCH($H92,'Net decay model'!$G$17:$G$71)),"-")} -> 0.6987124 | N105: {=IF(N93<>"-",INDEX('Net decay model'!$I$17:$I$71,MATCH($H92,'Net decay model'!$G$17:$G$71)),"-")} -> 0.6987124 | O105: {=IF(O93<>"-",INDEX('Net decay model'!$I$17:$I$71,MATCH($H92,'Net decay model'!$G$17:$G$71)),"-")} -> - | P105: {=IF(P93<>"-",INDEX('Net decay model'!$I$17:$I$71,MATCH($H92,'Net decay model'!$G$17:$G$71)),"-")} -> -
E106: Average coverage years provided per net per year over the length of the distribution interval in the absence of a grant | F106: # | G106: supp | H106: - | I106: {=IF(I93<>"-",INDEX('Net decay model'!$I$17:$I$71,MATCH(I93,'Net decay model'!$G$17:$G$71)),"-")} -> - | J106: {=IF(J93<>"-",INDEX('Net decay model'!$D$17:$D$71,MATCH(J93,'Net decay model'!$B$17:$B$71)),"-")} -> 0.51948293 | K106: {=IF(K93<>"-",INDEX('Net decay model'!$I$17:$I$71,MATCH(K93,'Net decay model'!$G$17:$G$71)),"-")} -> - | L106: {=IF(L93<>"-",INDEX('Net decay model'!$I$17:$I$71,MATCH(L93,'Net decay model'!$G$17:$G$71)),"-")} -> - | M106: {=IF(M93<>"-",INDEX('Net decay model'!$I$17:$I$71,MATCH(M93,'Net decay model'!$G$17:$G$71)),"-")} -> 0.60778556 | N106: {=IF(N93<>"-",INDEX('Net decay model'!$I$17:$I$71,MATCH(N93,'Net decay model'!$G$17:$G$71)),"-")} -> 0.60778556 | O106: {=IF(O93<>"-",INDEX('Net decay model'!$I$17:$I$71,MATCH(O93,'Net decay model'!$G$17:$G$71)),"-")} -> - | P106: {=IF(P93<>"-",INDEX('Net decay model'!$I$17:$I$71,MATCH(P93,'Net decay model'!$G$17:$G$71)),"-")} -> -
E107: Average coverage years provided per net per year over the distribution interval if a grant is made | F107: # | G107: supp | H107: - | I107: {=IF(I94<>"-",INDEX('Net decay model'!$I$17:$I$71,MATCH(I94,'Net decay model'!$G$17:$G$71)),"-")} -> - | J107: {=IF(J94<>"-",INDEX('Net decay model'!$D$17:$D$71,MATCH(J94,'Net decay model'!$B$17:$B$71)),"-")} -> 0.61594532 | K107: {=IF(K94<>"-",INDEX('Net decay model'!$I$17:$I$71,MATCH(K94,'Net decay model'!$G$17:$G$71)),"-")} -> - | L107: {=IF(L94<>"-",INDEX('Net decay model'!$I$17:$I$71,MATCH(L94,'Net decay model'!$G$17:$G$71)),"-")} -> - | M107: {=INDEX('Net decay model'!$I$17:$I$71,MATCH(M94,'Net decay model'!$G$17:$G$71))} -> 0.6987124 | N107: {=INDEX('Net decay model'!$I$17:$I$71,MATCH(N94,'Net decay model'!$G$17:$G$71))} -> 0.70861676 | O107: {=IF(O94<>"-",INDEX('Net decay model'!$I$17:$I$71,MATCH(O94,'Net decay model'!$G$17:$G$71)),"-")} -> - | P107: {=IF(P94<>"-",INDEX('Net decay model'!$I$17:$I$71,MATCH(P94,'Net decay model'!$G$17:$G$71)),"-")} -> -
E108: Change in average coverage years provided per net per year as a result of a grant shortening the time interval between distributions | F108: # | G108: calc | H108: - | I108: =IF(I93<>"-",I107-I106,"-") -> - | J108: =IF(J93<>"-",J107-J106,"-") -> 0.096462387 | K108: =IF(K93<>"-",K107-K106,"-") -> - | L108: =IF(L93<>"-",L107-L106,"-") -> - | M108: =IF(M93<>"-",M107-M106,"-") -> 0.090926836 | N108: =IF(N93<>"-",N107-N106,"-") -> 0.1008312 | O108: =IF(O93<>"-",O107-O106,"-") -> - | P108: =IF(P93<>"-",P107-P106,"-") -> -
C110: Adjustment for shortening the interval between distributions
E111: Cost per coverage year provided per net per year for a standard 36-month distribution interval | F111: $ | G111: calc | H111: - | I111: =IF(I93<>"-",I99/I105,"-") -> - | J111: =IF(J93<>"-",J99/J105,"-") -> 3.3407202 | K111: =IF(K93<>"-",K99/K105,"-") -> - | L111: =IF(L93<>"-",L99/L105,"-") -> - | M111: =IF(M93<>"-",M99/M105,"-") -> 2.0710333 | N111: =IF(N93<>"-",N99/N105,"-") -> 2.5419329 | O111: =IF(O93<>"-",O99/O105,"-") -> - | P111: =IF(P93<>"-",P99/P105,"-") -> -
E112: Cost per incremental coverage year provided per net per year as a result of a grant shortening the time interval between distributions | F112: $ | G112: calc | H112: - | I112: =IF(I93<>"-",I102/I108,"-") -> - | J112: =IF(J93<>"-",J102/J108,"-") -> 4.7258821 | K112: =IF(K93<>"-",K102/K108,"-") -> - | L112: =IF(L93<>"-",L102/L108,"-") -> - | M112: =IF(M93<>"-",M102/M108,"-") -> 3.1829034 | N112: =IF(N93<>"-",N102/N108,"-") -> 4.0261461 | O112: =IF(O93<>"-",O102/O108,"-") -> - | P112: =IF(P93<>"-",P102/P108,"-") -> -
E113: Cost-effectiveness of shortening the time interval between distributions as a proportion of the cost-effectiveness of funding a standard 36-month interval that wouldn't have happened otherwise | F113: % | G113: calc | H113: - | I113: =IF(I93<>"-",I111/I112,"-") -> - | J113: =IF(J93<>"-",J111/J112,"-") -> 0.70689876 | K113: =IF(K93<>"-",K111/K112,"-") -> - | L113: =IF(L93<>"-",L111/L112,"-") -> - | M113: =IF(M93<>"-",M111/M112,"-") -> 0.65067427 | N113: =IF(N93<>"-",N111/N112,"-") -> 0.63135634 | O113: =IF(O93<>"-",O111/O112,"-") -> - | P113: =IF(P93<>"-",P111/P112,"-") -> -
E114: Adjustment for program impact being to move distributions closer together | F114: % | G114: calc | H114: - | I114: =IF(I93<>"-",I113-1,0) -> 0 | J114: =IF(J93<>"-",J113-1,0) -> -0.29310124 | K114: =IF(K93<>"-",K113-1,0) -> 0 | L114: =IF(L93<>"-",L113-1,0) -> 0 | M114: =IF(M93<>"-",M113-1,0) -> -0.34932573 | N114: =IF(N93<>"-",N113-1,0) -> -0.36864366 | O114: =IF(O93<>"-",O113-1,0) -> 0 | P114: =IF(P93<>"-",P113-1,0) -> 0
A116: Residual nets from previous distributions
C118: Time intervals between distributions in different scenarios
E119: Standard number of months between ITN distributions as modeled in this CEA | F119: =F92 -> # | G119: feed | H119: =H92 -> 36 | I119: =I92 -> - | J119: =J92 -> - | K119: =K92 -> - | L119: =L92 -> - | M119: =M92 -> - | N119: =N92 -> - | O119: =O92 -> - | P119: =P92 -> -
E120: Expected number of months between the previous net distribution and the upcoming distribution in the absence of a grant | F120: =F93 -> # | G120: feed | H120: =H93 -> - | I120: =I93 -> - | J120: =J93 -> 42 | K120: =K93 -> - | L120: =L93 -> - | M120: =M93 -> 45 | N120: =N93 -> 45 | O120: =O93 -> - | P120: =P93 -> -
E121: Expected number of months between the previous net distribution and the upcoming distribution if a grant is made | F121: =F94 -> # | G121: feed | H121: =H94 -> - | I121: =I94 -> - | J121: =J94 -> 33 | K121: =K94 -> - | L121: =L94 -> - | M121: =M94 -> 36 | N121: =N94 -> 35 | O121: =O94 -> - | P121: =P94 -> -
...

Sheet Counterfactual malaria
I1: Against Malaria Foundation
I2: Chad | J2: DRC | K2: Guinea | L2: Nigeria | M2: Nigeria | N2: South Sudan | O2: Togo | P2: Uganda
A3: Supplemental calculations for counterfactual malaria mortality and incidence | F3: unit | G3: type | H3: Overall | L3: GF states | M3: PMI states
E4: Final cost-effectiveness estimate (pulled from "Main calcs" sheet for visibility) | F4: ='Main CEA'!F203 -> xbenchmark | G4: main | H4: ='Main CEA'!H203 -> - | I4: ='Main CEA'!I203 -> 4.8202994 | J4: ='Main CEA'!J203 -> 14.629025 | K4: ='Main CEA'!K203 -> 22.79223 | L4: ='Main CEA'!L203 -> 16.778736 | M4: ='Main CEA'!M203 -> 13.250427 | N4: ='Main CEA'!N203 -> 7.1630004 | O4: ='Main CEA'!O203 -> 8.8061654 | P4: ='Main CEA'!P203 -> 15.60304
A5: Counterfactual malaria mortality among 1-59-month-olds
C7: Population estimates
E8: Population age 1-11 months (2019) | F8: =Inputs!F85 -> # | G8: =Inputs!G85 -> input | H8: =Inputs!H85 -> - | I8: =Inputs!I85 -> 679765.58 | J8: =Inputs!J85 -> 2588275.6 | K8: =Inputs!K85 -> 418381.76 | L8: =Inputs!L85 -> 3254748 | M8: =Inputs!M85 -> 1982320 | ... P8: =Inputs!P85 -> 1389726.8
E9: Population age 12-59 months (2019) | F9: =Inputs!F86 -> # | G9: =Inputs!G86 -> input | H9: =Inputs!H86 -> - | I9: =Inputs!I86 -> 2593740.2 | J9: =Inputs!J86 -> 10821149 | K9: =Inputs!K86 -> 1689051.3 | L9: =Inputs!L86 -> 12757890 | M9: =Inputs!M86 -> 7939853 | ... P9: =Inputs!P86 -> 5581405.2
C11: Baseline malaria mortality
E12: Annual malaria mortality rate among 1-11-month-olds (2019) | F12: =Inputs!F89 -> per 100k | G12: =Inputs!G89 -> input | H12: =Inputs!H89 -> - | I12: =Inputs!I89 -> 206.31696 | J12: =Inputs!J89 -> 676.67097 | K12: =Inputs!K89 -> 597.02458 | L12: =Inputs!L89 -> 279.38 | M12: =Inputs!M89 -> 339.26 | ... P12: =Inputs!P89 -> 535.97224
E13: Annual malaria mortality rate among 12-59-month-olds (2019) | F13: =Inputs!F90 -> per 100k | G13: =Inputs!G90 -> input | H13: =Inputs!H90 -> - | I13: =Inputs!I90 -> 112.39657 | J13: =Inputs!J90 -> 216.90017 | K13: =Inputs!K90 -> 310.51042 | L13: =Inputs!L90 -> 268.21 | M13: =Inputs!M90 -> 278.52 | ... P13: =Inputs!P90 -> 160.12047
E14: Total malaria deaths among children aged 1-59 months per year (2019) | F14: # | G14: calc | H14: - | I14: =(I12*I8+I13*I9)/100000 -> 4317.7465 | J14: =(J12*J8+J13*J9)/100000 -> 40985.199 | K14: =(K12*K8+K13*K9)/100000 -> 7742.5222 | L14: =(L12*L8+L13*L9)/100000 -> 43311.052 | M14: =(M12*M8+M13*M9)/100000 -> 28839.297 | N14: =(N12*N8+N13*N9)/100000 -> 3747.2961 | O14: =(O12*O8+O13*O9)/100000 -> 1798.2641 | P14: =(P12*P8+P13*P9)/100000 -> 16385.522
E15: Annual malaria mortality rate among 1-59-month-olds (2019) | F15: % | G15: calc | H15: - | I15: =I14/SUM(I8:I9) -> 0.0013189977 | J15: =J14/SUM(J8:J9) -> 0.0030564473 | K15: =K14/SUM(K8:K9) -> 0.0036739114 | L15: =L14/SUM(L8:L9) -> 0.0027048043 | M15: =M14/SUM(M8:M9) -> 0.0029065506 | N15: =N14/SUM(N8:N9) -> 0.0025161796 | O15: =O14/SUM(O8:O9) -> 0.0016391362 | P15: =P14/SUM(P8:P9) -> 0.0023504822
C17: Adjusting for deaths averted by seasonal malaria chemoprevention (SMC)
E18: Target population of 3-59 month-olds for seasonal malaria chemoprevention programs (SMC) | F18: =Inputs!F93 -> # | G18: =Inputs!G93 -> input | H18: =Inputs!H93 -> - | I18: =Inputs!I93 -> - | J18: =Inputs!J93 -> - | K18: =Inputs!K93 -> - | L18: =Inputs!L93 -> 6450000 | M18: =Inputs!M93 -> 8960943 | ... P18: =Inputs!P93 -> -
E19: Total population age 1-59 months | F19: # | G19: calc | H19: - | I19: - | J19: - | K19: - | L19: =SUM(L8:L9) -> 16012638 | M19: =SUM(M8:M9) -> 9922173 | N19: =SUM(N8:N9) -> 1489280.1 | O19: =SUM(O8:O9) -> 1097080.4 | P19: -
E20: Proportion of total population age 1-59 months living in areas where SMC is implemented (calculated) | F20: % | G20: calc | H20: =IF(H18="-","-",H18/H19) -> - | I20: =IF(I18="-","-",I18/I19) -> - | J20: =IF(J18="-","-",J18/J19) -> - | K20: =IF(K18="-","-",K18/K19) -> - | L20: =IF(L18="-","-",L18/L19) -> 0.40280683 | M20: =IF(M18="-","-",M18/M19) -> 0.90312304 | N20: =IF(N18="-","-",N18/N19) -> - | O20: =IF(O18="-","-",O18/O19) -> 0.44664003 | P20: =IF(P18="-","-",P18/P19) -> -
E21: Proportion of total population age 1-59 months living in areas where SMC is implemented | F21: =Inputs!F94 -> % | G21: =Inputs!G94 -> input | H21: =Inputs!H94 -> - | I21: =Inputs!I94 -> - | J21: =Inputs!J94 -> - | K21: =Inputs!K94 -> - | L21: =Inputs!L94 -> - | M21: =Inputs!M94 -> - | ... Q21: =Inputs!Q94
E22: Probability that available bed nets would be targeted across the country evenly in the absence of grantee support | F22: =Inputs!F95 -> % | G22: =Inputs!G95 -> input | H22: =Inputs!H95 -> - | I22: =Inputs!I95 -> - | J22: =Inputs!J95 -> - | K22: =Inputs!K95 -> - | L22: =Inputs!L95 -> - | M22: =Inputs!M95 -> - | N22: - | O22: =Inputs!O95 -> 0.7 | P22: =Inputs!P95 -> -
E23: Probability that available bed nets would be targeted at non-SMC areas in the absence of grantee support | F23: =Inputs!F96 -> % | G23: =Inputs!G96 -> input | H23: =Inputs!H96 -> - | I23: =Inputs!I96 -> - | J23: =Inputs!J96 -> - | K23: =Inputs!K96 -> - | L23: =Inputs!L96 -> - | M23: =Inputs!M96 -> - | N23: - | O23: =Inputs!O96 -> 0.3 | P23: =Inputs!P96 -> -
E24: Proportion of counterfactually distributed nets distributed in areas where SMC is implemented | F24: % | G24: calc | H24: - | I24: 1 | J24: =IF(J22="-",IF(J20="-",IF(J21="-","-",J21),J20),(J20*J22)+J23) -> - | K24: =IF(K22="-",IF(K20="-",IF(K21="-","-",K21),K20),(K20*K22)+K23) -> - | L24: =IF(L22="-",IF(L20="-",IF(L21="-","-",L21),L20),(L20*L22)+L23) -> 0.40280683 | M24: =IF(M22="-",IF(M20="-",IF(M21="-","-",M21),M20),(M20*M22)+M23) -> 0.90312304 | N24: =IF(N22="-",IF(N20="-",IF(N21="-","-",N21),N20),(N20*N22)+N23) -> 0.3 | O24: =IF(O22="-",IF(O20="-",IF(O21="-","-",O21),O20),(O20*O22)+O23) -> 0.61264802 | P24: =IF(P22="-",IF(P20="-",IF(P21="-","-",P21),P20),(P20*P22)+P23) -> -
E25: Malaria-attributable deaths averted by SMC per year among 1-59-month-olds living in areas where SMC is implemented | F25: =Inputs!F97 -> per 1k | G25: =Inputs!G97 -> input | H25: =Inputs!H97 -> - | I25: =Inputs!I97 -> 0.91339 | J25: =Inputs!J97 -> 0 | K25: =Inputs!K97 -> 0 | L25: =Inputs!L97 -> 1.57538 | M25: =Inputs!M97 -> 1.57538 | ... P25: =Inputs!P97 -> 0
E26: Malaria-attributable mortality reduction as a result of seasonal malaria chemoprevention (SMC) | F26: ppt | G26: calc | H26: - | I26: =IF(I24="-",0,(I24*I25/1000)) -> 0.00091339 | J26: =IF(J24="-",0,(J24*J25/1000)) -> 0 | K26: =IF(K24="-",0,(K24*K25/1000)) -> 0 | L26: =IF(L24="-",0,(L24*L25/1000)) -> 0.00063457383 | M26: =IF(M24="-",0,(M24*M25/1000)) -> 0.001422762 | N26: =IF(N24="-",0,(N24*N25/1000)) -> 0.000434442 | O26: =IF(O24="-",0,(O24*O25/1000)) -> 0.00071024897 | P26: =IF(P24="-",0,(P24*P25/1000)) -> 0
A28: Counterfactual malaria incidence
C30: Malaria incidence among people under age 15
E31: Malaria incidence among people under age 5 | F31: =Inputs!F100 -> per 100k | G31: =Inputs!G100 -> input | H31: =Inputs!H100 -> - | I31: =Inputs!I100 -> 22099.7 | J31: =Inputs!J100 -> 87914.34 | K31: =Inputs!K100 -> 71510.277 | L31: =Inputs!L100 -> 61766.056 | M31: =Inputs!M100 -> 75404.464 | ... P31: =Inputs!P100 -> 65525.524
E32: Malaria incidence among people age 5 to 14 | F32: =Inputs!F101 -> per 100k | G32: =Inputs!G101 -> input | H32: =Inputs!H101 -> - | I32: =Inputs!I101 -> 22099.7 | J32: =Inputs!J101 -> 35845.966 | K32: =Inputs!K101 -> 29839.074 | L32: =Inputs!L101 -> 26873.555 | M32: =Inputs!M101 -> 32080.311 | ... P32: =Inputs!P101 -> 27394.999
E33: Expected reduction in malaria incidence among people under age 5 sleeping under nets | F33: ='Main CEA'!F67 -> % | G33: main | H33: ='Main CEA'!H67 -> - | I33: ='Main CEA'!I67 -> 0.24020784 | J33: ='Main CEA'!J67 -> 0.55831846 | K33: ='Main CEA'!K67 -> 0.46006843 | L33: ='Main CEA'!L67 -> 0.50167397 | M33: ='Main CEA'!M67 -> 0.50167397 | N33: ='Main CEA'!N67 -> 0.40188586 | O33: ='Main CEA'!O67 -> 0.38926519 | P33: ='Main CEA'!P67 -> 0.51346742
E34: Baseline proportion of 1-59-month-old children sleeping under nets | F34: =Inputs!F137 -> % | G34: =Inputs!G137 -> input | H34: =Inputs!H137 -> - | I34: =Inputs!I137 -> 0.313 | J34: =Inputs!J137 -> 0.591 | K34: =Inputs!K137 -> 0.586 | L34: =Inputs!L137 -> 0.51 | M34: =Inputs!M137 -> 0.471 | ... P34: =Inputs!P137 -> 0.704
E35: Expected increase in malaria incidence in the absence of an ITN distribution | F35: % | G35: calc | H35: - | I35: =1/((1-I33)*I34+(1-I34))-1 -> 0.081297403 | J35: =1/((1-J33)*J34+(1-J34))-1 -> 0.49246205 | K35: =1/((1-K33)*K34+(1-K34))-1 -> 0.369113 | L35: =1/((1-L33)*L34+(1-L34))-1 -> 0.34382182 | M35: =1/((1-M33)*M34+(1-M34))-1 -> 0.30939487 | N35: =1/((1-N33)*N34+(1-N34))-1 -> 0.24770985 | O35: =1/((1-O33)*O34+(1-O34))-1 -> 0.44815425 | P35: =1/((1-P33)*P34+(1-P34))-1 -> 0.56612426
E36: Malaria incidence among people under age 5 in the absence of a distribution | F36: % | G36: calc | H36: - | I36: =I31*(1+I$35)/100000 -> 0.23896348 | J36: =J31*(1+J$35)/100000 -> 1.3120882 | K36: =K31*(1+K$35)/100000 -> 0.9790565 | L36: =L31*(1+L$35)/100000 -> 0.83002573 | M36: =M31*(1+M$35)/100000 -> 0.98734218 | N36: =N31*(1+N$35)/100000 -> 0.73521426 | O36: =O31*(1+O$35)/100000 -> 1.0648694 | P36: =P31*(1+P$35)/100000 -> 1.0262111
E37: Malaria incidence among people age 5 to 14 in the absence of a distribution | F37: % | G37: calc | H37: - | I37: =I32*(1+I$35)/100000 -> 0.23896348 | J37: =J32*(1+J$35)/100000 -> 0.53498743 | K37: =K32*(1+K$35)/100000 -> 0.40853064 | L37: =L32*(1+L$35)/100000 -> 0.3611327 | M37: =M32*(1+M$35)/100000 -> 0.42005795 | N37: =N32*(1+N$35)/100000 -> 0.31164979 | O37: =O32*(1+O$35)/100000 -> 0.44668425 | P37: =P32*(1+P$35)/100000 -> 0.42903972

Sheet Insecticide resistance
I1: Against Malaria Foundation
I2: Chad | J2: DRC | K2: Guinea | L2: Nigeria | M2: Nigeria | N2: South Sudan | O2: Togo | P2: Uganda
A3: Supplemental calculations for the insecticide resistance adjustment | F3: unit | G3: type | H3: Overall | L3: GF states | M3: PMI states
E4: Final cost-effectiveness estimate (pulled from "Main calcs" sheet for visibility) | F4: ='Main CEA'!F203 -> xbenchmark | G4: main | H4: ='Main CEA'!H203 -> - | I4: ='Main CEA'!I203 -> 4.8202994 | J4: ='Main CEA'!J203 -> 14.629025 | K4: ='Main CEA'!K203 -> 22.79223 | L4: ='Main CEA'!L203 -> 16.778736 | M4: ='Main CEA'!M203 -> 13.250427 | N4: ='Main CEA'!N203 -> 7.1630004 | O4: ='Main CEA'!O203 -> 8.8061654 | P4: ='Main CEA'!P203 -> 15.60304
A5: Insecticide resistance for standard nets
C7: Resistance to pyrethroid insecticides
E8: Average mosquito mortality rate found in pyrethroid bioassays (2015-2019) | F8: =Inputs!F106 -> % | G8: =Inputs!G106 -> input | H8: =Inputs!H106 -> - | I8: =Inputs!I106 -> 0.2369133 | J8: =Inputs!J106 -> 0.5206558 | K8: =Inputs!K106 -> 0.7017647 | L8: =Inputs!L106 -> 0.7498112 | M8: =Inputs!M106 -> 0.7498112 | ... P8: =Inputs!P106 -> 0.4379605
E9: Average year pyrethroid bioassays were conducted | F9: =Inputs!F107 -> year | G9: =Inputs!G107 -> input | H9: =Inputs!H107 -> - | I9: =Inputs!I107 -> 2014.93 | J9: =Inputs!J107 -> 2016.56 | K9: =Inputs!K107 -> 2016.97 | L9: =Inputs!L107 -> 2017.41 | M9: =Inputs!M107 -> 2017.41 | ... P9: =Inputs!P107 -> 2016.11
E10: Expected year of ITN distribution | F10: =Inputs!F108 -> year | G10: =Inputs!G108 -> input | H10: =Inputs!H108 -> - | I10: =Inputs!I108 -> 2026 | J10: =Inputs!J108 -> 2024 | K10: =Inputs!K108 -> 2025 | L10: =Inputs!L108 -> 2023 | M10: =Inputs!M108 -> 2023 | ... P10: =Inputs!P108 -> 2023
E11: Number of years between bioassay data collection and the expected year of ITN distribution | F11: # | G11: calc | H11: - | I11: =I10-I9 -> 11.07 | J11: =J10-J9 -> 7.44 | K11: =K10-K9 -> 8.03 | L11: =L10-L9 -> 5.59 | M11: =M10-M9 -> 5.59 | N11: =N10-N9 -> 3 | O11: =O10-O9 -> 7.53 | P11: =P10-P9 -> 6.89
E12: Expected annual change in mosquito mortality rates over time | F12: =Inputs!F109 -> ppt | G12: =Inputs!G109 -> input | H12: =Inputs!H109 -> -0.0083333333 | I12: =Inputs!I109 -> - | J12: =Inputs!J109 -> - | K12: =Inputs!K109 -> - | L12: =Inputs!L109 -> - | M12: =Inputs!M109 -> - | ... P12: =Inputs!P109 -> -
E13: Estimated change in mosquito mortality rates between bioassay data collection and the expected year of ITN distribution | F13: % | G13: calc | H13: - | I13: =$H12*I11 -> -0.09225 | J13: =$H12*J11 -> -0.062 | K13: =$H12*K11 -> -0.066916667 | L13: =$H12*L11 -> -0.046583333 | M13: =$H12*M11 -> -0.046583333 | N13: =$H12*N11 -> -0.025 | O13: =$H12*O11 -> -0.06275 | P13: =$H12*P11 -> -0.057416667
E14: Estimated mosquito mortality rate in the year of ITN distribution | F14: % | G14: calc | H14: - | I14: =MAX(I8+I13,0) -> 0.1446633 | J14: =MAX(J8+J13,0) -> 0.4586558 | K14: =MAX(K8+K13,0) -> 0.63484803 | L14: =MAX(L8+L13,0) -> 0.70322787 | M14: =MAX(M8+M13,0) -> 0.70322787 | N14: =MAX(N8+N13,0) -> 0.492 | O14: =MAX(O8+O13,0) -> 0.1657974 | P14: =MAX(P8+P13,0) -> 0.38054383
C16: Role of insecticide in the protective effect of nets
E17: Proportion of the protective effect of ITNs that is due to the physical barrier of the net | F17: =Inputs!F112 -> % | G17: =Inputs!G112 -> input | H17: =Inputs!H112 -> 0.2702179 | I17: =Inputs!I112 -> - | J17: =Inputs!J112 -> - | K17: =Inputs!K112 -> - | L17: =Inputs!L112 -> - | M17: =Inputs!M112 -> - | ... P17: =Inputs!P112 -> -
E18: Proportion of the protective effect of ITNs that is due to pyrethroid insecticide | F18: % | G18: calc | H18: =1-H17 -> 0.7297821 | I18: - | J18: - | K18: - | L18: - | M18: - | N18: - | O18: - | P18: -
C20: ITN effectiveness compared to trial contexts
E21: Effectiveness of ITNs in upcoming distributions relative to nets in studies included in Cochrane reviews | F21: % | G21: calc | H21: - | I21: =$H17+(I14*$H18) -> 0.37579059 | J21: =$H17+(J14*$H18) -> 0.60493669 | K21: =$H17+(K14*$H18) -> 0.73351863 | L21: =$H17+(L14*$H18) -> 0.78342101 | M21: =$H17+(M14*$H18) -> 0.78342101 | N21: =$H17+(N14*$H18) -> 0.62927069 | O21: =$H17+(O14*$H18) -> 0.39121387 | P21: =$H17+(P14*$H18) -> 0.54793198
E22: Reduction in effectiveness caused by resistance to pyrethroid insecticide | F22: % | G22: calc | H22: - | I22: =1-I21 -> 0.62420941 | J22: =1-J21 -> 0.39506331 | K22: =1-K21 -> 0.26648137 | L22: =1-L21 -> 0.21657899 | M22: =1-M21 -> 0.21657899 | N22: =1-N21 -> 0.37072931 | O22: =1-O21 -> 0.60878613 | P22: =1-P21 -> 0.45206802
A24: Insecticide resistance for PBO nets
C26: Resistance to pyrethroid insecticides plus a piperonyl-butoxide (PBO) synergist
E27: Average mosquito mortality rate found in bioassays of pyrethroid plus PBO (2015-2019) | F27: =Inputs!F115 -> % | G27: =Inputs!G115 -> input | H27: =Inputs!H115 -> - | I27: =Inputs!I115 -> 0.54575 | J27: =Inputs!J115 -> 0.9597 | K27: =Inputs!K115 -> 0.8975 | L27: =Inputs!L115 -> 0.9255039 | M27: =Inputs!M115 -> 0.9255039 | ... P27: =Inputs!P115 -> 0.9541395
E28: Average mosquito mortality rate found in the same bioassays of pyrethroid only | F28: =Inputs!F116 -> % | G28: =Inputs!G116 -> input | H28: =Inputs!H116 -> - | I28: =Inputs!I116 -> 0.4292125 | J28: =Inputs!J116 -> 0.5559 | K28: =Inputs!K116 -> 0.6 | L28: =Inputs!L116 -> 0.691197 | M28: =Inputs!M116 -> 0.691197 | ... P28: =Inputs!P116 -> 0.5084116
E29: Initial proportion of resistance that remains when using PBO | F29: % | G29: calc | H29: - | I29: =(1-I27)/(1-I28) -> 0.79583032 | J29: =(1-J27)/(1-J28) -> 0.090745328 | K29: =(1-K27)/(1-K28) -> 0.25625 | L29: =(1-L27)/(1-L28) -> 0.2412415 | M29: =(1-M27)/(1-M28) -> 0.2412415 | N29: =(1-N27)/(1-N28) -> 0.099602731 | O29: =(1-O27)/(1-O28) -> 0.081035453 | P29: =(1-P27)/(1-P28) -> 0.093290444
E30: Reduction in effectiveness due to insecticide resistance in areas where PBO nets are effective | F30: % | G30: calc | H30: - | I30: =I22*I29 -> 0.49676478 | J30: =J22*J29 -> 0.035850149 | K30: =K22*K29 -> 0.068285851 | L30: =L22*L29 -> 0.052247841 | M30: =M22*M29 -> 0.052247841 | N30: =N22*N29 -> 0.036925651 | O30: =O22*O29 -> 0.049333259 | P30: =P22*P29 -> 0.042173626
C32: External validity adjustments for country representativeness
E33: Proportion of bioassay test sites with confirmed pyrethroid insecticide resistance (2015-2019) | F33: =Inputs!F117 -> % | G33: =Inputs!G117 -> input | H33: =Inputs!H117 -> - | I33: =Inputs!I117 -> 1 | J33: =Inputs!J117 -> 0.8051948 | K33: =Inputs!K117 -> 0.7647059 | L33: =Inputs!L117 -> 0.6246787 | M33: =Inputs!M117 -> 0.6246787 | ... P33: =Inputs!P117 -> 0.9868421
E34: Proportion of test sites detected to have relevant resistance mechanism (2015-2019) | F34: =Inputs!F118 -> % | G34: =Inputs!G118 -> input | H34: =Inputs!H118 -> - | I34: =Inputs!I118 -> 0.7142857 | J34: =Inputs!J118 -> 1 | K34: =Inputs!K118 -> 0.7916667 | L34: =Inputs!L118 -> 0.7916667 | M34: =Inputs!M118 -> 0.7916667 | ... P34: =Inputs!P118 -> 0.8333333
E35: Estimated proportion of country where PBO nets are more effective than standard ITNs | F35: % | G35: calc | H35: - | I35: =I33*I34 -> 0.7142857 | J35: =J33*J34 -> 0.8051948 | K35: =K33*K34 -> 0.6053922 | L35: =L33*L34 -> 0.49453733 | M35: =M33*M34 -> 0.49453733 | N35: =N33*N34 -> 0.81341373 | O35: =O33*O34 -> 0.7916667 | P35: =P33*P34 -> 0.82236838
A37: Insecticide resistance for Dual AI nets
C39: Resistance to insecticides used in Dual AI nets
E40: Reduction in effectiveness due to insecticide resistance with chlorfenapyr nets | F40: =Inputs!F121 -> % | G40: =Inputs!G121 -> input | H40: =Inputs!H121 -> 0 | I40: =Inputs!I121 -> - | J40: =Inputs!J121 -> - | K40: =Inputs!K121 -> - | L40: =Inputs!L121 -> - | M40: =Inputs!M121 -> - | ... P40: =Inputs!P121 -> -
E41: Reduction in effectiveness due to insecticide resistance with other Dual AI nets | F41: % | G41: calc | H41: =H22 -> - | I41: =I22 -> 0.62420941 | J41: =J22 -> 0.39506331 | K41: =K22 -> 0.26648137 | L41: =L22 -> 0.21657899 | M41: =M22 -> 0.21657899 | N41: =N22 -> 0.37072931 | O41: =O22 -> 0.60878613 | P41: =P22 -> 0.45206802
A43: Insecticide resistance adjustment
C45: Breakdown of nets purchased
E46: Expected proportion of standard ITNs purchased for distributions | F46: =Inputs!F127 -> % | G46: =Inputs!G127 -> input | H46: =Inputs!H127 -> - | I46: =Inputs!I127 -> 0.7 | J46: =Inputs!J127 -> 0 | K46: =Inputs!K127 -> 0.7 | L46: =Inputs!L127 -> 0 | M46: =Inputs!M127 -> 0 | ... P46: =Inputs!P127 -> 0
E47: Expected proportion of PBO nets purchased for distributions | F47: =Inputs!F124 -> % | G47: =Inputs!G124 -> input | H47: =Inputs!H124 -> - | I47: =Inputs!I124 -> 0.3 | J47: =Inputs!J124 -> 0.5 | K47: =Inputs!K124 -> 0.3 | L47: =Inputs!L124 -> 1 | M47: =Inputs!M124 -> 1 | ... P47: =Inputs!P124 -> 1
E48: Expected proportion of chlorfenapyr nets purchased for distributions | F48: =Inputs!F125 -> % | G48: =Inputs!G125 -> input | H48: =Inputs!H125 -> - | I48: =Inputs!I125 -> 0 | J48: =Inputs!J125 -> 0.45 | K48: =Inputs!K125 -> 0 | L48: =Inputs!L125 -> 0 | M48: =Inputs!M125 -> 0 | ... P48: =Inputs!P125 -> 0
E49: Expected proportion of other Dual AI nets purchased for distributions | F49: =Inputs!F126 -> % | G49: =Inputs!G126 -> input | H49: =Inputs!H126 -> - | I49: =Inputs!I126 -> 0 | J49: =Inputs!J126 -> 0.05 | K49: =Inputs!K126 -> 0 | L49: =Inputs!L126 -> 0 | M49: =Inputs!M126 -> 0 | ... P49: =Inputs!P126 -> 0
C51: Final net breakdown
E52: Proportion of nets that are standard nets | F52: % | G52: calc | H52: - | I52: =I46 -> 0.7 | J52: =J46 -> 0 | K52: =K46 -> 0.7 | L52: =L46 -> 0 | M52: =M46 -> 0 | N52: =N46 -> 0.81 | O52: =O46 -> 0.5 | P52: =P46 -> 0
E53: Proportion of nets that are PBO nets distributed to areas where PBO nets are effective | F53: % | G53: calc | H53: - | I53: =MIN(I35,I47) -> 0.3 | J53: =MIN(J35,J47) -> 0.5 | K53: =MIN(K35,K47) -> 0.3 | L53: =MIN(L35,L47) -> 0.49453733 | M53: =MIN(M35,M47) -> 0.49453733 | N53: =MIN(N35,N47) -> 0.19 | O53: =MIN(O35,O47) -> 0.5 | P53: =MIN(P35,P47) -> 0.82236838
E54: Proportion of nets that are PBO nets distributed to areas where PBO nets are not effective | F54: % | G54: calc | H54: - | I54: =I47-I53 -> 0 | J54: =J47-J53 -> 0 | K54: =K47-K53 -> 0 | L54: =L47-L53 -> 0.50546267 | M54: =M47-M53 -> 0.50546267 | N54: =N47-N53 -> 0 | O54: =O47-O53 -> 0 | P54: =P47-P53 -> 0.17763162
E55: Proportion of nets that are chlorfenapyr nets | F55: % | G55: calc | H55: - | I55: =I48 -> 0 | J55: =J48 -> 0.45 | K55: =K48 -> 0 | L55: =L48 -> 0 | M55: =M48 -> 0 | N55: =N48 -> 0 | O55: =O48 -> 0 | P55: =P48 -> 0
E56: Proportion of nets that are other Dual AI nets | F56: % | G56: calc | H56: - | I56: =I49 -> 0 | J56: =J49 -> 0.05 | K56: =K49 -> 0 | L56: =L49 -> 0 | M56: =M49 -> 0 | N56: =N49 -> 0 | O56: =O49 -> 0 | P56: =P49 -> 0
C58: Insecticide resistance adjustment by net type
E59: Adjustment for standard nets | F59: % | G59: calc | H59: - | I59: =-I22 -> -0.62420941 | J59: =-J22 -> -0.39506331 | K59: =-K22 -> -0.26648137 | L59: =-L22 -> -0.21657899 | M59: =-M22 -> -0.21657899 | N59: =-N22 -> -0.37072931 | O59: =-O22 -> -0.60878613 | P59: =-P22 -> -0.45206802
E60: Adjustment for PBO nets distributed to areas where PBO nets are effective | F60: % | G60: calc | H60: - | I60: =-I30 -> -0.49676478 | J60: =-J30 -> -0.035850149 | K60: =-K30 -> -0.068285851 | L60: =-L30 -> -0.052247841 | M60: =-M30 -> -0.052247841 | N60: =-N30 -> -0.036925651 | O60: =-O30 -> -0.049333259 | P60: =-P30 -> -0.042173626
E61: Adjustment for PBO nets distributed to areas where PBO nets are not effective | F61: % | G61: calc | H61: - | I61: =-I22 -> -0.62420941 | J61: =-J22 -> -0.39506331 | K61: =-K22 -> -0.26648137 | L61: =-L22 -> -0.21657899 | M61: =-M22 -> -0.21657899 | N61: =-N22 -> -0.37072931 | O61: =-O22 -> -0.60878613 | P61: =-P22 -> -0.45206802
E62: Adjustment for chlorfenapyr nets | F62: % | G62: calc | H62: - | I62: =-$H40 -> 0 | J62: =-$H40 -> 0 | K62: =-$H40 -> 0 | L62: =-$H40 -> 0 | M62: =-$H40 -> 0 | N62: =-$H40 -> 0 | O62: =-$H40 -> 0 | P62: =-$H40 -> 0
E63: Adjustment for other Dual AI nets | F63: % | G63: calc | H63: - | I63: =-I41 -> -0.62420941 | J63: =-J41 -> -0.39506331 | K63: =-K41 -> -0.26648137 | L63: =-L41 -> -0.21657899 | M63: =-M41 -> -0.21657899 | N63: =-N41 -> -0.37072931 | O63: =-O41 -> -0.60878613 | P63: =-P41 -> -0.45206802
C65: Final insecticide resistance adjustment incorporating Dual AI nets
E66: Adjustment for insecticide resistance | F66: % | G66: calc | H66: - | I66: =SUMPRODUCT(I52:I56,I59:I63) -> -0.58597602 | J66: =SUMPRODUCT(J52:J56,J59:J63) -> -0.03767824 | K66: =SUMPRODUCT(K52:K56,K59:K63) -> -0.20702271 | L66: =SUMPRODUCT(L52:L56,L59:L63) -> -0.1353111 | M66: =SUMPRODUCT(M52:M56,M59:M63) -> -0.1353111 | N66: =SUMPRODUCT(N52:N56,N59:N63) -> -0.30730661 | O66: =SUMPRODUCT(O52:O56,O59:O63) -> -0.32905969 | P66: =SUMPRODUCT(P52:P56,P59:P63) -> -0.11498383

Sheet LeverageFunging
I1: Against Malaria Foundation
I2: Chad | J2: DRC | K2: Guinea | L2: Nigeria | M2: Nigeria | N2: South Sudan | O2: Togo | P2: Uganda
A3: Supplemental calculations for the leverage/funging adjustment | F3: unit | G3: type | H3: Overall | L3: GF states | M3: PMI states
E4: Final cost-effectiveness estimate (pulled from "Main calcs" sheet for visibility) | F4: ='Main CEA'!F203 -> xbenchmark | G4: main | H4: ='Main CEA'!H203 -> - | I4: ='Main CEA'!I203 -> 4.8202994 | J4: ='Main CEA'!J203 -> 14.629025 | K4: ='Main CEA'!K203 -> 22.79223 | L4: ='Main CEA'!L203 -> 16.778736 | M4: ='Main CEA'!M203 -> 13.250427 | N4: ='Main CEA'!N203 -> 7.1630004 | O4: ='Main CEA'!O203 -> 8.8061654 | P4: ='Main CEA'!P203 -> 15.60304
A5: Costs
C7: GiveWell costs
E8: Grant size | F8: =Inputs!F8 -> $ | G8: =Inputs!G8 -> input | H8: =Inputs!H8 -> 1000000 | I8: =Inputs!I8 -> - | J8: =Inputs!J8 -> - | K8: =Inputs!K8 -> - | L8: =Inputs!L8 -> - | M8: =Inputs!M8 -> - | ... P8: =Inputs!P8 -> -
C10: Cost breakdown
E11: Percentage of total costs covered by the grantee | F11: =Inputs!F11 -> % | G11: =Inputs!G11 -> input | H11: =Inputs!H11 -> - | I11: =Inputs!I11 -> 0.9562847 | J11: =Inputs!J11 -> 0.9449092 | K11: =Inputs!K11 -> 0.9562847 | L11: =Inputs!L11 -> 0.9613383 | M11: =Inputs!M11 -> 0.9613383 | ... P11: =Inputs!P11 -> 0.9553321
E12: Percentage of total costs covered by other philanthropic actors | F12: =Inputs!F12 -> % | G12: =Inputs!G12 -> input | H12: =Inputs!H12 -> - | I12: =Inputs!I12 -> 0 | J12: =Inputs!J12 -> 0 | K12: =Inputs!K12 -> 0 | L12: =Inputs!L12 -> 0 | M12: =Inputs!M12 -> 0 | ... P12: =Inputs!P12 -> 0
E13: Percentage of total costs covered by domestic governments | F13: =Inputs!F13 -> % | G13: =Inputs!G13 -> input | H13: =Inputs!H13 -> - | I13: =Inputs!I13 -> 0.0437153 | J13: =Inputs!J13 -> 0.0550908 | K13: =Inputs!K13 -> 0.0437153 | L13: =Inputs!L13 -> 0.0386617 | M13: =Inputs!M13 -> 0.0386617 | ... P13: =Inputs!P13 -> 0.0446679
C15: Total costs
E16: Total spending by all contributors | F16: ='Main CEA'!F16 -> $ | G16: main | H16: ='Main CEA'!H16 -> - | I16: ='Main CEA'!I16 -> 1045713.7 | J16: ='Main CEA'!J16 -> 1058302.7 | K16: ='Main CEA'!K16 -> 1045713.7 | L16: ='Main CEA'!L16 -> 1040216.5 | M16: ='Main CEA'!M16 -> 1040216.5 | N16: ='Main CEA'!N16 -> 1067466 | O16: ='Main CEA'!O16 -> 1042128.6 | P16: ='Main CEA'!P16 -> 1046756.4
C18: Total spending attributable to different actors
E19: Total spending contributed by grantee | F19: ='Main CEA'!F19 -> $ | G19: main | H19: ='Main CEA'!H19 -> - | I19: ='Main CEA'!I19 -> 1000000 | J19: ='Main CEA'!J19 -> 1000000 | K19: ='Main CEA'!K19 -> 1000000 | L19: ='Main CEA'!L19 -> 1000000 | M19: ='Main CEA'!M19 -> 1000000 | N19: ='Main CEA'!N19 -> 1000000 | O19: ='Main CEA'!O19 -> 1000000 | P19: ='Main CEA'!P19 -> 1000000
E20: Total spending contributed by other philanthropic actors | F20: ='Main CEA'!F20 -> $ | G20: main | H20: ='Main CEA'!H20 -> - | I20: ='Main CEA'!I20 -> 0 | J20: ='Main CEA'!J20 -> 0 | K20: ='Main CEA'!K20 -> 0 | L20: ='Main CEA'!L20 -> 0 | M20: ='Main CEA'!M20 -> 0 | N20: ='Main CEA'!N20 -> 0 | O20: ='Main CEA'!O20 -> 0 | P20: ='Main CEA'!P20 -> 0
E21: Total spending contributed by domestic governments | F21: ='Main CEA'!F21 -> $ | G21: main | H21: ='Main CEA'!H21 -> - | I21: ='Main CEA'!I21 -> 45713.688 | J21: ='Main CEA'!J21 -> 58302.745 | K21: ='Main CEA'!K21 -> 45713.688 | L21: ='Main CEA'!L21 -> 40216.54 | M21: ='Main CEA'!M21 -> 40216.54 | N21: ='Main CEA'!N21 -> 67466.092 | O21: ='Main CEA'!O21 -> 42128.568 | P21: ='Main CEA'!P21 -> 46756.411
C23: Upstream / downstream spending
E24: Total spending causally upstream of donations to grantee | F24: ='Main CEA'!F24 -> $ | G24: main | H24: ='Main CEA'!H24 -> - | I24: ='Main CEA'!I24 -> 1000000 | J24: ='Main CEA'!J24 -> 1000000 | K24: ='Main CEA'!K24 -> 1000000 | L24: ='Main CEA'!L24 -> 1000000 | M24: ='Main CEA'!M24 -> 1000000 | N24: ='Main CEA'!N24 -> 1000000 | O24: ='Main CEA'!O24 -> 1000000 | P24: ='Main CEA'!P24 -> 1000000
E25: Total spending causally downstream of donations to grantee | F25: ='Main CEA'!F25 -> $ | G25: main | H25: ='Main CEA'!H25 -> - | I25: ='Main CEA'!I25 -> 45713.688 | J25: ='Main CEA'!J25 -> 58302.745 | K25: ='Main CEA'!K25 -> 45713.688 | L25: ='Main CEA'!L25 -> 40216.54 | M25: ='Main CEA'!M25 -> 40216.54 | N25: ='Main CEA'!N25 -> 67466.092 | O25: ='Main CEA'!O25 -> 42128.568 | P25: ='Main CEA'!P25 -> 46756.411
A27: Counterfactual funding scenarios
C29: Probability of scenarios in the absence of philanthropic funding
E30: Scenario 1: Domestic governments would replace philanthropic costs | F30: =Inputs!F195 -> % | G30: =Inputs!G195 -> input | H30: =Inputs!H195 -> - | I30: =Inputs!I195 -> 0 | J30: =Inputs!J195 -> 0 | K30: =Inputs!K195 -> 0 | L30: =Inputs!L195 -> 0 | M30: =Inputs!M195 -> 0 | ... P30: =Inputs!P195 -> 0
E31: Scenario 2: Global Fund and/or PMI would replace philanthropic costs | F31: =Inputs!F196 -> % | G31: =Inputs!G196 -> input | H31: =Inputs!H196 -> - | I31: =Inputs!I196 -> 0.4 | J31: =Inputs!J196 -> 0.2 | K31: =Inputs!K196 -> 0.35 | L31: =Inputs!L196 -> 0.35 | M31: =Inputs!M196 -> 0.2 | ... P31: =Inputs!P196 -> 0.4
E32: Scenario 3: Other upstream costs would stay the same (downstream costs would shrink in proportion to the total size of the program) | F32: =Inputs!F197 -> % | G32: =Inputs!G197 -> input | H32: =Inputs!H197 -> - | I32: =Inputs!I197 -> 0 | J32: =Inputs!J197 -> 0 | K32: =Inputs!K197 -> 0 | L32: =Inputs!L197 -> 0 | M32: =Inputs!M197 -> 0 | ... P32: =Inputs!P197 -> 0
E33: Scenario 4: Distributions would go unfunded | F33: % | G33: calc | H33: - | I33: =1-SUM(I30:I32) -> 0.6 | J33: =1-SUM(J30:J32) -> 0.8 | K33: =1-SUM(K30:K32) -> 0.65 | L33: =1-SUM(L30:L32) -> 0.65 | M33: =1-SUM(M30:M32) -> 0.8 | N33: =1-SUM(N30:N32) -> 0.85 | O33: =1-SUM(O30:O32) -> 0.4 | P33: =1-SUM(P30:P32) -> 0.6
C35: Proportion of the program that would still occur in each scenario
E36: Scenario 1: Domestic governments would replace philanthropic costs | F36: =Inputs!F200 -> % | G36: =Inputs!G200 -> input | H36: =Inputs!H200 -> 1 | I36: =Inputs!I200 -> - | J36: =Inputs!J200 -> - | K36: =Inputs!K200 -> - | L36: =Inputs!L200 -> - | M36: =Inputs!M200 -> - | ... P36: =Inputs!P200 -> -
E37: Scenario 2: Global Fund and/or PMI would replace philanthropic costs | F37: =Inputs!F201 -> % | G37: =Inputs!G201 -> input | H37: =Inputs!H201 -> 1 | I37: =Inputs!I201 -> - | J37: =Inputs!J201 -> - | K37: =Inputs!K201 -> - | L37: =Inputs!L201 -> - | M37: =Inputs!M201 -> - | ... P37: =Inputs!P201 -> -
E38: Scenario 3: Other upstream costs would stay the same (downstream costs would shrink in proportion to the total size of the program) | F38: % | G38: calc | H38: - | I38: =I20/I24 -> 0 | J38: =J20/J24 -> 0 | K38: =K20/K24 -> 0 | L38: =L20/L24 -> 0 | M38: =M20/M24 -> 0 | N38: =N20/N24 -> 0 | O38: =O20/O24 -> 0 | P38: =P20/P24 -> 0
E39: Scenario 4: Distributions would go unfunded | F39: =Inputs!F202 -> % | G39: =Inputs!G202 -> input | H39: =Inputs!H202 -> 0 | I39: =Inputs!I202 -> - | J39: =Inputs!J202 -> - | K39: =Inputs!K202 -> - | L39: =Inputs!L202 -> - | M39: =Inputs!M202 -> - | ... P39: =Inputs!P202 -> -
A41: Value of spending
C43: Cost-effectiveness of the program (before leverage and funging)
E44: Units of value generated per dollar spent (before final adjustments) | F44: ='Main CEA'!F143 -> UoV | G44: main | H44: ='Main CEA'!H143 -> - | I44: ='Main CEA'!I143 -> 0.011373971 | J44: ='Main CEA'!J143 -> 0.040377722 | K44: ='Main CEA'!K143 -> 0.082100138 | L44: ='Main CEA'!L143 -> 0.054831566 | M44: ='Main CEA'!M143 -> 0.036271711 | N44: ='Main CEA'!N143 -> 0.019397973 | O44: ='Main CEA'!O143 -> 0.038052084 | P44: ='Main CEA'!P143 -> 0.057820168
E45: Total supplemental grantee-level adjustment | F45: ='Main CEA'!F172 -> % | G45: main | H45: ='Main CEA'!H172 -> -0.04 | I45: ='Main CEA'!I172 -> - | J45: ='Main CEA'!J172 -> - | K45: ='Main CEA'!K172 -> - | L45: ='Main CEA'!L172 -> - | M45: ='Main CEA'!M172 -> - | N45: ='Main CEA'!N172 -> - | O45: ='Main CEA'!O172 -> - | P45: ='Main CEA'!P172 -> -
E46: Total supplemental intervention-level adjustment | F46: ='Main CEA'!F189 -> % | G46: main | H46: ='Main CEA'!H189 -> - | I46: ='Main CEA'!I189 -> 0.529 | J46: ='Main CEA'!J189 -> 0.479 | K46: ='Main CEA'!K189 -> 0.379 | L46: ='Main CEA'!L189 -> 0.479 | M46: ='Main CEA'!M189 -> 0.479 | N46: ='Main CEA'!N189 -> 0.379 | O46: ='Main CEA'!O189 -> 0.379 | P46: ='Main CEA'!P189 -> 0.379
E47: Units of value generated per dollar donated to grantee (after supplemental adjustments) | F47: UoV | G47: calc | H47: - | I47: =I44*(1+$H45)*(1+I46) -> 0.016695169 | J47: =J44*(1+$H45)*(1+J46) -> 0.057329905 | K47: =K44*(1+$H45)*(1+K46) -> 0.10868745 | L47: =L44*(1+$H45)*(1+L46) -> 0.077852051 | M47: =M44*(1+$H45)*(1+M46) -> 0.051500026 | N47: =N44*(1+$H45)*(1+N46) -> 0.025679813 | O47: =O44*(1+$H45)*(1+O46) -> 0.050374871 | P47: =P44*(1+$H45)*(1+P46) -> 0.076544651
C49: Lives saved by the program (before leverage and funging)
E50: Total lives saved (before final adjustments) | F50: ='Main CEA'!F154 -> # | G50: main | H50: ='Main CEA'!H154 -> - | I50: ='Main CEA'!I154 -> 69.001061 | J50: ='Main CEA'!J154 -> 250.66427 | K50: ='Main CEA'!K154 -> 588.1917 | L50: ='Main CEA'!L154 -> 392.17081 | M50: ='Main CEA'!M154 -> 243.78345 | N50: ='Main CEA'!N154 -> 122.9351 | O50: ='Main CEA'!O154 -> 260.73544 | P50: ='Main CEA'!P154 -> 363.81499
E51: Total supplemental grantee-level adjustment | F51: ='Main CEA'!F172 -> % | G51: main | H51: ='Main CEA'!H172 -> -0.04 | I51: ='Main CEA'!I172 -> - | J51: ='Main CEA'!J172 -> - | K51: ='Main CEA'!K172 -> - | L51: ='Main CEA'!L172 -> - | M51: ='Main CEA'!M172 -> - | N51: ='Main CEA'!N172 -> - | O51: ='Main CEA'!O172 -> - | P51: ='Main CEA'!P172 -> -
E52: Total supplemental intervention-level adjustment affecting lives saved | F52: ='Main CEA'!F214 -> % | G52: main | H52: ='Main CEA'!H214 -> - | I52: ='Main CEA'!I214 -> 0.014 | J52: ='Main CEA'!J214 -> -0.036 | K52: ='Main CEA'!K214 -> -0.136 | L52: ='Main CEA'!L214 -> -0.036 | M52: ='Main CEA'!M214 -> -0.036 | N52: ='Main CEA'!N214 -> -0.136 | O52: ='Main CEA'!O214 -> -0.136 | P52: ='Main CEA'!P214 -> -0.136
E53: Total lives saved (after supplemental adjustments) | F53: # | G53: calc | H53: - | I53: =I50*(1+$H51)*(1+I52) -> 67.168393 | J53: =J50*(1+$H51)*(1+J52) -> 231.97474 | K53: =K50*(1+$H51)*(1+K52) -> 487.86972 | L53: =L50*(1+$H51)*(1+L52) -> 362.93056 | M53: =M50*(1+$H51)*(1+M52) -> 225.60695 | N53: =N50*(1+$H51)*(1+N52) -> 101.96729 | O53: =O50*(1+$H51)*(1+O52) -> 216.2644 | P53: =P50*(1+$H51)*(1+P52) -> 301.76271
C55: Counterfactual value of spending from non-philanthropic actors
E56: Counterfactual value per dollar spent by domestic governments | F56: =Inputs!F205 -> UoV | G56: =Inputs!G205 -> input | H56: =Inputs!H205 -> 0.005057 | I56: =Inputs!I205 -> - | J56: =Inputs!J205 -> - | K56: =Inputs!K205 -> - | L56: =Inputs!L205 -> - | M56: =Inputs!M205 -> - | ... P56: =Inputs!P205 -> -
E57: Counterfactual value per dollar spent by the Global Fund or PMI | F57: =Inputs!F206 -> UoV | G57: =Inputs!G206 -> input | H57: =Inputs!H206 -> 0.015433 | I57: =Inputs!I206 -> - | J57: =Inputs!J206 -> - | K57: =Inputs!K206 -> - | L57: =Inputs!L206 -> - | M57: =Inputs!M206 -> - | ... P57: =Inputs!P206 -> -
A59: Value generated across different counterfactual scenarios
C61: Scenario 1: Domestic governments would replace philanthropic spending
D62: Hypothetical impact of shifting government spending
E63: Amount of spending domestic governments would shift to the grantee program | F63: $ | G63: calc | H63: - | I63: =I19 -> 1000000 | J63: =J19 -> 1000000 | K63: =K19 -> 1000000 | L63: =L19 -> 1000000 | M63: =M19 -> 1000000 | N63: =N19 -> 1000000 | O63: =O19 -> 1000000 | P63: =P19 -> 1000000
E64: Value generated by shifting government spending to the grantee program | F64: UoV | G64: calc | H64: - | I64: =I63*I47 -> 16695.169 | J64: =J63*J47 -> 57329.905 | K64: =K63*K47 -> 108687.45 | L64: =L63*L47 -> 77852.051 | M64: =M63*M47 -> 51500.026 | N64: =N63*N47 -> 25679.813 | O64: =O63*O47 -> 50374.871 | P64: =P63*P47 -> 76544.651
E65: Value lost by shifting spending away from programs domestic governments would otherwise have funded | F65: UoV | G65: calc | H65: - | I65: =I63*$H56 -> 5057 | J65: =J63*$H56 -> 5057 | K65: =K63*$H56 -> 5057 | L65: =L63*$H56 -> 5057 | M65: =M63*$H56 -> 5057 | N65: =N63*$H56 -> 5057 | O65: =O63*$H56 -> 5057 | P65: =P63*$H56 -> 5057
E66: Net value generated by shifting government spending to the grantee program | F66: UoV | G66: calc | H66: - | I66: =I64-I65 -> 11638.169 | J66: =J64-J65 -> 52272.905 | K66: =K64-K65 -> 103630.45 | L66: =L64-L65 -> 72795.051 | M66: =M64-M65 -> 46443.026 | N66: =N64-N65 -> 20622.813 | O66: =O64-O65 -> 45317.871 | P66: =P64-P65 -> 71487.651
E67: Change in value generated by the grantee program if this scenario represented the true counterfactual | F67: UoV | G67: calc | H67: - | I67: =-I66 -> -11638.169 | J67: =-J66 -> -52272.905 | K67: =-K66 -> -103630.45 | L67: =-L66 -> -72795.051 | M67: =-M66 -> -46443.026 | N67: =-N66 -> -20622.813 | O67: =-O66 -> -45317.871 | P67: =-P66 -> -71487.651
E68: Probability of this scenario representing the true counterfactual | F68: =F30 -> % | G68: feed | H68: =H30 -> - | I68: =I30 -> 0 | J68: =J30 -> 0 | K68: =K30 -> 0 | L68: =L30 -> 0 | M68: =M30 -> 0 | N68: =N30 -> 0 | O68: =O30 -> 0 | P68: =P30 -> 0
E69: Expected change in value generated by the grantee program | F69: UoV | G69: calc | H69: - | I69: =I67*I68 -> 0 | J69: =J67*J68 -> 0 | K69: =K67*K68 -> 0 | L69: =L67*L68 -> 0 | M69: =M67*M68 -> 0 | N69: =N67*N68 -> 0 | O69: =O67*O68 -> 0 | P69: =P67*P68 -> 0
C71: Scenario 2: The Global Fund and/or PMI would replace philanthropic spending
D72: Hypothetical impact of shifting Global Fund and/or PMI spending
E73: Amount of spending the Global Fund and/or PMI would shift to the grantee program | F73: $ | G73: calc | H73: - | I73: =I19 -> 1000000 | J73: =J19 -> 1000000 | K73: =K19 -> 1000000 | L73: =L19 -> 1000000 | M73: =M19 -> 1000000 | N73: =N19 -> 1000000 | O73: =O19 -> 1000000 | P73: =P19 -> 1000000
E74: Value generated by shifting Global Fund and/or PMI spending to the grantee program | F74: UoV | G74: calc | H74: - | I74: =I73*I47 -> 16695.169 | J74: =J73*J47 -> 57329.905 | K74: =K73*K47 -> 108687.45 | L74: =L73*L47 -> 77852.051 | M74: =M73*M47 -> 51500.026 | N74: =N73*N47 -> 25679.813 | O74: =O73*O47 -> 50374.871 | P74: =P73*P47 -> 76544.651
E75: Value lost by shifting spending away from programs the Global Fund and/or PMI would otherwise have funded | F75: UoV | G75: calc | H75: - | I75: =I73*$H57 -> 15433 | J75: =J73*$H57 -> 15433 | K75: =K73*$H57 -> 15433 | L75: =L73*$H57 -> 15433 | M75: =M73*$H57 -> 15433 | N75: =N73*$H57 -> 15433 | O75: =O73*$H57 -> 15433 | P75: =P73*$H57 -> 15433
E76: Net value generated by shifting Global Fund and/or PMI spending to the grantee program | F76: UoV | G76: calc | H76: - | I76: =I74-I75 -> 1262.1691 | J76: =J74-J75 -> 41896.905 | K76: =K74-K75 -> 93254.447 | L76: =L74-L75 -> 62419.051 | M76: =M74-M75 -> 36067.026 | N76: =N74-N75 -> 10246.813 | O76: =O74-O75 -> 34941.871 | P76: =P74-P75 -> 61111.651
E77: Change in value generated by the grantee program if this scenario represented the true counterfactual | F77: UoV | G77: calc | H77: - | I77: =-I76 -> -1262.1691 | J77: =-J76 -> -41896.905 | K77: =-K76 -> -93254.447 | L77: =-L76 -> -62419.051 | M77: =-M76 -> -36067.026 | N77: =-N76 -> -10246.813 | O77: =-O76 -> -34941.871 | P77: =-P76 -> -61111.651
E78: Probability of this scenario representing the true counterfactual | F78: =F31 -> % | G78: feed | H78: =H31 -> - | I78: =I31 -> 0.4 | J78: =J31 -> 0.2 | K78: =K31 -> 0.35 | L78: =L31 -> 0.35 | M78: =M31 -> 0.2 | N78: =N31 -> 0.15 | O78: =O31 -> 0.6 | P78: =P31 -> 0.4
E79: Expected change in value generated by the grantee program | F79: UoV | G79: calc | H79: - | I79: =I77*I78 -> -504.86765 | J79: =J77*J78 -> -8379.3809 | K79: =K77*K78 -> -32639.056 | L79: =L77*L78 -> -21846.668 | M79: =M77*M78 -> -7213.4051 | N79: =N77*N78 -> -1537.0219 | O79: =O77*O78 -> -20965.123 | P79: =P77*P78 -> -24444.66
C81: Scenario 3: Other upstream costs would stay the same and the program would be smaller
D82: Hypothetical impact of shifting government spending
E83: Amount of spending domestic governments would shift away from the grantee program | F83: $ | G83: calc | H83: - | I83: =I21*(1-I38) -> 45713.688 | J83: =J21*(1-J38) -> 58302.745 | K83: =K21*(1-K38) -> 45713.688 | L83: =L21*(1-L38) -> 40216.54 | M83: =M21*(1-M38) -> 40216.54 | N83: =N21*(1-N38) -> 67466.092 | O83: =O21*(1-O38) -> 42128.568 | P83: =P21*(1-P38) -> 46756.411
E84: Value generated by shifting spending toward programs domestic governments would otherwise have supported | F84: UoV | G84: calc | H84: - | I84: =I83*$H56 -> 231.17412 | J84: =J83*$H56 -> 294.83698 | K84: =K83*$H56 -> 231.17412 | L84: =L83*$H56 -> 203.37504 | M84: =M83*$H56 -> 203.37504 | N84: =N83*$H56 -> 341.17603 | O84: =O83*$H56 -> 213.04417 | P84: =P83*$H56 -> 236.44717
E85: Value lost by shifting government spending away from the grantee program | F85: UoV | G85: calc | H85: - | I85: 0 | J85: 0 | K85: 0 | L85: 0 | M85: 0 | N85: 0 | O85: 0 | P85: 0
E86: Net value generated by shifting government spending away from the grantee program | F86: UoV | G86: calc | H86: - | I86: =I84-I85 -> 231.17412 | J86: =J84-J85 -> 294.83698 | K86: =K84-K85 -> 231.17412 | L86: =L84-L85 -> 203.37504 | M86: =M84-M85 -> 203.37504 | N86: =N84-N85 -> 341.17603 | O86: =O84-O85 -> 213.04417 | P86: =P84-P85 -> 236.44717
E87: Change in value generated by the grantee program if this scenario represented the true counterfactual | F87: UoV | G87: calc | H87: - | I87: =-I86 -> -231.17412 | J87: =-J86 -> -294.83698 | K87: =-K86 -> -231.17412 | L87: =-L86 -> -203.37504 | M87: =-M86 -> -203.37504 | N87: =-N86 -> -341.17603 | O87: =-O86 -> -213.04417 | P87: =-P86 -> -236.44717
E88: Probability of this scenario representing the true counterfactual | F88: =F32 -> % | G88: feed | H88: =H32 -> - | I88: =I32 -> 0 | J88: =J32 -> 0 | K88: =K32 -> 0 | L88: =L32 -> 0 | M88: =M32 -> 0 | N88: =N32 -> 0 | O88: =O32 -> 0 | P88: =P32 -> 0
E89: Expected change in value generated by the program | F89: UoV | G89: calc | H89: - | I89: =I87*I88 -> 0 | J89: =J87*J88 -> 0 | K89: =K87*K88 -> 0 | L89: =L87*L88 -> 0 | M89: =M87*M88 -> 0 | N89: =N87*N88 -> 0 | O89: =O87*O88 -> 0 | P89: =P87*P88 -> 0
C91: Scenario 4: The grantee program would go unfunded
D92: Hypothetical impact of shifting government spending
E93: Amount of spending domestic governments would shift away from the grantee program | F93: $ | G93: calc | H93: - | I93: =I21 -> 45713.688 | J93: =J21 -> 58302.745 | K93: =K21 -> 45713.688 | L93: =L21 -> 40216.54 | M93: =M21 -> 40216.54 | N93: =N21 -> 67466.092 | O93: =O21 -> 42128.568 | P93: =P21 -> 46756.411
E94: Value generated by shifting spending to programs domestic governments would otherwise have funded | F94: UoV | G94: calc | H94: - | I94: =I93*$H56 -> 231.17412 | J94: =J93*$H56 -> 294.83698 | K94: =K93*$H56 -> 231.17412 | L94: =L93*$H56 -> 203.37504 | M94: =M93*$H56 -> 203.37504 | N94: =N93*$H56 -> 341.17603 | O94: =O93*$H56 -> 213.04417 | P94: =P93*$H56 -> 236.44717
E95: Value lost by shifting government spending away from the grantee program | F95: UoV | G95: calc | H95: - | I95: 0 | J95: 0 | K95: 0 | L95: 0 | M95: 0 | N95: 0 | O95: 0 | P95: 0
E96: Net value generated by shifting government spending away from the grantee program | F96: UoV | G96: calc | H96: - | I96: =I94-I95 -> 231.17412 | J96: =J94-J95 -> 294.83698 | K96: =K94-K95 -> 231.17412 | L96: =L94-L95 -> 203.37504 | M96: =M94-M95 -> 203.37504 | N96: =N94-N95 -> 341.17603 | O96: =O94-O95 -> 213.04417 | P96: =P94-P95 -> 236.44717
E97: Change in value generated by the grantee program if this scenario represented the true counterfactual | F97: UoV | G97: calc | H97: - | I97: =-I96 -> -231.17412 | J97: =-J96 -> -294.83698 | K97: =-K96 -> -231.17412 | L97: =-L96 -> -203.37504 | M97: =-M96 -> -203.37504 | N97: =-N96 -> -341.17603 | O97: =-O96 -> -213.04417 | P97: =-P96 -> -236.44717
E98: Probability of this scenario representing the true counterfactual | F98: =F33 -> % | G98: feed | H98: =H33 -> - | I98: =I33 -> 0.6 | J98: =J33 -> 0.8 | K98: =K33 -> 0.65 | L98: =L33 -> 0.65 | M98: =M33 -> 0.8 | N98: =N33 -> 0.85 | O98: =O33 -> 0.4 | P98: =P33 -> 0.6
E99: Expected change in value generated by the program | F99: UoV | G99: calc | H99: - | I99: =I97*I98 -> -138.70447 | J99: =J97*J98 -> -235.86958 | K99: =K97*K98 -> -150.26318 | L99: =L97*L98 -> -132.19378 | M99: =M97*M98 -> -162.70003 | N99: =N97*N98 -> -289.99962 | O99: =O97*O98 -> -85.217668 | P99: =P97*P98 -> -141.8683
A101: Final leverage and funging adjustment
C103: Change in value generated as a result of leverage and funging
E104: Total value generated by grantee spending before adjusting for leverage and funging | F104: UoV | G104: calc | H104: - | I104: =I19*I47 -> 16695.169 | J104: =J19*J47 -> 57329.905 | K104: =K19*K47 -> 108687.45 | L104: =L19*L47 -> 77852.051 | M104: =M19*M47 -> 51500.026 | N104: =N19*N47 -> 25679.813 | O104: =O19*O47 -> 50374.871 | P104: =P19*P47 -> 76544.651
E105: Change in value generated as a result of crowding funding into the program (leverage) | F105: UoV | G105: calc | H105: - | I105: =SUM(I89,I99) -> -138.70447 | J105: =SUM(J89,J99) -> -235.86958 | K105: =SUM(K89,K99) -> -150.26318 | L105: =SUM(L89,L99) -> -132.19378 | M105: =SUM(M89,M99) -> -162.70003 | N105: =SUM(N89,N99) -> -289.99962 | O105: =SUM(O89,O99) -> -85.217668 | P105: =SUM(P89,P99) -> -141.8683
E106: Change in value generated as a result of crowding funding out of the program (funging) | F106: UoV | G106: calc | H106: - | I106: =SUM(I69,I79) -> -504.86765 | J106: =SUM(J69,J79) -> -8379.3809 | K106: =SUM(K69,K79) -> -32639.056 | L106: =SUM(L69,L79) -> -21846.668 | M106: =SUM(M69,M79) -> -7213.4051 | N106: =SUM(N69,N79) -> -1537.0219 | O106: =SUM(O69,O79) -> -20965.123 | P106: =SUM(P69,P79) -> -24444.66
E107: Total expected change in value generated as a result of leverage and funging | F107: UoV | G107: calc | H107: - | I107: =SUM(I69,I79,I89,I99) -> -643.57212 | J107: =SUM(J69,J79,J89,J99) -> -8615.2505 | K107: =SUM(K69,K79,K89,K99) -> -32789.32 | L107: =SUM(L69,L79,L89,L99) -> -21978.862 | M107: =SUM(M69,M79,M89,M99) -> -7376.1051 | N107: =SUM(N69,N79,N89,N99) -> -1827.0216 | O107: =SUM(O69,O79,O89,O99) -> -21050.34 | P107: =SUM(P69,P79,P89,P99) -> -24586.529
E108: Total value generated by grantee spending after adjusting for leverage and funging | F108: UOV | G108: calc | H108: - | I108: =SUM(I104,I107) -> 16051.597 | J108: =SUM(J104,J107) -> 48714.654 | K108: =SUM(K104,K107) -> 75898.127 | L108: =SUM(L104,L107) -> 55873.189 | M108: =SUM(M104,M107) -> 44123.92 | N108: =SUM(N104,N107) -> 23852.791 | O108: =SUM(O104,O107) -> 29324.531 | P108: =SUM(P104,P107) -> 51958.122
C110: Final leverage and funging adjustment
E111: Adjustment for the possibility of crowding funding into the program (leverage) | F111: % | G111: calc | H111: - | I111: =I105/I104 -> -0.0083080602 | J111: =J105/J104 -> -0.0041142504 | K111: =K105/K104 -> -0.0013825256 | L111: =L105/L104 -> -0.0016980128 | M111: =M105/M104 -> -0.0031592224 | N111: =N105/N104 -> -0.011292902 | O111: =O105/O104 -> -0.0016916702 | P111: =P105/P104 -> -0.0018534058
E112: Adjustment for the possibility of crowding funding out of the program (funging) | F112: % | G112: calc | H112: - | I112: =I106/I104 -> -0.030240344 | J112: =J106/J104 -> -0.14616073 | K112: =K106/K104 -> -0.30030199 | L112: =L106/L104 -> -0.28061776 | M112: =M106/M104 -> -0.14006605 | N112: =N106/N104 -> -0.059853316 | O112: =O106/O104 -> -0.41618216 | P112: =P106/P104 -> -0.31935165
E113: Adjustment for leverage and funging | F113: % | G113: calc | H113: - | I113: =I107/I104 -> -0.038548404 | J113: =J107/J104 -> -0.15027498 | K113: =K107/K104 -> -0.30168451 | L113: =L107/L104 -> -0.28231577 | M113: =M107/M104 -> -0.14322527 | N113: =N107/N104 -> -0.071146218 | O113: =O107/O104 -> -0.41787383 | P113: =P107/P104 -> -0.32120505
A115: Leverage and funging adjustment for counterfactual impact estimates
C117: Leverage and funging adjustment for counterfactual output estimates
E118: Leverage and funging adjustment for counterfactual output estimates | F118: % | G118: calc | H118: - | I118: =((MIN(I67,0)*I68)+(MIN(I77,0)*I78)+I105)/I104 -> -0.038548404 | J118: =((MIN(J67,0)*J68)+(MIN(J77,0)*J78)+J105)/J104 -> -0.15027498 | K118: =((MIN(K67,0)*K68)+(MIN(K77,0)*K78)+K105)/K104 -> -0.30168451 | L118: =((MIN(L67,0)*L68)+(MIN(L77,0)*L78)+L105)/L104 -> -0.28231577 | M118: =((MIN(M67,0)*M68)+(MIN(M77,0)*M78)+M105)/M104 -> -0.14322527 | N118: =((MIN(N67,0)*N68)+(MIN(N77,0)*N78)+N105)/N104 -> -0.071146218 | O118: =((MIN(O67,0)*O68)+(MIN(O77,0)*O78)+O105)/O104 -> -0.41787383 | P118: =((MIN(P67,0)*P68)+(MIN(P77,0)*P78)+P105)/P104 -> -0.32120505
C120: Leverage and funging adjustment for counterfactual outcome estimates (lives saved)
E121: Value assigned to averting a malaria-attributable death of a person under age 5 | F121: =Inputs!F154 -> UoV | G121: =Inputs!G154 -> input | H121: =Inputs!H154 -> 116.25262 | I121: =Inputs!I154 -> - | J121: =Inputs!J154 -> - | K121: =Inputs!K154 -> - | L121: =Inputs!L154 -> - | M121: =Inputs!M154 -> - | ... P121: =Inputs!P154 -> -
E122: Mortalities averted among people under age 5 by the counterfactual usage of leveraged funds, assuming they would have been spent on exclusively life-saving programs | F122: # | G122: calc | H122: - | I122: =-(I105/$H121) -> 1.1931298 | J122: =-(J105/$H121) -> 2.0289399 | K122: =-(K105/$H121) -> 1.2925573 | L122: =-(L105/$H121) -> 1.1371251 | M122: =-(M105/$H121) -> 1.3995386 | N122: =-(N105/$H121) -> 2.4945642 | O122: =-(O105/$H121) -> 0.73303869 | P122: =-(P105/$H121) -> 1.220345
E123: Total lives saved (after supplemental adjustments) | F123: =F53 -> # | G123: feed | H123: =H53 -> - | I123: =I53 -> 67.168393 | J123: =J53 -> 231.97474 | K123: =K53 -> 487.86972 | L123: =L53 -> 362.93056 | M123: =M53 -> 225.60695 | N123: =N53 -> 101.96729 | O123: =O53 -> 216.2644 | P123: =P53 -> 301.76271
...

Sheet Inputs
I1: Against Malaria Foundation
I2: Chad | J2: DRC | K2: Guinea | L2: Nigeria | M2: Nigeria | N2: South Sudan | O2: Togo | P2: Uganda
A3: Inputs | F3: unit | G3: type | H3: Overall | L3: GF states | M3: PMI states | R3: Source | S3: GW analysis and discussion
E4: Final cost-effectiveness estimate (pulled from "Main calcs" sheet for visibility) | F4: ='Main CEA'!F203 -> xbenchmark | G4: main | H4: ='Main CEA'!H203 -> - | I4: ='Main CEA'!I203 -> 4.8202994 | J4: ='Main CEA'!J203 -> 14.629025 | K4: ='Main CEA'!K203 -> 22.79223 | L4: ='Main CEA'!L203 -> 16.778736 | M4: ='Main CEA'!M203 -> 13.250427 | N4: ='Main CEA'!N203 -> 7.1630004 | O4: ='Main CEA'!O203 -> 8.8061654 | P4: ='Main CEA'!P203 -> 15.60304
A5: Costs
C7: GiveWell costs
E8: Grant size | F8: $ | G8: input | H8: 1000000 | I8: - | J8: - | K8: - | L8: - | M8: - | N8: - | O8: - | P8: - | R8: Arbitrary value
C10: Cost breakdown
E11: Percentage of total costs covered by the grantee | F11: % | G11: input | H11: - | I11: 0.9562847 | J11: 0.9449092 | K11: 0.9562847 | L11: 0.9613383 | M11: 0.9613383 | N11: 0.936798 | O11: 0.9595745 | P11: 0.9553321 | R11: GW analysis | S11: GW's analysis of AMF cost per net [unpublished]
E12: Percentage of total costs covered by other philanthropic actors | F12: % | G12: input | H12: - | I12: =K12 -> 0 | J12: 0 | K12: 0 | L12: 0 | M12: 0 | N12: 0 | O12: 0 | P12: 0 | R12: GW analysis | S12: GW's analysis of AMF cost per net [unpublished]
E13: Percentage of total costs covered by domestic governments | F13: % | G13: input | H13: - | I13: =K13 -> 0.0437153 | J13: 0.0550908 | K13: 0.0437153 | L13: 0.0386617 | M13: 0.0386617 | N13: 0.0632021 | O13: 0.0404255 | P13: 0.0446679 | R13: GW analysis | S13: GW's analysis of AMF cost per net [unpublished]
C15: Cost per net
E16: Total cost per insecticide-treated net (ITN) distributed | F16: $ | G16: input | H16: - | I16: =K16 -> 3.93785 | J16: 5.85033 | K16: 3.93785 | L16: 4.34117 | M16: 4.34117 | N16: 5.32824 | O16: 3.66624 | P16: 4.44504 | R16: GW analysis | S16: GW's analysis of AMF cost per net [unpublished]
A18: Outputs
C20: Net usage
E21: Proportion of distributed nets that were used in trials from the Pryce et al. 2018 meta-analysis | F21: % | G21: input | H21: 0.7 | I21: - | J21: - | K21: - | L21: - | M21: - | N21: - | O21: - | P21: - | R21: GW analysis | S21: Updated GiveWell summary of ITN RCTs
E22: Adjustment for net usage in program contexts | F22: % | G22: input | H22: -0.1 | I22: - | J22: - | K22: - | L22: - | M22: - | N22: - | O22: - | P22: - | R22: GW guesstimate
C24: Net coverage
E25: Number of people sleeping under each used net | F25: # | G25: input | H25: - | I25: 1.93645 | J25: 2.15114 | K25: 1.99095 | L25: 1.93645 | M25: 1.93645 | N25: 1.93645 | O25: 1.72163 | P25: 1.76505 | R25: GW analysis | S25: GW's analysis of the number of people covered per net
C27: Age distribution of population
E28: Total national population | F28: # | G28: input | H28: - | I28: =IFERROR(__xludf.DUMMYFUNCTION("FILTER('GBD estimates'!$H$4:$H$2400,'GBD estimates'!$B$4:$B$2400=I$2,'GBD estimates'!$D$4:$D$2400=""All Ages"")"),1.639885974E7) -> 16398860 | J28: =IFERROR(__xludf.DUMMYFUNCTION("FILTER('GBD estimates'!$H$4:$H$2400,'GBD estimates'!$B$4:$B$2400=J$2,'GBD estimates'!$D$4:$D$2400=""All Ages"")"),8.767044378E7) -> 87670444 | K28: =IFERROR(__xludf.DUMMYFUNCTION("FILTER('GBD estimates'!$H$4:$H$2400,'GBD estimates'!$B$4:$B$2400=K$2,'GBD estimates'!$D$4:$D$2400=""All Ages"")"),1.264314893E7) -> 12643149 | L28: =IFERROR(__xludf.DUMMYFUNCTION("FILTER('GBD estimates'!$H$4:$H$2400,'GBD estimates'!$B$4:$B$2400=L$2,'GBD estimates'!$D$4:$D$2400=""All Ages"")"),2.148237857E8) -> 2.1482379e+08 | M28: =IFERROR(__xludf.DUMMYFUNCTION("FILTER('GBD estimates'!$H$4:$H$2400,'GBD estimates'!$B$4:$B$2400=M$2,'GBD estimates'!$D$4:$D$2400=""All Ages"")"),2.148237857E8) -> 2.1482379e+08 | N28: =IFERROR(__xludf.DUMMYFUNCTION("FILTER('GBD estimates'!$H$4:$H$2400,'GBD estimates'!$B$4:$B$2400=N$2,'GBD estimates'!$D$4:$D$2400=""All Ages"")"),9282963.047) -> 9282963 | O28: =IFERROR(__xludf.DUMMYFUNCTION("FILTER('GBD estimates'!$H$4:$H$2400,'GBD estimates'!$B$4:$B$2400=O$2,'GBD estimates'!$D$4:$D$2400=""All Ages"")"),7921526.585) -> 7921526.6 | P28: =IFERROR(__xludf.DUMMYFUNCTION("FILTER('GBD estimates'!$H$4:$H$2400,'GBD estimates'!$B$4:$B$2400=P$2,'GBD estimates'!$D$4:$D$2400=""All Ages"")"),4.111785624E7) -> 41117856 | R28: GBD 2019
E29: National population under age 5 | F29: # | G29: input | H29: - | I29: =IFERROR(__xludf.DUMMYFUNCTION("FILTER('GBD estimates'!$H$4:$H$2400,'GBD estimates'!$B$4:$B$2400=I$2,'GBD estimates'!$D$4:$D$2400=""Under 5"")"),3332666.562) -> 3332666.6 | J29: =IFERROR(__xludf.DUMMYFUNCTION("FILTER('GBD estimates'!$H$4:$H$2400,'GBD estimates'!$B$4:$B$2400=J$2,'GBD estimates'!$D$4:$D$2400=""Under 5"")"),1.362946515E7) -> 13629465 | K29: =IFERROR(__xludf.DUMMYFUNCTION("FILTER('GBD estimates'!$H$4:$H$2400,'GBD estimates'!$B$4:$B$2400=K$2,'GBD estimates'!$D$4:$D$2400=""Under 5"")"),2143394.877) -> 2143394.9 | L29: =IFERROR(__xludf.DUMMYFUNCTION("FILTER('GBD estimates'!$H$4:$H$2400,'GBD estimates'!$B$4:$B$2400=L$2,'GBD estimates'!$D$4:$D$2400=""Under 5"")"),3.352163783E7) -> 33521638 | M29: =IFERROR(__xludf.DUMMYFUNCTION("FILTER('GBD estimates'!$H$4:$H$2400,'GBD estimates'!$B$4:$B$2400=M$2,'GBD estimates'!$D$4:$D$2400=""Under 5"")"),3.352163783E7) -> 33521638 | N29: =IFERROR(__xludf.DUMMYFUNCTION("FILTER('GBD estimates'!$H$4:$H$2400,'GBD estimates'!$B$4:$B$2400=N$2,'GBD estimates'!$D$4:$D$2400=""Under 5"")"),1516375.155) -> 1516375.2 | O29: =IFERROR(__xludf.DUMMYFUNCTION("FILTER('GBD estimates'!$H$4:$H$2400,'GBD estimates'!$B$4:$B$2400=O$2,'GBD estimates'!$D$4:$D$2400=""Under 5"")"),1114855.207) -> 1114855.2 | P29: =IFERROR(__xludf.DUMMYFUNCTION("FILTER('GBD estimates'!$H$4:$H$2400,'GBD estimates'!$B$4:$B$2400=P$2,'GBD estimates'!$D$4:$D$2400=""Under 5"")"),7089749.816) -> 7089749.8 | R29: GBD 2019
E30: National population age 5-14 | F30: # | G30: input | H30: - | I30: =IFERROR(__xludf.DUMMYFUNCTION("FILTER('GBD estimates'!$H$4:$H$2400,'GBD estimates'!$B$4:$B$2400=I$2,'GBD estimates'!$D$4:$D$2400=""5-14 years"")"),4977421.002) -> 4977421 | J30: =IFERROR(__xludf.DUMMYFUNCTION("FILTER('GBD estimates'!$H$4:$H$2400,'GBD estimates'!$B$4:$B$2400=J$2,'GBD estimates'!$D$4:$D$2400=""5-14 years"")"),2.406568016E7) -> 24065680 | K30: =IFERROR(__xludf.DUMMYFUNCTION("FILTER('GBD estimates'!$H$4:$H$2400,'GBD estimates'!$B$4:$B$2400=K$2,'GBD estimates'!$D$4:$D$2400=""5-14 years"")"),3569794.5) -> 3569794.5 | L30: =IFERROR(__xludf.DUMMYFUNCTION("FILTER('GBD estimates'!$H$4:$H$2400,'GBD estimates'!$B$4:$B$2400=L$2,'GBD estimates'!$D$4:$D$2400=""5-14 years"")"),6.022643653E7) -> 60226437 | M30: =IFERROR(__xludf.DUMMYFUNCTION("FILTER('GBD estimates'!$H$4:$H$2400,'GBD estimates'!$B$4:$B$2400=M$2,'GBD estimates'!$D$4:$D$2400=""5-14 years"")"),6.022643653E7) -> 60226437 | N30: =IFERROR(__xludf.DUMMYFUNCTION("FILTER('GBD estimates'!$H$4:$H$2400,'GBD estimates'!$B$4:$B$2400=N$2,'GBD estimates'!$D$4:$D$2400=""5-14 years"")"),2652127.884) -> 2652127.9 | O30: =IFERROR(__xludf.DUMMYFUNCTION("FILTER('GBD estimates'!$H$4:$H$2400,'GBD estimates'!$B$4:$B$2400=O$2,'GBD estimates'!$D$4:$D$2400=""5-14 years"")"),2032780.787) -> 2032780.8 | P30: =IFERROR(__xludf.DUMMYFUNCTION("FILTER('GBD estimates'!$H$4:$H$2400,'GBD estimates'!$B$4:$B$2400=P$2,'GBD estimates'!$D$4:$D$2400=""5-14 years"")"),1.198772212E7) -> 11987722 | R30: GBD 2019
A32: Effective coverage years provided per net
C34: Net coverage years lost to attrition
E35: Percentage of nets remaining in use two years after the CTN distributions in trials from the Pryce et al. 2018 meta-analysis | F35: % | G35: input | H35: 1 | I35: - | J35: - | K35: - | L35: - | M35: - | N35: - | O35: - | P35: - | R35: GW analysis | S35: GW's model of ITN coverage years compared to CTNs
E36: Average percentage of nets remaining in use during the 1st year after an ITN distribution | F36: % | G36: input | H36: 0.9539455 | I36: - | J36: - | K36: - | L36: - | M36: - | N36: - | O36: - | P36: - | R36: GW analysis | S36: GW's model of ITN coverage years compared to CTNs
E37: Average percentage of nets remaining in use during the 2nd year after an ITN distribution | F37: % | G37: input | H37: 0.8345774 | I37: - | J37: - | K37: - | L37: - | M37: - | N37: - | O37: - | P37: - | R37: GW analysis | S37: GW's model of ITN coverage years compared to CTNs
E38: Average percentage of nets remaining in use during the 3rd year after an ITN distribution | F38: % | G38: input | H38: 0.6935533 | I38: - | J38: - | K38: - | L38: - | M38: - | N38: - | O38: - | P38: - | R38: GW analysis | S38: GW's model of ITN coverage years compared to CTNs
C40: Net coverage years lost due to physical decay
E41: Percentage of remaining nets lost due to physical damage at the midpoint of the 1st year after an ITN distribution | F41: % | G41: input | H41: 0.0346098 | I41: - | J41: - | K41: - | L41: - | M41: - | N41: - | O41: - | P41: - | R41: GW analysis | S41: GW's model of ITN coverage years compared to CTNs
E42: Percentage of remaining nets lost due to physical damage at the midpoint of the 2nd year after an ITN distribution | F42: % | G42: input | H42: 0.1536925 | I42: - | J42: - | K42: - | L42: - | M42: - | N42: - | O42: - | P42: - | R42: GW analysis | S42: GW's model of ITN coverage years compared to CTNs
E43: Percentage of remaining nets lost due to physical damage at the midpoint of the 3rd year after an ITN distribution | F43: % | G43: input | H43: 0.3453212 | I43: - | J43: - | K43: - | L43: - | M43: - | N43: - | O43: - | P43: - | R43: GW analysis | S43: GW's model of ITN coverage years compared to CTNs
E44: Ratio of physical net decay in trials of CTN distributions from the Pryce et al. 2018 meta-analysis compared to physical net decay from grantee ITN distributions | F44: % | G44: input | H44: 0.33 | I44: - | J44: - | K44: - | L44: - | M44: - | N44: - | O44: - | P44: - | R44: GW analysis | S44: GW's model of ITN coverage years compared to CTNs
C46: Net coverage years lost due to insecticide decay
E47: Proportion of net coverage lost due to insecticide decay for CTNs distributed in trials from the Pryce et al. 2018 meta-analysis | F47: % | G47: input | H47: 0 | I47: - | J47: - | K47: - | L47: - | M47: - | N47: - | O47: - | P47: - | R47: GW analysis | S47: GW's model of ITN coverage years compared to CTNs
E48: Proportion of net coverage lost due to insecticide decay for ITNs distributed in grantee distributions | F48: % | G48: input | H48: 0 | I48: - | J48: - | K48: - | L48: - | M48: - | N48: - | O48: - | P48: - | R48: GW analysis | S48: GW's model of ITN coverage years compared to CTNs
C50: Trial-equivalent coverage years provided per distributed net
E51: Effective net coverage years provided by a CTN distributed in a trial from the Pryce et al. 2018 meta-analysis (reference value) | F51: # | G51: input | H51: 1 | I51: - | J51: - | K51: - | L51: - | M51: - | N51: - | O51: - | P51: - | R51: Arbitrary value
C53: Adjustment for generic ITNs
E54: Adjustment for reduced net coverage provided by generic ITNs | F54: % | G54: input | H54: -0.15 | I54: - | J54: - | K54: - | L54: - | M54: - | N54: - | O54: - | P54: - | R54: GW guesstimate
C56: Breakdown of net types purchased for distributions
E57: Expected proportion of ITNs purchased that are generic ITNs | F57: % | G57: input | H57: 0.465547 | I57: - | J57: - | K57: - | L57: - | M57: - | N57: - | O57: - | P57: - | R57: GW analysis | S57: GW's analysis of AMF net purchases by net type
C59: Adjustment for lower net durability in DRC
E60: Adjustment for lower net durability in DRC than in other countries | F60: % | G60: input | H60: - | I60: - | J60: -0.1737044 | K60: - | L60: - | M60: - | N60: - | O60: - | P60: - | R60: GW analysis | S60: GW's analysis of DRC net durability
C62: Extrapolated net decay rate over a six-year period
E63: Effective coverage years provided per net in the 4th year after a grantee ITN distribution | F63: # | G63: input | H63: 0.218549 | I63: - | J63: - | K63: - | L63: - | M63: - | N63: - | O63: - | P63: - | R63: GW analysis | S63: GW's model of ITN coverage years compared to CTNs
E64: Effective coverage years provided per net in the 5th year after a grantee ITN distribution | F64: # | G64: input | H64: 0.065935 | I64: - | J64: - | K64: - | L64: - | M64: - | N64: - | O64: - | P64: - | R64: GW analysis | S64: GW's model of ITN coverage years compared to CTNs
E65: Effective coverage years provided per net in the 6th year after a grantee ITN distribution | F65: # | G65: input | H65: 0.010989 | I65: - | J65: - | K65: - | L65: - | M65: - | N65: - | O65: - | P65: - | R65: GW analysis | S65: GW's model of ITN coverage years compared to CTNs
C67: Adjusted net decay rate adjusted for lower net durability in DRC
E68: Adjustment for lower effective coverage years provided in the 1st year after a grantee ITN distribution in DRC | F68: % | G68: input | H68: - | I68: - | J68: -0.1165152 | K68: - | L68: - | M68: - | N68: - | O68: - | P68: - | R68: GW analysis | S68: GW's analysis of DRC net durability
E69: Adjustment for lower effective coverage years provided in the 2nd year after a grantee ITN distribution in DRC | F69: % | G69: input | H69: - | I69: - | J69: -0.1609735 | K69: - | L69: - | M69: - | N69: - | O69: - | P69: - | R69: GW analysis | S69: GW's analysis of DRC net durability
E70: Adjustment for lower effective coverage years provided in the 3rd year after a grantee ITN distribution in DRC | F70: % | G70: input | H70: - | I70: - | J70: -0.3246594 | K70: - | L70: - | M70: - | N70: - | O70: - | P70: - | R70: GW analysis | S70: GW's analysis of DRC net durability
C72: Changes in net distribution intervals
E73: Standard number of months between ITN distributions as modeled in this CEA | F73: # | G73: input | H73: 36 | I73: - | J73: - | K73: - | L73: - | M73: - | N73: - | O73: - | P73: -
E74: Expected number of months between the previous net distribution and the upcoming distribution in the absence of a grant | F74: # | G74: input | H74: - | I74: - | J74: 42 | K74: - | L74: - | M74: 45 | N74: 45 | O74: - | P74: - | R74: GW analysis
E75: Expected number of months between the previous net distribution and the upcoming distribution if a grant is made | F75: # | G75: input | H75: - | I75: - | J75: 33 | K75: - | L75: - | M75: 36 | N75: 35 | O75: - | P75: - | R75: GW analysis
C77: Residual net retention and discard rate
E78: Proportion of residual nets that is retained at start of a new distribution | F78: % | G78: input | H78: 0.5 | I78: - | J78: - | K78: - | L78: - | M78: - | N78: - | O78: - | P78: - | R78: GW guesstimate
E79: Proportion of residual nets that is discarded at start of a new distribution | F79: % | G79: input | H79: 0.5 | I79: - | J79: - | K79: - | L79: - | M79: - | N79: - | O79: - | P79: - | R79: GW guesstimate
E80: Proportion of net durability studies that capture contributions from residual nets | F80: % | G80: input | H80: 0.5 | I80: - | J80: - | K80: - | L80: - | M80: - | N80: - | O80: - | P80: - | R80: GW guesstimate
A82: Counterfactual malaria mortality and incidence
C84: Population estimates
E85: Population age 1-11 months (2019) | F85: # | G85: input | H85: - | I85: =IFERROR(__xludf.DUMMYFUNCTION("FILTER('GBD estimates'!$H$4:$H$2400,'GBD estimates'!$B$4:$B$2400=I$2,'GBD estimates'!$D$4:$D$2400=""Post neonatal"")"),679765.5845) -> 679765.58 | J85: =IFERROR(__xludf.DUMMYFUNCTION("FILTER('GBD estimates'!$H$4:$H$2400,'GBD estimates'!$B$4:$B$2400=J$2,'GBD estimates'!$D$4:$D$2400=""Post neonatal"")"),2588275.621) -> 2588275.6 | K85: =IFERROR(__xludf.DUMMYFUNCTION("FILTER('GBD estimates'!$H$4:$H$2400,'GBD estimates'!$B$4:$B$2400=K$2,'GBD estimates'!$D$4:$D$2400=""Post neonatal"")"),418381.7553) -> 418381.76 | L85: 3254748 | M85: 1982320 | N85: =IFERROR(__xludf.DUMMYFUNCTION("FILTER('GBD estimates'!$H$4:$H$2400,'GBD estimates'!$B$4:$B$2400=N$2,'GBD estimates'!$D$4:$D$2400=""Post neonatal"")"),312473.8751) -> 312473.88 | O85: =IFERROR(__xludf.DUMMYFUNCTION("FILTER('GBD estimates'!$H$4:$H$2400,'GBD estimates'!$B$4:$B$2400=O$2,'GBD estimates'!$D$4:$D$2400=""Post neonatal"")"),209954.9274) -> 209954.93 | P85: =IFERROR(__xludf.DUMMYFUNCTION("FILTER('GBD estimates'!$H$4:$H$2400,'GBD estimates'!$B$4:$B$2400=P$2,'GBD estimates'!$D$4:$D$2400=""Post neonatal"")"),1389726.819) -> 1389726.8 | R85: GBD 2019
E86: Population age 12-59 months (2019) | F86: # | G86: input | H86: - | I86: =IFERROR(__xludf.DUMMYFUNCTION("FILTER('GBD estimates'!$H$4:$H$2400,'GBD estimates'!$B$4:$B$2400=I$2,'GBD estimates'!$D$4:$D$2400=""1 to 4"")"),2593740.178) -> 2593740.2 | J86: =IFERROR(__xludf.DUMMYFUNCTION("FILTER('GBD estimates'!$H$4:$H$2400,'GBD estimates'!$B$4:$B$2400=J$2,'GBD estimates'!$D$4:$D$2400=""1 to 4"")"),1.082114861E7) -> 10821149 | K86: =IFERROR(__xludf.DUMMYFUNCTION("FILTER('GBD estimates'!$H$4:$H$2400,'GBD estimates'!$B$4:$B$2400=K$2,'GBD estimates'!$D$4:$D$2400=""1 to 4"")"),1689051.292) -> 1689051.3 | L86: 12757890 | M86: 7939853 | N86: =IFERROR(__xludf.DUMMYFUNCTION("FILTER('GBD estimates'!$H$4:$H$2400,'GBD estimates'!$B$4:$B$2400=N$2,'GBD estimates'!$D$4:$D$2400=""1 to 4"")"),1176806.224) -> 1176806.2 | O86: =IFERROR(__xludf.DUMMYFUNCTION("FILTER('GBD estimates'!$H$4:$H$2400,'GBD estimates'!$B$4:$B$2400=O$2,'GBD estimates'!$D$4:$D$2400=""1 to 4"")"),887125.4327) -> 887125.43 | P86: =IFERROR(__xludf.DUMMYFUNCTION("FILTER('GBD estimates'!$H$4:$H$2400,'GBD estimates'!$B$4:$B$2400=P$2,'GBD estimates'!$D$4:$D$2400=""1 to 4"")"),5581405.246) -> 5581405.2 | R86: GBD 2019
C88: Baseline malaria mortality
E89: Annual malaria mortality rate among 1-11-month-olds (2019) | F89: per 100k | G89: input | H89: - | I89: =IFERROR(__xludf.DUMMYFUNCTION("FILTER('GBD estimates'!$AY$4:$AY$2400,'GBD estimates'!$AS$4:$AS$2400=I$2,'GBD estimates'!$AU$4:$AU$2400=""28-364 days"")"),206.3169556) -> 206.31696 | J89: =IFERROR(__xludf.DUMMYFUNCTION("FILTER('GBD estimates'!$AY$4:$AY$2400,'GBD estimates'!$AS$4:$AS$2400=J$2,'GBD estimates'!$AU$4:$AU$2400=""28-364 days"")"),676.6709689) -> 676.67097 | K89: =IFERROR(__xludf.DUMMYFUNCTION("FILTER('GBD estimates'!$AY$4:$AY$2400,'GBD estimates'!$AS$4:$AS$2400=K$2,'GBD estimates'!$AU$4:$AU$2400=""28-364 days"")"),597.0245755) -> 597.02458 | L89: 279.38 | M89: 339.26 | N89: =IFERROR(__xludf.DUMMYFUNCTION("FILTER('GBD estimates'!$AY$4:$AY$2400,'GBD estimates'!$AS$4:$AS$2400=N$2,'GBD estimates'!$AU$4:$AU$2400=""28-364 days"")"),633.5822854) -> 633.58229 | O89: =IFERROR(__xludf.DUMMYFUNCTION("FILTER('GBD estimates'!$AY$4:$AY$2400,'GBD estimates'!$AS$4:$AS$2400=O$2,'GBD estimates'!$AU$4:$AU$2400=""28-364 days"")"),273.9085238) -> 273.90852 | P89: =IFERROR(__xludf.DUMMYFUNCTION("FILTER('GBD estimates'!$AY$4:$AY$2400,'GBD estimates'!$AS$4:$AS$2400=P$2,'GBD estimates'!$AU$4:$AU$2400=""28-364 days"")"),535.9722374) -> 535.97224 | R89: GBD 2019
E90: Annual malaria mortality rate among 12-59-month-olds (2019) | F90: per 100k | G90: input | H90: - | I90: =IFERROR(__xludf.DUMMYFUNCTION("FILTER('GBD estimates'!$AY$4:$AY$2400,'GBD estimates'!$AS$4:$AS$2400=I$2,'GBD estimates'!$AU$4:$AU$2400=""1-4 YEARS"")"),112.3965653) -> 112.39657 | J90: =IFERROR(__xludf.DUMMYFUNCTION("FILTER('GBD estimates'!$AY$4:$AY$2400,'GBD estimates'!$AS$4:$AS$2400=J$2,'GBD estimates'!$AU$4:$AU$2400=""1-4 YEARS"")"),216.900166) -> 216.90017 | K90: =IFERROR(__xludf.DUMMYFUNCTION("FILTER('GBD estimates'!$AY$4:$AY$2400,'GBD estimates'!$AS$4:$AS$2400=K$2,'GBD estimates'!$AU$4:$AU$2400=""1-4 YEARS"")"),310.5104231) -> 310.51042 | L90: 268.21 | M90: 278.52 | N90: =IFERROR(__xludf.DUMMYFUNCTION("FILTER('GBD estimates'!$AY$4:$AY$2400,'GBD estimates'!$AS$4:$AS$2400=N$2,'GBD estimates'!$AU$4:$AU$2400=""1-4 YEARS"")"),150.1960967) -> 150.1961 | O90: =IFERROR(__xludf.DUMMYFUNCTION("FILTER('GBD estimates'!$AY$4:$AY$2400,'GBD estimates'!$AS$4:$AS$2400=O$2,'GBD estimates'!$AU$4:$AU$2400=""1-4 YEARS"")"),137.8812522) -> 137.88125 | P90: =IFERROR(__xludf.DUMMYFUNCTION("FILTER('GBD estimates'!$AY$4:$AY$2400,'GBD estimates'!$AS$4:$AS$2400=P$2,'GBD estimates'!$AU$4:$AU$2400=""1-4 YEARS"")"),160.1204666) -> 160.12047 | R90: GBD 2019
C92: Adjusting for deaths averted by seasonal malaria chemoprevention (SMC)
E93: Target population of 3-59 month-olds for seasonal malaria chemoprevention programs (SMC) | F93: # | G93: input | H93: - | I93: - | J93: - | K93: - | L93: 6450000 | M93: 8960943 | N93: - | O93: 490000 | P93: - | R93: GW analysis & Malaria Consortium | S93: GW's analysis of Nigerian state-level population estimates
E94: Proportion of total population age 1-59 months living in areas where SMC is implemented | F94: % | G94: input | H94: - | I94: - | J94: - | K94: - | L94: - | M94: - | N94: 0.3 | O94: - | P94: - | R94: GW guesstimate
E95: Probability that available bed nets would be targeted across the country evenly in the absence of grantee support | F95: % | G95: input | H95: - | I95: - | J95: - | K95: - | L95: - | M95: - | N95: - | O95: 0.7 | P95: - | R95: GW guesstimate
E96: Probability that available bed nets would be targeted at non-SMC areas in the absence of grantee support | F96: % | G96: input | H96: - | I96: - | J96: - | K96: - | L96: - | M96: - | N96: - | O96: 0.3 | P96: - | R96: GW guesstimate
E97: Malaria-attributable deaths averted by SMC per year among 1-59-month-olds living in areas where SMC is implemented | F97: per 1k | G97: input | H97: - | I97: 0.91339 | J97: 0 | K97: 0 | L97: 1.57538 | M97: 1.57538 | N97: 1.44814 | O97: 1.15931 | P97: 0 | R97: GW analysis
C99: Malaria incidence among people under age 15
E100: Malaria incidence among people under age 5 | F100: per 100k | G100: input | H100: - | I100: 22099.7 | J100: =IFERROR(__xludf.DUMMYFUNCTION("FILTER('GBD estimates'!$BU$4:$BU$2400,'GBD estimates'!$BO$4:$BO$2400=J$2,'GBD estimates'!$BQ$4:$BQ$2400=""<5 years"")"),87914.33967) -> 87914.34 | K100: =IFERROR(__xludf.DUMMYFUNCTION("FILTER('GBD estimates'!$BU$4:$BU$2400,'GBD estimates'!$BO$4:$BO$2400=K$2,'GBD estimates'!$BQ$4:$BQ$2400=""<5 years"")"),71510.2768) -> 71510.277 | L100: 61766.056 | M100: 75404.464 | N100: =IFERROR(__xludf.DUMMYFUNCTION("FILTER('GBD estimates'!$BU$4:$BU$2400,'GBD estimates'!$BO$4:$BO$2400=N$2,'GBD estimates'!$BQ$4:$BQ$2400=""<5 years"")"),58925.09826) -> 58925.098 | O100: =IFERROR(__xludf.DUMMYFUNCTION("FILTER('GBD estimates'!$BU$4:$BU$2400,'GBD estimates'!$BO$4:$BO$2400=O$2,'GBD estimates'!$BQ$4:$BQ$2400=""<5 years"")"),73532.86785) -> 73532.868 | P100: =IFERROR(__xludf.DUMMYFUNCTION("FILTER('GBD estimates'!$BU$4:$BU$2400,'GBD estimates'!$BO$4:$BO$2400=P$2,'GBD estimates'!$BQ$4:$BQ$2400=""<5 years"")"),65525.52366) -> 65525.524 | R100: GBD 2019
E101: Malaria incidence among people age 5 to 14 | F101: per 100k | G101: input | H101: - | I101: 22099.7 | J101: =IFERROR(__xludf.DUMMYFUNCTION("FILTER('GBD estimates'!$BU$4:$BU$2400,'GBD estimates'!$BO$4:$BO$2400=J$2,'GBD estimates'!$BQ$4:$BQ$2400=""5-14 years"")"),35845.96564) -> 35845.966 | K101: =IFERROR(__xludf.DUMMYFUNCTION("FILTER('GBD estimates'!$BU$4:$BU$2400,'GBD estimates'!$BO$4:$BO$2400=K$2,'GBD estimates'!$BQ$4:$BQ$2400=""5-14 years"")"),29839.07359) -> 29839.074 | L101: 26873.555 | M101: 32080.311 | N101: =IFERROR(__xludf.DUMMYFUNCTION("FILTER('GBD estimates'!$BU$4:$BU$2400,'GBD estimates'!$BO$4:$BO$2400=N$2,'GBD estimates'!$BQ$4:$BQ$2400=""5-14 years"")"),24977.74508) -> 24977.745 | O101: =IFERROR(__xludf.DUMMYFUNCTION("FILTER('GBD estimates'!$BU$4:$BU$2400,'GBD estimates'!$BO$4:$BO$2400=O$2,'GBD estimates'!$BQ$4:$BQ$2400=""5-14 years"")"),30845.0741) -> 30845.074 | P101: =IFERROR(__xludf.DUMMYFUNCTION("FILTER('GBD estimates'!$BU$4:$BU$2400,'GBD estimates'!$BO$4:$BO$2400=P$2,'GBD estimates'!$BQ$4:$BQ$2400=""5-14 years"")"),27394.99883) -> 27394.999 | R101: GBD 2019
A103: Insecticide resistance adjustment
C105: Resistance to pyrethroid insecticides
E106: Average mosquito mortality rate found in pyrethroid bioassays (2015-2019) | F106: % | G106: input | H106: - | I106: 0.2369133 | J106: 0.5206558 | K106: 0.7017647 | L106: 0.7498112 | M106: 0.7498112 | N106: 0.517 | O106: 0.2285474 | P106: 0.4379605 | R106: GW analysis | S106: GW's insecticide resistance analysis
E107: Average year pyrethroid bioassays were conducted | F107: year | G107: input | H107: - | I107: 2014.93 | J107: 2016.56 | K107: 2016.97 | L107: 2017.41 | M107: 2017.41 | N107: 2020 | O107: 2015.47 | P107: 2016.11 | R107: GW analysis | S107: GW's insecticide resistance analysis
E108: Expected year of ITN distribution | F108: year | G108: input | H108: - | I108: 2026 | J108: 2024 | K108: 2025 | L108: 2023 | M108: 2023 | N108: 2023 | O108: 2023 | P108: 2023 | R108: Against Malaria Foundation
E109: Expected annual change in mosquito mortality rates over time | F109: ppt | G109: input | H109: =-0.05/6 -> -0.0083333333 | I109: - | J109: - | K109: - | L109: - | M109: - | N109: - | O109: - | P109: - | R109: WHO Global report on insecticide resistance in malaria vectors: 2010-2016
C111: Role of insecticide in the protective effect of nets
E112: Proportion of the protective effect of ITNs that is due to the physical barrier of the net | F112: % | G112: input | H112: 0.2702179 | I112: - | J112: - | K112: - | L112: - | M112: - | N112: - | O112: - | P112: - | R112: GW analysis | S112: GW's insecticide resistance analysis
C114: Resistance to pyrethroid insecticides plus a piperonyl-butoxide (PBO) synergist
E115: Average mosquito mortality rate found in bioassays of pyrethroid plus PBO (2015-2019) | F115: % | G115: input | H115: - | I115: 0.54575 | J115: 0.9597 | K115: 0.8975 | L115: 0.9255039 | M115: 0.9255039 | N115: 0.9563198 | O115: 0.928 | P115: 0.9541395 | R115: GW analysis | S115: GW's insecticide resistance analysis
E116: Average mosquito mortality rate found in the same bioassays of pyrethroid only | F116: % | G116: input | H116: - | I116: 0.4292125 | J116: 0.5559 | K116: 0.6 | L116: 0.691197 | M116: 0.691197 | N116: 0.5614558 | O116: 0.1115 | P116: 0.5084116 | R116: GW analysis | S116: GW's insecticide resistance analysis
E117: Proportion of bioassay test sites with confirmed pyrethroid insecticide resistance (2015-2019) | F117: % | G117: input | H117: - | I117: 1 | J117: 0.8051948 | K117: 0.7647059 | L117: 0.6246787 | M117: 0.6246787 | N117: 0.8873604 | O117: 1 | P117: 0.9868421 | R117: GW analysis | S117: GW's insecticide resistance analysis
E118: Proportion of test sites detected to have relevant resistance mechanism (2015-2019) | F118: % | G118: input | H118: - | I118: 0.7142857 | J118: 1 | K118: 0.7916667 | L118: 0.7916667 | M118: 0.7916667 | N118: 0.9166667 | O118: 0.7916667 | P118: 0.8333333 | R118: GW analysis | S118: GW's insecticide resistance analysis
C120: Resistance to insecticides used in other Dual AI nets
E121: Reduction in effectiveness due to insecticide resistance with chlorfenapyr nets | F121: % | G121: input | H121: 0 | I121: - | J121: - | K121: - | L121: - | M121: - | N121: - | O121: - | P121: - | R121: GW guesstimate
C123: Breakdown of nets purchased
E124: Expected proportion of PBO nets purchased for distributions | F124: % | G124: input | H124: - | I124: 0.3 | J124: 0.5 | K124: 0.3 | L124: 1 | M124: 1 | N124: 0.19 | O124: 0.5 | P124: 1 | R124: GW guesstimate
E125: Expected proportion of chlorfenapyr nets purchased for distributions | F125: % | G125: input | H125: - | I125: 0 | J125: 0.45 | K125: 0 | L125: 0 | M125: 0 | N125: 0 | O125: 0 | P125: 0 | R125: GW guesstimate
E126: Expected proportion of other Dual AI nets purchased for distributions | F126: % | G126: input | H126: - | I126: 0 | J126: 0.05 | K126: 0 | L126: 0 | M126: 0 | N126: 0 | O126: 0 | P126: 0 | R126: GW guesstimate
E127: Expected proportion of standard ITNs purchased for distributions | F127: % | G127: input | H127: - | I127: =1-SUM(I124:I126) -> 0.7 | J127: =1-SUM(J124:J126) -> 0 | K127: =1-SUM(K124:K126) -> 0.7 | L127: =1-SUM(L124:L126) -> 0 | M127: =1-SUM(M124:M126) -> 0 | N127: =1-SUM(N124:N126) -> 0.81 | O127: =1-SUM(O124:O126) -> 0.5 | P127: =1-SUM(P124:P126) -> 0 | R127: GW guesstimate
A129: Outcomes
C131: Mortality reduction among people under age 5
E132: Reduction in malaria incidence for children under age 5 receiving nets found in the Pryce et al. 2018 meta-analysis | F132: % | G132: input | H132: 0.45 | I132: - | J132: - | K132: - | L132: - | M132: - | N132: - | O132: - | P132: - | R132: Pryce et al. 2018
...

Sheet Net decay model
A1: Net decay model (separated from the "Effective coverage" sheet to preserve space)
B3: For more information about how we model LLIN decay rates, see this page.
B5: Annual net decay function, DRC | G5: Annual net decay function, other countries
B6: Midpoint of year following a distribution | C6: Projected effective coverage years per year | G6: Midpoint of year following a distribution | H6: Projected effective coverage years per year
B7: 0 | C7: 1 | G7: 0 | H7: 1
B8: 1 | C8: ='Effective coverage'!J82 -> 0.80864958 | G8: 1 | H8: ='Effective coverage'!I82 -> 0.91529541
B9: 2 | C9: ='Effective coverage'!J83 -> 0.60045961 | G9: 2 | H9: ='Effective coverage'!I83 -> 0.71566228
B10: 3 | C10: ='Effective coverage'!J84 -> 0.32485453 | G10: 3 | H10: ='Effective coverage'!I84 -> 0.48102325
B11: 4 | C11: ='Effective coverage'!J85 -> 0.070176942 | G11: 4 | H11: ='Effective coverage'!I85 -> 0.20328728
B12: 5 | C12: ='Effective coverage'!J86 -> 0 | G12: 5 | H12: ='Effective coverage'!I86 -> 0.061330624
B13: 6 | C13: ='Effective coverage'!J87 -> 0 | G13: 6 | H13: ='Effective coverage'!I87 -> 0.010221616
B15: Expanded net decay function, DRC | G15: Expanded net decay function, other countries
B16: Months after distribution | C16: Projected effective coverage years | D16: Average coverage years per year based on cumulative interval | E16: Effective coverage years remaining at the end of the month | G16: Months after distribution | H16: Projected effective coverage years | I16: Average coverage years per year based on cumulative interval | J16: Effective coverage years remaining at the end of the month
B17: 0 | C17: =C7 -> 1 | D17: =AVERAGE(C$17:C17) -> 1 | E17: =SUM(C18:C89)/12 -> 1.8103116 | G17: 0 | H17: =H7 -> 1 | I17: =AVERAGE(H$17:H17) -> 1 | J17: =SUM(H18:H89)/12 -> 2.3637745
B18: 1 | C18: =C17-((C17-C20)/3) -> 0.96810826 | D18: =AVERAGE(C$17:C18) -> 0.98405413 | E18: =SUM(C19:C90)/12 -> 1.7296359 | G18: 1 | H18: =H17-((H17-H20)/3) -> 0.98588257 | I18: =AVERAGE(H$17:H18) -> 0.99294128 | J18: =SUM(H19:H90)/12 -> 2.2816176
B19: 2 | C19: =C18-((C17-C20)/3) -> 0.93621653 | D19: =AVERAGE(C$17:C19) -> 0.96810826 | E19: =SUM(C20:C91)/12 -> 1.6516179 | G19: 2 | H19: =H18-((H17-H20)/3) -> 0.97176514 | I19: =AVERAGE(H$17:H19) -> 0.98588257 | J19: =SUM(H20:H91)/12 -> 2.2006372
B20: 3 | C20: =average(C17,C23) -> 0.90432479 | D20: =AVERAGE(C$17:C20) -> 0.9521624 | E20: =SUM(C21:C92)/12 -> 1.5762575 | G20: 3 | H20: =average(H17,H23) -> 0.9576477 | I20: =AVERAGE(H$17:H20) -> 0.97882385 | J20: =SUM(H21:H92)/12 -> 2.1208332
B21: 4 | C21: =C20-((C20-C23)/3) -> 0.87243305 | D21: =AVERAGE(C$17:C21) -> 0.93621653 | E21: =SUM(C22:C93)/12 -> 1.5035547 | G21: 4 | H21: =H20-((H20-H23)/3) -> 0.94353027 | I21: =AVERAGE(H$17:H21) -> 0.97176514 | J21: =SUM(H22:H93)/12 -> 2.0422057
B22: 5 | C22: =C21-((C20-C23)/3) -> 0.84054132 | D22: =AVERAGE(C$17:C22) -> 0.92027066 | E22: =SUM(C23:C94)/12 -> 1.4335096 | G22: 5 | H22: =H21-((H20-H23)/3) -> 0.92941284 | I22: =AVERAGE(H$17:H22) -> 0.96470642 | J22: =SUM(H23:H94)/12 -> 1.9647547
B23: 6 | C23: =C8 -> 0.80864958 | D23: =AVERAGE(C$17:C23) -> 0.90432479 | E23: =SUM(C24:C95)/12 -> 1.3661221 | G23: 6 | H23: =H8 -> 0.91529541 | I23: =AVERAGE(H$17:H23) -> 0.9576477 | J23: =SUM(H24:H95)/12 -> 1.88848
B24: 7 | C24: =C23-((C23-C26)/3) -> 0.79130042 | D24: =AVERAGE(C$17:C24) -> 0.89019674 | E24: =SUM(C25:C96)/12 -> 1.3001804 | G24: 7 | H24: =H23-((H23-H26)/3) -> 0.89865931 | I24: =AVERAGE(H$17:H24) -> 0.95027416 | J24: =SUM(H25:H96)/12 -> 1.8135918
B25: 8 | C25: =C24-((C23-C26)/3) -> 0.77395125 | D25: =AVERAGE(C$17:C25) -> 0.87728058 | E25: =SUM(C26:C97)/12 -> 1.2356845 | G25: 8 | H25: =H24-((H23-H26)/3) -> 0.88202322 | I25: =AVERAGE(H$17:H25) -> 0.94269072 | J25: =SUM(H26:H97)/12 -> 1.7400898
B26: 9 | C26: =average(C23,C29) -> 0.75660209 | D26: =AVERAGE(C$17:C26) -> 0.86521273 | E26: =SUM(C27:C98)/12 -> 1.1726343 | G26: 9 | H26: =average(H23,H29) -> 0.86538713 | I26: =AVERAGE(H$17:H26) -> 0.93496036 | J26: =SUM(H27:H98)/12 -> 1.6679742
B27: 10 | C27: =C26-((C26-C29)/3) -> 0.73925293 | D27: =AVERAGE(C$17:C27) -> 0.85376184 | E27: =SUM(C28:C99)/12 -> 1.1110299 | G27: 10 | H27: =H26-((H26-H29)/3) -> 0.84875103 | I27: =AVERAGE(H$17:H27) -> 0.92712315 | J27: =SUM(H28:H99)/12 -> 1.597245
B28: 11 | C28: =C27-((C26-C29)/3) -> 0.72190376 | D28: =AVERAGE(C$17:C28) -> 0.84277366 | E28: =SUM(C29:C100)/12 -> 1.0508713 | G28: 11 | H28: =H27-((H26-H29)/3) -> 0.83211494 | I28: =AVERAGE(H$17:H28) -> 0.9192058 | J28: =SUM(H29:H100)/12 -> 1.5279021
B29: 12 | C29: =average(C23,C35) -> 0.7045546 | D29: =AVERAGE(C$17:C29) -> 0.83214143 | E29: =SUM(C30:C101)/12 -> 0.99215839 | G29: 12 | H29: =average(H23,H35) -> 0.81547884 | I29: =AVERAGE(H$17:H29) -> 0.9112268 | J29: =SUM(H30:H101)/12 -> 1.4599455
B30: 13 | C30: =C29-((C29-C32)/3) -> 0.68720543 | D30: =AVERAGE(C$17:C30) -> 0.82178886 | E30: =SUM(C31:C102)/12 -> 0.93489127 | G30: 13 | H30: =H29-((H29-H32)/3) -> 0.79884275 | I30: =AVERAGE(H$17:H30) -> 0.90319937 | J30: =SUM(H31:H102)/12 -> 1.3933753
B31: 14 | C31: =C30-((C29-C32)/3) -> 0.66985627 | D31: =AVERAGE(C$17:C31) -> 0.81166002 | E31: =SUM(C32:C103)/12 -> 0.87906992 | G31: 14 | H31: =H30-((H29-H32)/3) -> 0.78220665 | I31: =AVERAGE(H$17:H31) -> 0.89513319 | J31: =SUM(H32:H103)/12 -> 1.3281914
B32: 15 | C32: =average(C29,C35) -> 0.65250711 | D32: =AVERAGE(C$17:C32) -> 0.80171296 | E32: =SUM(C33:C104)/12 -> 0.82469432 | G32: 15 | H32: =average(H29,H35) -> 0.76557056 | I32: =AVERAGE(H$17:H32) -> 0.88703552 | J32: =SUM(H33:H104)/12 -> 1.2643938
B33: 16 | C33: =C32-((C32-C35)/3) -> 0.63515794 | D33: =AVERAGE(C$17:C33) -> 0.79191561 | E33: =SUM(C34:C105)/12 -> 0.7717645 | G33: 16 | H33: =H32-((H32-H35)/3) -> 0.74893446 | I33: =AVERAGE(H$17:H33) -> 0.87891193 | J33: =SUM(H34:H105)/12 -> 1.2019826
B34: 17 | C34: =C33-((C32-C35)/3) -> 0.61780878 | D34: =AVERAGE(C$17:C34) -> 0.78224301 | E34: =SUM(C35:C106)/12 -> 0.72028043 | G34: 17 | H34: =H33-((H32-H35)/3) -> 0.73229837 | I34: =AVERAGE(H$17:H34) -> 0.87076673 | J34: =SUM(H35:H106)/12 -> 1.1409578
B35: 18 | C35: =C9 -> 0.60045961 | D35: =AVERAGE(C$17:C35) -> 0.77267546 | E35: =SUM(C36:C107)/12 -> 0.67024213 | G35: 18 | H35: =H9 -> 0.71566228 | I35: =AVERAGE(H$17:H35) -> 0.86260334 | J35: =SUM(H36:H107)/12 -> 1.0813192
B36: 19 | C36: =C35-((C35-C38)/3) -> 0.57749252 | D36: =AVERAGE(C$17:C36) -> 0.76291631 | E36: =SUM(C37:C108)/12 -> 0.62211775 | G36: 19 | H36: =H35-((H35-H38)/3) -> 0.69610902 | I36: =AVERAGE(H$17:H36) -> 0.85427862 | J36: =SUM(H37:H108)/12 -> 1.0233102
B37: 20 | C37: =C36-((C35-C38)/3) -> 0.55452543 | D37: =AVERAGE(C$17:C37) -> 0.75299294 | E37: =SUM(C38:C109)/12 -> 0.5759073 | G37: 20 | H37: =H36-((H35-H38)/3) -> 0.67655577 | I37: =AVERAGE(H$17:H37) -> 0.84581563 | J37: =SUM(H38:H109)/12 -> 0.96693051
B38: 21 | C38: =average(C35,C41) -> 0.53155834 | D38: =AVERAGE(C$17:C38) -> 0.74292773 | E38: =SUM(C39:C110)/12 -> 0.53161077 | G38: 21 | H38: =average(H35,H41) -> 0.65700252 | I38: =AVERAGE(H$17:H38) -> 0.83723322 | J38: =SUM(H39:H110)/12 -> 0.9121803
B39: 22 | C39: =C38-((C38-C41)/3) -> 0.50859125 | D39: =AVERAGE(C$17:C39) -> 0.73273919 | E39: =SUM(C40:C111)/12 -> 0.48922817 | G39: 22 | H39: =H38-((H38-H41)/3) -> 0.63744927 | I39: =AVERAGE(H$17:H39) -> 0.82854696 | J39: =SUM(H40:H111)/12 -> 0.85905952
B40: 23 | C40: =C39-((C38-C41)/3) -> 0.48562416 | D40: =AVERAGE(C$17:C40) -> 0.72244273 | E40: =SUM(C41:C112)/12 -> 0.44875949 | G40: 23 | H40: =H39-((H38-H41)/3) -> 0.61789602 | I40: =AVERAGE(H$17:H40) -> 0.81976984 | J40: =SUM(H41:H112)/12 -> 0.80756819
B41: 24 | C41: =average(C35,C47) -> 0.46265707 | D41: =AVERAGE(C$17:C41) -> 0.7120513 | E41: =SUM(C42:C113)/12 -> 0.41020473 | G41: 24 | H41: =average(H35,H47) -> 0.59834276 | I41: =AVERAGE(H$17:H41) -> 0.81091275 | J41: =SUM(H42:H113)/12 -> 0.75770629
B42: 25 | C42: =C41-((C41-C44)/3) -> 0.43968998 | D42: =AVERAGE(C$17:C42) -> 0.70157587 | E42: =SUM(C43:C114)/12 -> 0.3735639 | G42: 25 | H42: =H41-((H41-H44)/3) -> 0.57878951 | I42: =AVERAGE(H$17:H42) -> 0.80198494 | J42: =SUM(H43:H114)/12 -> 0.70947383
B43: 26 | C43: =C42-((C41-C44)/3) -> 0.41672289 | D43: =AVERAGE(C$17:C43) -> 0.69102576 | E43: =SUM(C44:C115)/12 -> 0.33883699 | G43: 26 | H43: =H42-((H41-H44)/3) -> 0.55923626 | I43: =AVERAGE(H$17:H43) -> 0.79299424 | J43: =SUM(H44:H115)/12 -> 0.66287081
B44: 27 | C44: =average(C41,C47) -> 0.3937558 | D44: =AVERAGE(C$17:C44) -> 0.68040897 | E44: =SUM(C45:C116)/12 -> 0.30602401 | G44: 27 | H44: =average(H41,H47) -> 0.53968301 | I44: =AVERAGE(H$17:H44) -> 0.78394741 | J44: =SUM(H45:H116)/12 -> 0.61789723
B45: 28 | C45: =C44-((C44-C47)/3) -> 0.37078871 | D45: =AVERAGE(C$17:C45) -> 0.66973241 | E45: =SUM(C46:C117)/12 -> 0.27512495 | G45: 28 | H45: =H44-((H44-H47)/3) -> 0.52012976 | I45: =AVERAGE(H$17:H45) -> 0.77485025 | J45: =SUM(H46:H117)/12 -> 0.57455308
B46: 29 | C46: =C45-((C44-C47)/3) -> 0.34782162 | D46: =AVERAGE(C$17:C46) -> 0.65900205 | E46: =SUM(C47:C118)/12 -> 0.24613981 | G46: 29 | H46: =H45-((H44-H47)/3) -> 0.5005765 | I46: =AVERAGE(H$17:H46) -> 0.7657078 | J46: =SUM(H47:H118)/12 -> 0.53283837
B47: 30 | C47: =C10 -> 0.32485453 | D47: =AVERAGE(C$17:C47) -> 0.6482231 | E47: =SUM(C48:C119)/12 -> 0.2190686 | G47: 30 | H47: =H10 -> 0.48102325 | I47: =AVERAGE(H$17:H47) -> 0.75652442 | J47: =SUM(H48:H119)/12 -> 0.4927531
B48: 31 | C48: =C47-((C47-C50)/3) -> 0.3036314 | D48: =AVERAGE(C$17:C48) -> 0.63745461 | E48: =SUM(C49:C120)/12 -> 0.19376599 | G48: 31 | H48: =H47-((H47-H50)/3) -> 0.45787859 | I48: =AVERAGE(H$17:H48) -> 0.74719174 | J48: =SUM(H49:H120)/12 -> 0.45459655
B49: 32 | C49: =C48-((C47-C50)/3) -> 0.28240827 | D49: =AVERAGE(C$17:C49) -> 0.62669563 | E49: =SUM(C50:C121)/12 -> 0.17023196 | G49: 32 | H49: =H48-((H47-H50)/3) -> 0.43473392 | I49: =AVERAGE(H$17:H49) -> 0.73772332 | J49: =SUM(H50:H121)/12 -> 0.41836873
B50: 33 | C50: =average(C47,C53) -> 0.26118513 | D50: =AVERAGE(C$17:C50) -> 0.61594532 | E50: =SUM(C51:C122)/12 -> 0.14846654 | G50: 33 | H50: =average(H47,H53) -> 0.41158926 | I50: =AVERAGE(H$17:H50) -> 0.72813114 | J50: =SUM(H51:H122)/12 -> 0.38406962
B51: 34 | C51: =C50-((C50-C53)/3) -> 0.239962 | D51: =AVERAGE(C$17:C51) -> 0.60520294 | E51: =SUM(C52:C123)/12 -> 0.1284697 | G51: 34 | H51: =H50-((H50-H53)/3) -> 0.38844459 | I51: =AVERAGE(H$17:H51) -> 0.71842581 | J51: =SUM(H52:H123)/12 -> 0.35169924
B52: 35 | C52: =C51-((C50-C53)/3) -> 0.21873887 | D52: =AVERAGE(C$17:C52) -> 0.59446783 | E52: =SUM(C53:C124)/12 -> 0.11024146 | G52: 35 | H52: =H51-((H50-H53)/3) -> 0.36529993 | I52: =AVERAGE(H$17:H52) -> 0.70861676 | J52: =SUM(H53:H124)/12 -> 0.32125758
B53: 36 | C53: =average(C47,C59) -> 0.19751574 | D53: =AVERAGE(C$17:C53) -> 0.58373939 | E53: =SUM(C54:C125)/12 -> 0.093781818 | G53: 36 | H53: =average(H47,H59) -> 0.34215526 | I53: =AVERAGE(H$17:H53) -> 0.6987124 | J53: =SUM(H54:H125)/12 -> 0.29274464
B54: 37 | C54: =C53-((C53-C56)/3) -> 0.1762926 | D54: =AVERAGE(C$17:C54) -> 0.57301711 | E54: =SUM(C55:C126)/12 -> 0.079090768 | G54: 37 | H54: =H53-((H53-H56)/3) -> 0.3190106 | I54: =AVERAGE(H$17:H54) -> 0.68872024 | J54: =SUM(H55:H126)/12 -> 0.26616042
B55: 38 | C55: =C54-((C53-C56)/3) -> 0.15506947 | D55: =AVERAGE(C$17:C55) -> 0.5623005 | E55: =SUM(C56:C127)/12 -> 0.066168312 | G55: 38 | H55: =H54-((H53-H56)/3) -> 0.29586593 | I55: =AVERAGE(H$17:H55) -> 0.67864706 | J55: =SUM(H56:H127)/12 -> 0.24150493
B56: 39 | C56: =average(C53,C59) -> 0.13384634 | D56: =AVERAGE(C$17:C56) -> 0.55158915 | E56: =SUM(C57:C128)/12 -> 0.05501445 | G56: 39 | H56: =average(H53,H59) -> 0.27272127 | I56: =AVERAGE(H$17:H56) -> 0.66849891 | J56: =SUM(H57:H128)/12 -> 0.21877816
B57: 40 | C57: =C56-((C56-C59)/3) -> 0.11262321 | D57: =AVERAGE(C$17:C57) -> 0.54088266 | E57: =SUM(C58:C129)/12 -> 0.045629183 | G57: 40 | H57: =H56-((H56-H59)/3) -> 0.2495766 | I57: =AVERAGE(H$17:H57) -> 0.65828129 | J57: =SUM(H58:H129)/12 -> 0.1979801
B58: 41 | C58: =C57-((C56-C59)/3) -> 0.091400074 | D58: =AVERAGE(C$17:C58) -> 0.53018069 | E58: =SUM(C59:C130)/12 -> 0.03801251 | G58: 41 | H58: =H57-((H56-H59)/3) -> 0.22643194 | I58: =AVERAGE(H$17:H58) -> 0.64799917 | J58: =SUM(H59:H130)/12 -> 0.17911078
B59: 42 | C59: =C11 -> 0.070176942 | D59: =AVERAGE(C$17:C59) -> 0.51948293 | E59: =SUM(C60:C131)/12 -> 0.032164432 | G59: 42 | H59: =H11 -> 0.20328728 | I59: =AVERAGE(H$17:H59) -> 0.63765703 | J59: =SUM(H60:H131)/12 -> 0.16217017
B60: 43 | C60: =C59-((C59-C62)/3) -> 0.064328863 | D60: =AVERAGE(C$17:C60) -> 0.50913852 | E60: =SUM(C61:C132)/12 -> 0.026803693 | G60: 43 | H60: =H59-((H59-H62)/3) -> 0.19145755 | I60: =AVERAGE(H$17:H60) -> 0.62751613 | J60: =SUM(H61:H132)/12 -> 0.14621537
B61: 44 | C61: =C60-((C59-C62)/3) -> 0.058480785 | D61: =AVERAGE(C$17:C61) -> 0.49912391 | E61: =SUM(C62:C133)/12 -> 0.021930294 | G61: 44 | H61: =H60-((H59-H62)/3) -> 0.17962783 | I61: =AVERAGE(H$17:H61) -> 0.61756306 | J61: =SUM(H62:H133)/12 -> 0.13124639
B62: 45 | C62: =average(C59,C65) -> 0.052632706 | D62: =AVERAGE(C$17:C62) -> 0.48941758 | E62: =SUM(C63:C134)/12 -> 0.017544235 | G62: 45 | H62: =average(H59,H65) -> 0.16779811 | I62: =AVERAGE(H$17:H62) -> 0.60778556 | J62: =SUM(H63:H134)/12 -> 0.11726321
B63: 46 | C63: =C62-((C62-C65)/3) -> 0.046784628 | D63: =AVERAGE(C$17:C63) -> 0.47999985 | E63: =SUM(C64:C135)/12 -> 0.013645516 | G63: 46 | H63: =H62-((H62-H65)/3) -> 0.15596839 | I63: =AVERAGE(H$17:H63) -> 0.59817243 | J63: =SUM(H64:H135)/12 -> 0.10426585
B64: 47 | C64: =C63-((C62-C65)/3) -> 0.040936549 | D64: =AVERAGE(C$17:C64) -> 0.4708527 | E64: =SUM(C65:C136)/12 -> 0.010234137 | G64: 47 | H64: =H63-((H62-H65)/3) -> 0.14413867 | I64: =AVERAGE(H$17:H64) -> 0.58871339 | J64: =SUM(H65:H136)/12 -> 0.09225429
B65: 48 | C65: =average(C59,C71) -> 0.035088471 | D65: =AVERAGE(C$17:C65) -> 0.46195955 | E65: =SUM(C66:C137)/12 -> 0.0073100981 | G65: 48 | H65: =average(H59,H71) -> 0.13230895 | I65: =AVERAGE(H$17:H65) -> 0.57939902 | J65: =SUM(H66:H137)/12 -> 0.081228544
B66: 49 | C66: =C65-((C65-C68)/3) -> 0.029240392 | D66: =AVERAGE(C$17:C66) -> 0.45330517 | E66: =SUM(C67:C138)/12 -> 0.0048733987 | G66: 49 | H66: =H65-((H65-H68)/3) -> 0.12047923 | I66: =AVERAGE(H$17:H66) -> 0.57022062 | J66: =SUM(H67:H138)/12 -> 0.071188608
B67: 50 | C67: =C66-((C65-C68)/3) -> 0.023392314 | D67: =AVERAGE(C$17:C67) -> 0.44487551 | E67: =SUM(C68:C139)/12 -> 0.0029240392 | G67: 50 | H67: =H66-((H65-H68)/3) -> 0.10864951 | I67: =AVERAGE(H$17:H67) -> 0.56117021 | J67: =SUM(H68:H139)/12 -> 0.062134483
B68: 51 | C68: =average(C65,C71) -> 0.017544235 | D68: =AVERAGE(C$17:C68) -> 0.4366576 | E68: =SUM(C69:C140)/12 -> 0.0014620196 | G68: 51 | H68: =average(H65,H71) -> 0.096819787 | I68: =AVERAGE(H$17:H68) -> 0.55224039 | J68: =SUM(H69:H140)/12 -> 0.054066167
B69: 52 | C69: =C68-((C68-C71)/3) -> 0.011696157 | D69: =AVERAGE(C$17:C69) -> 0.42863946 | E69: =SUM(C70:C141)/12 -> 0.00048733987 | G69: 52 | H69: =H68-((H68-H71)/3) -> 0.084990066 | I69: =AVERAGE(H$17:H69) -> 0.54342435 | J69: =SUM(H70:H141)/12 -> 0.046983662
B70: 53 | C70: =C69-((C68-C71)/3) -> 0.0058480785 | D70: =AVERAGE(C$17:C70) -> 0.42080999 | E70: =SUM(C71:C142)/12 -> 0 | G70: 53 | H70: =H69-((H68-H71)/3) -> 0.073160345 | I70: =AVERAGE(H$17:H70) -> 0.53471575 | J70: =SUM(H71:H142)/12 -> 0.040886966
B71: 54 | C71: =C12 -> 0 | D71: =AVERAGE(C$17:C71) -> 0.4131589 | E71: =SUM(C72:C143)/12 -> 0 | G71: 54 | H71: =H12 -> 0.061330624 | I71: =AVERAGE(H$17:H71) -> 0.52610875 | J71: =SUM(H72:H143)/12 -> 0.035776081
B72: 55 | C72: =C71-((C71-C74)/3) -> 0 | D72: =AVERAGE(C$17:C72) -> 0.40578106 | E72: =SUM(C73:C144)/12 -> 0 | G72: 55 | H72: =H71-((H71-H74)/3) -> 0.05707154 | I72: =AVERAGE(H$17:H72) -> 0.51773309 | J72: =SUM(H73:H144)/12 -> 0.031020119
B73: 56 | C73: =C72-((C71-C74)/3) -> 0 | D73: =AVERAGE(C$17:C73) -> 0.39866209 | E73: =SUM(C74:C145)/12 -> 0 | G73: 56 | H73: =H72-((H71-H74)/3) -> 0.052812456 | I73: =AVERAGE(H$17:H73) -> 0.50957659 | J73: =SUM(H74:H145)/12 -> 0.026619081
B74: 57 | C74: =average(C71,C77) -> 0 | D74: =AVERAGE(C$17:C74) -> 0.39178861 | E74: =SUM(C75:C146)/12 -> 0 | G74: 57 | H74: =average(H71,H77) -> 0.048553372 | I74: =AVERAGE(H$17:H74) -> 0.50162791 | J74: =SUM(H75:H146)/12 -> 0.022572967
B75: 58 | C75: =C74-((C74-C77)/3) -> 0 | D75: =AVERAGE(C$17:C75) -> 0.38514812 | E75: =SUM(C76:C147)/12 -> 0 | G75: 58 | H75: =H74-((H74-H77)/3) -> 0.044294288 | I75: =AVERAGE(H$17:H75) -> 0.49387649 | J75: =SUM(H76:H147)/12 -> 0.018881776
B76: 59 | C76: =C75-((C74-C77)/3) -> 0 | D76: =AVERAGE(C$17:C76) -> 0.37872899 | E76: =SUM(C77:C148)/12 -> 0 | G76: 59 | H76: =H75-((H74-H77)/3) -> 0.040035204 | I76: =AVERAGE(H$17:H76) -> 0.48631247 | J76: =SUM(H77:H148)/12 -> 0.015545509
B77: 60 | C77: =average(C71,C83) -> 0 | D77: =AVERAGE(C$17:C77) -> 0.37252032 | E77: =SUM(C78:C149)/12 -> 0 | G77: 60 | H77: =average(H71,H83) -> 0.03577612 | I77: =AVERAGE(H$17:H77) -> 0.47892663 | J77: =SUM(H78:H149)/12 -> 0.012564166
B78: 61 | C78: =C77-((C77-C80)/3) -> 0 | D78: =AVERAGE(C$17:C78) -> 0.36651192 | E78: =SUM(C79:C150)/12 -> 0 | G78: 61 | H78: =H77-((H77-H80)/3) -> 0.031517036 | I78: =AVERAGE(H$17:H78) -> 0.47171034 | J78: =SUM(H79:H150)/12 -> 0.0099377464
B79: 62 | C79: =C78-((C77-C80)/3) -> 0 | D79: =AVERAGE(C$17:C79) -> 0.36069427 | E79: =SUM(C80:C151)/12 -> 0 | G79: 62 | H79: =H78-((H77-H80)/3) -> 0.027257952 | I79: =AVERAGE(H$17:H79) -> 0.46465554 | J79: =SUM(H80:H151)/12 -> 0.0076662505
B80: 63 | C80: =average(C77,C83) -> 0 | D80: =AVERAGE(C$17:C80) -> 0.35505843 | E80: =SUM(C81:C152)/12 -> 0 | G80: 63 | H80: =average(H77,H83) -> 0.022998868 | I80: =AVERAGE(H$17:H80) -> 0.45775466 | J80: =SUM(H81:H152)/12 -> 0.0057496782
B81: 64 | C81: =C80-((C80-C83)/3) -> 0 | D81: =AVERAGE(C$17:C81) -> 0.34959599 | E81: =SUM(C82:C153)/12 -> 0 | G81: 64 | H81: =H80-((H80-H83)/3) -> 0.018739784 | I81: =AVERAGE(H$17:H81) -> 0.45100058 | J81: =SUM(H82:H153)/12 -> 0.0041880295
B82: 65 | C82: =C81-((C80-C83)/3) -> 0 | D82: =AVERAGE(C$17:C82) -> 0.34429908 | E82: =SUM(C83:C154)/12 -> 0 | G82: 65 | H82: =H81-((H80-H83)/3) -> 0.0144807 | I82: =AVERAGE(H$17:H82) -> 0.44438665 | J82: =SUM(H83:H154)/12 -> 0.0029813046
B83: 66 | C83: =C13 -> 0 | D83: =AVERAGE(C$17:C83) -> 0.33916029 | E83: =SUM(C84:C155)/12 -> 0 | G83: 66 | H83: =H13 -> 0.010221616 | I83: =AVERAGE(H$17:H83) -> 0.43790657 | J83: =SUM(H84:H155)/12 -> 0.0021295033
B84: 67 | C84: =C83-((C83-C86)/3) -> 0 | D84: =AVERAGE(C$17:C84) -> 0.33417264 | E84: =SUM(C85:C156)/12 -> 0 | G84: 67 | H84: =H83-((H83-H86)/3) -> 0.008518013 | I84: =AVERAGE(H$17:H84) -> 0.43159203 | J84: =SUM(H85:H156)/12 -> 0.0014196688
B85: 68 | C85: =C84-((C83-C86)/3) -> 0 | D85: =AVERAGE(C$17:C85) -> 0.32932955 | E85: =SUM(C86:C157)/12 -> 0 | G85: 68 | H85: =H84-((H83-H86)/3) -> 0.0068144104 | I85: =AVERAGE(H$17:H85) -> 0.42543584 | J85: =SUM(H86:H157)/12 -> 0.0008518013
B86: 69 | C86: =average(C83,C89) -> 0 | D86: =AVERAGE(C$17:C86) -> 0.32462485 | E86: =SUM(C87:C158)/12 -> 0 | G86: 69 | H86: =average(H83,H89) -> 0.0051108078 | I86: =AVERAGE(H$17:H86) -> 0.41943119 | J86: =SUM(H87:H158)/12 -> 0.00042590065
B87: 70 | C87: =C86-((C86-C89)/3) -> 0 | D87: =AVERAGE(C$17:C87) -> 0.32005267 | E87: =SUM(C88:C159)/12 -> 0 | G87: 70 | H87: =H86-((H86-H89)/3) -> 0.0034072052 | I87: =AVERAGE(H$17:H87) -> 0.4135717 | J87: =SUM(H88:H159)/12 -> 0.00014196688
B88: 71 | C88: =C87-((C86-C89)/3) -> 0 | D88: =AVERAGE(C$17:C88) -> 0.31560749 | E88: =SUM(C89:C160)/12 -> 0 | G88: 71 | H88: =H87-((H86-H89)/3) -> 0.0017036026 | I88: =AVERAGE(H$17:H88) -> 0.40785131 | J88: =SUM(H89:H160)/12 -> 0
B89: 72 | C89: 0 | D89: =AVERAGE(C$17:C89) -> 0.3112841 | E89: =SUM(C90:C161)/12 -> 0 | G89: 72 | H89: 0 | I89: =AVERAGE(H$17:H89) -> 0.40226431 | J89: =SUM(H90:H161)/12 -> 0

Sheet GBD estimates
B2: Global Burden of Disease Study 2019 (GBD 2019) Population Estimates 1950-2019 | L2: Global Burden of Disease Study 2019 (GBD 2019) Population Estimates 1950-2019 | V2: GBD 2019 Results Tool: All-cause mortalities among 1-59-month-olds (2004) | AG2: GBD 2019 Results Tool: All-cause mortality rates among 1-59-month-olds (2019) | AR2: GBD 2019 Results Tool: Malaria mortality rates among 1-59-month-olds (2019) | BC2: GBD 2019 Results Tool: Malaria mortalities (2019) | BN2: GBD 2019 Results Tool: Malaria incidence (2019) | BY2: GBD 2019 Results Tool: All-cause mortalities (2019)
B3: Location | C3: Sex | D3: Age group | E3: Year | F3: Measure | G3: Metric | H3: val | I3: upper | J3: lower | L3: Location | M3: Sex | N3: Age group | O3: Year | P3: Measure | Q3: Metric | R3: val | S3: upper | T3: lower | V3: measure | W3: location | X3: sex | Y3: age | Z3: cause | AA3: metric | AB3: year | AC3: val | AD3: upper | AE3: lower | AG3: measure | AH3: location | AI3: sex | AJ3: age | AK3: cause | AL3: metric | AM3: year | AN3: val | AO3: upper | AP3: lower | AR3: measure | AS3: location | AT3: sex | AU3: age | AV3: cause | AW3: metric | AX3: year | AY3: val | AZ3: upper | BA3: lower | BC3: measure | BD3: location | BE3: sex | BF3: age | BG3: cause | BH3: metric | BI3: year | BJ3: val | BK3: upper | BL3: lower | BN3: measure | BO3: location | BP3: sex | BQ3: age | BR3: cause | BS3: metric | BT3: year | BU3: val | BV3: upper | BW3: lower | BY3: measure | BZ3: location | CA3: sex | CB3: age | CC3: cause | CD3: metric | CE3: year | CF3: val | CG3: upper | CH3: lower
B4: Angola | C4: both | D4: <1 year | E4: 2019 | F4: Population | G4: Number | H4: 1060897.5 | I4: 1165729.5 | J4: 952349.72 | L4: Angola | M4: both | N4: <1 year | O4: 2004 | P4: Population | Q4: Number | R4: 766655.39 | S4: 872713.23 | T4: 665972.43 | V4: Deaths | W4: Angola | X4: Both | Y4: 28-364 days | Z4: All causes | AA4: Number | AB4: 2004 | AC4: 36076.934 | AD4: 40672.437 | AE4: 31760.134 | AG4: Deaths | AH4: Angola | AI4: Both | AJ4: 28-364 days | AK4: All causes | AL4: Rate | AM4: 2019 | AN4: 1752.7383 | AO4: 2199.8857 | AP4: 1358.6877 | AR4: Deaths | AS4: Angola | AT4: Both | AU4: 28-364 days | AV4: Malaria | AW4: Rate | AX4: 2019 | AY4: 235.89519 | AZ4: 457.74573 | BA4: 95.041576 | BC4: Deaths | BD4: Angola | BE4: Both | BF4: <5 years | BG4: Malaria | BH4: Number | BI4: 2019 | BJ4: 6045.4005 | BK4: 11288.042 | BL4: 2589.0651 | BN4: Incidence | BO4: Angola | BP4: Both | BQ4: <5 years | BR4: Malaria | BS4: Rate | BT4: 2019 | BU4: 51927.107 | BV4: 85961.594 | BW4: 27903.588 | BY4: Deaths | BZ4: Angola | CA4: Both | CB4: <5 years | CC4: All causes | CD4: Number | CE4: 2019 | CF4: 58764.734 | CG4: 70800.184 | CH4: 48125.424
B5: Angola | C5: both | D5: <20 years | E5: 2019 | F5: Population | G5: Number | H5: 17055870 | I5: 18741235 | J5: 15310765 | L5: Angola | M5: both | N5: <20 years | O5: 2004 | P5: Population | Q5: Number | R5: 9833198.8 | S5: 11193507 | T5: 8541829.1 | V5: Deaths | W5: Angola | X5: Both | Y5: 1-4 years | Z5: All causes | AA5: Number | AB5: 2004 | AC5: 46845.383 | AD5: 52471.959 | AE5: 41763.843 | AG5: Deaths | AH5: Angola | AI5: Both | AJ5: 1-4 years | AK5: All causes | AL5: Rate | AM5: 2019 | AN5: 432.20799 | AO5: 516.89315 | AP5: 355.7176 | AR5: Deaths | AS5: Angola | AT5: Both | AU5: 1-4 years | AV5: Malaria | AW5: Rate | AX5: 2019 | AY5: 84.523694 | AZ5: 153.69083 | BA5: 37.670384 | BC5: Deaths | BD5: Angola | BE5: Both | BF5: All ages | BG5: Malaria | BH5: Number | BI5: 2019 | BJ5: 10784.338 | BK5: 21289.657 | BL5: 4631.7152 | BN5: Incidence | BO5: Angola | BP5: Both | BQ5: 5-14 years | BR5: Malaria | BS5: Rate | BT5: 2019 | BU5: 22588.549 | BV5: 38190.598 | BW5: 12574.498 | BY5: Deaths | BZ5: Bangladesh | CA5: Both | CB5: <5 years | CC5: All causes | CD5: Number | CE5: 2019 | CF5: 77869.603 | CG5: 94199.292 | CH5: 63035.082
B6: Angola | C6: both | D6: 0 to 14 | E6: 2019 | F6: Population | G6: Number | H6: 13987336 | I6: 15369486 | J6: 12556194 | L6: Angola | M6: both | N6: 0 to 14 | O6: 2004 | P6: Population | Q6: Number | R6: 8030779.9 | S6: 9141744.6 | T6: 6976117.3 | V6: Deaths | W6: Bangladesh | X6: Both | Y6: 28-364 days | Z6: All causes | AA6: Number | AB6: 2004 | AC6: 58038.965 | AD6: 65209.37 | AE6: 51061.859 | AG6: Deaths | AH6: Bangladesh | AI6: Both | AJ6: 28-364 days | AK6: All causes | AL6: Rate | AM6: 2019 | AN6: 569.38912 | AO6: 756.48411 | AP6: 417.21603 | AR6: Deaths | AS6: Bangladesh | AT6: Both | AU6: 28-364 days | AV6: Malaria | AW6: Rate | AX6: 2019 | AY6: 0.00069002 | AZ6: 0.004182336 | BA6: 1.45e-05 | BC6: Deaths | BD6: Bangladesh | BE6: Both | BF6: <5 years | BG6: Malaria | BH6: Number | BI6: 2019 | BJ6: 0.029200817 | BK6: 0.17530279 | BL6: 0.000621395 | BN6: Incidence | BO6: Bangladesh | BP6: Both | BQ6: <5 years | BR6: Malaria | BS6: Rate | BT6: 2019 | BU6: 1.7680405 | BV6: 7.6663893 | BW6: 0.18354673 | BY6: Deaths | BZ6: Benin | CA6: Both | CB6: <5 years | CC6: All causes | CD6: Number | CE6: 2019 | CF6: 41955.349 | CG6: 51546.334 | CH6: 34315.243
B7: Angola | C7: both | D7: 1 to 4 | E7: 2019 | F7: Population | G7: Number | H7: 4086252.7 | I7: 4490033.3 | J7: 3668159.8 | L7: Angola | M7: both | N7: 1 to 4 | O7: 2004 | P7: Population | Q7: Number | R7: 2580477.8 | S7: 2937456.8 | T7: 2241590 | V7: Deaths | W7: Bangladesh | X7: Both | Y7: 1-4 years | Z7: All causes | AA7: Number | AB7: 2004 | AC7: 51105.417 | AD7: 59733.752 | AE7: 43295.147 | AG7: Deaths | AH7: Bangladesh | AI7: Both | AJ7: 1-4 years | AK7: All causes | AL7: Rate | AM7: 2019 | AN7: 102.61393 | AO7: 123.19716 | AP7: 85.073605 | AR7: Deaths | AS7: Bangladesh | AT7: Both | AU7: 1-4 years | AV7: Malaria | AW7: Rate | AX7: 2019 | AY7: 0.000104614 | AZ7: 0.000653077 | BA7: 2.18e-06 | BC7: Deaths | BD7: Bangladesh | BE7: Both | BF7: All ages | BG7: Malaria | BH7: Number | BI7: 2019 | BJ7: 110.05186 | BK7: 658.22848 | BL7: 2.2528956 | BN7: Incidence | BO7: Bangladesh | BP7: Both | BQ7: 5-14 years | BR7: Malaria | BS7: Rate | BT7: 2019 | BU7: 3.5299014 | BV7: 15.270894 | BW7: 0.36734572 | BY7: Deaths | BZ7: Bhutan | CA7: Both | CB7: <5 years | CC7: All causes | CD7: Number | CE7: 2019 | CF7: 444.58552 | CG7: 602.23694 | CH7: 322.01511
B8: Angola | C8: both | D8: 10 to 14 | E8: 2019 | F8: Population | G8: Number | H8: 3998471.9 | I8: 4393578.5 | J8: 3589360.5 | L8: Angola | M8: both | N8: 10 to 14 | O8: 2004 | P8: Population | Q8: Number | R8: 2078667.7 | S8: 2366227.1 | T8: 1805681.4 | V8: Deaths | W8: Benin | X8: Both | Y8: 28-364 days | Z8: All causes | AA8: Number | AB8: 2004 | AC8: 12755.239 | AD8: 14199.142 | AE8: 11393.322 | AG8: Deaths | AH8: Benin | AI8: Both | AJ8: 28-364 days | AK8: All causes | AL8: Rate | AM8: 2019 | AN8: 2597.2913 | AO8: 3197.683 | AP8: 2122.8281 | AR8: Deaths | AS8: Benin | AT8: Both | AU8: 28-364 days | AV8: Malaria | AW8: Rate | AX8: 2019 | AY8: 598.09385 | AZ8: 1071.698 | BA8: 265.55934 | BC8: Deaths | BD8: Benin | BE8: Both | BF8: <5 years | BG8: Malaria | BH8: Number | BI8: 2019 | BJ8: 7660.5447 | BK8: 13019.322 | BL8: 3490.7064 | BN8: Incidence | BO8: Benin | BP8: Both | BQ8: <5 years | BR8: Malaria | BS8: Rate | BT8: 2019 | BU8: 105373.93 | BV8: 140432.06 | BW8: 71863.113 | BY8: Deaths | BZ8: Botswana | CA8: Both | CB8: <5 years | CC8: All causes | CD8: Number | CE8: 2019 | CF8: 2002.7306 | CG8: 2751.0166 | CH8: 1464.0651
B9: Angola | C9: both | D9: 10 to 19 | E9: 2019 | F9: Population | G9: Number | H9: 7067006.1 | I9: 7765327.9 | J9: 6343931.5 | L9: Angola | M9: both | N9: 10 to 19 | O9: 2004 | P9: Population | Q9: Number | R9: 3881086.7 | S9: 4417989.8 | T9: 3371393.1 | V9: Deaths | W9: Benin | X9: Both | Y9: 1-4 years | Z9: All causes | AA9: Number | AB9: 2004 | AC9: 17284.109 | AD9: 19904.991 | AE9: 14693.277 | AG9: Deaths | AH9: Benin | AI9: Both | AJ9: 1-4 years | AK9: All causes | AL9: Rate | AM9: 2019 | AN9: 863.49327 | AO9: 1058.6693 | AP9: 708.8816 | AR9: Deaths | AS9: Benin | AT9: Both | AU9: 1-4 years | AV9: Malaria | AW9: Rate | AX9: 2019 | AY9: 269.62529 | AZ9: 454.94182 | BA9: 124.94501 | BC9: Deaths | BD9: Benin | BE9: Both | BF9: All ages | BG9: Malaria | BH9: Number | BI9: 2019 | BJ9: 13263.969 | BK9: 24203.424 | BL9: 5733.2203 | BN9: Incidence | BO9: Benin | BP9: Both | BQ9: 5-14 years | BR9: Malaria | BS9: Rate | BT9: 2019 | BU9: 42747.546 | BV9: 78705.929 | BW9: 26041.858 | BY9: Deaths | BZ9: Burkina Faso | CA9: Both | CB9: <5 years | CC9: All causes | CD9: Number | CE9: 2019 | CF9: 98779.14 | CG9: 124689.12 | CH9: 78328.174
B10: Angola | C10: both | D10: 10 to 24 | E10: 2019 | F10: Population | G10: Number | H10: 9628365.6 | I10: 10579787 | J10: 8643220.5 | L10: Angola | M10: both | N10: 10 to 24 | O10: 2004 | P10: Population | Q10: Number | R10: 5350887.5 | S10: 6091120.4 | T10: 4648168.7 | V10: Deaths | W10: Bhutan | X10: Both | Y10: 28-364 days | Z10: All causes | AA10: Number | AB10: 2004 | AC10: 279.08004 | AD10: 334.75702 | AE10: 228.1471 | AG10: Deaths | AH10: Bhutan | AI10: Both | AJ10: 28-364 days | AK10: All causes | AL10: Rate | AM10: 2019 | AN10: 671.13068 | AO10: 908.17565 | AP10: 485.83278 | AR10: Deaths | AS10: Bhutan | AT10: Both | AU10: 28-364 days | AV10: Malaria | AW10: Rate | AX10: 2019 | AY10: 0 | AZ10: 0 | BA10: 0 | BC10: Deaths | BD10: Bhutan | BE10: Both | BF10: <5 years | BG10: Malaria | BH10: Number | BI10: 2019 | BJ10: 0 | BK10: 0 | BL10: 0 | BN10: Incidence | BO10: Bhutan | BP10: Both | BQ10: <5 years | BR10: Malaria | BS10: Rate | BT10: 2019 | BU10: 3.1539587 | BV10: 11.527567 | BW10: 0.43211194 | BY10: Deaths | BZ10: Burundi | CA10: Both | CB10: <5 years | CC10: All causes | CD10: Number | CE10: 2019 | CF10: 29680.591 | CG10: 37386.728 | CH10: 23772.213
B11: Angola | C11: both | D11: 15 to 19 | E11: 2019 | F11: Population | G11: Number | H11: 3068534.1 | I11: 3371749.5 | J11: 2754571.1 | L11: Angola | M11: both | N11: 15 to 19 | O11: 2004 | P11: Population | Q11: Number | R11: 1802419 | S11: 2051762.6 | T11: 1565711.7 | V11: Deaths | W11: Bhutan | X11: Both | Y11: 1-4 years | Z11: All causes | AA11: Number | AB11: 2004 | AC11: 267.42505 | AD11: 315.68674 | AE11: 222.3909 | AG11: Deaths | AH11: Bhutan | AI11: Both | AJ11: 1-4 years | AK11: All causes | AL11: Rate | AM11: 2019 | AN11: 144.40782 | AO11: 191.36394 | AP11: 105.59972 | AR11: Deaths | AS11: Bhutan | AT11: Both | AU11: 1-4 years | AV11: Malaria | AW11: Rate | AX11: 2019 | AY11: 0 | AZ11: 0 | BA11: 0 | BC11: Deaths | BD11: Bhutan | BE11: Both | BF11: All ages | BG11: Malaria | BH11: Number | BI11: 2019 | BJ11: 0 | BK11: 0 | BL11: 0 | BN11: Incidence | BO11: Bhutan | BP11: Both | BQ11: 5-14 years | BR11: Malaria | BS11: Rate | BT11: 2019 | BU11: 6.274249 | BV11: 22.789602 | BW11: 0.86614411 | BY11: Deaths | BZ11: Côte d'Ivoire | CA11: Both | CB11: <5 years | CC11: All causes | CD11: Number | CE11: 2019 | CF11: 64816.604 | CG11: 77050.051 | CH11: 54290.738
B12: Angola | C12: both | D12: 15 to 39 | E12: 2019 | F12: Population | G12: Number | H12: 11203690 | I12: 12311528 | J12: 10057585 | L12: Angola | M12: both | N12: 15 to 39 | O12: 2004 | P12: Population | Q12: Number | R12: 6516668.6 | S12: 7418431.6 | T12: 5660975.2 | V12: Deaths | W12: Botswana | X12: Both | Y12: 28-364 days | Z12: All causes | AA12: Number | AB12: 2004 | AC12: 907.21744 | AD12: 1149.5914 | AE12: 721.98958 | AG12: Deaths | AH12: Botswana | AI12: Both | AJ12: 28-364 days | AK12: All causes | AL12: Rate | AM12: 2019 | AN12: 1063.0882 | AO12: 1482.3008 | AP12: 770.08447 | AR12: Deaths | AS12: Botswana | AT12: Both | AU12: 28-364 days | AV12: Malaria | AW12: Rate | AX12: 2019 | AY12: 1.4165728 | AZ12: 4.0553535 | BA12: 0.22956534 | BC12: Deaths | BD12: Botswana | BE12: Both | BF12: <5 years | BG12: Malaria | BH12: Number | BI12: 2019 | BJ12: 5.6727379 | BK12: 16.261586 | BL12: 1.0105955 | BN12: Incidence | BO12: Botswana | BP12: Both | BQ12: <5 years | BR12: Malaria | BS12: Rate | BT12: 2019 | BU12: 64.229922 | BV12: 111.99958 | BW12: 2.8280297 | BY12: Deaths | BZ12: Cabo Verde | CA12: Both | CB12: <5 years | CC12: All causes | CD12: Number | CE12: 2019 | CF12: 186.66541 | CG12: 252.7093 | CH12: 134.91041
B13: Angola | C13: both | D13: 15-49 years | E13: 2019 | F13: Population | G13: Number | H13: 13529214 | I13: 14866095 | J13: 12144946 | L13: Angola | M13: both | N13: 15-49 years | O13: 2004 | P13: Population | Q13: Number | R13: 7838978.4 | S13: 8923409.7 | T13: 6809504.7 | V13: Deaths | W13: Botswana | X13: Both | Y13: 1-4 years | Z13: All causes | AA13: Number | AB13: 2004 | AC13: 1092.408 | AD13: 1373.0056 | AE13: 870.0637 | AG13: Deaths | AH13: Botswana | AI13: Both | AJ13: 1-4 years | AK13: All causes | AL13: Rate | AM13: 2019 | AN13: 283.69447 | AO13: 385.24497 | AP13: 210.70248 | AR13: Deaths | AS13: Botswana | AT13: Both | AU13: 1-4 years | AV13: Malaria | AW13: Rate | AX13: 2019 | AY13: 2.6588723 | AZ13: 7.7079246 | BA13: 0.46683662 | BC13: Deaths | BD13: Botswana | BE13: Both | BF13: All ages | BG13: Malaria | BH13: Number | BI13: 2019 | BJ13: 14.40944 | BK13: 40.701856 | BL13: 2.5177984 | BN13: Incidence | BO13: Botswana | BP13: Both | BQ13: 5-14 years | BR13: Malaria | BS13: Rate | BT13: 2019 | BU13: 118.71884 | BV13: 200.61398 | BW13: 5.6495112 | BY13: Deaths | BZ13: Cameroon | CA13: Both | CB13: <5 years | CC13: All causes | CD13: Number | CE13: 2019 | CF13: 64035.007 | CG13: 77248.082 | CH13: 52538.238
B14: Angola | C14: both | D14: 20 plus | E14: 2019 | F14: Population | G14: Number | H14: 13082292 | I14: 14375889 | J14: 11744011 | L14: Angola | M14: both | N14: 20 plus | O14: 2004 | P14: Population | Q14: Number | R14: 7397989.5 | S14: 8421707.9 | T14: 6426571.2 | V14: Deaths | W14: Burkina Faso | X14: Both | Y14: 28-364 days | Z14: All causes | AA14: Number | AB14: 2004 | AC14: 30009.897 | AD14: 33259.65 | AE14: 26995.718 | AG14: Deaths | AH14: Burkina Faso | AI14: Both | AJ14: 28-364 days | AK14: All causes | AL14: Rate | AM14: 2019 | AN14: 3755.4625 | AO14: 4762.3606 | AP14: 2976.366 | AR14: Deaths | AS14: Burkina Faso | AT14: Both | AU14: 28-364 days | AV14: Malaria | AW14: Rate | AX14: 2019 | AY14: 630.44304 | AZ14: 1201.2791 | BA14: 246.96086 | BC14: Deaths | BD14: Burkina Faso | BE14: Both | BF14: <5 years | BG14: Malaria | BH14: Number | BI14: 2019 | BJ14: 16395.369 | BK14: 29949.507 | BL14: 6870.1377 | BN14: Incidence | BO14: Burkina Faso | BP14: Both | BQ14: <5 years | BR14: Malaria | BS14: Rate | BT14: 2019 | BU14: 55520.049 | BV14: 86740.005 | BW14: 31636.118 | BY14: Deaths | BZ14: Central African Republic | CA14: Both | CB14: <5 years | CC14: All causes | CD14: Number | CE14: 2019 | CF14: 23959.048 | CG14: 30037.091 | CH14: 19186.661
B15: Angola | C15: both | D15: 20 to 24 | E15: 2019 | F15: Population | G15: Number | H15: 2561359.5 | I15: 2814458.7 | J15: 2299289 | L15: Angola | M15: both | N15: 20 to 24 | O15: 2004 | P15: Population | Q15: Number | R15: 1469800.8 | S15: 1673130.6 | T15: 1276775.5 | V15: Deaths | W15: Burkina Faso | X15: Both | Y15: 1-4 years | Z15: All causes | AA15: Number | AB15: 2004 | AC15: 47781.096 | AD15: 53945.501 | AE15: 41837.328 | AG15: Deaths | AH15: Burkina Faso | AI15: Both | AJ15: 1-4 years | AK15: All causes | AL15: Rate | AM15: 2019 | AN15: 1306.9345 | AO15: 1624.1553 | AP15: 1049.3042 | AR15: Deaths | AS15: Burkina Faso | AT15: Both | AU15: 1-4 years | AV15: Malaria | AW15: Rate | AX15: 2019 | AY15: 334.72615 | AZ15: 602.44886 | BA15: 147.73377 | BC15: Deaths | BD15: Burkina Faso | BE15: Both | BF15: All ages | BG15: Malaria | BH15: Number | BI15: 2019 | BJ15: 26304.747 | BK15: 48308.499 | BL15: 10690.717 | BN15: Incidence | BO15: Burkina Faso | BP15: Both | BQ15: 5-14 years | BR15: Malaria | BS15: Rate | BT15: 2019 | BU15: 24693.609 | BV15: 38635.958 | BW15: 16809.516 | BY15: Deaths | BZ15: Chad | CA15: Both | CB15: <5 years | CC15: All causes | CD15: Number | CE15: 2019 | CF15: 85575.123 | CG15: 104782.31 | CH15: 70380.654
... B54: Bangladesh | C54: both | D54: 1 to 4 | E54: 2019 | F54: Population | G54: Number | H54: 11111674 | I54: 12408919 | J54: 9851614.3 | L54: Bangladesh | M54: both | N54: 1 to 4 | O54: 2004 | P54: Population | Q54: Number | R54: 13598075 | S54: 14694298 | T54: 12447400 | V54: Deaths | W54: India | X54: Both | Y54: 28-364 days | Z54: All causes | AA54: Number | AB54: 2004 | AC54: 470294.14 | AD54: 533134.46 | AE54: 409638.4 | AG54: Deaths | AH54: India | AI54: Both | AJ54: 28-364 days | AK54: All causes | AL54: Rate | AM54: 2019 | AN54: 808.56523 | AO54: 993.2851 | AP54: 668.52966 | AR54: Deaths | AS54: India | AT54: Both | AU54: 28-364 days | AV54: Malaria | AW54: Rate | AX54: 2019 | AY54: 22.026992 | AZ54: 44.153281 | BA54: 9.1393527 | BC54: Deaths | BD54: India | BE54: Both | BF54: <5 years | BG54: Malaria | BH54: Number | BI54: 2019 | BJ54: 9702.4522 | BK54: 20848.618 | BL54: 3905.2386 | BN54: Incidence | BO54: India | BP54: Both | BQ54: <5 years | BR54: Malaria | BS54: Rate | BT54: 2019 | BU54: 390.55225 | BV54: 988.57458 | BW54: 142.1626 | BY54: Deaths | BZ54: Zimbabwe | CA54: Both | CB54: <5 years | CC54: All causes | CD54: Number | CE54: 2019 | CF54: 23565.855 | CG54: 29921.144 | CH54: 18630.768
B55: Bangladesh | C55: both | D55: 10 to 14 | E55: 2019 | F55: Population | G55: Number | H55: 15384844 | I55: 17180965 | J55: 13640208 | L55: Bangladesh | M55: both | N55: 10 to 14 | O55: 2004 | P55: Population | Q55: Number | R55: 15909487 | S55: 17192048 | T55: 14563220 | V55: Deaths | W55: India | X55: Both | Y55: 1-4 years | Z55: All causes | AA55: Number | AB55: 2004 | AC55: 427485.32 | AD55: 552268.14 | AE55: 326407.02 | AG55: Deaths | AH55: India | AI55: Both | AJ55: 1-4 years | AK55: All causes | AL55: Rate | AM55: 2019 | AN55: 119.49017 | AO55: 147.20611 | AP55: 97.820352 | AR55: Deaths | AS55: India | AT55: Both | AU55: 1-4 years | AV55: Malaria | AW55: Rate | AX55: 2019 | AY55: 5.0626141 | AZ55: 11.253511 | BA55: 1.9373849 | BC55: Deaths | BD55: India | BE55: Both | BF55: All ages | BG55: Malaria | BH55: Number | BI55: 2019 | BJ55: 33371.999 | BK55: 85712.188 | BL55: 11843.172 | BN55: Incidence | BO55: India | BP55: Both | BQ55: 5-14 years | BR55: Malaria | BS55: Rate | BT55: 2019 | BU55: 490.38606 | BV55: 1009.685 | BW55: 226.732
B56: Bangladesh | C56: both | D56: 10 to 19 | E56: 2019 | F56: Population | G56: Number | H56: 30703530 | I56: 34288048 | J56: 27221761 | L56: Bangladesh | M56: both | N56: 10 to 19 | O56: 2004 | P56: Population | Q56: Number | R56: 30333760 | S56: 32779149 | T56: 27766905 | V56: Deaths | W56: Kenya | X56: Both | Y56: 28-364 days | Z56: All causes | AA56: Number | AB56: 2004 | AC56: 32320.529 | AD56: 38186.071 | AE56: 27309.667 | AG56: Deaths | AH56: Kenya | AI56: Both | AJ56: 28-364 days | AK56: All causes | AL56: Rate | AM56: 2019 | AN56: 1281.1812 | AO56: 1558.0924 | AP56: 1033.2154 | AR56: Deaths | AS56: Kenya | AT56: Both | AU56: 28-364 days | AV56: Malaria | AW56: Rate | AX56: 2019 | AY56: 185.50058 | AZ56: 357.97506 | BA56: 71.090716 | BC56: Deaths | BD56: Kenya | BE56: Both | BF56: <5 years | BG56: Malaria | BH56: Number | BI56: 2019 | BJ56: 4618.0637 | BK56: 8830.2677 | BL56: 1787.0174 | BN56: Incidence | BO56: Kenya | BP56: Both | BQ56: <5 years | BR56: Malaria | BS56: Rate | BT56: 2019 | BU56: 27339.893 | BV56: 53118.98 | BW56: 9226.1663
B57: Bangladesh | C57: both | D57: 10 to 24 | E57: 2019 | F57: Population | G57: Number | H57: 45315333 | I57: 50605722 | J57: 40176591 | L57: Bangladesh | M57: both | N57: 10 to 24 | O57: 2004 | P57: Population | Q57: Number | R57: 43050968 | S57: 46521568 | T57: 39407978 | V57: Deaths | W57: Kenya | X57: Both | Y57: 1-4 years | Z57: All causes | AA57: Number | AB57: 2004 | AC57: 26406.74 | AD57: 30943.715 | AE57: 22568.648 | AG57: Deaths | AH57: Kenya | AI57: Both | AJ57: 1-4 years | AK57: All causes | AL57: Rate | AM57: 2019 | AN57: 241.62726 | AO57: 291.74329 | AP57: 197.93694 | AR57: Deaths | AS57: Kenya | AT57: Both | AU57: 1-4 years | AV57: Malaria | AW57: Rate | AX57: 2019 | AY57: 39.612831 | AZ57: 73.405521 | BA57: 15.645901 | BC57: Deaths | BD57: Kenya | BE57: Both | BF57: All ages | BG57: Malaria | BH57: Number | BI57: 2019 | BJ57: 8048.9231 | BK57: 16747.534 | BL57: 2812.3716 | BN57: Incidence | BO57: Kenya | BP57: Both | BQ57: 5-14 years | BR57: Malaria | BS57: Rate | BT57: 2019 | BU57: 12152.384 | BV57: 23117.956 | BW57: 5931.3612
B58: Bangladesh | C58: both | D58: 15 to 19 | E58: 2019 | F58: Population | G58: Number | H58: 15318686 | I58: 17107083 | J58: 13581553 | L58: Bangladesh | M58: both | N58: 15 to 19 | O58: 2004 | P58: Population | Q58: Number | R58: 14424273 | S58: 15587101 | T58: 13203685 | V58: Deaths | W58: Lesotho | X58: Both | Y58: 28-364 days | Z58: All causes | AA58: Number | AB58: 2004 | AC58: 2372.2255 | AD58: 2769.5351 | AE58: 2013.4466 | AG58: Deaths | AH58: Lesotho | AI58: Both | AJ58: 28-364 days | AK58: All causes | AL58: Rate | AM58: 2019 | AN58: 2522.9431 | AO58: 3120.8641 | AP58: 1975.3328 | AR58: Deaths | AS58: Lesotho | AT58: Both | AU58: 28-364 days | AV58: Malaria | AW58: Rate | AX58: 2019 | AY58: 0 | AZ58: 0 | BA58: 0 | BC58: Deaths | BD58: Lesotho | BE58: Both | BF58: <5 years | BG58: Malaria | BH58: Number | BI58: 2019 | BJ58: 0 | BK58: 0 | BL58: 0 | BN58: Incidence | BO58: Lesotho | BP58: Both | BQ58: <5 years | BR58: Malaria | BS58: Rate | BT58: 2019 | BU58: 0 | BV58: 0 | BW58: 0
B59: Bangladesh | C59: both | D59: 15 to 39 | E59: 2019 | F59: Population | G59: Number | H59: 67803097 | I59: 75724239 | J59: 60115635 | L59: Bangladesh | M59: both | N59: 15 to 39 | O59: 2004 | P59: Population | Q59: Number | R59: 57334074 | S59: 61957711 | T59: 52481444 | V59: Deaths | W59: Lesotho | X59: Both | Y59: 1-4 years | Z59: All causes | AA59: Number | AB59: 2004 | AC59: 1264.3435 | AD59: 1474.7548 | AE59: 1085.3463 | AG59: Deaths | AH59: Lesotho | AI59: Both | AJ59: 1-4 years | AK59: All causes | AL59: Rate | AM59: 2019 | AN59: 368.87241 | AO59: 449.40307 | AP59: 294.19332 | AR59: Deaths | AS59: Lesotho | AT59: Both | AU59: 1-4 years | AV59: Malaria | AW59: Rate | AX59: 2019 | AY59: 0 | AZ59: 0 | BA59: 0 | BC59: Deaths | BD59: Lesotho | BE59: Both | BF59: All ages | BG59: Malaria | BH59: Number | BI59: 2019 | BJ59: 0 | BK59: 0 | BL59: 0 | BN59: Incidence | BO59: Lesotho | BP59: Both | BQ59: 5-14 years | BR59: Malaria | BS59: Rate | BT59: 2019 | BU59: 0 | BV59: 0 | BW59: 0
B60: Bangladesh | C60: both | D60: 15-49 years | E60: 2019 | F60: Population | G60: Number | H60: 86164879 | I60: 96224293 | J60: 76393813 | L60: Bangladesh | M60: both | N60: 15-49 years | O60: 2004 | P60: Population | Q60: Number | R60: 69536911 | S60: 75142704 | T60: 63652670 | V60: Deaths | W60: Liberia | X60: Both | Y60: 28-364 days | Z60: All causes | AA60: Number | AB60: 2004 | AC60: 5732.2161 | AD60: 6241.5182 | AE60: 5261.8804 | AG60: Deaths | AH60: Liberia | AI60: Both | AJ60: 28-364 days | AK60: All causes | AL60: Rate | AM60: 2019 | AN60: 2131.7657 | AO60: 2888.2927 | AP60: 1574.7186 | AR60: Deaths | AS60: Liberia | AT60: Both | AU60: 28-364 days | AV60: Malaria | AW60: Rate | AX60: 2019 | AY60: 646.90172 | AZ60: 1196.5682 | BA60: 270.64435 | BC60: Deaths | BD60: Liberia | BE60: Both | BF60: <5 years | BG60: Malaria | BH60: Number | BI60: 2019 | BJ60: 1856.906 | BK60: 3311.9397 | BL60: 809.94204 | BN60: Incidence | BO60: Liberia | BP60: Both | BQ60: <5 years | BR60: Malaria | BS60: Rate | BT60: 2019 | BU60: 104895.34 | BV60: 154743.87 | BW60: 41668.672
B61: Bangladesh | C61: both | D61: 20 plus | E61: 2019 | F61: Population | G61: Number | H61: 99889476 | I61: 1.1155913e+08 | J61: 88564086 | L61: Bangladesh | M61: both | N61: 20 plus | O61: 2004 | P61: Population | Q61: Number | R61: 69969298 | S61: 75611888 | T61: 64047250 | V61: Deaths | W61: Liberia | X61: Both | Y61: 1-4 years | Z61: All causes | AA61: Number | AB61: 2004 | AC61: 5629.6817 | AD61: 6458.4736 | AE61: 4863.8993 | AG61: Deaths | AH61: Liberia | AI61: Both | AJ61: 1-4 years | AK61: All causes | AL61: Rate | AM61: 2019 | AN61: 500.936 | AO61: 664.51631 | AP61: 375.81404 | AR61: Deaths | AS61: Liberia | AT61: Both | AU61: 1-4 years | AV61: Malaria | AW61: Rate | AX61: 2019 | AY61: 192.3072 | AZ61: 333.46704 | BA61: 83.429529 | BC61: Deaths | BD61: Liberia | BE61: Both | BF61: All ages | BG61: Malaria | BH61: Number | BI61: 2019 | BJ61: 4586.6646 | BK61: 8175.4235 | BL61: 1943.9763 | BN61: Incidence | BO61: Liberia | BP61: Both | BQ61: 5-14 years | BR61: Malaria | BS61: Rate | BT61: 2019 | BU61: 42035.054 | BV61: 69863.091 | BW61: 22032.812
B62: Bangladesh | C62: both | D62: 20 to 24 | E62: 2019 | F62: Population | G62: Number | H62: 14611803 | I62: 16317674 | J62: 12954830 | L62: Bangladesh | M62: both | N62: 20 to 24 | O62: 2004 | P62: Population | Q62: Number | R62: 12717208 | S62: 13742419 | T62: 11641073 | V62: Deaths | W62: Madagascar | X62: Both | Y62: 28-364 days | Z62: All causes | AA62: Number | AB62: 2004 | AC62: 23382.783 | AD62: 26736.562 | AE62: 20160.512 | AG62: Deaths | AH62: Madagascar | AI62: Both | AJ62: 28-364 days | AK62: All causes | AL62: Rate | AM62: 2019 | AN62: 2041.9807 | AO62: 2506.0103 | AP62: 1652.7819 | AR62: Deaths | AS62: Madagascar | AT62: Both | AU62: 28-364 days | AV62: Malaria | AW62: Rate | AX62: 2019 | AY62: 182.35201 | AZ62: 409.28273 | BA62: 59.972336 | BC62: Deaths | BD62: Madagascar | BE62: Both | BF62: <5 years | BG62: Malaria | BH62: Number | BI62: 2019 | BJ62: 2884.2828 | BK62: 6016.8425 | BL62: 969.35976 | BN62: Incidence | BO62: Madagascar | BP62: Both | BQ62: <5 years | BR62: Malaria | BS62: Rate | BT62: 2019 | BU62: 21227.953 | BV62: 37702.124 | BW62: 8735.0956
B63: Bangladesh | C63: both | D63: 25 plus | E63: 2019 | F63: Population | G63: Number | H63: 85280436 | I63: 95236596 | J63: 75609666 | L63: Bangladesh | M63: both | N63: 25 plus | O63: 2004 | P63: Population | Q63: Number | R63: 57253529 | S63: 61869084 | T63: 52408713 | V63: Deaths | W63: Madagascar | X63: Both | Y63: 1-4 years | Z63: All causes | AA63: Number | AB63: 2004 | AC63: 21933.655 | AD63: 24983.482 | AE63: 19140.27 | AG63: Deaths | AH63: Madagascar | AI63: Both | AJ63: 1-4 years | AK63: All causes | AL63: Rate | AM63: 2019 | AN63: 413.25496 | AO63: 500.99302 | AP63: 342.47052 | AR63: Deaths | AS63: Madagascar | AT63: Both | AU63: 1-4 years | AV63: Malaria | AW63: Rate | AX63: 2019 | AY63: 41.217177 | AZ63: 87.600714 | BA63: 14.074596 | BC63: Deaths | BD63: Madagascar | BE63: Both | BF63: All ages | BG63: Malaria | BH63: Number | BI63: 2019 | BJ63: 5919.7819 | BK63: 13254.54 | BL63: 1914.3136 | BN63: Incidence | BO63: Madagascar | BP63: Both | BQ63: 5-14 years | BR63: Malaria | BS63: Rate | BT63: 2019 | BU63: 10463.392 | BV63: 16650.013 | BW63: 5582.6396
B64: Bangladesh | C64: both | D64: 25 to 29 | E64: 2019 | F64: Population | G64: Number | H64: 13893664 | I64: 15515696 | J64: 12318128 | L64: Bangladesh | M64: both | N64: 25 to 29 | O64: 2004 | P64: Population | Q64: Number | R64: 11677391 | S64: 12618777 | T64: 10689246 | V64: Deaths | W64: Malawi | X64: Both | Y64: 28-364 days | Z64: All causes | AA64: Number | AB64: 2004 | AC64: 21849.389 | AD64: 24181.826 | AE64: 19764.887 | AG64: Deaths | AH64: Malawi | AI64: Both | AJ64: 28-364 days | AK64: All causes | AL64: Rate | AM64: 2019 | AN64: 1778.8067 | AO64: 2283.4058 | AP64: 1390.4942 | AR64: Deaths | AS64: Malawi | AT64: Both | AU64: 28-364 days | AV64: Malaria | AW64: Rate | AX64: 2019 | AY64: 301.59395 | AZ64: 600.15296 | BA64: 122.08023 | BC64: Deaths | BD64: Malawi | BE64: Both | BF64: <5 years | BG64: Malaria | BH64: Number | BI64: 2019 | BJ64: 3990.1387 | BK64: 7557.9531 | BL64: 1720.2136 | BN64: Incidence | BO64: Malawi | BP64: Both | BQ64: <5 years | BR64: Malaria | BS64: Rate | BT64: 2019 | BU64: 50875.334 | BV64: 80225.511 | BW64: 23648.188
B65: Bangladesh | C65: both | D65: 25 to 49 | E65: 2019 | F65: Population | G65: Number | H65: 56232834 | I65: 62802273 | J65: 49857199 | L65: Bangladesh | M65: both | N65: 25 to 49 | O65: 2004 | P65: Population | Q65: Number | R65: 42394558 | S65: 45813416 | T65: 38806376 | V65: Deaths | W65: Malawi | X65: Both | Y65: 1-4 years | Z65: All causes | AA65: Number | AB65: 2004 | AC65: 27853.021 | AD65: 30875.657 | AE65: 25051.477 | AG65: Deaths | AH65: Malawi | AI65: Both | AJ65: 1-4 years | AK65: All causes | AL65: Rate | AM65: 2019 | AN65: 464.42856 | AO65: 588.7167 | AP65: 367.24169 | AR65: Deaths | AS65: Malawi | AT65: Both | AU65: 1-4 years | AV65: Malaria | AW65: Rate | AX65: 2019 | AY65: 111.28084 | AZ65: 201.2688 | BA65: 48.983747 | BC65: Deaths | BD65: Malawi | BE65: Both | BF65: All ages | BG65: Malaria | BH65: Number | BI65: 2019 | BJ65: 7076.3341 | BK65: 14069.774 | BL65: 2898.5224 | BN65: Incidence | BO65: Malawi | BP65: Both | BQ65: 5-14 years | BR65: Malaria | BS65: Rate | BT65: 2019 | BU65: 23059.013 | BV65: 40431.527 | BW65: 13207.835
B66: Bangladesh | C66: both | D66: 30 to 34 | E66: 2019 | F66: Population | G66: Number | H66: 12819236 | I66: 14315832 | J66: 11365539 | L66: Bangladesh | M66: both | N66: 30 to 34 | O66: 2004 | P66: Population | Q66: Number | R66: 10103771 | S66: 10918298 | T66: 9248786.2 | V66: Deaths | W66: Mali | X66: Both | Y66: 28-364 days | Z66: All causes | AA66: Number | AB66: 2004 | AC66: 27809.371 | AD66: 30851.743 | AE66: 24880.893 | AG66: Deaths | AH66: Mali | AI66: Both | AJ66: 28-364 days | AK66: All causes | AL66: Rate | AM66: 2019 | AN66: 3423.6281 | AO66: 4230.2569 | AP66: 2790.3541 | AR66: Deaths | AS66: Mali | AT66: Both | AU66: 28-364 days | AV66: Malaria | AW66: Rate | AX66: 2019 | AY66: 520.01036 | AZ66: 1073.1326 | BA66: 204.85383 | BC66: Deaths | BD66: Mali | BE66: Both | BF66: <5 years | BG66: Malaria | BH66: Number | BI66: 2019 | BJ66: 14107.832 | BK66: 27485.393 | BL66: 5744.8089 | BN66: Incidence | BO66: Mali | BP66: Both | BQ66: <5 years | BR66: Malaria | BS66: Rate | BT66: 2019 | BU66: 39219.94 | BV66: 63752.011 | BW66: 17559.621
... B105: Benin | C105: both | D105: 15 to 19 | E105: 2019 | F105: Population | G105: Number | H105: 1340791.1 | I105: 1480254.3 | J105: 1198000.9 | L105: Benin | M105: both | N105: 15 to 19 | O105: 2004 | P105: Population | Q105: Number | R105: 772395.59 | S105: 834397.55 | T105: 711697.03 | V105: Deaths | W105: Zimbabwe | X105: Both | Y105: 1-4 years | Z105: All causes | AA105: Number | AB105: 2004 | AC105: 9858.1793 | AD105: 11010.19 | AE105: 8872.8517 | AG105: Deaths | AH105: Zimbabwe | AI105: Both | AJ105: 1-4 years | AK105: All causes | AL105: Rate | AM105: 2019 | AN105: 336.05153 | AO105: 420.96017 | AP105: 269.31127 | AR105: Deaths | AS105: Zimbabwe | AT105: Both | AU105: 1-4 years | AV105: Malaria | AW105: Rate | AX105: 2019 | AY105: 49.538143 | AZ105: 128.87682 | BA105: 5.9588273 | BC105: Deaths | BD105: Zimbabwe | BE105: Both | BF105: All ages | BG105: Malaria | BH105: Number | BI105: 2019 | BJ105: 2068.1857 | BK105: 5768.2955 | BL105: 239.03867 | BN105: Incidence | BO105: Zimbabwe | BP105: Both | BQ105: 5-14 years | BR105: Malaria | BS105: Rate | BT105: 2019 | BU105: 3382.5798 | BV105: 13012.384 | BW105: 509.97148
B106: Benin | C106: both | D106: 15 to 39 | E106: 2019 | F106: Population | G106: Number | H106: 4887393.8 | I106: 5395880.9 | J106: 4366734.8 | L106: Benin | M106: both | N106: 15 to 39 | O106: 2004 | P106: Population | Q106: Number | R106: 2855235.2 | S106: 3084444.4 | T106: 2630795.5
B107: Benin | C107: both | D107: 15-49 years | E107: 2019 | F107: Population | G107: Number | H107: 5823842.2 | I107: 6429612.3 | J107: 5203620.5 | L107: Benin | M107: both | N107: 15-49 years | O107: 2004 | P107: Population | Q107: Number | R107: 3367548.5 | S107: 3637869.4 | T107: 3102910.4
B108: Benin | C108: both | D108: 20 plus | E108: 2019 | F108: Population | G108: Number | H108: 5563282.3 | I108: 6142089.2 | J108: 4970620.3 | L108: Benin | M108: both | N108: 20 plus | O108: 2004 | P108: Population | Q108: Number | R108: 3214332.5 | S108: 3472368.9 | T108: 2961665.5
B109: Benin | C109: both | D109: 20 to 24 | E109: 2019 | F109: Population | G109: Number | H109: 1157654.3 | I109: 1278068.3 | J109: 1034367.6 | L109: Benin | M109: both | N109: 20 to 24 | O109: 2004 | P109: Population | Q109: Number | R109: 661115.74 | S109: 714185.02 | T109: 609162.09
B110: Benin | C110: both | D110: 25 plus | E110: 2019 | F110: Population | G110: Number | H110: 4405622.1 | I110: 4863875.3 | J110: 3936436.5 | L110: Benin | M110: both | N110: 25 plus | O110: 2004 | P110: Population | Q110: Number | R110: 2553213 | S110: 2758165.2 | T110: 2352569.2
B111: Benin | C111: both | D111: 25 to 29 | E111: 2019 | F111: Population | G111: Number | H111: 972108.33 | I111: 1073222.7 | J111: 868581.7 | L111: Benin | M111: both | N111: 25 to 29 | O111: 2004 | P111: Population | Q111: Number | R111: 582200.08 | S111: 628934.62 | T111: 536448
B112: Benin | C112: both | D112: 25 to 49 | E112: 2019 | F112: Population | G112: Number | H112: 3325400.3 | I112: 3671376.8 | J112: 2971142.1 | L112: Benin | M112: both | N112: 25 to 49 | O112: 2004 | P112: Population | Q112: Number | R112: 1934039.5 | S112: 2089298 | T112: 1782011.7
B113: Benin | C113: both | D113: 30 to 34 | E113: 2019 | F113: Population | G113: Number | H113: 779117.56 | I113: 860157.9 | J113: 696143.87 | L113: Benin | M113: both | N113: 30 to 34 | O113: 2004 | P113: Population | Q113: Number | R113: 470815.35 | S113: 508608.78 | T113: 433816.42
B114: Benin | C114: both | D114: 35 to 39 | E114: 2019 | F114: Population | G114: Number | H114: 637717.21 | I114: 704049.71 | J114: 569802.24 | L114: Benin | M114: both | N114: 35 to 39 | O114: 2004 | P114: Population | Q114: Number | R114: 368705.01 | S114: 398301.81 | T114: 339730.4
B115: Benin | C115: both | D115: 40 to 44 | E115: 2019 | F115: Population | G115: Number | H115: 524920.51 | I115: 579520.4 | J115: 469018.05 | L115: Benin | M115: both | N115: 40 to 44 | O115: 2004 | P115: Population | Q115: Number | R115: 291514.39 | S115: 314914.91 | T115: 268605.78
B116: Benin | C116: both | D116: 45 to 49 | E116: 2019 | F116: Population | G116: Number | H116: 411533.16 | I116: 454339 | J116: 367706.11 | L116: Benin | M116: both | N116: 45 to 49 | O116: 2004 | P116: Population | Q116: Number | R116: 220802.36 | S116: 238526.67 | T116: 203450.65
B117: Benin | C117: both | D117: 5 to 19 | E117: 2019 | F117: Population | G117: Number | H117: 4874425.4 | I117: 5381563.2 | J117: 4355147.9 | L117: Benin | M117: both | N117: 5 to 19 | O117: 2004 | P117: Population | Q117: Number | R117: 2973048.9 | S117: 3211715.9 | T117: 2739348.3
... B2400: Zimbabwe | C2400: both | D2400: Under 5 | E2400: 2019 | F2400: Population | G2400: Number | H2400: 2109552.7 | I2400: 2340010.2 | J2400: 1871535.6 | L2400: Zimbabwe | M2400: both | N2400: Under 5 | O2400: 2004 | P2400: Population | Q2400: Number | R2400: 1884916.9 | S2400: 2034043.8 | T2400: 1722877.7

Sheet Simple CEA
I1: Against Malaria Foundation
I2: Chad | J2: DRC | K2: Guinea | L2: Nigeria | M2: Nigeria | N2: South Sudan | O2: Togo | P2: Uganda
F3: unit | G3: type | H3: Overall | L3: GF states | M3: PMI states
A4: Simple CEA
C6: Grant
E7: Grant size | F7: $ | G7: input | H7: - | I7: 1000000 | J7: 1000000 | K7: 1000000 | L7: 1000000 | M7: 1000000 | N7: 1000000 | O7: 1000000 | P7: 1000000
C9: Under-five mortality benefits
E10: Cost per person under age five reached | F10: $ | G10: input | H10: - | I10: ='Main CEA'!I$29/'Main CEA'!$H$37/'Main CEA'!I$41/'Main CEA'!I$50 -> 15.188725 | J10: ='Main CEA'!J$29/'Main CEA'!$H$37/'Main CEA'!J$41/'Main CEA'!J$50 -> 26.238295 | K10: ='Main CEA'!K$29/'Main CEA'!$H$37/'Main CEA'!K$41/'Main CEA'!K$50 -> 17.709184 | L10: ='Main CEA'!L$29/'Main CEA'!$H$37/'Main CEA'!L$41/'Main CEA'!L$50 -> 21.922664 | M10: ='Main CEA'!M$29/'Main CEA'!$H$37/'Main CEA'!M$41/'Main CEA'!M$50 -> 21.922664 | N10: ='Main CEA'!N$29/'Main CEA'!$H$37/'Main CEA'!N$41/'Main CEA'!N$50 -> 25.047412 | O10: ='Main CEA'!O$29/'Main CEA'!$H$37/'Main CEA'!O$41/'Main CEA'!O$50 -> 23.046747 | P10: ='Main CEA'!P$29/'Main CEA'!$H$37/'Main CEA'!P$41/'Main CEA'!P$50 -> 22.147874
