Workbook
Name BDT_to_USD_2017: #REF!
Name BDT_to_USD_2014: #REF!
Name lesser_lean_season_duration: #REF!
Name nls_household_size: #REF!
Name primary_lean_season_duration: #REF!

Sheet Start here
A1: Notes on how to engage with our cost-effectiveness analysis
A2: This workbook contains our cost-effectiveness analysis. Cost-effectiveness is one factor we use to assess which opportunities are the highest-priority to support. We also consider other factors such as urgency, quality of implementation, and more. If you're a donor interested in supporting the top charity we believe will do the most good at the time your donation is granted, please consider supporting the Top Charities Fund. On the "Moral weights and discount rate" sheet, we've included GiveWell and conventional estimates for a few parameters. If you'd like to see how our results would change based on different inputs for these parameters, you can make a copy of this spreadsheet and enter your own values in the "Anyone" column. Expanding the formula bar at the top of the page (by clicking and dragging the bottom boundary) may make it easier to read the contents of explanatory cells.
A6: Notes on text color coding
A7: Blue text: direct input
A8: Green text: pulling from another cell in this workbook
A9: Black text: calculation
A11: Index
A12: Moral weights and discount rate | B12: Allows staff members or anyone else to supply discount rates and numbers used to trade off different good outcomes
A13: AMF | B13: Cost-effectiveness analysis for long-lasting insecticide-treated net distributions by the Against Malaria Foundation.
A14: GiveDirectly | B14: Cost-effectiveness analysis for unconditional cash transfers by GiveDirectly.
A15: Deworm the World | B15: Cost-effectiveness analysis for deworming by Deworm the World
A16: Unlimit Health | B16: Cost-effectiveness analysis for deworming by Unlimit Health
A17: Sightsavers | B17: Cost-effectiveness analysis for deworming by Sightsavers
A18: Malaria Consortium | B18: Cost-effectiveness analysis for seasonal malaria chemoprevention by Malaria Consortium
A19: Helen Keller International | B19: Cost-effectiveness analysis for vitamin A supplementation by Helen Keller International
A20: New Incentives | B20: Cost-effectiveness analysis for conditional cash transfers for immunization by New Incentives
A21: Value of counterfactual spending by other actors | B21: Used in the leverage and funging adjustments to our cost-effectiveness analyses
A22: Supplemental intervention-level adjustments | B22: Intervention-level adjustments for outcomes not explicitly modeled in our cost-effectiveness analyses
A24: Helpful GiveWell references
A25: =HYPERLINK("https://docs.google.com/document/d/1ZKq-MNU-xtn_48uN33L6VvBEZRAduvjwWMeaEffL4K4/","Guide to GiveWell cost-effectiveness analyses") -> Guide to GiveWell cost-effectiveness analyses
A26: =HYPERLINK("http://www.givewell.org/charities/top-charities","Full reviews of our top charities") -> Full reviews of our top charities
A27: =HYPERLINK("http://www.givewell.org/international/technical/criteria/cost-effectiveness/cost-effectiveness-models","Past versions of our cost-effectiveness analyses") -> Past versions of our cost-effectiveness analyses
A28: =HYPERLINK("http://www.givewell.org/international/technical/criteria/cost-effectiveness","Discussion of cost-effectiveness as a criterion") -> Discussion of cost-effectiveness as a criterion
A29: =HYPERLINK("http://www.givewell.org/international/technical/criteria/cost-effectiveness#MoreonGiveWellsviewsoncosteffectivenessestimates","Blog posts discussing cost-effectiveness") -> Blog posts discussing cost-effectiveness

Sheet Moral weights and discount rate
A1: Moral weights and discount rate | B1: Active | C1: GiveWell 2020 | D1: Anyone | E1: Conventional | F1: Alex | G1: Andrew | H1: Caitlin | I1: Dan | J1: Isabel | K1: James | L1: Josh | M1: Marinella | N1: Michael | O1: Natalie | P1: Nicole | Q1: Olivia | R1: Stephan | S1: Tom | T1: Notes
A2: Moral weights
A4: Consumption Increases
A5: Value assigned to doubling consumption for one person for one year | B5: {=index($A$1:$V$39,match($A5,$A$1:$A$39,0),match($A$17,$A$1:$T$1,0))} -> 1 | C5: 1 | E5: =1/2.5 -> 0.4
A7: Averting deaths
A8: Value assigned to averting the death of an individual under 5 from malaria | B8: =index($A$1:$V$39,match($A8,$A$1:$A$39,0),match($A$17,$A$1:$T$1,0)) -> 116.25262 | C8: 116.25262 | E8: 36.53 | T8: Lopez et al. 2006
A9: Value assigned to averting the death of an individual 5 or older from malaria | B9: =index($A$1:$V$39,match($A9,$A$1:$A$39,0),match($A$17,$A$1:$T$1,0)) -> 73.191405 | C9: 73.191405 | E9: 29.77 | T9: Lopez et al. 2006
A10: Value assigned to averting the death of a 6- to 59-month-old child (VAS) | B10: =index($A$1:$V$39,match($A10,$A$1:$A$39,0),match($A$17,$A$1:$T$1,0)) -> 118.73259 | C10: 118.73259 | E10: 36.53 | T10: Lopez et al. 2006
A11: Value assigned to averting the death of an individual under 5 from vaccine-preventable diseases | B11: =index($A$1:$V$39,match($A11,$A$1:$A$39,0),match($A$17,$A$1:$T$1,0)) -> 116.25262 | C11: =C8 -> 116.25262 | E11: 36.53 | T11: Lopez et al. 2006
A12: Value assigned to averting the death of an individual 5-14 years old from vaccine-preventable diseases | B12: =index($A$1:$V$39,match($A12,$A$1:$A$39,0),match($A$17,$A$1:$T$1,0)) -> 133.7 | C12: 133.7 | E12: 36.9 | T12: Lopez et al. 2006
A13: Value assigned to averting the death of an individual 15-49 years old from vaccine-preventable diseases | B13: =index($A$1:$V$39,match($A13,$A$1:$A$39,0),match($A$17,$A$1:$T$1,0)) -> 103.58571 | C13: 103.58571 | E13: 29.77 | T13: Lopez et al. 2006
A14: Value assigned to averting the death of an individual 50-74 years old from vaccine-preventable diseases | B14: =index($A$1:$V$39,match($A14,$A$1:$A$39,0),match($A$17,$A$1:$T$1,0)) -> 42.44 | C14: 42.44 | E14: 11.85 | T14: Lopez et al. 2006
A16: Active column pulls from:
A17: GiveWell 2020
A19: Derived value assignments
A20: Value assigned to increasing consumption by 10% for one person for one year | B20: =B5*(ln(1.1)/ln(2)) -> 0.13750352 | C20: =if(C5>0,C5*(ln(1.1)/ln(2)),"") -> 0.13750352 | D20: =if(D5>0,D5*(ln(1.1)/ln(2)),"") | E20: =E5*(ln(1.1)/ln(2)) -> 0.05500141
A21: Value assigned to increasing consumption by 25% for one person for one year | B21: =B5*(ln(1.25)/ln(2)) -> 0.32192809 | C21: =if(C5>0,C5*(ln(1.25)/ln(2)),"") -> 0.32192809 | D21: =if(D5>0,D5*(ln(1.25)/ln(2)),"") | E21: =E5*(ln(1.25)/ln(2)) -> 0.12877124
A22: Value assigned to increasing ln(consumption) by one unit for one person for one year | B22: =B5/ln(2) -> 1.442695 | C22: =if(C5>0,C5/ln(2),"") -> 1.442695 | D22: =if(D5>0,D5/ln(2),"") | E22: =E5/ln(2) -> 0.57707802
A24: Value assigned to increasing consumption by 10% for 100 people for one year | B24: =100*B5*(ln(1.1)/ln(2)) -> 13.750352 | C24: =if(C5>0,100*C5*(ln(1.1)/ln(2)),"") -> 13.750352 | D24: =if(D5>0,100*D5*(ln(1.1)/ln(2)),"") | E24: =100*E5*(ln(1.1)/ln(2)) -> 5.5001409
A25: Value assigned to increasing consumption by 25% for 100 people for one year | B25: =100*B5*(ln(1.25)/ln(2)) -> 32.192809 | C25: =if(C5>0,100*C5*(ln(1.25)/ln(2)),"") -> 32.192809 | D25: =if(D5>0,100*D5*(ln(1.25)/ln(2)),"") | E25: =100*E5*(ln(1.25)/ln(2)) -> 12.877124
A27: Implications
A28: Value of an age 5+ life saved relative to an under-5 life saved | B28: =iferror(B9/B8, " ") -> 0.62958931 | C28: =iferror(C9/C8, " ") -> 0.62958931 | D28: =iferror(D9/D8, " ") | E28: =iferror(E9/E8, " ") -> 0.81494662
A29: Value of doubling consumption for one person for one year relative to saving the life of a child under-5 (AMF) | B29: =iferror(B5/B8, " ") -> 0.008601957 | C29: =iferror(C5/C8, " ") -> 0.008601957 | D29: =iferror(D5/D8, " ") | E29: =iferror(E5/E8, " ") -> 0.010949904
B30: =iferror(B8/#REF!, " ") | C30: =iferror(C8/#REF!, " ") | D30: =iferror(D8/#REF!, " ") | E30: =iferror(E8/#REF!, " ")
A31: Discount rate
A32: Improving circumstances over time | B32: =index($A$1:$V$39,match($A32,$A$1:$A$39,0),match($A$17,$A$1:$T$1,0)) -> 0.017 | C32: 0.017
A33: Compounding non-monetary benefits | B33: =index($A$1:$V$39,match($A33,$A$1:$A$39,0),match($A$17,$A$1:$T$1,0)) -> 0.009 | C33: 0.009
A34: Temporal uncertainty | B34: =index($A$1:$V$39,match($A34,$A$1:$A$39,0),match($A$17,$A$1:$T$1,0)) -> 0.014 | C34: 0.014
A35: Pure time preference (donors) | B35: =index($A$1:$V$39,match($A35,$A$1:$A$39,0),match($A$17,$A$1:$T$1,0)) -> 0 | C35: 0
A36: Pure time preference (program participants) | B36: =index($A$1:$V$39,match($A36,$A$1:$A$39,0),match($A$17,$A$1:$T$1,0)) -> 0 | C36: 0
A37: Overall discount rate | B37: =index($A$1:$V$39,match($A37,$A$1:$A$39,0),match($A$17,$A$1:$T$1,0)) -> 0.04 | C37: =sum(C32:C36) -> 0.04 | E37: =C37 -> 0.04

Sheet AMF
A1: Long-lasting insecticide-treated net (LLIN) distributions - Against Malaria Foundation (AMF) | B1: DRC | C1: Guinea | D1: Togo | E1: Uganda | F1: Nigeria (PMI states) | G1: Nigeria (Global Fund states) | H1: Chad | I1: South Sudan
A5: Funding allocation
A7: Percentage of total costs covered by AMF | B7: 0.5039085 | C7: 0.6365521 | D7: 0.6534446 | E7: 0.5993375 | F7: 0.6809358 | G7: 0.6809358 | H7: 0.6365521 | I7: 0.4300644
A8: Percentage of total costs covered by other philanthropic actors | B8: 0 | C8: 0 | D8: 0 | E8: 0 | F8: 0 | G8: 0 | H8: 0 | I8: 0
A10: Number of people covered
A12: Costs
A13: Donation to AMF (arbitrary size) | B13: 100000 | C13: 100000 | D13: 100000 | E13: 100000 | F13: 100000 | G13: 100000 | H13: 100000 | I13: 100000
A14: Total spending by all contributors | B14: =B13/B7 -> 198448.73 | C14: =C13/C7 -> 157096.33 | D14: =D13/D7 -> 153035.16 | E14: =E13/E7 -> 166850.9 | F14: =F13/F7 -> 146856.72 | G14: =G13/G7 -> 146856.72 | H14: =H13/H7 -> 157096.33 | I14: =I13/I7 -> 232523.32
A15: Cost per long-lasting insecticide-treated net (LLIN) distributed | B15: 5.85033 | C15: 3.93785 | D15: 3.66624 | E15: 4.44504 | F15: 4.34286 | G15: 4.34286 | H15: 3.93785 | I15: 5.32824
A17: Net usage
A18: Number of nets distributed | B18: =B14/B15 -> 33920.946 | C18: =C14/C15 -> 39893.935 | D18: =D14/D15 -> 41741.719 | E18: =E14/E15 -> 37536.422 | F18: =F14/F15 -> 33815.67 | G18: =G14/G15 -> 33815.67 | H18: =H14/H15 -> 39893.935 | I18: =I14/I15 -> 43639.798
A19: Proportion of distributed nets used in trials from Pryce et al. 2018 meta-analysis | B19: 0.7 | C19: 0.7 | D19: 0.7 | E19: 0.7 | F19: 0.7 | G19: 0.7 | H19: 0.7 | I19: 0.7
A20: Adjustment for net usage in program contexts | B20: 0.9 | C20: 0.9 | D20: 0.9 | E20: 0.9 | F20: 0.9 | G20: 0.9 | H20: 0.9 | I20: 0.9
A21: Proportion of distributed nets used in program contexts | B21: =B19*B20 -> 0.63 | C21: =C19*C20 -> 0.63 | D21: =D19*D20 -> 0.63 | E21: =E19*E20 -> 0.63 | F21: =F19*F20 -> 0.63 | G21: =G19*G20 -> 0.63 | H21: =H19*H20 -> 0.63 | I21: =I19*I20 -> 0.63
A22: Number of nets used | B22: =B18*B21 -> 21370.196 | C22: =C18*C21 -> 25133.179 | D22: =D18*D21 -> 26297.283 | E22: =E18*E21 -> 23647.946 | F22: =F18*F21 -> 21303.872 | G22: =G18*G21 -> 21303.872 | H22: =H18*H21 -> 25133.179 | I22: =I18*I21 -> 27493.072
A24: Net coverage
A25: Number of people sleeping under each used net | B25: 2.15114 | C25: 1.99095 | D25: 1.72163 | E25: 1.76505 | F25: 1.93645 | G25: 1.93645 | H25: 1.93645 | I25: 1.93645
A26: Total number of people sleeping under distributed nets | B26: =B22*B25 -> 45970.283 | C26: =C22*C25 -> 50038.903 | D26: =D22*D25 -> 45274.192 | E26: =E22*E25 -> 41739.807 | F26: =F22*F25 -> 41253.884 | G26: =G22*G25 -> 41253.884 | H26: =H22*H25 -> 48669.145 | I26: =I22*I25 -> 53238.96
A27: Equivalent coverage-years for an LLIN over a 36-month distribution | B27: =2.11*(1-0.173704447529312) -> 1.7434836 | C27: 2.11 | D27: 2.11 | E27: 2.11 | F27: 2.11 | G27: 2.11 | H27: 2.11 | I27: 2.11
A28: Adjustment for net coverage years lost due to residual nets from previous distributions | B28: 0.97 | C28: 0.97 | D28: 0.97 | E28: 0.97 | F28: 0.98 | G28: 0.97 | H28: 0.97 | I28: 0.97
A29: Adjustment for program impact being to move distributions closer together | B29: =1-29.74486% -> 0.7025514 | C29: 1 | D29: 1 | E29: 1 | F29: =1-35.0995389911857% -> 0.64900461 | G29: 1 | H29: 1 | I29: =1-36.86111% -> 0.6313889
A30: Total person-years of effective coverage | B30: =B26*B27*B28*B29 -> 54619.143 | C30: =C26*C27*C28*C29 -> 102414.62 | D30: =D26*D27*D28*D29 -> 92662.688 | E30: =E26*E27*E28*E29 -> 85428.863 | F30: =F26*F27*F28*F29 -> 55363.196 | G30: =G26*G27*G28*G29 -> 84434.324 | H30: =H26*H27*H28*H29 -> 99611.138 | I30: =I26*I27*I28*I29 -> 68798.774
A32: Age distribution of net coverage
A34: Percent of population under 5 years old (used for mortality effects and development effects) | B34: =13629465.1519444/87670443.7766788 -> 0.15546249 | C34: =2143394.87689442/12643148.9336671 -> 0.16953015 | D34: =1114855.20710404/7921526.58517355 -> 0.14073742 | E34: =7089749.81596238/41117856.2413241 -> 0.17242508 | F34: =33521637.830718/214823785.7115 -> 0.15604249 | G34: =33521637.830718/214823785.7115 -> 0.15604249 | H34: =3332666.56158174/16398859.7420741 -> 0.20322551 | I34: =1516375.15541563/9282963.04697691 -> 0.16335034
A35: Percent of population ages 5-9 | B35: =12763832.6557654/87670443.7766788 -> 0.14558878 | C35: =1933404.91137462/12643148.9336671 -> 0.15292115 | D35: =1074824.79732476/7921526.58517355 -> 0.13568405 | E35: =6314355.69254718/41117856.2413241 -> 0.15356724 | F35: =31315804.4739165/214823785.7115 -> 0.14577438 | G35: =31315804.4739165/214823785.7115 -> 0.14577438 | H35: =2751338.52652141/16398859.7420741 -> 0.16777621 | I35: =1342387.97845529/9282963.04697691 -> 0.1446077
A36: Percent of population ages 10-14 | B36: =11301847.5012717/87670443.7766788 -> 0.12891286 | C36: =1636389.58910505/12643148.9336671 -> 0.12942896 | D36: =957955.990123928/7921526.58517355 -> 0.12093073 | E36: =5673366.42359162/41117856.2413241 -> 0.13797817 | F36: =28910632.0515107/214823785.7115 -> 0.13457836 | G36: =28910632.0515107/214823785.7115 -> 0.13457836 | H36: =2226082.47505384/16398859.7420741 -> 0.13574617 | I36: =1309739.90536986/9282963.04697691 -> 0.14109072
A37: Percent of population ages 5-14 (used for development effects only) | B37: =24065680.1570372/87670443.7766788 -> 0.27450164 | C37: =3569794.50047968/12643148.9336671 -> 0.28235011 | D37: =2032780.78744869/7921526.58517355 -> 0.25661478 | E37: =11987722.1161388/41117856.2413241 -> 0.29154541 | F37: =60226436.5254272/214823785.7115 -> 0.28035274 | G37: =60226436.5254272/214823785.7115 -> 0.28035274 | H37: =4977421.00157526/16398859.7420741 -> 0.30352238 | I37: =2652127.88382515/9282963.04697691 -> 0.28569842
A39: Person-years of coverage for under 5s | B39: =B30*B34 -> 8491.2278 | C39: =C30*C34 -> 17362.366 | D39: =D30*D34 -> 13041.108 | E39: =E30*E34 -> 14730.079 | F39: =F30*F34 -> 8639.0108 | G39: =G30*G34 -> 13175.342 | H39: =H30*H34 -> 20243.524 | I39: =I30*I34 -> 11238.303
A40: Person-years of coverage for ages 5-14 | B40: =B30*B37 -> 14993.044 | C40: =C30*C37 -> 28916.78 | D40: =D30*D37 -> 23778.615 | E40: =E30*E37 -> 24906.393 | F40: =F30*F37 -> 15521.224 | G40: =G30*G37 -> 23671.394 | H40: =H30*H37 -> 30234.21 | I40: =I30*I37 -> 19655.701
A41: Person-years of coverage for under 15s | B41: =B40+B39 -> 23484.272 | C41: =C40+C39 -> 46279.146 | D41: =D40+D39 -> 36819.723 | E41: =E40+E39 -> 39636.471 | F41: =F40+F39 -> 24160.234 | G41: =G40+G39 -> 36846.736 | H41: =H40+H39 -> 50477.734 | I41: =I40+I39 -> 30894.004
A43: Mortality reduction in children under 5
A45: Effect of bednet distributions on mortality
A46: Reduction in malaria incidence for children under 5 receiving nets (from Pryce et al. 2018 meta-analysis) | B46: 0.45 | C46: 0.45 | D46: 0.45 | E46: 0.45 | F46: 0.45 | G46: 0.45 | H46: 0.45 | I46: 0.45
A47: Reduction in malaria incidence for children under 5 sleeping under nets | B47: =B46/B19 -> 0.64285714 | C47: =C46/C19 -> 0.64285714 | D47: =D46/D19 -> 0.64285714 | E47: =E46/E19 -> 0.64285714 | F47: =F46/F19 -> 0.64285714 | G47: =G46/G19 -> 0.64285714 | H47: =H46/H19 -> 0.64285714 | I47: =I46/I19 -> 0.64285714
A48: Internal validity adjustment — Nets | B48: 0.95 | C48: 0.95 | D48: 0.95 | E48: 0.95 | F48: 0.95 | G48: 0.95 | H48: 0.95 | I48: 0.95
A49: External validity adjustment — Nets | B49: 0.95 | C49: 0.95 | D49: 0.95 | E49: 0.95 | F49: 0.95 | G49: 0.95 | H49: 0.95 | I49: 0.95
A50: Efficacy reduction due to insecticide resistance | B50: 0.0376862 | C50: 0.2070199 | D50: 0.3290476 | E50: 0.11499111 | F50: 0.13530442 | G50: 0.13530442 | H50: 0.585957 | I50: 0.3067736
A51: Ratio of the reduction in malaria mortality to the reduction in malaria incidence | B51: 1 | C51: 1 | D51: 1 | E51: 1 | F51: 1 | G51: 1 | H51: 1 | I51: 1
A52: Expected reduction in malaria mortality among children treated | B52: =B47*B48*B49*(1-B50)*B51 -> 0.55831385 | C52: =C47*C48*C49*(1-C50)*C51 -> 0.46007006 | D52: =D47*D48*D49*(1-D50)*D51 -> 0.38927221 | E52: =E47*E48*E49*(1-E50)*E51 -> 0.51346319 | F52: =F47*F48*F49*(1-F50)*F51 -> 0.50167785 | G52: =G47*G48*G49*(1-G50)*G51 -> 0.50167785 | H52: =H47*H48*H49*(1-H50)*H51 -> 0.24021888 | I52: =I47*I48*I49*(1-I50)*I51 -> 0.4021951
A54: Counterfactual mortality in the absence of bednets
A55: Annual 1-59 month malaria mortality rate in AMF countries (per 1,000 child-years, GBD 2019) | B55: 3.05645 | C55: 3.67391 | D55: 1.63914 | E55: 2.35048 | F55: 2.90653 | G55: 2.70483 | H55: 1.31903 | I55: 2.51618
A56: Ratio of indirect malaria deaths per direct malaria death | B56: 0.75 | C56: 0.75 | D56: 0.75 | E56: 0.75 | F56: 0.75 | G56: 0.75 | H56: 0.75 | I56: 0.75
A57: Malaria-attributable deaths in target population (per 1,000 child-years), 1-59-month-old children, 2019, before adjusting for SMC | B57: =B55*(1+B56) -> 5.3487875 | C57: =C55*(1+C56) -> 6.4293425 | D57: =D55*(1+D56) -> 2.868495 | E57: =E55*(1+E56) -> 4.11334 | F57: =F55*(1+F56) -> 5.0864275 | G57: =G55*(1+G56) -> 4.7334525 | H57: =H55*(1+H56) -> 2.3083025 | I57: =I55*(1+I56) -> 4.403315
A58: Malaria-attributable deaths averted per 1,000 children per year targeted with seasonal malaria chemoprevention | B58: 0 | C58: 0 | D58: 0.55084206 | E58: 0 | F58: 1.15929 | G58: 0.51706 | H58: 0.74863514 | I58: 0.39662
A59: Malaria-attributable deaths in target population (per 1,000 child-years), 1-59-month-old children, 2019, after adjusting for SMC | B59: =B57-B58 -> 5.3487875 | C59: =C57-C58 -> 6.4293425 | D59: =D57-D58 -> 2.3176529 | E59: =E57-E58 -> 4.11334 | F59: =F57-F58 -> 3.9271375 | G59: =G57-G58 -> 4.2163925 | H59: =H57-H58 -> 1.5596674 | I59: =I57-I58 -> 4.006695
A60: Proportion of 1-59-month-old children sleeping under a net, 2019 | B60: 0.591 | C60: 0.586 | D60: 0.795 | E60: 0.704 | F60: 0.4709335 | G60: 0.5097281 | H60: 0.313 | I60: 0.494
A61: Malaria-attributable deaths (per 1,000 person-years), 1-59 month-old-children, 2019, in absence of bed nets | B61: =B59/((1-B52)*B60+(1-B60)) -> 7.9828298 | C61: =C59/((1-C52)*C60+(1-C60)) -> 8.8025079 | D61: =D59/((1-D52)*D60+(1-D60)) -> 3.3563461 | E61: =E59/((1-E52)*E60+(1-E60)) -> 6.4419715 | F61: =F59/((1-F52)*F60+(1-F60)) -> 5.1419614 | G61: =G59/((1-G52)*G60+(1-G60)) -> 5.6650568 | H61: =H59/((1-H52)*H60+(1-H60)) -> 1.6864706 | I61: =I59/((1-I52)*I60+(1-I60)) -> 5.0001459
A63: Deaths averted per 1,000 person-years of coverage for under 5s | B63: =B52*B61 -> 4.4569244 | C63: =C52*C61 -> 4.0497704 | D63: =D52*D61 -> 1.3065322 | E63: =E52*E61 -> 3.3077153 | F63: =F52*F61 -> 2.5796081 | G63: =G52*G61 -> 2.8420335 | H63: =H52*H61 -> 0.40512206 | I63: =I52*I61 -> 2.0110342
A65: Total number of under-5 deaths averted | B65: =(B39/1000)*B63 -> 37.844761 | C65: =(C39/1000)*C63 -> 70.313595 | D65: =(D39/1000)*D63 -> 17.038628 | E65: =(E39/1000)*E63 -> 48.722907 | F65: =(F39/1000)*F63 -> 22.285262 | G65: =(G39/1000)*G63 -> 37.444763 | H65: =(H39/1000)*H63 -> 8.2010982 | I65: =(I39/1000)*I63 -> 22.600611
A67: Comparable valuation
A68: Value assigned to averting the death of an individual under 5 from malaria | B68: {=index('Moral weights and discount rate'!$A$1:$ZU$39,match($A68,'Moral weights and discount rate'!$A$1:$A$39,0),match('Moral weights and discount rate'!$A$17,'Moral weights and discount rate'!$A$1:$ZU1,0))} -> 116.25262 | C68: {=index('Moral weights and discount rate'!$A$1:$ZU$39,match($A68,'Moral weights and discount rate'!$A$1:$A$39,0),match('Moral weights and discount rate'!$A$17,'Moral weights and discount rate'!$A$1:$ZU1,0))} -> 116.25262 | D68: {=index('Moral weights and discount rate'!$A$1:$ZU$39,match($A68,'Moral weights and discount rate'!$A$1:$A$39,0),match('Moral weights and discount rate'!$A$17,'Moral weights and discount rate'!$A$1:$ZU1,0))} -> 116.25262 | E68: {=index('Moral weights and discount rate'!$A$1:$ZU$39,match($A68,'Moral weights and discount rate'!$A$1:$A$39,0),match('Moral weights and discount rate'!$A$17,'Moral weights and discount rate'!$A$1:$ZU1,0))} -> 116.25262 | F68: {=index('Moral weights and discount rate'!$A$1:$ZU$39,match($A68,'Moral weights and discount rate'!$A$1:$A$39,0),match('Moral weights and discount rate'!$A$17,'Moral weights and discount rate'!$A$1:$ZU1,0))} -> 116.25262 | G68: {=index('Moral weights and discount rate'!$A$1:$ZU$39,match($A68,'Moral weights and discount rate'!$A$1:$A$39,0),match('Moral weights and discount rate'!$A$17,'Moral weights and discount rate'!$A$1:$ZU1,0))} -> 116.25262 | H68: {=index('Moral weights and discount rate'!$A$1:$ZU$39,match($A68,'Moral weights and discount rate'!$A$1:$A$39,0),match('Moral weights and discount rate'!$A$17,'Moral weights and discount rate'!$A$1:$ZU1,0))} -> 116.25262 | I68: {=index('Moral weights and discount rate'!$A$1:$ZU$39,match($A68,'Moral weights and discount rate'!$A$1:$A$39,0),match('Moral weights and discount rate'!$A$17,'Moral weights and discount rate'!$A$1:$ZU1,0))} -> 116.25262
A69: Total units of value from under-5 deaths averted (before accounting for leverage and funging) | B69: =B65*B68 -> 4399.5524 | C69: =C65*C68 -> 8174.1393 | D69: =D65*D68 -> 1980.785 | E69: =E65*E68 -> 5664.1654 | F69: =F65*F68 -> 2590.72 | G69: =G65*G68 -> 4353.0517 | H69: =H65*H68 -> 953.39912 | I69: =I65*I68 -> 2627.3802
A71: Mortality reduction in individuals 5+ years old
A73: Ratio of 5+ malaria deaths to under-5 malaria deaths
A74: Number of malaria deaths per year (GBD 2019) | B74: 57160.15 | C74: 11336.5 | D74: 5436.19 | E74: 22586.59 | F74: 55752.713 | G74: 77647.608 | H74: 7194.2 | I74: 5109.31
A75: Number of under-5 malaria deaths per year (GBD 2019) | B75: 44077.95 | C75: 8181.1 | D75: 1880.41 | E75: 17385.77 | F75: 30014.758 | G75: 44919.362 | H75: 4525.73 | I75: 4010.3
A76: Number of age 5+ malaria deaths per year | B76: =B74-B75 -> 13082.2 | C76: =C74-C75 -> 3155.4 | D76: =D74-D75 -> 3555.78 | E76: =E74-E75 -> 5200.82 | F76: =F74-F75 -> 25737.955 | G76: =G74-G75 -> 32728.247 | H76: =H74-H75 -> 2668.47 | I76: =I74-I75 -> 1099.01
A77: Ratio of 5+ malaria deaths to under-5 malaria deaths | B77: =B76/B75 -> 0.29679692 | C77: =C76/C75 -> 0.38569386 | D77: =D76/D75 -> 1.89096 | E77: =E76/E75 -> 0.29914234 | F77: =F76/F75 -> 0.85751 | G77: =G76/G75 -> 0.72859999 | H77: =H76/H75 -> 0.58962201 | I77: =I76/I75 -> 0.27404683
A78: Relative efficacy of LLINs for reducing mortality of individuals age 5+ | B78: 0.8 | C78: 0.8 | D78: 0.8 | E78: 0.8 | F78: 0.8 | G78: 0.8 | H78: 0.8 | I78: 0.8
A80: Total number of age 5+ deaths averted | B80: =B65*B77*B78 -> 8.9857669 | C80: =C65*C77*C78 -> 21.695617 | D80: =D65*D77*D78 -> 25.77549 | E80: =E65*E77*E78 -> 11.660068 | F80: =F65*F77*F78 -> 15.287868 | G80: =G65*G77*G78 -> 21.825803 | H80: =H65*H77*H78 -> 3.8684384 | I80: =I65*I77*I78 -> 4.9549007
A82: Comparable valuation
A83: Value assigned to averting the death of an individual 5 or older from malaria | B83: {=index('Moral weights and discount rate'!$A$1:$ZU$39,match($A83,'Moral weights and discount rate'!$A$1:$A$39,0),match('Moral weights and discount rate'!$A$17,'Moral weights and discount rate'!$A$1:$ZU1,0))} -> 73.191405 | C83: {=index('Moral weights and discount rate'!$A$1:$ZU$39,match($A83,'Moral weights and discount rate'!$A$1:$A$39,0),match('Moral weights and discount rate'!$A$17,'Moral weights and discount rate'!$A$1:$ZU1,0))} -> 73.191405 | D83: {=index('Moral weights and discount rate'!$A$1:$ZU$39,match($A83,'Moral weights and discount rate'!$A$1:$A$39,0),match('Moral weights and discount rate'!$A$17,'Moral weights and discount rate'!$A$1:$ZU1,0))} -> 73.191405 | E83: {=index('Moral weights and discount rate'!$A$1:$ZU$39,match($A83,'Moral weights and discount rate'!$A$1:$A$39,0),match('Moral weights and discount rate'!$A$17,'Moral weights and discount rate'!$A$1:$ZU1,0))} -> 73.191405 | F83: {=index('Moral weights and discount rate'!$A$1:$ZU$39,match($A83,'Moral weights and discount rate'!$A$1:$A$39,0),match('Moral weights and discount rate'!$A$17,'Moral weights and discount rate'!$A$1:$ZU1,0))} -> 73.191405 | G83: {=index('Moral weights and discount rate'!$A$1:$ZU$39,match($A83,'Moral weights and discount rate'!$A$1:$A$39,0),match('Moral weights and discount rate'!$A$17,'Moral weights and discount rate'!$A$1:$ZU1,0))} -> 73.191405 | H83: {=index('Moral weights and discount rate'!$A$1:$ZU$39,match($A83,'Moral weights and discount rate'!$A$1:$A$39,0),match('Moral weights and discount rate'!$A$17,'Moral weights and discount rate'!$A$1:$ZU1,0))} -> 73.191405 | I83: {=index('Moral weights and discount rate'!$A$1:$ZU$39,match($A83,'Moral weights and discount rate'!$A$1:$A$39,0),match('Moral weights and discount rate'!$A$17,'Moral weights and discount rate'!$A$1:$ZU1,0))} -> 73.191405
A84: Total units of value from age 5+ deaths averted (before accounting for leverage and funging) | B84: =B83*B80 -> 657.6809 | C84: =C83*C80 -> 1587.9327 | D84: =D83*D80 -> 1886.5443 | E84: =E83*E80 -> 853.41673 | F84: =F83*F80 -> 1118.9406 | G84: =G83*G80 -> 1597.4612 | H84: =H83*H80 -> 283.13644 | I84: =I83*I80 -> 362.65614
A86: Overall mortality reduction
A88: Total deaths averted | B88: =B80+B65 -> 46.830528 | C88: =C80+C65 -> 92.009212 | D88: =D80+D65 -> 42.814117 | E88: =E80+E65 -> 60.382974 | F88: =F80+F65 -> 37.573131 | G88: =G80+G65 -> 59.270567 | H88: =H80+H65 -> 12.069537 | I88: =I80+I65 -> 27.555512
A90: Reduction in malaria prevalence (used for estimating income increases)
A92: Relative reduction in malaria prevalence
A93: Expected reduction in malaria prevalence in current day distributions | B93: =B52 -> 0.55831385 | C93: =C52 -> 0.46007006 | D93: =D52 -> 0.38927221 | E93: =E52 -> 0.51346319 | F93: =F52 -> 0.50167785 | G93: =G52 -> 0.50167785 | H93: =H52 -> 0.24021888 | I93: =I52 -> 0.4021951
A95: Baseline malaria prevalence
A96: Malaria prevalence in AMF context (Age <5) (GBD 2019) | B96: =28309.33/100000 -> 0.2830933 | C96: =33757.61/100000 -> 0.3375761 | D96: =30426.94/100000 -> 0.3042694 | E96: =38599.14/100000 -> 0.3859914 | F96: 0.28164561 | G96: 0.19509225 | H96: 0.118 | I96: =18320.81/100000 -> 0.1832081
A97: Malaria prevalence in AMF context (Age 5-9) (GBD 2019) | B97: =31278.98/100000 -> 0.3127898 | C97: =37364.59/100000 -> 0.3736459 | D97: =33589.94/100000 -> 0.3358994 | E97: =42709.18/100000 -> 0.4270918 | H97: 0.118 | I97: =20351.11/100000 -> 0.2035111
A98: Malaria prevalence in AMF context (Age 10-14) (GBD 2019) | B98: =29161.94/100000 -> 0.2916194 | C98: =34825.88/100000 -> 0.3482588 | D98: =31313.64/100000 -> 0.3131364 | E98: =39785.54/100000 -> 0.3978554 | H98: 0.118 | I98: =18971.28/100000 -> 0.1897128
A99: Malaria prevalence in AMF context (Age 5-14) (GBD 2019) | B99: =30284.77/100000 -> 0.3028477 | C99: =36200.85/100000 -> 0.3620085 | D99: =32517.22/100000 -> 0.3251722 | E99: =41325.53/100000 -> 0.4132553 | F99: 0.2954578 | G99: 0.21171631 | H99: 0.118 | I99: =19669.69/100000 -> 0.1966969
A100: Expected increase in malaria prevalence in the absence of an LLIN distribution | B100: =1/((1-B93)*B60+(1-B60)) - 1 -> 0.49245597 | C100: =1/((1-C93)*C60+(1-C60)) - 1 -> 0.36911479 | D100: =1/((1-D93)*D60+(1-D60)) - 1 -> 0.44816595 | E100: =1/((1-E93)*E60+(1-E60)) - 1 -> 0.56611696 | F100: =1/((1-F93)*F60+(1-F60)) - 1 -> 0.30934081 | G100: =1/((1-G93)*G60+(1-G60)) - 1 -> 0.3435791 | H100: =1/((1-H93)*H60+(1-H60)) - 1 -> 0.081301442 | I100: =1/((1-I93)*I60+(1-I60)) - 1 -> 0.24794772
A101: Counterfactual malaria prevalence in AMF context in absence of distribution (Age <5) | B101: =B96*(1+B100) -> 0.42250429 | C101: =C96*(1+C100) -> 0.46218043 | D101: =D96*(1+D100) -> 0.44063258 | E101: =E96*(1+E100) -> 0.60450768 | F101: =F96*(1+F100) -> 0.36877009 | G101: =G96*(1+G100) -> 0.26212186 | H101: =H96*(1+H100) -> 0.12759357 | I101: =I96*(1+I100) -> 0.22863413
A102: Counterfactual malaria prevalence in AMF context in absence of distribution (Ages 5-14) | B102: =B99*(1+B100) -> 0.45198686 | C102: =C99*(1+C100) -> 0.49563119 | D102: =D99*(1+D100) -> 0.47090331 | E102: =E99*(1+E100) -> 0.64720614 | F102: =F99*(1+F100) -> 0.38685496 | G102: =G99*(1+G100) -> 0.2844576 | H102: =H99*(1+H100) -> 0.12759357 | I102: =I99*(1+I100) -> 0.24546745
A104: Absolute reduction in malaria prevalence
A105: Percentage point reduction in the point-in-time probability of a covered child being infected with malaria (Age <5) | B105: =B93*B101 -> 0.23588999 | C105: =C93*C101 -> 0.21263538 | D105: =D93*D101 -> 0.17152602 | E105: =E93*E101 -> 0.31039244 | F105: =F93*F101 -> 0.18500378 | G105: =G93*G101 -> 0.13150073 | H105: =H93*H101 -> 0.030650384 | I105: =I93*I101 -> 0.091955528
A106: Percentage point reduction in the point-in-time probability of a covered child being infected with malaria (Age 5-14) | B106: =B93*B102 -> 0.25235052 | C106: =C93*C102 -> 0.22802507 | D106: =D93*D102 -> 0.18330957 | E106: =E93*E102 -> 0.33231653 | F106: =F93*F102 -> 0.19407656 | G106: =G93*G102 -> 0.14270608 | H106: =H93*H102 -> 0.030650384 | I106: =I93*I102 -> 0.098725805
A108: Long-term income increases for children currently aged 14 and under
A110: Prevalence reduction
A111: Reduction in the number of people infected with malaria at a single point of time (Age<5) | B111: =B39*B105 -> 2002.9957 | C111: =C39*C105 -> 3691.8533 | D111: =D39*D105 -> 2236.8893 | E111: =E39*E105 -> 4572.1052 | F111: =F39*F105 -> 1598.2497 | G111: =G39*G105 -> 1732.5671 | H111: =H39*H105 -> 620.47178 | I111: =I39*I105 -> 1033.4241
A112: Reduction in the number of people infected with malaria at a single point of time (Age 5-14) | B112: =B40*B106 -> 3783.5025 | C112: =C40*C106 -> 6593.7509 | D112: =D40*D106 -> 4358.8477 | E112: =E40*E106 -> 8276.8059 | F112: =F40*F106 -> 3012.3057 | G112: =G40*G106 -> 3378.0518 | H112: =H40*H106 -> 926.69015 | I112: =I40*I106 -> 1940.5249
A114: Increase in income from prevalence reduction
A115: Increase in income from reducing point-in-time probability of malaria infection from 100% to 0% for an individual for one year between the ages of 0 and 14 | B115: 0.023 | C115: 0.023 | D115: 0.023 | E115: 0.023 | F115: 0.023 | G115: 0.023 | H115: 0.023 | I115: 0.023
A116: Additional replicability adjustment for relationship between malaria and income | B116: 0.52 | C116: 0.52 | D116: 0.52 | E116: 0.52 | F116: 0.52 | G116: 0.52 | H116: 0.52 | I116: 0.52
A117: Adjusted increase in ln(income) from reducing point-in-time probability of malaria infection from 100% to 0% for an individual for one year between the ages of 0 and 14 | B117: =(ln(1+B115)-ln(1))*B116 -> 0.011824533 | C117: =(ln(1+C115)-ln(1))*C116 -> 0.011824533 | D117: =(ln(1+D115)-ln(1))*D116 -> 0.011824533 | E117: =(ln(1+E115)-ln(1))*E116 -> 0.011824533 | F117: =(ln(1+F115)-ln(1))*F116 -> 0.011824533 | G117: =(ln(1+G115)-ln(1))*G116 -> 0.011824533 | H117: =(ln(1+H115)-ln(1))*H116 -> 0.011824533 | I117: =(ln(1+I115)-ln(1))*I116 -> 0.011824533
A119: Duration of long term benefits
A120: Average number of years between nets being distributed and the beginning of long term benefits | B120: 10 | C120: 10 | D120: 10 | E120: 10 | F120: 10 | G120: 10 | H120: 10 | I120: 10
A121: Discount rate | B121: {=index('Moral weights and discount rate'!$1:$39,match("Overall discount rate",'Moral weights and discount rate'!$A:$A,0), match("Active",'Moral weights and discount rate'!$1:$1,0))} -> 0.04 | C121: {=index('Moral weights and discount rate'!$1:$39,match("Overall discount rate",'Moral weights and discount rate'!$A:$A,0), match("Active",'Moral weights and discount rate'!$1:$1,0))} -> 0.04 | D121: {=index('Moral weights and discount rate'!$1:$39,match("Overall discount rate",'Moral weights and discount rate'!$A:$A,0), match("Active",'Moral weights and discount rate'!$1:$1,0))} -> 0.04 | E121: {=index('Moral weights and discount rate'!$1:$39,match("Overall discount rate",'Moral weights and discount rate'!$A:$A,0), match("Active",'Moral weights and discount rate'!$1:$1,0))} -> 0.04 | F121: {=index('Moral weights and discount rate'!$1:$39,match("Overall discount rate",'Moral weights and discount rate'!$A:$A,0), match("Active",'Moral weights and discount rate'!$1:$1,0))} -> 0.04 | G121: {=index('Moral weights and discount rate'!$1:$39,match("Overall discount rate",'Moral weights and discount rate'!$A:$A,0), match("Active",'Moral weights and discount rate'!$1:$1,0))} -> 0.04 | H121: {=index('Moral weights and discount rate'!$1:$39,match("Overall discount rate",'Moral weights and discount rate'!$A:$A,0), match("Active",'Moral weights and discount rate'!$1:$1,0))} -> 0.04 | I121: {=index('Moral weights and discount rate'!$1:$39,match("Overall discount rate",'Moral weights and discount rate'!$A:$A,0), match("Active",'Moral weights and discount rate'!$1:$1,0))} -> 0.04
A122: Benefit on one year's income (discounted back because of delay between distribution and working for income) | B122: =B117/(1+B121)^B120 -> 0.007988231 | C122: =C117/(1+C121)^C120 -> 0.007988231 | D122: =D117/(1+D121)^D120 -> 0.007988231 | E122: =E117/(1+E121)^E120 -> 0.007988231 | F122: =F117/(1+F121)^F120 -> 0.007988231 | G122: =G117/(1+G121)^G120 -> 0.007988231 | H122: =H117/(1+H121)^H120 -> 0.007988231 | I122: =I117/(1+I121)^I120 -> 0.007988231
A123: Duration of long term benefits of AMF (in years) | B123: 40 | C123: 40 | D123: 40 | E123: 40 | F123: 40 | G123: 40 | H123: 40 | I123: 40
A124: Present value of lifetime benefits from reducing prevalence from 1 to 0 for an individual for one year between the ages of 0 and 14 | B124: =pv(B121,B123,-B122,,1) -> 0.16443362 | C124: =pv(C121,C123,-C122,,1) -> 0.16443362 | D124: =pv(D121,D123,-D122,,1) -> 0.16443362 | E124: =pv(E121,E123,-E122,,1) -> 0.16443362 | F124: =pv(F121,F123,-F122,,1) -> 0.16443362 | G124: =pv(G121,G123,-G122,,1) -> 0.16443362 | H124: =pv(H121,H123,-H122,,1) -> 0.16443362 | I124: =pv(I121,I123,-I122,,1) -> 0.16443362
A125: Multiplier for resource sharing within households | B125: 2 | C125: 2 | D125: 2 | E125: 2 | F125: 2 | G125: 2 | H125: 2 | I125: 2
A127: Present value of benefits from reducing point-in-time probability of malaria infection from 100% to 0% for an individual for one year between the ages of 0 and 14 | B127: =B125*B124 -> 0.32886724 | C127: =C125*C124 -> 0.32886724 | D127: =D125*D124 -> 0.32886724 | E127: =E125*E124 -> 0.32886724 | F127: =F125*F124 -> 0.32886724 | G127: =G125*G124 -> 0.32886724 | H127: =H125*H124 -> 0.32886724 | I127: =I125*I124 -> 0.32886724
A129: Total units of increase in units of annual ln(income) (Age<5) — Present value | B129: =B111*B127 -> 658.71965 | C129: =C111*C127 -> 1214.1296 | D129: =D111*D127 -> 735.63959 | E129: =E111*E127 -> 1503.6156 | F129: =F111*F127 -> 525.61196 | G129: =G111*G127 -> 569.78456 | H129: =H111*H127 -> 204.05284 | I129: =I111*I127 -> 339.85932
A130: Total units of increase in units of annual ln(income) (Ages 5-14) — Present value | B130: =B112*B127 -> 1244.27 | C130: =C112*C127 -> 2168.4686 | D130: =D112*D127 -> 1433.4822 | E130: =E112*E127 -> 2721.9703 | F130: =F112*F127 -> 990.64866 | G130: =G112*G127 -> 1110.9306 | H130: =H112*H127 -> 304.75803 | I130: =I112*I127 -> 638.17507
A132: Comparable valuation
A133: Value assigned to increasing ln(consumption) by one unit for one person for one year | B133: {=index('Moral weights and discount rate'!$A$1:$ZW$39,match($A133,'Moral weights and discount rate'!$A$1:$A$39,0),match('Moral weights and discount rate'!$A$17,'Moral weights and discount rate'!$A$1:$ZW1,0))} -> 1.442695 | C133: {=index('Moral weights and discount rate'!$A$1:$ZW$39,match($A133,'Moral weights and discount rate'!$A$1:$A$39,0),match('Moral weights and discount rate'!$A$17,'Moral weights and discount rate'!$A$1:$ZW1,0))} -> 1.442695 | D133: {=index('Moral weights and discount rate'!$A$1:$ZW$39,match($A133,'Moral weights and discount rate'!$A$1:$A$39,0),match('Moral weights and discount rate'!$A$17,'Moral weights and discount rate'!$A$1:$ZW1,0))} -> 1.442695 | E133: {=index('Moral weights and discount rate'!$A$1:$ZW$39,match($A133,'Moral weights and discount rate'!$A$1:$A$39,0),match('Moral weights and discount rate'!$A$17,'Moral weights and discount rate'!$A$1:$ZW1,0))} -> 1.442695 | F133: {=index('Moral weights and discount rate'!$A$1:$ZW$39,match($A133,'Moral weights and discount rate'!$A$1:$A$39,0),match('Moral weights and discount rate'!$A$17,'Moral weights and discount rate'!$A$1:$ZW1,0))} -> 1.442695 | G133: {=index('Moral weights and discount rate'!$A$1:$ZW$39,match($A133,'Moral weights and discount rate'!$A$1:$A$39,0),match('Moral weights and discount rate'!$A$17,'Moral weights and discount rate'!$A$1:$ZW1,0))} -> 1.442695 | H133: {=index('Moral weights and discount rate'!$A$1:$ZW$39,match($A133,'Moral weights and discount rate'!$A$1:$A$39,0),match('Moral weights and discount rate'!$A$17,'Moral weights and discount rate'!$A$1:$ZW1,0))} -> 1.442695 | I133: {=index('Moral weights and discount rate'!$A$1:$ZW$39,match($A133,'Moral weights and discount rate'!$A$1:$A$39,0),match('Moral weights and discount rate'!$A$17,'Moral weights and discount rate'!$A$1:$ZW1,0))} -> 1.442695
A134: Total units of value from development benefits generated, before accounting for leverage and funging | B134: =B133*sum(B129:B130) -> 2745.4338 | C134: =C133*sum(C129:C130) -> 4880.0577 | D134: =D133*sum(D129:D130) -> 3129.3813 | E134: =E133*sum(E129:E130) -> 6096.2318 | F134: =F133*sum(F129:F130) -> 2187.5017 | G134: =G133*sum(G129:G130) -> 2424.7594 | H134: =H133*sum(H129:H130) -> 734.05892 | I134: =I133*sum(I129:I130) -> 1411.0054
...

Sheet GiveDirectly
A1: Cash Transfers - GiveDirectly | B1: Overall
A3: Size of transfer
A4: Arbitrary donation size | B4: 100000
A5: Transfers as a percentage of total cost | B5: 0.83
A6: Total funding available for cash transfers out of hypothetical donation | B6: =B4*B5 -> 83000
A7: Total size of transfer per household (nominal USD) | B7: 1000
A8: Average household size | B8: 4.7
A9: Size of transfer per person (nominal USD) | B9: =B7/B8 -> 212.76596
A11: Investment returns
A12: Percentage of transfers invested | B12: 0.39
A13: Amount invested (nominal USD) | B13: =B9*B12 -> 82.978723
A14: Total increase in consumption per person made possible by funds transferred (nominal USD) | B14: =(1-B12)*B9 -> 129.78723
A15: Return on investment | B15: 0.1
A16: Annual increase in consumption per person made possible by investment returns (nominal USD) | B16: =B13*B15 -> 8.2978723
A18: Present value of transfer
A19: Baseline annual consumption per capita (in nominal USD) | B19: 285.92229
A20: Total immediate increase in ln(consumption) per person made possible by funds transferred | B20: =LN(B19+B14)-LN(B19) -> 0.3742667
A21: Future annual increase in ln(consumption) per person — from returns on investments | B21: =LN(B19+B16)-LN(B19) -> 0.028608278
A22: Discount rate | B22: {=index('Moral weights and discount rate'!1:39,match("Overall discount rate",'Moral weights and discount rate'!A:A,0), match("Active",'Moral weights and discount rate'!1:1,0))} -> 0.04
A23: Duration of investment benefits (in years) | B23: 10
A24: Present value of future increases in ln(consumption) per person (excluding the last year of expected benefits) | B24: =PV(B22,B23-1,-B21) -> 0.21271203
A25: Percent of investment returned when benefits end | B25: 0.2
A26: Present value of ln(consumption) increase in the last year of expected benefits | B26: =(LN(B19+B13*(B15+B25))-LN(B19))/(1+B22)^B23 -> 0.056396595
A27: Present value of all future increases in ln(consumption) | B27: =B26+B24 -> 0.26910863
A28: Total present value of cash transfer in terms of increases in ln(consumption) | B28: =B27+B20 -> 0.64337533
A29: Discount to the benefits of cash from potential negative spillover effects on consumption | B29: 0.05
A30: Total present value of cash transfer accounting for spillovers | B30: =(1-B29)*B28 -> 0.61120656
A31: Total units of increase in ln(consumption) per household | B31: =B30*B8 -> 2.8726708
A33: Number of transfers made | B33: =B6/B7 -> 83
A34: Total units of increase in ln(consumption) | B34: =B31*B33 -> 238.43168
A35: Value assigned to increasing ln(consumption) by one unit for one person for one year | B35: {=index('Moral weights and discount rate'!$A$1:$ZU$39,match($A35,'Moral weights and discount rate'!$A$1:$A$39,0),match('Moral weights and discount rate'!$A$17,'Moral weights and discount rate'!$A$1:$ZU1,0))} -> 1.442695
A37: Total units of value generated | B37: =B34*B35 -> 343.9842
A38: Units of value generated per dollar spent | B38: =B37/B4 -> 0.003439842
A40: Contribution of each outcome to overall cost-effectiveness
A42: Percent of cash's modeled benefits coming from short-term consumption increases | B42: =if(B12<>"", iferror(B20/(B20+B27)," "), "") -> 0.58172373
A43: Percent of cash's modeled benefits coming from investment returns in the future | B43: =if(B12<>"", iferror(B27/(B27+B20)," "), "") -> 0.41827627
A45: Initial cost-effectiveness estimate in multiples of cash transfers | B45: {=B37/index(GiveDirectly!B:B,match("Total units of value generated, after accounting for all adjustments",GiveDirectly!A:A,0))} -> 1.0254307
A47: Supplemental charity-level adjustments — GiveDirectly
A49: Risk of wastage
A50: Double treatment | B50: 0
A51: Ineffective goods | B51: 0
A52: Goods purchased and left in storage until they expire / Cash doesn't reach recipients or is taken back from them inappropriately | B52: 0.03
A53: Total adjustment for risk of wastage | B53: =sum(B50:B52) -> 0.03
A55: Quality of monitoring and evaluation
A56: Misappropriation without monitoring results | B56: 0
A57: False monitoring results | B57: 0
A58: Total adjustment for quality of monitoring and evaluation | B58: =sum(B55:B57) -> 0
A60: Confidence in funds being used for intended purpose
A61: Change of priorities | B61: 0
A62: Non-funding bottlenecks | B62: 0
A63: Within-org fungibility | B63: 0.05
A64: Total adjustment for confidence in funds being used for intended purpose | B64: =sum(B61:B63) -> 0.05
A66: Total adjustment factor | B66: =1-sum(B53,B58,B64) -> 0.92
A68: Results after supplemental charity-level adjustments
A70: Cost-effectiveness in multiples of cash transfers, after supplemental charity-level adjustments | B70: =B45*B66 -> 0.94339623
A72: Supplemental intervention-level adjustments — Cash
A73: Outcomes included in our core model (above)
A74: =IFERROR(__xludf.DUMMYFUNCTION("filter('Supplemental intervention-level'!C:C,'Supplemental intervention-level'!A:A=""Cash"",'Supplemental intervention-level'!D:D=""Explicitly modeled"")"),"Immediate consumption benefit") -> Immediate consumption benefit
A75: =IFERROR(__xludf.DUMMYFUNCTION("""COMPUTED_VALUE"""),"Investment of income increases") -> Investment of income increases
A77: Supplemental intervention-level adjustments
A78: =IFERROR(__xludf.DUMMYFUNCTION("filter('Supplemental intervention-level'!C:C,'Supplemental intervention-level'!A:A=""Cash"",'Supplemental intervention-level'!D:D=""Not explicitly modeled"")"),"Changes in PPP and exchange rates") -> Changes in PPP and exchange rates | B78: {=iferror(if(isblank(A78),"",index('Supplemental intervention-level'!$M:M,match(1,('Supplemental intervention-level'!C:C=A78)*('Supplemental intervention-level'!A:A="Cash"),0))),"Not specified")} -> -0.07
A79: =IFERROR(__xludf.DUMMYFUNCTION("""COMPUTED_VALUE"""),"Developmental effects") -> Developmental effects | B79: {=iferror(if(isblank(A79),"",index('Supplemental intervention-level'!$M:M,match(1,('Supplemental intervention-level'!C:C=A79)*('Supplemental intervention-level'!A:A="Cash"),0))),"Not specified")} -> 0.05
A80: =IFERROR(__xludf.DUMMYFUNCTION("""COMPUTED_VALUE"""),"Reduced morbidity") -> Reduced morbidity | B80: {=iferror(if(isblank(A80),"",index('Supplemental intervention-level'!$M:M,match(1,('Supplemental intervention-level'!C:C=A80)*('Supplemental intervention-level'!A:A="Cash"),0))),"Not specified")} -> 0.04
A81: =IFERROR(__xludf.DUMMYFUNCTION("""COMPUTED_VALUE"""),"Child mortality effects") -> Child mortality effects | B81: {=iferror(if(isblank(A81),"",index('Supplemental intervention-level'!$M:M,match(1,('Supplemental intervention-level'!C:C=A81)*('Supplemental intervention-level'!A:A="Cash"),0))),"Not specified")} -> 0.04
B82: {=iferror(if(isblank(A82),"",index('Supplemental intervention-level'!$M:M,match(1,('Supplemental intervention-level'!C:C=A82)*('Supplemental intervention-level'!A:A="Cash"),0))),"Not specified")}
A83: Total adjustment factor | B83: =1+sum(B77:B82) -> 1.06
A85: Cost-effectiveness after all adjustments
A86: Total units of value generated, after accounting for all adjustments | B86: =B37*(B66)*B83 -> 335.45339
A87: Units of value generated per philanthropic dollar spent, after accounting for all adjustments | B87: =B86/B4 -> 0.0033545339
A89: Cost-effectiveness in multiples of cash transfers, after all adjustments | B89: {=B86/index(GiveDirectly!$B:$B,match("Total units of value generated, after accounting for all adjustments",GiveDirectly!$A:$A,0))} -> 1

Sheet Deworm the World
A1: Deworming - Deworm the World | B1: Kenya | C1: Azad Jammu and Kashmir, Pakistan | D1: Balochistan, Pakistan | E1: Gilgit-Baltistan, Pakistan | F1: Islamabad Capital Territory, Pakistan | G1: Khyber Pakhtunkhwa, Pakistan | H1: Punjab, Pakistan | I1: Sindh, Pakistan | J1: Lagos, Nigeria | K1: Oyo, Nigeria | L1: Ogun, Nigeria | M1: Rivers, Nigeria | N1: Cross River, Nigeria
A5: Long-term income effects from deworming
A7: Treatment effect of deworming on ln(income) in the Miguel and Kremer 2004 study population | B7: 0.109 | C7: 0.109 | D7: 0.109 | E7: 0.109 | F7: 0.109 | G7: 0.109 | H7: 0.109 | I7: 0.109 | J7: 0.109 | K7: 0.109 | L7: 0.109 | M7: 0.109 | N7: 0.109
A8: Coverage in the treatment group (Miguel and Kremer) | B8: 0.75 | C8: 0.75 | D8: 0.75 | E8: 0.75 | F8: 0.75 | G8: 0.75 | H8: 0.75 | I8: 0.75 | J8: 0.75 | K8: 0.75 | L8: 0.75 | M8: 0.75 | N8: 0.75
A9: Coverage in the control group (Miguel and Kremer) | B9: 0.05 | C9: 0.05 | D9: 0.05 | E9: 0.05 | F9: 0.05 | G9: 0.05 | H9: 0.05 | I9: 0.05 | J9: 0.05 | K9: 0.05 | L9: 0.05 | M9: 0.05 | N9: 0.05
A10: Estimated treatment effect on the treated | B10: =B7/((B8-B9)-B9*B7) -> 0.15693615 | C10: =C7/((C8-C9)-C9*C7) -> 0.15693615 | D10: =D7/((D8-D9)-D9*D7) -> 0.15693615 | E10: =E7/((E8-E9)-E9*E7) -> 0.15693615 | F10: =F7/((F8-F9)-F9*F7) -> 0.15693615 | G10: =G7/((G8-G9)-G9*G7) -> 0.15693615 | H10: =H7/((H8-H9)-H9*H7) -> 0.15693615 | I10: =I7/((I8-I9)-I9*I7) -> 0.15693615 | ... N10: =N7/((N8-N9)-N9*N7) -> 0.15693615
A11: Replicability adjustment for deworming | B11: 0.13 | C11: 0.13 | D11: 0.13 | E11: 0.13 | F11: 0.13 | G11: 0.13 | H11: 0.13 | I11: 0.13 | J11: 0.13 | K11: 0.13 | L11: 0.13 | M11: 0.13 | N11: 0.13
A12: Adjustment for years of treatment in Miguel and Kremer vs. years of treatment in charities' programs | B12: 0.9 | C12: 0.9 | D12: 0.9 | E12: 0.9 | F12: 0.9 | G12: 0.9 | H12: 0.9 | I12: 0.9 | J12: 0.9 | K12: 0.9 | L12: 0.9 | M12: 0.9 | N12: 0.9
A13: Additional years of treatment assigned to the treatment group from Miguel and Kremer | B13: 2.41 | C13: 2.41 | D13: 2.41 | E13: 2.41 | F13: 2.41 | G13: 2.41 | H13: 2.41 | I13: 2.41 | J13: 2.41 | K13: 2.41 | L13: 2.41 | M13: 2.41 | N13: 2.41
A14: Estimated annual treatment effect on the treated after adjustments | B14: =B10*B11/B13*B12 -> 0.0076188917 | C14: =C10*C11/C13*C12 -> 0.0076188917 | D14: =D10*D11/D13*D12 -> 0.0076188917 | E14: =E10*E11/E13*E12 -> 0.0076188917 | F14: =F10*F11/F13*F12 -> 0.0076188917 | G14: =G10*G11/G13*G12 -> 0.0076188917 | H14: =H10*H11/H13*H12 -> 0.0076188917 | I14: =I10*I11/I13*I12 -> 0.0076188917 | ... N14: =N10*N11/N13*N12 -> 0.0076188917
A16: Discount rate | B16: {=index('Moral weights and discount rate'!$1:$39,match("Overall discount rate",'Moral weights and discount rate'!$A:$A,0), match("Active",'Moral weights and discount rate'!$1:$1,0))} -> 0.04 | C16: {=index('Moral weights and discount rate'!$1:$39,match("Overall discount rate",'Moral weights and discount rate'!$A:$A,0), match("Active",'Moral weights and discount rate'!$1:$1,0))} -> 0.04 | D16: {=index('Moral weights and discount rate'!$1:$39,match("Overall discount rate",'Moral weights and discount rate'!$A:$A,0), match("Active",'Moral weights and discount rate'!$1:$1,0))} -> 0.04 | E16: {=index('Moral weights and discount rate'!$1:$39,match("Overall discount rate",'Moral weights and discount rate'!$A:$A,0), match("Active",'Moral weights and discount rate'!$1:$1,0))} -> 0.04 | F16: {=index('Moral weights and discount rate'!$1:$39,match("Overall discount rate",'Moral weights and discount rate'!$A:$A,0), match("Active",'Moral weights and discount rate'!$1:$1,0))} -> 0.04 | G16: {=index('Moral weights and discount rate'!$1:$39,match("Overall discount rate",'Moral weights and discount rate'!$A:$A,0), match("Active",'Moral weights and discount rate'!$1:$1,0))} -> 0.04 | H16: {=index('Moral weights and discount rate'!$1:$39,match("Overall discount rate",'Moral weights and discount rate'!$A:$A,0), match("Active",'Moral weights and discount rate'!$1:$1,0))} -> 0.04 | I16: {=index('Moral weights and discount rate'!$1:$39,match("Overall discount rate",'Moral weights and discount rate'!$A:$A,0), match("Active",'Moral weights and discount rate'!$1:$1,0))} -> 0.04 | ... N16: {=index('Moral weights and discount rate'!$1:$39,match("Overall discount rate",'Moral weights and discount rate'!$A:$A,0), match("Active",'Moral weights and discount rate'!$1:$1,0))} -> 0.04
A17: Average number of years between deworming and the beginning of long-term benefits | B17: 8 | C17: 8 | D17: 8 | E17: 8 | F17: 8 | G17: 8 | H17: 8 | I17: 8 | J17: 8 | K17: 8 | L17: 8 | M17: 8 | N17: 8
A18: Benefit on one year's income (discounted back because of delay between deworming and working for income) | B18: =B14/(1+B16)^B17 -> 0.0055670496 | C18: =C14/(1+C16)^C17 -> 0.0055670496 | D18: =D14/(1+D16)^D17 -> 0.0055670496 | E18: =E14/(1+E16)^E17 -> 0.0055670496 | F18: =F14/(1+F16)^F17 -> 0.0055670496 | G18: =G14/(1+G16)^G17 -> 0.0055670496 | H18: =H14/(1+H16)^H17 -> 0.0055670496 | I18: =I14/(1+I16)^I17 -> 0.0055670496 | ... N18: =N14/(1+N16)^N17 -> 0.0055670496
A19: Duration of long-term benefits of deworming (in years) | B19: 40 | C19: 40 | D19: 40 | E19: 40 | F19: 40 | G19: 40 | H19: 40 | I19: 40 | J19: 40 | K19: 40 | L19: 40 | M19: 40 | N19: 40
A21: Present value of lifetime benefits from a year of deworming (before decay adjustment, in terms of increases in ln(income)) | B21: =pv(B16,B19,-B18,,1) -> 0.11459485 | C21: =pv(C16,C19,-C18,,1) -> 0.11459485 | D21: =pv(D16,D19,-D18,,1) -> 0.11459485 | E21: =pv(E16,E19,-E18,,1) -> 0.11459485 | F21: =pv(F16,F19,-F18,,1) -> 0.11459485 | G21: =pv(G16,G19,-G18,,1) -> 0.11459485 | H21: =pv(H16,H19,-H18,,1) -> 0.11459485 | I21: =pv(I16,I19,-I18,,1) -> 0.11459485 | ... N21: =pv(N16,N19,-N18,,1) -> 0.11459485
A22: Adjustment for benefits decaying over time | B22: -0.1 | C22: -0.1 | D22: -0.1 | E22: -0.1 | F22: -0.1 | G22: -0.1 | H22: -0.1 | I22: -0.1 | J22: -0.1 | K22: -0.1 | L22: -0.1 | M22: -0.1 | N22: -0.1
A23: Present value of lifetime benefits from a year of deworming (after decay adjustment, in terms of increases in ln(income)) | B23: =B21*(1+B22) -> 0.10313536 | C23: =C21*(1+C22) -> 0.10313536 | D23: =D21*(1+D22) -> 0.10313536 | E23: =E21*(1+E22) -> 0.10313536 | F23: =F21*(1+F22) -> 0.10313536 | G23: =G21*(1+G22) -> 0.10313536 | H23: =H21*(1+H22) -> 0.10313536 | I23: =I21*(1+I22) -> 0.10313536 | ... N23: =N21*(1+N22) -> 0.10313536
A25: Multiplier for resource sharing within households | B25: 2 | C25: 2 | D25: 2 | E25: 2 | F25: 2 | G25: 2 | H25: 2 | I25: 2 | J25: 2 | K25: 2 | L25: 2 | M25: 2 | N25: 2
A27: Adjusted long-term benefits per year of deworming per person assigned to treatment in terms of ln(consumption) | B27: =B25*B23 -> 0.20627072 | C27: =C25*C23 -> 0.20627072 | D27: =D25*D23 -> 0.20627072 | E27: =E25*E23 -> 0.20627072 | F27: =F25*F23 -> 0.20627072 | G27: =G25*G23 -> 0.20627072 | H27: =H25*H23 -> 0.20627072 | I27: =I25*I23 -> 0.20627072 | ... N27: =N25*N23 -> 0.20627072
A29: Funding allocation
A31: Percentage of total costs covered by Deworm the World | B31: 0.6082843 | C31: 0.4014779 | D31: 0.4014779 | E31: 0.4014779 | F31: 0.4014779 | G31: 0.4014779 | H31: 0.4014779 | I31: 0.4014779 | J31: 0.6735345 | K31: 0.6084396 | L31: 0.62703532 | M31: 0.6220757 | N31: 0.58940161
A32: Percentage of total costs covered by other philanthropic actors | B32: 0.0234169 | C32: 0.2573664 | D32: 0.2573664 | E32: 0.2573664 | F32: 0.2573664 | G32: 0.2573664 | H32: 0.2573664 | I32: 0.2573664 | J32: 0 | K32: 0.0090019 | L32: 0 | M32: 0.023113655 | N32: 0.035189769
A33: Percentage of total costs covered by domestic governments (financial costs) | B33: 0.009947 | C33: 0 | D33: 0 | E33: 0 | F33: 0 | G33: 0 | H33: 0 | I33: 0 | J33: 0 | K33: 0 | L33: 0 | M33: 0 | N33: 0.0015079661
A34: Percentage of total costs covered by domestic governments (in-kind costs) | B34: 0.3 | C34: 0.3 | D34: 0.3 | E34: 0.3 | F34: 0.3 | G34: 0.3 | H34: 0.3 | I34: 0.3 | J34: 0.2999999 | K34: 0.3000001 | L34: 0.3 | M34: 0.3 | N34: 0.3
A35: Percentage of total costs covered by drug donations | B35: 0.0583518 | C35: 0.0411558 | D35: 0.0411558 | E35: 0.0411558 | F35: 0.0411558 | G35: 0.0411558 | H35: 0.0411558 | I35: 0.0411558 | J35: 0.0264655 | K35: 0.0825584 | L35: 0.072964622 | M35: 0.054810638 | N35: 0.073900651
A37: Number of children dewormed per year
A39: Donation to Deworm the World (arbitrary size) | B39: 100000 | C39: 100000 | D39: 100000 | E39: 100000 | F39: 100000 | G39: 100000 | H39: 100000 | I39: 100000 | J39: 100000 | K39: 100000 | L39: 100000 | M39: 100000 | N39: 100000
A40: Total spending by all contributors | B40: =B39/B31 -> 164396.81 | C40: =C39/C31 -> 249079.71 | D40: =D39/D31 -> 249079.71 | E40: =E39/E31 -> 249079.71 | F40: =F39/F31 -> 249079.71 | G40: =G39/G31 -> 249079.71 | H40: =H39/H31 -> 249079.71 | I40: =I39/I31 -> 249079.71 | ... N40: =N39/N31 -> 169663.6
A41: Proportion of deworming going to children — DtW | B41: 1 | C41: 1 | D41: 1 | E41: 1 | F41: 1 | G41: 1 | H41: 1 | I41: 1 | J41: 1 | K41: 1 | L41: 1 | M41: 1 | N41: 1
A42: Worm burden adjustment — DtW | B42: 0.20523514 | C42: 0.0355752 | D42: 0.0128676 | E42: 0.1264055 | F42: 0.0075692 | G42: 0.0531569 | H42: 0.0075692 | I42: 0.0128676 | J42: 0.070053262 | K42: 0.11076949 | L42: 0.20523514 | M42: 0.083261082 | N42: 0.12338307
A43: Present value of lifetime benefits from a year of deworming — in terms of increases in ln(consumption) — DtW | B43: =B27*B41*B42 -> 0.042334002 | C43: =C27*C41*C42 -> 0.0073381223 | D43: =D27*D41*D42 -> 0.0026542092 | E43: =E27*E41*E42 -> 0.026073754 | F43: =F27*F41*F42 -> 0.0015613044 | G43: =G27*G41*G42 -> 0.010964712 | H43: =H27*H41*H42 -> 0.0015613044 | I43: =I27*I41*I42 -> 0.0026542092 | ... N43: =N27*N41*N42 -> 0.025450316
A44: Value assigned to increasing ln(consumption) by one unit for one person for one year | B44: {=index('Moral weights and discount rate'!$A$1:$ZU$39,match($A44,'Moral weights and discount rate'!$A$1:$A$39,0),match('Moral weights and discount rate'!$A$17,'Moral weights and discount rate'!$A$1:$ZU1,0))} -> 1.442695 | C44: {=index('Moral weights and discount rate'!$A$1:$ZU$39,match($A44,'Moral weights and discount rate'!$A$1:$A$39,0),match('Moral weights and discount rate'!$A$17,'Moral weights and discount rate'!$A$1:$ZU1,0))} -> 1.442695 | D44: {=index('Moral weights and discount rate'!$A$1:$ZU$39,match($A44,'Moral weights and discount rate'!$A$1:$A$39,0),match('Moral weights and discount rate'!$A$17,'Moral weights and discount rate'!$A$1:$ZU1,0))} -> 1.442695 | E44: {=index('Moral weights and discount rate'!$A$1:$ZU$39,match($A44,'Moral weights and discount rate'!$A$1:$A$39,0),match('Moral weights and discount rate'!$A$17,'Moral weights and discount rate'!$A$1:$ZU1,0))} -> 1.442695 | F44: {=index('Moral weights and discount rate'!$A$1:$ZU$39,match($A44,'Moral weights and discount rate'!$A$1:$A$39,0),match('Moral weights and discount rate'!$A$17,'Moral weights and discount rate'!$A$1:$ZU1,0))} -> 1.442695 | G44: {=index('Moral weights and discount rate'!$A$1:$ZU$39,match($A44,'Moral weights and discount rate'!$A$1:$A$39,0),match('Moral weights and discount rate'!$A$17,'Moral weights and discount rate'!$A$1:$ZU1,0))} -> 1.442695 | H44: {=index('Moral weights and discount rate'!$A$1:$ZU$39,match($A44,'Moral weights and discount rate'!$A$1:$A$39,0),match('Moral weights and discount rate'!$A$17,'Moral weights and discount rate'!$A$1:$ZU1,0))} -> 1.442695 | I44: {=index('Moral weights and discount rate'!$A$1:$ZU$39,match($A44,'Moral weights and discount rate'!$A$1:$A$39,0),match('Moral weights and discount rate'!$A$17,'Moral weights and discount rate'!$A$1:$ZU1,0))} -> 1.442695 | ... N44: {=index('Moral weights and discount rate'!$A$1:$ZU$39,match($A44,'Moral weights and discount rate'!$A$1:$A$39,0),match('Moral weights and discount rate'!$A$17,'Moral weights and discount rate'!$A$1:$ZU1,0))} -> 1.442695
A45: Units of value from each year of deworming — DtW | B45: =(B43*B44) -> 0.061075054 | C45: =(C43*C44) -> 0.010586673 | D45: =(D43*D44) -> 0.0038292144 | E45: =(E43*E44) -> 0.037616476 | F45: =(F43*F44) -> 0.0022524861 | G45: =(G43*G44) -> 0.015818736 | H45: =(H43*H44) -> 0.0022524861 | I45: =(I43*I44) -> 0.0038292144 | ... N45: =(N43*N44) -> 0.036717045
A46: Cost per child dewormed (per year) — DtW | B46: 0.64757 | C46: 0.74247 | D46: 0.74247 | E46: 0.74247 | F46: 0.74247 | G46: 0.74247 | H46: 0.74247 | I46: 0.74247 | J46: 0.75506 | K46: 0.78975 | L46: 1.5182461 | M46: 0.74800772 | N46: 1.1612276
A47: Total number of children dewormed (per year) — DtW | B47: =B40/B46 -> 253867.25 | C47: =C40/C46 -> 335474.45 | D47: =D40/D46 -> 335474.45 | E47: =E40/E46 -> 335474.45 | F47: =F40/F46 -> 335474.45 | G47: =G40/G46 -> 335474.45 | H47: =H40/H46 -> 335474.45 | I47: =I40/I46 -> 335474.45 | ... N47: =N40/N46 -> 146107.1
A49: Intuition check
A51: Aggregate adjustment to Miguel and Kremer development effect — DtW | B51: =product(B11:B12,B42) -> 0.024012512 | C51: =product(C11:C12,C42) -> 0.0041622984 | D51: =product(D11:D12,D42) -> 0.0015055092 | E51: =product(E11:E12,E42) -> 0.014789444 | F51: =product(F11:F12,F42) -> 0.0008855964 | G51: =product(G11:G12,G42) -> 0.0062193573 | H51: =product(H11:H12,H42) -> 0.0008855964 | I51: =product(I11:I12,I42) -> 0.0015055092 | ... N51: =product(N11:N12,N42) -> 0.01443582
A53: Initial results
A55: =A43 -> Present value of lifetime benefits from a year of deworming — in terms of increases in ln(consumption) — DtW | B55: =B43 -> 0.042334002 | C55: =C43 -> 0.0073381223 | D55: =D43 -> 0.0026542092 | E55: =E43 -> 0.026073754 | F55: =F43 -> 0.0015613044 | G55: =G43 -> 0.010964712 | H55: =H43 -> 0.0015613044 | ... N55: =N43 -> 0.025450316
A56: =A44 -> Value assigned to increasing ln(consumption) by one unit for one person for one year | B56: =B44 -> 1.442695 | C56: =C44 -> 1.442695 | D56: =D44 -> 1.442695 | E56: =E44 -> 1.442695 | F56: =F44 -> 1.442695 | G56: =G44 -> 1.442695 | H56: =H44 -> 1.442695 | ... N56: =N44 -> 1.442695
A57: =A47 -> Total number of children dewormed (per year) — DtW | B57: =B47 -> 253867.25 | C57: =C47 -> 335474.45 | D57: =D47 -> 335474.45 | E57: =E47 -> 335474.45 | F57: =F47 -> 335474.45 | G57: =G47 -> 335474.45 | H57: =H47 -> 335474.45 | ... N57: =N47 -> 146107.1
A58: Total units of value generated | B58: =product(B55:B57) -> 15504.956 | C58: =product(C55:C57) -> 3551.5581 | D58: =product(D55:D57) -> 1284.6036 | E58: =product(E55:E57) -> 12619.366 | F58: =product(F55:F57) -> 755.65152 | G58: =product(G55:G57) -> 5306.7817 | H58: =product(H55:H57) -> 755.65152 | I58: =product(I55:I57) -> 1284.6036 | ... N58: =product(N55:N57) -> 5364.6211
A59: Units of value generated per dollar spent | B59: =B58/B40 -> 0.094314212 | C59: =C58/C40 -> 0.014258721 | D59: =D58/D40 -> 0.0051573995 | E59: =E58/E40 -> 0.050663967 | F59: =F58/F40 -> 0.0030337739 | G59: =G58/G40 -> 0.021305556 | H59: =H58/H40 -> 0.0030337739 | I59: =I58/I40 -> 0.0051573995 | ... N59: =N58/N40 -> 0.031619163
A61: Initial cost-effectiveness estimate in multiples of cash transfers | B61: {=B59/index(GiveDirectly!$B:$B,match("Units of value generated per philanthropic dollar spent, after accounting for all adjustments",GiveDirectly!$A:$A,0))} -> 28.115444 | C61: {=C59/index(GiveDirectly!$B:$B,match("Units of value generated per philanthropic dollar spent, after accounting for all adjustments",GiveDirectly!$A:$A,0))} -> 4.2505818 | D61: {=D59/index(GiveDirectly!$B:$B,match("Units of value generated per philanthropic dollar spent, after accounting for all adjustments",GiveDirectly!$A:$A,0))} -> 1.5374414 | E61: {=E59/index(GiveDirectly!$B:$B,match("Units of value generated per philanthropic dollar spent, after accounting for all adjustments",GiveDirectly!$A:$A,0))} -> 15.103131 | F61: {=F59/index(GiveDirectly!$B:$B,match("Units of value generated per philanthropic dollar spent, after accounting for all adjustments",GiveDirectly!$A:$A,0))} -> 0.90438013 | G61: {=G59/index(GiveDirectly!$B:$B,match("Units of value generated per philanthropic dollar spent, after accounting for all adjustments",GiveDirectly!$A:$A,0))} -> 6.3512715 | H61: {=H59/index(GiveDirectly!$B:$B,match("Units of value generated per philanthropic dollar spent, after accounting for all adjustments",GiveDirectly!$A:$A,0))} -> 0.90438013 | I61: {=I59/index(GiveDirectly!$B:$B,match("Units of value generated per philanthropic dollar spent, after accounting for all adjustments",GiveDirectly!$A:$A,0))} -> 1.5374414 | ... N61: {=N59/index(GiveDirectly!$B:$B,match("Units of value generated per philanthropic dollar spent, after accounting for all adjustments",GiveDirectly!$A:$A,0))} -> 9.4257991
A63: Supplemental charity-level adjustments — Deworm the World
A65: Risk of wastage
A66: Double treatment | B66: 0 | C66: 0 | D66: 0 | E66: 0 | F66: 0 | G66: 0 | H66: 0 | I66: 0 | J66: 0 | K66: 0 | L66: 0 | M66: 0 | N66: 0
A67: Ineffective goods | B67: 0.02 | C67: 0.02 | D67: 0.02 | E67: 0.02 | F67: 0.02 | G67: 0.02 | H67: 0.02 | I67: 0.02 | J67: 0.02 | K67: 0.02 | L67: 0.02 | M67: 0.02 | N67: 0.02
A68: Goods purchased and left in storage until they expire / Cash doesn't reach recipients or is taken back from them inappropriately | B68: 0 | C68: 0 | D68: 0 | E68: 0 | F68: 0 | G68: 0 | H68: 0 | I68: 0 | J68: 0 | K68: 0 | L68: 0 | M68: 0 | N68: 0
A69: Total adjustment for risk of wastage | B69: =SUM(B66:B68) -> 0.02 | C69: =SUM(C66:C68) -> 0.02 | D69: =SUM(D66:D68) -> 0.02 | E69: =SUM(E66:E68) -> 0.02 | F69: =SUM(F66:F68) -> 0.02 | G69: =SUM(G66:G68) -> 0.02 | H69: =SUM(H66:H68) -> 0.02 | I69: =SUM(I66:I68) -> 0.02 | ... N69: =SUM(N66:N68) -> 0.02
A71: Quality of monitoring and evaluation
A72: Misappropriation without monitoring results | B72: 0.01 | C72: 0.01 | D72: 0.01 | E72: 0.01 | F72: 0.01 | G72: 0.01 | H72: 0.01 | I72: 0.01 | J72: 0.05 | K72: 0.05 | L72: 0.05 | M72: 0.05 | N72: 0.05
A73: False monitoring results | B73: 0.01 | C73: 0.01 | D73: 0.01 | E73: 0.01 | F73: 0.01 | G73: 0.01 | H73: 0.01 | I73: 0.01 | J73: 0.01 | K73: 0.01 | L73: 0.01 | M73: 0.01 | N73: 0.01
A74: Total adjustment for quality of monitoring and evaluation | B74: =sum(B71:B73) -> 0.02 | C74: =sum(C71:C73) -> 0.02 | D74: =sum(D71:D73) -> 0.02 | E74: =sum(E71:E73) -> 0.02 | F74: =sum(F71:F73) -> 0.02 | G74: =sum(G71:G73) -> 0.02 | H74: =sum(H71:H73) -> 0.02 | I74: =sum(I71:I73) -> 0.02 | ... N74: =sum(N71:N73) -> 0.06
A76: Confidence in funds being used for intended purpose
A77: Change of priorities | B77: 0 | C77: 0 | D77: 0 | E77: 0 | F77: 0 | G77: 0 | H77: 0 | I77: 0 | J77: 0 | K77: 0 | L77: 0 | M77: 0 | N77: 0
A78: Non-funding bottlenecks | B78: 0 | C78: 0 | D78: 0 | E78: 0 | F78: 0 | G78: 0 | H78: 0 | I78: 0 | J78: 0 | K78: 0 | L78: 0 | M78: 0 | N78: 0
A79: Within-org fungibility | B79: 0.05 | C79: 0.05 | D79: 0.05 | E79: 0.05 | F79: 0.05 | G79: 0.05 | H79: 0.05 | I79: 0.05 | J79: 0.05 | K79: 0.05 | L79: 0.05 | M79: 0.05 | N79: 0.05
A80: Total adjustment for confidence in funds being used for intended purpose | B80: =sum(B77:B79) -> 0.05 | C80: =sum(C77:C79) -> 0.05 | D80: =sum(D77:D79) -> 0.05 | E80: =sum(E77:E79) -> 0.05 | F80: =sum(F77:F79) -> 0.05 | G80: =sum(G77:G79) -> 0.05 | H80: =sum(H77:H79) -> 0.05 | I80: =sum(I77:I79) -> 0.05 | ... N80: =sum(N77:N79) -> 0.05
A82: Total adjustment factor | B82: =1-sum(B69,B74,B80) -> 0.91 | C82: =1-sum(C69,C74,C80) -> 0.91 | D82: =1-sum(D69,D74,D80) -> 0.91 | E82: =1-sum(E69,E74,E80) -> 0.91 | F82: =1-sum(F69,F74,F80) -> 0.91 | G82: =1-sum(G69,G74,G80) -> 0.91 | H82: =1-sum(H69,H74,H80) -> 0.91 | I82: =1-sum(I69,I74,I80) -> 0.91 | ... N82: =1-sum(N69,N74,N80) -> 0.87
A84: Results after supplemental charity-level adjustments
A86: Total units of value generated | B86: =B58*B82 -> 14109.51 | C86: =C58*C82 -> 3231.9179 | D86: =D58*D82 -> 1168.9893 | E86: =E58*E82 -> 11483.623 | F86: =F58*F82 -> 687.64288 | G86: =G58*G82 -> 4829.1714 | H86: =H58*H82 -> 687.64288 | I86: =I58*I82 -> 1168.9893 | ... N86: =N58*N82 -> 4667.2203
A87: Units of value per dollar spent | B87: =B86/B40 -> 0.085825933 | C87: =C86/C40 -> 0.012975436 | D87: =D86/D40 -> 0.0046932336 | E87: =E86/E40 -> 0.04610421 | F87: =F86/F40 -> 0.0027607342 | G87: =G86/G40 -> 0.019388056 | H87: =H86/H40 -> 0.0027607342 | I87: =I86/I40 -> 0.0046932336 | ... N87: =N86/N40 -> 0.027508672
A88: Cost-effectiveness in multiples of cash transfers, after supplemental charity-level adjustments | B88: {=B87/index(GiveDirectly!$B:$B,match("Units of value generated per philanthropic dollar spent, after accounting for all adjustments",GiveDirectly!$A:$A,0))} -> 25.585054 | C88: {=C87/index(GiveDirectly!$B:$B,match("Units of value generated per philanthropic dollar spent, after accounting for all adjustments",GiveDirectly!$A:$A,0))} -> 3.8680295 | D88: {=D87/index(GiveDirectly!$B:$B,match("Units of value generated per philanthropic dollar spent, after accounting for all adjustments",GiveDirectly!$A:$A,0))} -> 1.3990717 | E88: {=E87/index(GiveDirectly!$B:$B,match("Units of value generated per philanthropic dollar spent, after accounting for all adjustments",GiveDirectly!$A:$A,0))} -> 13.74385 | F88: {=F87/index(GiveDirectly!$B:$B,match("Units of value generated per philanthropic dollar spent, after accounting for all adjustments",GiveDirectly!$A:$A,0))} -> 0.82298592 | G88: {=G87/index(GiveDirectly!$B:$B,match("Units of value generated per philanthropic dollar spent, after accounting for all adjustments",GiveDirectly!$A:$A,0))} -> 5.7796571 | H88: {=H87/index(GiveDirectly!$B:$B,match("Units of value generated per philanthropic dollar spent, after accounting for all adjustments",GiveDirectly!$A:$A,0))} -> 0.82298592 | I88: {=I87/index(GiveDirectly!$B:$B,match("Units of value generated per philanthropic dollar spent, after accounting for all adjustments",GiveDirectly!$A:$A,0))} -> 1.3990717 | ... N88: {=N87/index(GiveDirectly!$B:$B,match("Units of value generated per philanthropic dollar spent, after accounting for all adjustments",GiveDirectly!$A:$A,0))} -> 8.2004453
A90: Supplemental intervention-level adjustments — Deworming
A91: Outcomes included in our core model (above)
A92: =IFERROR(__xludf.DUMMYFUNCTION("filter('Supplemental intervention-level'!C:C,'Supplemental intervention-level'!A:A=""Deworming"",'Supplemental intervention-level'!D:D=""Explicitly modeled"")"),"Developmental effects") -> Developmental effects
A94: Supplemental intervention-level adjustments
A95: =IFERROR(__xludf.DUMMYFUNCTION("filter('Supplemental intervention-level'!C:C,'Supplemental intervention-level'!A:A=""Deworming"",'Supplemental intervention-level'!D:D=""Not explicitly modeled"",'Supplemental intervention-level'!B:B=""Unlimit HealthDTWI"")"),"Direct health effects") -> Direct health effects | B95: {=iferror(if(isblank($A95),"",index('Supplemental intervention-level'!$M:$M,match(1,('Supplemental intervention-level'!$C:$C=$A95)*('Supplemental intervention-level'!$A:$A="Deworming"),0))),"Not specified")} -> 0.008 | C95: {=iferror(if(isblank($A95),"",index('Supplemental intervention-level'!$M:$M,match(1,('Supplemental intervention-level'!$C:$C=$A95)*('Supplemental intervention-level'!$A:$A="Deworming"),0))),"Not specified")} -> 0.008 | D95: {=iferror(if(isblank($A95),"",index('Supplemental intervention-level'!$M:$M,match(1,('Supplemental intervention-level'!$C:$C=$A95)*('Supplemental intervention-level'!$A:$A="Deworming"),0))),"Not specified")} -> 0.008 | E95: {=iferror(if(isblank($A95),"",index('Supplemental intervention-level'!$M:$M,match(1,('Supplemental intervention-level'!$C:$C=$A95)*('Supplemental intervention-level'!$A:$A="Deworming"),0))),"Not specified")} -> 0.008 | F95: {=iferror(if(isblank($A95),"",index('Supplemental intervention-level'!$M:$M,match(1,('Supplemental intervention-level'!$C:$C=$A95)*('Supplemental intervention-level'!$A:$A="Deworming"),0))),"Not specified")} -> 0.008 | G95: {=iferror(if(isblank($A95),"",index('Supplemental intervention-level'!$M:$M,match(1,('Supplemental intervention-level'!$C:$C=$A95)*('Supplemental intervention-level'!$A:$A="Deworming"),0))),"Not specified")} -> 0.008 | H95: {=iferror(if(isblank($A95),"",index('Supplemental intervention-level'!$M:$M,match(1,('Supplemental intervention-level'!$C:$C=$A95)*('Supplemental intervention-level'!$A:$A="Deworming"),0))),"Not specified")} -> 0.008 | I95: {=iferror(if(isblank($A95),"",index('Supplemental intervention-level'!$M:$M,match(1,('Supplemental intervention-level'!$C:$C=$A95)*('Supplemental intervention-level'!$A:$A="Deworming"),0))),"Not specified")} -> 0.008 | ... N95: {=iferror(if(isblank($A95),"",index('Supplemental intervention-level'!$M:$M,match(1,('Supplemental intervention-level'!$C:$C=$A95)*('Supplemental intervention-level'!$A:$A="Deworming"),0))),"Not specified")} -> 0.008
A96: =IFERROR(__xludf.DUMMYFUNCTION("""COMPUTED_VALUE"""),"HIV reduction") -> HIV reduction | B96: {=iferror(if(isblank($A96),"",index('Supplemental intervention-level'!$M:$M,match(1,('Supplemental intervention-level'!$C:$C=$A96)*('Supplemental intervention-level'!$A:$A="Deworming"),0))),"Not specified")} -> 0.06 | C96: {=iferror(if(isblank($A96),"",index('Supplemental intervention-level'!$M:$M,match(1,('Supplemental intervention-level'!$C:$C=$A96)*('Supplemental intervention-level'!$A:$A="Deworming"),0))),"Not specified")} -> 0.06 | D96: {=iferror(if(isblank($A96),"",index('Supplemental intervention-level'!$M:$M,match(1,('Supplemental intervention-level'!$C:$C=$A96)*('Supplemental intervention-level'!$A:$A="Deworming"),0))),"Not specified")} -> 0.06 | E96: {=iferror(if(isblank($A96),"",index('Supplemental intervention-level'!$M:$M,match(1,('Supplemental intervention-level'!$C:$C=$A96)*('Supplemental intervention-level'!$A:$A="Deworming"),0))),"Not specified")} -> 0.06 | F96: {=iferror(if(isblank($A96),"",index('Supplemental intervention-level'!$M:$M,match(1,('Supplemental intervention-level'!$C:$C=$A96)*('Supplemental intervention-level'!$A:$A="Deworming"),0))),"Not specified")} -> 0.06 | G96: {=iferror(if(isblank($A96),"",index('Supplemental intervention-level'!$M:$M,match(1,('Supplemental intervention-level'!$C:$C=$A96)*('Supplemental intervention-level'!$A:$A="Deworming"),0))),"Not specified")} -> 0.06 | H96: {=iferror(if(isblank($A96),"",index('Supplemental intervention-level'!$M:$M,match(1,('Supplemental intervention-level'!$C:$C=$A96)*('Supplemental intervention-level'!$A:$A="Deworming"),0))),"Not specified")} -> 0.06 | I96: {=iferror(if(isblank($A96),"",index('Supplemental intervention-level'!$M:$M,match(1,('Supplemental intervention-level'!$C:$C=$A96)*('Supplemental intervention-level'!$A:$A="Deworming"),0))),"Not specified")} -> 0.06 | ... N96: {=iferror(if(isblank($A96),"",index('Supplemental intervention-level'!$M:$M,match(1,('Supplemental intervention-level'!$C:$C=$A96)*('Supplemental intervention-level'!$A:$A="Deworming"),0))),"Not specified")} -> 0.06
A97: =IFERROR(__xludf.DUMMYFUNCTION("""COMPUTED_VALUE"""),"Possible increases in diseases of affluence (harms of deworming)") -> Possible increases in diseases of affluence (harms of deworming) | B97: {=iferror(if(isblank($A97),"",index('Supplemental intervention-level'!$M:$M,match(1,('Supplemental intervention-level'!$C:$C=$A97)*('Supplemental intervention-level'!$A:$A="Deworming"),0))),"Not specified")} -> -0.025 | C97: {=iferror(if(isblank($A97),"",index('Supplemental intervention-level'!$M:$M,match(1,('Supplemental intervention-level'!$C:$C=$A97)*('Supplemental intervention-level'!$A:$A="Deworming"),0))),"Not specified")} -> -0.025 | D97: {=iferror(if(isblank($A97),"",index('Supplemental intervention-level'!$M:$M,match(1,('Supplemental intervention-level'!$C:$C=$A97)*('Supplemental intervention-level'!$A:$A="Deworming"),0))),"Not specified")} -> -0.025 | E97: {=iferror(if(isblank($A97),"",index('Supplemental intervention-level'!$M:$M,match(1,('Supplemental intervention-level'!$C:$C=$A97)*('Supplemental intervention-level'!$A:$A="Deworming"),0))),"Not specified")} -> -0.025 | F97: {=iferror(if(isblank($A97),"",index('Supplemental intervention-level'!$M:$M,match(1,('Supplemental intervention-level'!$C:$C=$A97)*('Supplemental intervention-level'!$A:$A="Deworming"),0))),"Not specified")} -> -0.025 | G97: {=iferror(if(isblank($A97),"",index('Supplemental intervention-level'!$M:$M,match(1,('Supplemental intervention-level'!$C:$C=$A97)*('Supplemental intervention-level'!$A:$A="Deworming"),0))),"Not specified")} -> -0.025 | H97: {=iferror(if(isblank($A97),"",index('Supplemental intervention-level'!$M:$M,match(1,('Supplemental intervention-level'!$C:$C=$A97)*('Supplemental intervention-level'!$A:$A="Deworming"),0))),"Not specified")} -> -0.025 | I97: {=iferror(if(isblank($A97),"",index('Supplemental intervention-level'!$M:$M,match(1,('Supplemental intervention-level'!$C:$C=$A97)*('Supplemental intervention-level'!$A:$A="Deworming"),0))),"Not specified")} -> -0.025 | ... N97: {=iferror(if(isblank($A97),"",index('Supplemental intervention-level'!$M:$M,match(1,('Supplemental intervention-level'!$C:$C=$A97)*('Supplemental intervention-level'!$A:$A="Deworming"),0))),"Not specified")} -> -0.025
A98: =IFERROR(__xludf.DUMMYFUNCTION("""COMPUTED_VALUE"""),"Averted mortality") -> Averted mortality | B98: {=iferror(if(isblank($A98),"",index('Supplemental intervention-level'!$M:$M,match(1,('Supplemental intervention-level'!$C:$C=$A98)*('Supplemental intervention-level'!$A:$A="Deworming"),0))),"Not specified")} -> 0.035 | C98: {=iferror(if(isblank($A98),"",index('Supplemental intervention-level'!$M:$M,match(1,('Supplemental intervention-level'!$C:$C=$A98)*('Supplemental intervention-level'!$A:$A="Deworming"),0))),"Not specified")} -> 0.035 | D98: {=iferror(if(isblank($A98),"",index('Supplemental intervention-level'!$M:$M,match(1,('Supplemental intervention-level'!$C:$C=$A98)*('Supplemental intervention-level'!$A:$A="Deworming"),0))),"Not specified")} -> 0.035 | E98: {=iferror(if(isblank($A98),"",index('Supplemental intervention-level'!$M:$M,match(1,('Supplemental intervention-level'!$C:$C=$A98)*('Supplemental intervention-level'!$A:$A="Deworming"),0))),"Not specified")} -> 0.035 | F98: {=iferror(if(isblank($A98),"",index('Supplemental intervention-level'!$M:$M,match(1,('Supplemental intervention-level'!$C:$C=$A98)*('Supplemental intervention-level'!$A:$A="Deworming"),0))),"Not specified")} -> 0.035 | G98: {=iferror(if(isblank($A98),"",index('Supplemental intervention-level'!$M:$M,match(1,('Supplemental intervention-level'!$C:$C=$A98)*('Supplemental intervention-level'!$A:$A="Deworming"),0))),"Not specified")} -> 0.035 | H98: {=iferror(if(isblank($A98),"",index('Supplemental intervention-level'!$M:$M,match(1,('Supplemental intervention-level'!$C:$C=$A98)*('Supplemental intervention-level'!$A:$A="Deworming"),0))),"Not specified")} -> 0.035 | I98: {=iferror(if(isblank($A98),"",index('Supplemental intervention-level'!$M:$M,match(1,('Supplemental intervention-level'!$C:$C=$A98)*('Supplemental intervention-level'!$A:$A="Deworming"),0))),"Not specified")} -> 0.035 | ... N98: {=iferror(if(isblank($A98),"",index('Supplemental intervention-level'!$M:$M,match(1,('Supplemental intervention-level'!$C:$C=$A98)*('Supplemental intervention-level'!$A:$A="Deworming"),0))),"Not specified")} -> 0.035
A99: =IFERROR(__xludf.DUMMYFUNCTION("""COMPUTED_VALUE"""),"Short-term anemia effects") -> Short-term anemia effects | B99: {=iferror(if(isblank($A99),"",index('Supplemental intervention-level'!$M:$M,match(1,('Supplemental intervention-level'!$C:$C=$A99)*('Supplemental intervention-level'!$A:$A="Deworming"),0))),"Not specified")} -> 0.09 | C99: {=iferror(if(isblank($A99),"",index('Supplemental intervention-level'!$M:$M,match(1,('Supplemental intervention-level'!$C:$C=$A99)*('Supplemental intervention-level'!$A:$A="Deworming"),0))),"Not specified")} -> 0.09 | D99: {=iferror(if(isblank($A99),"",index('Supplemental intervention-level'!$M:$M,match(1,('Supplemental intervention-level'!$C:$C=$A99)*('Supplemental intervention-level'!$A:$A="Deworming"),0))),"Not specified")} -> 0.09 | E99: {=iferror(if(isblank($A99),"",index('Supplemental intervention-level'!$M:$M,match(1,('Supplemental intervention-level'!$C:$C=$A99)*('Supplemental intervention-level'!$A:$A="Deworming"),0))),"Not specified")} -> 0.09 | F99: {=iferror(if(isblank($A99),"",index('Supplemental intervention-level'!$M:$M,match(1,('Supplemental intervention-level'!$C:$C=$A99)*('Supplemental intervention-level'!$A:$A="Deworming"),0))),"Not specified")} -> 0.09 | G99: {=iferror(if(isblank($A99),"",index('Supplemental intervention-level'!$M:$M,match(1,('Supplemental intervention-level'!$C:$C=$A99)*('Supplemental intervention-level'!$A:$A="Deworming"),0))),"Not specified")} -> 0.09 | H99: {=iferror(if(isblank($A99),"",index('Supplemental intervention-level'!$M:$M,match(1,('Supplemental intervention-level'!$C:$C=$A99)*('Supplemental intervention-level'!$A:$A="Deworming"),0))),"Not specified")} -> 0.09 | I99: {=iferror(if(isblank($A99),"",index('Supplemental intervention-level'!$M:$M,match(1,('Supplemental intervention-level'!$C:$C=$A99)*('Supplemental intervention-level'!$A:$A="Deworming"),0))),"Not specified")} -> 0.09 | ... N99: {=iferror(if(isblank($A99),"",index('Supplemental intervention-level'!$M:$M,match(1,('Supplemental intervention-level'!$C:$C=$A99)*('Supplemental intervention-level'!$A:$A="Deworming"),0))),"Not specified")} -> 0.09
A100: =IFERROR(__xludf.DUMMYFUNCTION("""COMPUTED_VALUE"""),"Investment of income increases") -> Investment of income increases | B100: {=iferror(if(isblank($A100),"",index('Supplemental intervention-level'!$M:$M,match(1,('Supplemental intervention-level'!$C:$C=$A100)*('Supplemental intervention-level'!$A:$A="Deworming"),0))),"Not specified")} -> 0.1 | C100: {=iferror(if(isblank($A100),"",index('Supplemental intervention-level'!$M:$M,match(1,('Supplemental intervention-level'!$C:$C=$A100)*('Supplemental intervention-level'!$A:$A="Deworming"),0))),"Not specified")} -> 0.1 | D100: {=iferror(if(isblank($A100),"",index('Supplemental intervention-level'!$M:$M,match(1,('Supplemental intervention-level'!$C:$C=$A100)*('Supplemental intervention-level'!$A:$A="Deworming"),0))),"Not specified")} -> 0.1 | E100: {=iferror(if(isblank($A100),"",index('Supplemental intervention-level'!$M:$M,match(1,('Supplemental intervention-level'!$C:$C=$A100)*('Supplemental intervention-level'!$A:$A="Deworming"),0))),"Not specified")} -> 0.1 | F100: {=iferror(if(isblank($A100),"",index('Supplemental intervention-level'!$M:$M,match(1,('Supplemental intervention-level'!$C:$C=$A100)*('Supplemental intervention-level'!$A:$A="Deworming"),0))),"Not specified")} -> 0.1 | G100: {=iferror(if(isblank($A100),"",index('Supplemental intervention-level'!$M:$M,match(1,('Supplemental intervention-level'!$C:$C=$A100)*('Supplemental intervention-level'!$A:$A="Deworming"),0))),"Not specified")} -> 0.1 | H100: {=iferror(if(isblank($A100),"",index('Supplemental intervention-level'!$M:$M,match(1,('Supplemental intervention-level'!$C:$C=$A100)*('Supplemental intervention-level'!$A:$A="Deworming"),0))),"Not specified")} -> 0.1 | I100: {=iferror(if(isblank($A100),"",index('Supplemental intervention-level'!$M:$M,match(1,('Supplemental intervention-level'!$C:$C=$A100)*('Supplemental intervention-level'!$A:$A="Deworming"),0))),"Not specified")} -> 0.1 | ... N100: {=iferror(if(isblank($A100),"",index('Supplemental intervention-level'!$M:$M,match(1,('Supplemental intervention-level'!$C:$C=$A100)*('Supplemental intervention-level'!$A:$A="Deworming"),0))),"Not specified")} -> 0.1
A101: =IFERROR(__xludf.DUMMYFUNCTION("""COMPUTED_VALUE"""),"Non-income long-run benefits of deworming") -> Non-income long-run benefits of deworming | B101: {=iferror(if(isblank($A101),"",index('Supplemental intervention-level'!$M:$M,match(1,('Supplemental intervention-level'!$C:$C=$A101)*('Supplemental intervention-level'!$A:$A="Deworming"),0))),"Not specified")} -> 0.04 | C101: {=iferror(if(isblank($A101),"",index('Supplemental intervention-level'!$M:$M,match(1,('Supplemental intervention-level'!$C:$C=$A101)*('Supplemental intervention-level'!$A:$A="Deworming"),0))),"Not specified")} -> 0.04 | D101: {=iferror(if(isblank($A101),"",index('Supplemental intervention-level'!$M:$M,match(1,('Supplemental intervention-level'!$C:$C=$A101)*('Supplemental intervention-level'!$A:$A="Deworming"),0))),"Not specified")} -> 0.04 | E101: {=iferror(if(isblank($A101),"",index('Supplemental intervention-level'!$M:$M,match(1,('Supplemental intervention-level'!$C:$C=$A101)*('Supplemental intervention-level'!$A:$A="Deworming"),0))),"Not specified")} -> 0.04 | F101: {=iferror(if(isblank($A101),"",index('Supplemental intervention-level'!$M:$M,match(1,('Supplemental intervention-level'!$C:$C=$A101)*('Supplemental intervention-level'!$A:$A="Deworming"),0))),"Not specified")} -> 0.04 | G101: {=iferror(if(isblank($A101),"",index('Supplemental intervention-level'!$M:$M,match(1,('Supplemental intervention-level'!$C:$C=$A101)*('Supplemental intervention-level'!$A:$A="Deworming"),0))),"Not specified")} -> 0.04 | H101: {=iferror(if(isblank($A101),"",index('Supplemental intervention-level'!$M:$M,match(1,('Supplemental intervention-level'!$C:$C=$A101)*('Supplemental intervention-level'!$A:$A="Deworming"),0))),"Not specified")} -> 0.04 | I101: {=iferror(if(isblank($A101),"",index('Supplemental intervention-level'!$M:$M,match(1,('Supplemental intervention-level'!$C:$C=$A101)*('Supplemental intervention-level'!$A:$A="Deworming"),0))),"Not specified")} -> 0.04 | ... N101: {=iferror(if(isblank($A101),"",index('Supplemental intervention-level'!$M:$M,match(1,('Supplemental intervention-level'!$C:$C=$A101)*('Supplemental intervention-level'!$A:$A="Deworming"),0))),"Not specified")} -> 0.04
A102: =IFERROR(__xludf.DUMMYFUNCTION("""COMPUTED_VALUE"""),"Drug resistance") -> Drug resistance | B102: {=iferror(if(isblank($A102),"",index('Supplemental intervention-level'!$M:$M,match(1,('Supplemental intervention-level'!$C:$C=$A102)*('Supplemental intervention-level'!$A:$A="Deworming"),0))),"Not specified")} -> -0.04 | C102: {=iferror(if(isblank($A102),"",index('Supplemental intervention-level'!$M:$M,match(1,('Supplemental intervention-level'!$C:$C=$A102)*('Supplemental intervention-level'!$A:$A="Deworming"),0))),"Not specified")} -> -0.04 | D102: {=iferror(if(isblank($A102),"",index('Supplemental intervention-level'!$M:$M,match(1,('Supplemental intervention-level'!$C:$C=$A102)*('Supplemental intervention-level'!$A:$A="Deworming"),0))),"Not specified")} -> -0.04 | E102: {=iferror(if(isblank($A102),"",index('Supplemental intervention-level'!$M:$M,match(1,('Supplemental intervention-level'!$C:$C=$A102)*('Supplemental intervention-level'!$A:$A="Deworming"),0))),"Not specified")} -> -0.04 | F102: {=iferror(if(isblank($A102),"",index('Supplemental intervention-level'!$M:$M,match(1,('Supplemental intervention-level'!$C:$C=$A102)*('Supplemental intervention-level'!$A:$A="Deworming"),0))),"Not specified")} -> -0.04 | G102: {=iferror(if(isblank($A102),"",index('Supplemental intervention-level'!$M:$M,match(1,('Supplemental intervention-level'!$C:$C=$A102)*('Supplemental intervention-level'!$A:$A="Deworming"),0))),"Not specified")} -> -0.04 | H102: {=iferror(if(isblank($A102),"",index('Supplemental intervention-level'!$M:$M,match(1,('Supplemental intervention-level'!$C:$C=$A102)*('Supplemental intervention-level'!$A:$A="Deworming"),0))),"Not specified")} -> -0.04 | I102: {=iferror(if(isblank($A102),"",index('Supplemental intervention-level'!$M:$M,match(1,('Supplemental intervention-level'!$C:$C=$A102)*('Supplemental intervention-level'!$A:$A="Deworming"),0))),"Not specified")} -> -0.04 | ... N102: {=iferror(if(isblank($A102),"",index('Supplemental intervention-level'!$M:$M,match(1,('Supplemental intervention-level'!$C:$C=$A102)*('Supplemental intervention-level'!$A:$A="Deworming"),0))),"Not specified")} -> -0.04
A103: =IFERROR(__xludf.DUMMYFUNCTION("""COMPUTED_VALUE"""),"Unprogrammed deworming") -> Unprogrammed deworming | B103: {=iferror(if(isblank($A103),"",index('Supplemental intervention-level'!$M:$M,match(1,('Supplemental intervention-level'!$C:$C=$A103)*('Supplemental intervention-level'!$A:$A="Deworming"),0))),"Not specified")} -> -0.14 | C103: {=iferror(if(isblank($A103),"",index('Supplemental intervention-level'!$M:$M,match(1,('Supplemental intervention-level'!$C:$C=$A103)*('Supplemental intervention-level'!$A:$A="Deworming"),0))),"Not specified")} -> -0.14 | D103: {=iferror(if(isblank($A103),"",index('Supplemental intervention-level'!$M:$M,match(1,('Supplemental intervention-level'!$C:$C=$A103)*('Supplemental intervention-level'!$A:$A="Deworming"),0))),"Not specified")} -> -0.14 | E103: {=iferror(if(isblank($A103),"",index('Supplemental intervention-level'!$M:$M,match(1,('Supplemental intervention-level'!$C:$C=$A103)*('Supplemental intervention-level'!$A:$A="Deworming"),0))),"Not specified")} -> -0.14 | F103: {=iferror(if(isblank($A103),"",index('Supplemental intervention-level'!$M:$M,match(1,('Supplemental intervention-level'!$C:$C=$A103)*('Supplemental intervention-level'!$A:$A="Deworming"),0))),"Not specified")} -> -0.14 | G103: {=iferror(if(isblank($A103),"",index('Supplemental intervention-level'!$M:$M,match(1,('Supplemental intervention-level'!$C:$C=$A103)*('Supplemental intervention-level'!$A:$A="Deworming"),0))),"Not specified")} -> -0.14 | H103: {=iferror(if(isblank($A103),"",index('Supplemental intervention-level'!$M:$M,match(1,('Supplemental intervention-level'!$C:$C=$A103)*('Supplemental intervention-level'!$A:$A="Deworming"),0))),"Not specified")} -> -0.14 | I103: {=iferror(if(isblank($A103),"",index('Supplemental intervention-level'!$M:$M,match(1,('Supplemental intervention-level'!$C:$C=$A103)*('Supplemental intervention-level'!$A:$A="Deworming"),0))),"Not specified")} -> -0.14 | ... N103: {=iferror(if(isblank($A103),"",index('Supplemental intervention-level'!$M:$M,match(1,('Supplemental intervention-level'!$C:$C=$A103)*('Supplemental intervention-level'!$A:$A="Deworming"),0))),"Not specified")} -> -0.14
A104: =IFERROR(__xludf.DUMMYFUNCTION("""COMPUTED_VALUE"""),"Marginal funding goes to lower priority areas") -> Marginal funding goes to lower priority areas | B104: {=iferror(if(isblank($A104),"",index('Supplemental intervention-level'!$M:$M,match(1,('Supplemental intervention-level'!$C:$C=$A104)*('Supplemental intervention-level'!$A:$A="Deworming"),0))),"Not specified")} -> -0.025 | C104: {=iferror(if(isblank($A104),"",index('Supplemental intervention-level'!$M:$M,match(1,('Supplemental intervention-level'!$C:$C=$A104)*('Supplemental intervention-level'!$A:$A="Deworming"),0))),"Not specified")} -> -0.025 | D104: {=iferror(if(isblank($A104),"",index('Supplemental intervention-level'!$M:$M,match(1,('Supplemental intervention-level'!$C:$C=$A104)*('Supplemental intervention-level'!$A:$A="Deworming"),0))),"Not specified")} -> -0.025 | E104: {=iferror(if(isblank($A104),"",index('Supplemental intervention-level'!$M:$M,match(1,('Supplemental intervention-level'!$C:$C=$A104)*('Supplemental intervention-level'!$A:$A="Deworming"),0))),"Not specified")} -> -0.025 | F104: {=iferror(if(isblank($A104),"",index('Supplemental intervention-level'!$M:$M,match(1,('Supplemental intervention-level'!$C:$C=$A104)*('Supplemental intervention-level'!$A:$A="Deworming"),0))),"Not specified")} -> -0.025 | G104: {=iferror(if(isblank($A104),"",index('Supplemental intervention-level'!$M:$M,match(1,('Supplemental intervention-level'!$C:$C=$A104)*('Supplemental intervention-level'!$A:$A="Deworming"),0))),"Not specified")} -> -0.025 | H104: {=iferror(if(isblank($A104),"",index('Supplemental intervention-level'!$M:$M,match(1,('Supplemental intervention-level'!$C:$C=$A104)*('Supplemental intervention-level'!$A:$A="Deworming"),0))),"Not specified")} -> -0.025 | I104: {=iferror(if(isblank($A104),"",index('Supplemental intervention-level'!$M:$M,match(1,('Supplemental intervention-level'!$C:$C=$A104)*('Supplemental intervention-level'!$A:$A="Deworming"),0))),"Not specified")} -> -0.025 | ... N104: {=iferror(if(isblank($A104),"",index('Supplemental intervention-level'!$M:$M,match(1,('Supplemental intervention-level'!$C:$C=$A104)*('Supplemental intervention-level'!$A:$A="Deworming"),0))),"Not specified")} -> -0.025
A105: =IFERROR(__xludf.DUMMYFUNCTION("""COMPUTED_VALUE"""),"General equilibrium effects") -> General equilibrium effects | B105: {=iferror(if(isblank($A105),"",index('Supplemental intervention-level'!$M:$M,match(1,('Supplemental intervention-level'!$C:$C=$A105)*('Supplemental intervention-level'!$A:$A="Deworming"),0))),"Not specified")} -> -0.03 | C105: {=iferror(if(isblank($A105),"",index('Supplemental intervention-level'!$M:$M,match(1,('Supplemental intervention-level'!$C:$C=$A105)*('Supplemental intervention-level'!$A:$A="Deworming"),0))),"Not specified")} -> -0.03 | D105: {=iferror(if(isblank($A105),"",index('Supplemental intervention-level'!$M:$M,match(1,('Supplemental intervention-level'!$C:$C=$A105)*('Supplemental intervention-level'!$A:$A="Deworming"),0))),"Not specified")} -> -0.03 | E105: {=iferror(if(isblank($A105),"",index('Supplemental intervention-level'!$M:$M,match(1,('Supplemental intervention-level'!$C:$C=$A105)*('Supplemental intervention-level'!$A:$A="Deworming"),0))),"Not specified")} -> -0.03 | F105: {=iferror(if(isblank($A105),"",index('Supplemental intervention-level'!$M:$M,match(1,('Supplemental intervention-level'!$C:$C=$A105)*('Supplemental intervention-level'!$A:$A="Deworming"),0))),"Not specified")} -> -0.03 | G105: {=iferror(if(isblank($A105),"",index('Supplemental intervention-level'!$M:$M,match(1,('Supplemental intervention-level'!$C:$C=$A105)*('Supplemental intervention-level'!$A:$A="Deworming"),0))),"Not specified")} -> -0.03 | H105: {=iferror(if(isblank($A105),"",index('Supplemental intervention-level'!$M:$M,match(1,('Supplemental intervention-level'!$C:$C=$A105)*('Supplemental intervention-level'!$A:$A="Deworming"),0))),"Not specified")} -> -0.03 | I105: {=iferror(if(isblank($A105),"",index('Supplemental intervention-level'!$M:$M,match(1,('Supplemental intervention-level'!$C:$C=$A105)*('Supplemental intervention-level'!$A:$A="Deworming"),0))),"Not specified")} -> -0.03 | ... N105: {=iferror(if(isblank($A105),"",index('Supplemental intervention-level'!$M:$M,match(1,('Supplemental intervention-level'!$C:$C=$A105)*('Supplemental intervention-level'!$A:$A="Deworming"),0))),"Not specified")} -> -0.03
B106: {=iferror(if(isblank($A106),"",index('Supplemental intervention-level'!$M:$M,match(1,('Supplemental intervention-level'!$C:$C=$A106)*('Supplemental intervention-level'!$A:$A="Deworming"),0))),"Not specified")} | C106: {=iferror(if(isblank($A106),"",index('Supplemental intervention-level'!$M:$M,match(1,('Supplemental intervention-level'!$C:$C=$A106)*('Supplemental intervention-level'!$A:$A="Deworming"),0))),"Not specified")} | D106: {=iferror(if(isblank($A106),"",index('Supplemental intervention-level'!$M:$M,match(1,('Supplemental intervention-level'!$C:$C=$A106)*('Supplemental intervention-level'!$A:$A="Deworming"),0))),"Not specified")} | E106: {=iferror(if(isblank($A106),"",index('Supplemental intervention-level'!$M:$M,match(1,('Supplemental intervention-level'!$C:$C=$A106)*('Supplemental intervention-level'!$A:$A="Deworming"),0))),"Not specified")} | F106: {=iferror(if(isblank($A106),"",index('Supplemental intervention-level'!$M:$M,match(1,('Supplemental intervention-level'!$C:$C=$A106)*('Supplemental intervention-level'!$A:$A="Deworming"),0))),"Not specified")} | G106: {=iferror(if(isblank($A106),"",index('Supplemental intervention-level'!$M:$M,match(1,('Supplemental intervention-level'!$C:$C=$A106)*('Supplemental intervention-level'!$A:$A="Deworming"),0))),"Not specified")} | H106: {=iferror(if(isblank($A106),"",index('Supplemental intervention-level'!$M:$M,match(1,('Supplemental intervention-level'!$C:$C=$A106)*('Supplemental intervention-level'!$A:$A="Deworming"),0))),"Not specified")} | I106: {=iferror(if(isblank($A106),"",index('Supplemental intervention-level'!$M:$M,match(1,('Supplemental intervention-level'!$C:$C=$A106)*('Supplemental intervention-level'!$A:$A="Deworming"),0))),"Not specified")} | ... N106: {=iferror(if(isblank($A106),"",index('Supplemental intervention-level'!$M:$M,match(1,('Supplemental intervention-level'!$C:$C=$A106)*('Supplemental intervention-level'!$A:$A="Deworming"),0))),"Not specified")}
B107: {=iferror(if(isblank($A107),"",index('Supplemental intervention-level'!$M:$M,match(1,('Supplemental intervention-level'!$C:$C=$A107)*('Supplemental intervention-level'!$A:$A="Deworming"),0))),"Not specified")} | C107: {=iferror(if(isblank($A107),"",index('Supplemental intervention-level'!$M:$M,match(1,('Supplemental intervention-level'!$C:$C=$A107)*('Supplemental intervention-level'!$A:$A="Deworming"),0))),"Not specified")} | D107: {=iferror(if(isblank($A107),"",index('Supplemental intervention-level'!$M:$M,match(1,('Supplemental intervention-level'!$C:$C=$A107)*('Supplemental intervention-level'!$A:$A="Deworming"),0))),"Not specified")} | E107: {=iferror(if(isblank($A107),"",index('Supplemental intervention-level'!$M:$M,match(1,('Supplemental intervention-level'!$C:$C=$A107)*('Supplemental intervention-level'!$A:$A="Deworming"),0))),"Not specified")} | F107: {=iferror(if(isblank($A107),"",index('Supplemental intervention-level'!$M:$M,match(1,('Supplemental intervention-level'!$C:$C=$A107)*('Supplemental intervention-level'!$A:$A="Deworming"),0))),"Not specified")} | G107: {=iferror(if(isblank($A107),"",index('Supplemental intervention-level'!$M:$M,match(1,('Supplemental intervention-level'!$C:$C=$A107)*('Supplemental intervention-level'!$A:$A="Deworming"),0))),"Not specified")} | H107: {=iferror(if(isblank($A107),"",index('Supplemental intervention-level'!$M:$M,match(1,('Supplemental intervention-level'!$C:$C=$A107)*('Supplemental intervention-level'!$A:$A="Deworming"),0))),"Not specified")} | I107: {=iferror(if(isblank($A107),"",index('Supplemental intervention-level'!$M:$M,match(1,('Supplemental intervention-level'!$C:$C=$A107)*('Supplemental intervention-level'!$A:$A="Deworming"),0))),"Not specified")} | ... N107: {=iferror(if(isblank($A107),"",index('Supplemental intervention-level'!$M:$M,match(1,('Supplemental intervention-level'!$C:$C=$A107)*('Supplemental intervention-level'!$A:$A="Deworming"),0))),"Not specified")}
A108: Total adjustment factor | B108: =1+sum(B94:B107) -> 1.073 | C108: =1+sum(C94:C107) -> 1.073 | D108: =1+sum(D94:D107) -> 1.073 | E108: =1+sum(E94:E107) -> 1.073 | F108: =1+sum(F94:F107) -> 1.073 | G108: =1+sum(G94:G107) -> 1.073 | H108: =1+sum(H94:H107) -> 1.073 | I108: =1+sum(I94:I107) -> 1.073 | ... N108: =1+sum(N94:N107) -> 1.073
A110: Results after supplemental intervention-level adjustments
A112: Total units of value generated | B112: =B86*B108 -> 15139.504 | C112: =C86*C108 -> 3467.8479 | D112: =D86*D108 -> 1254.3255 | E112: =E86*E108 -> 12321.928 | F112: =F86*F108 -> 737.84081 | G112: =G86*G108 -> 5181.7009 | H112: =H86*H108 -> 737.84081 | I112: =I86*I108 -> 1254.3255 | ... N112: =N86*N108 -> 5007.9274
A113: Units of value per dollar spent | B113: =B112/B40 -> 0.092091226 | C113: =C112/C40 -> 0.013922643 | D113: =D112/D40 -> 0.0050358396 | E113: =E112/E40 -> 0.049469818 | F113: =F112/F40 -> 0.0029622678 | G113: =G112/G40 -> 0.020803384 | H113: =H112/H40 -> 0.0029622678 | I113: =I112/I40 -> 0.0050358396 | ... N113: =N112/N40 -> 0.029516805
A114: Cost-effectiveness in multiples of cash transfers, after supplemental intervention-level adjustments | B114: {=B113/index(GiveDirectly!$B:$B,match("Units of value generated per philanthropic dollar spent, after accounting for all adjustments",GiveDirectly!$A:$A,0))} -> 27.452763 | C114: {=C113/index(GiveDirectly!$B:$B,match("Units of value generated per philanthropic dollar spent, after accounting for all adjustments",GiveDirectly!$A:$A,0))} -> 4.1503956 | D114: {=D113/index(GiveDirectly!$B:$B,match("Units of value generated per philanthropic dollar spent, after accounting for all adjustments",GiveDirectly!$A:$A,0))} -> 1.501204 | E114: {=E113/index(GiveDirectly!$B:$B,match("Units of value generated per philanthropic dollar spent, after accounting for all adjustments",GiveDirectly!$A:$A,0))} -> 14.747151 | F114: {=F113/index(GiveDirectly!$B:$B,match("Units of value generated per philanthropic dollar spent, after accounting for all adjustments",GiveDirectly!$A:$A,0))} -> 0.88306389 | G114: {=G113/index(GiveDirectly!$B:$B,match("Units of value generated per philanthropic dollar spent, after accounting for all adjustments",GiveDirectly!$A:$A,0))} -> 6.201572 | H114: {=H113/index(GiveDirectly!$B:$B,match("Units of value generated per philanthropic dollar spent, after accounting for all adjustments",GiveDirectly!$A:$A,0))} -> 0.88306389 | I114: {=I113/index(GiveDirectly!$B:$B,match("Units of value generated per philanthropic dollar spent, after accounting for all adjustments",GiveDirectly!$A:$A,0))} -> 1.501204 | ... N114: {=N113/index(GiveDirectly!$B:$B,match("Units of value generated per philanthropic dollar spent, after accounting for all adjustments",GiveDirectly!$A:$A,0))} -> 8.7990778
A116: Leverage/Funging adjustment
A118: Cost per treatment breakdown:
A119: Deworm the World | B119: =B31*B$46 -> 0.39390666 | C119: =C31*C$46 -> 0.2980853 | D119: =D31*D$46 -> 0.2980853 | E119: =E31*E$46 -> 0.2980853 | F119: =F31*F$46 -> 0.2980853 | G119: =G31*G$46 -> 0.2980853 | H119: =H31*H$46 -> 0.2980853 | I119: =I31*I$46 -> 0.2980853 | ... N119: =N31*N$46 -> 0.68442942
A120: Other philanthropic actors | B120: =B32*B$46 -> 0.015164082 | C120: =C32*C$46 -> 0.19108683 | D120: =D32*D$46 -> 0.19108683 | E120: =E32*E$46 -> 0.19108683 | F120: =F32*F$46 -> 0.19108683 | G120: =G32*G$46 -> 0.19108683 | H120: =H32*H$46 -> 0.19108683 | I120: =I32*I$46 -> 0.19108683 | ... N120: =N32*N$46 -> 0.040863331
A121: Government financial costs | B121: =B33*B$46 -> 0.0064413788 | C121: =C33*C$46 -> 0 | D121: =D33*D$46 -> 0 | E121: =E33*E$46 -> 0 | F121: =F33*F$46 -> 0 | G121: =G33*G$46 -> 0 | H121: =H33*H$46 -> 0 | I121: =I33*I$46 -> 0 | ... N121: =N33*N$46 -> 0.0017510919
A122: Government in-kind costs | B122: =B34*B$46 -> 0.194271 | C122: =C34*C$46 -> 0.222741 | D122: =D34*D$46 -> 0.222741 | E122: =E34*E$46 -> 0.222741 | F122: =F34*F$46 -> 0.222741 | G122: =G34*G$46 -> 0.222741 | H122: =H34*H$46 -> 0.222741 | I122: =I34*I$46 -> 0.222741 | ... N122: =N34*N$46 -> 0.34836828
A123: Drug donations | B123: =B35*B$46 -> 0.037786875 | C123: =C35*C$46 -> 0.030556947 | D123: =D35*D$46 -> 0.030556947 | E123: =E35*E$46 -> 0.030556947 | F123: =F35*F$46 -> 0.030556947 | G123: =G35*G$46 -> 0.030556947 | H123: =H35*H$46 -> 0.030556947 | I123: =I35*I$46 -> 0.030556947 | ... N123: =N35*N$46 -> 0.085815476
A124: Total costs | B124: =sum(B119:B123) -> 0.64757 | C124: =sum(C119:C123) -> 0.74247007 | D124: =sum(D119:D123) -> 0.74247007 | E124: =sum(E119:E123) -> 0.74247007 | F124: =sum(F119:F123) -> 0.74247007 | G124: =sum(G119:G123) -> 0.74247007 | H124: =sum(H119:H123) -> 0.74247007 | I124: =sum(I119:I123) -> 0.74247007 | ... N124: =sum(N119:N123) -> 1.1612276
A125: CHECKSUM | B125: =(B124-B46)/B124 -> 0 | C125: =(C124-C46)/C124 -> 9.999999e-08 | D125: =(D124-D46)/D124 -> 9.999999e-08 | E125: =(E124-E46)/E124 -> 9.999999e-08 | F125: =(F124-F46)/F124 -> 9.999999e-08 | G125: =(G124-G46)/G124 -> 9.999999e-08 | H125: =(H124-H46)/H124 -> 9.999999e-08 | I125: =(I124-I46)/I124 -> 9.999999e-08 | ... N125: =(N124-N46)/N124 -> 0
A127: Total expenditure attributable to different actors:
A128: Deworm the World | B128: =B31*B$40 -> 100000 | C128: =C31*C$40 -> 100000 | D128: =D31*D$40 -> 100000 | E128: =E31*E$40 -> 100000 | F128: =F31*F$40 -> 100000 | G128: =G31*G$40 -> 100000 | H128: =H31*H$40 -> 100000 | I128: =I31*I$40 -> 100000 | ... N128: =N31*N$40 -> 100000
A129: Other philanthropic actors | B129: =B32*B$40 -> 3849.6637 | C129: =C32*C$40 -> 64104.749 | D129: =D32*D$40 -> 64104.749 | E129: =E32*E$40 -> 64104.749 | F129: =F32*F$40 -> 64104.749 | G129: =G32*G$40 -> 64104.749 | H129: =H32*H$40 -> 64104.749 | I129: =I32*I$40 -> 64104.749 | ... N129: =N32*N$40 -> 5970.4229
A130: Government financial costs | B130: =B33*B$40 -> 1635.2551 | C130: =C33*C$40 -> 0 | D130: =D33*D$40 -> 0 | E130: =E33*E$40 -> 0 | F130: =F33*F$40 -> 0 | G130: =G33*G$40 -> 0 | H130: =H33*H$40 -> 0 | I130: =I33*I$40 -> 0 | ... N130: =N33*N$40 -> 255.84696
A131: Government in-kind costs | B131: =B34*B$40 -> 49319.044 | C131: =C34*C$40 -> 74723.914 | D131: =D34*D$40 -> 74723.914 | E131: =E34*E$40 -> 74723.914 | F131: =F34*F$40 -> 74723.914 | G131: =G34*G$40 -> 74723.914 | H131: =H34*H$40 -> 74723.914 | I131: =I34*I$40 -> 74723.914 | ... N131: =N34*N$40 -> 50899.08
...

Sheet Unlimit Health
A1: Deworming - Unlimit Health (formerly known as the SCI Foundation (SCI)) | B1: Overall | C1: Ethiopia | D1: DRC | E1: Madagascar | F1: Tanzania | G1: Cote d'Ivoire | H1: Uganda | I1: Liberia | J1: Burundi | K1: Pemba, Zanzibar | L1: Unguja, Zanzibar | M1: Sudan | N1: Niger | O1: Mauritania | P1: Malawi
A5: Funding allocation
A7: Percentage of funding to be allocated to each country with marginal donations | B7: =sum(C7:P7) -> 1 | C7: 0.23409826 | D7: 0.073032089 | E7: 0.13149468 | F7: 0.16606921 | G7: 0.05870865 | H7: 0.12965205 | I7: 0.012521109 | J7: 0.037635034 | K7: 0.003980788 | L7: 0.01496666 | M7: 0.095184572 | N7: 0.013281741 | O7: 0.0079960109 | P7: 0.021379152
A8: Percentage of total costs covered by Unlimit Health | B8: =B15/B16 -> 0.3881312 | C8: 0.3881312 | D8: 0.3881312 | E8: 0.3881312 | F8: 0.3881312 | G8: 0.3881312 | H8: 0.3881312 | I8: 0.3881312 | J8: 0.3881312 | K8: 0.3881312 | L8: 0.3881312 | M8: 0.3881312 | N8: 0.3881312 | O8: 0.3881312 | P8: 0.3881312
A9: Percentage of total costs covered by domestic governments (financial costs) | B9: =sumproduct(C9:I9,$C$16:$I$16)/sum($C$16:$I$16) -> 0 | C9: 0 | D9: 0 | E9: 0 | F9: 0 | G9: 0 | H9: 0 | I9: 0 | J9: 0 | K9: 0 | L9: 0 | M9: 0 | N9: 0 | O9: 0 | P9: 0
A10: Percentage of total costs covered by domestic governments (in-kind costs) | B10: =sumproduct(C10:I10,$C$16:$I$16)/sum($C$16:$I$16) -> 0.3 | C10: 0.3 | D10: 0.3 | E10: 0.3 | F10: 0.3 | G10: 0.3 | H10: 0.3 | I10: 0.3 | J10: 0.3 | K10: 0.3 | L10: 0.3 | M10: 0.3 | N10: 0.3 | O10: 0.3 | P10: 0.3
A11: Percentage of total costs covered by drug donations | B11: =sumproduct(C11:I11,$C$16:$I$16)/sum($C$16:$I$16) -> 0.3118688 | C11: 0.3118688 | D11: 0.3118688 | E11: 0.3118688 | F11: 0.3118688 | G11: 0.3118688 | H11: 0.3118688 | I11: 0.3118688 | J11: 0.3118688 | K11: 0.3118688 | L11: 0.3118688 | M11: 0.3118688 | N11: 0.3118688 | O11: 0.3118688 | P11: 0.3118688
A13: Number of children dewormed per year with hypothetical donation (Unlimit Health)
A15: Donation to Unlimit Health (arbitrary size) | B15: 100000 | C15: =100000*C7 -> 23409.826 | D15: =100000*D7 -> 7303.2089 | E15: =100000*E7 -> 13149.468 | F15: =100000*F7 -> 16606.921 | G15: =100000*G7 -> 5870.865 | H15: =100000*H7 -> 12965.205 | I15: =100000*I7 -> 1252.1109 | J15: =100000*J7 -> 3763.5034 | ... P15: =100000*P7 -> 2137.9152
A16: Total amount spent on the program by all contributors | B16: =sum(C16:P16) -> 257644.84 | C16: =C15/C8 -> 60314.207 | D16: =D15/D8 -> 18816.341 | E16: =E15/E8 -> 33878.925 | F16: =F15/F8 -> 42786.874 | G16: =G15/G8 -> 15125.98 | H16: =H15/H8 -> 33404.181 | I16: =I15/I8 -> 3225.9991 | J16: =J15/J8 -> 9696.472 | ... P16: =P15/P8 -> 5508.228
A17: Proportion of deworming going to children — Unlimit Health | B17: =sumproduct(C17:P17,C25:P25) -> 0.7862708 | C17: 0.72849882 | D17: 0.93731113 | E17: 1 | F17: 0.90816869 | G17: 1 | H17: 0.45794467 | I17: 0.70588969 | J17: 1 | K17: 0.25308255 | L17: 0.25308255 | M17: 0.72033591 | N17: 0.38242939 | O17: 1 | P17: 0.65353516
A18: Worm burden adjustment — Unlimit Health | B18: =sumproduct(C18:P18,C25:P25) -> 0.092104387 | C18: 0.05674557 | D18: 0.20523514 | E18: 0.20523514 | F18: 0.069440209 | G18: 0.092644434 | H18: 0.0090417406 | I18: 0.16756656 | J18: 0.12586874 | K18: 0.033399067 | L18: 0.0061850125 | M18: 0.075454864 | N18: 0.043687841 | O18: 0.20523514 | P18: 0.10463036
A19: Adjusted long-term benefits per year of deworming per person treated in terms of ln(consumption) | B19: ='Deworm the World'!$B$27 -> 0.20627072 | C19: ='Deworm the World'!$B$27 -> 0.20627072 | D19: ='Deworm the World'!$B$27 -> 0.20627072 | E19: ='Deworm the World'!$B$27 -> 0.20627072 | F19: ='Deworm the World'!$B$27 -> 0.20627072 | G19: ='Deworm the World'!$B$27 -> 0.20627072 | H19: ='Deworm the World'!$B$27 -> 0.20627072 | I19: ='Deworm the World'!$B$27 -> 0.20627072 | ... P19: ='Deworm the World'!$B$27 -> 0.20627072
A20: Present value of lifetime benefits from a year of deworming — in terms of increases in ln(consumption) — Unlimit Health | B20: =B19*B17*B18 -> 0.014937918 | C20: =C19*C17*C18 -> 0.0085270421 | D20: =D19*D17*D18 -> 0.039680131 | E20: =E19*E17*E18 -> 0.042334002 | F20: =F19*F17*F18 -> 0.013008138 | G20: =G19*G17*G18 -> 0.019109835 | H20: =H19*H17*H18 -> 0.00085408805 | I20: =I19*I17*I18 -> 0.024398425 | ... P20: =P19*P17*P18 -> 0.014104713
A21: Value assigned to increasing ln(consumption) by one unit for one person for one year | B21: {=index('Moral weights and discount rate'!$A$1:$ZU$39,match($A21,'Moral weights and discount rate'!$A$1:$A$39,0),match('Moral weights and discount rate'!$A$17,'Moral weights and discount rate'!$A$1:$ZU$1,0))} -> 1.442695 | C21: {=index('Moral weights and discount rate'!$A$1:$ZU$39,match($A21,'Moral weights and discount rate'!$A$1:$A$39,0),match('Moral weights and discount rate'!$A$17,'Moral weights and discount rate'!$A$1:$ZU$1,0))} -> 1.442695 | D21: {=index('Moral weights and discount rate'!$A$1:$ZU$39,match($A21,'Moral weights and discount rate'!$A$1:$A$39,0),match('Moral weights and discount rate'!$A$17,'Moral weights and discount rate'!$A$1:$ZU$1,0))} -> 1.442695 | E21: {=index('Moral weights and discount rate'!$A$1:$ZU$39,match($A21,'Moral weights and discount rate'!$A$1:$A$39,0),match('Moral weights and discount rate'!$A$17,'Moral weights and discount rate'!$A$1:$ZU$1,0))} -> 1.442695 | F21: {=index('Moral weights and discount rate'!$A$1:$ZU$39,match($A21,'Moral weights and discount rate'!$A$1:$A$39,0),match('Moral weights and discount rate'!$A$17,'Moral weights and discount rate'!$A$1:$ZU$1,0))} -> 1.442695 | G21: {=index('Moral weights and discount rate'!$A$1:$ZU$39,match($A21,'Moral weights and discount rate'!$A$1:$A$39,0),match('Moral weights and discount rate'!$A$17,'Moral weights and discount rate'!$A$1:$ZU$1,0))} -> 1.442695 | H21: {=index('Moral weights and discount rate'!$A$1:$ZU$39,match($A21,'Moral weights and discount rate'!$A$1:$A$39,0),match('Moral weights and discount rate'!$A$17,'Moral weights and discount rate'!$A$1:$ZU$1,0))} -> 1.442695 | I21: {=index('Moral weights and discount rate'!$A$1:$ZU$39,match($A21,'Moral weights and discount rate'!$A$1:$A$39,0),match('Moral weights and discount rate'!$A$17,'Moral weights and discount rate'!$A$1:$ZU$1,0))} -> 1.442695 | ... P21: {=index('Moral weights and discount rate'!$A$1:$ZU$39,match($A21,'Moral weights and discount rate'!$A$1:$A$39,0),match('Moral weights and discount rate'!$A$17,'Moral weights and discount rate'!$A$1:$ZU$1,0))} -> 1.442695
A22: Units of value from each year of deworming — Unlimit Health | B22: =(B20*$B$21) -> 0.02155086 | C22: =(C20*C21) -> 0.012301921 | D22: =(D20*D21) -> 0.057246328 | E22: =(E20*E21) -> 0.061075054 | F22: =(F20*F21) -> 0.018766776 | G22: =(G20*G21) -> 0.027569664 | H22: =(H20*H21) -> 0.0012321886 | I22: =(I20*I21) -> 0.035199486 | J22: =(J20*J21) -> 0.037456743 | ... P22: =(P20*P21) -> 0.0203488
A23: Cost per person dewormed (per year) — Unlimit Health | B23: 1.0289662 | C23: 1.0289662 | D23: 1.0289662 | E23: 1.0289662 | F23: 1.0289662 | G23: 1.0289662 | H23: 1.0289662 | I23: 1.0289662 | J23: 1.0289662 | K23: 1.0289662 | L23: 1.0289662 | M23: 1.0289662 | N23: 1.0289662 | O23: 1.0289662 | P23: 1.0289662
A24: Total number of children dewormed (per year) — Unlimit Health | B24: =sum(C24:P24) -> 250391.93 | C24: =C16/C23 -> 58616.314 | D24: =D16/D23 -> 18286.646 | E24: =E16/E23 -> 32925.206 | F24: =F16/F23 -> 41582.389 | G24: =G16/G23 -> 14700.172 | H24: =H16/H23 -> 32463.827 | I24: =I16/I23 -> 3135.1846 | J24: =J16/J23 -> 9423.5086 | ... P24: =P16/P23 -> 5353.167
A25: Percentage of children dewormed (per year) in each country | B25: =sum(C25:P25) -> 1 | C25: =C24/$B$24 -> 0.23409826 | D25: =D24/$B$24 -> 0.073032089 | E25: =E24/$B$24 -> 0.13149468 | F25: =F24/$B$24 -> 0.16606921 | G25: =G24/$B$24 -> 0.05870865 | H25: =H24/$B$24 -> 0.12965205 | I25: =I24/$B$24 -> 0.012521109 | J25: =J24/$B$24 -> 0.037635034 | ... P25: =P24/$B$24 -> 0.021379152
A28: Intuition check
A30: Aggregate adjustment to Miguel and Kremer development effect — Unlimit Health | B30: =product('Deworm the World'!$B$11:$B$12,B18) -> 0.010776213 | C30: =product('Deworm the World'!$B$11:$B$12,C18) -> 0.0066392317 | D30: =product('Deworm the World'!$B$11:$B$12,D18) -> 0.024012512 | E30: =product('Deworm the World'!$B$11:$B$12,E18) -> 0.024012512 | F30: =product('Deworm the World'!$B$11:$B$12,F18) -> 0.0081245045 | G30: =product('Deworm the World'!$B$11:$B$12,G18) -> 0.010839399 | H30: =product('Deworm the World'!$B$11:$B$12,H18) -> 0.0010578837 | I30: =product('Deworm the World'!$B$11:$B$12,I18) -> 0.019605287 | ... P30: =product('Deworm the World'!$B$11:$B$12,P18) -> 0.012241752
A32: Initial results
A34: =A20 -> Present value of lifetime benefits from a year of deworming — in terms of increases in ln(consumption) — Unlimit Health | B34: =B20 -> 0.014937918 | C34: =C20 -> 0.0085270421 | D34: =D20 -> 0.039680131 | E34: =E20 -> 0.042334002 | F34: =F20 -> 0.013008138 | G34: =G20 -> 0.019109835 | H34: =H20 -> 0.00085408805 | ... P34: =P20 -> 0.014104713
A35: =A21 -> Value assigned to increasing ln(consumption) by one unit for one person for one year | B35: =B21 -> 1.442695 | C35: =C21 -> 1.442695 | D35: =D21 -> 1.442695 | E35: =E21 -> 1.442695 | F35: =F21 -> 1.442695 | G35: =G21 -> 1.442695 | H35: =H21 -> 1.442695 | ... P35: =P21 -> 1.442695
A36: =A24 -> Total number of children dewormed (per year) — Unlimit Health | B36: =B24 -> 250391.93 | C36: =C24 -> 58616.314 | D36: =D24 -> 18286.646 | E36: =E24 -> 32925.206 | F36: =F24 -> 41582.389 | G36: =G24 -> 14700.172 | H36: =H24 -> 32463.827 | ... P36: =P24 -> 5353.167
A37: Total units of value generated, before accounting for leverage and funging | B37: =sum(C37:P37) -> 6105.3201 | C37: =product(C34:C36) -> 721.09328 | D37: =product(D34:D36) -> 1046.8433 | E37: =product(E34:E36) -> 2010.9088 | F37: =product(F34:F36) -> 780.36739 | G37: =product(G34:G36) -> 405.27879 | H37: =product(H34:H36) -> 40.001557 | I37: =product(I34:I36) -> 110.35689 | J37: =product(J34:J36) -> 352.97393 | ... P37: =product(P34:P36) -> 108.93052
A38: Units of value generated per dollar spent, before accounting for leverage/funging | B38: =B37/B16 -> 0.023696652 | C38: =C37/C16 -> 0.011955612 | D38: =D37/D16 -> 0.055634798 | E38: =E37/E16 -> 0.059355742 | F38: =F37/F16 -> 0.018238477 | G38: =G37/G16 -> 0.026793555 | H38: =H37/H16 -> 0.0011975015 | I38: =I37/I16 -> 0.034208592 | ... P38: =P37/P16 -> 0.019775965
A40: Initial cost-effectiveness estimate in multiples of cash transfers | B40: {=B38/index(GiveDirectly!$B:$B,match("Units of value generated per philanthropic dollar spent, after accounting for all adjustments",GiveDirectly!$A:$A,0))} -> 7.0640669 | C40: {=C38/index(GiveDirectly!$B:$B,match("Units of value generated per philanthropic dollar spent, after accounting for all adjustments",GiveDirectly!$A:$A,0))} -> 3.5640159 | D40: {=D38/index(GiveDirectly!$B:$B,match("Units of value generated per philanthropic dollar spent, after accounting for all adjustments",GiveDirectly!$A:$A,0))} -> 16.584956 | E40: {=E38/index(GiveDirectly!$B:$B,match("Units of value generated per philanthropic dollar spent, after accounting for all adjustments",GiveDirectly!$A:$A,0))} -> 17.694185 | F40: {=F38/index(GiveDirectly!$B:$B,match("Units of value generated per philanthropic dollar spent, after accounting for all adjustments",GiveDirectly!$A:$A,0))} -> 5.4369629 | G40: {=G38/index(GiveDirectly!$B:$B,match("Units of value generated per philanthropic dollar spent, after accounting for all adjustments",GiveDirectly!$A:$A,0))} -> 7.9872662 | H40: {=H38/index(GiveDirectly!$B:$B,match("Units of value generated per philanthropic dollar spent, after accounting for all adjustments",GiveDirectly!$A:$A,0))} -> 0.35697999 | I40: {=I38/index(GiveDirectly!$B:$B,match("Units of value generated per philanthropic dollar spent, after accounting for all adjustments",GiveDirectly!$A:$A,0))} -> 10.197718 | ... P40: {=P38/index(GiveDirectly!$B:$B,match("Units of value generated per philanthropic dollar spent, after accounting for all adjustments",GiveDirectly!$A:$A,0))} -> 5.8952943
A42: Supplemental charity-level adjustments — Unlimit Health
A44: Risk of wastage
A45: Double treatment | B45: 0 | C45: 0 | D45: 0 | E45: 0 | F45: 0 | G45: 0 | H45: 0 | I45: 0 | J45: 0 | K45: 0 | L45: 0 | M45: 0 | N45: 0 | O45: 0 | P45: 0
A46: Ineffective goods | B46: 0 | C46: 0 | D46: 0 | E46: 0 | F46: 0 | G46: 0 | H46: 0 | I46: 0 | J46: 0 | K46: 0 | L46: 0 | M46: 0 | N46: 0 | O46: 0 | P46: 0
A47: Goods purchased and left in storage until they expire / Cash doesn't reach recipients or is taken back from them inappropriately | B47: 0 | C47: 0 | D47: 0 | E47: 0 | F47: 0 | G47: 0 | H47: 0 | I47: 0 | J47: 0 | K47: 0 | L47: 0 | M47: 0 | N47: 0 | O47: 0 | P47: 0
A48: Total adjustment for risk of wastage | B48: =SUM(B45:B47) -> 0 | C48: =SUM(C45:C47) -> 0 | D48: =SUM(D45:D47) -> 0 | E48: =SUM(E45:E47) -> 0 | F48: =SUM(F45:F47) -> 0 | G48: =SUM(G45:G47) -> 0 | H48: =SUM(H45:H47) -> 0 | I48: =SUM(I45:I47) -> 0 | ... P48: =SUM(P45:P47) -> 0
A50: Quality of monitoring and evaluation
A51: Misappropriation without monitoring results | B51: 0.1 | C51: 0.1 | D51: 0.1 | E51: 0.1 | F51: 0.1 | G51: 0.1 | H51: 0.1 | I51: 0.1 | J51: 0.1 | K51: 0.1 | L51: 0.1 | M51: 0.1 | N51: 0.1 | O51: 0.1 | P51: 0.1
A52: False monitoring results | B52: 0.05 | C52: 0.05 | D52: 0.05 | E52: 0.05 | F52: 0.05 | G52: 0.05 | H52: 0.05 | I52: 0.05 | J52: 0.05 | K52: 0.05 | L52: 0.05 | M52: 0.05 | N52: 0.05 | O52: 0.05 | P52: 0.05
A53: Total adjustment for quality of monitoring and evaluation | B53: =sum(B50:B52) -> 0.15 | C53: =sum(C50:C52) -> 0.15 | D53: =sum(D50:D52) -> 0.15 | E53: =sum(E50:E52) -> 0.15 | F53: =sum(F50:F52) -> 0.15 | G53: =sum(G50:G52) -> 0.15 | H53: =sum(H50:H52) -> 0.15 | I53: =sum(I50:I52) -> 0.15 | ... P53: =sum(P50:P52) -> 0.15
A55: Confidence in funds being used for intended purpose
A56: Change of priorities | B56: 0 | C56: 0 | D56: 0 | E56: 0 | F56: 0 | G56: 0 | H56: 0 | I56: 0 | J56: 0 | K56: 0 | L56: 0 | M56: 0 | N56: 0 | O56: 0 | P56: 0
A57: Non-funding bottlenecks | B57: 0 | C57: 0 | D57: 0 | E57: 0 | F57: 0 | G57: 0 | H57: 0 | I57: 0 | J57: 0 | K57: 0 | L57: 0 | M57: 0 | N57: 0 | O57: 0 | P57: 0
A58: Within-org fungibility | B58: 0 | C58: 0 | D58: 0 | E58: 0 | F58: 0 | G58: 0 | H58: 0 | I58: 0 | J58: 0 | K58: 0 | L58: 0 | M58: 0 | N58: 0 | O58: 0 | P58: 0
A59: Total adjustment for confidence in funds being used for intended purpose | B59: =sum(B56:B58) -> 0 | C59: =sum(C56:C58) -> 0 | D59: =sum(D56:D58) -> 0 | E59: =sum(E56:E58) -> 0 | F59: =sum(F56:F58) -> 0 | G59: =sum(G56:G58) -> 0 | H59: =sum(H56:H58) -> 0 | I59: =sum(I56:I58) -> 0 | ... P59: =sum(P56:P58) -> 0
A61: Total adjustment factor | B61: =1-sum(B48,B53,B59) -> 0.85 | C61: =1-sum(C48,C53,C59) -> 0.85 | D61: =1-sum(D48,D53,D59) -> 0.85 | E61: =1-sum(E48,E53,E59) -> 0.85 | F61: =1-sum(F48,F53,F59) -> 0.85 | G61: =1-sum(G48,G53,G59) -> 0.85 | H61: =1-sum(H48,H53,H59) -> 0.85 | I61: =1-sum(I48,I53,I59) -> 0.85 | ... P61: =1-sum(P48,P53,P59) -> 0.85
A63: Results after supplemental charity-level adjustments
A65: Total units of value generated | B65: =sum(C65:P65) -> 5189.5221 | C65: =C37*C61 -> 612.92929 | D65: =D37*D61 -> 889.81682 | E65: =E37*E61 -> 1709.2724 | F65: =F37*F61 -> 663.31228 | G65: =G37*G61 -> 344.48698 | H65: =H37*H61 -> 34.001323 | I65: =I37*I61 -> 93.803354 | J65: =J37*J61 -> 300.02784 | ... P65: =P37*P61 -> 92.590945
A66: Units of value per dollar spent | B66: =B65/B16 -> 0.020142154 | C66: =C65/C16 -> 0.010162271 | D66: =D65/D16 -> 0.047289578 | E66: =E65/E16 -> 0.050452381 | F66: =F65/F16 -> 0.015502705 | G66: =G65/G16 -> 0.022774522 | H66: =H65/H16 -> 0.0010178763 | I66: =I65/I16 -> 0.029077303 | ... P66: =P65/P16 -> 0.01680957
A67: Cost-effectiveness in multiples of cash transfers, after supplemental charity-level adjustments | B67: {=B66/index(GiveDirectly!$B:$B,match("Units of value generated per philanthropic dollar spent, after accounting for all adjustments",GiveDirectly!$A:$A,0))} -> 6.0044569 | C67: {=C66/index(GiveDirectly!$B:$B,match("Units of value generated per philanthropic dollar spent, after accounting for all adjustments",GiveDirectly!$A:$A,0))} -> 3.0294135 | D67: {=D66/index(GiveDirectly!$B:$B,match("Units of value generated per philanthropic dollar spent, after accounting for all adjustments",GiveDirectly!$A:$A,0))} -> 14.097213 | E67: {=E66/index(GiveDirectly!$B:$B,match("Units of value generated per philanthropic dollar spent, after accounting for all adjustments",GiveDirectly!$A:$A,0))} -> 15.040057 | F67: {=F66/index(GiveDirectly!$B:$B,match("Units of value generated per philanthropic dollar spent, after accounting for all adjustments",GiveDirectly!$A:$A,0))} -> 4.6214184 | G67: {=G66/index(GiveDirectly!$B:$B,match("Units of value generated per philanthropic dollar spent, after accounting for all adjustments",GiveDirectly!$A:$A,0))} -> 6.7891762 | H67: {=H66/index(GiveDirectly!$B:$B,match("Units of value generated per philanthropic dollar spent, after accounting for all adjustments",GiveDirectly!$A:$A,0))} -> 0.30343299 | I67: {=I66/index(GiveDirectly!$B:$B,match("Units of value generated per philanthropic dollar spent, after accounting for all adjustments",GiveDirectly!$A:$A,0))} -> 8.6680606 | ... P67: {=P66/index(GiveDirectly!$B:$B,match("Units of value generated per philanthropic dollar spent, after accounting for all adjustments",GiveDirectly!$A:$A,0))} -> 5.0110002
A69: Adjustments for effects excluded from our core model — Deworming
A70: Outcomes included in our core model (above)
A71: =IFERROR(__xludf.DUMMYFUNCTION("filter('Supplemental intervention-level'!C:C,'Supplemental intervention-level'!A:A=""Deworming"",'Supplemental intervention-level'!D:D=""Explicitly modeled"")"),"Developmental effects") -> Developmental effects
A73: Supplemental intervention-level adjustments
A74: =IFERROR(__xludf.DUMMYFUNCTION("filter('Supplemental intervention-level'!C:C,'Supplemental intervention-level'!A:A=""Deworming"",'Supplemental intervention-level'!D:D=""Not explicitly modeled"",'Supplemental intervention-level'!B:B=""Unlimit HealthDTWI"")"),"Direct health effects") -> Direct health effects | B74: {=iferror(if(isblank($A74),"",index('Supplemental intervention-level'!$M:$M,match(1,('Supplemental intervention-level'!$C:$C=$A74)*('Supplemental intervention-level'!$A:$A="Deworming"),0))),"Not specified")} -> 0.008 | C74: {=iferror(if(isblank($A74),"",index('Supplemental intervention-level'!$M:$M,match(1,('Supplemental intervention-level'!$C:$C=$A74)*('Supplemental intervention-level'!$A:$A="Deworming"),0))),"Not specified")} -> 0.008 | D74: {=iferror(if(isblank($A74),"",index('Supplemental intervention-level'!$M:$M,match(1,('Supplemental intervention-level'!$C:$C=$A74)*('Supplemental intervention-level'!$A:$A="Deworming"),0))),"Not specified")} -> 0.008 | E74: {=iferror(if(isblank($A74),"",index('Supplemental intervention-level'!$M:$M,match(1,('Supplemental intervention-level'!$C:$C=$A74)*('Supplemental intervention-level'!$A:$A="Deworming"),0))),"Not specified")} -> 0.008 | F74: {=iferror(if(isblank($A74),"",index('Supplemental intervention-level'!$M:$M,match(1,('Supplemental intervention-level'!$C:$C=$A74)*('Supplemental intervention-level'!$A:$A="Deworming"),0))),"Not specified")} -> 0.008 | G74: {=iferror(if(isblank($A74),"",index('Supplemental intervention-level'!$M:$M,match(1,('Supplemental intervention-level'!$C:$C=$A74)*('Supplemental intervention-level'!$A:$A="Deworming"),0))),"Not specified")} -> 0.008 | H74: {=iferror(if(isblank($A74),"",index('Supplemental intervention-level'!$M:$M,match(1,('Supplemental intervention-level'!$C:$C=$A74)*('Supplemental intervention-level'!$A:$A="Deworming"),0))),"Not specified")} -> 0.008 | I74: {=iferror(if(isblank($A74),"",index('Supplemental intervention-level'!$M:$M,match(1,('Supplemental intervention-level'!$C:$C=$A74)*('Supplemental intervention-level'!$A:$A="Deworming"),0))),"Not specified")} -> 0.008 | ... P74: {=iferror(if(isblank($A74),"",index('Supplemental intervention-level'!$M:$M,match(1,('Supplemental intervention-level'!$C:$C=$A74)*('Supplemental intervention-level'!$A:$A="Deworming"),0))),"Not specified")} -> 0.008
A75: =IFERROR(__xludf.DUMMYFUNCTION("""COMPUTED_VALUE"""),"HIV reduction") -> HIV reduction | B75: {=iferror(if(isblank($A75),"",index('Supplemental intervention-level'!$M:$M,match(1,('Supplemental intervention-level'!$C:$C=$A75)*('Supplemental intervention-level'!$A:$A="Deworming"),0))),"Not specified")} -> 0.06 | C75: {=iferror(if(isblank($A75),"",index('Supplemental intervention-level'!$M:$M,match(1,('Supplemental intervention-level'!$C:$C=$A75)*('Supplemental intervention-level'!$A:$A="Deworming"),0))),"Not specified")} -> 0.06 | D75: {=iferror(if(isblank($A75),"",index('Supplemental intervention-level'!$M:$M,match(1,('Supplemental intervention-level'!$C:$C=$A75)*('Supplemental intervention-level'!$A:$A="Deworming"),0))),"Not specified")} -> 0.06 | E75: {=iferror(if(isblank($A75),"",index('Supplemental intervention-level'!$M:$M,match(1,('Supplemental intervention-level'!$C:$C=$A75)*('Supplemental intervention-level'!$A:$A="Deworming"),0))),"Not specified")} -> 0.06 | F75: {=iferror(if(isblank($A75),"",index('Supplemental intervention-level'!$M:$M,match(1,('Supplemental intervention-level'!$C:$C=$A75)*('Supplemental intervention-level'!$A:$A="Deworming"),0))),"Not specified")} -> 0.06 | G75: {=iferror(if(isblank($A75),"",index('Supplemental intervention-level'!$M:$M,match(1,('Supplemental intervention-level'!$C:$C=$A75)*('Supplemental intervention-level'!$A:$A="Deworming"),0))),"Not specified")} -> 0.06 | H75: {=iferror(if(isblank($A75),"",index('Supplemental intervention-level'!$M:$M,match(1,('Supplemental intervention-level'!$C:$C=$A75)*('Supplemental intervention-level'!$A:$A="Deworming"),0))),"Not specified")} -> 0.06 | I75: {=iferror(if(isblank($A75),"",index('Supplemental intervention-level'!$M:$M,match(1,('Supplemental intervention-level'!$C:$C=$A75)*('Supplemental intervention-level'!$A:$A="Deworming"),0))),"Not specified")} -> 0.06 | ... P75: {=iferror(if(isblank($A75),"",index('Supplemental intervention-level'!$M:$M,match(1,('Supplemental intervention-level'!$C:$C=$A75)*('Supplemental intervention-level'!$A:$A="Deworming"),0))),"Not specified")} -> 0.06
A76: =IFERROR(__xludf.DUMMYFUNCTION("""COMPUTED_VALUE"""),"Possible increases in diseases of affluence (harms of deworming)") -> Possible increases in diseases of affluence (harms of deworming) | B76: {=iferror(if(isblank($A76),"",index('Supplemental intervention-level'!$M:$M,match(1,('Supplemental intervention-level'!$C:$C=$A76)*('Supplemental intervention-level'!$A:$A="Deworming"),0))),"Not specified")} -> -0.025 | C76: {=iferror(if(isblank($A76),"",index('Supplemental intervention-level'!$M:$M,match(1,('Supplemental intervention-level'!$C:$C=$A76)*('Supplemental intervention-level'!$A:$A="Deworming"),0))),"Not specified")} -> -0.025 | D76: {=iferror(if(isblank($A76),"",index('Supplemental intervention-level'!$M:$M,match(1,('Supplemental intervention-level'!$C:$C=$A76)*('Supplemental intervention-level'!$A:$A="Deworming"),0))),"Not specified")} -> -0.025 | E76: {=iferror(if(isblank($A76),"",index('Supplemental intervention-level'!$M:$M,match(1,('Supplemental intervention-level'!$C:$C=$A76)*('Supplemental intervention-level'!$A:$A="Deworming"),0))),"Not specified")} -> -0.025 | F76: {=iferror(if(isblank($A76),"",index('Supplemental intervention-level'!$M:$M,match(1,('Supplemental intervention-level'!$C:$C=$A76)*('Supplemental intervention-level'!$A:$A="Deworming"),0))),"Not specified")} -> -0.025 | G76: {=iferror(if(isblank($A76),"",index('Supplemental intervention-level'!$M:$M,match(1,('Supplemental intervention-level'!$C:$C=$A76)*('Supplemental intervention-level'!$A:$A="Deworming"),0))),"Not specified")} -> -0.025 | H76: {=iferror(if(isblank($A76),"",index('Supplemental intervention-level'!$M:$M,match(1,('Supplemental intervention-level'!$C:$C=$A76)*('Supplemental intervention-level'!$A:$A="Deworming"),0))),"Not specified")} -> -0.025 | I76: {=iferror(if(isblank($A76),"",index('Supplemental intervention-level'!$M:$M,match(1,('Supplemental intervention-level'!$C:$C=$A76)*('Supplemental intervention-level'!$A:$A="Deworming"),0))),"Not specified")} -> -0.025 | ... P76: {=iferror(if(isblank($A76),"",index('Supplemental intervention-level'!$M:$M,match(1,('Supplemental intervention-level'!$C:$C=$A76)*('Supplemental intervention-level'!$A:$A="Deworming"),0))),"Not specified")} -> -0.025
A77: =IFERROR(__xludf.DUMMYFUNCTION("""COMPUTED_VALUE"""),"Averted mortality") -> Averted mortality | B77: {=iferror(if(isblank($A77),"",index('Supplemental intervention-level'!$M:$M,match(1,('Supplemental intervention-level'!$C:$C=$A77)*('Supplemental intervention-level'!$A:$A="Deworming"),0))),"Not specified")} -> 0.035 | C77: {=iferror(if(isblank($A77),"",index('Supplemental intervention-level'!$M:$M,match(1,('Supplemental intervention-level'!$C:$C=$A77)*('Supplemental intervention-level'!$A:$A="Deworming"),0))),"Not specified")} -> 0.035 | D77: {=iferror(if(isblank($A77),"",index('Supplemental intervention-level'!$M:$M,match(1,('Supplemental intervention-level'!$C:$C=$A77)*('Supplemental intervention-level'!$A:$A="Deworming"),0))),"Not specified")} -> 0.035 | E77: {=iferror(if(isblank($A77),"",index('Supplemental intervention-level'!$M:$M,match(1,('Supplemental intervention-level'!$C:$C=$A77)*('Supplemental intervention-level'!$A:$A="Deworming"),0))),"Not specified")} -> 0.035 | F77: {=iferror(if(isblank($A77),"",index('Supplemental intervention-level'!$M:$M,match(1,('Supplemental intervention-level'!$C:$C=$A77)*('Supplemental intervention-level'!$A:$A="Deworming"),0))),"Not specified")} -> 0.035 | G77: {=iferror(if(isblank($A77),"",index('Supplemental intervention-level'!$M:$M,match(1,('Supplemental intervention-level'!$C:$C=$A77)*('Supplemental intervention-level'!$A:$A="Deworming"),0))),"Not specified")} -> 0.035 | H77: {=iferror(if(isblank($A77),"",index('Supplemental intervention-level'!$M:$M,match(1,('Supplemental intervention-level'!$C:$C=$A77)*('Supplemental intervention-level'!$A:$A="Deworming"),0))),"Not specified")} -> 0.035 | I77: {=iferror(if(isblank($A77),"",index('Supplemental intervention-level'!$M:$M,match(1,('Supplemental intervention-level'!$C:$C=$A77)*('Supplemental intervention-level'!$A:$A="Deworming"),0))),"Not specified")} -> 0.035 | ... P77: {=iferror(if(isblank($A77),"",index('Supplemental intervention-level'!$M:$M,match(1,('Supplemental intervention-level'!$C:$C=$A77)*('Supplemental intervention-level'!$A:$A="Deworming"),0))),"Not specified")} -> 0.035
A78: =IFERROR(__xludf.DUMMYFUNCTION("""COMPUTED_VALUE"""),"Short-term anemia effects") -> Short-term anemia effects | B78: {=iferror(if(isblank($A78),"",index('Supplemental intervention-level'!$M:$M,match(1,('Supplemental intervention-level'!$C:$C=$A78)*('Supplemental intervention-level'!$A:$A="Deworming"),0))),"Not specified")} -> 0.09 | C78: {=iferror(if(isblank($A78),"",index('Supplemental intervention-level'!$M:$M,match(1,('Supplemental intervention-level'!$C:$C=$A78)*('Supplemental intervention-level'!$A:$A="Deworming"),0))),"Not specified")} -> 0.09 | D78: {=iferror(if(isblank($A78),"",index('Supplemental intervention-level'!$M:$M,match(1,('Supplemental intervention-level'!$C:$C=$A78)*('Supplemental intervention-level'!$A:$A="Deworming"),0))),"Not specified")} -> 0.09 | E78: {=iferror(if(isblank($A78),"",index('Supplemental intervention-level'!$M:$M,match(1,('Supplemental intervention-level'!$C:$C=$A78)*('Supplemental intervention-level'!$A:$A="Deworming"),0))),"Not specified")} -> 0.09 | F78: {=iferror(if(isblank($A78),"",index('Supplemental intervention-level'!$M:$M,match(1,('Supplemental intervention-level'!$C:$C=$A78)*('Supplemental intervention-level'!$A:$A="Deworming"),0))),"Not specified")} -> 0.09 | G78: {=iferror(if(isblank($A78),"",index('Supplemental intervention-level'!$M:$M,match(1,('Supplemental intervention-level'!$C:$C=$A78)*('Supplemental intervention-level'!$A:$A="Deworming"),0))),"Not specified")} -> 0.09 | H78: {=iferror(if(isblank($A78),"",index('Supplemental intervention-level'!$M:$M,match(1,('Supplemental intervention-level'!$C:$C=$A78)*('Supplemental intervention-level'!$A:$A="Deworming"),0))),"Not specified")} -> 0.09 | I78: {=iferror(if(isblank($A78),"",index('Supplemental intervention-level'!$M:$M,match(1,('Supplemental intervention-level'!$C:$C=$A78)*('Supplemental intervention-level'!$A:$A="Deworming"),0))),"Not specified")} -> 0.09 | ... P78: {=iferror(if(isblank($A78),"",index('Supplemental intervention-level'!$M:$M,match(1,('Supplemental intervention-level'!$C:$C=$A78)*('Supplemental intervention-level'!$A:$A="Deworming"),0))),"Not specified")} -> 0.09
A79: =IFERROR(__xludf.DUMMYFUNCTION("""COMPUTED_VALUE"""),"Investment of income increases") -> Investment of income increases | B79: {=iferror(if(isblank($A79),"",index('Supplemental intervention-level'!$M:$M,match(1,('Supplemental intervention-level'!$C:$C=$A79)*('Supplemental intervention-level'!$A:$A="Deworming"),0))),"Not specified")} -> 0.1 | C79: {=iferror(if(isblank($A79),"",index('Supplemental intervention-level'!$M:$M,match(1,('Supplemental intervention-level'!$C:$C=$A79)*('Supplemental intervention-level'!$A:$A="Deworming"),0))),"Not specified")} -> 0.1 | D79: {=iferror(if(isblank($A79),"",index('Supplemental intervention-level'!$M:$M,match(1,('Supplemental intervention-level'!$C:$C=$A79)*('Supplemental intervention-level'!$A:$A="Deworming"),0))),"Not specified")} -> 0.1 | E79: {=iferror(if(isblank($A79),"",index('Supplemental intervention-level'!$M:$M,match(1,('Supplemental intervention-level'!$C:$C=$A79)*('Supplemental intervention-level'!$A:$A="Deworming"),0))),"Not specified")} -> 0.1 | F79: {=iferror(if(isblank($A79),"",index('Supplemental intervention-level'!$M:$M,match(1,('Supplemental intervention-level'!$C:$C=$A79)*('Supplemental intervention-level'!$A:$A="Deworming"),0))),"Not specified")} -> 0.1 | G79: {=iferror(if(isblank($A79),"",index('Supplemental intervention-level'!$M:$M,match(1,('Supplemental intervention-level'!$C:$C=$A79)*('Supplemental intervention-level'!$A:$A="Deworming"),0))),"Not specified")} -> 0.1 | H79: {=iferror(if(isblank($A79),"",index('Supplemental intervention-level'!$M:$M,match(1,('Supplemental intervention-level'!$C:$C=$A79)*('Supplemental intervention-level'!$A:$A="Deworming"),0))),"Not specified")} -> 0.1 | I79: {=iferror(if(isblank($A79),"",index('Supplemental intervention-level'!$M:$M,match(1,('Supplemental intervention-level'!$C:$C=$A79)*('Supplemental intervention-level'!$A:$A="Deworming"),0))),"Not specified")} -> 0.1 | ... P79: {=iferror(if(isblank($A79),"",index('Supplemental intervention-level'!$M:$M,match(1,('Supplemental intervention-level'!$C:$C=$A79)*('Supplemental intervention-level'!$A:$A="Deworming"),0))),"Not specified")} -> 0.1
A80: =IFERROR(__xludf.DUMMYFUNCTION("""COMPUTED_VALUE"""),"Non-income long-run benefits of deworming") -> Non-income long-run benefits of deworming | B80: {=iferror(if(isblank($A80),"",index('Supplemental intervention-level'!$M:$M,match(1,('Supplemental intervention-level'!$C:$C=$A80)*('Supplemental intervention-level'!$A:$A="Deworming"),0))),"Not specified")} -> 0.04 | C80: {=iferror(if(isblank($A80),"",index('Supplemental intervention-level'!$M:$M,match(1,('Supplemental intervention-level'!$C:$C=$A80)*('Supplemental intervention-level'!$A:$A="Deworming"),0))),"Not specified")} -> 0.04 | D80: {=iferror(if(isblank($A80),"",index('Supplemental intervention-level'!$M:$M,match(1,('Supplemental intervention-level'!$C:$C=$A80)*('Supplemental intervention-level'!$A:$A="Deworming"),0))),"Not specified")} -> 0.04 | E80: {=iferror(if(isblank($A80),"",index('Supplemental intervention-level'!$M:$M,match(1,('Supplemental intervention-level'!$C:$C=$A80)*('Supplemental intervention-level'!$A:$A="Deworming"),0))),"Not specified")} -> 0.04 | F80: {=iferror(if(isblank($A80),"",index('Supplemental intervention-level'!$M:$M,match(1,('Supplemental intervention-level'!$C:$C=$A80)*('Supplemental intervention-level'!$A:$A="Deworming"),0))),"Not specified")} -> 0.04 | G80: {=iferror(if(isblank($A80),"",index('Supplemental intervention-level'!$M:$M,match(1,('Supplemental intervention-level'!$C:$C=$A80)*('Supplemental intervention-level'!$A:$A="Deworming"),0))),"Not specified")} -> 0.04 | H80: {=iferror(if(isblank($A80),"",index('Supplemental intervention-level'!$M:$M,match(1,('Supplemental intervention-level'!$C:$C=$A80)*('Supplemental intervention-level'!$A:$A="Deworming"),0))),"Not specified")} -> 0.04 | I80: {=iferror(if(isblank($A80),"",index('Supplemental intervention-level'!$M:$M,match(1,('Supplemental intervention-level'!$C:$C=$A80)*('Supplemental intervention-level'!$A:$A="Deworming"),0))),"Not specified")} -> 0.04 | ... P80: {=iferror(if(isblank($A80),"",index('Supplemental intervention-level'!$M:$M,match(1,('Supplemental intervention-level'!$C:$C=$A80)*('Supplemental intervention-level'!$A:$A="Deworming"),0))),"Not specified")} -> 0.04
A81: =IFERROR(__xludf.DUMMYFUNCTION("""COMPUTED_VALUE"""),"Drug resistance") -> Drug resistance | B81: {=iferror(if(isblank($A81),"",index('Supplemental intervention-level'!$M:$M,match(1,('Supplemental intervention-level'!$C:$C=$A81)*('Supplemental intervention-level'!$A:$A="Deworming"),0))),"Not specified")} -> -0.04 | C81: {=iferror(if(isblank($A81),"",index('Supplemental intervention-level'!$M:$M,match(1,('Supplemental intervention-level'!$C:$C=$A81)*('Supplemental intervention-level'!$A:$A="Deworming"),0))),"Not specified")} -> -0.04 | D81: {=iferror(if(isblank($A81),"",index('Supplemental intervention-level'!$M:$M,match(1,('Supplemental intervention-level'!$C:$C=$A81)*('Supplemental intervention-level'!$A:$A="Deworming"),0))),"Not specified")} -> -0.04 | E81: {=iferror(if(isblank($A81),"",index('Supplemental intervention-level'!$M:$M,match(1,('Supplemental intervention-level'!$C:$C=$A81)*('Supplemental intervention-level'!$A:$A="Deworming"),0))),"Not specified")} -> -0.04 | F81: {=iferror(if(isblank($A81),"",index('Supplemental intervention-level'!$M:$M,match(1,('Supplemental intervention-level'!$C:$C=$A81)*('Supplemental intervention-level'!$A:$A="Deworming"),0))),"Not specified")} -> -0.04 | G81: {=iferror(if(isblank($A81),"",index('Supplemental intervention-level'!$M:$M,match(1,('Supplemental intervention-level'!$C:$C=$A81)*('Supplemental intervention-level'!$A:$A="Deworming"),0))),"Not specified")} -> -0.04 | H81: {=iferror(if(isblank($A81),"",index('Supplemental intervention-level'!$M:$M,match(1,('Supplemental intervention-level'!$C:$C=$A81)*('Supplemental intervention-level'!$A:$A="Deworming"),0))),"Not specified")} -> -0.04 | I81: {=iferror(if(isblank($A81),"",index('Supplemental intervention-level'!$M:$M,match(1,('Supplemental intervention-level'!$C:$C=$A81)*('Supplemental intervention-level'!$A:$A="Deworming"),0))),"Not specified")} -> -0.04 | ... P81: {=iferror(if(isblank($A81),"",index('Supplemental intervention-level'!$M:$M,match(1,('Supplemental intervention-level'!$C:$C=$A81)*('Supplemental intervention-level'!$A:$A="Deworming"),0))),"Not specified")} -> -0.04
A82: =IFERROR(__xludf.DUMMYFUNCTION("""COMPUTED_VALUE"""),"Unprogrammed deworming") -> Unprogrammed deworming | B82: {=iferror(if(isblank($A82),"",index('Supplemental intervention-level'!$M:$M,match(1,('Supplemental intervention-level'!$C:$C=$A82)*('Supplemental intervention-level'!$A:$A="Deworming"),0))),"Not specified")} -> -0.14 | C82: {=iferror(if(isblank($A82),"",index('Supplemental intervention-level'!$M:$M,match(1,('Supplemental intervention-level'!$C:$C=$A82)*('Supplemental intervention-level'!$A:$A="Deworming"),0))),"Not specified")} -> -0.14 | D82: {=iferror(if(isblank($A82),"",index('Supplemental intervention-level'!$M:$M,match(1,('Supplemental intervention-level'!$C:$C=$A82)*('Supplemental intervention-level'!$A:$A="Deworming"),0))),"Not specified")} -> -0.14 | E82: {=iferror(if(isblank($A82),"",index('Supplemental intervention-level'!$M:$M,match(1,('Supplemental intervention-level'!$C:$C=$A82)*('Supplemental intervention-level'!$A:$A="Deworming"),0))),"Not specified")} -> -0.14 | F82: {=iferror(if(isblank($A82),"",index('Supplemental intervention-level'!$M:$M,match(1,('Supplemental intervention-level'!$C:$C=$A82)*('Supplemental intervention-level'!$A:$A="Deworming"),0))),"Not specified")} -> -0.14 | G82: {=iferror(if(isblank($A82),"",index('Supplemental intervention-level'!$M:$M,match(1,('Supplemental intervention-level'!$C:$C=$A82)*('Supplemental intervention-level'!$A:$A="Deworming"),0))),"Not specified")} -> -0.14 | H82: {=iferror(if(isblank($A82),"",index('Supplemental intervention-level'!$M:$M,match(1,('Supplemental intervention-level'!$C:$C=$A82)*('Supplemental intervention-level'!$A:$A="Deworming"),0))),"Not specified")} -> -0.14 | I82: {=iferror(if(isblank($A82),"",index('Supplemental intervention-level'!$M:$M,match(1,('Supplemental intervention-level'!$C:$C=$A82)*('Supplemental intervention-level'!$A:$A="Deworming"),0))),"Not specified")} -> -0.14 | ... P82: {=iferror(if(isblank($A82),"",index('Supplemental intervention-level'!$M:$M,match(1,('Supplemental intervention-level'!$C:$C=$A82)*('Supplemental intervention-level'!$A:$A="Deworming"),0))),"Not specified")} -> -0.14
A83: =IFERROR(__xludf.DUMMYFUNCTION("""COMPUTED_VALUE"""),"Marginal funding goes to lower priority areas") -> Marginal funding goes to lower priority areas | B83: {=iferror(if(isblank($A83),"",index('Supplemental intervention-level'!$M:$M,match(1,('Supplemental intervention-level'!$C:$C=$A83)*('Supplemental intervention-level'!$A:$A="Deworming"),0))),"Not specified")} -> -0.025 | C83: {=iferror(if(isblank($A83),"",index('Supplemental intervention-level'!$M:$M,match(1,('Supplemental intervention-level'!$C:$C=$A83)*('Supplemental intervention-level'!$A:$A="Deworming"),0))),"Not specified")} -> -0.025 | D83: {=iferror(if(isblank($A83),"",index('Supplemental intervention-level'!$M:$M,match(1,('Supplemental intervention-level'!$C:$C=$A83)*('Supplemental intervention-level'!$A:$A="Deworming"),0))),"Not specified")} -> -0.025 | E83: {=iferror(if(isblank($A83),"",index('Supplemental intervention-level'!$M:$M,match(1,('Supplemental intervention-level'!$C:$C=$A83)*('Supplemental intervention-level'!$A:$A="Deworming"),0))),"Not specified")} -> -0.025 | F83: {=iferror(if(isblank($A83),"",index('Supplemental intervention-level'!$M:$M,match(1,('Supplemental intervention-level'!$C:$C=$A83)*('Supplemental intervention-level'!$A:$A="Deworming"),0))),"Not specified")} -> -0.025 | G83: {=iferror(if(isblank($A83),"",index('Supplemental intervention-level'!$M:$M,match(1,('Supplemental intervention-level'!$C:$C=$A83)*('Supplemental intervention-level'!$A:$A="Deworming"),0))),"Not specified")} -> -0.025 | H83: {=iferror(if(isblank($A83),"",index('Supplemental intervention-level'!$M:$M,match(1,('Supplemental intervention-level'!$C:$C=$A83)*('Supplemental intervention-level'!$A:$A="Deworming"),0))),"Not specified")} -> -0.025 | I83: {=iferror(if(isblank($A83),"",index('Supplemental intervention-level'!$M:$M,match(1,('Supplemental intervention-level'!$C:$C=$A83)*('Supplemental intervention-level'!$A:$A="Deworming"),0))),"Not specified")} -> -0.025 | ... P83: {=iferror(if(isblank($A83),"",index('Supplemental intervention-level'!$M:$M,match(1,('Supplemental intervention-level'!$C:$C=$A83)*('Supplemental intervention-level'!$A:$A="Deworming"),0))),"Not specified")} -> -0.025
A84: =IFERROR(__xludf.DUMMYFUNCTION("""COMPUTED_VALUE"""),"General equilibrium effects") -> General equilibrium effects | B84: {=iferror(if(isblank($A84),"",index('Supplemental intervention-level'!$M:$M,match(1,('Supplemental intervention-level'!$C:$C=$A84)*('Supplemental intervention-level'!$A:$A="Deworming"),0))),"Not specified")} -> -0.03 | C84: {=iferror(if(isblank($A84),"",index('Supplemental intervention-level'!$M:$M,match(1,('Supplemental intervention-level'!$C:$C=$A84)*('Supplemental intervention-level'!$A:$A="Deworming"),0))),"Not specified")} -> -0.03 | D84: {=iferror(if(isblank($A84),"",index('Supplemental intervention-level'!$M:$M,match(1,('Supplemental intervention-level'!$C:$C=$A84)*('Supplemental intervention-level'!$A:$A="Deworming"),0))),"Not specified")} -> -0.03 | E84: {=iferror(if(isblank($A84),"",index('Supplemental intervention-level'!$M:$M,match(1,('Supplemental intervention-level'!$C:$C=$A84)*('Supplemental intervention-level'!$A:$A="Deworming"),0))),"Not specified")} -> -0.03 | F84: {=iferror(if(isblank($A84),"",index('Supplemental intervention-level'!$M:$M,match(1,('Supplemental intervention-level'!$C:$C=$A84)*('Supplemental intervention-level'!$A:$A="Deworming"),0))),"Not specified")} -> -0.03 | G84: {=iferror(if(isblank($A84),"",index('Supplemental intervention-level'!$M:$M,match(1,('Supplemental intervention-level'!$C:$C=$A84)*('Supplemental intervention-level'!$A:$A="Deworming"),0))),"Not specified")} -> -0.03 | H84: {=iferror(if(isblank($A84),"",index('Supplemental intervention-level'!$M:$M,match(1,('Supplemental intervention-level'!$C:$C=$A84)*('Supplemental intervention-level'!$A:$A="Deworming"),0))),"Not specified")} -> -0.03 | I84: {=iferror(if(isblank($A84),"",index('Supplemental intervention-level'!$M:$M,match(1,('Supplemental intervention-level'!$C:$C=$A84)*('Supplemental intervention-level'!$A:$A="Deworming"),0))),"Not specified")} -> -0.03 | ... P84: {=iferror(if(isblank($A84),"",index('Supplemental intervention-level'!$M:$M,match(1,('Supplemental intervention-level'!$C:$C=$A84)*('Supplemental intervention-level'!$A:$A="Deworming"),0))),"Not specified")} -> -0.03
B85: {=iferror(if(isblank($A85),"",index('Supplemental intervention-level'!$M:$M,match(1,('Supplemental intervention-level'!$C:$C=$A85)*('Supplemental intervention-level'!$A:$A="Deworming"),0))),"Not specified")} | C85: {=iferror(if(isblank($A85),"",index('Supplemental intervention-level'!$M:$M,match(1,('Supplemental intervention-level'!$C:$C=$A85)*('Supplemental intervention-level'!$A:$A="Deworming"),0))),"Not specified")} | D85: {=iferror(if(isblank($A85),"",index('Supplemental intervention-level'!$M:$M,match(1,('Supplemental intervention-level'!$C:$C=$A85)*('Supplemental intervention-level'!$A:$A="Deworming"),0))),"Not specified")} | E85: {=iferror(if(isblank($A85),"",index('Supplemental intervention-level'!$M:$M,match(1,('Supplemental intervention-level'!$C:$C=$A85)*('Supplemental intervention-level'!$A:$A="Deworming"),0))),"Not specified")} | F85: {=iferror(if(isblank($A85),"",index('Supplemental intervention-level'!$M:$M,match(1,('Supplemental intervention-level'!$C:$C=$A85)*('Supplemental intervention-level'!$A:$A="Deworming"),0))),"Not specified")} | G85: {=iferror(if(isblank($A85),"",index('Supplemental intervention-level'!$M:$M,match(1,('Supplemental intervention-level'!$C:$C=$A85)*('Supplemental intervention-level'!$A:$A="Deworming"),0))),"Not specified")} | H85: {=iferror(if(isblank($A85),"",index('Supplemental intervention-level'!$M:$M,match(1,('Supplemental intervention-level'!$C:$C=$A85)*('Supplemental intervention-level'!$A:$A="Deworming"),0))),"Not specified")} | I85: {=iferror(if(isblank($A85),"",index('Supplemental intervention-level'!$M:$M,match(1,('Supplemental intervention-level'!$C:$C=$A85)*('Supplemental intervention-level'!$A:$A="Deworming"),0))),"Not specified")} | ... P85: {=iferror(if(isblank($A85),"",index('Supplemental intervention-level'!$M:$M,match(1,('Supplemental intervention-level'!$C:$C=$A85)*('Supplemental intervention-level'!$A:$A="Deworming"),0))),"Not specified")}
B86: {=iferror(if(isblank($A86),"",index('Supplemental intervention-level'!$M:$M,match(1,('Supplemental intervention-level'!$C:$C=$A86)*('Supplemental intervention-level'!$A:$A="Deworming"),0))),"Not specified")} | C86: {=iferror(if(isblank($A86),"",index('Supplemental intervention-level'!$M:$M,match(1,('Supplemental intervention-level'!$C:$C=$A86)*('Supplemental intervention-level'!$A:$A="Deworming"),0))),"Not specified")} | D86: {=iferror(if(isblank($A86),"",index('Supplemental intervention-level'!$M:$M,match(1,('Supplemental intervention-level'!$C:$C=$A86)*('Supplemental intervention-level'!$A:$A="Deworming"),0))),"Not specified")} | E86: {=iferror(if(isblank($A86),"",index('Supplemental intervention-level'!$M:$M,match(1,('Supplemental intervention-level'!$C:$C=$A86)*('Supplemental intervention-level'!$A:$A="Deworming"),0))),"Not specified")} | F86: {=iferror(if(isblank($A86),"",index('Supplemental intervention-level'!$M:$M,match(1,('Supplemental intervention-level'!$C:$C=$A86)*('Supplemental intervention-level'!$A:$A="Deworming"),0))),"Not specified")} | G86: {=iferror(if(isblank($A86),"",index('Supplemental intervention-level'!$M:$M,match(1,('Supplemental intervention-level'!$C:$C=$A86)*('Supplemental intervention-level'!$A:$A="Deworming"),0))),"Not specified")} | H86: {=iferror(if(isblank($A86),"",index('Supplemental intervention-level'!$M:$M,match(1,('Supplemental intervention-level'!$C:$C=$A86)*('Supplemental intervention-level'!$A:$A="Deworming"),0))),"Not specified")} | I86: {=iferror(if(isblank($A86),"",index('Supplemental intervention-level'!$M:$M,match(1,('Supplemental intervention-level'!$C:$C=$A86)*('Supplemental intervention-level'!$A:$A="Deworming"),0))),"Not specified")} | ... P86: {=iferror(if(isblank($A86),"",index('Supplemental intervention-level'!$M:$M,match(1,('Supplemental intervention-level'!$C:$C=$A86)*('Supplemental intervention-level'!$A:$A="Deworming"),0))),"Not specified")}
A87: Total adjustment factor | B87: =1+sum(B73:B86) -> 1.073 | C87: =1+sum(C73:C86) -> 1.073 | D87: =1+sum(D73:D86) -> 1.073 | E87: =1+sum(E73:E86) -> 1.073 | F87: =1+sum(F73:F86) -> 1.073 | G87: =1+sum(G73:G86) -> 1.073 | H87: =1+sum(H73:H86) -> 1.073 | I87: =1+sum(I73:I86) -> 1.073 | ... P87: =1+sum(P73:P86) -> 1.073
A89: Results after supplemental intervention-level adjustments
A90: Total units of value generated, before accounting for leverage and funging | B90: =sum(C90:P90) -> 5568.3572 | C90: =C65*C87 -> 657.67313 | D90: =D65*D87 -> 954.77344 | E90: =E65*E87 -> 1834.0493 | F90: =F65*F87 -> 711.73408 | G90: =G65*G87 -> 369.63452 | H90: =H65*H87 -> 36.48342 | I90: =I65*I87 -> 100.651 | J90: =J65*J87 -> 321.92988 | ... P90: =P65*P87 -> 99.350084
A91: Units of value generated per dollar spent, before accounting for leverage/funging | B91: =B90/B16 -> 0.021612532 | C91: =C90/C16 -> 0.010904116 | D91: =D90/D16 -> 0.050741717 | E91: =E90/E16 -> 0.054135405 | F91: =F90/F16 -> 0.016634402 | G91: =G90/G16 -> 0.024437062 | H91: =H90/H16 -> 0.0010921812 | I91: =I90/I16 -> 0.031199947 | ... P91: =P90/P16 -> 0.018036669
A93: Cost-effectiveness in multiples of cash transfers, after supplemental intervention-level adjustments | B93: {=B91/index(GiveDirectly!$B:$B,match("Units of value generated per philanthropic dollar spent, after accounting for all adjustments",GiveDirectly!$A:$A,0))} -> 6.4427822 | C93: {=C91/index(GiveDirectly!$B:$B,match("Units of value generated per philanthropic dollar spent, after accounting for all adjustments",GiveDirectly!$A:$A,0))} -> 3.2505607 | D93: {=D91/index(GiveDirectly!$B:$B,match("Units of value generated per philanthropic dollar spent, after accounting for all adjustments",GiveDirectly!$A:$A,0))} -> 15.126309 | E93: {=E91/index(GiveDirectly!$B:$B,match("Units of value generated per philanthropic dollar spent, after accounting for all adjustments",GiveDirectly!$A:$A,0))} -> 16.137981 | F93: {=F91/index(GiveDirectly!$B:$B,match("Units of value generated per philanthropic dollar spent, after accounting for all adjustments",GiveDirectly!$A:$A,0))} -> 4.958782 | G93: {=G91/index(GiveDirectly!$B:$B,match("Units of value generated per philanthropic dollar spent, after accounting for all adjustments",GiveDirectly!$A:$A,0))} -> 7.2847861 | H93: {=H91/index(GiveDirectly!$B:$B,match("Units of value generated per philanthropic dollar spent, after accounting for all adjustments",GiveDirectly!$A:$A,0))} -> 0.3255836 | I93: {=I91/index(GiveDirectly!$B:$B,match("Units of value generated per philanthropic dollar spent, after accounting for all adjustments",GiveDirectly!$A:$A,0))} -> 9.300829 | ... P93: {=P91/index(GiveDirectly!$B:$B,match("Units of value generated per philanthropic dollar spent, after accounting for all adjustments",GiveDirectly!$A:$A,0))} -> 5.3768032
A95: Leverage/Funging adjustment
A97: Cost per person dewormed per year breakdown:
A98: Philanthropic actors | B98: =B8*B$23 -> 0.3993739 | C98: =C8*C$23 -> 0.3993739 | D98: =D8*D$23 -> 0.3993739 | E98: =E8*E$23 -> 0.3993739 | F98: =F8*F$23 -> 0.3993739 | G98: =G8*G$23 -> 0.3993739 | H98: =H8*H$23 -> 0.3993739 | I98: =I8*I$23 -> 0.3993739 | ... P98: =P8*P$23 -> 0.3993739
A99: Government financial costs | B99: =B9*B$23 -> 0 | C99: =C9*C$23 -> 0 | D99: =D9*D$23 -> 0 | E99: =E9*E$23 -> 0 | F99: =F9*F$23 -> 0 | G99: =G9*G$23 -> 0 | H99: =H9*H$23 -> 0 | I99: =I9*I$23 -> 0 | ... P99: =P9*P$23 -> 0
A100: Government in-kind costs | B100: =B10*B$23 -> 0.30868987 | C100: =C10*C$23 -> 0.30868987 | D100: =D10*D$23 -> 0.30868987 | E100: =E10*E$23 -> 0.30868987 | F100: =F10*F$23 -> 0.30868987 | G100: =G10*G$23 -> 0.30868987 | H100: =H10*H$23 -> 0.30868987 | I100: =I10*I$23 -> 0.30868987 | ... P100: =P10*P$23 -> 0.30868987
A101: Donated drug costs | B101: =B11*B$23 -> 0.32090246 | C101: =C11*C$23 -> 0.32090246 | D101: =D11*D$23 -> 0.32090246 | E101: =E11*E$23 -> 0.32090246 | F101: =F11*F$23 -> 0.32090246 | G101: =G11*G$23 -> 0.32090246 | H101: =H11*H$23 -> 0.32090246 | I101: =I11*I$23 -> 0.32090246 | ... P101: =P11*P$23 -> 0.32090246
A102: Total costs | B102: =sum(B98:B101) -> 1.0289662 | C102: =sum(C98:C101) -> 1.0289662 | D102: =sum(D98:D101) -> 1.0289662 | E102: =sum(E98:E101) -> 1.0289662 | F102: =sum(F98:F101) -> 1.0289662 | G102: =sum(G98:G101) -> 1.0289662 | H102: =sum(H98:H101) -> 1.0289662 | I102: =sum(I98:I101) -> 1.0289662 | ... P102: =sum(P98:P101) -> 1.0289662
A103: CHECKSUM | B103: =(B102-B23)/B102 -> 0 | C103: =(C102-C23)/C102 -> 0 | D103: =(D102-D23)/D102 -> 0 | E103: =(E102-E23)/E102 -> 0 | F103: =(F102-F23)/F102 -> 0 | G103: =(G102-G23)/G102 -> 0 | H103: =(H102-H23)/H102 -> 0 | I103: =(I102-I23)/I102 -> 0 | ... P103: =(P102-P23)/P102 -> 0
A105: Total expenditure attributable to different actors:
A106: Philanthropic actors | B106: =B15 -> 100000 | C106: =C15 -> 23409.826 | D106: =D15 -> 7303.2089 | E106: =E15 -> 13149.468 | F106: =F15 -> 16606.921 | G106: =G15 -> 5870.865 | H106: =H15 -> 12965.205 | I106: =I15 -> 1252.1109 | ... P106: =P15 -> 2137.9152
A107: Government financial costs | B107: =sum(C107:P107) -> 0 | C107: =C9*C$16 -> 0 | D107: =D9*D$16 -> 0 | E107: =E9*E$16 -> 0 | F107: =F9*F$16 -> 0 | G107: =G9*G$16 -> 0 | H107: =H9*H$16 -> 0 | I107: =I9*I$16 -> 0 | J107: =J9*J$16 -> 0 | ... P107: =P9*P$16 -> 0
A108: Government in-kind costs | B108: =sum(C108:P108) -> 77293.451 | C108: =C10*C$16 -> 18094.262 | D108: =D10*D$16 -> 5644.9022 | E108: =E10*E$16 -> 10163.678 | F108: =F10*F$16 -> 12836.062 | G108: =G10*G$16 -> 4537.7941 | H108: =H10*H$16 -> 10021.254 | I108: =I10*I$16 -> 967.79972 | J108: =J10*J$16 -> 2908.9416 | ... P108: =P10*P$16 -> 1652.4684
A109: Donated drug costs | B109: =sum(C109:P109) -> 80351.385 | C109: =C11*C$16 -> 18810.119 | D109: =D11*D$16 -> 5868.2296 | E109: =E11*E$16 -> 10565.78 | F109: =F11*F$16 -> 13343.891 | G109: =G11*G$16 -> 4717.3213 | H109: =H11*H$16 -> 10417.722 | I109: =I11*I$16 -> 1006.0885 | J109: =J11*J$16 -> 3024.0271 | ... P109: =P11*P$16 -> 1717.8445
A110: Total expenditure | B110: =sum(B106:B109) -> 257644.84 | C110: =sum(C106:C109) -> 60314.207 | D110: =sum(D106:D109) -> 18816.341 | E110: =sum(E106:E109) -> 33878.925 | F110: =sum(F106:F109) -> 42786.874 | G110: =sum(G106:G109) -> 15125.98 | H110: =sum(H106:H109) -> 33404.181 | I110: =sum(I106:I109) -> 3225.9991 | ... P110: =sum(P106:P109) -> 5508.228
A112: Upstream / downstream expenditure
A113: Expenditure causally upstream of our donation | B113: =B106+B107 -> 100000 | C113: =C106+C107 -> 23409.826 | D113: =D106+D107 -> 7303.2089 | E113: =E106+E107 -> 13149.468 | F113: =F106+F107 -> 16606.921 | G113: =G106+G107 -> 5870.865 | H113: =H106+H107 -> 12965.205 | I113: =I106+I107 -> 1252.1109 | ... P113: =P106+P107 -> 2137.9152
A114: Expenditure causally downstream of our donation | B114: =B108+B109 -> 157644.84 | C114: =C108+C109 -> 36904.381 | D114: =D108+D109 -> 11513.132 | E114: =E108+E109 -> 20729.457 | F114: =F108+F109 -> 26179.953 | G114: =G108+G109 -> 9255.1154 | H114: =H108+H109 -> 20438.976 | I114: =I108+I109 -> 1973.8882 | ... P114: =P108+P109 -> 3370.3129
A116: Counterfactual value of spending from non-philanthropic actors (units of value per dollar)
A117: Domestic government financial costs | B117: ='Value of counterfactual spendin'!$B$41 -> 0.0035787122 | C117: ='Value of counterfactual spendin'!$B$41 -> 0.0035787122 | D117: ='Value of counterfactual spendin'!$B$41 -> 0.0035787122 | E117: ='Value of counterfactual spendin'!$B$41 -> 0.0035787122 | F117: ='Value of counterfactual spendin'!$B$41 -> 0.0035787122 | G117: ='Value of counterfactual spendin'!$B$41 -> 0.0035787122 | H117: ='Value of counterfactual spendin'!$B$41 -> 0.0035787122 | I117: ='Value of counterfactual spendin'!$B$41 -> 0.0035787122 | ... P117: ='Value of counterfactual spendin'!$B$41 -> 0.0035787122
A118: Domestic government in-kind costs | B118: ='Value of counterfactual spendin'!$B$41 -> 0.0035787122 | C118: ='Value of counterfactual spendin'!$B$41 -> 0.0035787122 | D118: ='Value of counterfactual spendin'!$B$41 -> 0.0035787122 | E118: ='Value of counterfactual spendin'!$B$41 -> 0.0035787122 | F118: ='Value of counterfactual spendin'!$B$41 -> 0.0035787122 | G118: ='Value of counterfactual spendin'!$B$41 -> 0.0035787122 | H118: ='Value of counterfactual spendin'!$B$41 -> 0.0035787122 | I118: ='Value of counterfactual spendin'!$B$41 -> 0.0035787122 | ... P118: ='Value of counterfactual spendin'!$B$41 -> 0.0035787122
A119: Donated drug costs | B119: ='Value of counterfactual spendin'!$B$43 -> 0.0039318303 | C119: ='Value of counterfactual spendin'!$B$43 -> 0.0039318303 | D119: ='Value of counterfactual spendin'!$B$43 -> 0.0039318303 | E119: ='Value of counterfactual spendin'!$B$43 -> 0.0039318303 | F119: ='Value of counterfactual spendin'!$B$43 -> 0.0039318303 | G119: ='Value of counterfactual spendin'!$B$43 -> 0.0039318303 | H119: ='Value of counterfactual spendin'!$B$43 -> 0.0039318303 | I119: ='Value of counterfactual spendin'!$B$43 -> 0.0039318303 | ... P119: ='Value of counterfactual spendin'!$B$43 -> 0.0039318303
A121: Probability of scenarios in absence of philanthropic spending
A122: Scenario 1: Government costs would replace philanthropic costs | B122: 0.2 | C122: 0.2 | D122: 0.2 | E122: 0.2 | F122: 0.2 | G122: 0.2 | H122: 0.2 | I122: 0.2 | J122: 0.2 | K122: 0.2 | L122: 0.2 | M122: 0.2 | N122: 0.2 | O122: 0.2 | P122: 0.2
A123: Scenario 3: Government financial costs would stay the same | B123: 0 | C123: 0 | D123: 0 | E123: 0 | F123: 0 | G123: 0 | H123: 0 | I123: 0 | J123: 0 | K123: 0 | L123: 0 | M123: 0 | N123: 0 | O123: 0 | P123: 0
A124: Scenario 4: Distributions would go unfunded | B124: 0.8 | C124: 0.8 | D124: 0.8 | E124: 0.8 | F124: 0.8 | G124: 0.8 | H124: 0.8 | I124: 0.8 | J124: 0.8 | K124: 0.8 | L124: 0.8 | M124: 0.8 | N124: 0.8 | O124: 0.8 | P124: 0.8
A126: What fraction of the program would still happen?
A127: Scenario 1: Government costs would replace philanthropic costs | B127: =1 -> 1 | C127: =1 -> 1 | D127: =1 -> 1 | E127: =1 -> 1 | F127: =1 -> 1 | G127: =1 -> 1 | H127: =1 -> 1 | I127: =1 -> 1 | ... P127: =1 -> 1
A128: Scenario 3: Government financial costs would stay the same | B128: =B107/B113 -> 0 | C128: =C107/C113 -> 0 | D128: =D107/D113 -> 0 | E128: =E107/E113 -> 0 | F128: =F107/F113 -> 0 | G128: =G107/G113 -> 0 | H128: =H107/H113 -> 0 | I128: =I107/I113 -> 0 | ... P128: =P107/P113 -> 0
A129: Scenario 4: Distributions would go unfunded | B129: 0 | C129: 0 | D129: 0 | E129: 0 | F129: 0 | G129: 0 | H129: 0 | I129: 0 | J129: 0 | K129: 0 | L129: 0 | M129: 0 | N129: 0 | O129: 0 | P129: 0
A131: Expected change in amount of funding spent on deworming by non-philanthropic actors in absence of philanthropic spending
...

Sheet Sightsavers
B1: Senegal | C1: Chad, Priority 1 areas | D1: Chad, Priority 2 areas | E1: Bas Uele, DRC | F1: Haut Katanga, DRC | G1: Haut Lomami, DRC | H1: Haut Uele, DRC | I1: Ituri, DRC | J1: Kasai, DRC | K1: Kasai Central, DRC | L1: Kasai Oriental, DRC | M1: Kinshasa, DRC | N1: Kongo Central, DRC | O1: Lomami, DRC | P1: Mai Ndombe, DRC | Q1: Nord Ubangi, DRC | R1: Sud Kivu, DRC | S1: Tanganyika, DRC | T1: Tshopo, DRC | U1: West, Cameroon | V1: North, Cameroon | W1: Far-North, Cameroon | X1: East, Cameroon | Y1: Adamoua, Cameroon | Z1: Littoral, Cameroon | AA1: South, Cameroon | AB1: Benue State | AC1: Kebbi State | AD1: Kogi State | AE1: Kwara State | AF1: Sokoto State | AG1: Taraba State | AH1: Yobe State | AI1: Kaduna State | AJ1: Kano State | AK1: Katsina State | AL1: Niger State | AM1: Adamawa State | AN1: Zamfara State | AO1: Guinea-Bissau
A5: Funding allocation
A7: Percentage of total costs covered by Sightsavers | B7: 0.5983684 | C7: 0.4287292 | D7: 0.5182276 | E7: 0.4511091 | F7: 0.4511091 | G7: 0.4511091 | H7: 0.4511091 | I7: 0.4511091 | J7: 0.4511091 | K7: 0.4511091 | L7: 0.4511091 | M7: 0.4511091 | N7: 0.4511091 | O7: 0.4511091 | P7: 0.4511091 | Q7: 0.4511091 | R7: 0.4511091 | S7: 0.4511091 | T7: 0.4511091 | U7: 0.466908 | V7: 0.466908 | W7: 0.466908 | X7: 0.466908 | Y7: 0.466908 | Z7: 0.466908 | AA7: 0.466908 | AB7: 0.3969397 | AC7: 0.3396181 | AD7: 0.3396181 | AE7: 0.3396181 | AF7: 0.3396181 | AG7: 0.4020451 | AH7: 0.4577311 | AI7: 0.4257635 | AJ7: 0.4257635 | AK7: 0.4257635 | AL7: 0.4257635 | AM7: 0.4257635 | AN7: 0.4257635 | AO7: 0.6650286
A8: Percentage of total costs covered by domestic governments | B8: 0.3 | C8: 0.3 | D8: 0.3 | E8: 0.3 | F8: 0.3 | G8: 0.3 | H8: 0.3 | I8: 0.3 | J8: 0.3 | K8: 0.3 | L8: 0.3 | M8: 0.3 | N8: 0.3 | O8: 0.3 | P8: 0.3 | Q8: 0.3 | R8: 0.3 | S8: 0.3 | T8: 0.3 | U8: 0.3 | V8: 0.3 | W8: 0.3 | X8: 0.3 | Y8: 0.3 | Z8: 0.3 | AA8: 0.3 | AB8: 0.3 | AC8: 0.3 | AD8: 0.3 | AE8: 0.3 | AF8: 0.3 | AG8: 0.3 | AH8: 0.3 | AI8: 0.3 | AJ8: 0.3 | AK8: 0.3 | AL8: 0.3 | AM8: 0.3 | AN8: 0.3 | AO8: 0.3
A9: Percentage of total costs covered by drug donations | B9: 0.1016316 | C9: 0.2712708 | D9: 0.1817724 | E9: 0.2488909 | F9: 0.2488909 | G9: 0.2488909 | H9: 0.2488909 | I9: 0.2488909 | J9: 0.2488909 | K9: 0.2488909 | L9: 0.2488909 | M9: 0.2488909 | N9: 0.2488909 | O9: 0.2488909 | P9: 0.2488909 | Q9: 0.2488909 | R9: 0.2488909 | S9: 0.2488909 | T9: 0.2488909 | U9: 0.233092 | V9: 0.233092 | W9: 0.233092 | X9: 0.233092 | Y9: 0.233092 | Z9: 0.233092 | AA9: 0.233092 | AB9: 0.3030603 | AC9: 0.3603819 | AD9: 0.3603819 | AE9: 0.3603819 | AF9: 0.3603819 | AG9: 0.2979549 | AH9: 0.2422689 | AI9: 0.2742365 | AJ9: 0.2742365 | AK9: 0.2742365 | AL9: 0.2742365 | AM9: 0.2742365 | AN9: 0.2742365 | AO9: 0.0349714
A11: Number of children dewormed per year with hypothetical donation (Sightsavers)
A13: Donation to Sightsavers (arbitrary size) | B13: 100000 | C13: 100000 | D13: 100000 | E13: 100000 | F13: 100000 | G13: 100000 | H13: 100000 | I13: 100000 | J13: 100000 | K13: 100000 | L13: 100000 | M13: 100000 | N13: 100000 | O13: 100000 | P13: 100000 | Q13: 100000 | R13: 100000 | S13: 100000 | T13: 100000 | U13: 100000 | V13: 100000 | W13: 100000 | X13: 100000 | Y13: 100000 | Z13: 100000 | AA13: 100000 | AB13: 100000 | AC13: 100000 | AD13: 100000 | AE13: 100000 | AF13: 100000 | AG13: 100000 | AH13: 100000 | AI13: 100000 | AJ13: 100000 | AK13: 100000 | AL13: 100000 | AM13: 100000 | AN13: 100000 | AO13: 100000
A14: Total amount spent on the program by all contributors | B14: =B13/B7 -> 167121.12 | C14: =C13/C7 -> 233247.47 | D14: =D13/D7 -> 192965.41 | E14: =E13/E7 -> 221675.87 | F14: =F13/F7 -> 221675.87 | G14: =G13/G7 -> 221675.87 | H14: =H13/H7 -> 221675.87 | I14: =I13/I7 -> 221675.87 | ... AO14: =AO13/AO7 -> 150369.47
A15: Proportion of deworming going to children — Sightsavers | B15: 1 | C15: 1 | D15: 1 | E15: 1 | F15: 1 | G15: 1 | H15: 1 | I15: 1 | J15: 1 | K15: 1 | L15: 1 | M15: 1 | N15: 1 | O15: 1 | P15: 1 | Q15: 1 | R15: 1 | S15: 1 | T15: 1 | U15: 1 | V15: 1 | W15: 1 | X15: 1 | Y15: 1 | Z15: 1 | AA15: 1 | AB15: 1 | AC15: 1 | AD15: 1 | AE15: 1 | AF15: 1 | AG15: 1 | AH15: 1 | AI15: 1 | AJ15: 1 | AK15: 1 | AL15: 1 | AM15: 1 | AN15: 1 | AO15: 1
A16: Worm burden adjustment — Sightsavers | B16: 0.0503918 | C16: 0.1790904 | D16: 0.1793355 | E16: 0.1502089 | F16: 0.107008 | G16: 0.0825506 | H16: 0.0593199 | I16: 0.1232411 | J16: 0.0365127 | K16: 0.0281174 | L16: 0.1976973 | M16: 0.0090277 | N16: 0.1976973 | O16: 0.1761263 | P16: 0.019004 | Q16: 0.1077984 | R16: 0.0628656 | S16: 0.0481668 | T16: 0.1000329 | U16: 0.0382545 | V16: 0.1189598 | W16: 0.093283 | X16: 0.050537 | Y16: 0.05922 | Z16: 0.0122405 | AA16: 0.067867 | AB16: 0.0827056 | AC16: 0.0861491 | AD16: 0.0732903 | AE16: 0.1063387 | AF16: 0.1069378 | AG16: 0.0379111 | AH16: 0.0499738 | AI16: 0.1794266 | AJ16: 0.0927923 | AK16: 0.0535485 | AL16: 0.1946866 | AM16: 0.1230215 | AN16: 0.1946866 | AO16: 0.013708
A17: Adjusted long-term benefits per year of deworming per person treated in terms of ln(consumption) | B17: ='Deworm the World'!$B$27 -> 0.20627072 | C17: ='Deworm the World'!$B$27 -> 0.20627072 | D17: ='Deworm the World'!$B$27 -> 0.20627072 | E17: ='Deworm the World'!$B$27 -> 0.20627072 | F17: ='Deworm the World'!$B$27 -> 0.20627072 | G17: ='Deworm the World'!$B$27 -> 0.20627072 | H17: ='Deworm the World'!$B$27 -> 0.20627072 | I17: ='Deworm the World'!$B$27 -> 0.20627072 | ... AO17: ='Deworm the World'!$B$27 -> 0.20627072
A18: Present value of lifetime benefits from a year of deworming — in terms of increases in ln(consumption) | B18: =B16*B15*B17 -> 0.010394353 | C18: =C16*C15*C17 -> 0.036941107 | D18: =D16*D15*D17 -> 0.036991664 | E18: =E16*E15*E17 -> 0.030983699 | F18: =F16*F15*F17 -> 0.022072618 | G18: =G16*G15*G17 -> 0.017027772 | H18: =H16*H15*H17 -> 0.012235959 | I18: =I16*I15*I17 -> 0.025421031 | ... AO18: =AO16*AO15*AO17 -> 0.0028275591
A19: Value assigned to increasing ln(consumption) by one unit for one person for one year | B19: {=index('Moral weights and discount rate'!$A$1:$ZU$39,match($A19,'Moral weights and discount rate'!$A$1:$A$39,0),match('Moral weights and discount rate'!$A$17,'Moral weights and discount rate'!$A$1:$ZU$1,0))} -> 1.442695 | C19: {=index('Moral weights and discount rate'!$A$1:$ZU$39,match($A19,'Moral weights and discount rate'!$A$1:$A$39,0),match('Moral weights and discount rate'!$A$17,'Moral weights and discount rate'!$A$1:$ZU$1,0))} -> 1.442695 | D19: {=index('Moral weights and discount rate'!$A$1:$ZU$39,match($A19,'Moral weights and discount rate'!$A$1:$A$39,0),match('Moral weights and discount rate'!$A$17,'Moral weights and discount rate'!$A$1:$ZU$1,0))} -> 1.442695 | E19: {=index('Moral weights and discount rate'!$A$1:$ZU$39,match($A19,'Moral weights and discount rate'!$A$1:$A$39,0),match('Moral weights and discount rate'!$A$17,'Moral weights and discount rate'!$A$1:$ZU$1,0))} -> 1.442695 | F19: {=index('Moral weights and discount rate'!$A$1:$ZU$39,match($A19,'Moral weights and discount rate'!$A$1:$A$39,0),match('Moral weights and discount rate'!$A$17,'Moral weights and discount rate'!$A$1:$ZU$1,0))} -> 1.442695 | G19: {=index('Moral weights and discount rate'!$A$1:$ZU$39,match($A19,'Moral weights and discount rate'!$A$1:$A$39,0),match('Moral weights and discount rate'!$A$17,'Moral weights and discount rate'!$A$1:$ZU$1,0))} -> 1.442695 | H19: {=index('Moral weights and discount rate'!$A$1:$ZU$39,match($A19,'Moral weights and discount rate'!$A$1:$A$39,0),match('Moral weights and discount rate'!$A$17,'Moral weights and discount rate'!$A$1:$ZU$1,0))} -> 1.442695 | I19: {=index('Moral weights and discount rate'!$A$1:$ZU$39,match($A19,'Moral weights and discount rate'!$A$1:$A$39,0),match('Moral weights and discount rate'!$A$17,'Moral weights and discount rate'!$A$1:$ZU$1,0))} -> 1.442695 | ... AO19: {=index('Moral weights and discount rate'!$A$1:$ZU$39,match($A19,'Moral weights and discount rate'!$A$1:$A$39,0),match('Moral weights and discount rate'!$A$17,'Moral weights and discount rate'!$A$1:$ZU$1,0))} -> 1.442695
A20: Units of value from each year of deworming — Sightsavers | B20: =(B18*B19) -> 0.014995882 | C20: =(C18*C19) -> 0.053294751 | D20: =(D18*D19) -> 0.05336769 | E20: =(E18*E19) -> 0.044700028 | F20: =(F18*F19) -> 0.031844056 | G20: =(G18*G19) -> 0.024565882 | H20: =(H18*H19) -> 0.017652757 | I20: =(I18*I19) -> 0.036674795 | ... AO20: =(AO18*AO19) -> 0.0040793055
A21: Cost per person dewormed (per year) — Sightsavers | B21: 1.51904 | C21: 1.26664 | D21: 1.7252 | E21: 1.27013 | F21: 1.27013 | G21: 1.27013 | H21: 1.27013 | I21: 1.27013 | J21: 1.27013 | K21: 1.27013 | L21: 1.27013 | M21: 1.27013 | N21: 1.27013 | O21: 1.27013 | P21: 1.27013 | Q21: 1.27013 | R21: 1.27013 | S21: 1.27013 | T21: 1.27013 | U21: 0.8544 | V21: 0.8544 | W21: 0.8544 | X21: 0.8544 | Y21: 0.8544 | Z21: 0.8544 | AA21: 0.8544 | AB21: 0.93964 | AC21: 0.81978 | AD21: 0.81978 | AE21: 0.81978 | AF21: 0.81978 | AG21: 1.05855 | AH21: 1.41189 | AI21: 0.96164 | AJ21: 0.96164 | AK21: 0.96164 | AL21: 0.96164 | AM21: 0.96164 | AN21: 0.96164 | AO21: 5.32065
A22: Total number of children dewormed (per year) | B22: =B14/B21 -> 110017.59 | C22: =C14/C21 -> 184146.61 | D22: =D14/D21 -> 111851.04 | E22: =E14/E21 -> 174530.06 | F22: =F14/F21 -> 174530.06 | G22: =G14/G21 -> 174530.06 | H22: =H14/H21 -> 174530.06 | I22: =I14/I21 -> 174530.06 | ... AO22: =AO14/AO21 -> 28261.485
A24: Intuition check
A26: Aggregate adjustment to Miguel and Kremer development effect — Sightsavers | B26: =product('Deworm the World'!$B$11:$B$12,B16) -> 0.0058958406 | C26: =product('Deworm the World'!$B$11:$B$12,C16) -> 0.020953577 | D26: =product('Deworm the World'!$B$11:$B$12,D16) -> 0.020982253 | E26: =product('Deworm the World'!$B$11:$B$12,E16) -> 0.017574441 | F26: =product('Deworm the World'!$B$11:$B$12,F16) -> 0.012519936 | G26: =product('Deworm the World'!$B$11:$B$12,G16) -> 0.0096584202 | H26: =product('Deworm the World'!$B$11:$B$12,H16) -> 0.0069404283 | I26: =product('Deworm the World'!$B$11:$B$12,I16) -> 0.014419209 | ... AO26: =product('Deworm the World'!$B$11:$B$12,AO16) -> 0.001603836
A28: Initial results
A30: =A18 -> Present value of lifetime benefits from a year of deworming — in terms of increases in ln(consumption) | B30: =B18 -> 0.010394353 | C30: =C18 -> 0.036941107 | D30: =D18 -> 0.036991664 | E30: =E18 -> 0.030983699 | F30: =F18 -> 0.022072618 | G30: =G18 -> 0.017027772 | H30: =H18 -> 0.012235959 | ... AO30: =AO18 -> 0.0028275591
A31: =A19 -> Value assigned to increasing ln(consumption) by one unit for one person for one year | B31: =B19 -> 1.442695 | C31: =C19 -> 1.442695 | D31: =D19 -> 1.442695 | E31: =E19 -> 1.442695 | F31: =F19 -> 1.442695 | G31: =G19 -> 1.442695 | H31: =H19 -> 1.442695 | ... AO31: =AO19 -> 1.442695
A32: =A22 -> Total number of children dewormed (per year) | B32: =B22 -> 110017.59 | C32: =C22 -> 184146.61 | D32: =D22 -> 111851.04 | E32: =E22 -> 174530.06 | F32: =F22 -> 174530.06 | G32: =G22 -> 174530.06 | H32: =H22 -> 174530.06 | ... AO32: =AO22 -> 28261.485
A33: Total units of value generated | B33: =product(B30:B32) -> 1649.8108 | C33: =product(C30:C32) -> 9814.048 | D33: =product(D30:D32) -> 5969.2314 | E33: =product(E30:E32) -> 7801.4986 | F33: =product(F30:F32) -> 5557.745 | G33: =product(G30:G32) -> 4287.4849 | H33: =product(H30:H32) -> 3080.9367 | I33: =product(I30:I32) -> 6400.8542 | ... AO33: =product(AO30:AO32) -> 115.28723
A34: Units of value generated per dollar spent | B34: =B33/B14 -> 0.0098719465 | C34: =C33/C14 -> 0.042075689 | D34: =D33/D14 -> 0.030934204 | E34: =E33/E14 -> 0.03519327 | F34: =F33/F14 -> 0.025071494 | G34: =G33/G14 -> 0.019341235 | H34: =H33/H14 -> 0.013898386 | I34: =I33/I14 -> 0.028874836 | ... AO34: =AO33/AO14 -> 0.00076669307
A36: Initial cost-effectiveness estimate in multiples of cash transfers | B36: {=B34/index(GiveDirectly!$B:$B,match("Units of value generated per philanthropic dollar spent, after accounting for all adjustments",GiveDirectly!$A:$A,0))} -> 2.9428668 | C36: {=C34/index(GiveDirectly!$B:$B,match("Units of value generated per philanthropic dollar spent, after accounting for all adjustments",GiveDirectly!$A:$A,0))} -> 12.542932 | D36: {=D34/index(GiveDirectly!$B:$B,match("Units of value generated per philanthropic dollar spent, after accounting for all adjustments",GiveDirectly!$A:$A,0))} -> 9.2216102 | E36: {=E34/index(GiveDirectly!$B:$B,match("Units of value generated per philanthropic dollar spent, after accounting for all adjustments",GiveDirectly!$A:$A,0))} -> 10.491255 | F36: {=F34/index(GiveDirectly!$B:$B,match("Units of value generated per philanthropic dollar spent, after accounting for all adjustments",GiveDirectly!$A:$A,0))} -> 7.4739126 | G36: {=G34/index(GiveDirectly!$B:$B,match("Units of value generated per philanthropic dollar spent, after accounting for all adjustments",GiveDirectly!$A:$A,0))} -> 5.7656995 | H36: {=H34/index(GiveDirectly!$B:$B,match("Units of value generated per philanthropic dollar spent, after accounting for all adjustments",GiveDirectly!$A:$A,0))} -> 4.1431645 | I36: {=I34/index(GiveDirectly!$B:$B,match("Units of value generated per philanthropic dollar spent, after accounting for all adjustments",GiveDirectly!$A:$A,0))} -> 8.6077042 | ... AO36: {=AO34/index(GiveDirectly!$B:$B,match("Units of value generated per philanthropic dollar spent, after accounting for all adjustments",GiveDirectly!$A:$A,0))} -> 0.22855427
A38: Supplemental charity-level adjustments — Sightsavers
A40: Risk of wastage
A41: Double treatment | B41: 0 | C41: 0 | D41: 0 | E41: 0 | F41: 0 | G41: 0 | H41: 0 | I41: 0 | J41: 0 | K41: 0 | L41: 0 | M41: 0 | N41: 0 | O41: 0 | P41: 0 | Q41: 0 | R41: 0 | S41: 0 | T41: 0 | U41: 0 | V41: 0 | W41: 0 | X41: 0 | Y41: 0 | Z41: 0 | AA41: 0 | AB41: 0 | AC41: 0 | AD41: 0 | AE41: 0 | AF41: 0 | AG41: 0 | AH41: 0 | AI41: 0 | AJ41: 0 | AK41: 0 | AL41: 0 | AM41: 0 | AN41: 0 | AO41: 0
A42: Ineffective goods | B42: 0 | C42: 0 | D42: 0 | E42: 0 | F42: 0 | G42: 0 | H42: 0 | I42: 0 | J42: 0 | K42: 0 | L42: 0 | M42: 0 | N42: 0 | O42: 0 | P42: 0 | Q42: 0 | R42: 0 | S42: 0 | T42: 0 | U42: 0 | V42: 0 | W42: 0 | X42: 0 | Y42: 0 | Z42: 0 | AA42: 0 | AB42: 0 | AC42: 0 | AD42: 0 | AE42: 0 | AF42: 0 | AG42: 0 | AH42: 0 | AI42: 0 | AJ42: 0 | AK42: 0 | AL42: 0 | AM42: 0 | AN42: 0 | AO42: 0
A43: Goods purchased and left in storage until they expire / Cash doesn't reach recipients or is taken back from them inappropriately | B43: 0 | C43: 0 | D43: 0 | E43: 0 | F43: 0 | G43: 0 | H43: 0 | I43: 0 | J43: 0 | K43: 0 | L43: 0 | M43: 0 | N43: 0 | O43: 0 | P43: 0 | Q43: 0 | R43: 0 | S43: 0 | T43: 0 | U43: 0 | V43: 0 | W43: 0 | X43: 0 | Y43: 0 | Z43: 0 | AA43: 0 | AB43: 0 | AC43: 0 | AD43: 0 | AE43: 0 | AF43: 0 | AG43: 0 | AH43: 0 | AI43: 0 | AJ43: 0 | AK43: 0 | AL43: 0 | AM43: 0 | AN43: 0 | AO43: 0
A44: Total adjustment for risk of wastage | B44: =SUM(B41:B43) -> 0 | C44: =SUM(C41:C43) -> 0 | D44: =SUM(D41:D43) -> 0 | E44: =SUM(E41:E43) -> 0 | F44: =SUM(F41:F43) -> 0 | G44: =SUM(G41:G43) -> 0 | H44: =SUM(H41:H43) -> 0 | I44: =SUM(I41:I43) -> 0 | ... AO44: =SUM(AO41:AO43) -> 0
A46: Quality of monitoring and evaluation
A47: Misappropriation without monitoring results | B47: 0.03 | C47: 0.03 | D47: 0.03 | E47: 0.03 | F47: 0.03 | G47: 0.03 | H47: 0.03 | I47: 0.03 | J47: 0.03 | K47: 0.03 | L47: 0.03 | M47: 0.03 | N47: 0.03 | O47: 0.03 | P47: 0.03 | Q47: 0.03 | R47: 0.03 | S47: 0.03 | T47: 0.03 | U47: 0.03 | V47: 0.03 | W47: 0.03 | X47: 0.03 | Y47: 0.03 | Z47: 0.03 | AA47: 0.03 | AB47: 0.03 | AC47: 0.03 | AD47: 0.03 | AE47: 0.03 | AF47: 0.03 | AG47: 0.03 | AH47: 0.03 | AI47: 0.03 | AJ47: 0.03 | AK47: 0.03 | AL47: 0.03 | AM47: 0.03 | AN47: 0.03 | AO47: 0.03
A48: False monitoring results | B48: 0.05 | C48: 0.05 | D48: 0.05 | E48: 0.05 | F48: 0.05 | G48: 0.05 | H48: 0.05 | I48: 0.05 | J48: 0.05 | K48: 0.05 | L48: 0.05 | M48: 0.05 | N48: 0.05 | O48: 0.05 | P48: 0.05 | Q48: 0.05 | R48: 0.05 | S48: 0.05 | T48: 0.05 | U48: 0.05 | V48: 0.05 | W48: 0.05 | X48: 0.05 | Y48: 0.05 | Z48: 0.05 | AA48: 0.05 | AB48: 0.05 | AC48: 0.05 | AD48: 0.05 | AE48: 0.05 | AF48: 0.05 | AG48: 0.05 | AH48: 0.05 | AI48: 0.05 | AJ48: 0.05 | AK48: 0.05 | AL48: 0.05 | AM48: 0.05 | AN48: 0.05 | AO48: 0.05
A49: Total adjustment for quality of monitoring and evaluation | B49: =sum(B46:B48) -> 0.08 | C49: =sum(C46:C48) -> 0.08 | D49: =sum(D46:D48) -> 0.08 | E49: =sum(E46:E48) -> 0.08 | F49: =sum(F46:F48) -> 0.08 | G49: =sum(G46:G48) -> 0.08 | H49: =sum(H46:H48) -> 0.08 | I49: =sum(I46:I48) -> 0.08 | ... AO49: =sum(AO46:AO48) -> 0.08
A51: Confidence in funds being used for intended purpose
A52: Change of priorities | B52: 0.02 | C52: 0.02 | D52: 0.02 | E52: 0.02 | F52: 0.02 | G52: 0.02 | H52: 0.02 | I52: 0.02 | J52: 0.02 | K52: 0.02 | L52: 0.02 | M52: 0.02 | N52: 0.02 | O52: 0.02 | P52: 0.02 | Q52: 0.02 | R52: 0.02 | S52: 0.02 | T52: 0.02 | U52: 0.02 | V52: 0.02 | W52: 0.02 | X52: 0.02 | Y52: 0.02 | Z52: 0.02 | AA52: 0.02 | AB52: 0.02 | AC52: 0.02 | AD52: 0.02 | AE52: 0.02 | AF52: 0.02 | AG52: 0.02 | AH52: 0.02 | AI52: 0.02 | AJ52: 0.02 | AK52: 0.02 | AL52: 0.02 | AM52: 0.02 | AN52: 0.02 | AO52: 0.02
A53: Non-funding bottlenecks | B53: 0 | C53: 0 | D53: 0 | E53: 0 | F53: 0 | G53: 0 | H53: 0 | I53: 0 | J53: 0 | K53: 0 | L53: 0 | M53: 0 | N53: 0 | O53: 0 | P53: 0 | Q53: 0 | R53: 0 | S53: 0 | T53: 0 | U53: 0 | V53: 0 | W53: 0 | X53: 0 | Y53: 0 | Z53: 0 | AA53: 0 | AB53: 0 | AC53: 0 | AD53: 0 | AE53: 0 | AF53: 0 | AG53: 0 | AH53: 0 | AI53: 0 | AJ53: 0 | AK53: 0 | AL53: 0 | AM53: 0 | AN53: 0 | AO53: 0
A54: Within-org fungibility | B54: 0.05 | C54: 0.05 | D54: 0.05 | E54: 0.05 | F54: 0.05 | G54: 0.05 | H54: 0.05 | I54: 0.05 | J54: 0.05 | K54: 0.05 | L54: 0.05 | M54: 0.05 | N54: 0.05 | O54: 0.05 | P54: 0.05 | Q54: 0.05 | R54: 0.05 | S54: 0.05 | T54: 0.05 | U54: 0.05 | V54: 0.05 | W54: 0.05 | X54: 0.05 | Y54: 0.05 | Z54: 0.05 | AA54: 0.05 | AB54: 0.05 | AC54: 0.05 | AD54: 0.05 | AE54: 0.05 | AF54: 0.05 | AG54: 0.05 | AH54: 0.05 | AI54: 0.05 | AJ54: 0.05 | AK54: 0.05 | AL54: 0.05 | AM54: 0.05 | AN54: 0.05 | AO54: 0.05
A55: Total adjustment for confidence in funds being used for intended purpose | B55: =sum(B52:B54) -> 0.07 | C55: =sum(C52:C54) -> 0.07 | D55: =sum(D52:D54) -> 0.07 | E55: =sum(E52:E54) -> 0.07 | F55: =sum(F52:F54) -> 0.07 | G55: =sum(G52:G54) -> 0.07 | H55: =sum(H52:H54) -> 0.07 | I55: =sum(I52:I54) -> 0.07 | ... AO55: =sum(AO52:AO54) -> 0.07
A57: Total adjustment factor | B57: =1-sum(B44,B49,B55) -> 0.85 | C57: =1-sum(C44,C49,C55) -> 0.85 | D57: =1-sum(D44,D49,D55) -> 0.85 | E57: =1-sum(E44,E49,E55) -> 0.85 | F57: =1-sum(F44,F49,F55) -> 0.85 | G57: =1-sum(G44,G49,G55) -> 0.85 | H57: =1-sum(H44,H49,H55) -> 0.85 | I57: =1-sum(I44,I49,I55) -> 0.85 | ... AO57: =1-sum(AO44,AO49,AO55) -> 0.85
A59: Results after supplemental charity-level adjustments
A60: Total units of value generated | B60: =B33*B57 -> 1402.3392 | C60: =C33*C57 -> 8341.9408 | D60: =D33*D57 -> 5073.8467 | E60: =E33*E57 -> 6631.2738 | F60: =F33*F57 -> 4724.0833 | G60: =G33*G57 -> 3644.3622 | H60: =H33*H57 -> 2618.7962 | I60: =I33*I57 -> 5440.7261 | ... AO60: =AO33*AO57 -> 97.994148
A61: Units of value per dollar spent | B61: =B60/B14 -> 0.0083911546 | C61: =C60/C14 -> 0.035764336 | D61: =D60/D14 -> 0.026294074 | E61: =E60/E14 -> 0.02991428 | F61: =F60/F14 -> 0.02131077 | G61: =G60/G14 -> 0.016440049 | H61: =H60/H14 -> 0.011813628 | I61: =I60/I14 -> 0.024543611 | ... AO61: =AO60/AO14 -> 0.00065168911
A62: Cost-effectiveness in multiples of cash transfers, after supplemental charity-level adjustments | B62: {=B61/index(GiveDirectly!$B:$B,match("Units of value generated per philanthropic dollar spent, after accounting for all adjustments",GiveDirectly!$A:$A,0))} -> 2.5014368 | C62: {=C61/index(GiveDirectly!$B:$B,match("Units of value generated per philanthropic dollar spent, after accounting for all adjustments",GiveDirectly!$A:$A,0))} -> 10.661492 | D62: {=D61/index(GiveDirectly!$B:$B,match("Units of value generated per philanthropic dollar spent, after accounting for all adjustments",GiveDirectly!$A:$A,0))} -> 7.8383687 | E62: {=E61/index(GiveDirectly!$B:$B,match("Units of value generated per philanthropic dollar spent, after accounting for all adjustments",GiveDirectly!$A:$A,0))} -> 8.9175666 | F62: {=F61/index(GiveDirectly!$B:$B,match("Units of value generated per philanthropic dollar spent, after accounting for all adjustments",GiveDirectly!$A:$A,0))} -> 6.3528257 | G62: {=G61/index(GiveDirectly!$B:$B,match("Units of value generated per philanthropic dollar spent, after accounting for all adjustments",GiveDirectly!$A:$A,0))} -> 4.9008446 | H62: {=H61/index(GiveDirectly!$B:$B,match("Units of value generated per philanthropic dollar spent, after accounting for all adjustments",GiveDirectly!$A:$A,0))} -> 3.5216898 | I62: {=I61/index(GiveDirectly!$B:$B,match("Units of value generated per philanthropic dollar spent, after accounting for all adjustments",GiveDirectly!$A:$A,0))} -> 7.3165486 | ... AO62: {=AO61/index(GiveDirectly!$B:$B,match("Units of value generated per philanthropic dollar spent, after accounting for all adjustments",GiveDirectly!$A:$A,0))} -> 0.19427113
A64: Supplemental intervention-level adjustments — Deworming
A65: Outcomes included in our core model (above)
A66: =IFERROR(__xludf.DUMMYFUNCTION("filter('Supplemental intervention-level'!C:C,'Supplemental intervention-level'!A:A=""Deworming"",'Supplemental intervention-level'!D:D=""Explicitly modeled"")"),"Developmental effects") -> Developmental effects
A68: Supplemental intervention-level adjustments
A69: =IFERROR(__xludf.DUMMYFUNCTION("filter('Supplemental intervention-level'!C:C,'Supplemental intervention-level'!A:A=""Deworming"",'Supplemental intervention-level'!D:D=""Not explicitly modeled"")"),"Direct health effects") -> Direct health effects | B69: {=iferror(if(isblank($A69),"",index('Supplemental intervention-level'!$M:$M,match(1,('Supplemental intervention-level'!$C:$C=$A69)*('Supplemental intervention-level'!$A:$A="Deworming"),0))),"Not specified")} -> 0.008 | C69: {=iferror(if(isblank($A69),"",index('Supplemental intervention-level'!$M:$M,match(1,('Supplemental intervention-level'!$C:$C=$A69)*('Supplemental intervention-level'!$A:$A="Deworming"),0))),"Not specified")} -> 0.008 | D69: {=iferror(if(isblank($A69),"",index('Supplemental intervention-level'!$M:$M,match(1,('Supplemental intervention-level'!$C:$C=$A69)*('Supplemental intervention-level'!$A:$A="Deworming"),0))),"Not specified")} -> 0.008 | E69: {=iferror(if(isblank($A69),"",index('Supplemental intervention-level'!$M:$M,match(1,('Supplemental intervention-level'!$C:$C=$A69)*('Supplemental intervention-level'!$A:$A="Deworming"),0))),"Not specified")} -> 0.008 | F69: {=iferror(if(isblank($A69),"",index('Supplemental intervention-level'!$M:$M,match(1,('Supplemental intervention-level'!$C:$C=$A69)*('Supplemental intervention-level'!$A:$A="Deworming"),0))),"Not specified")} -> 0.008 | G69: {=iferror(if(isblank($A69),"",index('Supplemental intervention-level'!$M:$M,match(1,('Supplemental intervention-level'!$C:$C=$A69)*('Supplemental intervention-level'!$A:$A="Deworming"),0))),"Not specified")} -> 0.008 | H69: {=iferror(if(isblank($A69),"",index('Supplemental intervention-level'!$M:$M,match(1,('Supplemental intervention-level'!$C:$C=$A69)*('Supplemental intervention-level'!$A:$A="Deworming"),0))),"Not specified")} -> 0.008 | I69: {=iferror(if(isblank($A69),"",index('Supplemental intervention-level'!$M:$M,match(1,('Supplemental intervention-level'!$C:$C=$A69)*('Supplemental intervention-level'!$A:$A="Deworming"),0))),"Not specified")} -> 0.008 | ... AO69: {=iferror(if(isblank($A69),"",index('Supplemental intervention-level'!$M:$M,match(1,('Supplemental intervention-level'!$C:$C=$A69)*('Supplemental intervention-level'!$A:$A="Deworming"),0))),"Not specified")} -> 0.008
A70: =IFERROR(__xludf.DUMMYFUNCTION("""COMPUTED_VALUE"""),"HIV reduction") -> HIV reduction | B70: {=iferror(if(isblank($A70),"",index('Supplemental intervention-level'!$M:$M,match(1,('Supplemental intervention-level'!$C:$C=$A70)*('Supplemental intervention-level'!$A:$A="Deworming"),0))),"Not specified")} -> 0.06 | C70: {=iferror(if(isblank($A70),"",index('Supplemental intervention-level'!$M:$M,match(1,('Supplemental intervention-level'!$C:$C=$A70)*('Supplemental intervention-level'!$A:$A="Deworming"),0))),"Not specified")} -> 0.06 | D70: {=iferror(if(isblank($A70),"",index('Supplemental intervention-level'!$M:$M,match(1,('Supplemental intervention-level'!$C:$C=$A70)*('Supplemental intervention-level'!$A:$A="Deworming"),0))),"Not specified")} -> 0.06 | E70: {=iferror(if(isblank($A70),"",index('Supplemental intervention-level'!$M:$M,match(1,('Supplemental intervention-level'!$C:$C=$A70)*('Supplemental intervention-level'!$A:$A="Deworming"),0))),"Not specified")} -> 0.06 | F70: {=iferror(if(isblank($A70),"",index('Supplemental intervention-level'!$M:$M,match(1,('Supplemental intervention-level'!$C:$C=$A70)*('Supplemental intervention-level'!$A:$A="Deworming"),0))),"Not specified")} -> 0.06 | G70: {=iferror(if(isblank($A70),"",index('Supplemental intervention-level'!$M:$M,match(1,('Supplemental intervention-level'!$C:$C=$A70)*('Supplemental intervention-level'!$A:$A="Deworming"),0))),"Not specified")} -> 0.06 | H70: {=iferror(if(isblank($A70),"",index('Supplemental intervention-level'!$M:$M,match(1,('Supplemental intervention-level'!$C:$C=$A70)*('Supplemental intervention-level'!$A:$A="Deworming"),0))),"Not specified")} -> 0.06 | I70: {=iferror(if(isblank($A70),"",index('Supplemental intervention-level'!$M:$M,match(1,('Supplemental intervention-level'!$C:$C=$A70)*('Supplemental intervention-level'!$A:$A="Deworming"),0))),"Not specified")} -> 0.06 | ... AO70: {=iferror(if(isblank($A70),"",index('Supplemental intervention-level'!$M:$M,match(1,('Supplemental intervention-level'!$C:$C=$A70)*('Supplemental intervention-level'!$A:$A="Deworming"),0))),"Not specified")} -> 0.06
A71: =IFERROR(__xludf.DUMMYFUNCTION("""COMPUTED_VALUE"""),"Possible increases in diseases of affluence (harms of deworming)") -> Possible increases in diseases of affluence (harms of deworming) | B71: {=iferror(if(isblank($A71),"",index('Supplemental intervention-level'!$M:$M,match(1,('Supplemental intervention-level'!$C:$C=$A71)*('Supplemental intervention-level'!$A:$A="Deworming"),0))),"Not specified")} -> -0.025 | C71: {=iferror(if(isblank($A71),"",index('Supplemental intervention-level'!$M:$M,match(1,('Supplemental intervention-level'!$C:$C=$A71)*('Supplemental intervention-level'!$A:$A="Deworming"),0))),"Not specified")} -> -0.025 | D71: {=iferror(if(isblank($A71),"",index('Supplemental intervention-level'!$M:$M,match(1,('Supplemental intervention-level'!$C:$C=$A71)*('Supplemental intervention-level'!$A:$A="Deworming"),0))),"Not specified")} -> -0.025 | E71: {=iferror(if(isblank($A71),"",index('Supplemental intervention-level'!$M:$M,match(1,('Supplemental intervention-level'!$C:$C=$A71)*('Supplemental intervention-level'!$A:$A="Deworming"),0))),"Not specified")} -> -0.025 | F71: {=iferror(if(isblank($A71),"",index('Supplemental intervention-level'!$M:$M,match(1,('Supplemental intervention-level'!$C:$C=$A71)*('Supplemental intervention-level'!$A:$A="Deworming"),0))),"Not specified")} -> -0.025 | G71: {=iferror(if(isblank($A71),"",index('Supplemental intervention-level'!$M:$M,match(1,('Supplemental intervention-level'!$C:$C=$A71)*('Supplemental intervention-level'!$A:$A="Deworming"),0))),"Not specified")} -> -0.025 | H71: {=iferror(if(isblank($A71),"",index('Supplemental intervention-level'!$M:$M,match(1,('Supplemental intervention-level'!$C:$C=$A71)*('Supplemental intervention-level'!$A:$A="Deworming"),0))),"Not specified")} -> -0.025 | I71: {=iferror(if(isblank($A71),"",index('Supplemental intervention-level'!$M:$M,match(1,('Supplemental intervention-level'!$C:$C=$A71)*('Supplemental intervention-level'!$A:$A="Deworming"),0))),"Not specified")} -> -0.025 | ... AO71: {=iferror(if(isblank($A71),"",index('Supplemental intervention-level'!$M:$M,match(1,('Supplemental intervention-level'!$C:$C=$A71)*('Supplemental intervention-level'!$A:$A="Deworming"),0))),"Not specified")} -> -0.025
A72: =IFERROR(__xludf.DUMMYFUNCTION("""COMPUTED_VALUE"""),"Averted mortality") -> Averted mortality | B72: {=iferror(if(isblank($A72),"",index('Supplemental intervention-level'!$M:$M,match(1,('Supplemental intervention-level'!$C:$C=$A72)*('Supplemental intervention-level'!$A:$A="Deworming"),0))),"Not specified")} -> 0.035 | C72: {=iferror(if(isblank($A72),"",index('Supplemental intervention-level'!$M:$M,match(1,('Supplemental intervention-level'!$C:$C=$A72)*('Supplemental intervention-level'!$A:$A="Deworming"),0))),"Not specified")} -> 0.035 | D72: {=iferror(if(isblank($A72),"",index('Supplemental intervention-level'!$M:$M,match(1,('Supplemental intervention-level'!$C:$C=$A72)*('Supplemental intervention-level'!$A:$A="Deworming"),0))),"Not specified")} -> 0.035 | E72: {=iferror(if(isblank($A72),"",index('Supplemental intervention-level'!$M:$M,match(1,('Supplemental intervention-level'!$C:$C=$A72)*('Supplemental intervention-level'!$A:$A="Deworming"),0))),"Not specified")} -> 0.035 | F72: {=iferror(if(isblank($A72),"",index('Supplemental intervention-level'!$M:$M,match(1,('Supplemental intervention-level'!$C:$C=$A72)*('Supplemental intervention-level'!$A:$A="Deworming"),0))),"Not specified")} -> 0.035 | G72: {=iferror(if(isblank($A72),"",index('Supplemental intervention-level'!$M:$M,match(1,('Supplemental intervention-level'!$C:$C=$A72)*('Supplemental intervention-level'!$A:$A="Deworming"),0))),"Not specified")} -> 0.035 | H72: {=iferror(if(isblank($A72),"",index('Supplemental intervention-level'!$M:$M,match(1,('Supplemental intervention-level'!$C:$C=$A72)*('Supplemental intervention-level'!$A:$A="Deworming"),0))),"Not specified")} -> 0.035 | I72: {=iferror(if(isblank($A72),"",index('Supplemental intervention-level'!$M:$M,match(1,('Supplemental intervention-level'!$C:$C=$A72)*('Supplemental intervention-level'!$A:$A="Deworming"),0))),"Not specified")} -> 0.035 | ... AO72: {=iferror(if(isblank($A72),"",index('Supplemental intervention-level'!$M:$M,match(1,('Supplemental intervention-level'!$C:$C=$A72)*('Supplemental intervention-level'!$A:$A="Deworming"),0))),"Not specified")} -> 0.035
A73: =IFERROR(__xludf.DUMMYFUNCTION("""COMPUTED_VALUE"""),"Short-term anemia effects") -> Short-term anemia effects | B73: {=iferror(if(isblank($A73),"",index('Supplemental intervention-level'!$M:$M,match(1,('Supplemental intervention-level'!$C:$C=$A73)*('Supplemental intervention-level'!$A:$A="Deworming"),0))),"Not specified")} -> 0.09 | C73: {=iferror(if(isblank($A73),"",index('Supplemental intervention-level'!$M:$M,match(1,('Supplemental intervention-level'!$C:$C=$A73)*('Supplemental intervention-level'!$A:$A="Deworming"),0))),"Not specified")} -> 0.09 | D73: {=iferror(if(isblank($A73),"",index('Supplemental intervention-level'!$M:$M,match(1,('Supplemental intervention-level'!$C:$C=$A73)*('Supplemental intervention-level'!$A:$A="Deworming"),0))),"Not specified")} -> 0.09 | E73: {=iferror(if(isblank($A73),"",index('Supplemental intervention-level'!$M:$M,match(1,('Supplemental intervention-level'!$C:$C=$A73)*('Supplemental intervention-level'!$A:$A="Deworming"),0))),"Not specified")} -> 0.09 | F73: {=iferror(if(isblank($A73),"",index('Supplemental intervention-level'!$M:$M,match(1,('Supplemental intervention-level'!$C:$C=$A73)*('Supplemental intervention-level'!$A:$A="Deworming"),0))),"Not specified")} -> 0.09 | G73: {=iferror(if(isblank($A73),"",index('Supplemental intervention-level'!$M:$M,match(1,('Supplemental intervention-level'!$C:$C=$A73)*('Supplemental intervention-level'!$A:$A="Deworming"),0))),"Not specified")} -> 0.09 | H73: {=iferror(if(isblank($A73),"",index('Supplemental intervention-level'!$M:$M,match(1,('Supplemental intervention-level'!$C:$C=$A73)*('Supplemental intervention-level'!$A:$A="Deworming"),0))),"Not specified")} -> 0.09 | I73: {=iferror(if(isblank($A73),"",index('Supplemental intervention-level'!$M:$M,match(1,('Supplemental intervention-level'!$C:$C=$A73)*('Supplemental intervention-level'!$A:$A="Deworming"),0))),"Not specified")} -> 0.09 | ... AO73: {=iferror(if(isblank($A73),"",index('Supplemental intervention-level'!$M:$M,match(1,('Supplemental intervention-level'!$C:$C=$A73)*('Supplemental intervention-level'!$A:$A="Deworming"),0))),"Not specified")} -> 0.09
A74: =IFERROR(__xludf.DUMMYFUNCTION("""COMPUTED_VALUE"""),"Investment of income increases") -> Investment of income increases | B74: {=iferror(if(isblank($A74),"",index('Supplemental intervention-level'!$M:$M,match(1,('Supplemental intervention-level'!$C:$C=$A74)*('Supplemental intervention-level'!$A:$A="Deworming"),0))),"Not specified")} -> 0.1 | C74: {=iferror(if(isblank($A74),"",index('Supplemental intervention-level'!$M:$M,match(1,('Supplemental intervention-level'!$C:$C=$A74)*('Supplemental intervention-level'!$A:$A="Deworming"),0))),"Not specified")} -> 0.1 | D74: {=iferror(if(isblank($A74),"",index('Supplemental intervention-level'!$M:$M,match(1,('Supplemental intervention-level'!$C:$C=$A74)*('Supplemental intervention-level'!$A:$A="Deworming"),0))),"Not specified")} -> 0.1 | E74: {=iferror(if(isblank($A74),"",index('Supplemental intervention-level'!$M:$M,match(1,('Supplemental intervention-level'!$C:$C=$A74)*('Supplemental intervention-level'!$A:$A="Deworming"),0))),"Not specified")} -> 0.1 | F74: {=iferror(if(isblank($A74),"",index('Supplemental intervention-level'!$M:$M,match(1,('Supplemental intervention-level'!$C:$C=$A74)*('Supplemental intervention-level'!$A:$A="Deworming"),0))),"Not specified")} -> 0.1 | G74: {=iferror(if(isblank($A74),"",index('Supplemental intervention-level'!$M:$M,match(1,('Supplemental intervention-level'!$C:$C=$A74)*('Supplemental intervention-level'!$A:$A="Deworming"),0))),"Not specified")} -> 0.1 | H74: {=iferror(if(isblank($A74),"",index('Supplemental intervention-level'!$M:$M,match(1,('Supplemental intervention-level'!$C:$C=$A74)*('Supplemental intervention-level'!$A:$A="Deworming"),0))),"Not specified")} -> 0.1 | I74: {=iferror(if(isblank($A74),"",index('Supplemental intervention-level'!$M:$M,match(1,('Supplemental intervention-level'!$C:$C=$A74)*('Supplemental intervention-level'!$A:$A="Deworming"),0))),"Not specified")} -> 0.1 | ... AO74: {=iferror(if(isblank($A74),"",index('Supplemental intervention-level'!$M:$M,match(1,('Supplemental intervention-level'!$C:$C=$A74)*('Supplemental intervention-level'!$A:$A="Deworming"),0))),"Not specified")} -> 0.1
A75: =IFERROR(__xludf.DUMMYFUNCTION("""COMPUTED_VALUE"""),"Non-income long-run benefits of deworming") -> Non-income long-run benefits of deworming | B75: {=iferror(if(isblank($A75),"",index('Supplemental intervention-level'!$M:$M,match(1,('Supplemental intervention-level'!$C:$C=$A75)*('Supplemental intervention-level'!$A:$A="Deworming"),0))),"Not specified")} -> 0.04 | C75: {=iferror(if(isblank($A75),"",index('Supplemental intervention-level'!$M:$M,match(1,('Supplemental intervention-level'!$C:$C=$A75)*('Supplemental intervention-level'!$A:$A="Deworming"),0))),"Not specified")} -> 0.04 | D75: {=iferror(if(isblank($A75),"",index('Supplemental intervention-level'!$M:$M,match(1,('Supplemental intervention-level'!$C:$C=$A75)*('Supplemental intervention-level'!$A:$A="Deworming"),0))),"Not specified")} -> 0.04 | E75: {=iferror(if(isblank($A75),"",index('Supplemental intervention-level'!$M:$M,match(1,('Supplemental intervention-level'!$C:$C=$A75)*('Supplemental intervention-level'!$A:$A="Deworming"),0))),"Not specified")} -> 0.04 | F75: {=iferror(if(isblank($A75),"",index('Supplemental intervention-level'!$M:$M,match(1,('Supplemental intervention-level'!$C:$C=$A75)*('Supplemental intervention-level'!$A:$A="Deworming"),0))),"Not specified")} -> 0.04 | G75: {=iferror(if(isblank($A75),"",index('Supplemental intervention-level'!$M:$M,match(1,('Supplemental intervention-level'!$C:$C=$A75)*('Supplemental intervention-level'!$A:$A="Deworming"),0))),"Not specified")} -> 0.04 | H75: {=iferror(if(isblank($A75),"",index('Supplemental intervention-level'!$M:$M,match(1,('Supplemental intervention-level'!$C:$C=$A75)*('Supplemental intervention-level'!$A:$A="Deworming"),0))),"Not specified")} -> 0.04 | I75: {=iferror(if(isblank($A75),"",index('Supplemental intervention-level'!$M:$M,match(1,('Supplemental intervention-level'!$C:$C=$A75)*('Supplemental intervention-level'!$A:$A="Deworming"),0))),"Not specified")} -> 0.04 | ... AO75: {=iferror(if(isblank($A75),"",index('Supplemental intervention-level'!$M:$M,match(1,('Supplemental intervention-level'!$C:$C=$A75)*('Supplemental intervention-level'!$A:$A="Deworming"),0))),"Not specified")} -> 0.04
A76: =IFERROR(__xludf.DUMMYFUNCTION("""COMPUTED_VALUE"""),"Other NTD prevention (relevant to Sightsavers and END Fund)") -> Other NTD prevention (relevant to Sightsavers and END Fund) | B76: {=iferror(if(isblank($A76),"",index('Supplemental intervention-level'!$M:$M,match(1,('Supplemental intervention-level'!$C:$C=$A76)*('Supplemental intervention-level'!$A:$A="Deworming"),0))),"Not specified")} -> 0.14 | C76: {=iferror(if(isblank($A76),"",index('Supplemental intervention-level'!$M:$M,match(1,('Supplemental intervention-level'!$C:$C=$A76)*('Supplemental intervention-level'!$A:$A="Deworming"),0))),"Not specified")} -> 0.14 | D76: {=iferror(if(isblank($A76),"",index('Supplemental intervention-level'!$M:$M,match(1,('Supplemental intervention-level'!$C:$C=$A76)*('Supplemental intervention-level'!$A:$A="Deworming"),0))),"Not specified")} -> 0.14 | E76: {=iferror(if(isblank($A76),"",index('Supplemental intervention-level'!$M:$M,match(1,('Supplemental intervention-level'!$C:$C=$A76)*('Supplemental intervention-level'!$A:$A="Deworming"),0))),"Not specified")} -> 0.14 | F76: {=iferror(if(isblank($A76),"",index('Supplemental intervention-level'!$M:$M,match(1,('Supplemental intervention-level'!$C:$C=$A76)*('Supplemental intervention-level'!$A:$A="Deworming"),0))),"Not specified")} -> 0.14 | G76: {=iferror(if(isblank($A76),"",index('Supplemental intervention-level'!$M:$M,match(1,('Supplemental intervention-level'!$C:$C=$A76)*('Supplemental intervention-level'!$A:$A="Deworming"),0))),"Not specified")} -> 0.14 | H76: {=iferror(if(isblank($A76),"",index('Supplemental intervention-level'!$M:$M,match(1,('Supplemental intervention-level'!$C:$C=$A76)*('Supplemental intervention-level'!$A:$A="Deworming"),0))),"Not specified")} -> 0.14 | I76: {=iferror(if(isblank($A76),"",index('Supplemental intervention-level'!$M:$M,match(1,('Supplemental intervention-level'!$C:$C=$A76)*('Supplemental intervention-level'!$A:$A="Deworming"),0))),"Not specified")} -> 0.14 | ... AO76: {=iferror(if(isblank($A76),"",index('Supplemental intervention-level'!$M:$M,match(1,('Supplemental intervention-level'!$C:$C=$A76)*('Supplemental intervention-level'!$A:$A="Deworming"),0))),"Not specified")} -> 0.14
A77: =IFERROR(__xludf.DUMMYFUNCTION("""COMPUTED_VALUE"""),"Drug resistance") -> Drug resistance | B77: {=iferror(if(isblank($A77),"",index('Supplemental intervention-level'!$M:$M,match(1,('Supplemental intervention-level'!$C:$C=$A77)*('Supplemental intervention-level'!$A:$A="Deworming"),0))),"Not specified")} -> -0.04 | C77: {=iferror(if(isblank($A77),"",index('Supplemental intervention-level'!$M:$M,match(1,('Supplemental intervention-level'!$C:$C=$A77)*('Supplemental intervention-level'!$A:$A="Deworming"),0))),"Not specified")} -> -0.04 | D77: {=iferror(if(isblank($A77),"",index('Supplemental intervention-level'!$M:$M,match(1,('Supplemental intervention-level'!$C:$C=$A77)*('Supplemental intervention-level'!$A:$A="Deworming"),0))),"Not specified")} -> -0.04 | E77: {=iferror(if(isblank($A77),"",index('Supplemental intervention-level'!$M:$M,match(1,('Supplemental intervention-level'!$C:$C=$A77)*('Supplemental intervention-level'!$A:$A="Deworming"),0))),"Not specified")} -> -0.04 | F77: {=iferror(if(isblank($A77),"",index('Supplemental intervention-level'!$M:$M,match(1,('Supplemental intervention-level'!$C:$C=$A77)*('Supplemental intervention-level'!$A:$A="Deworming"),0))),"Not specified")} -> -0.04 | G77: {=iferror(if(isblank($A77),"",index('Supplemental intervention-level'!$M:$M,match(1,('Supplemental intervention-level'!$C:$C=$A77)*('Supplemental intervention-level'!$A:$A="Deworming"),0))),"Not specified")} -> -0.04 | H77: {=iferror(if(isblank($A77),"",index('Supplemental intervention-level'!$M:$M,match(1,('Supplemental intervention-level'!$C:$C=$A77)*('Supplemental intervention-level'!$A:$A="Deworming"),0))),"Not specified")} -> -0.04 | I77: {=iferror(if(isblank($A77),"",index('Supplemental intervention-level'!$M:$M,match(1,('Supplemental intervention-level'!$C:$C=$A77)*('Supplemental intervention-level'!$A:$A="Deworming"),0))),"Not specified")} -> -0.04 | ... AO77: {=iferror(if(isblank($A77),"",index('Supplemental intervention-level'!$M:$M,match(1,('Supplemental intervention-level'!$C:$C=$A77)*('Supplemental intervention-level'!$A:$A="Deworming"),0))),"Not specified")} -> -0.04
