Workbook
Name BDT_to_USD_2017: #REF!
Name BDT_to_USD_2014: #REF!
Name lesser_lean_season_duration: #REF!
Name nls_household_size: #REF!
Name primary_lean_season_duration: #REF!

Sheet Start here
A1: Notes on how to engage with our cost-effectiveness analysis
A2: This workbook contains our cost-effectiveness analysis. Cost-effectiveness is one factor we use to assess which opportunities are the highest-priority to support. We also consider other factors such as urgency, quality of implementation, and more. If you're a donor interested in supporting the top charity we believe will do the most good at the time your donation is granted, please consider supporting the Top Charities Fund. On the "Moral weights and discount rate" sheet, we've included GiveWell and conventional estimates for a few parameters. If you'd like to see how our results would change based on different inputs for these parameters, you can make a copy of this spreadsheet and enter your own values in the "Anyone" column. Expanding the formula bar at the top of the page (by clicking and dragging the bottom boundary) may make it easier to read the contents of explanatory cells.
A6: Notes on text color coding
A7: Blue text: direct input
A8: Green text: pulling from another cell in this workbook
A9: Black text: calculation
A11: Index
A12: Moral weights and discount rate | B12: Allows staff members or anyone else to supply discount rates and numbers used to trade off different good outcomes
A13: AMF | B13: Cost-effectiveness analysis for long-lasting insecticide-treated net distributions by the Against Malaria Foundation.
A14: GiveDirectly | B14: Cost-effectiveness analysis for unconditional cash transfers by GiveDirectly.
A15: Deworm the World | B15: Cost-effectiveness analysis for deworming by Deworm the World
A16: Unlimit Health | B16: Cost-effectiveness analysis for deworming by Unlimit Health
A17: Sightsavers | B17: Cost-effectiveness analysis for deworming by Sightsavers
A18: Malaria Consortium | B18: Cost-effectiveness analysis for seasonal malaria chemoprevention by Malaria Consortium
A19: Helen Keller International | B19: Cost-effectiveness analysis for vitamin A supplementation by Helen Keller International
A20: New Incentives | B20: Cost-effectiveness analysis for conditional cash transfers for immunization by New Incentives
A21: Value of counterfactual spending by other actors | B21: Used in the leverage and funging adjustments to our cost-effectiveness analyses
A22: Supplemental intervention-level adjustments | B22: Intervention-level adjustments for outcomes not explicitly modeled in our cost-effectiveness analyses
A24: Helpful GiveWell references
A25: =HYPERLINK("https://docs.google.com/document/d/1ZKq-MNU-xtn_48uN33L6VvBEZRAduvjwWMeaEffL4K4/","Guide to GiveWell cost-effectiveness analyses") -> Guide to GiveWell cost-effectiveness analyses
A26: =HYPERLINK("http://www.givewell.org/charities/top-charities","Full reviews of our top charities") -> Full reviews of our top charities
A27: =HYPERLINK("http://www.givewell.org/international/technical/criteria/cost-effectiveness/cost-effectiveness-models","Past versions of our cost-effectiveness analyses") -> Past versions of our cost-effectiveness analyses
A28: =HYPERLINK("http://www.givewell.org/international/technical/criteria/cost-effectiveness","Discussion of cost-effectiveness as a criterion") -> Discussion of cost-effectiveness as a criterion
A29: =HYPERLINK("http://www.givewell.org/international/technical/criteria/cost-effectiveness#MoreonGiveWellsviewsoncosteffectivenessestimates","Blog posts discussing cost-effectiveness") -> Blog posts discussing cost-effectiveness

Sheet Index
A1: Index
A2: New CEA | B2: New cost-effectiveness analysis (CEA) of GiveDirectly's Cash for Poverty Relief program
A3: Analysis
A4: Baseline | B4: Calculation of our best guess of baseline consumption of GiveDirectly's recipients
A5: Consumption | B5: Investment returns function given assumptions about amount invested and ROI
A6: GE | B6: Adjustments to the headline economic multiplier estimate from Egger et al.
A7: Spillover | B7: Bottom-up reconstruction of the Egger et al. multiplier
A8: Mortality | B8: Comparison of Egger et al. mortality estimate with cross-country data
A9: Development | B9: Sense check of how development effects might contribute to cost-effectiveness
A10: RFMF | B10: Estimate of program reach across countries currently targeted by the Cash for Poverty Relief program
A11: Uncertainty
A12: Inputs | B12: Inputs for Monte Carlo simulations of our GiveDirectly model
A13: Sims | B13: Simulations of our GiveDirectly CEA based on the inputs in the previous tab
A14: Raw
A15: WB | B15: Poverty, food insecurity, and other data from the World Bank
A16: IHME | B16: Child mortality data from the Institute for Health Metrics and Evaluation
A17: UNICEF | B17: Child mortality data from UNICEF
A18: Equivalence | B18: Adult equivalence conversion factor calculations
A19: Papers | B19: Papers which estimate economic mutlipliers
A20: u5m papers | B20: Papers which estimate under-5 mortality
A21: GD data
A22: Summ | B22: Overview of data sent to us by GiveDirectly
A23: Historic | B23: Historic funding allocation data across GiveDirectly programs
A24: Flex | B24: Flex and unrestricted funding data across programs
A25: Country | B25: Estimate of program reach across countries currently targeted by the Cash for Poverty Relief program

Sheet New CEA
A1: What is this? This tab outlines our current (new) CEA of GiveDirectly
B2: Kenya | C2: Malawi | D2: Mozambique | E2: Rwanda | F2: Uganda
A3: Program reach
A4: Arbitrary donation (nominal USD) | B4: 1000000 | C4: 1000000 | D4: 1000000 | E4: 1000000 | F4: 1000000
A5: Total size of transfer per household (nominal USD) | B5: 865 | C5: 1000 | D5: 1000 | E5: 1100 | F5: 955
A6: Transfers as a percentage of total cost | B6: 0.84 | C6: 0.84 | D6: 0.75 | E6: 0.85 | F6: 0.71
A7: Number of households receiving transfer | B7: =(B4*B6)/B5 -> 971.09827 | C7: =(C4*C6)/C5 -> 840 | D7: =(D4*D6)/D5 -> 750 | E7: =(E4*E6)/E5 -> 772.72727 | F7: =(F4*F6)/F5 -> 743.4555
A8: PPP adjustment (2017) | B8: =Baseline!B22 -> 2.3689924 | C8: =Baseline!C22 -> 2.9315863 | D8: =Baseline!D22 -> 2.8119848 | E8: =Baseline!E22 -> 2.7940238 | F8: =Baseline!F22 -> 2.961996
A9: Total size of transfer per household (PPP 2017) | B9: =B8*B5 -> 2049.1784 | C9: =C8*C5 -> 2931.5863 | D9: =D8*D5 -> 2811.9848 | E9: =E8*E5 -> 3073.4262 | F9: =F8*F5 -> 2828.7061
A10: Average household size | B10: =Baseline!B4 -> 4.2 | C10: =Baseline!C4 -> 4.5 | D10: =Baseline!D4 -> 4.4 | E10: =Baseline!E4 -> 4.3 | F10: =Baseline!F4 -> 4.8
A11: Size of transfer per person (PPP 2017) | B11: =B9/B10 -> 487.89962 | C11: =C9/C10 -> 651.46361 | D11: =D9/D10 -> 639.08746 | E11: =E9/E10 -> 714.75028 | F11: =F9/F10 -> 589.31378
A12: Number of people reached | B12: =B10*B7 -> 4078.6127 | C12: =C10*C7 -> 3780 | D12: =D10*D7 -> 3300 | E12: =E10*E7 -> 3322.7273 | F12: =F10*F7 -> 3568.5864
A13: Consumption gains to recipients
A14: Baseline annual consumption per capita (PPP 2017) | B14: =Baseline!B35 -> 651.96604 | C14: =Baseline!C35 -> 469.98486 | D14: =Baseline!D35 -> 449.78149 | E14: =Baseline!E35 -> 532.64139 | F14: =Baseline!F35 -> 625.55328
A15: Percentage of transfers invested | B15: 0.43 | C15: =$B15 -> 0.43 | D15: =$B15 -> 0.43 | E15: =$B15 -> 0.43 | F15: =$B15 -> 0.43
A16: Percentage of transfers consumed in year 1 | B16: =1-B15 -> 0.57 | C16: =1-C15 -> 0.57 | D16: =1-D15 -> 0.57 | E16: =1-E15 -> 0.57 | F16: =1-F15 -> 0.57
A17: Implied increase in consumption per person in year 1 | B17: =B16*B11 -> 278.10278 | C17: =C16*C11 -> 371.33426 | D17: =D16*D11 -> 364.27985 | E17: =E16*E11 -> 407.40766 | F17: =F16*F11 -> 335.90885
A18: Percentage increase in consumption over baseline | B18: =((B17+B14)/B14)-1 -> 0.42656023 | C18: =((C17+C14)/C14)-1 -> 0.79009835 | D18: =((D17+D14)/D14)-1 -> 0.80990406 | E18: =((E17+E14)/E14)-1 -> 0.76488172 | F18: =((F17+F14)/F14)-1 -> 0.53697881
A19: Immediate increase in ln(consumption) per person | B19: =ln(1+B18)-ln(1) -> 0.35526612 | C19: =ln(1+C18)-ln(1) -> 0.58227056 | D19: =ln(1+D18)-ln(1) -> 0.59327384 | E19: =ln(1+E18)-ln(1) -> 0.56808367 | F19: =ln(1+F18)-ln(1) -> 0.42981868
A20: Value assigned to increasing ln(consumption) by one unit for one person for one year | B20: 1.442695 | C20: 1.442695 | D20: 1.442695 | E20: 1.442695 | F20: 1.442695
A21: Units of value from year 1 consumption gains per person | B21: =B19*B20 -> 0.51254066 | C21: =C19*C20 -> 0.84003885 | D21: =D19*D20 -> 0.85591322 | E21: =E19*E20 -> 0.8195715 | F21: =F19*F20 -> 0.62009728
A22: Units of value from year 1 consumption gains given program reach | B22: =B21*B12 -> 2090.4549 | C22: =C21*C12 -> 3175.3469 | D22: =D21*D12 -> 2824.5136 | E22: =E21*E12 -> 2723.2126 | F22: =F21*F12 -> 2212.8707
A23: Value of year 2-10 consumption returns as % of year 1 consumption returns | B23: =Consumption!B23 -> 1.2304527 | C23: =Consumption!B37 -> 1.3605831 | D23: =Consumption!B50 -> 1.3976761 | E23: =Consumption!B63 -> 1.3404766 | F23: =Consumption!B76 -> 1.2680226
A24: Units of value from year 1-10 consumption gains | B24: =B22+(B22*B23) -> 4662.6608 | C24: =C22+(C22*C23) -> 7495.6702 | D24: =D22+(D22*D23) -> 6772.2688 | E24: =E22+(E22*E23) -> 6373.6154 | F24: =F22+(F22*F23) -> 5018.8407
A25: Distributional adjustment (accounting for consumption gains accruing to richer recipients) | B25: 0.9 | C25: 0.9 | D25: 0.9 | E25: 0.9 | F25: 0.9
A26: Units of value from year 1-10 consumption gains post adjustments | B26: =B24*B25 -> 4196.3947 | C26: =C24*C25 -> 6746.1032 | D26: =D24*D25 -> 6095.0419 | E26: =E24*E25 -> 5736.2538 | F26: =F24*F25 -> 4516.9566
A27: Units of value from recipient consumption gains per $ donated | B27: =B26/B4 -> 0.0041963947 | C27: =C26/C4 -> 0.0067461032 | D27: =D26/D4 -> 0.0060950419 | E27: =E26/E4 -> 0.0057362538 | F27: =F26/F4 -> 0.0045169566
A28: Previous GiveDirectly cost-effectiveness estimate (units of value per $) | B28: 0.003355 | C28: 0.003355 | D28: 0.003355 | E28: 0.003355 | F28: 0.003355
A29: Initial CE from recipient consumption gains (x previous benchmark) | B29: =B27/B28 -> 1.2507883 | C29: =C27/C28 -> 2.010761 | D29: =D27/D28 -> 1.816704 | E29: =E27/E28 -> 1.7097627 | F29: =F27/F28 -> 1.3463358
A30: Spillovers to non-recipients/general equilibrium effects
A31: Egger et al. economic multiplier | B31: 2.5 | C31: 2.5 | D31: 2.5 | E31: 2.5 | F31: 2.5
A32: Double-counting adjustment (stripping out recipient consumption gains) | B32: =GE!$B$7 -> 0.7032 | C32: =GE!$B$7 -> 0.7032 | D32: =GE!$B$7 -> 0.7032 | E32: =GE!$B$7 -> 0.7032 | F32: =GE!$B$7 -> 0.7032
A33: IV adjustment (regressing Egger et al. towards prior) | B33: 0.6 | C33: 0.6 | D33: 0.6 | E33: 0.6 | F33: 0.6
A34: EV adjustment (generalizing the multiplier to current program conditions) | B34: 0.8 | C34: 0.7 | D34: 0.7 | E34: 0.75 | F34: 0.75
A35: Distributional adjustment (accounting for consumption spillovers accruing to richer non-recipients) | B35: 0.8 | C35: 0.8 | D35: 0.8 | E35: 0.8 | F35: 0.8
A36: Spillover/general equilibrium benefits (as % of recipient consumption benefits), post adjustments | B36: =B31*B35*B32*B33*B34 -> 0.675072 | C36: =C31*C35*C32*C33*C34 -> 0.590688 | D36: =D31*D35*D32*D33*D34 -> 0.590688 | E36: =E31*E35*E32*E33*E34 -> 0.63288 | F36: =F31*F35*F32*F33*F34 -> 0.63288
A37: Units of value from non-recipient spillovers | B37: =B26*B36 -> 2832.8686 | C37: =C26*C36 -> 3984.8422 | D37: =D26*D36 -> 3600.2681 | E37: =E26*E36 -> 3630.3603 | F37: =F26*F36 -> 2858.6915
A38: Units of value from consumption gains and non-recipient spillovers | B38: =B26+B37 -> 7029.2633 | C38: =C26+C37 -> 10730.945 | D38: =D26+D37 -> 9695.3101 | E38: =E26+E37 -> 9366.6142 | F38: =F26+F37 -> 7375.6481
A39: Initial CE from consumption gains and spillovers (x previous benchmark) | B39: =(B38/B4)/B28 -> 2.0951604 | C39: =(C38/C4)/C28 -> 3.1984934 | D39: =(D38/D4)/D28 -> 2.8898093 | E39: =(E38/E4)/E28 -> 2.7918373 | F39: =(F38/F4)/F28 -> 2.1984048
A40: Mortality benefits
A41: Share of children under 5 in targeted population | B41: =Equivalence!B20/Equivalence!B41 -> 0.12879127 | C41: =Equivalence!C20/Equivalence!C41 -> 0.15125027 | D41: =Equivalence!D20/Equivalence!D41 -> 0.16132609 | E41: =Equivalence!E20/Equivalence!E41 -> 0.13732137 | F41: =Equivalence!F20/Equivalence!F41 -> 0.16653773
A42: Number of under-5 children reached | B42: =B41*B12 -> 525.2897 | C42: =C41*C12 -> 571.72601 | D42: =D41*D12 -> 532.37608 | E42: =E41*E12 -> 456.28147 | F42: =F41*F12 -> 594.30429
A43: Average under-5 mortality rate in each country (2023) | B43: {=INDEX(UNICEF!$R$12:$R$211,MATCH(B$2,UNICEF!$B$12:$B$211,0))/1000} -> 0.0410984 | C43: {=INDEX(UNICEF!$R$12:$R$211,MATCH(C$2,UNICEF!$B$12:$B$211,0))/1000} -> 0.0400934 | D43: {=INDEX(UNICEF!$R$12:$R$211,MATCH(D$2,UNICEF!$B$12:$B$211,0))/1000} -> 0.0662141 | E43: {=INDEX(UNICEF!$R$12:$R$211,MATCH(E$2,UNICEF!$B$12:$B$211,0))/1000} -> 0.0380244 | F43: {=INDEX(UNICEF!$R$12:$R$211,MATCH(F$2,UNICEF!$B$12:$B$211,0))/1000} -> 0.0405296
A44: Under-5 mortality rate in Egger et al. preliminary results (2015-2017) | B44: =57/1000 -> 0.057 | C44: =57/1000 -> 0.057 | D44: =57/1000 -> 0.057 | E44: =57/1000 -> 0.057 | F44: =57/1000 -> 0.057
A45: Under-5 mortality rate in UNICEF data (2016) | B45: {=INDEX(UNICEF!$K$12:$K$211,MATCH($B$2,UNICEF!$B$12:$B$211,0))/1000} -> 0.0462512 | C45: {=INDEX(UNICEF!$K$12:$K$211,MATCH($B$2,UNICEF!$B$12:$B$211,0))/1000} -> 0.0462512 | D45: {=INDEX(UNICEF!$K$12:$K$211,MATCH($B$2,UNICEF!$B$12:$B$211,0))/1000} -> 0.0462512 | E45: {=INDEX(UNICEF!$K$12:$K$211,MATCH($B$2,UNICEF!$B$12:$B$211,0))/1000} -> 0.0462512 | F45: {=INDEX(UNICEF!$K$12:$K$211,MATCH($B$2,UNICEF!$B$12:$B$211,0))/1000} -> 0.0462512
A46: Adjustment for GiveDirectly's under-5 population being at higher risk | B46: =B44/B45 -> 1.2324005 | C46: =C44/C45 -> 1.2324005 | D46: =D44/D45 -> 1.2324005 | E46: =E44/E45 -> 1.2324005 | F46: =F44/F45 -> 1.2324005
A47: Under-5 morality rate in GiveDirectly target population (2023) | B47: =B43*B46 -> 0.050649687 | C47: =C43*C46 -> 0.049411124 | D47: =D43*D46 -> 0.081602287 | E47: =E43*E46 -> 0.046861288 | F47: =F43*F46 -> 0.049948698
A48: % reduction in under 5 mortality due to transfer, unadjusted | B48: 0.45 | C48: 0.45 | D48: 0.45 | E48: 0.45 | F48: 0.45
A49: Internal validity adjustment | B49: 0.5 | C49: 0.5 | D49: 0.5 | E49: 0.5 | F49: 0.5
A50: % reduction in under 5 mortality among recipient households, adjusted | B50: =B48*B49 -> 0.225 | C50: =C48*C49 -> 0.225 | D50: =D48*D49 -> 0.225 | E50: =E48*E49 -> 0.225 | F50: =F48*F49 -> 0.225
A51: Under-5 deaths averted among recipient households | B51: =B42*B47*B50 -> 5.9862958 | C51: =C42*C47*C50 -> 6.3561657 | D51: =D42*D47*D50 -> 9.7746989 | E51: =E42*E47*E50 -> 4.810936 | F51: =F42*F47*F50 -> 6.6790632
A52: Value assigned to averting an under-5 death | B52: 116 | C52: 116 | D52: 116 | E52: 116 | F52: 116
A53: Units of value from child mortality benefits | B53: =B51*B52 -> 694.41031 | C53: =C51*C52 -> 737.31522 | D53: =D51*D52 -> 1133.8651 | E53: =E51*E52 -> 558.06857 | F53: =F51*F52 -> 774.77133
A54: Adult mortality benefits (as % of child mortality benefits) | B54: 0.5 | C54: 0.5 | D54: 0.5 | E54: 0.5 | F54: 0.5
A55: Units of value from child and adult mortality benefits | B55: =B53+(B53*B54) -> 1041.6155 | C55: =C53+(C53*C54) -> 1105.9728 | D55: =D53+(D53*D54) -> 1700.7976 | E55: =E53+(E53*E54) -> 837.10286 | F55: =F53+(F53*F54) -> 1162.157
A56: Units of value from consumption and mortality benefits | B56: =B55+B38 -> 8070.8788 | C56: =C55+C38 -> 11836.918 | D56: =D55+D38 -> 11396.108 | E56: =E55+E38 -> 10203.717 | F56: =F55+F38 -> 8537.8051
A57: Initial CE from consumption and child mortality (x previous benchmark) | B57: =(B56/B4)/B28 -> 2.4056271 | C57: =(C56/C4)/C28 -> 3.5281425 | D57: =(D56/D4)/D28 -> 3.3967534 | E57: =(E56/E4)/E28 -> 3.0413464 | F57: =(F56/F4)/F28 -> 2.5448003
A58: Supplementary adjustments
A59: Reduced morbidity | B59: 0.1 | C59: 0.1 | D59: 0.1 | E59: 0.1 | F59: 0.1
A60: Developmental effects | B60: 0.05 | C60: 0.05 | D60: 0.05 | E60: 0.05 | F60: 0.05
A61: Leverage & funging | B61: 0.02 | C61: 0.02 | D61: 0.02 | E61: 0.02 | F61: 0.02
A62: Risk of wastage/fraud | B62: -0.02 | C62: -0.02 | D62: -0.02 | E62: -0.02 | F62: -0.02
A63: Within-org fungibility | B63: -0.05 | C63: -0.05 | D63: -0.05 | E63: -0.05 | F63: -0.05
A64: Psychological spillovers | B64: -0.02 | C64: -0.02 | D64: -0.02 | E64: -0.02 | F64: -0.02
A65: Total adjustment factor | B65: =1+SUM(B59:B64) -> 1.08 | C65: =1+SUM(C59:C64) -> 1.08 | D65: =1+SUM(D59:D64) -> 1.08 | E65: =1+SUM(E59:E64) -> 1.08 | F65: =1+SUM(F59:F64) -> 1.08
A66: Disaggregated cost-effectiveness estimate (x cash) | B66: =B57*B65 -> 2.5980772 | C66: =C57*C65 -> 3.8103939 | D66: =D57*D65 -> 3.6684937 | E66: =E57*E65 -> 3.2846541 | F66: =F57*F65 -> 2.7483844
A67: Estimate of where marginal $ goes | B67: =Flex!C8 -> 0.16246277 | C67: =Flex!C5 -> 0.3325308 | D67: =Flex!C13 -> 0.021891394 | E67: =Flex!C4 -> 0.30206188 | F67: =Flex!C7 -> 0.18105316
A68: Aggregated cost-effectiveness estimate (x cash) | B68: =IFERROR(__xludf.DUMMYFUNCTION("AVERAGE.WEIGHTED(B66,B67,C66,C67,D66,D67,E66,E67,F66,F67)"),3.2592450461417592) -> 3.259245
A69: Cost per life saved | B69: =B4/(B51*(1+B54)) -> 111365.47 | C69: =C4/(C51*(1+C54)) -> 104885.04 | D69: =D4/(D51*(1+D54)) -> 68203.295 | E69: =E4/(E51*(1+E54)) -> 138573.17 | F69: =F4/(F51*(1+F54)) -> 99814.397
A71: Breakdown of bottom-line
A72: In units of value
A73: Consumption benefits to recipients | B73: =B26 -> 4196.3947 | C73: =C26 -> 6746.1032 | D73: =D26 -> 6095.0419 | E73: =E26 -> 5736.2538 | F73: =F26 -> 4516.9566
A74: Spillover benefits to non-recipients | B74: =B73*B36 -> 2832.8686 | C74: =C73*C36 -> 3984.8422 | D74: =D73*D36 -> 3600.2681 | E74: =E73*E36 -> 3630.3603 | F74: =F73*F36 -> 2858.6915
A75: Mortality benefits | B75: =B55 -> 1041.6155 | C75: =C55 -> 1105.9728 | D75: =D55 -> 1700.7976 | E75: =E55 -> 837.10286 | F75: =F55 -> 1162.157
A76: Additional benefits and downsides | B76: =SUM(B73:B75)*B65-SUM(B73:B75) -> 645.6703 | C76: =SUM(C73:C75)*C65-SUM(C73:C75) -> 946.95346 | D76: =SUM(D73:D75)*D65-SUM(D73:D75) -> 911.68861 | E76: =SUM(E73:E75)*E65-SUM(E73:E75) -> 816.29736 | F76: =SUM(F73:F75)*F65-SUM(F73:F75) -> 683.02441
A77: Total units of value | B77: =SUM(B73:B76) -> 8716.5491 | C77: =SUM(C73:C76) -> 12783.872 | D77: =SUM(D73:D76) -> 12307.796 | E77: =SUM(E73:E76) -> 11020.014 | F77: =SUM(F73:F76) -> 9220.8295
A78: Units of value per $ | B78: =B77/B4 -> 0.0087165491 | C78: =C77/C4 -> 0.012783872 | D78: =D77/D4 -> 0.012307796 | E78: =E77/E4 -> 0.011020014 | F78: =F77/F4 -> 0.0092208295
A79: In percentages | B79: Kenya | C79: Malawi | D79: Mozambique | E79: Rwanda | F79: Uganda
A80: Consumption benefits to recipients | B80: =B73/SUM(B$73:B$76) -> 0.48142845 | C80: =C73/SUM(C$73:C$76) -> 0.52770423 | D80: =D73/SUM(D$73:D$76) -> 0.49521797 | E80: =E73/SUM(E$73:E$76) -> 0.52053052 | F80: =F73/SUM(F$73:F$76) -> 0.48986445
A81: Spillover benefits to non-recipients | B81: =B74/SUM(B$73:B$76) -> 0.32499887 | C81: =C74/SUM(C$73:C$76) -> 0.31170856 | D81: =D74/SUM(D$73:D$76) -> 0.29251931 | E81: =E74/SUM(E$73:E$76) -> 0.32943336 | F81: =F74/SUM(F$73:F$76) -> 0.31002542
A82: Mortality benefits | B82: =B75/SUM(B$73:B$76) -> 0.11949861 | C82: =C75/SUM(C$73:C$76) -> 0.086513136 | D82: =D75/SUM(D$73:D$76) -> 0.13818864 | E82: =E75/SUM(E$73:E$76) -> 0.075962048 | F82: =F75/SUM(F$73:F$76) -> 0.12603606
A83: Additional benefits and downsides | B83: =B76/SUM(B$73:B$76) -> 0.074074074 | C83: =C76/SUM(C$73:C$76) -> 0.074074074 | D83: =D76/SUM(D$73:D$76) -> 0.074074074 | E83: =E76/SUM(E$73:E$76) -> 0.074074074 | F83: =F76/SUM(F$73:F$76) -> 0.074074074

Sheet Analysis
A1: Analysis
A2: Baseline | B2: Calculation of our best guess of baseline consumption of GiveDirectly's recipients
A3: Consumption | B3: Investment returns function given assumptions about amount invested and ROI
A4: GE | B4: Adjustments to the headline economic multiplier estimate from Egger et al.
A5: Spillover | B5: Bottom-up reconstruction of the Egger et al. multiplier
A6: Mortality | B6: Comparison of Egger et al. mortality estimate with cross-country data
A7: Development | B7: Sense check of how development effects might contribute to cost-effectiveness
A8: RFMF | B8: Estimate of program reach across countries currently targeted by the Cash for Poverty Relief program

Sheet Baseline
A1: What is this? This tab calculates our best guess of baseline consumption of GiveDirectly's recipients in the 5 countries they have live Poverty Relief programs
A2: Notes: latest consumption surveys sourced from World Bank PIP | B2: Kenya | C2: Malawi | D2: Mozambique | E2: Rwanda | F2: Uganda | G2: Notes
A3: Demographics
A4: Average rural household size | B4: 4.2 | C4: 4.5 | D4: 4.4 | E4: 4.3 | F4: 4.8
A6: Consumption - Government consumption survey data
A7: Annual consumption per adult equivalent in lowest quintile (local currency, latest year available) | B7: =SUM(3398*12)*(32088/41428) -> 31582.994 | E7: 86000 | F7: =sum(36758*12) -> 441096
A8: Step 1: convert from adult equivalent to per capita terms
A9: Implied adjustment to get measures in per capita terms | B9: =Equivalence!B90 -> 0.84912187 | E9: =Equivalence!E90 -> 0.9254366 | F9: =Equivalence!F90 -> 0.92119457
A10: Annual consumption per capita in lowest quintile (local currency, latest year available) | B10: =B7*B9 -> 26817.811 | C10: 76823 | D10: =224*12 -> 2688 | E10: =E7*E9 -> 79587.548 | F10: =F7*F9 -> 406335.24
A11: Year data was collected | B11: 2021 | C11: 2019 | D11: 2019 | E11: 2016 | F11: 2019
A12: Year prices are expressed in | B12: 2021 | C12: 2019 | D12: 2019 | E12: 2014 | F12: 2010
A13: Step 2: account for economic growth since data collection year
A14: Years since data collection | B14: =2024-B11 -> 3 | C14: =2024-C11 -> 5 | D14: =2024-D11 -> 5 | E14: =2024-E11 -> 8 | F14: =2024-F11 -> 5
A15: Estimated consumption growth per year | B15: 0.02 | C15: 0.01 | D15: 0.01 | E15: 0.02 | F15: 0.02
A16: Estimated annual consumption per capita in lowest quintile (local currency, 2024, not PPP adjusted) | B16: =B10*(1+B15)^B14 -> 28459.276 | C16: =C10*(1+C15)^C14 -> 80741.745 | D16: =D10*(1+D15)^D14 -> 2825.115 | E16: =E10*(1+E15)^E14 -> 93249.497 | F16: =F10*(1+F15)^F14 -> 448626.94
A17: Step 3: covert to USD
A18: Official exchange rate in 2017 | B18: {=INDEX(WB!$E$13:$BO$17,MATCH(B$2,WB!$A$13:$A$17,0),MATCH(2017,WB!$E$12:$BO$12,0))} -> 103.41 | C18: {=INDEX(WB!$E$13:$BO$17,MATCH(C$2,WB!$A$13:$A$17,0),MATCH(2017,WB!$E$12:$BO$12,0))} -> 730.2725 | D18: {=INDEX(WB!$E$13:$BO$17,MATCH(D$2,WB!$A$13:$A$17,0),MATCH(2017,WB!$E$12:$BO$12,0))} -> 63.58432 | E18: {=INDEX(WB!$E$13:$BO$17,MATCH(E$2,WB!$A$13:$A$17,0),MATCH(2017,WB!$E$12:$BO$12,0))} -> 831.5543 | F18: {=INDEX(WB!$E$13:$BO$17,MATCH(F$2,WB!$A$13:$A$17,0),MATCH(2017,WB!$E$12:$BO$12,0))} -> 3611.224 | G18: NB: this is the nominal exchange rate
A19: LCU conversion factor in 2017 | B19: {=INDEX(WB!$E$4:$BO$8,MATCH(B$2,WB!$A$4:$A$8,0),MATCH(2017,WB!$E$3:$BO$3,0))} -> 43.65147 | C19: {=INDEX(WB!$E$4:$BO$8,MATCH(C$2,WB!$A$4:$A$8,0),MATCH(2017,WB!$E$3:$BO$3,0))} -> 249.1049 | D19: {=INDEX(WB!$E$4:$BO$8,MATCH(D$2,WB!$A$4:$A$8,0),MATCH(2017,WB!$E$3:$BO$3,0))} -> 22.6119 | E19: {=INDEX(WB!$E$4:$BO$8,MATCH(E$2,WB!$A$4:$A$8,0),MATCH(2017,WB!$E$3:$BO$3,0))} -> 297.6189 | F19: {=INDEX(WB!$E$4:$BO$8,MATCH(F$2,WB!$A$4:$A$8,0),MATCH(2017,WB!$E$3:$BO$3,0))} -> 1219.186 | G19: This takes into account cost-of-living differentials
A20: Annual consumption per capita (nominal USD 2017) | B20: =B16/B18 -> 275.20816 | C20: =C16/C18 -> 110.56386 | D20: =D16/D18 -> 44.431001 | E20: =E16/E18 -> 112.13879 | F20: =F16/F18 -> 124.23127
A21: Bottom quintile annual consumption per capita (2017 PPP) | B21: =B16/B19 -> 651.96604 | C21: =C16/C19 -> 324.12749 | D21: =D16/D19 -> 124.9393 | E21: =E16/E19 -> 313.31847 | F21: =F16/F19 -> 367.97252
A22: Implied PPP adjustment | B22: =B21/B20 -> 2.3689924 | C22: =C21/C20 -> 2.9315863 | D22: =D18/D19 -> 2.8119848 | E22: =E21/E20 -> 2.7940238 | F22: =F21/F20 -> 2.961996
A24: Consumption - RCT data
A25: Annual consumption per capita (nominal) | C25: =((13.96+19.18)/C4)*12 -> 88.373333 | E25: =10.7*12 -> 128.4
A26: Year this esimate comes from | B26: 2014 | C26: 2019 | E26: 2016 | F26: 2016
A27: Annual consumption per capita (PPP adjusted, year of data collection) | B27: =2536/B4 -> 603.80952 | C27: =C25*C22 -> 259.07405 | E27: =E25*E22 -> 358.75266 | F27: =2828/F4 -> 589.16667
A28: Years since data collection | B28: =2024-B26 -> 10 | C28: =2024-C26 -> 5 | E28: =2024-E26 -> 8 | F28: =2024-F26 -> 8
A29: Estimated annual consumption per capita (PPP adjusted, 2024) | B29: =B27*(1+B15)^B28 -> 736.04044 | C29: =C27*(1+C15)^C28 -> 272.28943 | E29: =E27*(1+E15)^E28 -> 420.33592 | F29: =F27*(1+F15)^F28 -> 690.30265
A31: Best guess
A32: Bottom quintile consumption estimates implied by government surveys | B32: =B21 -> 651.96604 | C32: =C21 -> 324.12749 | D32: =D21 -> 124.9393 | E32: =E21 -> 313.31847 | F32: =F21 -> 367.97252
A33: RCT estimates | B33: =B29 -> 736.04044 | C33: =C29 -> 272.28943 | D33: =D29 | E33: =E29 -> 420.33592 | F33: =F29 -> 690.30265
A34: Ad hoc adjustment to government consumption estimates | B34: 1 | C34: 1.45 | D34: 3.6 | E34: 1.7 | F34: 1.7
A35: Best-guess of consumption of GiveDirectly recipients | B35: =B32*B34 -> 651.96604 | C35: =C32*C34 -> 469.98486 | D35: =D32*D34 -> 449.78149 | E35: =E32*E34 -> 532.64139 | F35: =F32*F34 -> 625.55328
A37: Size of transfer
A38: Size of transfer (nominal USD) | B38: 1000 | C38: 1000 | D38: 1000 | E38: 1000 | F38: 1000
A39: Size of transfer (2017 PPP) | B39: =B22*B38 -> 2368.9924 | C39: =C22*C38 -> 2931.5863 | D39: =D22*D38 -> 2811.9848 | E39: =E22*E38 -> 2794.0238 | F39: =F22*F38 -> 2961.996 | G39: Intuition: $1k 'goes further' in different countries
A43: Compared to absolute poverty benchmarks
A44: Absolute poverty line (2017 prices) | B44: 2.15 | C44: 2.15 | D44: 2.15 | E44: 2.15 | F44: 2.15
A45: Estimated requirement to meet basic calorific needs (2017 prices) | B45: 0.83 | C45: 0.83 | D45: 0.83 | E45: 0.83 | F45: 0.83
B46: Kenya | C46: Malawi | D46: Mozambique | E46: Rwanda | F46: Uganda
A47: Implied consumption per day (current best guess) | B47: =B35/365 -> 1.7862083 | C47: =C35/365 -> 1.2876297 | D47: =D35/365 -> 1.2322781 | E47: =E35/365 -> 1.4592915 | F47: =F35/365 -> 1.7138446
A48: Implied poverty gap | B48: =(B44-B47)/B44 -> 0.16920543 | C48: =(C44-C47)/C44 -> 0.40110245 | D48: =(D44-D47)/D44 -> 0.42684742 | E48: =(E44-E47)/E44 -> 0.32125978 | F48: =(F44-F47)/F44 -> 0.20286298
B50: Kenya | C50: Malawi | D50: Mozambique | E50: Rwanda | F50: Uganda | G50: Kenya | H50: Malawi | I50: Mozambique | J50: Rwanda | K50: Uganda
A51: Best guess of consumption per capita of GiveDirectly recipients | B51: =B35 -> 651.96604 | C51: =C35 -> 469.98486 | D51: =D35 -> 449.78149 | E51: =E35 -> 532.64139 | F51: =F35 -> 625.55328 | G51: =B51/$B51 -> 1 | H51: =C51/$B51 -> 0.72087322 | I51: =D51/$B51 -> 0.68988485 | J51: =E51/$B51 -> 0.81697721 | K51: =F51/$B51 -> 0.95948752
A52: PIP median consumption estimates (per day) | B52: =WB!S88 -> 3.098574 | C52: =WB!S96 -> 1.533903 | D52: =WB!S93 -> 1.293979 | E52: =WB!S100 -> 2.073805 | F52: =WB!S111 -> 2.43913 | G52: =B52/$B52 -> 1 | H52: =C52/$B52 -> 0.49503514 | I52: =D52/$B52 -> 0.41760468 | J52: =E52/$B52 -> 0.66927722 | K52: =F52/$B52 -> 0.78717823
A53: GDP per capita | B53: =WB!BP22 -> 5699.8212 | C53: =WB!BP23 -> 1493.6631 | D53: =WB!BP24 -> 1683.4586 | E53: =WB!BP25 -> 3029.5881 | F53: =WB!BP26 -> 2792.5334 | G53: =B53/$B53 -> 1 | H53: =C53/$B53 -> 0.26205439 | I53: =D53/$B53 -> 0.29535288 | J53: =E53/$B53 -> 0.53152336 | K53: =F53/$B53 -> 0.48993351
A54: % of people not living in multidimensional poverty | B54: =1-WB!C32 -> 0.546 | C54: =1-WB!C33 -> 0.217 | E54: =1-WB!C35 -> 0.426 | F54: =1-WB!C36 -> 0.477 | G54: =B54/$B54 -> 1 | H54: =C54/$B54 -> 0.3974359 | J54: =E54/$B54 -> 0.78021978 | K54: =F54/$B54 -> 0.87362637
A55: % of children not stunted | B55: =1-WB!C41 -> 0.806 | C55: =1-WB!C42 -> 0.63 | D55: =1-WB!C43 -> 0.622 | E55: =1-WB!C44 -> 0.674 | F55: =1-WB!C45 -> 0.721 | G55: =B55/$B$55 -> 1 | H55: =C55/$B$55 -> 0.78163772 | I55: =D55/$B$55 -> 0.77171216 | J55: =E55/$B$55 -> 0.83622829 | K55: =F55/$B$55 -> 0.89454094
B58: Kenya | C58: Malawi | D58: Mozambique | E58: Rwanda | F58: Uganda
A59: Government survey estimates | B59: =B21 -> 651.96604 | C59: =C21 -> 324.12749 | D59: =D21 -> 124.9393 | E59: =E21 -> 313.31847 | F59: =F21 -> 367.97252
A60: RCT estimates | B60: =B29 -> 736.04044 | C60: =C29 -> 272.28943 | D60: =D29 | E60: =E29 -> 420.33592 | F60: =F29 -> 690.30265
A61: GiveWell best-guess | B61: =B35 -> 651.96604 | C61: =C35 -> 469.98486 | D61: =D35 -> 449.78149 | E61: =E35 -> 532.64139 | F61: =F35 -> 625.55328
B81: Kenya (old) | C81: Kenya | D81: Malawi | E81: Mozambique | F81: Rwanda | G81: Uganda
B82: 670 | C82: 651.96604 | D82: 469.98486 | E82: 449.78149 | F82: 532.64139 | G82: 625.55328
A83: GiveWell best-guess | B83: =B82/365 -> 1.8356164 | C83: =C82/365 -> 1.7862083 | D83: =D82/365 -> 1.2876297 | E83: =E82/365 -> 1.2322781 | F83: =F82/365 -> 1.4592915 | G83: =G82/365 -> 1.7138446

Sheet Consumption
A1: What is this? This tab constructs an investment returns function given assumptions about amount invested and ROI
A3: Consumption returns assumptions | B3: Kenya | C3: Malawi | D3: Mozambique | E3: Rwanda | F3: Uganda
A4: Amount of transfer invested | B4: ='New CEA'!B15 -> 0.43 | C4: ='New CEA'!C15 -> 0.43 | D4: ='New CEA'!D15 -> 0.43 | E4: ='New CEA'!E15 -> 0.43 | F4: ='New CEA'!F15 -> 0.43
A5: Year 2 ROI | B5: 0.4 | C5: 0.4 | D5: 0.4 | E5: 0.4 | F5: 0.4
A6: Decay in consumption returns | B6: -0.2 | C6: =$B6 -> -0.2 | D6: =$B6 -> -0.2 | E6: =$B6 -> -0.2 | F6: =$B6 -> -0.2
A7: Counterfactual growth in recipient consumption | B7: =Baseline!B15 -> 0.02 | C7: =Baseline!C15 -> 0.01 | D7: =Baseline!D15 -> 0.01 | E7: =Baseline!E15 -> 0.02 | F7: =Baseline!F15 -> 0.02
A8: Moral weights
A9: Discount rate | B9: 0.04
A10: Value assigned to increasing ln(consumption) by one unit for one person for one year | B10: ='New CEA'!$B$20 -> 1.442695
A12: Kenya | B12: 2024 | C12: =B12+1 -> 2025 | D12: =C12+1 -> 2026 | E12: =D12+1 -> 2027 | F12: =E12+1 -> 2028 | G12: =F12+1 -> 2029 | H12: =G12+1 -> 2030 | I12: =H12+1 -> 2031 | J12: =I12+1 -> 2032 | K12: =J12+1 -> 2033
A13: Number of people reached | B13: ='New CEA'!B12 -> 4078.6127
A14: Transfer size per person | B14: ='New CEA'!B11 -> 487.89962
A15: Year 1 increase in consumption | B15: =B14*(1-B$4) -> 278.10278
A16: Amount invested/saved | B16: =B14-B15 -> 209.79684
A17: Baseline/counterfactual consumption | B17: ='New CEA'!$B$14 -> 651.96604 | C17: =B17*(1+$B$7) -> 665.00536 | D17: =C17*(1+$B$7) -> 678.30546 | E17: =D17*(1+$B$7) -> 691.87157 | F17: =E17*(1+$B$7) -> 705.709 | G17: =F17*(1+$B$7) -> 719.82318 | H17: =G17*(1+$B$7) -> 734.21965 | I17: =H17*(1+$B$7) -> 748.90404 | J17: =I17*(1+$B$7) -> 763.88212 | K17: =J17*(1+$B$7) -> 779.15976
A18: Counterfactual increase in consumption | B18: =B15 -> 278.10278 | C18: =B16*$B$5 -> 83.918735 | D18: =C18*(1+$B$6) -> 67.134988 | E18: =D18*(1+$B$6) -> 53.70799 | F18: =E18*(1+$B$6) -> 42.966392 | G18: =F18*(1+$B$6) -> 34.373114 | H18: =G18*(1+$B$6) -> 27.498491 | I18: =H18*(1+$B$6) -> 21.998793 | J18: =I18*(1+$B$6) -> 17.599034 | K18: =J18*(1+$B$6) -> 14.079227
A19: Increase in ln(consumption) | B19: =ln(B17+B18)-ln(B17) -> 0.35526612 | C19: =ln(C17+C18)-ln(C17) -> 0.11884254 | D19: =ln(D17+D18)-ln(D17) -> 0.094377531 | E19: =ln(E17+E18)-ln(E17) -> 0.074761503 | F19: =ln(F17+F18)-ln(F17) -> 0.05910253 | G19: =ln(G17+G18)-ln(G17) -> 0.046647072 | H19: =ln(H17+H18)-ln(H17) -> 0.036768359 | I19: =ln(I17+I18)-ln(I17) -> 0.02895148 | ... K19: =ln(K17+K18)-ln(K17) -> 0.017908439
A20: Discounted increase in ln(consumption) | B20: =B19/(1+$B$9)^(B$12-2024) -> 0.35526612 | C20: =C19/(1+$B$9)^(C$12-2024) -> 0.11427167 | D20: =D19/(1+$B$9)^(D$12-2024) -> 0.087257333 | E20: =E19/(1+$B$9)^(E$12-2024) -> 0.066462704 | F20: =F19/(1+$B$9)^(F$12-2024) -> 0.05052109 | G20: =G19/(1+$B$9)^(G$12-2024) -> 0.038340493 | H20: =H19/(1+$B$9)^(H$12-2024) -> 0.029058568 | I20: =I19/(1+$B$9)^(I$12-2024) -> 0.022000746 | ... K20: =K19/(1+$B$9)^(K$12-2024) -> 0.012582232
A21: Discounted units of value | B21: =B20*$B$10 -> 0.51254066 | C21: =C20*$B$10 -> 0.16485917 | D21: =D20*$B$10 -> 0.12588572 | E21: =E20*$B$10 -> 0.095885414 | F21: =F20*$B$10 -> 0.072886526 | G21: =G20*$B$10 -> 0.055313639 | H21: =H20*$B$10 -> 0.041922652 | I21: =I20*$B$10 -> 0.031740367 | ... K21: =K20*$B$10 -> 0.018152323
A22: Total units of value given people reached | B22: =B21*$B$13 -> 2090.4549 | C22: =C21*$B$13 -> 672.39671 | D22: =D21*$B$13 -> 513.4391 | E22: =E21*$B$13 -> 391.07947 | F22: =F21*$B$13 -> 297.27591 | G22: =G21*$B$13 -> 225.60291 | H22: =H21*$B$13 -> 170.98626 | I22: =I21*$B$13 -> 129.45666 | ... K22: =K21*$B$13 -> 74.036297
A23: Year 2-10 consumption gains (as % of year 1 consumption gains) | B23: =SUM(C22:K22)/B22 -> 1.2304527
A24: Relative consumption gains (%) | B24: =B18/B17 -> 0.42656023 | C24: =C18/C17 -> 0.12619257 | D24: =D18/D17 -> 0.098974565 | E24: =E18/E17 -> 0.07762711 | F24: =F18/F17 -> 0.060884007 | G24: =G18/G17 -> 0.047752163 | H24: =H18/H17 -> 0.037452677 | I24: =I18/I17 -> 0.029374648 | ... K24: =K18/K17 -> 0.018069757
A26: Malawi | B26: 2024 | C26: =B26+1 -> 2025 | D26: =C26+1 -> 2026 | E26: =D26+1 -> 2027 | F26: =E26+1 -> 2028 | G26: =F26+1 -> 2029 | H26: =G26+1 -> 2030 | I26: =H26+1 -> 2031 | J26: =I26+1 -> 2032 | K26: =J26+1 -> 2033
A27: Number of people reached | B27: ='New CEA'!C12 -> 3780
A28: Transfer size per person | B28: ='New CEA'!C11 -> 651.46361
A29: Year 1 increase in consumption | B29: =B28*(1-C$4) -> 371.33426
A30: Amount invested/saved | B30: =B28-B29 -> 280.12935
A31: Baseline/counterfactual consumption | B31: ='New CEA'!C14 -> 469.98486 | C31: =B31*(1+$C$7) -> 474.6847 | D31: =C31*(1+$B$7) -> 484.1784 | E31: =D31*(1+$B$7) -> 493.86197 | F31: =E31*(1+$B$7) -> 503.73921 | G31: =F31*(1+$B$7) -> 513.81399 | H31: =G31*(1+$B$7) -> 524.09027 | I31: =H31*(1+$B$7) -> 534.57207 | J31: =I31*(1+$B$7) -> 545.26352 | K31: =J31*(1+$B$7) -> 556.16879
A32: Counterfactual increase in consumption | B32: =B29 -> 371.33426 | C32: =B30*$C$5 -> 112.05174 | D32: =C32*(1+$C$6) -> 89.641393 | E32: =D32*(1+$C$6) -> 71.713114 | F32: =E32*(1+$C$6) -> 57.370491 | G32: =F32*(1+$C$6) -> 45.896393 | H32: =G32*(1+$C$6) -> 36.717115 | I32: =H32*(1+$C$6) -> 29.373692 | J32: =I32*(1+$C$6) -> 23.498953 | K32: =J32*(1+$C$6) -> 18.799163
A33: Increase in ln(consumption) | B33: =ln(B31+B32)-ln(B31) -> 0.58227056 | C33: =ln(C31+C32)-ln(C31) -> 0.21192493 | D33: =ln(D31+D32)-ln(D31) -> 0.16986196 | E33: =ln(E31+E32)-ln(E31) -> 0.135587 | F33: =ln(F31+F32)-ln(F31) -> 0.10785774 | G33: =ln(G31+G32)-ln(G31) -> 0.085558164 | H33: =ln(H31+H32)-ln(H31) -> 0.067713563 | I33: =ln(I31+I32)-ln(I31) -> 0.053491521 | ... K33: =ln(K31+K32)-ln(K31) -> 0.033242478
A34: Discounted increase in ln(consumption) | B34: =B33/(1+$B$9)^(B$12-2024) -> 0.58227056 | C34: =C33/(1+$B$9)^(C$12-2024) -> 0.20377397 | D34: =D33/(1+$B$9)^(D$12-2024) -> 0.15704693 | E34: =E33/(1+$B$9)^(E$12-2024) -> 0.12053635 | F34: =F33/(1+$B$9)^(F$12-2024) -> 0.092197248 | G34: =G33/(1+$B$9)^(G$12-2024) -> 0.070322575 | H34: =H33/(1+$B$9)^(H$12-2024) -> 0.053515013 | I34: =I33/(1+$B$9)^(I$12-2024) -> 0.04064916 | ... K34: =K33/(1+$B$9)^(K$12-2024) -> 0.023355724
A35: Discounted units of value | B35: =B34*$B$10 -> 0.84003885 | C35: =C34*$B$10 -> 0.2939837 | D35: =D34*$B$10 -> 0.22657083 | E35: =E34*$B$10 -> 0.17389719 | F35: =F34*$B$10 -> 0.13301251 | G35: =G34*$B$10 -> 0.10145403 | H35: =H34*$B$10 -> 0.077205843 | I35: =I34*$B$10 -> 0.058644342 | ... K35: =K34*$B$10 -> 0.033695187
A36: Total units of value given people reached | B36: =B35*$B$13 -> 3426.1931 | C36: =C35*$B$13 -> 1199.0457 | D36: =D35*$B$13 -> 924.09468 | E36: =E35*$B$13 -> 709.25929 | F36: =F35*$B$13 -> 542.50653 | G36: =G35*$B$13 -> 413.79169 | H36: =H35*$B$13 -> 314.89273 | I36: =I35*$B$13 -> 239.18756 | ... K36: =K35*$B$13 -> 137.42962
A37: Year 2-10 consumption gains (as % of year 1 consumption gains) | B37: =SUM(C36:K36)/B36 -> 1.3605831
A39: Mozambique | B39: 2024 | C39: =B39+1 -> 2025 | D39: =C39+1 -> 2026 | E39: =D39+1 -> 2027 | F39: =E39+1 -> 2028 | G39: =F39+1 -> 2029 | H39: =G39+1 -> 2030 | I39: =H39+1 -> 2031 | J39: =I39+1 -> 2032 | K39: =J39+1 -> 2033
A40: Number of people reached | B40: ='New CEA'!D12 -> 3300
A41: Transfer size per person | B41: ='New CEA'!D11 -> 639.08746
A42: Year 1 increase in consumption | B42: =B41*(1-D$4) -> 364.27985
A43: Amount invested/saved | B43: =B41-B42 -> 274.80761
A44: Baseline/counterfactual consumption | B44: ='New CEA'!D14 -> 449.78149 | C44: =B44*(1+$D$7) -> 454.2793 | D44: =C44*(1+$D$7) -> 458.8221 | E44: =D44*(1+$D$7) -> 463.41032 | F44: =E44*(1+$D$7) -> 468.04442 | G44: =F44*(1+$D$7) -> 472.72487 | H44: =G44*(1+$D$7) -> 477.45211 | I44: =H44*(1+$D$7) -> 482.22664 | J44: =I44*(1+$D$7) -> 487.0489 | K44: =J44*(1+$D$7) -> 491.91939
A45: Counterfactual increase in consumption | B45: =B42 -> 364.27985 | C45: =B43*$D$5 -> 109.92304 | D45: =C45*(1+$D$6) -> 87.938435 | E45: =D45*(1+$D$6) -> 70.350748 | F45: =E45*(1+$D$6) -> 56.280598 | G45: =F45*(1+$D$6) -> 45.024479 | H45: =G45*(1+$D$6) -> 36.019583 | I45: =H45*(1+$D$6) -> 28.815666 | J45: =I45*(1+$D$6) -> 23.052533 | K45: =J45*(1+$D$6) -> 18.442026
A46: Increase in ln(consumption) | B46: =ln(B44+B45)-ln(B44) -> 0.59327384 | C46: =ln(C44+C45)-ln(C44) -> 0.21670074 | D46: =ln(D44+D45)-ln(D44) -> 0.17534838 | E46: =ln(E44+E45)-ln(E44) -> 0.14133542 | F46: =ln(F44+F45)-ln(F44) -> 0.11354855 | G46: =ln(G44+G45)-ln(G44) -> 0.090977694 | H46: =ln(H44+H45)-ln(H44) -> 0.07273104 | I46: =ln(I44+I45)-ln(I44) -> 0.058038168 | ... K46: =ln(K44+K45)-ln(K44) -> 0.036804273
A47: Discounted increase in ln(consumption) | B47: =B46/(1+$B$9)^(B$12-2024) -> 0.59327384 | C47: =C46/(1+$B$9)^(C$12-2024) -> 0.2083661 | D47: =D46/(1+$B$9)^(D$12-2024) -> 0.16211943 | E47: =E46/(1+$B$9)^(E$12-2024) -> 0.12564667 | F47: =F46/(1+$B$9)^(F$12-2024) -> 0.097061776 | G47: =G46/(1+$B$9)^(G$12-2024) -> 0.074777033 | H47: =H46/(1+$B$9)^(H$12-2024) -> 0.057480397 | I47: =I46/(1+$B$9)^(I$12-2024) -> 0.044104237 | ... K47: =K46/(1+$B$9)^(K$12-2024) -> 0.025858194
A48: Discounted units of value | B48: =B47*$B$10 -> 0.85591322 | C48: =C47*$B$10 -> 0.30060874 | D48: =D47*$B$10 -> 0.2338889 | E48: =E47*$B$10 -> 0.18126983 | F48: =F47*$B$10 -> 0.14003054 | G48: =G47*$B$10 -> 0.10788045 | H48: =H47*$B$10 -> 0.082926684 | I48: =I47*$B$10 -> 0.063628965 | ... K48: =K47*$B$10 -> 0.037305488
A49: Total units of value given people reached | B49: =B48*$B$13 -> 3490.9386 | C49: =C48*$B$13 -> 1226.0666 | D49: =D48*$B$13 -> 953.94223 | E49: =E48*$B$13 -> 739.32944 | F49: =F48*$B$13 -> 571.13036 | G49: =G48*$B$13 -> 440.00259 | H49: =H48*$B$13 -> 338.22583 | I49: =I48*$B$13 -> 259.5179 | ... K49: =K48*$B$13 -> 152.15464
A50: Year 2-10 consumption gains (as % of year 1 consumption gains) | B50: =SUM(C49:K49)/B49 -> 1.3976761
A52: Rwanda | B52: 2024 | C52: =B52+1 -> 2025 | D52: =C52+1 -> 2026 | E52: =D52+1 -> 2027 | F52: =E52+1 -> 2028 | G52: =F52+1 -> 2029 | H52: =G52+1 -> 2030 | I52: =H52+1 -> 2031 | J52: =I52+1 -> 2032 | K52: =J52+1 -> 2033
A53: Number of people reached | B53: ='New CEA'!E12 -> 3322.7273
A54: Transfer size per person | B54: ='New CEA'!E11 -> 714.75028
A55: Year 1 increase in consumption | B55: =B54*(1-E$4) -> 407.40766
A56: Amount invested/saved | B56: =B54-B55 -> 307.34262
A57: Baseline/counterfactual consumption | B57: ='New CEA'!E14 -> 532.64139 | C57: =B57*(1+$E$7) -> 543.29422 | D57: =C57*(1+$E$7) -> 554.1601 | E57: =D57*(1+$E$7) -> 565.24331 | F57: =E57*(1+$E$7) -> 576.54817 | G57: =F57*(1+$E$7) -> 588.07913 | H57: =G57*(1+$E$7) -> 599.84072 | I57: =H57*(1+$E$7) -> 611.83753 | J57: =I57*(1+$E$7) -> 624.07428 | K57: =J57*(1+$E$7) -> 636.55577
A58: Counterfactual increase in consumption | B58: =B55 -> 407.40766 | C58: =B56*$E$5 -> 122.93705 | D58: =C58*(1+$E$6) -> 98.349639 | E58: =D58*(1+$E$6) -> 78.679711 | F58: =E58*(1+$E$6) -> 62.943769 | G58: =F58*(1+$E$6) -> 50.355015 | H58: =G58*(1+$E$6) -> 40.284012 | I58: =H58*(1+$E$6) -> 32.22721 | J58: =I58*(1+$E$6) -> 25.781768 | K58: =J58*(1+$E$6) -> 20.625414 | L58: =B58/sum(B58:K58) -> 0.43360095
A59: Increase in ln(consumption) | B59: =ln(B57+B58)-ln(B57) -> 0.56808367 | C59: =ln(C57+C58)-ln(C57) -> 0.20398585 | D59: =ln(D57+D58)-ln(D57) -> 0.16337243 | E59: =ln(E57+E58)-ln(E57) -> 0.13032291 | F59: =ln(F57+F58)-ln(F57) -> 0.10361512 | G59: =ln(G57+G58)-ln(G57) -> 0.082157016 | H59: =ln(H57+H58)-ln(H57) -> 0.064998898 | I59: =ln(I57+I58)-ln(I57) -> 0.051332475 | ... K59: =ln(K57+K58)-ln(K57) -> 0.031887722
A60: Discounted increase in ln(consumption) | B60: =B59/(1+$B$9)^(B$12-2024) -> 0.56808367 | C60: =C59/(1+$B$9)^(C$12-2024) -> 0.19614024 | D60: =D59/(1+$B$9)^(D$12-2024) -> 0.15104699 | E60: =E59/(1+$B$9)^(E$12-2024) -> 0.11585659 | F60: =F59/(1+$B$9)^(F$12-2024) -> 0.088570642 | G60: =G59/(1+$B$9)^(G$12-2024) -> 0.067527078 | H60: =H59/(1+$B$9)^(H$12-2024) -> 0.051369573 | I60: =I59/(1+$B$9)^(I$12-2024) -> 0.039008462 | ... K60: =K59/(1+$B$9)^(K$12-2024) -> 0.02240389
A61: Discounted units of value | B61: =B60*$B$10 -> 0.8195715 | C61: =C60*$B$10 -> 0.28297055 | D61: =D60*$B$10 -> 0.21791475 | E61: =E60*$B$10 -> 0.16714573 | F61: =F60*$B$10 -> 0.12778043 | G61: =G60*$B$10 -> 0.097420981 | H61: =H60*$B$10 -> 0.074110629 | I61: =I60*$B$10 -> 0.056277315 | ... K61: =K60*$B$10 -> 0.032321981
A62: Total units of value given people reached | B62: =B61*$B$13 -> 3342.7147 | C62: =C61*$B$13 -> 1154.1273 | D62: =D61*$B$13 -> 888.78987 | E62: =E61*$B$13 -> 681.72272 | F62: =F61*$B$13 -> 521.16687 | G62: =G61*$B$13 -> 397.34245 | H62: =H61*$B$13 -> 302.26855 | I62: =I61*$B$13 -> 229.53337 | ... K62: =K61*$B$13 -> 131.82884
A63: Year 2-10 consumption gains (as % of year 1 consumption gains) | B63: =SUM(C62:K62)/B62 -> 1.3404766
A65: Uganda | B65: 2024 | C65: =B65+1 -> 2025 | D65: =C65+1 -> 2026 | E65: =D65+1 -> 2027 | F65: =E65+1 -> 2028 | G65: =F65+1 -> 2029 | H65: =G65+1 -> 2030 | I65: =H65+1 -> 2031 | J65: =I65+1 -> 2032 | K65: =J65+1 -> 2033
A66: Number of people reached | B66: ='New CEA'!F12 -> 3568.5864
A67: Transfer size per person | B67: ='New CEA'!F11 -> 589.31378
A68: Year 1 increase in consumption | B68: =B67*(1-F$4) -> 335.90885
A69: Amount invested/saved | B69: =B67-B68 -> 253.40492
A70: Baseline/counterfactual consumption | B70: ='New CEA'!F14 -> 625.55328 | C70: =B70*(1+$F$7) -> 638.06434 | D70: =C70*(1+$F$7) -> 650.82563 | E70: =D70*(1+$F$7) -> 663.84214 | F70: =E70*(1+$F$7) -> 677.11898 | G70: =F70*(1+$F$7) -> 690.66136 | H70: =G70*(1+$F$7) -> 704.47459 | I70: =H70*(1+$F$7) -> 718.56408 | J70: =I70*(1+$F$7) -> 732.93536 | K70: =J70*(1+$F$7) -> 747.59407
A71: Counterfactual increase in consumption | B71: =B68 -> 335.90885 | C71: =B69*$F$5 -> 101.36197 | D71: =C71*(1+$F$6) -> 81.089576 | E71: =D71*(1+$F$6) -> 64.871661 | F71: =E71*(1+$F$6) -> 51.897329 | G71: =F71*(1+$F$6) -> 41.517863 | H71: =G71*(1+$F$6) -> 33.21429 | I71: =H71*(1+$F$6) -> 26.571432 | J71: =I71*(1+$F$6) -> 21.257146 | K71: =J71*(1+$F$6) -> 17.005717
A72: Increase in ln(consumption) | B72: =ln(B70+B71)-ln(B70) -> 0.42981868 | C72: =ln(C70+C71)-ln(C70) -> 0.1474355 | D72: =ln(D70+D71)-ln(D70) -> 0.11742291 | E72: =ln(E70+E71)-ln(E70) -> 0.093236683 | F72: =ln(F70+F71)-ln(F70) -> 0.073849099 | G72: =ln(G70+G71)-ln(G70) -> 0.058375692 | H72: =ln(H70+H71)-ln(H70) -> 0.046069902 | I72: =ln(I70+I71)-ln(I70) -> 0.03631121 | ... K72: =ln(K70+K71)-ln(K70) -> 0.022492399
A73: Discounted increase in ln(consumption) | B73: =B72/(1+$B$9)^(B$12-2024) -> 0.42981868 | C73: =C72/(1+$B$9)^(C$12-2024) -> 0.14176491 | D73: =D72/(1+$B$9)^(D$12-2024) -> 0.10856408 | E73: =E72/(1+$B$9)^(E$12-2024) -> 0.082887072 | F73: =F72/(1+$B$9)^(F$12-2024) -> 0.063126519 | G73: =G72/(1+$B$9)^(G$12-2024) -> 0.047980564 | H73: =H72/(1+$B$9)^(H$12-2024) -> 0.036409713 | I73: =I72/(1+$B$9)^(I$12-2024) -> 0.027593535 | ... K73: =K72/(1+$B$9)^(K$12-2024) -> 0.015802861
A74: Discounted units of value | B74: =B73*$B$10 -> 0.62009728 | C74: =C73*$B$10 -> 0.20452353 | D74: =D73*$B$10 -> 0.15662486 | E74: =E73*$B$10 -> 0.11958077 | F74: =F73*$B$10 -> 0.091072317 | G74: =G73*$B$10 -> 0.069221322 | H74: =H73*$B$10 -> 0.052528112 | I74: =I73*$B$10 -> 0.039809057 | ... K74: =K73*$B$10 -> 0.022798709
A75: Total units of value given people reached | B75: =B74*$B$13 -> 2529.1366 | C75: =C74*$B$13 -> 834.17227 | D75: =D74*$B$13 -> 638.81216 | E75: =E74*$B$13 -> 487.72364 | F75: =F74*$B$13 -> 371.44871 | G75: =G74*$B$13 -> 282.32696 | H75: =H74*$B$13 -> 214.24182 | I75: =I74*$B$13 -> 162.36572 | ... K75: =K74*$B$13 -> 92.987105
A76: Year 2-10 consumption gains (as % of year 1 consumption gains) | B76: =SUM(C75:K75)/B75 -> 1.2680226
A78: Sense checks
A80: What do our assumptions imply about the marginal propensity to consume?
B81: Kenya | C81: Malawi | D81: Mozambique | E81: Rwanda | F81: Uganda
A82: Implied marginal propensity to consume (year 2) | B82: =SUM(B18:C18)/B14 -> 0.742 | C82: =SUM(B32:C32)/B28 -> 0.742 | D82: =SUM(B45:C45)/B41 -> 0.742 | E82: =SUM(B58:C58)/B54 -> 0.742 | F82: =SUM(B71:C71)/B67 -> 0.742
A84: How do our relative consumption gains compare to experimental estimates?
A85: Kenya | B85: Year 1 | C85: Year 2 | D85: Year 3 | E85: Year 4 | F85: Year 5 | G85: Year 6 | H85: Year 7 | I85: Year 8 | J85: Year 9 | K85: Year 10
A86: GiveWell estimates | B86: =B24 -> 0.42656023 | C86: =C24 -> 0.12619257 | D86: =D24 -> 0.098974565 | E86: =E24 -> 0.07762711 | F86: =F24 -> 0.060884007 | G86: =G24 -> 0.047752163 | H86: =H24 -> 0.037452677 | I86: =I24 -> 0.029374648 | ... K86: =K24 -> 0.018069757
A87: Egger et al. | C87: 0.13 | G87: 0.12
A88: Haushofer and Shapiro | B88: =36/157 -> 0.22929936 | D88: =17/187 -> 0.090909091
A89: Blattman et al. Uganda | E89: =21.6/201 -> 0.10746269 | J89: 0.01
A90: Blattman et al. Ethiopia | B90: 0.1 | F90: 0

Sheet GE
A1: What is this? This tab applies adjustments to the headline economic multiplier estimate from Egger et al.
A2: Accounting adjustment | C2: Notes
A3: Total transfer amount per person (denominator) | B3: =Consumption!$B$14 -> 487.89962
A4: Transfer multiplier | B4: 2.5 | C4: Egger et al. multiplier
A5: Implied economic activity generated (numerator) | B5: =B3*B4 -> 1219.7491 | C5: Implied
A6: Recipient consumption/investment returns by year 2 | B6: =SUM(Consumption!$B$18:$C$18) -> 362.02152 | C6: Calculated elsewhere in the model
A7: Implied accounting adjustment | B7: =(B5-B6)/B5 -> 0.7032
A9: Sense-check: what is our implied multiplier?
B10: Kenya | C10: Malawi | D10: Mozambique | E10: Rwanda | F10: Uganda | G10: Notes:
A11: Total transfer amount per person (denominator) | B11: ='New CEA'!B11 -> 487.89962 | C11: ='New CEA'!C11 -> 651.46361 | D11: ='New CEA'!D11 -> 639.08746 | E11: ='New CEA'!E11 -> 714.75028 | F11: ='New CEA'!F11 -> 589.31378
A12: Recipient consumption/investment returns by year 2 | B12: =SUM(Consumption!$B$18:$C$18) -> 362.02152 | C12: =SUM(Consumption!$B$32:$C$32) -> 483.386 | D12: =SUM(Consumption!$B$45:$C$45) -> 474.2029 | E12: =SUM(Consumption!$B$58:$C$58) -> 530.34471 | F12: =SUM(Consumption!$B$71:$C$71) -> 437.27082 | G12: Implied by my consumption assumptions
A13: Non-recipient consumption benefits (as % of recipient consumption benefits) | B13: ='New CEA'!B36 -> 0.675072 | C13: ='New CEA'!C36 -> 0.590688 | D13: ='New CEA'!D36 -> 0.590688 | E13: ='New CEA'!E36 -> 0.63288 | F13: ='New CEA'!F36 -> 0.63288
A14: Distributional adjustment | B14: ='New CEA'!B35 -> 0.8 | C14: ='New CEA'!C35 -> 0.8 | D14: ='New CEA'!D35 -> 0.8 | E14: ='New CEA'!E35 -> 0.8 | F14: ='New CEA'!F35 -> 0.8
A15: Non-recipient consumption/investment returns by year 2 | B15: =(B12*B13)/B14 -> 305.48824 | C15: =(C12*C13)/C14 -> 356.91289 | D15: =(D12*D13)/D14 -> 350.13245 | E15: =(E12*E13)/E14 -> 419.5557 | F15: =(F12*F13)/F14 -> 345.92495
A16: Recipient + non-recipient consumption & investment returns by year 2 (numerator) | B16: =B15+B12 -> 667.50976 | C16: =C15+C12 -> 840.29889 | D16: =D15+D12 -> 824.33535 | E16: =E15+E12 -> 949.90041 | F16: =F15+F12 -> 783.19577
A17: Implied multiplier | B17: =B16/B11 -> 1.3681293 | C17: =C16/C11 -> 1.2898631 | D17: =D16/D11 -> 1.2898631 | E17: =E16/E11 -> 1.3289962 | F17: =F16/F11 -> 1.3289962
A20: Sense-check: what do our assumptions imply about how we expect the multiplier to grow across time?
A21: Kenya | B21: Year 2 | C21: Year 3 | D21: Year 4 | E21: Year 5 | F21: Year 6 | G21: Year 7 | H21: Year 8 | I21: Year 9 | J21: Year 10
A22: Cumulative consumption gains of recipients | B22: =SUM(Consumption!$B18:C18) -> 362.02152 | C22: =SUM(Consumption!$B18:D18) -> 429.15651 | D22: =SUM(Consumption!$B18:E18) -> 482.8645 | E22: =SUM(Consumption!$B18:F18) -> 525.83089 | F22: =SUM(Consumption!$B18:G18) -> 560.204 | G22: =SUM(Consumption!$B18:H18) -> 587.7025 | H22: =SUM(Consumption!$B18:I18) -> 609.70129 | I22: =SUM(Consumption!$B18:J18) -> 627.30032 | J22: =SUM(Consumption!$B18:K18) -> 641.37955
A23: % increase from previous year | C23: =(C22-B22)/B22 -> 0.18544474 | D23: =(D22-C22)/C22 -> 0.12514779 | E23: =(E22-D22)/D22 -> 0.088982297 | F23: =(F22-E22)/E22 -> 0.065369141 | G23: =(G22-F22)/F22 -> 0.049086566 | H23: =(H22-G22)/G22 -> 0.037431852 | I23: =(I22-H22)/H22 -> 0.028865011 | J23: =(J22-I22)/I22 -> 0.022444158
A24: What this implies about by expected multiplier growth | B24: =B17 -> 1.3681293 | C24: =B24*(1+C23) -> 1.6218417 | D24: =C24*(1+D23) -> 1.8248116 | E24: =D24*(1+E23) -> 1.9871875 | F24: =E24*(1+F23) -> 2.1170882 | G24: =F24*(1+G23) -> 2.2210088 | H24: =G24*(1+H23) -> 2.3041453 | I24: =H24*(1+I23) -> 2.3706545 | J24: =I24*(1+J23) -> 2.4238618

Sheet Spillover
A1: What is this? This tab tries to reconstruct the Egger et al. multiplier from the bottom-up, given population census estimates and treatment effects estimated on recipients and non-recipients (Table 1)
A2: Transfer amount | B2: BOTEC | D2: Notes | E2: Source
A3: Recipient households | B3: 10500 | E3: "We provided one-time cash transfers of about USD 1000 to over 10,500 poor households across 653 randomized villages in rural Kenya", Egger et al. (2022)
A4: Size of transfer (PPP) | B4: 1871 | E4: "These households received a series of three transfers totaling KES 87,000, or USD 1871 PPP (USD 1000 nominal)"
A5: Total amount transferred | B5: =B3*B4 -> 19645500 | D5: Denominator of the multiplier
A6: Consumption multiplier
A7: Recipients
A8: Average effect on annual consumption, recipients (PPP) | B8: 338 | E8: Table 1, column 2
A9: Median timing of follow-up (months) | B9: 19 | E9: "The 5th/95th percentiles of timing ranged from 12 to 27 months, and the median survey was conducted 19 months after the experimental start month"
A10: Timing of follow-up (years, rounded) | B10: 2
A11: Average increase in consumption, recipient households | B11: =B10*B8 -> 676 | E11: "The increase in GDP is fairly stable over time; in fact, we cannot reject that the expenditure response is constant across all quarters (p-value of 0.53)", Egger et al. (2022), page 29
A12: Total increase in consumption, recipients | B12: =B11*B3 -> 7098000 | D12: Note: doesn't include asset expenditure
A13: Non-recipients
A14: Number of households in sampling frame | B14: 65000 | E14: "Our household and enterprise censuses of the study area count 65,383 households and 12,095 non-farm enterprises"
A15: % of households defined as nearby non-recipients | B15: 0.67 | E15: "We find that nonrecipient households account for 82% of the household contribution to the expenditure multiplier and 85% of the contribution to the income multiplier, both of which are somewhat higher than their share in the local population of 67%"
A16: Implied number of non-recipient households that were nearby recipient households | B16: =B14*B15 -> 43550
A17: Implied number of households that i) didn't receive transfers; ii) weren't nearby those that did (i.e. 'pure' controls) | B17: =B14-B3-B16 -> 10950
A18: Average effect on annual consumption, non-recipients (PPP) | B18: 334 | E18: Table 1, column 3
A19: Average increase in consumption, non-recipient households | B19: =B18*B10 -> 668 | D19: Assume same 2 year follow-up
A20: Total increase in consumption, non-recipients | B20: =B19*B16 -> 29091400
A22: Total increase in consumption among recipients + nearby non-recipients | B22: =B20+B12 -> 36189400
A23: Implied consumption multiplier | B23: =B22/B5 -> 1.8421216 | D23: Consumption multiplier in Egger et al. = 2.0. Roughly checks out
A25: Transfer amount that still needs to be 'explained' | B25: =B5-B12 -> 12547500 | D25: Remainder of the cash transfer that isn't yet accounted for
A26: Total increase in economic activity if we include this as investment expenditure (metal roofs, farming equipment, radios etc.) | B26: =B25+B22 -> 48736900 | D26: Assume all the transfer which isn't consumed goes towards investment
A27: Implied total economic multiplier | B27: =B26/B5 -> 2.4808175 | D27: Checks out
A29: Sense checks
B31: Bottom-up model | C31: Egger et al.
A32: Consumption gains to recipients | B32: =B12/$B$26 -> 0.14563914 | C32: =0.8*0.18 -> 0.144 | E32: "We find that nonrecipient households account for 82% of the household contribution to the expenditure multiplier and 85% of the contribution to the income multiplier, both of which are somewhat higher than their share in the local population of 67%" See Table 5 - consumption contributes ~2.0 of the 2.5 multiplier, implying a ~80% contribution
A33: Asset/investment gains to recipients | B33: =B25/$B$26 -> 0.2574538 | C33: 0.2
A34: Consumption gains to non-recipients | B34: =B20/$B$26 -> 0.59690707 | C34: =0.8*0.82 -> 0.656 | E34: "We find that nonrecipient households account for 82% of the household contribution to the expenditure multiplier and 85% of the contribution to the income multiplier, both of which are somewhat higher than their share in the local population of 67%" See Table 5 - consumption contributes ~2.0 of the 2.5 multiplier, implying a ~80% contribution

Sheet Mortality
A1: Sense checks
A2: How does the Egger et al. estimate triangulate with x-country correlations between u5 mortality and baseline consumption?
C3: Source
A4: u5 mortality rate during the trial | B4: 0.057 | C4: Egger et al. (2024), Table 1
A5: Reduction due to GD progam | B5: 0.45 | C5: "Unconditional cash transfers (accounting for spillovers) lead to 48% fewer infant deaths before age one and 45% fewer child deaths before age five", Walker et al. (2025), page 1
A6: Implied u5 mortality rate during GD program | B6: =B4*(1-B5) -> 0.03135
A8: Household consumption in control group in Egger et al. (PPP) | B8: 2536 | C8: Egger et al. (2022), Table 1
A9: Size of transfer per household (PPP) | B9: 1871 | C9: "These households received a series of three transfers totaling KES 87,000, or USD 1871 PPP (USD 1000 nominal)", Egger et al. (2022), page 2
A10: Average household size | B10: =Baseline!B4 -> 4.2
A11: Size of transfer per member (PPP) | B11: =B9/B10 -> 445.47619
A12: Marginal propensity to consume | B12: 0.76 | C12: "These estimates are broadly in line with what a simple model would imply from households’ marginal propensity to consume local value added, which we estimate to be approximately 0.76 over the study period", page 4
A13: Timing of follow-up (years) | B13: 1.5 | C13: "The 5th/95th percentiles of timing ranged from 12 to 27 months, and the median survey was conducted 19 months after the experimental start month", Egger et al. (2022), page 7
A14: Consumption per capita (non-recipients) | B14: =B8/B10 -> 603.80952
A15: Consumption per capita (recipients) | B15: =B14+(B11*B12)/B13 -> 829.51746
B17: Year consumption estimate pertains to | C17: Annual consumption per capita (2017 PPP) | D17: under-5 mortality rate (%)
A18: Egger et al - control | B18: 2015-17 | C18: =B14 -> 603.80952 | D18: =B4 -> 0.057
A19: Egger et al - recipients | B19: 2015-17 | C19: =B15 -> 829.51746 | D19: =B6 -> 0.03135 | E19: =(D23-D19)/D23 -> 0.32217975
A20: Burundi | B20: {=ROUND(INDEX(WB!$I$70:$I$114,MATCH($A20,WB!$C$70:$C$524,0)),0)} -> 2020 | C20: {=INDEX(WB!$R$70:$R$114,MATCH($A20,WB!$C$70:$C$524,0))*365} -> 854.58326 | D20: {=INDEX(UNICEF!$H$12:$R$211,MATCH($A20,UNICEF!$B$12:$B$211,0),MATCH($B20,UNICEF!$H$11:$R$11,0))/1000} -> 0.0542285
A21: Democratic Republic of the Congo | B21: {=ROUND(INDEX(WB!$I$70:$I$114,MATCH($A21,WB!$C$70:$C$524,0)),0)} -> 2020 | C21: {=INDEX(WB!$R$70:$R$114,MATCH($A21,WB!$C$70:$C$524,0))*365} -> 637.92547 | D21: {=INDEX(UNICEF!$H$12:$R$211,MATCH($A21,UNICEF!$B$12:$B$211,0),MATCH($B21,UNICEF!$H$11:$R$11,0))/1000} -> 0.0808046
A22: Ethiopia | B22: {=ROUND(INDEX(WB!$I$70:$I$114,MATCH($A22,WB!$C$70:$C$524,0)),0)} -> 2016 | C22: {=INDEX(WB!$R$70:$R$114,MATCH($A22,WB!$C$70:$C$524,0))*365} -> 1364.7299 | D22: {=INDEX(UNICEF!$H$12:$R$211,MATCH($A22,UNICEF!$B$12:$B$211,0),MATCH($B22,UNICEF!$H$11:$R$11,0))/1000} -> 0.0598782
A23: Kenya | B23: {=ROUND(INDEX(WB!$I$70:$I$114,MATCH($A23,WB!$C$70:$C$524,0)),0)} -> 2016 | C23: {=INDEX(WB!$R$70:$R$114,MATCH($A23,WB!$C$70:$C$524,0))*365} -> 1549.8305 | D23: {=INDEX(UNICEF!$H$12:$R$211,MATCH($A23,UNICEF!$B$12:$B$211,0),MATCH($B23,UNICEF!$H$11:$R$11,0))/1000} -> 0.0462512
A24: Lesotho | B24: {=ROUND(INDEX(WB!$I$70:$I$114,MATCH($A24,WB!$C$70:$C$524,0)),0)} -> 2017 | C24: {=INDEX(WB!$R$70:$R$114,MATCH($A24,WB!$C$70:$C$524,0))*365} -> 1694.8399 | D24: {=INDEX(UNICEF!$H$12:$R$211,MATCH($A24,UNICEF!$B$12:$B$211,0),MATCH($B24,UNICEF!$H$11:$R$11,0))/1000} -> 0.075958
A25: Madagascar | B25: {=ROUND(INDEX(WB!$I$70:$I$114,MATCH($A25,WB!$C$70:$C$524,0)),0)} -> 2013 | C25: {=INDEX(WB!$R$70:$R$114,MATCH($A25,WB!$C$70:$C$524,0))*365} -> 580.59199 | D25: {=INDEX(UNICEF!$H$12:$R$211,MATCH($A25,UNICEF!$B$12:$B$211,0),MATCH($B25,UNICEF!$H$11:$R$11,0))/1000} -> 0.0668041
A26: Mozambique | B26: {=ROUND(INDEX(WB!$I$70:$I$114,MATCH($A26,WB!$C$70:$C$524,0)),0)} -> 2020 | C26: {=INDEX(WB!$R$70:$R$114,MATCH($A26,WB!$C$70:$C$524,0))*365} -> 765.08453 | D26: {=INDEX(UNICEF!$H$12:$R$211,MATCH($A26,UNICEF!$B$12:$B$211,0),MATCH($B26,UNICEF!$H$11:$R$11,0))/1000} -> 0.0701006
A27: Malawi | B27: {=ROUND(INDEX(WB!$I$70:$I$114,MATCH($A27,WB!$C$70:$C$524,0)),0)} -> 2019 | C27: {=INDEX(WB!$R$70:$R$114,MATCH($A27,WB!$C$70:$C$524,0))*365} -> 755.3175 | D27: {=INDEX(UNICEF!$H$12:$R$211,MATCH($A27,UNICEF!$B$12:$B$211,0),MATCH($B27,UNICEF!$H$11:$R$11,0))/1000} -> 0.0454005
A28: Rwanda | B28: {=ROUND(INDEX(WB!$I$70:$I$114,MATCH($A28,WB!$C$70:$C$524,0)),0)} -> 2017 | C28: {=INDEX(WB!$R$70:$R$114,MATCH($A28,WB!$C$70:$C$524,0))*365} -> 1126.6805 | D28: {=INDEX(UNICEF!$H$12:$R$211,MATCH($A28,UNICEF!$B$12:$B$211,0),MATCH($B28,UNICEF!$H$11:$R$11,0))/1000} -> 0.0447029
A29: Tanzania | B29: {=ROUND(INDEX(WB!$I$70:$I$114,MATCH($A29,WB!$C$70:$C$524,0)),0)} -> 2018 | C29: {=INDEX(WB!$R$70:$R$114,MATCH($A29,WB!$C$70:$C$524,0))*365} -> 1202.5838 | D29: {=INDEX(UNICEF!$H$12:$R$211,MATCH($A29,UNICEF!$B$12:$B$211,0),MATCH($B29,UNICEF!$H$11:$R$11,0))/1000} -> 0.0478895
A30: Uganda | B30: {=ROUND(INDEX(WB!$I$70:$I$114,MATCH($A30,WB!$C$70:$C$524,0)),0)} -> 2017 | C30: {=INDEX(WB!$R$70:$R$114,MATCH($A30,WB!$C$70:$C$524,0))*365} -> 1290.8714 | D30: {=INDEX(UNICEF!$H$12:$R$211,MATCH($A30,UNICEF!$B$12:$B$211,0),MATCH($B30,UNICEF!$H$11:$R$11,0))/1000} -> 0.0500448
A31: Zambia | B31: {=ROUND(INDEX(WB!$I$70:$I$114,MATCH($A31,WB!$C$70:$C$524,0)),0)} -> 2015 | C31: {=INDEX(WB!$R$70:$R$114,MATCH($A31,WB!$C$70:$C$524,0))*365} -> 1085.6618 | D31: {=INDEX(UNICEF!$H$12:$R$211,MATCH($A31,UNICEF!$B$12:$B$211,0),MATCH($B31,UNICEF!$H$11:$R$11,0))/1000} -> 0.0680389
A32: Zimbabwe | B32: {=ROUND(INDEX(WB!$I$70:$I$114,MATCH($A32,WB!$C$70:$C$524,0)),0)} -> 2017 | C32: {=INDEX(WB!$R$70:$R$114,MATCH($A32,WB!$C$70:$C$524,0))*365} -> 1609.3598 | D32: {=INDEX(UNICEF!$H$12:$R$211,MATCH($A32,UNICEF!$B$12:$B$211,0),MATCH($B32,UNICEF!$H$11:$R$11,0))/1000} -> 0.0557896

Sheet Development
A1: What is this? Sense check of how development effects might contribute to CE given different treatment effects
B2: Kenya | C2: Malawi | D2: Mozambique | E2: Rwanda | F2: Uganda | G2: Notes
A3: Size of transfer
A4: Arbitrary donation (nominal USD) | B4: ='New CEA'!$B$4 -> 1000000 | C4: ='New CEA'!$B$4 -> 1000000 | D4: ='New CEA'!$B$4 -> 1000000 | E4: ='New CEA'!$B$4 -> 1000000 | F4: ='New CEA'!$B$4 -> 1000000
A5: Number of households receiving transfer | B5: ='New CEA'!B$7 -> 971.09827 | C5: ='New CEA'!C$7 -> 840 | D5: ='New CEA'!D$7 -> 750 | E5: ='New CEA'!E$7 -> 772.72727 | F5: ='New CEA'!F$7 -> 743.4555
A6: Average household size | B6: ='New CEA'!B10 -> 4.2 | C6: ='New CEA'!C10 -> 4.5 | D6: ='New CEA'!D10 -> 4.4 | E6: ='New CEA'!E10 -> 4.3 | F6: ='New CEA'!F10 -> 4.8
A7: Number of people directly targeted | B7: =B6*B5 -> 4078.6127 | C7: =C6*C5 -> 3780 | D7: =D6*D5 -> 3300 | E7: =E6*E5 -> 3322.7273 | F7: =F6*F5 -> 3568.5864
A8: u15 share of people targeted | B8: =SUM(Equivalence!B20:B22)/Equivalence!B41 -> 0.37811439 | C8: =SUM(Equivalence!C20:C22)/Equivalence!C41 -> 0.42592677 | D8: =SUM(Equivalence!D20:D22)/Equivalence!D41 -> 0.43291063 | E8: =SUM(Equivalence!E20:E22)/Equivalence!E41 -> 0.38066471 | F8: =SUM(Equivalence!F20:F22)/Equivalence!F41 -> 0.44781392
A9: Number of u15 children targeted | B9: =B8*B7 -> 1542.1822 | C9: =C8*C7 -> 1610.0032 | D9: =D8*D7 -> 1428.6051 | E9: =E8*E7 -> 1264.845 | F9: =F8*F7 -> 1598.0627
A10: Baseline annual consumption per capita (PPP 2017) | B10: ='New CEA'!B14 -> 651.96604 | C10: ='New CEA'!C14 -> 469.98486 | D10: ='New CEA'!D14 -> 449.78149 | E10: ='New CEA'!E14 -> 532.64139 | F10: ='New CEA'!F14 -> 625.55328
A11: Effect of exposure to GD program in childhood on adult earnings | B11: 0.02 | C11: 0.02 | D11: 0.02 | E11: 0.02 | F11: 0.02
A12: Annual increase in ln consumption in adulthood | B12: =ln(B10*(1+B11))-ln(B10) -> 0.019802627 | C12: =ln(C10*(1+C11))-ln(C10) -> 0.019802627 | D12: =ln(D10*(1+D11))-ln(D10) -> 0.019802627 | E12: =ln(E10*(1+E11))-ln(E10) -> 0.019802627 | F12: =ln(F10*(1+F11))-ln(F10) -> 0.019802627
A13: Years until benefits start to materialize | B13: 10 | C13: 10 | D13: 10 | E13: 10 | F13: 10
A14: Discount rate | B14: 0.04 | C14: 0.04 | D14: 0.04 | E14: 0.04 | F14: 0.04
A15: Benefit on one year's income, discounted | B15: =B12/(1+B14)^B13 -> 0.013377945 | C15: =C12/(1+C14)^C13 -> 0.013377945 | D15: =D12/(1+D14)^D13 -> 0.013377945 | E15: =E12/(1+E14)^E13 -> 0.013377945 | F15: =F12/(1+F14)^F13 -> 0.013377945
A16: Years of working life | B16: 40 | C16: 40 | D16: 40 | E16: 40 | F16: 40
A17: Present value of increase in adult ln consumption | B17: =pv(B14,B16,-B15) -> 0.26478665 | C17: =pv(C14,C16,-C15) -> 0.26478665 | D17: =pv(D14,D16,-D15) -> 0.26478665 | E17: =pv(E14,E16,-E15) -> 0.26478665 | F17: =pv(F14,F16,-F15) -> 0.26478665
A18: Multiplier for resource sharing within household | B18: 2 | C18: 2 | D18: 2 | E18: 2 | F18: 2
A19: Value assigned to increasing ln(consumption) by one unit for one person for one year | B19: 1.44 | C19: 1.44 | D19: 1.44 | E19: 1.44 | F19: 1.44
A20: Units of value from development benefits | B20: =B17*B18*B19*B9 -> 1176.0458 | C20: =C17*C18*C19*C9 -> 1227.7652 | D20: =D17*D18*D19*D9 -> 1089.4336 | E20: =E17*E18*E19*E9 -> 964.55253 | F20: =F17*F18*F19*F9 -> 1218.6595
A21: Units of value per $ | B21: =B20/B4 -> 0.0011760458 | C21: =C20/C4 -> 0.0012277652 | D21: =D20/D4 -> 0.0010894336 | E21: =E20/E4 -> 0.00096455253 | F21: =F20/F4 -> 0.0012186595
A22: Cost-effectiveness (x cash) | B22: =B21/0.003355 -> 0.35053527 | C22: =C21/0.003355 -> 0.36595087 | D22: =D21/0.003355 -> 0.3247194 | E22: =E21/0.003355 -> 0.28749703 | F22: =F21/0.003355 -> 0.36323681

Sheet RFMF
B1: Kenya | C1: Malawi | D1: Mozambique | E1: Rwanda | F1: Uganda
A2: Population estimate (million) | B2: =Equivalence!B41/1000000 -> 54.027475 | C2: =Equivalence!C41/1000000 -> 20.405306 | D2: =Equivalence!D41/1000000 -> 33.897345 | E2: =Equivalence!E41/1000000 -> 14.094674 | F2: =Equivalence!F41/1000000 -> 47.249574
A3: Average household size | B3: =Baseline!B4 -> 4.2 | C3: =Baseline!C4 -> 4.5 | D3: =Baseline!D4 -> 4.4 | E3: =Baseline!E4 -> 4.3 | F3: =Baseline!F4 -> 4.8
A4: Estimated number of households (million) | B4: =B2/B3 -> 12.863685 | C4: =C2/C3 -> 4.5345124 | D4: =D2/D3 -> 7.703942 | E4: =E2/E3 -> 3.2778312 | F4: =F2/F3 -> 9.8436613
A5: Poverty headcount rate (%) | B5: {=INDEX(WB!$N$70:$N$114,MATCH(B$1,WB!$C$70:$C$114,0))} -> 0.293651 | C5: {=INDEX(WB!$N$70:$N$114,MATCH(C$1,WB!$C$70:$C$114,0))} -> 0.700606 | D5: {=INDEX(WB!$N$70:$N$114,MATCH(D$1,WB!$C$70:$C$114,0))} -> 0.745284 | E5: {=INDEX(WB!$N$70:$N$114,MATCH(E$1,WB!$C$70:$C$114,0))} -> 0.520054 | F5: {=INDEX(WB!$N$70:$N$114,MATCH(F$1,WB!$C$70:$C$114,0))} -> 0.428616
A6: Estimated number of households living in extreme poverty (million) | B6: =B4*B5 -> 3.7774338 | C6: =C4*C5 -> 3.1769066 | D6: =D4*D5 -> 5.7416247 | E6: =E4*E5 -> 1.7046492 | F6: =F4*F5 -> 4.2191507
A7: Number of households that have received large one-off GD transfers | B7: =Country!B28 -> 122997 | C7: =Country!C28 -> 78579 | D7: =Country!D28 -> 5485 | E7: =Country!E28 -> 120393 | F7: =Country!F28 -> 78929
A8: Number of households that have received other types of GD transfers | B8: =406932-B7 -> 283935 | C8: =186900-C7 -> 108321 | E8: =221157-E7 -> 100764 | F8: =120520-F7 -> 41591
A9: Max % of households in extreme poverty that could have received a lump-sum GD transfer | B9: =B7/(B6*1000000) -> 0.032560994 | C9: =C7/(C6*1000000) -> 0.024734438 | D9: =D7/(D6*1000000) -> 0.00095530451 | E9: =E7/(E6*1000000) -> 0.070626261 | F9: =F7/(F6*1000000) -> 0.018707319
A10: Max % of households in extreme poverty that could have received any GD transfer | B10: =(B7+B8)/(B6*1000000) -> 0.1077271 | C10: =(C7+C8)/(C6*1000000) -> 0.058830813 | E10: =(E7+E8)/(E6*1000000) -> 0.12973754 | F10: =(F7+F8)/(F6*1000000) -> 0.028564991
A11: % of households in extreme poverty that have not received transfers | B11: =1-B9 -> 0.96743901 | C11: =1-C9 -> 0.97526556 | E11: =1-E9 -> 0.92937374 | F11: =1-F9 -> 0.98129268

Sheet Uncertainty
A1: Uncertainty
A2: Inputs | B2: Inputs for Monte Carlo simulations of our GiveDirectly model
A3: Sims | B3: Simulations of our GiveDirectly CEA based on the inputs in the previous tab

Sheet Inputs
A1: What is this? This tab specifies inputs for Monte Carlo simulations of our GiveDirectly model
B2: Distribution | C2: p5 | D2: p25 | E2: Kenya | F2: p75 | G2: p95
A3: Program reach
A4: Arbitrary donation (nominal USD) | E4: {=INDEX('New CEA'!$B4:$F4,MATCH($E$2,'New CEA'!B$2:F$2,0))} -> 1000000
A5: Transfers as a percentage of total cost | D5: =$E5-($E5*$H5) -> 0.7896 | E5: {=INDEX('New CEA'!$B6:$F6,MATCH($E$2,'New CEA'!B$2:F$2,0))} -> 0.84 | F5: =$E5+($E5*$H5) -> 0.8904 | H5: 0.06
A6: Total size of transfer per household (nominal USD) | E6: {=INDEX('New CEA'!$B5:$F5,MATCH($E$2,'New CEA'!B$2:F$2,0))} -> 865
A7: Number of households receiving transfer | E7: =(E4*E5)/E6 -> 971.09827
A8: Average household size | E8: {=INDEX('New CEA'!$B10:$F10,MATCH($E$2,'New CEA'!B$2:F$2,0))} -> 4.2
A9: Number of people reached | E9: =E8*E7 -> 4078.6127
A10: Consumption gains to recipients
A11: Baseline annual consumption per capita (PPP 2017) | B11: Uniform | D11: =$E11-($E11*$H11) -> 554.17113 | E11: {=INDEX('New CEA'!$B14:$F14,MATCH($E$2,'New CEA'!B$2:F$2,0))} -> 651.96604 | F11: =$E11+($E11*$H11) -> 749.76094 | H11: 0.15
A12: PPP adjustment (2017) | E12: {=INDEX('New CEA'!$B8:$F8,MATCH($E$2,'New CEA'!B$2:F$2,0))} -> 2.3689924
A13: Total size of transfer per household (PPP 2017) | E13: =E12*E6 -> 2049.1784
A14: Size of transfer per person (PPP 2017) | E14: =E13/E8 -> 487.89962
A15: Percentage of transfers invested | E15: {=INDEX('New CEA'!$B15:$F15,MATCH($E$2,'New CEA'!B$2:F$2,0))} -> 0.43
A16: Percentage of transfers consumed in year 1 | E16: =1-E15 -> 0.57
A17: Implied increase in consumption per person in year 1 | E17: =E16*E14 -> 278.10278
A18: Percentage increase in consumption over baseline | D18: =$E18-($E18*$H18) -> 0.3625762 | E18: =((E17+E11)/E11)-1 -> 0.42656023 | F18: =$E18+($E18*$H18) -> 0.49054427 | H18: 0.15
A19: Immediate increase in ln(consumption) per person | E19: =ln(1+E18)-ln(1) -> 0.35526612
A20: Value assigned to increasing ln(consumption) by one unit for one person for one year | B20: Uniform | D20: =$E20-($E20*$H20) -> 1.0820213 | E20: {=INDEX('New CEA'!$B20:$F20,MATCH($E$2,'New CEA'!B$2:F$2,0))} -> 1.442695 | F20: =$E20+($E20*$H20) -> 1.8033688 | H20: 0.25
A21: Units of value from year 1 consumption gains per person | E21: =E19*E20 -> 0.51254066
A22: Units of value from year 1 consumption gains given program reach | E22: =E21*E9 -> 2090.4549
A23: Value of year 2-10 consumption returns as % of year 1 consumption returns | B23: Uniform | D23: =$E23-($E23*$H23) -> 0.73827165 | E23: {=INDEX('New CEA'!$B23:$F23,MATCH($E$2,'New CEA'!B$2:F$2,0))} -> 1.2304527 | F23: =$E23+($E23*$H23) -> 1.7226338 | H23: 0.4
A24: Units of value from year 1-10 consumption gains | E24: =E22+(E22*E23) -> 4662.6608
A25: Distributional adjustment (accounting for consumption gains accruing to richer recipients) | E25: {=INDEX('New CEA'!$B25:$F25,MATCH($E$2,'New CEA'!B$2:F$2,0))} -> 0.9
A26: Units of value from year 1-10 consumption gains post adjustments | D26: =PERCENTILE(Sims!$G26:$SL26,0.25) -> 2839.1911 | E26: =E24*E25 -> 4196.3947 | F26: =PERCENTILE(Sims!$G26:$SL26,0.75) -> 5238.554
A27: Units of value from recipient consumption gains per $ donated | E27: =E26/E4 -> 0.0041963947
A28: Previous GiveDirectly cost-effectiveness estimate (units of value per $) | E28: {=INDEX('New CEA'!$B28:$F28,MATCH($E$2,'New CEA'!B$2:F$2,0))} -> 0.003355
A29: Initial CE from recipient consumption gains (x previous benchmark) | D29: =PERCENTILE(Sims!$G$29:$SL$29,0.25) -> 0.84625666 | E29: =E27/E28 -> 1.2507883 | F29: =PERCENTILE(Sims!$G$29:$SL$29,0.75) -> 1.561417
A30: Spillovers to non-recipients/general equilibrium effects
A31: Egger et al. economic multiplier | E31: {=INDEX('New CEA'!$B31:$F31,MATCH($E$2,'New CEA'!B$2:F$2,0))} -> 2.5
A32: Double-counting adjustment (stripping out recipient consumption gains) | E32: {=INDEX('New CEA'!$B32:$F32,MATCH($E$2,'New CEA'!B$2:F$2,0))} -> 0.7032
A33: IV adjustment (regressing Egger et al. towards prior) | B33: Uniform | D33: =$E33-($E33*$H33) -> 0.27 | E33: {=INDEX('New CEA'!$B33:$F33,MATCH($E$2,'New CEA'!B$2:F$2,0))} -> 0.6 | F33: =$E33+($E33*$H33) -> 0.93 | H33: 0.55
A34: EV adjustment (generalizing the multiplier to current program conditions) | B34: Uniform | D34: =$E34-($E34*$H34) -> 0.32 | E34: {=INDEX('New CEA'!$B34:$F34,MATCH($E$2,'New CEA'!B$2:F$2,0))} -> 0.8 | F34: =$E34+($E34*$H34) -> 1.28 | H34: 0.6
A35: Distributional adjustment (accounting for consumption spillovers accruing to richer non-recipients) | B35: Uniform | D35: =$E35-($E35*$H35) -> 0.6 | E35: {=INDEX('New CEA'!$B35:$F35,MATCH($E$2,'New CEA'!B$2:F$2,0))} -> 0.8 | F35: =$E35+($E35*$H35) -> 1 | H35: 0.25
A36: Spillover/general equilibrium benefits (as % of recipient consumption benefits), post adjustments | E36: =E31*E35*E32*E33*E34 -> 0.675072
A37: Units of value from non-recipient spillovers | D37: =PERCENTILE(Sims!$G37:$SL37,0.25) -> 384.87509 | E37: =E26*E36 -> 2832.8686 | F37: =PERCENTILE(Sims!$G37:$SL37,0.75) -> 4152.021
A38: Units of value from consumption gains and non-recipient spillovers | E38: =E26+E37 -> 7029.2633
A39: Initial CE from consumption gains and spillovers (x previous benchmark) | E39: =(E38/E4)/E28 -> 2.0951604
A40: Mortality benefits
A41: Share of u5s in targeted population | E41: {=INDEX('New CEA'!$B41:$F41,MATCH($E$2,'New CEA'!B$2:F$2,0))} -> 0.12879127
A42: Number of u5 children reached | E42: =E41*E9 -> 525.2897
A43: Average u5 mortality rate in each country (%) | E43: {=INDEX('New CEA'!$B43:$F43,MATCH($E$2,'New CEA'!B$2:F$2,0))} -> 0.0410984
A44: u5 mortality rate in Egger et al. (2015-2017) | E44: {=INDEX('New CEA'!$B44:$F44,MATCH($E$2,'New CEA'!B$2:F$2,0))} -> 0.057
A45: u5 mortality rate in UNICEF data (2016) | E45: {=INDEX('New CEA'!$B45:$F45,MATCH($E$2,'New CEA'!B$2:F$2,0))} -> 0.0462512
A46: Adjustment for GD u5 population being at higher risk | E46: =E44/E45 -> 1.2324005
A47: u5 morality rate in GD target population | E47: =E43*E46 -> 0.050649687
A48: % reduction in under 5 mortality due to transfer, unadjusted | E48: {=INDEX('New CEA'!$B48:$F48,MATCH($E$2,'New CEA'!B$2:F$2,0))} -> 0.45
A49: IV adjustment | B49: Uniform | D49: =$E49-($E49*$H49) -> 0.25 | E49: {=INDEX('New CEA'!$B49:$F49,MATCH($E$2,'New CEA'!B$2:F$2,0))} -> 0.5 | F49: =$E49+($E49*$H49) -> 0.75 | H49: 0.5
A50: % reduction in under 5 mortality among recipient households, adjusted | E50: =E48*E49 -> 0.225
A51: u5 deaths averted among recipient households | E51: =E42*E47*E50 -> 5.9862958
A52: Value assigned to averting an under-5 death | E52: {=INDEX('New CEA'!$B52:$F52,MATCH($E$2,'New CEA'!B$2:F$2,0))} -> 116
A53: Units of value from child mortality benefits | E53: =E51*E52 -> 694.41031
A54: Adult mortality benefits (as % of child mortality benefits) | E54: {=INDEX('New CEA'!$B54:$F54,MATCH($E$2,'New CEA'!B$2:F$2,0))} -> 0.5
A55: Units of value from child and adult mortality benefits | D55: =PERCENTILE(Sims!$G55:$SL55,0.25) -> 510.9122 | E55: =E53+(E53*E54) -> 1041.6155 | F55: =PERCENTILE(Sims!$G55:$SL55,0.75) -> 1535.4005
A56: Units of value from consumption and mortality benefits | E56: =E55+E38 -> 8070.8788
A57: Initial CE from consumption and child mortality (x previous benchmark) | E57: =(E56/E4)/E28 -> 2.4056271
A58: Supplementary adjustments
A59: Reduced morbidity | E59: {=INDEX('New CEA'!$B59:$F59,MATCH($E$2,'New CEA'!B$2:F$2,0))} -> 0.1
A60: Developmental effects | E60: {=INDEX('New CEA'!$B60:$F60,MATCH($E$2,'New CEA'!B$2:F$2,0))} -> 0.05
A61: Leverage & funging | E61: {=INDEX('New CEA'!$B61:$F61,MATCH($E$2,'New CEA'!B$2:F$2,0))} -> 0.02
A62: Risk of wastage/fraud | E62: {=INDEX('New CEA'!$B62:$F62,MATCH($E$2,'New CEA'!B$2:F$2,0))} -> -0.02
A63: Within-org fungibility | E63: {=INDEX('New CEA'!$B63:$F63,MATCH($E$2,'New CEA'!B$2:F$2,0))} -> -0.05
A64: Psychological spillovers | E64: {=INDEX('New CEA'!$B64:$F64,MATCH($E$2,'New CEA'!B$2:F$2,0))} -> -0.02
A65: Total adjustment factor | E65: =1+SUM(E59:E64) -> 1.08
A66: Disaggregated cost-effectiveness estimate (x cash) | C66: =PERCENTILE(Sims!$G$66:$SL$66,0.05) -> 1.0091742 | D66: =PERCENTILE(Sims!$G$66:$SL$66,0.25) -> 1.6056502 | E66: =E57*E65 -> 2.5980772 | F66: =PERCENTILE(Sims!$G$66:$SL$66,0.75) -> 3.2427921 | G66: =PERCENTILE(Sims!$G$66:$SL$66,0.95) -> 5.3199624

Sheet Sims
A1: What is this? This tab runs simulations of our GiveDirectly CEA based on the inputs in the previous tab | C1: Avg check | D1: p25 check | E1: p75 check
B2: =Inputs!E2 -> Kenya
A3: Program reach | F3: Sims >> | G3: 1 | H3: =G3+1 -> 2 | I3: =H3+1 -> 3 | J3: =I3+1 -> 4 | K3: =J3+1 -> 5 | L3: =K3+1 -> 6 | M3: =L3+1 -> 7 | N3: =M3+1 -> 8 | O3: =N3+1 -> 9 | ... SL3: =SK3+1 -> 500
A4: Arbitrary donation (nominal USD) | B4: =Inputs!E4 -> 1000000 | G4: =$B4 -> 1000000 | H4: =$B4 -> 1000000 | I4: =$B4 -> 1000000 | J4: =$B4 -> 1000000 | K4: =$B4 -> 1000000 | L4: =$B4 -> 1000000 | M4: =$B4 -> 1000000 | N4: =$B4 -> 1000000 | ... SL4: =$B4 -> 1000000
A5: Transfers as a percentage of total cost | B5: =Inputs!E5 -> 0.84 | C5: =AVERAGE(G5:SL5) -> 0.8355826 | D5: =PERCENTILE($G5:$SL5,0.25) -> 0.779675 | E5: =PERCENTILE($G5:$SL5,0.75) -> 0.889475 | G5: =RANDBETWEEN((Inputs!$E5-(Inputs!$E5-Inputs!$D5)*2)*10000,(Inputs!$E5+(Inputs!$F5-Inputs!$E5)*2)*10000)/10000 -> 0.8734 | H5: =RANDBETWEEN((Inputs!$E5-(Inputs!$E5-Inputs!$D5)*2)*10000,(Inputs!$E5+(Inputs!$F5-Inputs!$E5)*2)*10000)/10000 -> 0.9314 | I5: =RANDBETWEEN((Inputs!$E5-(Inputs!$E5-Inputs!$D5)*2)*10000,(Inputs!$E5+(Inputs!$F5-Inputs!$E5)*2)*10000)/10000 -> 0.857 | J5: =RANDBETWEEN((Inputs!$E5-(Inputs!$E5-Inputs!$D5)*2)*10000,(Inputs!$E5+(Inputs!$F5-Inputs!$E5)*2)*10000)/10000 -> 0.7686 | K5: =RANDBETWEEN((Inputs!$E5-(Inputs!$E5-Inputs!$D5)*2)*10000,(Inputs!$E5+(Inputs!$F5-Inputs!$E5)*2)*10000)/10000 -> 0.7801 | L5: =RANDBETWEEN((Inputs!$E5-(Inputs!$E5-Inputs!$D5)*2)*10000,(Inputs!$E5+(Inputs!$F5-Inputs!$E5)*2)*10000)/10000 -> 0.7534 | M5: =RANDBETWEEN((Inputs!$E5-(Inputs!$E5-Inputs!$D5)*2)*10000,(Inputs!$E5+(Inputs!$F5-Inputs!$E5)*2)*10000)/10000 -> 0.835 | N5: =RANDBETWEEN((Inputs!$E5-(Inputs!$E5-Inputs!$D5)*2)*10000,(Inputs!$E5+(Inputs!$F5-Inputs!$E5)*2)*10000)/10000 -> 0.9179 | ... SL5: =RANDBETWEEN((Inputs!$E5-(Inputs!$E5-Inputs!$D5)*2)*10000,(Inputs!$E5+(Inputs!$F5-Inputs!$E5)*2)*10000)/10000 -> 0.8834
A6: Total size of transfer per household (nominal USD) | B6: =Inputs!E6 -> 865 | G6: =$B6 -> 865 | H6: =$B6 -> 865 | I6: =$B6 -> 865 | J6: =$B6 -> 865 | K6: =$B6 -> 865 | L6: =$B6 -> 865 | M6: =$B6 -> 865 | N6: =$B6 -> 865 | ... SL6: =$B6 -> 865
A7: Number of households receiving transfer | B7: =(B4*B5)/B6 -> 971.09827 | G7: =(G4*G5)/G6 -> 1009.711 | H7: =(H4*H5)/H6 -> 1076.763 | I7: =(I4*I5)/I6 -> 990.75145 | J7: =(J4*J5)/J6 -> 888.55491 | K7: =(K4*K5)/K6 -> 901.84971 | L7: =(L4*L5)/L6 -> 870.98266 | M7: =(M4*M5)/M6 -> 965.31792 | N7: =(N4*N5)/N6 -> 1061.1561 | ... SL7: =(SL4*SL5)/SL6 -> 1021.2717
A8: Average household size | B8: =Inputs!E8 -> 4.2 | G8: =$B8 -> 4.2 | H8: =$B8 -> 4.2 | I8: =$B8 -> 4.2 | J8: =$B8 -> 4.2 | K8: =$B8 -> 4.2 | L8: =$B8 -> 4.2 | M8: =$B8 -> 4.2 | N8: =$B8 -> 4.2 | ... SL8: =$B8 -> 4.2
A9: Number of people reached | B9: =B8*B7 -> 4078.6127 | G9: =G8*G7 -> 4240.7861 | H9: =H8*H7 -> 4522.4046 | I9: =I8*I7 -> 4161.1561 | J9: =J8*J7 -> 3731.9306 | K9: =K8*K7 -> 3787.7688 | L9: =L8*L7 -> 3658.1272 | M9: =M8*M7 -> 4054.3353 | N9: =N8*N7 -> 4456.8555 | ... SL9: =SL8*SL7 -> 4289.341
A10: Consumption gains to recipients
A11: Baseline annual consumption per capita (PPP 2017) | B11: {=INDEX('New CEA'!$B14:$F14,MATCH($B$2,'New CEA'!B$2:F$2,0))} -> 651.96604 | C11: =AVERAGE(G11:SL11) -> 653.73655 | D11: =PERCENTILE($G11:$SL11,0.25) -> 554.05618 | E11: =PERCENTILE($G11:$SL11,0.75) -> 750.06737 | G11: =RANDBETWEEN((Inputs!$E11-(Inputs!$E11-Inputs!$D11)*2)*10000,(Inputs!$E11+(Inputs!$F11-Inputs!$E11)*2)*10000)/10000 -> 817.9051 | H11: =RANDBETWEEN((Inputs!$E11-(Inputs!$E11-Inputs!$D11)*2)*10000,(Inputs!$E11+(Inputs!$F11-Inputs!$E11)*2)*10000)/10000 -> 793.049 | I11: =RANDBETWEEN((Inputs!$E11-(Inputs!$E11-Inputs!$D11)*2)*10000,(Inputs!$E11+(Inputs!$F11-Inputs!$E11)*2)*10000)/10000 -> 697.8467 | J11: =RANDBETWEEN((Inputs!$E11-(Inputs!$E11-Inputs!$D11)*2)*10000,(Inputs!$E11+(Inputs!$F11-Inputs!$E11)*2)*10000)/10000 -> 488.0784 | K11: =RANDBETWEEN((Inputs!$E11-(Inputs!$E11-Inputs!$D11)*2)*10000,(Inputs!$E11+(Inputs!$F11-Inputs!$E11)*2)*10000)/10000 -> 819.7316 | L11: =RANDBETWEEN((Inputs!$E11-(Inputs!$E11-Inputs!$D11)*2)*10000,(Inputs!$E11+(Inputs!$F11-Inputs!$E11)*2)*10000)/10000 -> 609.1298 | M11: =RANDBETWEEN((Inputs!$E11-(Inputs!$E11-Inputs!$D11)*2)*10000,(Inputs!$E11+(Inputs!$F11-Inputs!$E11)*2)*10000)/10000 -> 484.7656 | N11: =RANDBETWEEN((Inputs!$E11-(Inputs!$E11-Inputs!$D11)*2)*10000,(Inputs!$E11+(Inputs!$F11-Inputs!$E11)*2)*10000)/10000 -> 604.9603 | ... SL11: =RANDBETWEEN((Inputs!$E11-(Inputs!$E11-Inputs!$D11)*2)*10000,(Inputs!$E11+(Inputs!$F11-Inputs!$E11)*2)*10000)/10000 -> 720.3762
A12: PPP adjustment (2017) | B12: {=INDEX('New CEA'!$B8:$F8,MATCH($B$2,'New CEA'!B$2:F$2,0))} -> 2.3689924 | G12: =$B12 -> 2.3689924 | H12: =$B12 -> 2.3689924 | I12: =$B12 -> 2.3689924 | J12: =$B12 -> 2.3689924 | K12: =$B12 -> 2.3689924 | L12: =$B12 -> 2.3689924 | M12: =$B12 -> 2.3689924 | N12: =$B12 -> 2.3689924 | ... SL12: =$B12 -> 2.3689924
A13: Total size of transfer per household (PPP 2017) | B13: =B12*B6 -> 2049.1784 | G13: =G12*G6 -> 2049.1784 | H13: =H12*H6 -> 2049.1784 | I13: =I12*I6 -> 2049.1784 | J13: =J12*J6 -> 2049.1784 | K13: =K12*K6 -> 2049.1784 | L13: =L12*L6 -> 2049.1784 | M13: =M12*M6 -> 2049.1784 | N13: =N12*N6 -> 2049.1784 | ... SL13: =SL12*SL6 -> 2049.1784
A14: Size of transfer per person (PPP 2017) | B14: =B13/B8 -> 487.89962 | G14: =G13/G8 -> 487.89962 | H14: =H13/H8 -> 487.89962 | I14: =I13/I8 -> 487.89962 | J14: =J13/J8 -> 487.89962 | K14: =K13/K8 -> 487.89962 | L14: =L13/L8 -> 487.89962 | M14: =M13/M8 -> 487.89962 | N14: =N13/N8 -> 487.89962 | ... SL14: =SL13/SL8 -> 487.89962
A15: Percentage of transfers invested | B15: {=INDEX('New CEA'!$B15:$F15,MATCH($B$2,'New CEA'!B$2:F$2,0))} -> 0.43 | G15: =$B15 -> 0.43 | H15: =$B15 -> 0.43 | I15: =$B15 -> 0.43 | J15: =$B15 -> 0.43 | K15: =$B15 -> 0.43 | L15: =$B15 -> 0.43 | M15: =$B15 -> 0.43 | N15: =$B15 -> 0.43 | ... SL15: =$B15 -> 0.43
A16: Percentage of transfers consumed in year 1 | B16: =1-B15 -> 0.57 | G16: =1-G15 -> 0.57 | H16: =1-H15 -> 0.57 | I16: =1-I15 -> 0.57 | J16: =1-J15 -> 0.57 | K16: =1-K15 -> 0.57 | L16: =1-L15 -> 0.57 | M16: =1-M15 -> 0.57 | N16: =1-N15 -> 0.57 | ... SL16: =1-SL15 -> 0.57
A17: Implied increase in consumption per person in year 1 | B17: =B16*B14 -> 278.10278 | G17: =G16*G14 -> 278.10278 | H17: =H16*H14 -> 278.10278 | I17: =I16*I14 -> 278.10278 | J17: =J16*J14 -> 278.10278 | K17: =K16*K14 -> 278.10278 | L17: =L16*L14 -> 278.10278 | M17: =M16*M14 -> 278.10278 | N17: =N16*N14 -> 278.10278 | ... SL17: =SL16*SL14 -> 278.10278
A18: Percentage increase in consumption over baseline | B18: =((B17+B11)/B11)-1 -> 0.42656023 | G18: =((G17+G11)/G11)-1 -> 0.3400184 | H18: =((H17+H11)/H11)-1 -> 0.35067541 | I18: =((I17+I11)/I11)-1 -> 0.39851558 | J18: =((J17+J11)/J11)-1 -> 0.56979121 | K18: =((K17+K11)/K11)-1 -> 0.33926078 | L18: =((L17+L11)/L11)-1 -> 0.45655751 | M18: =((M17+M11)/M11)-1 -> 0.57368506 | N18: =((N17+N11)/N11)-1 -> 0.45970419 | ... SL18: =((SL17+SL11)/SL11)-1 -> 0.38605216
A19: Immediate increase in ln(consumption) per person | B19: =ln(1+B18)-ln(1) -> 0.35526612 | G19: =ln(1+G18)-ln(1) -> 0.29268335 | H19: =ln(1+H18)-ln(1) -> 0.30060477 | I19: =ln(1+I18)-ln(1) -> 0.33541138 | J19: =ln(1+J18)-ln(1) -> 0.45094263 | K19: =ln(1+K18)-ln(1) -> 0.29211781 | L19: =ln(1+L18)-ln(1) -> 0.37607578 | M19: =ln(1+M18)-ln(1) -> 0.45342004 | N19: =ln(1+N18)-ln(1) -> 0.37823381 | ... SL19: =ln(1+SL18)-ln(1) -> 0.32645953
A20: Value assigned to increasing ln(consumption) by one unit for one person for one year | B20: {=INDEX('New CEA'!$B20:$F20,MATCH($B$2,'New CEA'!B$2:F$2,0))} -> 1.442695 | C20: =AVERAGE(G20:SL20) -> 1.4317102 | D20: =PERCENTILE($G20:$SL20,0.25) -> 1.062425 | E20: =PERCENTILE($G20:$SL20,0.75) -> 1.808775 | G20: =RANDBETWEEN((Inputs!$E20-(Inputs!$E20-Inputs!$D20)*2)*10000,(Inputs!$E20+(Inputs!$F20-Inputs!$E20)*2)*10000)/10000 -> 1.0819 | H20: =RANDBETWEEN((Inputs!$E20-(Inputs!$E20-Inputs!$D20)*2)*10000,(Inputs!$E20+(Inputs!$F20-Inputs!$E20)*2)*10000)/10000 -> 1.3141 | I20: =RANDBETWEEN((Inputs!$E20-(Inputs!$E20-Inputs!$D20)*2)*10000,(Inputs!$E20+(Inputs!$F20-Inputs!$E20)*2)*10000)/10000 -> 1.3866 | J20: =RANDBETWEEN((Inputs!$E20-(Inputs!$E20-Inputs!$D20)*2)*10000,(Inputs!$E20+(Inputs!$F20-Inputs!$E20)*2)*10000)/10000 -> 1.7509 | K20: =RANDBETWEEN((Inputs!$E20-(Inputs!$E20-Inputs!$D20)*2)*10000,(Inputs!$E20+(Inputs!$F20-Inputs!$E20)*2)*10000)/10000 -> 1.2413 | L20: =RANDBETWEEN((Inputs!$E20-(Inputs!$E20-Inputs!$D20)*2)*10000,(Inputs!$E20+(Inputs!$F20-Inputs!$E20)*2)*10000)/10000 -> 1.9923 | M20: =RANDBETWEEN((Inputs!$E20-(Inputs!$E20-Inputs!$D20)*2)*10000,(Inputs!$E20+(Inputs!$F20-Inputs!$E20)*2)*10000)/10000 -> 1.4653 | N20: =RANDBETWEEN((Inputs!$E20-(Inputs!$E20-Inputs!$D20)*2)*10000,(Inputs!$E20+(Inputs!$F20-Inputs!$E20)*2)*10000)/10000 -> 1.5902 | ... SL20: =RANDBETWEEN((Inputs!$E20-(Inputs!$E20-Inputs!$D20)*2)*10000,(Inputs!$E20+(Inputs!$F20-Inputs!$E20)*2)*10000)/10000 -> 0.9296
A21: Units of value from year 1 consumption gains per person | B21: =B19*B20 -> 0.51254066 | G21: =G19*G20 -> 0.31665411 | H21: =H19*H20 -> 0.39502473 | I21: =I19*I20 -> 0.46508141 | J21: =J19*J20 -> 0.78955544 | K21: =K19*K20 -> 0.36260583 | L21: =L19*L20 -> 0.74925578 | M21: =M19*M20 -> 0.66439639 | N21: =N19*N20 -> 0.6014674 | ... SL21: =SL19*SL20 -> 0.30347678
A22: Units of value from year 1 consumption gains given program reach | B22: =B21*B9 -> 2090.4549 | G22: =G21*G9 -> 1342.8624 | H22: =H21*H9 -> 1786.4617 | I22: =I21*I9 -> 1935.2764 | J22: =J21*J9 -> 2946.5662 | K22: =K21*K9 -> 1373.4671 | L22: =L21*L9 -> 2740.8729 | M22: =M21*M9 -> 2693.6857 | N22: =N21*N9 -> 2680.6533 | ... SL22: =SL21*SL9 -> 1301.7154
A23: Value of year 2-10 consumption returns as % of year 1 consumption returns | B23: {=INDEX('New CEA'!$B23:$F23,MATCH($B$2,'New CEA'!B$2:F$2,0))} -> 1.2304527 | C23: =AVERAGE(G23:SL23) -> 1.2266436 | D23: =PERCENTILE($G23:$SL23,0.25) -> 0.760075 | E23: =PERCENTILE($G23:$SL23,0.75) -> 1.694075 | G23: =RANDBETWEEN((Inputs!$E23-(Inputs!$E23-Inputs!$D23)*2)*10000,(Inputs!$E23+(Inputs!$F23-Inputs!$E23)*2)*10000)/10000 -> 2.0174 | H23: =RANDBETWEEN((Inputs!$E23-(Inputs!$E23-Inputs!$D23)*2)*10000,(Inputs!$E23+(Inputs!$F23-Inputs!$E23)*2)*10000)/10000 -> 0.79 | I23: =RANDBETWEEN((Inputs!$E23-(Inputs!$E23-Inputs!$D23)*2)*10000,(Inputs!$E23+(Inputs!$F23-Inputs!$E23)*2)*10000)/10000 -> 0.6015 | J23: =RANDBETWEEN((Inputs!$E23-(Inputs!$E23-Inputs!$D23)*2)*10000,(Inputs!$E23+(Inputs!$F23-Inputs!$E23)*2)*10000)/10000 -> 1.3924 | K23: =RANDBETWEEN((Inputs!$E23-(Inputs!$E23-Inputs!$D23)*2)*10000,(Inputs!$E23+(Inputs!$F23-Inputs!$E23)*2)*10000)/10000 -> 1.6309 | L23: =RANDBETWEEN((Inputs!$E23-(Inputs!$E23-Inputs!$D23)*2)*10000,(Inputs!$E23+(Inputs!$F23-Inputs!$E23)*2)*10000)/10000 -> 0.3069 | M23: =RANDBETWEEN((Inputs!$E23-(Inputs!$E23-Inputs!$D23)*2)*10000,(Inputs!$E23+(Inputs!$F23-Inputs!$E23)*2)*10000)/10000 -> 0.948 | N23: =RANDBETWEEN((Inputs!$E23-(Inputs!$E23-Inputs!$D23)*2)*10000,(Inputs!$E23+(Inputs!$F23-Inputs!$E23)*2)*10000)/10000 -> 1.694 | ... SL23: =RANDBETWEEN((Inputs!$E23-(Inputs!$E23-Inputs!$D23)*2)*10000,(Inputs!$E23+(Inputs!$F23-Inputs!$E23)*2)*10000)/10000 -> 0.7082
A24: Units of value from year 1-10 consumption gains | B24: =B22+(B22*B23) -> 4662.6608 | G24: =G22+(G22*G23) -> 4051.9529 | H24: =H22+(H22*H23) -> 3197.7664 | I24: =I22+(I22*I23) -> 3099.3451 | J24: =J22+(J22*J23) -> 7049.3649 | K24: =K22+(K22*K23) -> 3613.4545 | L24: =L22+(L22*L23) -> 3582.0468 | M24: =M22+(M22*M23) -> 5247.2998 | N24: =N22+(N22*N23) -> 7221.6799 | ... SL24: =SL22+(SL22*SL23) -> 2223.5903
A25: Distributional adjustment (accounting for consumption gains accruing to richer recipients) | B25: {=INDEX('New CEA'!$B25:$F25,MATCH($B$2,'New CEA'!B$2:F$2,0))} -> 0.9 | G25: =$B25 -> 0.9 | H25: =$B25 -> 0.9 | I25: =$B25 -> 0.9 | J25: =$B25 -> 0.9 | K25: =$B25 -> 0.9 | L25: =$B25 -> 0.9 | M25: =$B25 -> 0.9 | N25: =$B25 -> 0.9 | ... SL25: =$B25 -> 0.9
A26: Units of value from year 1-10 consumption gains post adjustments | B26: =B24*B25 -> 4196.3947 | G26: =G24*G25 -> 3646.7576 | H26: =H24*H25 -> 2877.9898 | I26: =I24*I25 -> 2789.4106 | J26: =J24*J25 -> 6344.4284 | K26: =K24*K25 -> 3252.109 | L26: =L24*L25 -> 3223.8421 | M26: =M24*M25 -> 4722.5698 | N26: =N24*N25 -> 6499.5119 | ... SL26: =SL24*SL25 -> 2001.2312
A27: Units of value from recipient consumption gains per $ donated | B27: =B26/B4 -> 0.0041963947 | G27: =G26/G4 -> 0.0036467576 | H27: =H26/H4 -> 0.0028779898 | I27: =I26/I4 -> 0.0027894106 | J27: =J26/J4 -> 0.0063444284 | K27: =K26/K4 -> 0.003252109 | L27: =L26/L4 -> 0.0032238421 | M27: =M26/M4 -> 0.0047225698 | N27: =N26/N4 -> 0.0064995119 | ... SL27: =SL26/SL4 -> 0.0020012312
A28: Previous GiveDirectly cost-effectiveness estimate (units of value per $) | B28: {=INDEX('New CEA'!$B28:$F28,MATCH($B$2,'New CEA'!B$2:F$2,0))} -> 0.003355 | G28: =$B28 -> 0.003355 | H28: =$B28 -> 0.003355 | I28: =$B28 -> 0.003355 | J28: =$B28 -> 0.003355 | K28: =$B28 -> 0.003355 | L28: =$B28 -> 0.003355 | M28: =$B28 -> 0.003355 | N28: =$B28 -> 0.003355 | ... SL28: =$B28 -> 0.003355
A29: Initial CE from recipient consumption gains (x previous benchmark) | B29: =B27/B28 -> 1.2507883 | G29: =G27/G28 -> 1.086962 | H29: =H27/H28 -> 0.85782109 | I29: =I27/I28 -> 0.83141895 | J29: =J27/J28 -> 1.8910368 | K29: =K27/K28 -> 0.96933205 | L29: =L27/L28 -> 0.96090675 | M29: =M27/M28 -> 1.4076214 | N29: =N27/N28 -> 1.9372614 | ... SL29: =SL27/SL28 -> 0.59649217
A30: Spillovers to non-recipients/general equilibrium effects
A31: Egger et al. economic multiplier | B31: {=INDEX('New CEA'!$B31:$F31,MATCH($B$2,'New CEA'!B$2:F$2,0))} -> 2.5 | G31: =$B31 -> 2.5 | H31: =$B31 -> 2.5 | I31: =$B31 -> 2.5 | J31: =$B31 -> 2.5 | K31: =$B31 -> 2.5 | L31: =$B31 -> 2.5 | M31: =$B31 -> 2.5 | N31: =$B31 -> 2.5 | ... SL31: =$B31 -> 2.5
A32: Double-counting adjustment (stripping out recipient consumption gains) | B32: {=INDEX('New CEA'!$B32:$F32,MATCH($B$2,'New CEA'!B$2:F$2,0))} -> 0.7032 | G32: =$B32 -> 0.7032 | H32: =$B32 -> 0.7032 | I32: =$B32 -> 0.7032 | J32: =$B32 -> 0.7032 | K32: =$B32 -> 0.7032 | L32: =$B32 -> 0.7032 | M32: =$B32 -> 0.7032 | N32: =$B32 -> 0.7032 | ... SL32: =$B32 -> 0.7032
A33: IV adjustment (regressing Egger et al. towards prior) | B33: {=INDEX('New CEA'!$B33:$F33,MATCH($B$2,'New CEA'!B$2:F$2,0))} -> 0.6 | C33: =AVERAGE(G33:SL33) -> 0.5980524 | D33: =PERCENTILE($G33:$SL33,0.25) -> 0.2747 | E33: =PERCENTILE($G33:$SL33,0.75) -> 0.931175 | G33: =RANDBETWEEN((Inputs!$E33-(Inputs!$E33-Inputs!$D33)*2)*10000,(Inputs!$E33+(Inputs!$F33-Inputs!$E33)*2)*10000)/10000 -> 0.6768 | H33: =RANDBETWEEN((Inputs!$E33-(Inputs!$E33-Inputs!$D33)*2)*10000,(Inputs!$E33+(Inputs!$F33-Inputs!$E33)*2)*10000)/10000 -> 0.5306 | I33: =RANDBETWEEN((Inputs!$E33-(Inputs!$E33-Inputs!$D33)*2)*10000,(Inputs!$E33+(Inputs!$F33-Inputs!$E33)*2)*10000)/10000 -> 0.9623 | J33: =RANDBETWEEN((Inputs!$E33-(Inputs!$E33-Inputs!$D33)*2)*10000,(Inputs!$E33+(Inputs!$F33-Inputs!$E33)*2)*10000)/10000 -> 0.4947 | K33: =RANDBETWEEN((Inputs!$E33-(Inputs!$E33-Inputs!$D33)*2)*10000,(Inputs!$E33+(Inputs!$F33-Inputs!$E33)*2)*10000)/10000 -> 1.1655 | L33: =RANDBETWEEN((Inputs!$E33-(Inputs!$E33-Inputs!$D33)*2)*10000,(Inputs!$E33+(Inputs!$F33-Inputs!$E33)*2)*10000)/10000 -> 1.1266 | M33: =RANDBETWEEN((Inputs!$E33-(Inputs!$E33-Inputs!$D33)*2)*10000,(Inputs!$E33+(Inputs!$F33-Inputs!$E33)*2)*10000)/10000 -> 1.2059 | N33: =RANDBETWEEN((Inputs!$E33-(Inputs!$E33-Inputs!$D33)*2)*10000,(Inputs!$E33+(Inputs!$F33-Inputs!$E33)*2)*10000)/10000 -> 0.1912 | ... SL33: =RANDBETWEEN((Inputs!$E33-(Inputs!$E33-Inputs!$D33)*2)*10000,(Inputs!$E33+(Inputs!$F33-Inputs!$E33)*2)*10000)/10000 -> 0.4488
A34: EV adjustment (generalizing the multiplier to current program conditions) | B34: {=INDEX('New CEA'!$B34:$F34,MATCH($B$2,'New CEA'!B$2:F$2,0))} -> 0.8 | C34: =AVERAGE(G34:SL34) -> 0.813611 | D34: =PERCENTILE($G34:$SL34,0.25) -> 0.322075 | E34: =PERCENTILE($G34:$SL34,0.75) -> 1.30445 | G34: =RANDBETWEEN((Inputs!$E34-(Inputs!$E34-Inputs!$D34)*2)*10000,(Inputs!$E34+(Inputs!$F34-Inputs!$E34)*2)*10000)/10000 -> 1.725 | H34: =RANDBETWEEN((Inputs!$E34-(Inputs!$E34-Inputs!$D34)*2)*10000,(Inputs!$E34+(Inputs!$F34-Inputs!$E34)*2)*10000)/10000 -> 0.652 | I34: =RANDBETWEEN((Inputs!$E34-(Inputs!$E34-Inputs!$D34)*2)*10000,(Inputs!$E34+(Inputs!$F34-Inputs!$E34)*2)*10000)/10000 -> 0.1359 | J34: =RANDBETWEEN((Inputs!$E34-(Inputs!$E34-Inputs!$D34)*2)*10000,(Inputs!$E34+(Inputs!$F34-Inputs!$E34)*2)*10000)/10000 -> 1.4214 | K34: =RANDBETWEEN((Inputs!$E34-(Inputs!$E34-Inputs!$D34)*2)*10000,(Inputs!$E34+(Inputs!$F34-Inputs!$E34)*2)*10000)/10000 -> 0.9153 | L34: =RANDBETWEEN((Inputs!$E34-(Inputs!$E34-Inputs!$D34)*2)*10000,(Inputs!$E34+(Inputs!$F34-Inputs!$E34)*2)*10000)/10000 -> 0.8247 | M34: =RANDBETWEEN((Inputs!$E34-(Inputs!$E34-Inputs!$D34)*2)*10000,(Inputs!$E34+(Inputs!$F34-Inputs!$E34)*2)*10000)/10000 -> -0.1189 | N34: =RANDBETWEEN((Inputs!$E34-(Inputs!$E34-Inputs!$D34)*2)*10000,(Inputs!$E34+(Inputs!$F34-Inputs!$E34)*2)*10000)/10000 -> 0.9632 | ... SL34: =RANDBETWEEN((Inputs!$E34-(Inputs!$E34-Inputs!$D34)*2)*10000,(Inputs!$E34+(Inputs!$F34-Inputs!$E34)*2)*10000)/10000 -> 1.6741
A35: Distributional adjustment (accounting for consumption spillovers accruing to richer non-recipients) | B35: {=INDEX('New CEA'!$B35:$F35,MATCH($B$2,'New CEA'!B$2:F$2,0))} -> 0.8 | C35: =AVERAGE(G35:SL35) -> 0.80576 | D35: =PERCENTILE($G35:$SL35,0.25) -> 0.6003 | E35: =PERCENTILE($G35:$SL35,0.75) -> 1.00695 | G35: =RANDBETWEEN((Inputs!$E35-(Inputs!$E35-Inputs!$D35)*2)*10000,(Inputs!$E35+(Inputs!$F35-Inputs!$E35)*2)*10000)/10000 -> 0.5452 | H35: =RANDBETWEEN((Inputs!$E35-(Inputs!$E35-Inputs!$D35)*2)*10000,(Inputs!$E35+(Inputs!$F35-Inputs!$E35)*2)*10000)/10000 -> 0.7726 | I35: =RANDBETWEEN((Inputs!$E35-(Inputs!$E35-Inputs!$D35)*2)*10000,(Inputs!$E35+(Inputs!$F35-Inputs!$E35)*2)*10000)/10000 -> 0.9993 | J35: =RANDBETWEEN((Inputs!$E35-(Inputs!$E35-Inputs!$D35)*2)*10000,(Inputs!$E35+(Inputs!$F35-Inputs!$E35)*2)*10000)/10000 -> 0.8575 | K35: =RANDBETWEEN((Inputs!$E35-(Inputs!$E35-Inputs!$D35)*2)*10000,(Inputs!$E35+(Inputs!$F35-Inputs!$E35)*2)*10000)/10000 -> 0.5581 | L35: =RANDBETWEEN((Inputs!$E35-(Inputs!$E35-Inputs!$D35)*2)*10000,(Inputs!$E35+(Inputs!$F35-Inputs!$E35)*2)*10000)/10000 -> 0.6819 | M35: =RANDBETWEEN((Inputs!$E35-(Inputs!$E35-Inputs!$D35)*2)*10000,(Inputs!$E35+(Inputs!$F35-Inputs!$E35)*2)*10000)/10000 -> 0.9749 | N35: =RANDBETWEEN((Inputs!$E35-(Inputs!$E35-Inputs!$D35)*2)*10000,(Inputs!$E35+(Inputs!$F35-Inputs!$E35)*2)*10000)/10000 -> 1.1299 | ... SL35: =RANDBETWEEN((Inputs!$E35-(Inputs!$E35-Inputs!$D35)*2)*10000,(Inputs!$E35+(Inputs!$F35-Inputs!$E35)*2)*10000)/10000 -> 0.9404
A36: Spillover/general equilibrium benefits (as % of recipient consumption benefits), post adjustments | B36: =B31*B35*B32*B33*B34 -> 0.675072 | G36: =G31*G35*G32*G33*G34 -> 1.1189847 | H36: =H31*H35*H32*H33*H34 -> 0.46988158 | I36: =I31*I35*I32*I33*I34 -> 0.22974428 | J36: =J31*J35*J32*J33*J34 -> 1.0600131 | K36: =K31*K35*K32*K33*K34 -> 1.0466624 | L36: =L31*L35*L32*L33*L34 -> 1.1137951 | M36: =M31*M35*M32*M33*M34 -> -0.24573787 | N36: =N31*N35*N32*N33*N34 -> 0.36581646 | ... SL36: =SL31*SL35*SL32*SL33*SL34 -> 1.2421262
A37: Units of value from non-recipient spillovers | B37: =B26*B36 -> 2832.8686 | G37: =G26*G36 -> 4080.6662 | H37: =H26*H36 -> 1352.3144 | I37: =I26*I36 -> 640.85111 | J37: =J26*J36 -> 6725.177 | K37: =K26*K36 -> 3403.8603 | L37: =L26*L36 -> 3590.6996 | M37: =M26*M36 -> -1160.5142 | N37: =N26*N36 -> 2377.6284 | ... SL37: =SL26*SL36 -> 2485.7818
A38: Units of value from consumption gains and non-recipient spillovers | B38: =B26+B37 -> 7029.2633 | G38: =G26+G37 -> 7727.4238 | H38: =H26+H37 -> 4230.3041 | I38: =I26+I37 -> 3430.2617 | J38: =J26+J37 -> 13069.605 | K38: =K26+K37 -> 6655.9694 | L38: =L26+L37 -> 6814.5417 | M38: =M26+M37 -> 3562.0555 | N38: =N26+N37 -> 8877.1404 | ... SL38: =SL26+SL37 -> 4487.013
A39: Initial CE from consumption gains and spillovers (x previous benchmark) | B39: =(B38/B4)/B28 -> 2.0951604 | G39: =(G38/G4)/G28 -> 2.303256 | H39: =(H38/H4)/H28 -> 1.2608954 | I39: =(I38/I4)/I28 -> 1.0224327 | J39: =(J38/J4)/J28 -> 3.8955605 | K39: =(K38/K4)/K28 -> 1.9838955 | L39: =(L38/L4)/L28 -> 2.03116 | M39: =(M38/M4)/M28 -> 1.0617155 | N39: =(N38/N4)/N28 -> 2.6459435 | ... SL39: =(SL38/SL4)/SL28 -> 1.3374107
A40: Mortality benefits
A41: Share of u5s in targeted population | B41: {=INDEX('New CEA'!$B41:$F41,MATCH($B$2,'New CEA'!B$2:F$2,0))} -> 0.12879127 | G41: =$B41 -> 0.12879127 | H41: =$B41 -> 0.12879127 | I41: =$B41 -> 0.12879127 | J41: =$B41 -> 0.12879127 | K41: =$B41 -> 0.12879127 | L41: =$B41 -> 0.12879127 | M41: =$B41 -> 0.12879127 | N41: =$B41 -> 0.12879127 | ... SL41: =$B41 -> 0.12879127
A42: Number of u5 children reached | B42: =B41*B9 -> 525.2897 | G42: =G41*G9 -> 546.17622 | H42: =H41*H9 -> 582.44623 | I42: =I41*I9 -> 535.92057 | J42: =J41*J9 -> 480.64008 | K42: =K41*K9 -> 487.83154 | L42: =L41*L9 -> 471.13484 | M42: =M41*M9 -> 522.16298 | N42: =N41*N9 -> 574.00407 | ... SL42: =SL41*SL9 -> 552.42967
A43: Average u5 mortality rate in each country (%) | B43: {=INDEX('New CEA'!$B43:$F43,MATCH($B$2,'New CEA'!B$2:F$2,0))} -> 0.0410984 | G43: =$B43 -> 0.0410984 | H43: =$B43 -> 0.0410984 | I43: =$B43 -> 0.0410984 | J43: =$B43 -> 0.0410984 | K43: =$B43 -> 0.0410984 | L43: =$B43 -> 0.0410984 | M43: =$B43 -> 0.0410984 | N43: =$B43 -> 0.0410984 | ... SL43: =$B43 -> 0.0410984
A44: u5 mortality rate in Egger et al. (2015-2017) | B44: {=INDEX('New CEA'!$B44:$F44,MATCH($B$2,'New CEA'!B$2:F$2,0))} -> 0.057 | G44: =$B44 -> 0.057 | H44: =$B44 -> 0.057 | I44: =$B44 -> 0.057 | J44: =$B44 -> 0.057 | K44: =$B44 -> 0.057 | L44: =$B44 -> 0.057 | M44: =$B44 -> 0.057 | N44: =$B44 -> 0.057 | ... SL44: =$B44 -> 0.057
A45: u5 mortality rate in UNICEF data (2016) | B45: {=INDEX('New CEA'!$B45:$F45,MATCH($B$2,'New CEA'!B$2:F$2,0))} -> 0.0462512 | G45: =$B45 -> 0.0462512 | H45: =$B45 -> 0.0462512 | I45: =$B45 -> 0.0462512 | J45: =$B45 -> 0.0462512 | K45: =$B45 -> 0.0462512 | L45: =$B45 -> 0.0462512 | M45: =$B45 -> 0.0462512 | N45: =$B45 -> 0.0462512 | ... SL45: =$B45 -> 0.0462512
A46: Adjustment for GD u5 population being at higher risk | B46: =B44/B45 -> 1.2324005 | G46: =$B46 -> 1.2324005 | H46: =$B46 -> 1.2324005 | I46: =$B46 -> 1.2324005 | J46: =$B46 -> 1.2324005 | K46: =$B46 -> 1.2324005 | L46: =$B46 -> 1.2324005 | M46: =$B46 -> 1.2324005 | N46: =$B46 -> 1.2324005 | ... SL46: =$B46 -> 1.2324005
A47: u5 morality rate in GD target population | B47: =B43*B46 -> 0.050649687 | G47: =G43*G46 -> 0.050649687 | H47: =H43*H46 -> 0.050649687 | I47: =I43*I46 -> 0.050649687 | J47: =J43*J46 -> 0.050649687 | K47: =K43*K46 -> 0.050649687 | L47: =L43*L46 -> 0.050649687 | M47: =M43*M46 -> 0.050649687 | N47: =N43*N46 -> 0.050649687 | ... SL47: =SL43*SL46 -> 0.050649687
A48: % reduction in under 5 mortality due to transfer, unadjusted | B48: {=INDEX('New CEA'!$B48:$F48,MATCH($B$2,'New CEA'!B$2:F$2,0))} -> 0.45 | G48: =$B48 -> 0.45 | H48: =$B48 -> 0.45 | I48: =$B48 -> 0.45 | J48: =$B48 -> 0.45 | K48: =$B48 -> 0.45 | L48: =$B48 -> 0.45 | M48: =$B48 -> 0.45 | N48: =$B48 -> 0.45 | ... SL48: =$B48 -> 0.45
A49: IV adjustment | B49: {=INDEX('New CEA'!$B49:$F49,MATCH($B$2,'New CEA'!B$2:F$2,0))} -> 0.5 | C49: =AVERAGE(G49:SL49) -> 0.501023 | D49: =PERCENTILE($G49:$SL49,0.25) -> 0.2541 | E49: =PERCENTILE($G49:$SL49,0.75) -> 0.76235 | G49: =RANDBETWEEN((Inputs!$E49-(Inputs!$E49-Inputs!$D49)*2)*10000,(Inputs!$E49+(Inputs!$F49-Inputs!$E49)*2)*10000)/10000 -> 0.2333 | H49: =RANDBETWEEN((Inputs!$E49-(Inputs!$E49-Inputs!$D49)*2)*10000,(Inputs!$E49+(Inputs!$F49-Inputs!$E49)*2)*10000)/10000 -> 0.2058 | I49: =RANDBETWEEN((Inputs!$E49-(Inputs!$E49-Inputs!$D49)*2)*10000,(Inputs!$E49+(Inputs!$F49-Inputs!$E49)*2)*10000)/10000 -> 0.9509 | J49: =RANDBETWEEN((Inputs!$E49-(Inputs!$E49-Inputs!$D49)*2)*10000,(Inputs!$E49+(Inputs!$F49-Inputs!$E49)*2)*10000)/10000 -> 0.4367 | K49: =RANDBETWEEN((Inputs!$E49-(Inputs!$E49-Inputs!$D49)*2)*10000,(Inputs!$E49+(Inputs!$F49-Inputs!$E49)*2)*10000)/10000 -> 0.0283 | L49: =RANDBETWEEN((Inputs!$E49-(Inputs!$E49-Inputs!$D49)*2)*10000,(Inputs!$E49+(Inputs!$F49-Inputs!$E49)*2)*10000)/10000 -> 0.771 | M49: =RANDBETWEEN((Inputs!$E49-(Inputs!$E49-Inputs!$D49)*2)*10000,(Inputs!$E49+(Inputs!$F49-Inputs!$E49)*2)*10000)/10000 -> 0.2469 | N49: =RANDBETWEEN((Inputs!$E49-(Inputs!$E49-Inputs!$D49)*2)*10000,(Inputs!$E49+(Inputs!$F49-Inputs!$E49)*2)*10000)/10000 -> 0.3106 | ... SL49: =RANDBETWEEN((Inputs!$E49-(Inputs!$E49-Inputs!$D49)*2)*10000,(Inputs!$E49+(Inputs!$F49-Inputs!$E49)*2)*10000)/10000 -> 0.4173
A50: % reduction in under 5 mortality among recipient households, adjusted | B50: =B48*B49 -> 0.225 | G50: =G48*G49 -> 0.104985 | H50: =H48*H49 -> 0.09261 | I50: =I48*I49 -> 0.427905 | J50: =J48*J49 -> 0.196515 | K50: =K48*K49 -> 0.012735 | L50: =L48*L49 -> 0.34695 | M50: =M48*M49 -> 0.111105 | N50: =N48*N49 -> 0.13977 | ... SL50: =SL48*SL49 -> 0.187785
A51: u5 deaths averted among recipient households | B51: =B42*B47*B50 -> 5.9862958 | G51: =G42*G47*G50 -> 2.9042688 | H51: =H42*H47*H50 -> 2.7320616 | I51: =I42*I47*I50 -> 11.615143 | J51: =J42*J47*J50 -> 4.7840141 | K51: =K42*K47*K50 -> 0.31466294 | L51: =L42*L47*L50 -> 8.2792095 | M51: =M42*M47*M50 -> 2.9384374 | N51: =N42*N47*N50 -> 4.0635509 | ... SL51: =SL42*SL47*SL50 -> 5.2542975
A52: Value assigned to averting an under-5 death | B52: {=INDEX('New CEA'!$B52:$F52,MATCH($B$2,'New CEA'!B$2:F$2,0))} -> 116 | G52: =$B52 -> 116 | H52: =$B52 -> 116 | I52: =$B52 -> 116 | J52: =$B52 -> 116 | K52: =$B52 -> 116 | L52: =$B52 -> 116 | M52: =$B52 -> 116 | N52: =$B52 -> 116 | ... SL52: =$B52 -> 116
A53: Units of value from child mortality benefits | B53: =B51*B52 -> 694.41031 | G53: =G51*G52 -> 336.89518 | H53: =H51*H52 -> 316.91914 | I53: =I51*I52 -> 1347.3566 | J53: =J51*J52 -> 554.94564 | K53: =K51*K52 -> 36.500901 | L53: =L51*L52 -> 960.38831 | M53: =M51*M52 -> 340.85874 | N53: =N51*N52 -> 471.3719 | ... SL53: =SL51*SL52 -> 609.49851
A54: Adult mortality benefits (as % of child mortality benefits) | B54: {=INDEX('New CEA'!$B54:$F54,MATCH($B$2,'New CEA'!B$2:F$2,0))} -> 0.5 | G54: =$B54 -> 0.5 | H54: =$B54 -> 0.5 | I54: =$B54 -> 0.5 | J54: =$B54 -> 0.5 | K54: =$B54 -> 0.5 | L54: =$B54 -> 0.5 | M54: =$B54 -> 0.5 | N54: =$B54 -> 0.5 | ... SL54: =$B54 -> 0.5
A55: Units of value from child and adult mortality benefits | B55: =B53+(B53*B54) -> 1041.6155 | G55: =G53+(G53*G54) -> 505.34277 | H55: =H53+(H53*H54) -> 475.37872 | I55: =I53+(I53*I54) -> 2021.0348 | J55: =J53+(J53*J54) -> 832.41846 | K55: =K53+(K53*K54) -> 54.751351 | L55: =L53+(L53*L54) -> 1440.5825 | M55: =M53+(M53*M54) -> 511.28811 | N55: =N53+(N53*N54) -> 707.05785 | ... SL55: =SL53+(SL53*SL54) -> 914.24777
A56: Units of value from consumption and mortality benefits | B56: =B55+B38 -> 8070.8788 | G56: =G55+G38 -> 8232.7665 | H56: =H55+H38 -> 4705.6828 | I56: =I55+I38 -> 5451.2965 | J56: =J55+J38 -> 13902.024 | K56: =K55+K38 -> 6710.7207 | L56: =L55+L38 -> 8255.1242 | M56: =M55+M38 -> 4073.3437 | N56: =N55+N38 -> 9584.1982 | ... SL56: =SL55+SL38 -> 5401.2608
A57: Initial CE from consumption and child mortality (x previous benchmark) | B57: =(B56/B4)/B28 -> 2.4056271 | G57: =(G56/G4)/G28 -> 2.4538797 | H57: =(H56/H4)/H28 -> 1.402588 | I57: =(I56/I4)/I28 -> 1.6248276 | J57: =(J56/J4)/J28 -> 4.1436733 | K57: =(K56/K4)/K28 -> 2.0002148 | L57: =(L56/L4)/L28 -> 2.4605437 | M57: =(M56/M4)/M28 -> 1.2141114 | N57: =(N56/N4)/N28 -> 2.856691 | ... SL57: =(SL56/SL4)/SL28 -> 1.6099138
A58: Supplementary adjustments
A59: Reduced morbidity | B59: {=INDEX('New CEA'!$B59:$F59,MATCH($B$2,'New CEA'!B$2:F$2,0))} -> 0.1 | G59: =$B59 -> 0.1 | H59: =$B59 -> 0.1 | I59: =$B59 -> 0.1 | J59: =$B59 -> 0.1 | K59: =$B59 -> 0.1 | L59: =$B59 -> 0.1 | M59: =$B59 -> 0.1 | N59: =$B59 -> 0.1 | ... SL59: =$B59 -> 0.1
A60: Developmental effects | B60: {=INDEX('New CEA'!$B60:$F60,MATCH($B$2,'New CEA'!B$2:F$2,0))} -> 0.05 | G60: =$B60 -> 0.05 | H60: =$B60 -> 0.05 | I60: =$B60 -> 0.05 | J60: =$B60 -> 0.05 | K60: =$B60 -> 0.05 | L60: =$B60 -> 0.05 | M60: =$B60 -> 0.05 | N60: =$B60 -> 0.05 | ... SL60: =$B60 -> 0.05
A61: Leverage & funging | B61: {=INDEX('New CEA'!$B61:$F61,MATCH($B$2,'New CEA'!B$2:F$2,0))} -> 0.02 | G61: =$B61 -> 0.02 | H61: =$B61 -> 0.02 | I61: =$B61 -> 0.02 | J61: =$B61 -> 0.02 | K61: =$B61 -> 0.02 | L61: =$B61 -> 0.02 | M61: =$B61 -> 0.02 | N61: =$B61 -> 0.02 | ... SL61: =$B61 -> 0.02
A62: Risk of wastage/fraud | B62: {=INDEX('New CEA'!$B62:$F62,MATCH($B$2,'New CEA'!B$2:F$2,0))} -> -0.02 | G62: =$B62 -> -0.02 | H62: =$B62 -> -0.02 | I62: =$B62 -> -0.02 | J62: =$B62 -> -0.02 | K62: =$B62 -> -0.02 | L62: =$B62 -> -0.02 | M62: =$B62 -> -0.02 | N62: =$B62 -> -0.02 | ... SL62: =$B62 -> -0.02
A63: Within-org fungibility | B63: {=INDEX('New CEA'!$B63:$F63,MATCH($B$2,'New CEA'!B$2:F$2,0))} -> -0.05 | G63: =$B63 -> -0.05 | H63: =$B63 -> -0.05 | I63: =$B63 -> -0.05 | J63: =$B63 -> -0.05 | K63: =$B63 -> -0.05 | L63: =$B63 -> -0.05 | M63: =$B63 -> -0.05 | N63: =$B63 -> -0.05 | ... SL63: =$B63 -> -0.05
A64: Psychological spillovers | B64: {=INDEX('New CEA'!$B64:$F64,MATCH($B$2,'New CEA'!B$2:F$2,0))} -> -0.02 | G64: =$B64 -> -0.02 | H64: =$B64 -> -0.02 | I64: =$B64 -> -0.02 | J64: =$B64 -> -0.02 | K64: =$B64 -> -0.02 | L64: =$B64 -> -0.02 | M64: =$B64 -> -0.02 | N64: =$B64 -> -0.02 | ... SL64: =$B64 -> -0.02
A65: Total adjustment factor | B65: =1+SUM(B59:B64) -> 1.08 | G65: =1+SUM(G59:G64) -> 1.08 | H65: =1+SUM(H59:H64) -> 1.08 | I65: =1+SUM(I59:I64) -> 1.08 | J65: =1+SUM(J59:J64) -> 1.08 | K65: =1+SUM(K59:K64) -> 1.08 | L65: =1+SUM(L59:L64) -> 1.08 | M65: =1+SUM(M59:M64) -> 1.08 | N65: =1+SUM(N59:N64) -> 1.08 | ... SL65: =1+SUM(SL59:SL64) -> 1.08
A66: Disaggregated cost-effectiveness estimate (x cash) | B66: =B57*B65 -> 2.5980772 | G66: =G57*G65 -> 2.6501901 | H66: =H57*H65 -> 1.5147951 | I66: =I57*I65 -> 1.7548138 | J66: =J57*J65 -> 4.4751671 | K66: =K57*K65 -> 2.160232 | L66: =L57*L65 -> 2.6573872 | M66: =M57*M65 -> 1.3112403 | N66: =N57*N65 -> 3.0852263 | ... SL66: =SL57*SL65 -> 1.7387069

Sheet Raw
A1: Raw
A2: WB | B2: Poverty, food insecurity, and other data from the World Bank
A3: IHME | B3: Child mortality data from the Institute for Health Metrics and Evaluation
A4: UNICEF | B4: Child mortality data from UNICEF
A5: Equivalence | B5: Adult equivalence conversion factor calculations
A6: Papers | B6: Papers which estimate economic mutlipliers
A7: u5m papers | B7: Papers which estimate under-5 mortality

Sheet WB
A1: PPP conversion factor, private consumption (LCU per international $)
A2: Source: World Bank
A3: Country Name | B3: Country Code | C3: Indicator Name | D3: Indicator Code | E3: 1960 | F3: 1961 | G3: 1962 | H3: 1963 | I3: 1964 | J3: 1965 | K3: 1966 | L3: 1967 | M3: 1968 | N3: 1969 | O3: 1970 | P3: 1971 | Q3: 1972 | R3: 1973 | S3: 1974 | T3: 1975 | U3: 1976 | V3: 1977 | W3: 1978 | X3: 1979 | Y3: 1980 | Z3: 1981 | AA3: 1982 | AB3: 1983 | AC3: 1984 | AD3: 1985 | AE3: 1986 | AF3: 1987 | AG3: 1988 | AH3: 1989 | AI3: 1990 | AJ3: 1991 | AK3: 1992 | AL3: 1993 | AM3: 1994 | AN3: 1995 | AO3: 1996 | AP3: 1997 | AQ3: 1998 | AR3: 1999 | AS3: 2000 | AT3: 2001 | AU3: 2002 | AV3: 2003 | AW3: 2004 | AX3: 2005 | AY3: 2006 | AZ3: 2007 | BA3: 2008 | BB3: 2009 | BC3: 2010 | BD3: 2011 | BE3: 2012 | BF3: 2013 | BG3: 2014 | BH3: 2015 | BI3: 2016 | BJ3: 2017 | BK3: 2018 | BL3: 2019 | BM3: 2020 | BN3: 2021 | BO3: 2022 | BP3: 2023
A4: Kenya | B4: KEN | C4: PPP conversion factor, private consumption (LCU per international $) | D4: PA.NUS.PRVT.PP | AI4: 4.662486 | AJ4: 5.371444 | AK4: 6.638518 | AL4: 9.412995 | AM4: 11.81717 | AN4: 11.67336 | AO4: 12.3462 | AP4: 13.43489 | AQ4: 14.11888 | AR4: 14.60992 | AS4: 15.54312 | AT4: 15.98336 | AU4: 16.04241 | AV4: 17.22603 | AW4: 18.72702 | AX4: 19.98042 | AY4: 22.15367 | AZ4: 23.64121 | BA4: 28.74122 | BB4: 31.50724 | BC4: 32.22683 | BD4: 35.62133 | BE4: 36.56151 | BF4: 37.90647 | BG4: 39.26264 | BH4: 40.57187 | BI4: 41.55217 | BJ4: 43.65147 | BK4: 43.28262 | BL4: 43.26185 | BM4: 43.22019 | BN4: 42.42797 | BO4: 42.29325 | BP4: 43.73735
A5: Mozambique | B5: MOZ | C5: PPP conversion factor, private consumption (LCU per international $) | D5: PA.NUS.PRVT.PP | AZ5: 11.55958 | BA5: 12.74669 | BB5: 13.27681 | BC5: 14.68568 | BD5: 15.82597 | BE5: 15.58562 | BF5: 16.43296 | BG5: 16.7203 | BH5: 17.15802 | BI5: 19.86096 | BJ5: 22.6119 | BK5: 22.83751 | BL5: 23.03137 | BM5: 23.39495 | BN5: 23.62321 | BO5: 24.12117 | BP5: 24.81866
A6: Malawi | B6: MWI | C6: PPP conversion factor, private consumption (LCU per international $) | D6: PA.NUS.PRVT.PP | AI6: 2.63805 | AJ6: 2.850146 | AK6: 3.423406 | AL6: 4.082506 | AM6: 5.357389 | AN6: 9.55346 | AO6: 12.7714 | AP6: 13.61998 | AQ6: 17.40161 | AR6: 24.65872 | AS6: 30.90937 | AT6: 36.88341 | AU6: 41.66098 | AV6: 44.63746 | AW6: 48.44251 | AX6: 54.0731 | AY6: 59.70344 | AZ6: 62.66359 | BA6: 65.6046 | BB6: 71.38365 | BC6: 75.43711 | BD6: 78.70302 | BE6: 92.98806 | BF6: 118.9128 | BG6: 148.2975 | BH6: 182.2958 | BI6: 220.4329 | BJ6: 249.1049 | BK6: 266.7161 | BL6: 277.8677 | BM6: 280.9026 | BN6: 282.0942 | BO6: 315.9216 | BP6: 390.7884
A7: Rwanda | B7: RWA | C7: PPP conversion factor, private consumption (LCU per international $) | D7: PA.NUS.PRVT.PP | AI7: 51.64465 | AJ7: 59.27588 | AK7: 63.03372 | AL7: 68.79069 | AN7: 129.7316 | AO7: 135.3783 | AP7: 148.1805 | AQ7: 154.977 | AR7: 148.0098 | AS7: 148.7582 | AT7: 149.5057 | AU7: 150.104 | AV7: 157.7062 | AW7: 172.4105 | AX7: 181.7843 | AY7: 191.7462 | AZ7: 203.357 | BA7: 226.0726 | BB7: 256.2474 | BC7: 251.4921 | BD7: 251.3052 | BE7: 258.3165 | BF7: 268.6642 | BG7: 267.7125 | BH7: 269.6642 | BI7: 281.0818 | BJ7: 297.6189 | BK7: 290.7546 | BL7: 291.5668 | BM7: 305.2331 | BN7: 291.5977 | BO7: 317.7501 | BP7: 365.5828
A8: Uganda | B8: UGA | C8: PPP conversion factor, private consumption (LCU per international $) | D8: PA.NUS.PRVT.PP | AL8: 455.2835 | AM8: 488.2484 | AN8: 506.033 | AO8: 526.9783 | AP8: 557.0062 | AQ8: 548.8694 | AR8: 568.1484 | AS8: 568.2317 | AT8: 562.9209 | AU8: 552.539 | AV8: 587.1726 | AW8: 593.1431 | AX8: 622.1483 | AY8: 646.7672 | AZ8: 667.4295 | BA8: 720.2108 | BB8: 816.8668 | BC8: 835.645 | BD8: 944.2556 | BE8: 1017.041 | BF8: 1064.346 | BG8: 1080.318 | BH8: 1126.516 | BI8: 1171.108 | BJ8: 1219.186 | BK8: 1241.169 | BL8: 1279.647 | BM8: 1315.932 | BN8: 1315.268 | BO8: 1305.44 | BP8: 1320.92
A10: Official exchange rate (LCU per US$, period average)
A11: Source: World Bank
A12: Country Name | B12: Country Code | C12: Indicator Name | D12: Indicator Code | E12: 1960 | F12: 1961 | G12: 1962 | H12: 1963 | I12: 1964 | J12: 1965 | K12: 1966 | L12: 1967 | M12: 1968 | N12: 1969 | O12: 1970 | P12: 1971 | Q12: 1972 | R12: 1973 | S12: 1974 | T12: 1975 | U12: 1976 | V12: 1977 | W12: 1978 | X12: 1979 | Y12: 1980 | Z12: 1981 | AA12: 1982 | AB12: 1983 | AC12: 1984 | AD12: 1985 | AE12: 1986 | AF12: 1987 | AG12: 1988 | AH12: 1989 | AI12: 1990 | AJ12: 1991 | AK12: 1992 | AL12: 1993 | AM12: 1994 | AN12: 1995 | AO12: 1996 | AP12: 1997 | AQ12: 1998 | AR12: 1999 | AS12: 2000 | AT12: 2001 | AU12: 2002 | AV12: 2003 | AW12: 2004 | AX12: 2005 | AY12: 2006 | AZ12: 2007 | BA12: 2008 | BB12: 2009 | BC12: 2010 | BD12: 2011 | BE12: 2012 | BF12: 2013 | BG12: 2014 | BH12: 2015 | BI12: 2016 | BJ12: 2017 | BK12: 2018 | BL12: 2019 | BM12: 2020 | BN12: 2021 | BO12: 2022 | BP12: 2023
A13: Kenya | B13: KEN | C13: Official exchange rate (LCU per US$, period average) | D13: PA.NUS.FCRF | E13: 7.14286 | F13: 7.14286 | G13: 7.14286 | H13: 7.14286 | I13: 7.14286 | J13: 7.14286 | K13: 7.14286 | L13: 7.14286 | M13: 7.14286 | N13: 7.14286 | O13: 7.14286 | P13: 7.14286 | Q13: 7.14286 | R13: 7.001192 | S13: 7.14286 | T13: 7.343193 | U13: 8.367145 | V13: 8.276561 | W13: 7.729383 | X13: 7.475309 | Y13: 7.420187 | Z13: 9.047498 | AA13: 10.92232 | AB13: 13.31152 | AC13: 14.41387 | AD13: 16.43212 | AE13: 16.22574 | AF13: 16.45449 | AG13: 17.7471 | AH13: 20.57247 | AI13: 22.91477 | AJ13: 27.50787 | AK13: 32.21683 | AL13: 58.00133 | AM13: 56.05058 | AN13: 51.42983 | AO13: 57.11487 | AP13: 58.73184 | AQ13: 60.3667 | AR13: 70.32622 | AS13: 76.17554 | AT13: 78.5632 | AU13: 78.74914 | AV13: 75.93557 | AW13: 79.17388 | AX13: 75.55411 | AY13: 72.10084 | AZ13: 67.31764 | BA13: 69.17532 | BB13: 77.35201 | BC13: 79.23315 | BD13: 88.81077 | BE13: 84.5296 | BF13: 86.12288 | BG13: 87.92216 | BH13: 98.17845 | BI13: 101.5044 | BJ13: 103.41 | BK13: 101.3016 | BL13: 101.9913 | BM13: 106.4508 | BN13: 109.6377 | BO13: 117.866 | BP13: 139.8464
A14: Mozambique | B14: MOZ | C14: Official exchange rate (LCU per US$, period average) | D14: PA.NUS.FCRF | E14: 0.02875 | F14: 0.02875 | G14: 0.02875 | H14: 0.02875 | I14: 0.02875 | J14: 0.02875 | K14: 0.02875 | L14: 0.02875 | M14: 0.02875 | N14: 0.02875 | O14: 0.02875 | P14: 0.028312 | Q14: 0.027053 | R14: 0.024515 | S14: 0.025408 | T14: 0.025553 | U14: 0.030229 | V14: 0.030407 | W14: 0.03 | X14: 0.03 | Y14: 0.0324 | Z14: 0.03535 | AA14: 0.03777 | AB14: 0.040183 | AC14: 0.042443 | AD14: 0.043181 | AE14: 0.040429 | AF14: 0.290731 | AG14: 0.524645 | AH14: 0.744918 | AI14: 0.929089 | AJ14: 1.434468 | AK14: 2.516554 | AL14: 3.874237 | AM14: 6.038588 | AN14: 9.024333 | AO14: 11.29375 | AP14: 11.54358 | AQ14: 11.87458 | AR14: 12.77511 | AS14: 15.22725 | AT14: 20.70364 | AU14: 23.67796 | AV14: 23.78227 | AW14: 22.58134 | AX14: 23.06097 | AY14: 25.40078 | AZ14: 25.84034 | BA14: 24.30064 | BB14: 27.5183 | BC14: 33.9601 | BD14: 29.0676 | BE14: 28.37298 | BF14: 30.10411 | BG14: 31.35269 | BH14: 39.98247 | BI14: 63.05623 | BJ14: 63.58432 | BK14: 60.32621 | BL14: 62.54833 | BM14: 69.465 | BN14: 65.465 | BO14: 63.85083 | BP14: 63.88583
A15: Malawi | B15: MWI | C15: Official exchange rate (LCU per US$, period average) | D15: PA.NUS.FCRF | E15: 0.714285 | F15: 0.714285 | G15: 0.714285 | H15: 0.714285 | I15: 0.714285 | J15: 0.714285 | K15: 0.714285 | L15: 0.724206 | M15: 0.833333 | N15: 0.833333 | O15: 0.833333 | P15: 0.830894 | Q15: 0.801558 | R15: 0.819262 | S15: 0.841203 | T15: 0.863833 | U15: 0.913011 | V15: 0.902928 | W15: 0.843745 | X15: 0.816878 | Y15: 0.812096 | Z15: 0.895299 | AA15: 1.055509 | AB15: 1.174763 | AC15: 1.41338 | AD15: 1.719097 | AE15: 1.861073 | AF15: 2.208743 | AG15: 2.561301 | AH15: 2.759524 | AI15: 2.728882 | AJ15: 2.803313 | AK15: 3.603275 | AL15: 4.402778 | AM15: 8.736405 | AN15: 15.28374 | AO15: 15.30847 | AP15: 16.44418 | AQ15: 31.07268 | AR15: 44.08814 | AS15: 59.54381 | AT15: 72.19733 | AU15: 76.68661 | AV15: 97.43248 | AW15: 108.8975 | AX15: 118.42 | AY15: 136.0125 | AZ15: 139.9575 | BA15: 140.5217 | BB15: 141.1683 | BC15: 150.4858 | BD15: 156.5158 | BE15: 249.1067 | BF15: 364.4058 | BG15: 424.8967 | BH15: 499.6058 | BI15: 718.005 | BJ15: 730.2725 | BK15: 732.3333 | BL15: 745.5407 | BM15: 749.5275
A16: Rwanda | B16: RWA | C16: Official exchange rate (LCU per US$, period average) | D16: PA.NUS.FCRF | E16: 50 | F16: 50 | G16: 50 | H16: 50 | I16: 50 | J16: 50 | K16: 87.5 | L16: 100 | M16: 100 | N16: 100 | O16: 100 | P16: 99.70733 | Q16: 92.105 | R16: 83.922 | S16: 92.30176 | T16: 92.27727 | U16: 97.01235 | V16: 95.93509 | W16: 89.48791 | X16: 86.69071 | Y16: 86.06388 | Z16: 87.16031 | AA16: 93.05997 | AB16: 96.09394 | AC16: 100.2329 | AD16: 101.2447 | AE16: 87.59092 | AF16: 79.46065 | AG16: 76.44774 | AH16: 80.14898 | AI16: 83.7041 | AJ16: 125.1642 | AK16: 133.9386 | AL16: 144.237 | AM16: 140.7038 | AN16: 262.1823 | AO16: 306.82 | AP16: 301.5298 | AQ16: 312.3141 | AR16: 333.9419 | AS16: 389.6962 | AT16: 442.9919 | AU16: 475.3652 | AV16: 537.655 | AW16: 577.449 | AX16: 557.8226 | AY16: 551.7103 | AZ16: 546.955 | BA16: 546.8487 | BB16: 568.2813 | BC16: 583.1309 | BD16: 600.3065 | BE16: 614.2951 | BF16: 646.636 | BG16: 682.4378 | BH16: 719.8596 | BI16: 787.2515 | BJ16: 831.5543 | BK16: 861.0934 | BL16: 899.3505 | BM16: 943.278 | BN16: 988.6248 | BO16: 1030.308 | BP16: 1160.099
A17: Uganda | B17: UGA | C17: Official exchange rate (LCU per US$, period average) | D17: PA.NUS.FCRF | E17: 0.07143 | F17: 0.07143 | G17: 0.07143 | H17: 0.07143 | I17: 0.07143 | J17: 0.07143 | K17: 0.07143 | L17: 0.07143 | M17: 0.07143 | N17: 0.07143 | O17: 0.07143 | P17: 0.07143 | Q17: 0.07143 | R17: 0.070214 | S17: 0.071359 | T17: 0.074219 | U17: 0.082662 | V17: 0.08259 | W17: 0.077357 | X17: 0.074828 | Y17: 0.07417 | Z17: 0.500523 | AA17: 0.940467 | AB17: 1.538625 | AC17: 3.597025 | AD17: 6.7202 | AE17: 14 | AF17: 42.84127 | AG17: 106.1358 | AH17: 223.0916 | AI17: 428.8547 | AJ17: 734.0099 | AK17: 1133.834 | AL17: 1195.017 | AM17: 979.4454 | AN17: 968.9167 | AO17: 1046.085 | AP17: 1083.009 | AQ17: 1240.306 | AR17: 1454.827 | AS17: 1644.475 | AT17: 1755.659 | AU17: 1797.551 | AV17: 1963.72 | AW17: 1810.305 | AX17: 1780.54 | AY17: 1831.452 | AZ17: 1723.492 | BA17: 1720.444 | BB17: 2030.488 | BC17: 2177.558 | BD17: 2522.802 | BE17: 2504.563 | BF17: 2586.89 | BG17: 2599.788 | BH17: 3240.645 | BI17: 3420.098 | BJ17: 3611.224 | BK17: 3727.069 | BL17: 3704.049 | BM17: 3718.249 | BN17: 3587.052 | BO17: 3689.817 | BP17: 3726.14
A19: GDP per capita, PPP (constant 2021 international $)
A20: Source: World Bank
A21: Country Name | B21: Country Code | C21: Indicator Name | D21: Indicator Code | E21: 1960 | F21: 1961 | G21: 1962 | H21: 1963 | I21: 1964 | J21: 1965 | K21: 1966 | L21: 1967 | M21: 1968 | N21: 1969 | O21: 1970 | P21: 1971 | Q21: 1972 | R21: 1973 | S21: 1974 | T21: 1975 | U21: 1976 | V21: 1977 | W21: 1978 | X21: 1979 | Y21: 1980 | Z21: 1981 | AA21: 1982 | AB21: 1983 | AC21: 1984 | AD21: 1985 | AE21: 1986 | AF21: 1987 | AG21: 1988 | AH21: 1989 | AI21: 1990 | AJ21: 1991 | AK21: 1992 | AL21: 1993 | AM21: 1994 | AN21: 1995 | AO21: 1996 | AP21: 1997 | AQ21: 1998 | AR21: 1999 | AS21: 2000 | AT21: 2001 | AU21: 2002 | AV21: 2003 | AW21: 2004 | AX21: 2005 | AY21: 2006 | AZ21: 2007 | BA21: 2008 | BB21: 2009 | BC21: 2010 | BD21: 2011 | BE21: 2012 | BF21: 2013 | BG21: 2014 | BH21: 2015 | BI21: 2016 | BJ21: 2017 | BK21: 2018 | BL21: 2019 | BM21: 2020 | BN21: 2021 | BO21: 2022 | BP21: 2023
A22: Kenya | B22: KEN | C22: GDP per capita, PPP (constant 2021 international $) | D22: NY.GDP.PCAP.PP.KD | AI22: 4128.8584 | AJ22: 4055.8709 | AK22: 3903.0975 | AL22: 3803.333 | AM22: 3792.6506 | AN22: 3850.0669 | AO22: 3902.6562 | AP22: 3817.7105 | AQ22: 3838.6923 | AR22: 3818.7044 | AS22: 3731.222 | AT22: 3756.733 | AU22: 3664.4099 | AV22: 3661.5842 | AW22: 3735.1341 | AX22: 3839.7449 | AY22: 3968.4489 | AZ22: 4116.4029 | BA22: 4004.871 | BB22: 4016.6123 | BC22: 4219.7079 | BD22: 4319.5639 | BE22: 4404.2447 | BF22: 4462.6578 | BG22: 4580.3912 | BH22: 4703.2977 | BI22: 4794.7142 | BJ22: 4871.5805 | BK22: 5043.1616 | BL22: 5197.2281 | BM22: 5079.9277 | BN22: 5360.3619 | BO22: 5513.8597 | BP22: 5699.8212
A23: Mozambique | B23: MOZ | C23: GDP per capita, PPP (constant 2021 international $) | D23: NY.GDP.PCAP.PP.KD | AI23: 539.02273 | AJ23: 554.82392 | AK23: 503.29684 | AL23: 543.05586 | AM23: 550.64079 | AN23: 537.73978 | AO23: 577.31178 | AP23: 628.24478 | AQ23: 676.93959 | AR23: 738.82866 | AS23: 726.44744 | AT23: 799.46174 | AU23: 854.51725 | AV23: 892.70924 | AW23: 941.0543 | AX23: 974.87698 | AY23: 1044.3723 | AZ23: 1095.4922 | BA23: 1140.5555 | BB23: 1176.3495 | BC23: 1220.2781 | BD23: 1269.5503 | BE23: 1330.3296 | BF23: 1374.8498 | BG23: 1435.9956 | BH23: 1495.9387 | BI23: 1517.9527 | BJ23: 1510.3943 | BK23: 1517.6418 | BL23: 1508.6356 | BM23: 1447.5714 | BN23: 1440.4597 | BO23: 1462.5693 | BP23: 1493.6631
A24: Malawi | B24: MWI | C24: GDP per capita, PPP (constant 2021 international $) | D24: NY.GDP.PCAP.PP.KD | AI24: 1086.3451 | AJ24: 1146.1138 | AK24: 1032.2681 | AL24: 1116.6589 | AM24: 1014.7199 | AN24: 1186.6939 | AO24: 1249.0998 | AP24: 1271.5409 | AQ24: 1294.0179 | AR24: 1304.0421 | AS24: 1294.4648 | AT24: 1201.2437 | AU24: 1192.0492 | AV24: 1228.4295 | AW24: 1261.2749 | AX24: 1267.3448 | AY24: 1290.2272 | AZ24: 1374.5697 | BA24: 1437.6162 | BB24: 1512.7416 | BC24: 1570.65 | BD24: 1601.5878 | BE24: 1586.4386 | BF24: 1625.9863 | BG24: 1670.2176 | BH24: 1670.2578 | BI24: 1666.1115 | BJ24: 1686.6739 | BK24: 1714.0907 | BL24: 1759.6301 | BM24: 1727.0488 | BN24: 1728.8254 | BO24: 1700.7051 | BP24: 1683.4586
A25: Rwanda | B25: RWA | C25: GDP per capita, PPP (constant 2021 international $) | D25: NY.GDP.PCAP.PP.KD | AI25: 1130.5159 | AJ25: 1077.6922 | AK25: 1115.4233 | AL25: 992.88051 | AM25: 579.97267 | AN25: 928.48139 | AO25: 886.48121 | AP25: 884.0368 | AQ25: 932.20668 | AR25: 961.24443 | AS25: 1028.8127 | AT25: 1100.638 | AU25: 1223.7577 | AV25: 1222.1446 | AW25: 1279.7297 | AX25: 1363.385 | AY25: 1450.0256 | AZ25: 1519.2304 | BA25: 1644.1108 | BB25: 1701.3164 | BC25: 1779.1089 | BD25: 1872.0483 | BE25: 1984.403 | BF25: 2029.2042 | BG25: 2103.7322 | BH25: 2236.0639 | BI25: 2312.3862 | BJ25: 2344.1561 | BK25: 2482.601 | BL25: 2652.9512 | BM25: 2502.7408 | BN25: 2709.4578 | BO25: 2863.5239 | BP25: 3029.5881
A26: Uganda | B26: UGA | C26: GDP per capita, PPP (constant 2021 international $) | D26: NY.GDP.PCAP.PP.KD | AI26: 1079.0107 | AJ26: 1102.2555 | AK26: 1101.7368 | AL26: 1152.9385 | AM26: 1186.4108 | AN26: 1287.5641 | AO26: 1366.7856 | AP26: 1395.2975 | AQ26: 1420.829 | AR26: 1486.3541 | AS26: 1485.733 | AT26: 1515.8831 | AU26: 1597.8181 | AV26: 1648.9848 | AW26: 1709.8925 | AX26: 1766.0927 | AY26: 1900.3503 | AZ26: 2000.6565 | BA26: 2112.154 | BB26: 2190.9903 | BC26: 2248.0118 | BD26: 2388.6766 | BE26: 2409.5957 | BF26: 2425.2443 | BG26: 2474.5152 | BH26: 2523.6572 | BI26: 2557.5798 | BJ26: 2547.0365 | BK26: 2617.0553 | BL26: 2692.5759 | BM26: 2681.1778 | BN26: 2688.2668 | BO26: 2728.5471 | BP26: 2792.5334
A29: Multidimensional poverty headcount ratio
A30: Source: World Bank
A31: Country Name | B31: Survey year | C31: Multidimensional poverty headcount ratio (%)
A32: Kenya | B32: 2015 | C32: 0.454
A33: Malawi | B33: 2019 | C33: 0.783
A34: Mozambique
A35: Rwanda | B35: 2016 | C35: 0.574
A36: Uganda | B36: 2019 | C36: 0.523
A38: Food security index
A39: Source: Economist Impact
A40: Country Name | B40: Reference year | C40: % of children stunted
A41: Kenya | B41: 2022 | C41: 0.194
A42: Malawi | B42: 2022 | C42: 0.37
A43: Mozambique | B43: 2022 | C43: 0.378
A44: Rwanda | B44: 2022 | C44: 0.326
A45: Uganda | B45: 2022 | C45: 0.279
A47: Population density
A48: Source: World Bank
A49: Country Name | B49: Country Code | C49: Indicator Name | D49: Indicator Code | E49: 1960 | F49: 1961 | G49: 1962 | H49: 1963 | I49: 1964 | J49: 1965 | K49: 1966 | L49: 1967 | M49: 1968 | N49: 1969 | O49: 1970 | P49: 1971 | Q49: 1972 | R49: 1973 | S49: 1974 | T49: 1975 | U49: 1976 | V49: 1977 | W49: 1978 | X49: 1979 | Y49: 1980 | Z49: 1981 | AA49: 1982 | AB49: 1983 | AC49: 1984 | AD49: 1985 | AE49: 1986 | AF49: 1987 | AG49: 1988 | AH49: 1989 | AI49: 1990 | AJ49: 1991 | AK49: 1992 | AL49: 1993 | AM49: 1994 | AN49: 1995 | AO49: 1996 | AP49: 1997 | AQ49: 1998 | AR49: 1999 | AS49: 2000 | AT49: 2001 | AU49: 2002 | AV49: 2003 | AW49: 2004 | AX49: 2005 | AY49: 2006 | AZ49: 2007 | BA49: 2008 | BB49: 2009 | BC49: 2010 | BD49: 2011 | BE49: 2012 | BF49: 2013 | BG49: 2014 | BH49: 2015 | BI49: 2016 | BJ49: 2017 | BK49: 2018 | BL49: 2019 | BM49: 2020 | BN49: 2021
A50: Kenya | B50: KEN | C50: Population density (people per sq. km of land area) | D50: EN.POP.DNST | F50: 14.1397 | G50: 14.69512 | H50: 15.2813 | I50: 15.89659 | J50: 16.54638 | K50: 17.22354 | L50: 17.92365 | M50: 18.64897 | N50: 19.3969 | O50: 20.15864 | P50: 20.90603 | Q50: 21.6518 | R50: 22.4205 | S50: 23.19983 | T50: 23.98691 | U50: 24.77821 | V50: 25.61294 | W50: 26.50916 | X50: 27.44599 | Y50: 28.44137 | Z50: 29.49356 | AA50: 30.59263 | AB50: 31.74871 | AC50: 32.95002 | AD50: 34.17817 | AE50: 35.42341 | AF50: 36.69061 | AG50: 37.9979 | AH50: 39.3362 | AI50: 40.69696 | AJ50: 42.02522 | AK50: 43.32102 | AL50: 44.61438 | AM50: 45.91795 | AN50: 47.22625 | AO50: 48.52187 | AP50: 49.83706 | AQ50: 51.19544 | AR50: 52.64984 | AS50: 54.20741 | AT50: 55.87438 | AU50: 57.59536 | AV50: 59.33008 | AW50: 61.13054 | AX50: 62.97749 | AY50: 64.87903 | AZ50: 66.83205 | BA50: 68.85282 | BB50: 70.92182 | BC50: 72.94847 | BD50: 74.91152 | BE50: 76.82786 | BF50: 78.70184 | BG50: 80.52828 | BH50: 82.31979 | BI50: 84.1527 | BJ50: 86.00368 | BK50: 87.7698 | BL50: 89.52358 | BM50: 91.34094 | BN50: 93.13282
A51: Mozambique | B51: MOZ | C51: Population density (people per sq. km of land area) | D51: EN.POP.DNST | F51: 8.796664 | G51: 8.978326 | H51: 9.16835 | I51: 9.36397 | J51: 9.568089 | K51: 9.778533 | L51: 9.994495 | M51: 10.21838 | N51: 10.45033 | O51: 10.69671 | P51: 10.9653 | Q51: 11.26756 | R51: 11.60211 | S51: 11.95888 | T51: 12.33975 | U51: 12.74093 | V51: 13.17884 | W51: 13.65895 | X51: 14.15072 | Y51: 14.51409 | Z51: 14.80202 | AA51: 15.13496 | AB51: 15.46749 | AC51: 15.8018 | AD51: 16.1246 | AE51: 16.41674 | AF51: 16.48668 | AG51: 16.47648 | AH51: 16.64285 | AI51: 16.91734 | AJ51: 17.24507 | AK51: 17.57023 | AL51: 18.06538 | AM51: 18.96395 | AN51: 19.83116 | AO51: 20.44756 | AP51: 21.00985 | AQ51: 21.52038 | AR51: 22.04773 | AS51: 22.59532 | AT51: 23.17037 | AU51: 23.77343 | AV51: 24.39883 | AW51: 25.04439 | AX51: 25.70146 | AY51: 26.36891 | AZ51: 27.06136 | BA51: 27.77992 | BB51: 28.53158 | BC51: 29.3417 | BD51: 30.21494 | BE51: 31.13967 | BF51: 32.11136 | BG51: 33.11211 | BH51: 34.13521 | BI51: 35.22024 | BJ51: 36.33033 | BK51: 37.41687 | BL51: 38.51267 | BM51: 39.6478 | BN51: 40.7908
A52: Malawi | B52: MWI | C52: Population density (people per sq. km of land area) | D52: EN.POP.DNST | F52: 39.3317 | G52: 40.29651 | H52: 41.29856 | I52: 42.32458 | J52: 43.37184 | K52: 44.45019 | L52: 45.56387 | M52: 46.70588 | N52: 47.86658 | O52: 49.0575 | P52: 50.30208 | Q52: 51.61199 | R52: 52.99363 | S52: 54.45693 | T52: 56.01363 | U52: 57.68165 | V52: 59.52176 | W52: 61.61232 | X52: 63.9493 | Y52: 66.47612 | Z52: 69.15455 | AA52: 71.95956 | AB52: 74.86548 | AC52: 77.84262 | AD52: 80.87694 | AE52: 83.8971 | AF52: 87.99314 | AG52: 92.85937 | AH52: 97.31539 | AI52: 101.1844 | AJ52: 104.2807 | AK52: 107.2913 | AL52: 108.7954 | AM52: 107.465 | AN52: 107.2636 | AO52: 109.3607 | AP52: 111.5049 | AQ52: 113.836 | AR52: 116.3975 | AS52: 119.1068 | AT52: 121.9646 | AU52: 124.9947 | AV52: 128.2135 | AW52: 131.6434 | AX52: 135.2954 | AY52: 139.142 | AZ52: 143.1424 | BA52: 147.321 | BB52: 151.6645 | BC52: 156.1139 | BD52: 160.6501 | BE52: 165.2657 | BF52: 169.97 | BG52: 174.7769 | BH52: 179.6663 | BI52: 184.6163 | BJ52: 189.6602 | BK52: 194.8227 | BL52: 200.1202 | BM52: 205.5267 | BN52: 210.9646
A53: Rwanda | B53: RWA | C53: Population density (people per sq. km of land area) | D53: EN.POP.DNST | F53: 123.4963 | G53: 126.5555 | H53: 129.36 | I53: 132.2919 | J53: 135.737 | K53: 139.6036 | L53: 143.8776 | M53: 148.4398 | N53: 153.1366 | O53: 157.9395 | P53: 162.7646 | Q53: 167.636 | R53: 172.6585 | S53: 177.8017 | T53: 183.0465 | U53: 188.4154 | V53: 193.8894 | W53: 199.5117 | X53: 205.6901 | Y53: 212.709 | Z53: 220.5904 | AA53: 229.1407 | AB53: 237.511 | AC53: 245.5099 | AD53: 254.0232 | AE53: 263.3889 | AF53: 273.0373 | AG53: 281.8798 | AH53: 289.5004 | AI53: 296.7151 | AJ53: 303.4325 | AK53: 310.3854 | AL53: 320.4191 | AM53: 272.909 | AN53: 230.5187 | AO53: 272.2136 | AP53: 310.7715 | AQ53: 320.8206 | AR53: 324.6691 | AS53: 328.7389 | AT53: 333.358 | AU53: 339.3719 | AV53: 347.3041 | AW53: 356.3783 | AX53: 365.8816 | AY53: 375.7627 | AZ53: 386.0222 | BA53: 396.5138 | BB53: 407.1235 | BC53: 417.8772 | BD53: 428.7366 | BE53: 439.4136 | BF53: 449.9939 | BG53: 460.8209 | BH53: 471.9481 | BI53: 483.6197 | BJ53: 495.7576 | BK53: 507.9776 | BL53: 520.2687 | BM53: 532.8886 | BN53: 545.6785
A54: Uganda | B54: UGA | C54: Population density (people per sq. km of land area) | D54: EN.POP.DNST | F54: 39.22947 | G54: 40.3825 | H54: 41.59458 | I54: 42.8645 | J54: 44.18726 | K54: 45.567 | L54: 47.01182 | M54: 48.52795 | N54: 50.08021 | O54: 51.63511 | P54: 53.13217 | Q54: 54.47957 | R54: 55.78349 | S54: 57.19772 | T54: 58.71057 | U54: 60.2834 | V54: 61.90507 | W54: 63.57039 | X54: 65.11942 | Y54: 66.48329 | Z54: 67.88228 | AA54: 69.46625 | AB54: 71.21231 | AC54: 73.15922 | AD54: 75.26608 | AE54: 77.50767 | AF54: 79.94703 | AG54: 82.52501 | AH54: 85.22368 | AI54: 88.01677 | AJ54: 90.94607 | AK54: 94.09922 | AL54: 97.40733 | AM54: 100.7208 | AN54: 103.5025 | AO54: 106.3489 | AP54: 109.4887 | AQ54: 112.7954 | AR54: 116.5069 | AS54: 120.2177 | AT54: 123.9344 | AU54: 127.8469 | AV54: 131.899 | AW54: 135.8595 | AX54: 139.8658 | AY54: 144.0029 | AZ54: 148.2899 | BA54: 152.6944 | BB54: 157.212 | BC54: 161.2893 | BD54: 166.047 | BE54: 170.9221 | BF54: 175.9105 | BG54: 181.2115 | BH54: 186.9008 | BI54: 193.2391 | BJ54: 200.1151 | BK54: 207.0387 | BL54: 214.1885 | BM54: 221.4473 | BN54: 228.6743
A56: Rural Access index
A57: Source: World Bank and Kenya Roads Board
A58: Locality | B58: Rural access index (%)
A59: Siaya | B59: 0.98
A60: Kenya | B60: 0.7
A61: Malawi | B61: 0.23
A62: Mozambique | B62: 0.2
A63: Rwanda | B63: 0.55
A64: Uganda | B64: 0.53
A66: PIP data
A67: Source: PIP
A68: Notes: in 2017 PPP
A69: region_name | B69: region_code | C69: country_name | D69: country_code | E69: reporting_year | F69: reporting_level | G69: survey_acronym | H69: survey_coverage | I69: survey_year | J69: welfare_type | K69: survey_comparability | L69: comparable_spell | M69: poverty_line | N69: headcount | O69: poverty_gap | P69: poverty_severity | Q69: watts | R69: mean | S69: median | T69: mld | U69: gini | V69: polarization | W69: decile1 | X69: decile2 | Y69: decile3 | Z69: decile4 | AA69: decile5 | AB69: decile6 | AC69: decile7 | AD69: decile8 | AE69: decile9 | AF69: decile10 | AG69: cpi | AH69: ppp | AI69: reporting_pop | AJ69: reporting_gdp | AK69: reporting_pce | AL69: is_interpolated | AM69: distribution_type | AN69: estimation_type | AO69: spl | AP69: spr
A70: Sub-Saharan Africa | B70: SSA | C70: Angola | D70: AGO | E70: 2018 | F70: national | G70: IDREA | H70: national | I70: 2018.17 | J70: consumption | K70: 2 | L70: 2018 | M70: 2.15 | N70: 0.31122 | O70: 0.119329 | P70: 0.06256 | Q70: 0.180669 | R70: 5.482073 | S70: 3.420502 | T70: 0.47789 | U70: 0.512721 | V70: 0.470982 | W70: 0.013295 | X70: 0.024281 | Y70: 0.033329 | Z70: 0.043429 | AA70: 0.055843 | AB70: 0.069814 | AC70: 0.088688 | AD70: 0.115687 | AE70: 0.15939 | AF70: 0.396244 | AG70: 1.231041 | AH70: 107.27 | AI70: 31457142 | AJ70: 2777.843 | AK70: 1495.341 | AL70: FALSE | AM70: micro | AN70: survey | AO70: 2.860251 | AP70: 0.422226
A71: Sub-Saharan Africa | B71: SSA | C71: Burundi | D71: BDI | E71: 2020 | F71: national | G71: EICVMB | H71: national | I71: 2020.15 | J71: consumption | K71: 2 | L71: 2020 | M71: 2.15 | N71: 0.620658 | O71: 0.234904 | P71: 0.115332 | Q71: 0.335573 | R71: 2.341324 | S71: 1.795875 | T71: 0.232365 | U71: 0.374565 | V71: 0.310079 | W71: 0.028756 | X71: 0.041799 | Y71: 0.050866 | Z71: 0.060824 | AA71: 0.071024 | AB71: 0.082381 | AC71: 0.096826 | AD71: 0.11716 | AE71: 0.151718 | AF71: 0.298645 | AG71: 1.048899 | AH71: 654.4216 | AI71: 12269875 | AJ71: 263.361 | AK71: 201.9599 | AL71: FALSE | AM71: micro | AN71: survey | AO71: 2.15 | AP71: 0.620658
A72: Sub-Saharan Africa | B72: SSA | C72: Benin | D72: BEN | E72: 2015 | F72: national | G72: EMICOV | H72: national | I72: 2015 | J72: consumption | K72: 1 | L72: 2011 - 2015 | M72: 2.15 | N72: 0.507093 | O72: 0.229842 | P72: 0.146344 | Q72: 0.417392 | R72: 3.003847 | S72: 2.123896 | T72: 0.446035 | U72: 0.477559 | V72: 0.383718 | W72: 0.010034 | X72: 0.022383 | Y72: 0.042682 | Z72: 0.053662 | AA72: 0.064635 | AB72: 0.076902 | AC72: 0.093287 | AD72: 0.115063 | AE72: 0.14511 | AF72: 0.37624 | AG72: 0.990478 | AH72: 219.4763 | AI72: 10932783 | AJ72: 1041.653 | AK72: 783.0327 | AL72: FALSE | AM72: micro | AN72: survey | AO72: 2.211948 | AP72: 0.523161
A73: Sub-Saharan Africa | B73: SSA | C73: Burkina Faso | D73: BFA | E73: 2018 | F73: national | G73: EHCVM | H73: national | I73: 2018.5 | J73: consumption | K73: 4 | L73: 2018 - 2021 | M73: 2.15 | N73: 0.312038 | O73: 0.084133 | P73: 0.031886 | Q73: 0.108093 | R73: 4.284381 | S73: 2.883932 | T73: 0.304067 | U73: 0.430167 | V73: 0.364042 | W73: 0.026191 | X73: 0.037193 | Y73: 0.04502 | Z73: 0.053109 | AA73: 0.062153 | AB73: 0.073366 | AC73: 0.088897 | AD73: 0.110656 | AE73: 0.150026 | AF73: 0.353389 | AG73: 1.03546 | AH73: 199.7414 | AI73: 20672181 | AJ73: 696.0446 | AK73: 458.5837 | AL73: FALSE | AM73: micro | AN73: survey | AO73: 2.591966 | AP73: 0.431955
A74: Sub-Saharan Africa | B74: SSA | C74: Botswana | D74: BWA | E74: 2015 | F74: national | G74: BMTHS | H74: national | I74: 2015.85 | J74: consumption | K74: 1 | L74: 2002 - 2015 | M74: 2.15 | N74: 0.154262 | O74: 0.041234 | P74: 0.016528 | Q74: 0.054412 | R74: 8.821087 | S74: 4.842955 | T74: 0.497053 | U74: 0.53325 | V74: 0.54851 | W74: 0.015319 | X74: 0.024151 | Y74: 0.03097 | Z74: 0.03904 | AA74: 0.04861 | AB74: 0.062274 | AC74: 0.081599 | AD74: 0.113067 | AE74: 0.17021 | AF74: 0.41476 | AG74: 0.964001 | AH74: 5.008663 | AI74: 2345329 | AJ74: 5869.738 | AK74: 2699.948 | AL74: FALSE | AM74: micro | AN74: survey | AO74: 3.571477 | AP74: 0.368493
A75: Sub-Saharan Africa | B75: SSA | C75: Central African Republic | D75: CAF | E75: 2021 | F75: national | G75: EHCVM | H75: national | I75: 2021 | J75: consumption | K75: 2 | L75: 2021 | M75: 2.15 | N75: 0.656665 | O75: 0.29749 | P75: 0.167422 | Q75: 0.461982 | R75: 2.240665 | S75: 1.566593 | T75: 0.314402 | U75: 0.430464 | V75: 0.390684 | W75: 0.021304 | X75: 0.03424 | Y75: 0.043906 | Z75: 0.053206 | AA75: 0.063852 | AB75: 0.077039 | AC75: 0.094644 | AD75: 0.119419 | AE75: 0.160944 | AF75: 0.331444 | AG75: 1.126138 | AH75: 306.8083 | AI75: 5457154 | AJ75: 370.9804 | AK75: 437.9715 | AL75: FALSE | AM75: micro | AN75: survey | AO75: 2.15 | AP75: 0.656665
A76: Sub-Saharan Africa | B76: SSA | C76: Côte d'Ivoire | D76: CIV | E76: 2021 | F76: national | G76: EHCVM | H76: national | I76: 2021.75 | J76: consumption | K76: 3 | L76: 2018 - 2021 | M76: 2.15 | N76: 0.097332 | O76: 0.018889 | P76: 0.005797 | Q76: 0.022968 | R76: 5.538418 | S76: 4.336595 | T76: 0.202706 | U76: 0.352754 | V76: 0.301685 | W76: 0.031491 | X76: 0.044063 | Y76: 0.053562 | Z76: 0.062767 | AA76: 0.0727 | AB76: 0.083995 | AC76: 0.098293 | AD76: 0.119711 | AE76: 0.15501 | AF76: 0.278409 | AG76: 1.072458 | AH76: 247.1344 | AI76: 27989969 | AJ76: 2333.353 | AK76: 1457.768 | AL76: FALSE | AM76: micro | AN76: survey | AO76: 3.318298 | AP76: 0.31851
A77: Sub-Saharan Africa | B77: SSA | C77: Cameroon | D77: CMR | E77: 2021 | F77: national | G77: ECAM-V | H77: national | I77: 2021.67 | J77: consumption | K77: 2 | L77: 2021 | M77: 2.15 | N77: 0.229922 | O77: 0.065891 | P77: 0.027072 | Q77: 0.087333 | R77: 5.373378 | S77: 3.908571 | T77: 0.303051 | U77: 0.421761 | V77: 0.405063 | W77: 0.021264 | X77: 0.032777 | Y77: 0.042216 | Z77: 0.053284 | AA77: 0.065948 | AB77: 0.080976 | AC77: 0.099446 | AD77: 0.12513 | AE77: 0.167465 | AF77: 0.311494 | AG77: 1.092621 | AH77: 236.9115 | AI77: 27678286 | AJ77: 1428.563 | AK77: 1064.669 | AL77: FALSE | AM77: micro | AN77: survey | AO77: 3.104286 | AP77: 0.384243
A78: Sub-Saharan Africa | B78: SSA | C78: Democratic Republic of the Congo | D78: COD | E78: 2020 | F78: national | G78: EGI-ODD | H78: national | I78: 2020 | J78: consumption | K78: 1 | L78: 2020 | M78: 2.15 | N78: 0.78942 | O78: 0.402777 | P78: 0.245831 | Q78: 0.662191 | R78: 1.747741 | S78: 1.179713 | T78: 0.341571 | U78: 0.447496 | V78: 0.376242 | W78: 0.020734 | X78: 0.033608 | Y78: 0.043297 | Z78: 0.052728 | AA78: 0.062418 | AB78: 0.074259 | AC78: 0.089523 | AD78: 0.112269 | AE78: 0.153316 | AF78: 0.357849 | AG78: 1.507206 | AH78: 630.6055 | AI78: 92853164 | AJ78: 487.4331 | AK78: 347.364 | AL78: FALSE | AM78: micro | AN78: survey | AO78: 2.15 | AP78: 0.78942
A79: Sub-Saharan Africa | B79: SSA | C79: Congo | D79: COG | E79: 2011 | F79: national | G79: ECOM | H79: national | I79: 2011.67 | J79: consumption | K79: 0 | L79: 2005 - 2011 | M79: 2.15 | N79: 0.353575 | O79: 0.137718 | P79: 0.070961 | Q79: 0.203308 | R79: 4.591497 | S79: 2.98038 | T79: 0.422273 | U79: 0.489387 | V79: 0.444321 | W79: 0.015604 | X79: 0.026352 | Y79: 0.035724 | Z79: 0.046536 | AA79: 0.059015 | AB79: 0.07269 | AC79: 0.090121 | AD79: 0.1166 | AE79: 0.158064 | AF79: 0.379293 | AG79: 0.871689 | AH79: 285.9693 | AI79: 4670673 | AJ79: 2320.34 | AK79: 834.1598 | AL79: FALSE | AM79: micro | AN79: survey | AO79: 2.64019 | AP79: 0.436663
A80: Sub-Saharan Africa | B80: SSA | C80: Comoros | D80: COM | E80: 2014 | F80: national | G80: EESIC | H80: national | I80: 2014 | J80: consumption | K80: 1 | L80: 2014 | M80: 2.15 | N80: 0.186437 | O80: 0.066578 | P80: 0.031926 | Q80: 0.094843 | R80: 6.423948 | S80: 4.389313 | T80: 0.364196 | U80: 0.453346 | V80: 0.441439 | W80: 0.016096 | X80: 0.028641 | Y80: 0.039645 | Z80: 0.051156 | AA80: 0.062486 | AB80: 0.076621 | AC80: 0.098235 | AD80: 0.123582 | AE80: 0.166871 | AF80: 0.336667 | AG80: 0.981893 | AH80: 213.5182 | AI80: 714612 | AJ80: 1336.49 | AK80: 1252.45 | AL80: FALSE | AM80: micro | AN80: survey | AO80: 3.344657 | AP80: 0.358765
A81: Sub-Saharan Africa | B81: SSA | C81: Cabo Verde | D81: CPV | E81: 2015 | F81: national | G81: IDRF | H81: national | I81: 2015 | J81: consumption | K81: 2 | L81: 2015 | M81: 2.15 | N81: 0.045642 | O81: 0.009667 | P81: 0.003249 | Q81: 0.012024 | R81: 9.503321 | S81: 6.727809 | T81: 0.301912 | U81: 0.423811 | V81: 0.393748 | W81: 0.022175 | X81: 0.034399 | Y81: 0.04362 | Z81: 0.053644 | AA81: 0.064786 | AB81: 0.078247 | AC81: 0.095383 | AD81: 0.120567 | AE81: 0.164157 | AF81: 0.323022 | AG81: 1.006385 | AH81: 47.61211 | AI81: 552166 | AJ81: 3169.079 | AK81: 1976.598 | AL81: FALSE | AM81: micro | AN81: survey | AO81: 4.513905 | AP81: 0.29072
A82: Sub-Saharan Africa | B82: SSA | C82: Ethiopia | D82: ETH | E82: 2015 | F82: national | G82: HICES | H82: national | I82: 2015.5 | J82: consumption | K82: 1 | L82: 1995 - 2015 | M82: 2.15 | N82: 0.269846 | O82: 0.076032 | P82: 0.031594 | Q82: 0.101029 | R82: 3.738986 | S82: 3.061885 | T82: 0.20627 | U82: 0.349931 | V82: 0.265602 | W82: 0.02889 | X82: 0.044562 | Y82: 0.055718 | Z82: 0.065207 | AA82: 0.0763 | AB82: 0.087166 | AC82: 0.097857 | AD82: 0.114191 | AE82: 0.145463 | AF82: 0.284648 | AG82: 0.863294 | AH82: 8.496417 | AI82: 104000000 | AJ82: 650.0305 | AK82: 451.299 | AL82: FALSE | AM82: micro | AN82: survey | AO82: 2.680942 | AP82: 0.410176
A83: Sub-Saharan Africa | B83: SSA | C83: Gabon | D83: GAB | E83: 2017 | F83: national | G83: EGEP | H83: national | I83: 2017 | J83: consumption | K83: 1 | L83: 2017 | M83: 2.15 | N83: 0.024686 | O83: 0.005801 | P83: 0.002337 | Q83: 0.007778 | R83: 12.33692 | S83: 9.673192 | T83: 0.250646 | U83: 0.380244 | V83: 0.351412 | W83: 0.022405 | X83: 0.038054 | Y83: 0.048519 | Z83: 0.059957 | AA83: 0.072078 | AB83: 0.08532 | AC83: 0.103324 | AD83: 0.126731 | AE83: 0.166351 | AF83: 0.27726 | AG83: 1 | AH83: 319.1603 | AI83: 2140215 | AJ83: 6893.384 | AK83: 2612.306 | AL83: FALSE | AM83: micro | AN83: survey | AO83: 5.986596 | AP83: 0.249855
A84: Sub-Saharan Africa | B84: SSA | C84: Ghana | D84: GHA | E84: 2016 | F84: national | G84: GLSS-VII | H84: national | I84: 2016.75 | J84: consumption | K84: 1 | L84: 1991 - 2016 | M84: 2.15 | N84: 0.252086 | O84: 0.093357 | P84: 0.048814 | Q84: 0.142737 | R84: 5.089204 | S84: 3.737927 | T84: 0.344042 | U84: 0.435209 | V84: 0.395128 | W84: 0.016053 | X84: 0.030642 | Y84: 0.042013 | Z84: 0.054235 | AA84: 0.066901 | AB84: 0.08107 | AC84: 0.098654 | AD84: 0.124348 | AE84: 0.163972 | AF84: 0.322112 | AG84: 0.972476 | AH84: 1.750992 | AI84: 30055272 | AJ84: 1728.097 | AK84: 1207.382 | AL84: FALSE | AM84: micro | AN84: survey | AO84: 3.018964 | AP84: 0.390661
A85: Sub-Saharan Africa | B85: SSA | C85: Guinea | D85: GIN | E85: 2018 | F85: national | G85: EHCVM | H85: national | I85: 2018.5 | J85: consumption | K85: 4 | L85: 2018 | M85: 2.15 | N85: 0.138201 | O85: 0.030877 | P85: 0.010417 | Q85: 0.03865 | R85: 4.398115 | S85: 3.803789 | T85: 0.144345 | U85: 0.29592 | V85: 0.256603 | W85: 0.034766 | X85: 0.0502 | Y85: 0.060307 | Z85: 0.070232 | AA85: 0.081058 | AB85: 0.092325 | AC85: 0.105911 | AD85: 0.123491 | AE85: 0.150856 | AF85: 0.230854 | AG85: 1.15028 | AH85: 3446.932 | AI85: 12716202 | AJ85: 910.6526 | AK85: 671.557 | AL85: FALSE | AM85: micro | AN85: survey | AO85: 3.051895 | AP85: 0.340482
A86: Sub-Saharan Africa | B86: SSA | C86: Gambia | D86: GMB | E86: 2020 | F86: national | G86: IHS | H86: national | I86: 2020.08 | J86: consumption | K86: 3 | L86: 2015 - 2020 | M86: 2.15 | N86: 0.172421 | O86: 0.045247 | P86: 0.017693 | Q86: 0.058966 | R86: 5.084616 | S86: 3.819652 | T86: 0.253372 | U86: 0.387572 | V86: 0.329004 | W86: 0.025926 | X86: 0.039858 | Y86: 0.049572 | Z86: 0.059365 | AA86: 0.069774 | AB86: 0.082103 | AC86: 0.097213 | AD86: 0.11935 | AE86: 0.150996 | AF86: 0.305844 | AG86: 1.21581 | AH86: 15.11425 | AI86: 2579269 | AJ86: 655.5761 | AK86: 544.2245 | AL86: FALSE | AM86: micro | AN86: survey | AO86: 3.059826 | AP86: 0.358722
A87: Sub-Saharan Africa | B87: SSA | C87: Guinea-Bissau | D87: GNB | E87: 2021 | F87: national | G87: EHCVM | H87: national | I87: 2021.75 | J87: consumption | K87: 4 | L87: 2018 - 2021 | M87: 2.15 | N87: 0.259629 | O87: 0.059465 | P87: 0.019461 | Q87: 0.07312 | R87: 3.88736 | S87: 3.11205 | T87: 0.180648 | U87: 0.334351 | V87: 0.297682 | W87: 0.033921 | X87: 0.045411 | Y87: 0.054573 | Z87: 0.064602 | AA87: 0.074746 | AB87: 0.086774 | AC87: 0.102218 | AD87: 0.121437 | AE87: 0.155047 | AF87: 0.26127 | AG87: 1.072176 | AH87: 232.1995 | AI87: 2094355 | AJ87: 613.8981 | AL87: FALSE | AM87: micro | AN87: survey | AO87: 2.706025 | AP87: 0.398611
A88: Sub-Saharan Africa | B88: SSA | C88: Kenya | D88: KEN | E88: 2015 | F88: national | G88: IHBS | H88: national | I88: 2015.67 | J88: consumption | K88: 3 | L88: 2005 - 2021 | M88: 2.15 | N88: 0.293651 | O88: 0.086358 | P88: 0.036862 | Q88: 0.117344 | R88: 4.246111 | S88: 3.098574 | T88: 0.279793 | U88: 0.407758 | V88: 0.359405 | W88: 0.024129 | X88: 0.037395 | Y88: 0.046667 | Z88: 0.055847 | AA88: 0.066524 | AB88: 0.079468 | AC88: 0.095219 | AD88: 0.119513 | AE88: 0.159622 | AF88: 0.315615 | AG88: 0.907895 | AH88: 41.63478 | AI88: 47550420 | AJ88: 1496.654 | AK88: 1130.224 | AL88: FALSE | AM88: micro | AN88: survey | AO88: 2.699287 | AP88: 0.424459
A89: Sub-Saharan Africa | B89: SSA | C89: Liberia | D89: LBR | E89: 2016 | F89: national | G89: HIES | H89: national | I89: 2016 | J89: consumption | K89: 1 | L89: 2014 - 2016 | M89: 2.15 | N89: 0.276177 | O89: 0.074764 | P89: 0.029057 | Q89: 0.097023 | R89: 3.883072 | S89: 3.095039 | T89: 0.206166 | U89: 0.352655 | V89: 0.30879 | W89: 0.029401 | X89: 0.042691 | Y89: 0.052907 | Z89: 0.063045 | AA89: 0.074134 | AB89: 0.086261 | AC89: 0.101024 | AD89: 0.122362 | AE89: 0.157208 | AF89: 0.270968 | AG89: 0.889524 | AH89: 47.99602 | AI89: 4706097 | AJ89: 675.0596 | AL89: FALSE | AM89: micro | AN89: survey | AO89: 2.697519 | AP89: 0.407823
A90: Sub-Saharan Africa | B90: SSA | C90: Lesotho | D90: LSO | E90: 2017 | F90: national | G90: CMSHBS | H90: national | I90: 2017.14 | J90: consumption | K90: 3 | L90: 2017 | M90: 2.15 | N90: 0.323999 | O90: 0.116292 | P90: 0.057461 | Q90: 0.168624 | R90: 4.643397 | S90: 3.237574 | T90: 0.354801 | U90: 0.448797 | V90: 0.448337 | W90: 0.017199 | X90: 0.029157 | Y90: 0.039011 | Z90: 0.049513 | AA90: 0.062699 | AB90: 0.079147 | AC90: 0.099884 | AD90: 0.125866 | AE90: 0.168542 | AF90: 0.328983 | AG90: 1.005504 | AH90: 5.243988 | AI90: 2174453 | AJ90: 1090.99 | AK90: 872.4615 | AL90: FALSE | AM90: micro | AN90: survey | AO90: 2.768787 | AP90: 0.430573
A91: Sub-Saharan Africa | B91: SSA | C91: Madagascar | D91: MDG | E91: 2012 | F91: national | G91: ENSOMD | H91: national | I91: 2012.73 | J91: consumption | K91: 3 | L91: 2001 - 2012 | M91: 2.15 | N91: 0.807301 | O91: 0.425858 | P91: 0.26362 | Q91: 0.706863 | R91: 1.590663 | S91: 1.118724 | T91: 0.307928 | U91: 0.426482 | V91: 0.366345 | W91: 0.021563 | X91: 0.035692 | Y91: 0.04557 | Z91: 0.054698 | AA91: 0.064833 | AB91: 0.076525 | AC91: 0.091669 | AD91: 0.115269 | AE91: 0.159315 | AF91: 0.334865 | AG91: 0.750794 | AH91: 962.9596 | AI91: 23420178 | AJ91: 452.205 | AK91: 337.5683 | AL91: FALSE | AM91: micro | AN91: survey | AO91: 2.15 | AP91: 0.807301
A92: Sub-Saharan Africa | B92: SSA | C92: Mali | D92: MLI | E92: 2021 | F92: national | G92: EHCVM | H92: national | I92: 2021.57 | J92: consumption | K92: 3 | L92: 2018 - 2021 | M92: 2.15 | N92: 0.208493 | O92: 0.045273 | P92: 0.014389 | Q92: 0.055269 | R92: 4.359942 | S92: 3.34881 | T92: 0.205207 | U92: 0.356536 | V92: 0.308612 | W92: 0.032295 | X92: 0.044036 | Y92: 0.053391 | Z92: 0.061701 | AA92: 0.071097 | AB92: 0.082521 | AC92: 0.097339 | AD92: 0.118847 | AE92: 0.155399 | AF92: 0.283376 | AG92: 1.065448 | AH92: 205.2734 | AI92: 22297489 | AJ92: 744.7604 | AK92: 576.3102 | AL92: FALSE | AM92: micro | AN92: survey | AO92: 2.824405 | AP92: 0.385491
A93: Sub-Saharan Africa | B93: SSA | C93: Mozambique | D93: MOZ | E93: 2019 | F93: national | G93: IOF | H93: national | I93: 2019.92 | J93: consumption | K93: 0 | L93: 1996 - 2019 | M93: 2.15 | N93: 0.745284 | O93: 0.376378 | P93: 0.231485 | Q93: 0.635327 | R93: 2.096122 | S93: 1.293979 | T93: 0.451608 | U93: 0.50454 | V93: 0.415777 | W93: 0.015912 | X93: 0.028574 | Y93: 0.037169 | Z93: 0.045919 | AA93: 0.055998 | AB93: 0.067931 | AC93: 0.08284 | AD93: 0.104722 | AE93: 0.1489 | AF93: 0.412034 | AG93: 1.102476 | AH93: 21.98802 | AI93: 31106827 | AJ93: 608.9636 | AL93: FALSE | AM93: micro | AN93: survey | AO93: 2.15 | AP93: 0.745284
A94: Sub-Saharan Africa | B94: SSA | C94: Mauritania | D94: MRT | E94: 2019 | F94: national | G94: EPCV | H94: national | I94: 2019.6 | J94: consumption | K94: 3 | L94: 2000 - 2019 | M94: 2.15 | N94: 0.053547 | O94: 0.013716 | P94: 0.005584 | Q94: 0.018153 | R94: 6.275556 | S94: 5.2767 | T94: 0.171692 | U94: 0.319968 | V94: 0.278616 | W94: 0.031322 | X94: 0.047159 | Y94: 0.057447 | Z94: 0.067558 | AA94: 0.078012 | AB94: 0.090089 | AC94: 0.104424 | AD94: 0.124159 | AE94: 0.153946 | AF94: 0.245883 | AG94: 1.073854 | AH94: 124.4526 | AI94: 4452702 | AJ94: 1635.84 | AK94: 1025.453 | AL94: FALSE | AM94: micro | AN94: survey | AO94: 3.78835 | AP94: 0.279043
A95: Sub-Saharan Africa | B95: SSA | C95: Mauritius | D95: MUS | E95: 2017 | F95: national | G95: HBS | H95: national | I95: 2017 | J95: consumption | K95: 0 | L95: 2006 - 2017 | M95: 2.15 | N95: 0.001253 | O95: 0.000148 | P95: 2.86e-05 | Q95: 0.000165 | R95: 16.50926 | S95: 12.73115 | T95: 0.226615 | U95: 0.367612 | V95: 0.290585 | W95: 0.029136 | X95: 0.043074 | Y95: 0.053298 | Z95: 0.062602 | AA95: 0.072064 | AB95: 0.082863 | AC95: 0.096271 | AD95: 0.114313 | AE95: 0.147697 | AF95: 0.298682 | AG95: 1 | AH95: 18.00942 | AI95: 1264887 | AJ95: 10247.7 | AK95: 7321.506 | AL95: FALSE | AM95: micro | AN95: survey | AO95: 7.515577 | AP95: 0.171468
A96: Sub-Saharan Africa | B96: SSA | C96: Malawi | D96: MWI | E96: 2019 | F96: national | G96: IHS-V | H96: national | I96: 2019.31 | J96: consumption | K96: 1 | L96: 2004 - 2019 | M96: 2.15 | N96: 0.700606 | O96: 0.293136 | P96: 0.152665 | Q96: 0.430292 | R96: 2.069363 | S96: 1.533903 | T96: 0.244964 | U96: 0.385432 | V96: 0.320792 | W96: 0.028504 | X96: 0.040992 | Y96: 0.050191 | Z96: 0.059323 | AA96: 0.068845 | AB96: 0.080383 | AC96: 0.094481 | AD96: 0.115452 | AE96: 0.152065 | AF96: 0.309764 | AG96: 1.262426 | AH96: 241.9305 | AI96: 19025351 | AJ96: 573.4001 | AL96: FALSE | AM96: micro | AN96: survey | AO96: 2.15 | AP96: 0.700606
A97: Sub-Saharan Africa | B97: SSA | C97: Namibia | D97: NAM | E97: 2015 | F97: national | G97: NHIES | H97: national | I97: 2015.27 | J97: consumption | K97: 1 | L97: 2003 - 2015 | M97: 2.15 | N97: 0.15617 | O97: 0.054375 | P97: 0.026096 | Q97: 0.077156 | R97: 11.65441 | S97: 5.684174 | T97: 0.642663 | U97: 0.590666 | V97: 0.624969 | W97: 0.009642 | X97: 0.017908 | Y97: 0.025025 | Z97: 0.033142 | AA97: 0.042754 | AB97: 0.055624 | AC97: 0.074254 | AD97: 0.104298 | AE97: 0.164853 | AF97: 0.472501 | AG97: 0.898743 | AH97: 6.898255 | AI97: 2293679 | AJ97: 4965.673 | AK97: 3412.02 | AL97: FALSE | AM97: micro | AN97: survey | AO97: 3.992087 | AP97: 0.362359
A98: Sub-Saharan Africa | B98: SSA | C98: Niger | D98: NER | E98: 2021 | F98: national | G98: EHCVM | H98: national | I98: 2021.5 | J98: consumption | K98: 5 | L98: 2018 - 2021 | M98: 2.15 | N98: 0.506138 | O98: 0.142683 | P98: 0.054336 | Q98: 0.183102 | R98: 2.689935 | S98: 2.131838 | T98: 0.176247 | U98: 0.328626 | V98: 0.252983 | W98: 0.037765 | X98: 0.04962 | Y98: 0.057773 | Z98: 0.065805 | AA98: 0.07465 | AB98: 0.083935 | AC98: 0.095375 | AD98: 0.112819 | AE98: 0.144168 | AF98: 0.27809 | AG98: 1.078229 | AH98: 245.1597 | AI98: 25730350 | AJ98: 507.7103 | AK98: 368.327 | AL98: FALSE | AM98: micro | AN98: survey | AO98: 2.215919 | AP98: 0.536161
A99: Sub-Saharan Africa | B99: SSA | C99: Nigeria | D99: NGA | E99: 2018 | F99: national | G99: LSS | H99: national | I99: 2018.75 | J99: consumption | K99: 5 | L99: 2018 | M99: 2.15 | N99: 0.308633 | O99: 0.089797 | P99: 0.036547 | Q99: 0.118601 | R99: 3.65593 | S99: 2.95327 | T99: 0.205496 | U99: 0.351277 | V99: 0.310844 | W99: 0.028844 | X99: 0.04223 | Y99: 0.052601 | Z99: 0.063297 | AA99: 0.074635 | AB99: 0.087468 | AC99: 0.102795 | AD99: 0.124163 | AE99: 0.156537 | AF99: 0.267432 | AG99: 1.209062 | AH99: 123.6724 | AI99: 202000000 | AJ99: 2512.08 | AL99: FALSE | AM99: micro | AN99: survey | AO99: 2.626635 | AP99: 0.426578
A100: Sub-Saharan Africa | B100: SSA | C100: Rwanda | D100: RWA | E100: 2016 | F100: national | G100: EICV-V | H100: national | I100: 2016.77 | J100: consumption | K100: 1 | L100: 2000 - 2016 | M100: 2.15 | N100: 0.520054 | O100: 0.183482 | P100: 0.08625 | Q100: 0.257086 | R100: 3.086796 | S100: 2.073805 | T100: 0.318572 | U100: 0.4371 | V100: 0.361875 | W100: 0.024358 | X100: 0.035878 | Y100: 0.044749 | Z100: 0.05335 | AA100: 0.062369 | AB100: 0.073249 | AC100: 0.087893 | AD100: 0.109909 | AE100: 0.151901 | AF100: 0.356344 | AG100: 0.976775 | AH100: 293.705 | AI100: 12161468 | AJ100: 758.937 | AK100: 601.9675 | AL100: FALSE | AM100: micro | AN100: survey | AO100: 2.186902 | AP100: 0.530063
A101: Sub-Saharan Africa | B101: SSA | C101: Sudan | D101: SDN | E101: 2014 | F101: national | G101: NBHS | H101: national | I101: 2014 | J101: consumption | K101: 1 | L101: 2014 | M101: 2.15 | N101: 0.152631 | O101: 0.036132 | P101: 0.012896 | Q101: 0.045994 | R101: 4.563742 | S101: 3.661623 | T101: 0.197039 | U101: 0.342432 | V101: 0.27548 | W101: 0.031741 | X101: 0.046535 | Y101: 0.055996 | Z101: 0.064665 | AA101: 0.074631 | AB101: 0.086334 | AC101: 0.099626 | AD101: 0.116737 | AE101: 0.145962 | AF101: 0.277774 | AG101: 0.591487 | AH101: 6.464017 | AI101: 37003245 | AJ101: 2253.633 | AK101: 1882.143 | AL101: FALSE | AM101: micro | AN101: survey | AO101: 2.980812 | AP101: 0.359166
A102: Sub-Saharan Africa | B102: SSA | C102: Senegal | D102: SEN | E102: 2021 | F102: national | G102: EHCVM | H102: national | I102: 2021.71 | J102: consumption | K102: 4 | L102: 2018 - 2021 | M102: 2.15 | N102: 0.099268 | O102: 0.01886 | P102: 0.005772 | Q102: 0.022883 | R102: 5.774327 | S102: 4.464661 | T102: 0.214701 | U102: 0.361577 | V102: 0.303626 | W102: 0.030212 | X102: 0.042782 | Y102: 0.05304 | Z102: 0.062168 | AA102: 0.072383 | AB102: 0.083614 | AC102: 0.098079 | AD102: 0.118095 | AE102: 0.151231 | AF102: 0.288395 | AG102: 1.097094 | AH102: 238.5777 | AI102: 17188928 | AJ102: 1443.326 | AK102: 968.7303 | AL102: FALSE | AM102: micro | AN102: survey | AO102: 3.38233 | AP102: 0.314656
A103: Sub-Saharan Africa | B103: SSA | C103: Sierra Leone | D103: SLE | E103: 2018 | F103: national | G103: SLIHS | H103: national | I103: 2018 | J103: consumption | K103: 1 | L103: 2003 - 2018 | M103: 2.15 | N103: 0.26062 | O103: 0.060404 | P103: 0.020104 | Q103: 0.074661 | R103: 3.885995 | S103: 2.95935 | T103: 0.208216 | U103: 0.356902 | V103: 0.288003 | W103: 0.033522 | X103: 0.045459 | Y103: 0.054191 | Z103: 0.062503 | AA103: 0.071065 | AB103: 0.081637 | AC103: 0.095304 | AD103: 0.114473 | AE103: 0.14786 | AF103: 0.293987 | AG103: 1.160295 | AH103: 2128.519 | AI103: 7861281 | AJ103: 617.5295 | AK103: 568.9407 | AL103: FALSE | AM103: micro | AN103: survey | AO103: 2.629675 | AP103: 0.411733
A104: Sub-Saharan Africa | B104: SSA | C104: South Sudan | D104: SSD | E104: 2016 | F104: national | G104: HFS-W3 | H104: national | I104: 2016.5 | J104: consumption | K104: 1 | L104: 2016 | M104: 2.15 | N104: 0.673273 | O104: 0.32024 | P104: 0.190897 | Q104: 0.52791 | R104: 2.15008 | S104: 1.520812 | T104: 0.346242 | U104: 0.441441 | V104: 0.405592 | W104: 0.017112 | X104: 0.03107 | Y104: 0.042256 | Z104: 0.053268 | AA104: 0.063998 | AB104: 0.077962 | AC104: 0.095284 | AD104: 0.123114 | AE104: 0.164742 | AF104: 0.331193 | AG104: 0.07038 | AH104: 34.92003 | AI104: 10862166 | AJ104: 926.102 | AL104: FALSE | AM104: imputed | AN104: survey | AO104: 2.15 | AP104: 0.673273
A105: Sub-Saharan Africa | B105: SSA | C105: Sao Tome and Principe | D105: STP | E105: 2017 | F105: national | G105: IOF | H105: national | I105: 2017 | J105: consumption | K105: 2 | L105: 2017 | M105: 2.15 | N105: 0.157236 | O105: 0.038994 | P105: 0.015114 | Q105: 0.051023 | R105: 5.451495 | S105: 3.998577 | T105: 0.277224 | U105: 0.407295 | V105: 0.333438 | W105: 0.025659 | X105: 0.03868 | Y105: 0.047479 | Z105: 0.056445 | AA105: 0.067044 | AB105: 0.078797 | AC105: 0.093456 | AD105: 0.113541 | AE105: 0.150794 | AF105: 0.328105 | AG105: 1000 | AH105: 11.42892 | AI105: 208036 | AJ105: 1368.545 | AL105: FALSE | AM105: micro | AN105: survey | AO105: 3.149289 | AP105: 0.362356
A106: Sub-Saharan Africa | B106: SSA | C106: Eswatini | D106: SWZ | E106: 2016 | F106: national | G106: HIES | H106: national | I106: 2016.17 | J106: consumption | K106: 1 | L106: 2000 - 2016 | M106: 2.15 | N106: 0.360798 | O106: 0.127577 | P106: 0.061863 | Q106: 0.181786 | R106: 5.632314 | S106: 2.95373 | T106: 0.521872 | U106: 0.545798 | V106: 0.574485 | W106: 0.014067 | X106: 0.022923 | Y106: 0.030128 | Z106: 0.037619 | AA106: 0.047068 | AB106: 0.060068 | AC106: 0.077798 | AD106: 0.107853 | AE106: 0.175162 | AF106: 0.427313 | AG106: 0.951387 | AH106: 6.117729 | AI106: 1144031 | AJ106: 3594.167 | AK106: 2326.617 | AL106: FALSE | AM106: micro | AN106: survey | AO106: 2.626865 | AP106: 0.445975
A107: Sub-Saharan Africa | B107: SSA | C107: Seychelles | D107: SYC | E107: 2018 | F107: national | G107: HBS | H107: national | I107: 2018.08 | J107: income | K107: 2 | L107: 2013 - 2018 | M107: 2.15 | N107: 0.00511 | O107: 0.00113 | P107: 0.000338 | Q107: 0.001351 | R107: 22.25156 | S107: 19.49796 | T107: 0.184474 | U107: 0.321253 | V107: 0.281675 | W107: 0.025766 | X107: 0.044641 | Y107: 0.057429 | Z107: 0.068978 | AA107: 0.081124 | AB107: 0.095003 | AC107: 0.10976 | AD107: 0.126285 | AE107: 0.151529 | AF107: 0.239485 | AG107: 1.03875 | AH107: 9.027125 | AI107: 96831.04 | AJ107: 16110.99 | AK107: 5448.093 | AL107: FALSE | AM107: micro | AN107: survey | AO107: 10.89898 | AP107: 0.174178
A108: Sub-Saharan Africa | B108: SSA | C108: Chad | D108: TCD | E108: 2022 | F108: national | G108: EHCVM | H108: national | I108: 2022 | J108: consumption | K108: 1 | L108: 2018 - 2022 | M108: 2.15 | N108: 0.308452 | O108: 0.084654 | P108: 0.033921 | Q108: 0.112019 | R108: 3.884317 | S108: 3.106669 | T108: 0.232331 | U108: 0.373577 | V108: 0.300917 | W108: 0.02806 | X108: 0.040829 | Y108: 0.050338 | Z108: 0.059533 | AA108: 0.074286 | AB108: 0.084714 | AC108: 0.097338 | AD108: 0.116069 | AE108: 0.153204 | AF108: 0.29563 | AG108: 1.07593 | AH108: 237.6564 | AI108: 17723315 | AJ108: 590.3052 | AK108: 465.8088 | AL108: FALSE | AM108: micro | AN108: survey | AO108: 2.703334 | AP108: 0.413657
...

Sheet IHME
A1: Source: IHME
A2: Raw data
A3: Condition | B3: Sex | C3: Age | D3: Location | E3: Measure | F3: Unit | G3: Forecast Scenario | H3: Year | I3: Value | J3: Lower | K3: Upper | L3: Data Suite
A4: All causes | B4: Both | C4: 28 to 364 days (post neonatal) | D4: Uganda | E4: Deaths | F4: Number | G4: Past estimate | H4: 2019 | I4: 28448.26 | J4: 24251.59 | K4: 33459.28 | L4: GBD
A5: All causes | B5: Both | C5: 1 to 4 | D5: Uganda | E5: Deaths | F5: Number | G5: Past estimate | H5: 2019 | I5: 27016.01 | J5: 21030.81 | K5: 35004.1 | L5: GBD
A6: Lower respiratory infections | B6: Both | C6: 28 to 364 days (post neonatal) | D6: Uganda | E6: Deaths | F6: Number | G6: Past estimate | H6: 2019 | I6: 2436.874 | J6: 1518.843 | K6: 3493.978 | L6: GBD
A7: Lower respiratory infections | B7: Both | C7: 1 to 4 | D7: Uganda | E7: Deaths | F7: Number | G7: Past estimate | H7: 2019 | I7: 2469.907 | J7: 1381.809 | K7: 3888.186 | L7: GBD
A8: Meningitis | B8: Both | C8: 28 to 364 days (post neonatal) | D8: Uganda | E8: Deaths | F8: Number | G8: Past estimate | H8: 2019 | I8: 927.6192 | J8: 516.9244 | K8: 1533.717 | L8: GBD
A9: Meningitis | B9: Both | C9: 1 to 4 | D9: Uganda | E9: Deaths | F9: Number | G9: Past estimate | H9: 2019 | I9: 896.3644 | J9: 467.2696 | K9: 1664.267 | L9: GBD
A10: Diphtheria | B10: Both | C10: 28 to 364 days (post neonatal) | D10: Uganda | E10: Deaths | F10: Number | G10: Past estimate | H10: 2019 | I10: 5.163541 | J10: 1.296665 | K10: 12.31983 | L10: GBD
A11: Diphtheria | B11: Both | C11: 1 to 4 | D11: Uganda | E11: Deaths | F11: Number | G11: Past estimate | H11: 2019 | I11: 12.94622 | J11: 3.668091 | K11: 30.72355 | L11: GBD
A12: Whooping cough | B12: Both | C12: 28 to 364 days (post neonatal) | D12: Uganda | E12: Deaths | F12: Number | G12: Past estimate | H12: 2019 | I12: 890.2326 | J12: 61.84167 | K12: 2740.03 | L12: GBD
A13: Whooping cough | B13: Both | C13: 1 to 4 | D13: Uganda | E13: Deaths | F13: Number | G13: Past estimate | H13: 2019 | I13: 1062.497 | J13: 75.01534 | K13: 3218.377 | L13: GBD
A14: Tetanus | B14: Both | C14: 28 to 364 days (post neonatal) | D14: Uganda | E14: Deaths | F14: Number | G14: Past estimate | H14: 2019 | I14: 5.73964 | J14: 0.786128 | K14: 21.46817 | L14: GBD
A15: Tetanus | B15: Both | C15: 1 to 4 | D15: Uganda | E15: Deaths | F15: Number | G15: Past estimate | H15: 2019 | I15: 5.467925 | J15: 0.738731 | K15: 22.12722 | L15: GBD
... A51: Malaria | B51: Both | C51: 1 to 4 | D51: Bauchi | E51: Deaths | F51: Number | G51: Past estimate | H51: 2019 | I51: 4387.199 | J51: 1436.107 | K51: 9890.638 | L51: GBD

Sheet UNICEF
A1: Child Mortality Estimates
A2: Country-specific Under-five mortality rate
A4: Estimates generated by the UN Inter-agency Group for Child Mortality Estimation (UN IGME) in 2023
A5: Downloaded from http://data.unicef.org
A7: Prepared by the Data and Analytics Section; Division of Data, Analytics, Planning and Monitoring, UNICEF
A8: Contact us: data@unicef.org
A10: Last update: 10 January 2023
A11: ISO.Code | B11: Country.Name | C11: SDG.Region | D11: SDG.Subregion | E11: UNICEF.Region | F11: UNICEF.Programme.Region | G11: Uncertainty.Bounds* | H11: 2013 | I11: =H11+1 -> 2014 | J11: =I11+1 -> 2015 | K11: =J11+1 -> 2016 | L11: =K11+1 -> 2017 | M11: =L11+1 -> 2018 | N11: =M11+1 -> 2019 | O11: =N11+1 -> 2020 | P11: =O11+1 -> 2021 | ... R11: =Q11+1 -> 2023
A12: AFG | B12: Afghanistan | C12: Central and Southern Asia | D12: Southern Asia | E12: South Asia | F12: South Asia | G12: Median | H12: 78.16 | I12: 75.2827 | J12: 72.677 | K12: 70.2342 | L12: 67.9116 | M12: 65.7521 | N12: 63.6159 | O12: 61.558 | P12: 59.6076 | Q12: 57.6797 | R12: 57.6797
A13: AGO | B13: Angola | C13: Sub-Saharan Africa | E13: Eastern and Southern Africa | F13: Eastern and Southern Africa | G13: Median | H13: 97.9462 | I13: 92.5325 | J13: 87.8809 | K13: 83.9762 | L13: 80.3623 | M13: 77.1449 | N13: 74.1864 | O13: 71.5188 | P13: 69.1266 | Q13: 66.8738 | R13: 66.8738
A14: AIA | B14: Anguilla | C14: Latin America and the Caribbean | E14: Latin America and Caribbean | F14: Latin America and Caribbean | G14: Median | H14: 7.8322 | I14: 7.6343 | J14: 7.4146 | K14: 7.1848 | L14: 6.943 | M14: 6.7169 | N14: 6.4986 | O14: 6.2721 | P14: 6.068 | Q14: 5.8746 | R14: 5.8746
A15: ALB | B15: Albania | C15: Europe and Northern America | D15: Europe | E15: Eastern Europe and Central Asia | F15: Europe and Central Asia | G15: Median | H15: 10.4684 | I15: 9.9279 | J15: 9.5754 | K15: 9.4004 | L15: 9.3338 | M15: 9.3429 | N15: 9.3854 | O15: 9.4282 | P15: 9.4574 | Q15: 9.438 | R15: 9.438
A16: AND | B16: Andorra | C16: Europe and Northern America | D16: Europe | E16: Western Europe | F16: Non-programme countries | G16: Median | H16: 3.9354 | I16: 3.7511 | J16: 3.5579 | K16: 3.3923 | L16: 3.2428 | M16: 3.1145 | N16: 2.9907 | O16: 2.8819 | P16: 2.7801 | Q16: 2.6877 | R16: 2.6877
A17: ARE | B17: United Arab Emirates | C17: Northern Africa and Western Asia | D17: Western Asia | E17: Middle East and North Africa | F17: Middle East and North Africa | G17: Median | H17: 8.1639 | I17: 7.9181 | J17: 7.644 | K17: 7.3373 | L17: 7.0054 | M17: 6.6521 | N17: 6.2931 | O17: 5.94 | P17: 5.6078 | Q17: 5.3054 | R17: 5.3054
A18: ARG | B18: Argentina | C18: Latin America and the Caribbean | E18: Latin America and Caribbean | F18: Latin America and Caribbean | G18: Median | H18: 12.7531 | I18: 12.2296 | J18: 11.7591 | K18: 11.3519 | L18: 10.9829 | M18: 10.645 | N18: 10.3151 | O18: 10.0163 | P18: 9.7176 | Q18: 9.4352 | R18: 9.4352
A19: ARM | B19: Armenia | C19: Northern Africa and Western Asia | D19: Western Asia | E19: Eastern Europe and Central Asia | F19: Europe and Central Asia | G19: Median | H19: 15.98 | I19: 15.2023 | J19: 14.4707 | K19: 13.7673 | L19: 13.1195 | M19: 12.4972 | N19: 11.9014 | O19: 11.3379 | P19: 10.7953 | Q19: 10.2829 | R19: 10.2829
A20: ATG | B20: Antigua and Barbuda | C20: Latin America and the Caribbean | E20: Latin America and Caribbean | F20: Latin America and Caribbean | G20: Median | H20: 11.2927 | I20: 11.1129 | J20: 10.9313 | K20: 10.7557 | L20: 10.5878 | M20: 10.4095 | N20: 10.211 | O20: 9.9938 | P20: 9.7559 | Q20: 9.5043 | R20: 9.5043
A21: AUS | B21: Australia | C21: Oceania | D21: Australia and New Zealand | E21: East Asia and Pacific | F21: Non-programme countries | G21: Median | H21: 4.127 | I21: 3.9807 | J21: 3.8801 | K21: 3.8199 | L21: 3.7935 | M21: 3.7861 | N21: 3.783 | O21: 3.7783 | P21: 3.7716 | Q21: 3.7558 | R21: 3.7558
A22: AUT | B22: Austria | C22: Europe and Northern America | D22: Europe | E22: Western Europe | F22: Non-programme countries | G22: Median | H22: 3.9126 | I22: 3.7995 | J22: 3.7136 | K22: 3.6483 | L22: 3.5959 | M22: 3.5459 | N22: 3.4872 | O22: 3.4123 | P22: 3.3169 | Q22: 3.2031 | R22: 3.2031
A23: AZE | B23: Azerbaijan | C23: Northern Africa and Western Asia | D23: Western Asia | E23: Eastern Europe and Central Asia | F23: Europe and Central Asia | G23: Median | H23: 30.5338 | I23: 28.4881 | J23: 26.5923 | K23: 24.7612 | L23: 23.1664 | M23: 21.7982 | N23: 20.6517 | O23: 19.7052 | P23: 18.8444 | Q23: 18.0679 | R23: 18.0679
A24: BDI | B24: Burundi | C24: Sub-Saharan Africa | E24: Eastern and Southern Africa | F24: Eastern and Southern Africa | G24: Median | H24: 75.2671 | I24: 71.049 | J24: 67.317 | K24: 64.0082 | L24: 61.0979 | M24: 58.5842 | N24: 56.3287 | O24: 54.2285 | P24: 52.3188 | Q24: 50.4931 | R24: 50.4931
A25: BEL | B25: Belgium | C25: Europe and Northern America | D25: Europe | E25: Western Europe | F25: Non-programme countries | G25: Median | H25: 4.2182 | I25: 4.1547 | J25: 4.1052 | K25: 4.0672 | L25: 4.0308 | M25: 3.9854 | N25: 3.9287 | O25: 3.8606 | P25: 3.7812 | Q25: 3.6947 | R25: 3.6947
A26: BEN | B26: Benin | C26: Sub-Saharan Africa | E26: West and Central Africa | F26: West and Central Africa | G26: Median | H26: 101.8625 | I26: 99.6344 | J26: 97.3959 | K26: 95.2118 | L26: 92.9918 | M26: 90.7155 | N26: 88.3078 | O26: 85.7602 | P26: 83.2989 | Q26: 80.7756 | R26: 80.7756
A27: BFA | B27: Burkina Faso | C27: Sub-Saharan Africa | E27: West and Central Africa | F27: West and Central Africa | G27: Median | H27: 107.8022 | I27: 104.0339 | J27: 100.413 | K27: 96.8682 | L27: 93.5708 | M27: 90.2826 | N27: 87.2745 | O27: 84.2622 | P27: 81.4061 | Q27: 78.7814 | R27: 78.7814
A28: BGD | B28: Bangladesh | C28: Central and Southern Asia | D28: Southern Asia | E28: South Asia | F28: South Asia | G28: Median | H28: 42.3606 | I28: 40.4014 | J28: 38.5389 | K28: 36.787 | L28: 35.1339 | M28: 33.6067 | N28: 32.2193 | O28: 30.9655 | P28: 29.8227 | Q28: 28.7752 | R28: 28.7752
A29: BGR | B29: Bulgaria | C29: Europe and Northern America | D29: Europe | E29: Eastern Europe and Central Asia | F29: Europe and Central Asia | G29: Median | H29: 9.2421 | I29: 8.676 | J29: 8.1593 | K29: 7.704 | L29: 7.3181 | M29: 6.9933 | N29: 6.7163 | O29: 6.4759 | P29: 6.2709 | Q29: 6.0985 | R29: 6.0985
A30: BHR | B30: Bahrain | C30: Northern Africa and Western Asia | D30: Western Asia | E30: Middle East and North Africa | F30: Middle East and North Africa | G30: Median | H30: 7.9475 | I30: 7.7687 | J30: 7.6075 | K30: 7.4558 | L30: 7.3005 | M30: 7.1535 | N30: 7.0068 | O30: 6.8595 | P30: 6.6946 | Q30: 6.5187 | R30: 6.5187
A31: BHS | B31: Bahamas | C31: Latin America and the Caribbean | E31: Latin America and Caribbean | F31: Non-programme countries | G31: Median | H31: 14.4432 | I31: 14.1858 | J31: 13.9764 | K31: 13.7983 | L31: 13.6593 | M31: 13.5479 | N31: 23.508 | O31: 13.3029 | P31: 13.1212 | Q31: 12.9071 | R31: 12.9071
A32: BIH | B32: Bosnia and Herzegovina | C32: Europe and Northern America | D32: Europe | E32: Eastern Europe and Central Asia | F32: Europe and Central Asia | G32: Median | H32: 6.4095 | I32: 6.3682 | J32: 6.3526 | K32: 6.3572 | L32: 6.3602 | M32: 6.3425 | N32: 6.303 | O32: 6.2358 | P32: 6.1431 | Q32: 6.0314 | R32: 6.0314
A33: BLR | B33: Belarus | C33: Europe and Northern America | D33: Europe | E33: Eastern Europe and Central Asia | F33: Europe and Central Asia | G33: Median | H33: 4.5739 | I33: 4.3231 | J33: 4.0869 | K33: 3.8526 | L33: 3.6142 | M33: 3.3702 | N33: 3.129 | O33: 2.9112 | P33: 2.7256 | Q33: 2.5742 | R33: 2.5742
A34: BLZ | B34: Belize | C34: Latin America and the Caribbean | E34: Latin America and Caribbean | F34: Latin America and Caribbean | G34: Median | H34: 17.0529 | I34: 16.3754 | J34: 15.6664 | K34: 14.9447 | L34: 14.2268 | M34: 13.5205 | N34: 12.8396 | O34: 12.1742 | P34: 11.5413 | Q34: 10.946 | R34: 10.946
A35: BOL | B35: Bolivia (Plurinational State of) | C35: Latin America and the Caribbean | E35: Latin America and Caribbean | F35: Latin America and Caribbean | G35: Median | H35: 35.4311 | I35: 33.5548 | J35: 31.869 | K35: 30.4187 | L35: 29.0862 | M35: 27.895 | N35: 26.7896 | O35: 25.7504 | P35: 24.7963 | Q35: 23.911 | R35: 23.911
A36: BRA | B36: Brazil | C36: Latin America and the Caribbean | E36: Latin America and Caribbean | F36: Latin America and Caribbean | G36: Median | H36: 16.7152 | I36: 16.2765 | J36: 15.9094 | K36: 16.6889 | L36: 15.3062 | M36: 15.0392 | N36: 14.7841 | O36: 14.5295 | P36: 14.2751 | Q36: 14.0249 | R36: 14.0249
A37: BRB | B37: Barbados | C37: Latin America and the Caribbean | E37: Latin America and Caribbean | F37: Latin America and Caribbean | G37: Median | H37: 13.8742 | I37: 13.6335 | J37: 13.3435 | K37: 13.0368 | L37: 12.6735 | M37: 12.3307 | N37: 11.9628 | O37: 11.5861 | P37: 11.2419 | Q37: 10.8713 | R37: 10.8713
A38: BRN | B38: Brunei Darussalam | C38: Eastern and South-Eastern Asia | D38: South-Eastern Asia | E38: East Asia and Pacific | F38: Non-programme countries | G38: Median | H38: 9.8602 | I38: 9.9008 | J38: 9.9237 | K38: 9.9253 | L38: 9.9269 | M38: 9.9073 | N38: 9.8802 | O38: 9.8464 | P38: 9.8053 | Q38: 9.7421 | R38: 9.7421
A39: BTN | B39: Bhutan | C39: Central and Southern Asia | D39: Southern Asia | E39: South Asia | F39: South Asia | G39: Median | H39: 33.6642 | I39: 32.043 | J39: 30.6738 | K39: 29.3982 | L39: 28.234 | M39: 27.208 | N39: 26.275 | O39: 25.3774 | P39: 24.5105 | Q39: 23.7139 | R39: 23.7139
A40: BWA | B40: Botswana | C40: Sub-Saharan Africa | E40: Eastern and Southern Africa | F40: Eastern and Southern Africa | G40: Median | H40: 51.2744 | I40: 50.3747 | J40: 48.5889 | K40: 47.3697 | L40: 44.2994 | M40: 43.6725 | N40: 42.6435 | O40: 41.3318 | P40: 39.9443 | Q40: 38.735 | R40: 38.735
A41: CAF | B41: Central African Republic | C41: Sub-Saharan Africa | E41: West and Central Africa | F41: West and Central Africa | G41: Median | H41: 120.1877 | I41: 117.6786 | J41: 114.7584 | K41: 111.9158 | L41: 110.1947 | M41: 108.0203 | N41: 105.2874 | O41: 102.4301 | P41: 99.3472 | Q41: 96.7819 | R41: 96.7819
A42: CAN | B42: Canada | C42: Europe and Northern America | D42: Northern America | E42: North America | F42: Non-programme countries | G42: Median | H42: 5.5073 | I42: 5.4362 | J42: 5.3703 | K42: 5.3095 | L42: 5.2515 | M42: 5.1953 | N42: 5.1381 | O42: 5.0785 | P42: 5.0156 | Q42: 4.941 | R42: 4.941
A43: CHE | B43: Switzerland | C43: Europe and Northern America | D43: Europe | E43: Western Europe | F43: Non-programme countries | G43: Median | H43: 4.3878 | I43: 4.332 | J43: 4.2693 | K43: 4.2026 | L43: 4.1366 | M43: 4.0809 | N43: 4.0423 | O43: 4.0216 | P43: 4.0187 | Q43: 4.0237 | R43: 4.0237
A44: CHL | B44: Chile | C44: Latin America and the Caribbean | E44: Latin America and Caribbean | F44: Latin America and Caribbean | G44: Median | H44: 8.2498 | I44: 8.1082 | J44: 7.9593 | K44: 7.7975 | L44: 7.6122 | M44: 7.399 | N44: 7.1479 | O44: 6.8559 | P44: 6.5672 | Q44: 6.2903 | R44: 6.2903
A45: CHN | B45: China | C45: Eastern and South-Eastern Asia | D45: Eastern Asia | E45: East Asia and Pacific | F45: East Asia and Pacific | G45: Median | H45: 12.461 | I45: 11.5432 | J45: 10.7048 | K45: 9.9459 | L45: 9.2474 | M45: 8.6073 | N45: 8.0281 | O45: 7.5074 | P45: 7.0309 | Q45: 6.5962 | R45: 6.5962
A46: CIV | B46: Côte d'Ivoire | C46: Sub-Saharan Africa | E46: West and Central Africa | F46: West and Central Africa | G46: Median | H46: 92.8243 | I46: 89.4002 | J46: 86.3145 | K46: 83.8387 | L46: 81.4684 | M46: 78.8512 | N46: 76.0645 | O46: 73.7512 | P46: 71.5055 | Q46: 69.3736 | R46: 69.3736
A47: CMR | B47: Cameroon | C47: Sub-Saharan Africa | E47: West and Central Africa | F47: West and Central Africa | G47: Median | H47: 97.4974 | I47: 93.4346 | J47: 89.3401 | K47: 85.8953 | L47: 82.7061 | M47: 79.7869 | N47: 77.3487 | O47: 74.8864 | P47: 72.1752 | Q47: 69.8341 | R47: 69.8341
A48: COD | B48: Democratic Republic of the Congo | C48: Sub-Saharan Africa | E48: West and Central Africa | F48: West and Central Africa | G48: Median | H48: 102.0691 | I48: 98.5928 | J48: 95.5046 | K48: 92.4485 | L48: 89.5488 | M48: 86.5327 | N48: 83.7509 | O48: 80.8046 | P48: 78.1538 | Q48: 75.55 | R48: 75.55
A49: COG | B49: Congo | C49: Sub-Saharan Africa | E49: West and Central Africa | F49: West and Central Africa | G49: Median | H49: 56.4255 | I49: 54.617 | J49: 52.8683 | K49: 51.0489 | L49: 49.3424 | M49: 47.784 | N49: 52.4439 | O49: 44.6569 | P49: 43.1935 | Q49: 41.6454 | R49: 41.6454
A50: COK | B50: Cook Islands | C50: Oceania | D50: Oceania (exc. Australia and New Zealand) | E50: East Asia and Pacific | F50: East Asia and Pacific | G50: Median | H50: 9.493 | I50: 9.1268 | J50: 8.8138 | K50: 8.5027 | L50: 8.2145 | M50: 7.9473 | N50: 7.6679 | O50: 7.4215 | P50: 7.1644 | Q50: 6.9403 | R50: 6.9403
A51: COL | B51: Colombia | C51: Latin America and the Caribbean | E51: Latin America and Caribbean | F51: Latin America and Caribbean | G51: Median | H51: 16.6213 | I51: 16.0996 | J51: 15.6039 | K51: 15.0953 | L51: 14.6302 | M51: 14.1526 | N51: 13.7014 | O51: 13.2601 | P51: 12.8155 | Q51: 12.3722 | R51: 12.3722
A52: COM | B52: Comoros | C52: Sub-Saharan Africa | E52: Eastern and Southern Africa | F52: Eastern and Southern Africa | G52: Median | H52: 65.8092 | I52: 63.6282 | J52: 61.415 | K52: 59.1354 | L52: 56.987 | M52: 54.9904 | N52: 53.1989 | O52: 51.4552 | P52: 49.7761 | Q52: 48.1678 | R52: 48.1678
A53: CPV | B53: Cabo Verde | C53: Sub-Saharan Africa | E53: West and Central Africa | F53: West and Central Africa | G53: Median | H53: 21.3209 | I53: 19.8097 | J53: 18.3426 | K53: 17.0207 | L53: 15.8759 | M53: 14.8938 | N53: 14.0659 | O53: 13.3782 | P53: 12.7884 | Q53: 12.2868 | R53: 12.2868
A54: CRI | B54: Costa Rica | C54: Latin America and the Caribbean | E54: Latin America and Caribbean | F54: Latin America and Caribbean | G54: Median | H54: 9.5927 | I54: 9.3024 | J54: 9.049 | K54: 8.8292 | L54: 8.637 | M54: 8.4532 | N54: 8.2644 | O54: 8.0785 | P54: 7.9037 | Q54: 7.7484 | R54: 7.7484
A55: CUB | B55: Cuba | C55: Latin America and the Caribbean | E55: Latin America and Caribbean | F55: Latin America and Caribbean | G55: Median | H55: 5.9986 | I55: 6.0269 | J55: 6.094 | K55: 6.2162 | L55: 6.3798 | M55: 6.5946 | N55: 6.8766 | O55: 7.1982 | P55: 7.5751 | Q55: 7.9594 | R55: 7.9594
A56: CYP | B56: Cyprus | C56: Northern Africa and Western Asia | D56: Western Asia | E56: Western Europe | F56: Non-programme countries | G56: Median | H56: 2.9874 | I56: 2.9449 | J56: 2.9401 | K56: 2.9714 | L56: 3.0311 | M56: 3.1169 | N56: 3.2284 | O56: 3.3471 | P56: 3.4449 | Q56: 3.5019 | R56: 3.5019
A57: CZE | B57: Czechia | C57: Europe and Northern America | D57: Europe | E57: Western Europe | F57: Non-programme countries | G57: Median | H57: 3.1373 | I57: 3.1422 | J57: 3.1737 | K57: 3.1973 | L57: 3.1847 | M57: 3.1316 | N57: 3.031 | O57: 2.9016 | P57: 2.7644 | Q57: 2.6317 | R57: 2.6317
A58: DEU | B58: Germany | C58: Europe and Northern America | D58: Europe | E58: Western Europe | F58: Non-programme countries | G58: Median | H58: 3.9904 | I58: 3.9559 | J58: 3.928 | K58: 3.8954 | L58: 3.8522 | M58: 3.7993 | N58: 3.7405 | O58: 3.68 | P58: 3.624 | Q58: 3.5718 | R58: 3.5718
A59: DJI | B59: Djibouti | C59: Sub-Saharan Africa | E59: Eastern and Southern Africa | F59: Middle East and North Africa | G59: Median | H59: 69.3738 | I59: 67.2965 | J59: 65.1971 | K59: 63.1848 | L59: 61.0116 | M59: 59.1459 | N59: 57.2758 | O59: 55.4035 | P59: 53.6511 | Q59: 51.8868 | R59: 51.8868
A60: DMA | B60: Dominica | C60: Latin America and the Caribbean | E60: Latin America and Caribbean | F60: Latin America and Caribbean | G60: Median | H60: 25.4615 | I60: 26.2878 | J60: 27.1267 | K60: 27.9617 | L60: 28.7885 | M60: 29.5922 | N60: 30.3467 | O60: 31.0569 | P60: 31.6831 | Q60: 32.2007 | R60: 32.2007
A61: DNK | B61: Denmark | C61: Europe and Northern America | D61: Europe | E61: Western Europe | F61: Non-programme countries | G61: Median | H61: 4.0842 | I61: 4.0869 | J61: 4.0705 | K61: 4.0292 | L61: 3.9615 | M61: 3.8782 | N61: 3.7866 | O61: 3.6915 | P61: 3.6006 | Q61: 3.5186 | R61: 3.5186
A62: DOM | B62: Dominican Republic | C62: Latin America and the Caribbean | E62: Latin America and Caribbean | F62: Latin America and Caribbean | G62: Median | H62: 35.0093 | I62: 35.0113 | J62: 35.0626 | K62: 35.0827 | L62: 35.0482 | M62: 34.8232 | N62: 34.4168 | O62: 33.8592 | P62: 33.1833 | Q62: 32.3884 | R62: 32.3884
A63: DZA | B63: Algeria | C63: Northern Africa and Western Asia | D63: Northern Africa | E63: Middle East and North Africa | F63: Middle East and North Africa | G63: Median | H63: 26.0456 | I63: 25.6679 | J63: 25.3025 | K63: 24.9107 | L63: 24.4724 | M63: 23.9804 | N63: 23.4606 | O63: 22.9104 | P63: 22.3376 | Q63: 21.7528 | R63: 21.7528
A64: ECU | B64: Ecuador | C64: Latin America and the Caribbean | E64: Latin America and Caribbean | F64: Latin America and Caribbean | G64: Median | H64: 16.5334 | I64: 15.8933 | J64: 15.3157 | K64: 14.8125 | L64: 14.3507 | M64: 13.9188 | N64: 13.4722 | O64: 13.0247 | P64: 12.5825 | Q64: 12.1514 | R64: 12.1514
A65: EGY | B65: Egypt | C65: Northern Africa and Western Asia | D65: Northern Africa | E65: Middle East and North Africa | F65: Middle East and North Africa | G65: Median | H65: 25.1909 | I65: 24.1896 | J65: 23.2497 | K65: 22.4113 | L65: 21.6118 | M65: 20.864 | N65: 20.1221 | O65: 19.4144 | P65: 18.7348 | Q65: 18.0746 | R65: 18.0746
A66: ERI | B66: Eritrea | C66: Sub-Saharan Africa | E66: Eastern and Southern Africa | F66: Eastern and Southern Africa | G66: Median | H66: 49.7353 | I66: 48.1238 | J66: 46.4433 | K66: 44.858 | L66: 43.387 | M66: 41.9362 | N66: 40.6051 | O66: 39.3274 | P66: 37.9584 | Q66: 36.6135 | R66: 36.6135
A67: ESP | B67: Spain | C67: Europe and Northern America | D67: Europe | E67: Western Europe | F67: Non-programme countries | G67: Median | H67: 3.4581 | I67: 3.3733 | J67: 3.3134 | K67: 3.2739 | L67: 3.2434 | M67: 3.2103 | N67: 3.1702 | O67: 3.1242 | P67: 3.0702 | Q67: 3.0099 | R67: 3.0099
A68: EST | B68: Estonia | C68: Europe and Northern America | D68: Europe | E68: Western Europe | F68: Non-programme countries | G68: Median | H68: 3.6194 | I68: 3.3551 | J68: 3.1141 | K68: 2.8881 | L68: 2.6741 | M68: 2.4729 | N68: 2.2879 | O68: 2.1267 | P68: 1.9933 | Q68: 1.8806 | R68: 1.8806
A69: ETH | B69: Ethiopia | C69: Sub-Saharan Africa | E69: Eastern and Southern Africa | F69: Eastern and Southern Africa | G69: Median | H69: 70.0884 | I69: 66.458 | J69: 63.0539 | K69: 59.8782 | L69: 56.95 | M69: 54.341 | N69: 52.0674 | O69: 49.9244 | P69: 48.002 | Q69: 46.2222 | R69: 46.2222
A70: FIN | B70: Finland | C70: Europe and Northern America | D70: Europe | E70: Western Europe | F70: Non-programme countries | G70: Median | H70: 2.6369 | I70: 2.5472 | J70: 2.4769 | K70: 2.4234 | L70: 2.3869 | M70: 2.3624 | N70: 2.3439 | O70: 2.3298 | P70: 2.3201 | Q70: 2.312 | R70: 2.312
A71: FJI | B71: Fiji | C71: Oceania | D71: Oceania (exc. Australia and New Zealand) | E71: East Asia and Pacific | F71: East Asia and Pacific | G71: Median | H71: 20.9503 | I71: 20.9642 | J71: 21.2958 | K71: 21.9621 | L71: 22.9396 | M71: 24.1696 | N71: 25.5375 | O71: 26.8152 | P71: 27.7191 | Q71: 28.2115 | R71: 28.2115
A72: FRA | B72: France | C72: Europe and Northern America | D72: Europe | E72: Western Europe | F72: Non-programme countries | G72: Median | H72: 4.1098 | I72: 4.1342 | J72: 4.1753 | K72: 4.219 | L72: 4.2493 | M72: 4.2503 | N72: 4.2252 | O72: 4.184 | P72: 4.1315 | Q72: 4.0685 | R72: 4.0685
A73: FSM | B73: Micronesia (Federated States of) | C73: Oceania | D73: Oceania (exc. Australia and New Zealand) | E73: East Asia and Pacific | F73: East Asia and Pacific | G73: Median | H73: 32.2358 | I73: 31.3518 | J73: 30.338 | K73: 29.4527 | L73: 28.5635 | M73: 27.582 | N73: 26.7086 | O73: 25.7781 | P73: 25.006 | Q73: 24.2116 | R73: 24.2116
A74: GAB | B74: Gabon | C74: Sub-Saharan Africa | E74: West and Central Africa | F74: West and Central Africa | G74: Median | H74: 54.459 | I74: 52.4211 | J74: 50.6307 | K74: 48.5768 | L74: 46.8422 | M74: 45.1526 | N74: 43.2678 | O74: 41.1491 | P74: 39.9195 | Q74: 38.8199 | R74: 38.8199
A75: GBR | B75: United Kingdom | C75: Europe and Northern America | D75: Europe | E75: Western Europe | F75: Non-programme countries | G75: Median | H75: 4.6461 | I75: 4.5405 | J75: 4.4743 | K75: 4.4333 | L75: 4.4004 | M75: 4.3652 | N75: 4.3198 | O75: 4.2592 | P75: 4.1841 | Q75: 4.0942 | R75: 4.0942
A76: GEO | B76: Georgia | C76: Northern Africa and Western Asia | D76: Western Asia | E76: Eastern Europe and Central Asia | F76: Europe and Central Asia | G76: Median | H76: 11.4155 | I76: 10.8865 | J76: 10.4926 | K76: 10.2144 | L76: 10.0059 | M76: 9.842 | N76: 9.7025 | O76: 9.5761 | P76: 9.4569 | Q76: 9.3302 | R76: 9.3302
A77: GHA | B77: Ghana | C77: Sub-Saharan Africa | E77: West and Central Africa | F77: West and Central Africa | G77: Median | H77: 60.3694 | I77: 57.7242 | J77: 55.2829 | K77: 52.9942 | L77: 50.8605 | M77: 48.9177 | N77: 47.0785 | O77: 45.3403 | P77: 43.7855 | Q77: 42.3444 | R77: 42.3444
A78: GIN | B78: Guinea | C78: Sub-Saharan Africa | E78: West and Central Africa | F78: West and Central Africa | G78: Median | H78: 115.5267 | I78: 114.1521 | J78: 112.3521 | K78: 109.8971 | L78: 107.9855 | M78: 105.9388 | N78: 103.7411 | O78: 101.2438 | P78: 98.6623 | Q78: 95.9619 | R78: 95.9619
A79: GMB | B79: Gambia | C79: Sub-Saharan Africa | E79: West and Central Africa | F79: West and Central Africa | G79: Median | H79: 64.5985 | I79: 61.9848 | J79: 59.4846 | K79: 57.0913 | L79: 54.8289 | M79: 52.723 | N79: 50.7438 | O79: 48.9272 | P79: 47.1993 | Q79: 45.5886 | R79: 45.5886
A80: GNB | B80: Guinea-Bissau | C80: Sub-Saharan Africa | E80: West and Central Africa | F80: West and Central Africa | G80: Median | H80: 99.5633 | I80: 95.6488 | J80: 92.1038 | K80: 88.7467 | L80: 85.6747 | M80: 82.6713 | N80: 79.7625 | O80: 77.0499 | P80: 74.4848 | Q80: 71.9068 | R80: 71.9068
A81: GNQ | B81: Equatorial Guinea | C81: Sub-Saharan Africa | E81: West and Central Africa | F81: West and Central Africa | G81: Median | H81: 100.2784 | I81: 96.7636 | J81: 93.4658 | K81: 90.2539 | L81: 87.4172 | M81: 84.3274 | N81: 81.4068 | O81: 78.6012 | P81: 76.0459 | Q81: 73.4217 | R81: 73.4217
A82: GRC | B82: Greece | C82: Europe and Northern America | D82: Europe | E82: Western Europe | F82: Non-programme countries | G82: Median | H82: 4.1239 | I82: 4.2012 | J82: 4.2545 | K82: 4.2688 | L82: 4.2485 | M82: 4.1984 | N82: 4.1288 | O82: 4.0513 | P82: 3.9742 | Q82: 3.8895 | R82: 3.8895
A83: GRD | B83: Grenada | C83: Latin America and the Caribbean | E83: Latin America and Caribbean | F83: Latin America and Caribbean | G83: Median | H83: 14.7552 | I83: 14.8796 | J83: 15.0027 | K83: 15.1479 | L83: 15.3136 | M83: 15.502 | N83: 15.7074 | O83: 15.9037 | P83: 16.0378 | Q83: 16.0139 | R83: 16.0139
A84: GTM | B84: Guatemala | C84: Latin America and the Caribbean | E84: Latin America and Caribbean | F84: Latin America and Caribbean | G84: Median | H84: 30.7129 | I84: 29.4985 | J84: 28.3531 | K84: 27.3355 | L84: 26.3538 | M84: 25.4252 | N84: 24.5513 | O84: 23.6941 | P84: 22.8592 | Q84: 22.085 | R84: 22.085
A85: GUY | B85: Guyana | C85: Latin America and the Caribbean | E85: Latin America and Caribbean | F85: Latin America and Caribbean | G85: Median | H85: 34.9939 | I85: 34.1149 | J85: 33.0903 | K85: 32.0659 | L85: 31.1281 | M85: 30.1806 | N85: 29.1955 | O85: 28.3267 | P85: 27.4503 | Q85: 26.5508 | R85: 26.5508
A86: HND | B86: Honduras | C86: Latin America and the Caribbean | E86: Latin America and Caribbean | F86: Latin America and Caribbean | G86: Median | H86: 22.0367 | I86: 21.2339 | J86: 20.4756 | K86: 19.7348 | L86: 19.0366 | M86: 18.3921 | N86: 17.7289 | O86: 17.13 | P86: 16.5599 | Q86: 16.005 | R86: 16.005
A87: HRV | B87: Croatia | C87: Europe and Northern America | D87: Europe | E87: Eastern Europe and Central Asia | F87: Europe and Central Asia | G87: Median | H87: 5.0565 | I87: 4.9775 | J87: 4.9149 | K87: 4.8594 | L87: 4.8114 | M87: 4.7666 | N87: 4.7266 | O87: 4.6866 | P87: 4.6468 | Q87: 4.5976 | R87: 4.5976
A88: HTI | B88: Haiti | C88: Latin America and the Caribbean | E88: Latin America and Caribbean | F88: Latin America and Caribbean | G88: Median | H88: 73.5055 | I88: 71.6674 | J88: 69.7319 | K88: 67.82 | L88: 65.9188 | M88: 64.1249 | N88: 62.1868 | O88: 60.157 | P88: 58.2464 | Q88: 56.4907 | R88: 56.4907
A89: HUN | B89: Hungary | C89: Europe and Northern America | D89: Europe | E89: Western Europe | F89: Non-programme countries | G89: Median | H89: 5.5686 | I89: 5.333 | J89: 5.0454 | K89: 4.7483 | L89: 4.4805 | M89: 4.2657 | N89: 4.1227 | O89: 4.0426 | P89: 4.0038 | Q89: 3.9893 | R89: 3.9893
A90: IDN | B90: Indonesia | C90: Eastern and South-Eastern Asia | D90: South-Eastern Asia | E90: East Asia and Pacific | F90: East Asia and Pacific | G90: Median | H90: 29.8251 | I90: 28.6339 | J90: 27.501 | K90: 26.4265 | L90: 25.45 | M90: 24.5043 | N90: 23.6128 | O90: 22.798 | P90: 22.0106 | Q90: 21.2615 | R90: 21.2615
A91: IND | B91: India | C91: Central and Southern Asia | D91: Southern Asia | E91: South Asia | F91: South Asia | G91: Median | H91: 49.0549 | I91: 46.2516 | J91: 43.5891 | K91: 41.0689 | L91: 38.6819 | M91: 36.4362 | N91: 34.3239 | O91: 32.3509 | P91: 30.5969 | Q91: 29.0647 | R91: 29.0647
A92: IRL | B92: Ireland | C92: Europe and Northern America | D92: Europe | E92: Western Europe | F92: Non-programme countries | G92: Median | H92: 3.8813 | I92: 3.788 | J92: 3.6879 | K92: 3.5853 | L92: 3.482 | M92: 3.3883 | N92: 3.3133 | O92: 3.2509 | P92: 3.193 | Q92: 3.1253 | R92: 3.1253
A93: IRN | B93: Iran (Islamic Republic of) | C93: Central and Southern Asia | D93: Southern Asia | E93: Middle East and North Africa | F93: Middle East and North Africa | G93: Median | H93: 16.7539 | I93: 16.0834 | J93: 15.459 | K93: 14.8511 | L93: 14.3138 | M93: 13.8527 | N93: 13.3674 | O93: 12.8928 | P93: 12.4438 | Q93: 12.0252 | R93: 12.0252
A94: IRQ | B94: Iraq | C94: Northern Africa and Western Asia | D94: Western Asia | E94: Middle East and North Africa | F94: Middle East and North Africa | G94: Median | H94: 31.548 | I94: 30.5551 | J94: 29.5307 | K94: 28.5748 | L94: 27.6841 | M94: 26.787 | N94: 25.8976 | O94: 25.0766 | P94: 24.2848 | Q94: 23.5189 | R94: 23.5189
A95: ISL | B95: Iceland | C95: Europe and Northern America | D95: Europe | E95: Western Europe | F95: Non-programme countries | G95: Median | H95: 2.6179 | I95: 2.6141 | J95: 2.6187 | K95: 2.6303 | L95: 2.6466 | M95: 2.6635 | N95: 2.6766 | O95: 2.6765 | P95: 2.6533 | Q95: 2.6181 | R95: 2.6181
A96: ISR | B96: Israel | C96: Northern Africa and Western Asia | D96: Western Asia | E96: Middle East and North Africa | F96: Non-programme countries | G96: Median | H96: 4.14 | I96: 4.0274 | J96: 3.9258 | K96: 3.8293 | L96: 3.7387 | M96: 3.6528 | N96: 3.5739 | O96: 3.5042 | P96: 3.4474 | Q96: 3.3999 | R96: 3.3999
A97: ITA | B97: Italy | C97: Europe and Northern America | D97: Europe | E97: Western Europe | F97: Non-programme countries | G97: Median | H97: 3.6876 | I97: 3.6042 | J97: 3.5215 | K97: 3.4274 | L97: 3.3172 | M97: 3.1894 | N97: 3.0469 | O97: 2.8964 | P97: 2.7521 | Q97: 2.6197 | R97: 2.6197
A98: JAM | B98: Jamaica | C98: Latin America and the Caribbean | E98: Latin America and Caribbean | F98: Latin America and Caribbean | G98: Median | H98: 18.856 | I98: 18.7689 | J98: 18.6827 | K98: 18.6346 | L98: 18.6596 | M98: 18.7373 | N98: 18.8394 | O98: 18.9146 | P98: 18.9019 | Q98: 18.773 | R98: 18.773
A99: JOR | B99: Jordan | C99: Northern Africa and Western Asia | D99: Western Asia | E99: Middle East and North Africa | F99: Middle East and North Africa | G99: Median | H99: 18.5529 | I99: 18.0381 | J99: 17.5383 | K99: 17.0314 | L99: 16.5338 | M99: 16.0393 | N99: 15.5458 | O99: 15.0781 | P99: 14.5838 | Q99: 14.1363 | R99: 14.1363
A100: JPN | B100: Japan | C100: Eastern and South-Eastern Asia | D100: Eastern Asia | E100: East Asia and Pacific | F100: Non-programme countries | G100: Median | H100: 2.9171 | I100: 2.8338 | J100: 2.7558 | K100: 2.6816 | L100: 2.6112 | M100: 2.5422 | N100: 2.4723 | O100: 2.4041 | P100: 2.3384 | Q100: 2.2761 | R100: 2.2761
A101: KAZ | B101: Kazakhstan | C101: Central and Southern Asia | D101: Central Asia | E101: Eastern Europe and Central Asia | F101: Europe and Central Asia | G101: Median | H101: 14.5282 | I101: 13.0231 | J101: 11.853 | K101: 11.0484 | L101: 10.5754 | M101: 10.3278 | N101: 10.2088 | O101: 10.1261 | P101: 9.9817 | Q101: 9.7367 | R101: 9.7367
A102: KEN | B102: Kenya | C102: Sub-Saharan Africa | E102: Eastern and Southern Africa | F102: Eastern and Southern Africa | G102: Median | H102: 50.0732 | I102: 48.9193 | J102: 47.5482 | K102: 46.2512 | L102: 45.4494 | M102: 44.3319 | N102: 43.4456 | O102: 42.9742 | P102: 41.889 | Q102: 41.0984 | R102: 41.0984
A103: KGZ | B103: Kyrgyzstan | C103: Central and Southern Asia | D103: Central Asia | E103: Eastern Europe and Central Asia | F103: Europe and Central Asia | G103: Median | H103: 24.7299 | I103: 23.4587 | J103: 22.2162 | K103: 21.0389 | L103: 19.9364 | M103: 18.9971 | N103: 18.2875 | O103: 17.7911 | P103: 17.4694 | Q103: 17.2539 | R103: 17.2539
...

Sheet Equivalence
A1: Adult equivalence reported in government consumption surveys
B2: Kenya | C2: Malawi | D2: Mozambique | E2: Rwanda | F2: Uganda
B3: See page 35 | C3: Does not report in adult equivalents | D3: Does not report in adult equivalents | E3: See page 10; take the average of male and female | F3: Does not report what adult equivalence scale they use; assume same as Rwanda
A4: 0-1 years | B4: 0.24 | E4: 0.41 | F4: =E4 -> 0.41
A5: 1-3 years | B5: 0.24 | E5: 0.56 | F5: =E5 -> 0.56
A6: 4-6 years | B6: 0.65 | E6: 0.76 | F6: =E6 -> 0.76
A7: 7-9 years | B7: 0.65 | E7: 0.91 | F7: =E7 -> 0.91
A8: 10-12 years | B8: 0.65 | E8: 1.03 | F8: =E8 -> 1.03
A9: 13-15 years | B9: 1 | E9: 1.05 | F9: =E9 -> 1.05
A10: 16-19 years | B10: 1 | E10: 1.03 | F10: =E10 -> 1.03
A11: 20-39 years | B11: 1 | E11: 1 | F11: =E11 -> 1
A12: 40-49 years | B12: 1 | E12: 0.95 | F12: =E12 -> 0.95
A13: 50-59 years | B13: 1 | E13: 0.9 | F13: =E13 -> 0.9
A14: 60-69 years | B14: 1 | E14: 0.85 | F14: =E14 -> 0.85
A15: 70+ years | B15: 1 | E15: 0.7 | F15: =E15 -> 0.7
A17: Population pyramids
A18: Source: Population pyramids
B19: Kenya (2022) | C19: Malawi | D19: Mozambique (2023) | E19: Rwanda (2023) | F19: Uganda
A20: 0-4 | B20: 6958267 | C20: 3086308 | D20: 5468526 | E20: 1935500 | F20: 7868837
A21: 5-9 | B21: 6707809 | C21: 2868379 | D21: 4848905 | E21: 1781999 | F21: 6969764
A22: 10-14 | B22: 6762490 | C22: 2736479 | D22: 4357090 | E22: 1647846 | F22: 6320416
A23: 15-19 | B23: 6153117 | C23: 2435364 | D23: 3680377 | E23: 1567486 | F23: 5599896
A24: 20-24 | B24: 5205957 | C24: 1959474 | D24: 3185810 | E24: 1331799 | F24: 4806951
A25: 25-29 | B25: 4398474 | C25: 1587884 | D25: 2663864 | E25: 1132559 | F25: 4011450
A26: 30-34 | B26: 3976138 | C26: 1334932 | D26: 2212567 | E26: 1027836 | F26: 3115028
A27: 35-39 | B27: 3432045 | C27: 1179103 | D27: 1795101 | E27: 949682 | F27: 2268319
A28: 40-44 | B28: 2757060 | C28: 977902 | D28: 1426843 | E28: 756672 | F28: 1685295
A29: 45-49 | B29: 2175625 | C29: 661392 | D29: 1202675 | E29: 510029 | F29: 1355288
A30: 50-54 | B30: 1717850 | C30: 452845 | D30: 955689 | E30: 392198 | F30: 1088896
A31: 55-59 | B31: 1305188 | C31: 342181 | D31: 692230 | E31: 316827 | F31: 795674
... A40: 100+ | B40: 3389 | C40: 748 | D40: 36 | E40: 145 | F40: 99
A41: Total | B41: =SUM(B20:B40) -> 54027475 | C41: =SUM(C20:C40) -> 20405306 | D41: =SUM(D20:D40) -> 33897345 | E41: =SUM(E20:E40) -> 14094674 | F41: =SUM(F20:F40) -> 47249574
A43: Putting into same format as age equivalent scale
A44: Note: assumes uniform distribution within age buckets
A45: 0-1 years | B45: =B20/5 -> 1391653.4 | C45: =C20/5 -> 617261.6 | D45: =D20/5 -> 1093705.2 | E45: =E20/5 -> 387100 | F45: =F20/5 -> 1573767.4
A46: 1-3 years | B46: =B20*(4/5) -> 5566613.6 | C46: =C20*(4/5) -> 2469046.4 | D46: =D20*(4/5) -> 4374820.8 | E46: =E20*(4/5) -> 1548400 | F46: =F20*(4/5) -> 6295069.6
A47: 4-6 years | B47: =(B20/5)+B21*(2/5) -> 4074777 | C47: =(C20/5)+C21*(2/5) -> 1764613.2 | D47: =(D20/5)+D21*(2/5) -> 3033267.2 | E47: =(E20/5)+E21*(2/5) -> 1099899.6 | F47: =(F20/5)+F21*(2/5) -> 4361673
A48: 7-9 years | B48: =B21*(3/5) -> 4024685.4 | C48: =C21*(3/5) -> 1721027.4 | D48: =D21*(3/5) -> 2909343 | E48: =E21*(3/5) -> 1069199.4 | F48: =F21*(3/5) -> 4181858.4
A49: 10-12 years | B49: =B22*(3/5) -> 4057494 | C49: =C22*(3/5) -> 1641887.4 | D49: =D22*(3/5) -> 2614254 | E49: =E22*(3/5) -> 988707.6 | F49: =F22*(3/5) -> 3792249.6
A50: 13-15 years | B50: =B22*(2/5)+B23*(1/5) -> 3935619.4 | C50: =C22*(2/5)+C23*(1/5) -> 1581664.4 | D50: =D22*(2/5)+D23*(1/5) -> 2478911.4 | E50: =E22*(2/5)+E23*(1/5) -> 972635.6 | F50: =F22*(2/5)+F23*(1/5) -> 3648145.6
A51: 16-19 years | B51: =B23*(4/5) -> 4922493.6 | C51: =C23*(4/5) -> 1948291.2 | D51: =D23*(4/5) -> 2944301.6 | E51: =E23*(4/5) -> 1253988.8 | F51: =F23*(4/5) -> 4479916.8
A52: 20-39 years | B52: =SUM(B24:B27) -> 17012614 | C52: =SUM(C24:C27) -> 6061393 | D52: =SUM(D24:D27) -> 9857342 | E52: =SUM(E24:E27) -> 4441876 | F52: =SUM(F24:F27) -> 14201748
A53: 40-49 years | B53: =SUM(B28:B29) -> 4932685 | C53: =SUM(C28:C29) -> 1639294 | D53: =SUM(D28:D29) -> 2629518 | E53: =SUM(E28:E29) -> 1266701 | F53: =SUM(F28:F29) -> 3040583
A54: 50-59 years | B54: =SUM(B30:B31) -> 3023038 | C54: =SUM(C30:C31) -> 795026 | D54: =SUM(D30:D31) -> 1647919 | E54: =SUM(E30:E31) -> 709025 | F54: =SUM(F30:F31) -> 1884570
A55: 60-69 years | B55: =SUM(B32:B33) -> 1534607 | C55: =SUM(C32:C33) -> 424582 | D55: =SUM(D32:D33) -> 932871 | E55: =SUM(E32:E33) -> 489595 | F55: =SUM(F32:F33) -> 955158
A56: 70+ years | B56: =SUM(B34:B40) -> 942848 | C56: =SUM(C34:C40) -> 358481 | D56: =SUM(D34:D40) -> 474797 | E56: =SUM(E34:E40) -> 254646 | F56: =SUM(F34:F40) -> 408602
A58: Expressed in % terms
A59: 0-1 years | B59: =B45/B$41 -> 0.025758254 | C59: =C45/C$41 -> 0.030250054 | D59: =D45/D$41 -> 0.032265217 | E59: =E45/E$41 -> 0.027464275 | F59: =F45/F$41 -> 0.033307547
A60: 1-3 years | B60: =B46/B$41 -> 0.10303301 | C60: =C46/C$41 -> 0.12100021 | D60: =D46/D$41 -> 0.12906087 | E60: =E46/E$41 -> 0.1098571 | F60: =F46/F$41 -> 0.13323019
A61: 4-6 years | B61: =B47/B$41 -> 0.07542046 | C61: =C47/C$41 -> 0.086478154 | D61: =D47/D$41 -> 0.089483917 | E61: =E47/E$41 -> 0.078036541 | F61: =F47/F$41 -> 0.092311372
A62: 7-9 years | B62: =B48/B$41 -> 0.074493309 | C62: =C48/C$41 -> 0.084342151 | D62: =D48/D$41 -> 0.085828049 | E62: =E48/E$41 -> 0.075858399 | F62: =F48/F$41 -> 0.088505738
A63: 10-12 years | B63: =B49/B$41 -> 0.075100567 | C63: =C49/C$41 -> 0.080463748 | D63: =D49/D$41 -> 0.077122677 | E63: =E49/E$41 -> 0.070147603 | F63: =F49/F$41 -> 0.080259974
A64: 13-15 years | B64: =B50/B$41 -> 0.072844778 | C64: =C50/C$41 -> 0.077512408 | D64: =D50/D$41 -> 0.073129958 | E64: =E50/E$41 -> 0.069007314 | F64: =F50/F$41 -> 0.077210127
A65: 16-19 years | B65: =B51/B$41 -> 0.091110932 | C65: =C51/C$41 -> 0.095479637 | D65: =D51/D$41 -> 0.086859357 | E65: =E51/E$41 -> 0.088968982 | F65: =F51/F$41 -> 0.094813909
A66: 20-39 years | B66: =B52/B$41 -> 0.31488819 | C66: =C52/C$41 -> 0.29704985 | D66: =D52/D$41 -> 0.29079983 | E66: =E52/E$41 -> 0.31514571 | F66: =F52/F$41 -> 0.30056881
A67: 40-49 years | B67: =B53/B$41 -> 0.091299566 | C67: =C53/C$41 -> 0.080336654 | D67: =D53/D$41 -> 0.077572978 | E67: =E53/E$41 -> 0.089870897 | F67: =F53/F$41 -> 0.064351543
A68: 50-59 years | B68: =B54/B$41 -> 0.055953716 | C68: =C54/C$41 -> 0.038961729 | D68: =D54/D$41 -> 0.048614987 | E68: =E54/E$41 -> 0.050304463 | F68: =F54/F$41 -> 0.039885439
A69: 60-69 years | B69: =B55/B$41 -> 0.028404196 | C69: =C55/C$41 -> 0.020807431 | D69: =D55/D$41 -> 0.027520474 | E69: =E55/E$41 -> 0.034736171 | F69: =F55/F$41 -> 0.020215166
A70: 70+ years | B70: =B56/B$41 -> 0.017451269 | C70: =C56/C$41 -> 0.017568029 | D70: =D56/D$41 -> 0.014006908 | E70: =E56/E$41 -> 0.018066824 | F70: =F56/F$41 -> 0.0086477393
A72: Backing out an adult equivalence conversion factor
A74: Average household size | B74: =Baseline!B4 -> 4.2 | C74: =Baseline!C4 -> 4.5 | D74: =Baseline!D4 -> 4.4 | E74: =Baseline!E4 -> 4.3 | F74: =Baseline!F4 -> 4.8
A75: Distribution of ages
A76: 0-1 years | B76: =B$74*B59 -> 0.10818466 | C76: =C$74*C59 -> 0.13612524 | D76: =D$74*D59 -> 0.14196696 | E76: =E$74*E59 -> 0.11809638 | F76: =F$74*F59 -> 0.15987622
A77: 1-3 years | B77: =B$74*B60 -> 0.43273866 | C77: =C$74*C60 -> 0.54450096 | D77: =D$74*D60 -> 0.56786782 | E77: =E$74*E60 -> 0.47238553 | F77: =F$74*F60 -> 0.6395049
A78: 4-6 years | B78: =B$74*B61 -> 0.31676593 | C78: =C$74*C61 -> 0.38915169 | D78: =D$74*D61 -> 0.39372923 | E78: =E$74*E61 -> 0.33555712 | F78: =F$74*F61 -> 0.44309459
A79: 7-9 years | B79: =B$74*B62 -> 0.3128719 | C79: =C$74*C62 -> 0.37953968 | D79: =D$74*D62 -> 0.37764342 | E79: =E$74*E62 -> 0.32619111 | F79: =F$74*F62 -> 0.42482754
A80: 10-12 years | B80: =B$74*B63 -> 0.31542238 | C80: =C$74*C63 -> 0.36208687 | D80: =D$74*D63 -> 0.33933978 | E80: =E$74*E63 -> 0.30163469 | F80: =F$74*F63 -> 0.38524788
A81: 13-15 years | B81: =B$74*B64 -> 0.30594807 | C81: =C$74*C64 -> 0.34880584 | D81: =D$74*D64 -> 0.32177181 | E81: =E$74*E64 -> 0.29673145 | F81: =F$74*F64 -> 0.37060861
A82: 16-19 years | B82: =B$74*B65 -> 0.38266591 | C82: =C$74*C65 -> 0.42965836 | D82: =D$74*D65 -> 0.38218117 | E82: =E$74*E65 -> 0.38256662 | F82: =F$74*F65 -> 0.45510676
A83: 20-39 years | B83: =B$74*B66 -> 1.3225304 | C83: =C$74*C66 -> 1.3367243 | D83: =D$74*D66 -> 1.2795192 | E83: =E$74*E66 -> 1.3551265 | F83: =F$74*F66 -> 1.4427303
A84: 40-49 years | B84: =B$74*B67 -> 0.38345818 | C84: =C$74*C67 -> 0.36151494 | D84: =D$74*D67 -> 0.3413211 | E84: =E$74*E67 -> 0.38644486 | F84: =F$74*F67 -> 0.30888741
A85: 50-59 years | B85: =B$74*B68 -> 0.23500561 | C85: =C$74*C68 -> 0.17532778 | D85: =D$74*D68 -> 0.21390594 | E85: =E$74*E68 -> 0.21630919 | F85: =F$74*F68 -> 0.19145011
A86: 60-69 years | B86: =B$74*B69 -> 0.11929762 | C86: =C$74*C69 -> 0.09363344 | D86: =D$74*D69 -> 0.12109009 | E86: =E$74*E69 -> 0.14936553 | F86: =F$74*F69 -> 0.097032799
A87: 70+ years | B87: =B$74*B70 -> 0.07329533 | C87: =C$74*C70 -> 0.079056129 | D87: =D$74*D70 -> 0.061630396 | E87: =E$74*E70 -> 0.077687345 | F87: =F$74*F70 -> 0.041509149
A88: Implied per adult equivalent | B88: =SUMPRODUCT(B4:B15,B76:B87) -> 3.5663119 | E88: =SUMPRODUCT(E4:E15,E76:E87) -> 3.9793774 | F88: =SUMPRODUCT(F4:F15,F76:F87) -> 4.4217339
A90: Implied adjustment to get things in per capita terms | B90: =B88/B74 -> 0.84912187 | C90: N/A | D90: N/A | E90: =E88/E74 -> 0.9254366 | F90: =F88/F74 -> 0.92119457

Sheet Papers
A1: Papers which estimate economic mutlipliers
A2: Source: Gassmann et al. 2023
A3: Author(s) | B3: Country | C3: Program Name | D3: Time Range of Study | E3: Method | F3: Multiplier Channel | G3: Outcome Indicator | H3: Multiplier | I3: Measurement Unit | J3: Macro/Meso/Micro | K3: Headline finding | L3: Best-guess | M3: Notes
A4: Neri et al., 2013 | B4: Brazil | C4: Bolsa Familia | D4: 2009 | E4: SAM | F4: Consumption, production | G4: National GDP | H4: 0.78 | I4: 1.78% GDP growth for 1% increase in BF spending | J4: Macro | K4: "The Programa Bolsa Família has the highest effect by a large margin: according to the model, if the government increased Bolsa Família expenditures by 1 per cent of GDP, overall economic activity would grow by 1.78 per cent" | L4: 1.78 | M4: I don't understand where the 0.78 figure comes from; 1.78% GDP growth from a 1% injection should imply a multiplier of >1
A5: Freire et al., 2018 | B5: Brazil | C5: Bolsa Familia | D5: 2008-2015 | E5: CGE | F5: Consumption, investment | G5: National GDP | H5: 1.04 | I5: Real GDP growth per 1 $ spent | J5: Macro | K5: "We figured out that each Brazilian Real spent with the BF program generates an increase of 1.04 Brazilian Reais on GDP in the period considered in this study" | L5: 1.04
A6: Filipiski & Taylor, 2012 | B6: Ghana | C6: Livelihood Empowerment Against Poverty | D6: 2007 | E6: CGE | F6: Consumption, production | G6: Transfer efficiency | H6: 1-1.42 | I6: Additional rural welfare per 1$ spent | J6: Macro | K6: Table 5 | L6: 1.42 | M6: Model E seems the most relevant: "Base model with unemployment and constrained input use"
A7: Lehmann & Masterson, 2014 | B7: Lebanon | C7: Winter Cash Assistance Program for Syrian Refugees | D7: 2014 | E7: Econometric techniques and back-of-the-envelope calculation | F7: Consumption | G7: National GDP | H7: 2.13* | I7: Additional GDP | J7: Macro | K7: "Each dollar that beneficiaries spend generates 2.13 dollars of GDP for the Lebanese economy" | L7: 2.13
A8: Filipiski & Taylor, 2012 | B8: Malawi | C8: Social Cash Transfer Program | D8: 2004 | E8: CGE | F8: Consumption | G8: Transfer efficiency | H8: 1-1.47 | I8: Additional rural welfare per 1$ spent | J8: Macro | K8: Table 3 | L8: 1.47 | M8: Model E seems the most relevant: "Base model with unemployment and constrained input use"
A9: Tiberti et al., 2018 | B9: South Africa | C9: Child Support Grant | D9: 2009 | E9: CGE (integrated micro-macro model) | F9: Consumption, labor supply, production | G9: National GDP | H9: 0.26%-0.28% | I9: Change in real GDP for 20% increase in CSG spending | J9: Macro | K9: Table 2 | M9: I don't think this estimate is analogous to a multiplier; can't easily make an apples-to-apples comparison
A10: Cunha, et al., 2022 | B10: Brazil | C10: Emergency Aid | D10: 2020 | E10: Econometric techniques (IV regression) | F10: Private formal employment | G10: Regional GDP | H10: 0.5-1.5 | I10: Increase in GDP per 1 $ spent | J10: Meso | K10: "Using two-stage least squares regressions we estimate a formal employment multiplier and then apply an analytical transformation to recover an implied GDP multiplier in the range of 0.5-1.5. The lower bound of this range lies below most estimates in the literature" | L10: 1 | M10: Take the midpoint of the range of estimates
A11: Jorge & da Graca, 2019 | B11: Brazil | C11: Bolsa Familia | D11: 2004-2012 | E11: Econometric techniques (panel data, OLS) | F11: Consumption | G11: GDP of municipalities in Sergipe | H11: 0* | I11: Estimated impact on municipal GDP (regression coefficient) | J11: Meso | K11: "Employing the methodology of panel data analysis we conclude that results does not prove the PBF influence on GDP of the investigated municipalities" | M11: I can't back out the point estimate of this null result
A12: Rougier et al., 2018 | B12: Brazil | C12: Bolsa Familia | D12: 2003-2010 | E12: Econometric techniques (reduced form local (structural) growth model with IV | F12: Consumption, local productive structures | G12: Municipal GDP in Ceará | H12: 0.0011 – 0.0017 12-18% | I12: pp increase in local growth per 1 pp increase in BFP/GDP ratio | J12: Meso | M12: I don't think this estimate is analogous to a multiplier; can't easily make an apples-to-apples comparison
