Workbook

Sheet Key
A1: Guide to interpreting this cost-effectiveness analysis
A2: Sheet descriptions
E4: Main CEA | F4: This sheet contains the primary calculations that result in final cost-effectiveness estimates. This sheet draws on inputs from the "Inputs" sheet and inputs calculated in the other supplemental sheets listed below.
E5: Counterfactual malaria | F5: This sheet contains our calculations of how high malaria mortality and prevalence rates would be in the absence of SMC campaigns.
E6: Leverage/Funging | F6: This sheet contains our calculations of the impact that crowding in and crowding out funding by other contributors has on the benefits of the program.
E7: Inputs | F7: This sheet contains all of the manually entered input values informing the CEA, along with the sources and reasoning supporting them. This sheet also contains inputs sourced from the "GBD estimates" sheet.
E8: GBD estimates | F8: This sheet contains disease burden and population datasets downloaded from the Institute of Health Metrics (IHME)'s Global Burden of Disease (GBD) project.
E9: Simple CEA | F9: This sheet contains a simplified version of the CEA that is designed to be comparable to our CEAs of other programs.
E10: Confidence intervals | F10: This sheet contains our best guesses of the 25th and 75th percentile values for each of the parameters of our simple CEA.
E11: Sensitivity analysis | F11: This sheet contains the outputs of our sensitivity analysis that tests the cost-effectiveness ranges that would result from updating certain inputs to their 25th or 75th percentile values.
A13: Terminology key
C15: Terms specific to this CEA
E16: SMC season | F16: The part of the year when SMC is delivered because malaria transmission is highest. In locations where GiveWell currently supports SMC, this is either four or five months each year.
E17: SMC cycle | F17: Refers to a monthly SMC treatment cycle, which consists of a three-day treatment regimen of SMC medication that provides protection from malaria for one month.
E18: SMC round | F18: Refers to a year's worth of SMC cycles, which are typically delievered over a period of four to five consecutive months during the rainy season.
E19: Sahel | F19: A subregion of Africa where malaria transmission tends to be highly seasonal. Historically, SMC was only delivered at large scale within the Sahel. Since 2020-21, SMC is now being piloted in locations outside the Sahel.
E20: Malaria-attributable mortality | F20: Deaths that could be averted by SMC, either directly (because they are malaria deaths) or indirectly (because malaria indirectly increases the risk of death from other causes).
E21: Indirect malaria deaths | F21: Deaths in which malaria plays a causal role, but are attributed to another cause. For example, malaria may increase the likelihood of death from malnutrition or other infectious diseases. Malaria control interventions often have a larger effect on all-cause mortality than would be expected exclusively from declines in malaria-specific mortality, which we interpret as evidence that averting malaria may also avert deaths attributed to other causes.
C23: Terms used across GiveWell's CEAs
E24: Internal validity | F24: Describes an adjustment we make to the treatment effect of an intervention to account for the possibility that the treatment effects found in studies may not represent the true effect the intervention had on the populations studied.
E25: External validity | F25: Describes an adjustment we make to the treatment effect of an intervention to account for differences in the program implementation or populations treated in studies from the program implementation or populations treated by grantee programs.
E26: Leverage | F26: Describes a situation where a grantee's spending on a program causes other organizations or governments to contribute more to the program than they otherwise would have. In most cases, accounting for leverage increases cost-effectiveness
E27: Funging | F27: Describes a situation where a grantee's spending on a program causes other organizations or governments to contribute less to the program than they otherwise would have. In most cases, accounting for funging decreases cost-effectiveness.
E28: Counterfactual | F28: In most cases, describes the state of the world that would exist if we did not provide funding to a grantee for a program. When discussing the "counterfactual value of other actors' spending," we are referring to how much benefit another organization's or government's spending would generate if it were spent on something other than the grantee program.
E29: Moral weights | F29: To compare cost-effectiveness across different programs, we use ‘moral weights’ to quantify the benefits of different program impacts (e.g. increased income vs reduced deaths). We benchmark the value of each benefit to a value of 1, which we define as the value of doubling someone’s consumption for one year.
E30: Philanthropic actors | F30: Non-governmental organizations (NGOs) providing funding to philanthropic programs.
A32: Unit and source key
C34: Unit labels used in the CEA
E35: # | F35: Number
E36: per 1k | F36: Rate per 1,000
E37: per 100k | F37: Rate per 100,000
E38: $ | F38: U.S. dollars
E39: ln($) | F39: The natural logarithm of a monetary value
E40: % | F40: Percentage
E41: ppt | F41: Percentage points
E42: UoV | F42: Units of value: an arbitrary unit GiveWell uses to compare the moral value of different types of outcomes, such as saving lives or increasing income
E43: xcash | F43: Cost-effectiveness in terms of multiples of GiveDirectly's unconditional cash transfer program
C45: Source labels used in the CEA
E47: input | F47: A value pulled from the "Inputs" sheet
E48: calc | F48: A value calculated using other values in the same sheet
E49: supp | F49: A value pulled from one of the sheets hosting supplemental calculations
E50: main | F50: A value pulled fom the "Main CEA" sheet
E51: feed | F51: A value pulled from an earlier section within the same sheet
A53: GiveWell analyses informing this model
C55: Analyses specific to this CEA
E56: GW's analysis of Malaria Consortium's cost per SMC cycle administered
E57: GW's analysis of the number of SMC cycles delivered per year
E58: GW's analysis of the indirect effects of Malaria Consortium's SMC programs relative to Cisse et al. 2016
E59: GW's analysis of SMC coverage in trials
E60: GW's analysis of malaria income effect size
E61: GW's analysis of subnational mortality rates for SMC
E62: GW's analysis of leverage and funging risk for SMC
E63: GW's analysis of malaria mortality averted due to vaccine rollout
E64: GW's analysis of SMC outside the Sahel
C66: Analyses referenced across GiveWell's CEAs
E67: GW's moral weights and discount rate
E68: GW's analysis on estimating multiplier for benefits experienced by other household members
E69: GW's supplemental intervention-level adjustments
E70: GiveWell's CEA for GiveDirectly's unconditional cash transfers
E71: GW's analysis of the counterfactual value of other actors' spending
E72: GW's analysis of the counterfactual value of Global Fund spending

Sheet Main CEA
I1: Malaria Consortium | S1: Malaria Consortium
I2: Burkina Faso | J2: Chad | K2: Côte d'Ivoire | L2: DRC | M2: DRC | N2: DRC | O2: DRC | P2: Mozambique | Q2: Nigeria | R2: Nigeria | S2: Nigeria | T2: Nigeria | U2: Nigeria | V2: Nigeria | W2: Nigeria | X2: Nigeria | Y2: Nigeria | Z2: South Sudan | AA2: Togo | AB2: Uganda
A3: Main calculations | F3: unit | G3: type | H3: Overall | L3: Haut-Katanga | M3: Haut-Lomami | N3: Lualaba | O3: Tanganyika | P3: Nampula | Q3: Bauchi | R3: Borno | S3: FCT (Abuja) | T3: Kebbi | U3: Kogi | V3: Nasarawa | W3: Oyo | X3: Plateau | Y3: Sokoto | Z3: Northern Bahr El Ghazal | AB3: Karamoja
E4: Final cost-effectiveness estimate (pulled from below for visibility) | F4: =F193 -> xcash | G4: feed | H4: =H193 -> - | I4: =I193 -> 13.310868 | J4: =J193 -> 14.65303 | K4: =K193 -> 8.5184856 | L4: =L193 -> 10.227025 | M4: =M193 -> 11.22453 | N4: =N193 -> 12.200271 | O4: =O193 -> 12.821222 | ... AB4: =AB193 -> 6.7780673
A5: Costs
C7: GiveWell costs
E8: =HYPERLINK(buildUrl(CELL("address", Inputs!E8)), Inputs!E8) -> Grant size | F8: =Inputs!F8 -> $ | G8: =Inputs!G8 -> input | H8: =Inputs!H8 -> - | I8: =Inputs!I8 -> 0.01 | J8: =Inputs!J8 -> 0.01 | K8: =Inputs!K8 -> 0.01 | L8: =Inputs!L8 -> 0.01 | M8: =Inputs!M8 -> 0.01 | ... AB8: =Inputs!AB8 -> 0.01
C10: Cost breakdown
E11: =HYPERLINK(buildUrl(CELL("address", Inputs!E11)), Inputs!E11) -> Percentage of total costs covered by the grantee | F11: =Inputs!F11 -> % | G11: =Inputs!G11 -> input | H11: =Inputs!H11 -> - | I11: =Inputs!I11 -> 0.8944838 | J11: =Inputs!J11 -> 0.90224903 | K11: =Inputs!K11 -> 0.906659 | L11: =Inputs!L11 -> 0.50149962 | M11: =Inputs!M11 -> 0.50149962 | ... AB11: =Inputs!AB11 -> 0.89331272
E12: =HYPERLINK(buildUrl(CELL("address", Inputs!E12)), Inputs!E12) -> Percentage of total costs covered by other philanthropic actors | F12: =Inputs!F12 -> % | G12: =Inputs!G12 -> input | H12: =Inputs!H12 -> - | I12: =Inputs!I12 -> 0 | J12: =Inputs!J12 -> 0 | K12: =Inputs!K12 -> 0 | L12: =Inputs!L12 -> 0.43937414 | M12: =Inputs!M12 -> 0.43937414 | ... AB12: =Inputs!AB12 -> 0
E13: =HYPERLINK(buildUrl(CELL("address", Inputs!E13)), Inputs!E13) -> Percentage of total costs covered by domestic governments | F13: =Inputs!F13 -> % | G13: =Inputs!G13 -> input | H13: =Inputs!H13 -> - | I13: =Inputs!I13 -> 0.1055162 | J13: =Inputs!J13 -> 0.09775097 | K13: =Inputs!K13 -> 0.093341 | L13: =Inputs!L13 -> 0.05912624 | M13: =Inputs!M13 -> 0.05912624 | ... AB13: =Inputs!AB13 -> 0.10668728
C15: Total costs
E16: Total spending by all contributors | F16: $ | G16: calc | H16: - | I16: =IF(I8="-",$H8/I11,I8/I11) -> 0.011179632 | J16: =IF(J8="-",$H8/J11,J8/J11) -> 0.011083415 | K16: =IF(K8="-",$H8/K11,K8/K11) -> 0.011029505 | L16: =IF(L8="-",$H8/L11,L8/L11) -> 0.019940195 | M16: =IF(M8="-",$H8/M11,M8/M11) -> 0.019940195 | N16: =IF(N8="-",$H8/N11,N8/N11) -> 0.019940195 | O16: =IF(O8="-",$H8/O11,O8/O11) -> 0.019940195 | P16: =IF(P8="-",$H8/P11,P8/P11) -> 19516180 | ... AB16: =IF(AB8="-",$H8/AB11,AB8/AB11) -> 0.011194288
C18: Total spending attributable to different actors
E19: Total spending contributed by grantee | F19: $ | G19: calc | H19: - | I19: =I$16*I11 -> 0.01 | J19: =J$16*J11 -> 0.01 | K19: =K$16*K11 -> 0.01 | L19: =L$16*L11 -> 0.01 | M19: =M$16*M11 -> 0.01 | N19: =N$16*N11 -> 0.01 | O19: =O$16*O11 -> 0.01 | P19: =P$16*P11 -> 17456907 | ... AB19: =AB$16*AB11 -> 0.01
E20: Total spending contributed by other philanthropic actors | F20: $ | G20: calc | H20: - | I20: =I$16*I12 -> 0 | J20: =J$16*J12 -> 0 | K20: =K$16*K12 -> 0 | L20: =L$16*L12 -> 0.0087612059 | M20: =M$16*M12 -> 0.0087612059 | N20: =N$16*N12 -> 0.0087612059 | O20: =O$16*O12 -> 0.0087612059 | P20: =P$16*P12 -> 0 | ... AB20: =AB$16*AB12 -> 0
E21: Total spending contributed by domestic governments | F21: $ | G21: calc | H21: - | I21: =I$16*I13 -> 0.0011796323 | J21: =J$16*J13 -> 0.0010834145 | K21: =K$16*K13 -> 0.001029505 | L21: =L$16*L13 -> 0.0011789887 | M21: =M$16*M13 -> 0.0011789887 | N21: =N$16*N13 -> 0.0011789887 | O21: =O$16*O13 -> 0.0011789887 | P21: =P$16*P13 -> 2059273.2 | ... AB21: =AB$16*AB13 -> 0.0011942882
C23: Upstream / downstream spending
E24: Total spending causally upstream of donations to grantee | F24: $ | G24: calc | H24: - | I24: =SUM(I19:I20) -> 0.01 | J24: =SUM(J19:J20) -> 0.01 | K24: =SUM(K19:K20) -> 0.01 | L24: =SUM(L19:L20) -> 0.018761206 | M24: =SUM(M19:M20) -> 0.018761206 | N24: =SUM(N19:N20) -> 0.018761206 | O24: =SUM(O19:O20) -> 0.018761206 | P24: =SUM(P19:P20) -> 17456907 | ... AB24: =SUM(AB19:AB20) -> 0.01
E25: Total spending causally downstream of donations to grantee | F25: $ | G25: calc | H25: - | I25: =I21 -> 0.0011796323 | J25: =J21 -> 0.0010834145 | K25: =K21 -> 0.001029505 | L25: =L21 -> 0.0011789887 | M25: =M21 -> 0.0011789887 | N25: =N21 -> 0.0011789887 | O25: =O21 -> 0.0011789887 | P25: =P21 -> 2059273.2 | ... AB25: =AB21 -> 0.0011942882
C27: Cost per child covered
E28: =HYPERLINK(buildUrl(CELL("address", Inputs!E16)), Inputs!E16) -> Cost per seasonal malaria chemoprevention (SMC) cycle administered | F28: =Inputs!F16 -> $ | G28: =Inputs!G16 -> input | H28: =Inputs!H16 -> - | I28: =Inputs!I16 -> 1.641799 | J28: =Inputs!J16 -> 1.943721 | K28: =Inputs!K16 -> 2.525697 | L28: =Inputs!L16 -> 1.943721 | M28: =Inputs!M16 -> 1.943721 | ... AB28: =Inputs!AB16 -> 1.9852456
E29: =HYPERLINK(buildUrl(CELL("address", Inputs!E17)), Inputs!E17) -> Number of SMC cycles per year | F29: =Inputs!F17 -> # | G29: =Inputs!G17 -> input | H29: =Inputs!H17 -> - | I29: =Inputs!I17 -> 4.312275 | J29: =Inputs!J17 -> 4 | K29: =Inputs!K17 -> 5 | L29: =Inputs!L17 -> 4 | M29: =Inputs!M17 -> 4 | ... AB29: =Inputs!AB17 -> 5
E30: Total cost per child treated with all cycles of SMC in a year | F30: $ | G30: calc | H30: - | I30: =I28*I29 -> 7.0798888 | J30: =J28*J29 -> 7.774884 | K30: =K28*K29 -> 12.628485 | L30: =L28*L29 -> 7.774884 | M30: =M28*M29 -> 7.774884 | N30: =N28*N29 -> 7.774884 | O30: =O28*O29 -> 7.774884 | P30: =P28*P29 -> 8.2932718 | ... AB30: =AB28*AB29 -> 9.9262278
E31: Upstream costs per child treated with all cycles of SMC in a year | F31: $ | G31: calc | H31: - | I31: =(I24/I16)*I30 -> 6.3328458 | J31: =(J24/J16)*J30 -> 7.0148815 | K31: =(K24/K16)*K30 -> 11.44973 | L31: =(L24/L16)*L30 -> 7.3151843 | M31: =(M24/M16)*M30 -> 7.3151843 | N31: =(N24/N16)*N30 -> 7.3151843 | O31: =(O24/O16)*O30 -> 7.3151843 | P31: =(P24/P16)*P30 -> 7.4181972 | ... AB31: =(AB24/AB16)*AB30 -> 8.8672256
A33: Outputs
C35: Total children covered
E36: Total people under age 5 receiving a year of SMC | F36: # | G36: calc | H36: - | I36: =I19/I31 -> 0.0015790689 | J36: =J19/J31 -> 0.0014255408 | K36: =K19/K31 -> 0.00087338307 | L36: =L19/L31 -> 0.0013670195 | M36: =M19/M31 -> 0.0013670195 | N36: =N19/N31 -> 0.0013670195 | O36: =O19/O31 -> 0.0013670195 | P36: =P19/P31 -> 2353254.6 | ... AB36: =AB19/AB31 -> 0.0011277485
A38: Outcomes
C40: Mortality reduction among people under age 5 (treated population)
E41: =HYPERLINK(buildUrl(CELL("address", Inputs!E45)), Inputs!E45) -> Reduction in malaria incidence for children under age 5 targeted for SMC found in GiveWell's adjusted version of the Meremikwu et al. 2012 meta-analysis | F41: =Inputs!F45 -> % | G41: =Inputs!G45 -> input | H41: =Inputs!H45 -> 0.75 | I41: =Inputs!I45 -> - | J41: =Inputs!J45 -> - | K41: =Inputs!K45 -> - | L41: =Inputs!L45 -> - | M41: =Inputs!M45 -> - | ... AB41: =Inputs!AB45 -> -
E42: =HYPERLINK(buildUrl(CELL("address", Inputs!E46)), Inputs!E46) -> Estimated proportion of children targeted for SMC in trials that received SMC | F42: =Inputs!F46 -> % | G42: =Inputs!G46 -> input | H42: =Inputs!H46 -> 0.8977 | I42: - | J42: - | K42: - | L42: - | M42: - | N42: - | O42: - | P42: - | Q42: - | R42: - | S42: - | T42: - | U42: - | V42: - | W42: - | X42: - | Y42: - | Z42: - | AA42: - | AB42: -
E43: Implied reduction in malaria incidence among children under age 5 receiving SMC | F43: % | G43: calc | H43: =H41/H42 -> 0.83546842 | I43: - | J43: - | K43: - | L43: - | M43: - | N43: - | O43: - | P43: - | Q43: - | R43: - | S43: - | T43: - | U43: - | V43: - | W43: - | X43: - | Y43: - | Z43: - | AA43: - | AB43: -
E44: =HYPERLINK(buildUrl(CELL("address", Inputs!E47)), Inputs!E47) -> Internal validity adjustment | F44: =Inputs!F47 -> % | G44: =Inputs!G47 -> input | H44: =Inputs!H47 -> -0.05 | I44: =Inputs!I47 -> - | J44: =Inputs!J47 -> - | K44: =Inputs!K47 -> - | L44: =Inputs!L47 -> - | M44: =Inputs!M47 -> - | ... AB44: =Inputs!AB47 -> -
E45: =HYPERLINK(buildUrl(CELL("address", Inputs!E48)), Inputs!E48) -> External validity adjustment | F45: =Inputs!F48 -> % | G45: =Inputs!G48 -> input | H45: =Inputs!H48 -> 0 | I45: =Inputs!I48 -> - | J45: =Inputs!J48 -> - | K45: =Inputs!K48 -> - | L45: =Inputs!L48 -> - | M45: =Inputs!M48 -> - | ... AB45: =Inputs!AB48 -> -
E46: =HYPERLINK(buildUrl(CELL("address", Inputs!E49)), Inputs!E49) -> Adjustment for lower effectiveness outside the Sahel region of Africa | F46: =Inputs!F49 -> % | G46: =Inputs!G49 -> input | H46: =Inputs!H49 -> - | I46: =Inputs!I49 -> 0 | J46: =Inputs!J49 -> 0 | K46: =Inputs!K49 -> 0 | L46: =Inputs!L49 -> -0.25 | M46: =Inputs!M49 -> -0.25 | ... AB46: =Inputs!AB49 -> -0.25
E47: Expected reduction in malaria incidence among children under age 5 receiving SMC | F47: % | G47: calc | H47: - | I47: =$H43*(1+$H44)*(1+$H45)*(1+I46) -> 0.793695 | J47: =$H43*(1+$H44)*(1+$H45)*(1+J46) -> 0.793695 | K47: =$H43*(1+$H44)*(1+$H45)*(1+K46) -> 0.793695 | L47: =$H43*(1+$H44)*(1+$H45)*(1+L46) -> 0.59527125 | M47: =$H43*(1+$H44)*(1+$H45)*(1+M46) -> 0.59527125 | N47: =$H43*(1+$H44)*(1+$H45)*(1+N46) -> 0.59527125 | O47: =$H43*(1+$H44)*(1+$H45)*(1+O46) -> 0.59527125 | P47: =$H43*(1+$H44)*(1+$H45)*(1+P46) -> 0.59527125 | ... AB47: =$H43*(1+$H44)*(1+$H45)*(1+AB46) -> 0.59527125
E48: =HYPERLINK(buildUrl(CELL("address", Inputs!E50)), Inputs!E50) -> Ratio of the reduction in malaria mortality to the reduction in malaria incidence | F48: =Inputs!F50 -> % | G48: =Inputs!G50 -> input | H48: =Inputs!H50 -> 1 | I48: =Inputs!I50 -> - | J48: =Inputs!J50 -> - | K48: =Inputs!K50 -> - | L48: =Inputs!L50 -> - | M48: =Inputs!M50 -> - | ... AB48: =Inputs!AB50 -> -
E49: Expected reduction in malaria mortality among children under age 5 receiving SMC | F49: % | G49: calc | H49: - | I49: =I47*$H48 -> 0.793695 | J49: =J47*$H48 -> 0.793695 | K49: =K47*$H48 -> 0.793695 | L49: =L47*$H48 -> 0.59527125 | M49: =M47*$H48 -> 0.59527125 | N49: =N47*$H48 -> 0.59527125 | O49: =O47*$H48 -> 0.59527125 | P49: =P47*$H48 -> 0.59527125 | ... AB49: =AB47*$H48 -> 0.59527125
E50: =HYPERLINK(buildUrl(CELL("address", 'Counterfactual malaria'!E30)), 'Counterfactual malaria'!E30) -> Annual malaria mortality rate among 3-59-month-olds | F50: ='Counterfactual malaria'!F30 -> % | G50: supp | H50: ='Counterfactual malaria'!H30 -> - | I50: ='Counterfactual malaria'!I30 -> 0.0031550343 | J50: ='Counterfactual malaria'!J30 -> 0.0027922656 | K50: ='Counterfactual malaria'!K30 -> 0.0027416285 | L50: ='Counterfactual malaria'!L30 -> 0.0034548952 | M50: ='Counterfactual malaria'!M30 -> 0.0037111602 | N50: ='Counterfactual malaria'!N30 -> 0.004094441 | O50: ='Counterfactual malaria'!O30 -> 0.0044204672 | ... AB50: ='Counterfactual malaria'!AB30 -> 0.0022459667
E51: =HYPERLINK(buildUrl(CELL("address", Inputs!E52)), Inputs!E52) -> Indirect malaria deaths per direct malaria death | F51: =Inputs!F52 -> # | G51: =Inputs!G52 -> input | H51: =Inputs!H52 -> 0.75 | I51: =Inputs!I52 -> - | J51: =Inputs!J52 -> - | K51: =Inputs!K52 -> - | L51: =Inputs!L52 -> - | M51: =Inputs!M52 -> - | ... AB51: =Inputs!AB52 -> -
E52: Total malaria-attributable mortality rate (including direct and indirect malaria deaths) | F52: % | G52: calc | H52: - | I52: =I50*(1+$H51) -> 0.00552131 | J52: =J50*(1+$H51) -> 0.0048864648 | K52: =K50*(1+$H51) -> 0.0047978499 | L52: =L50*(1+$H51) -> 0.0060460666 | M52: =M50*(1+$H51) -> 0.0064945303 | N52: =N50*(1+$H51) -> 0.0071652717 | O52: =O50*(1+$H51) -> 0.0077358176 | P52: =P50*(1+$H51) -> 0.005631891 | ... AB52: =AB50*(1+$H51) -> 0.0039304417
E53: =HYPERLINK(buildUrl(CELL("address", Inputs!E51)), Inputs!E51) -> Relative reduction in mortality rate due to vaccine rollout | F53: =Inputs!F51 -> % | G53: =Inputs!G51 -> input | H53: =Inputs!H51 -> - | I53: =Inputs!I51 -> -0.14 | J53: =Inputs!J51 -> -0.02 | K53: =Inputs!K51 -> -0.12 | L53: =Inputs!L51 -> -0.11 | M53: =Inputs!M51 -> -0.11 | ... AB53: =Inputs!AB51 -> -0.17
E54: Total malaria-attributable mortality rate (including direct and indirect malaria deaths and adjustment for malaria vaccine rollout) | F54: % | G54: calc | H54: - | I54: =I50*(1+$H51)*(1+I53) -> 0.0047483266 | J54: =J50*(1+$H51)*(1+J53) -> 0.0047887355 | K54: =K50*(1+$H51)*(1+K53) -> 0.0042221079 | L54: =L50*(1+$H51)*(1+L53) -> 0.0053809993 | M54: =M50*(1+$H51)*(1+M53) -> 0.005780132 | N54: =N50*(1+$H51)*(1+N53) -> 0.0063770918 | O54: =O50*(1+$H51)*(1+O53) -> 0.0068848776 | P54: =P50*(1+$H51)*(1+P53) -> 0.0046744695 | ... AB54: =AB50*(1+$H51)*(1+AB53) -> 0.0032622666
E55: Expected number of annual malaria-attributable mortalities among the target population in the absence of SMC | F55: # | G55: calc | H55: - | I55: =I36*I54 -> 7.497935e-06 | J55: =J36*J54 -> 6.8265379e-06 | K55: =K36*K54 -> 3.6875176e-06 | L55: =L36*L54 -> 7.3559313e-06 | M55: =M36*M54 -> 7.9015534e-06 | N55: =N36*N54 -> 8.7176092e-06 | O55: =O36*O54 -> 9.4117623e-06 | P55: =P36*P54 -> 11000.217 | ... AB55: =AB36*AB54 -> 3.6790162e-06
E56: =HYPERLINK(buildUrl(CELL("address", Inputs!E53)), Inputs!E53) -> Proportion of annual malaria mortality that occurs during the SMC season | F56: =Inputs!F53 -> % | G56: =Inputs!G53 -> input | H56: =Inputs!H53 -> - | I56: =Inputs!I53 -> 0.7 | J56: =Inputs!J53 -> 0.7 | K56: =Inputs!K53 -> 0.7 | L56: =Inputs!L53 -> 0.515 | M56: =Inputs!M53 -> 0.515 | ... AB56: =Inputs!AB53 -> 0.62
E57: Expected number of malaria-attributable mortalities among the target population during the SMC season in the absence of SMC | F57: # | G57: calc | H57: - | I57: =I55*I56 -> 5.2485545e-06 | J57: =J55*J56 -> 4.7785765e-06 | K57: =K55*K56 -> 2.5812623e-06 | L57: =L55*L56 -> 3.7883046e-06 | M57: =M55*M56 -> 4.0693e-06 | N57: =N55*N56 -> 4.4895687e-06 | O57: =O55*O56 -> 4.8470576e-06 | P57: =P55*P56 -> 5665.1118 | ... AB57: =AB55*AB56 -> 2.28099e-06
E58: Total deaths averted among people under age 5 | F58: # | G58: calc | H58: - | I58: =I49*I57 -> 4.1657515e-06 | J58: =J49*J57 -> 3.7927323e-06 | K58: =K49*K57 -> 2.048735e-06 | L58: =L49*L57 -> 2.2550688e-06 | M58: =M49*M57 -> 2.4223373e-06 | N58: =N49*N57 -> 2.6725112e-06 | O58: =O49*O57 -> 2.885314e-06 | P58: =P49*P57 -> 3372.2782 | ... AB58: =AB49*AB57 -> 1.3578078e-06
C60: Mortality reduction among people age 5 and older (untreated population)
E61: =HYPERLINK(buildUrl(CELL("address", Inputs!E56)), Inputs!E56) -> Reduction in malaria incidence among the SMC-eligible population found in Cisse et al. 2016 | F61: =Inputs!F56 -> % | G61: =Inputs!G56 -> input | H61: =Inputs!H56 -> 0.6 | I61: =Inputs!I56 -> - | J61: =Inputs!J56 -> - | K61: =Inputs!K56 -> - | L61: =Inputs!L56 -> - | M61: =Inputs!M56 -> - | ... AB61: =Inputs!AB56 -> -
E62: =HYPERLINK(buildUrl(CELL("address", Inputs!E57)), Inputs!E57) -> Reduction in malaria incidence among the population too old to be eligible for SMC found in Cisse et al. 2016 | F62: =Inputs!F57 -> % | G62: =Inputs!G57 -> input | H62: =Inputs!H57 -> 0.26 | I62: =Inputs!I57 -> - | J62: =Inputs!J57 -> - | K62: =Inputs!K57 -> - | L62: =Inputs!L57 -> - | M62: =Inputs!M57 -> - | ... AB62: =Inputs!AB57 -> -
E63: Implied proportion of the protective effect of SMC received by the population too old to be eligible for SMC | F63: % | G63: calc | H63: =H62/H61 -> 0.43333333 | I63: - | J63: - | K63: - | L63: - | M63: - | N63: - | O63: - | P63: - | Q63: - | R63: - | S63: - | T63: - | U63: - | V63: - | W63: - | X63: - | Y63: - | Z63: - | AA63: - | AB63: -
E64: =HYPERLINK(buildUrl(CELL("address", Inputs!E58)), Inputs!E58) -> Adjustment for differences in program coverage and transmission intensity in the populations studied by the Cisse et al. 2016 trial and the populations targeted by grantee programs | F64: =Inputs!F58 -> % | G64: =Inputs!G58 -> input | H64: =Inputs!H58 -> -0.6912579 | I64: =Inputs!I58 -> - | J64: =Inputs!J58 -> - | K64: =Inputs!K58 -> - | L64: =Inputs!L58 -> - | M64: =Inputs!M58 -> - | ... AB64: =Inputs!AB58 -> -
E65: Expected proportion of the protective effect of SMC received by the population too old to be eligible for SMC | F65: % | G65: calc | H65: =H63*(1+H64) -> 0.13378824 | I65: - | J65: - | K65: - | L65: - | M65: - | N65: - | O65: - | P65: - | Q65: - | R65: - | S65: - | T65: - | U65: - | V65: - | W65: - | X65: - | Y65: - | Z65: - | AA65: - | AB65: -
E66: Expected reduction in malaria incidence among people age 5 and older | F66: % | G66: calc | H66: - | I66: =I49*$H65 -> 0.10618706 | J66: =J49*$H65 -> 0.10618706 | K66: =K49*$H65 -> 0.10618706 | L66: =L49*$H65 -> 0.079640295 | M66: =M49*$H65 -> 0.079640295 | N66: =N49*$H65 -> 0.079640295 | O66: =O49*$H65 -> 0.079640295 | P66: =P49*$H65 -> 0.079640295 | ... AB66: =AB49*$H65 -> 0.079640295
E67: =E48 -> Ratio of the reduction in malaria mortality to the reduction in malaria incidence | F67: =F48 -> % | G67: feed | H67: =H48 -> 1 | I67: =I48 -> - | J67: =J48 -> - | K67: =K48 -> - | L67: =L48 -> - | M67: =M48 -> - | N67: =N48 -> - | O67: =O48 -> - | ... AB67: =AB48 -> -
E68: Expected reduction in malaria mortality among people age 5 and older | F68: % | G68: calc | H68: - | I68: =I66*$H67 -> 0.10618706 | J68: =J66*$H67 -> 0.10618706 | K68: =K66*$H67 -> 0.10618706 | L68: =L66*$H67 -> 0.079640295 | M68: =M66*$H67 -> 0.079640295 | N68: =N66*$H67 -> 0.079640295 | O68: =O66*$H67 -> 0.079640295 | P68: =P66*$H67 -> 0.079640295 | ... AB68: =AB66*$H67 -> 0.079640295
E69: =HYPERLINK(buildUrl(CELL("address", 'Counterfactual malaria'!E35)), 'Counterfactual malaria'!E35) -> Malaria mortalities among people age 5 and older per malaria mortality among 3-59-month-olds | F69: ='Counterfactual malaria'!F35 -> # | G69: supp | H69: ='Counterfactual malaria'!H35 -> - | I69: ='Counterfactual malaria'!I35 -> 0.81407796 | J69: ='Counterfactual malaria'!J35 -> 0.65286404 | K69: ='Counterfactual malaria'!K35 -> 1.2422312 | L69: ='Counterfactual malaria'!L35 -> 0.35109492 | M69: ='Counterfactual malaria'!M35 -> 0.35092613 | N69: ='Counterfactual malaria'!N35 -> 0.35097276 | O69: ='Counterfactual malaria'!O35 -> 0.35121563 | ... AB69: ='Counterfactual malaria'!AB35 -> 0.39437985
E70: Expected number of malaria-attributable mortalities among the target population during the SMC season in the absence of SMC | F70: # | G70: calc | H70: - | I70: =I57*I69 -> 4.2727326e-06 | J70: =J57*J69 -> 3.1197608e-06 | K70: =K57*K69 -> 3.2065246e-06 | L70: =L57*L69 -> 1.3300545e-06 | M70: =M57*M69 -> 1.4280237e-06 | N70: =N57*N69 -> 1.5757163e-06 | O70: =O57*O69 -> 1.7023624e-06 | P70: =P57*P69 -> 9981.0701 | ... AB70: =AB57*AB69 -> 8.9957649e-07
E71: Total deaths averted among people age 5 and older | F71: # | G71: calc | H71: - | I71: =I68*I70 -> 4.5370891e-07 | J71: =J68*J70 -> 3.3127822e-07 | K71: =K68*K70 -> 3.4049141e-07 | L71: =L68*L70 -> 1.0592593e-07 | M71: =M68*M70 -> 1.1372823e-07 | N71: =N68*N70 -> 1.2549051e-07 | O71: =O68*O70 -> 1.3557664e-07 | P71: =P68*P70 -> 794.89537 | ... AB71: =AB68*AB70 -> 7.1642537e-08
C73: Malaria incidence reduction among people under age 15
E74: =HYPERLINK(buildUrl(CELL("address", 'Counterfactual malaria'!E43)), 'Counterfactual malaria'!E43) -> Adjusted malaria incidence among people under 5 | F74: ='Counterfactual malaria'!F43 -> % | G74: supp | H74: ='Counterfactual malaria'!H43 -> - | I74: ='Counterfactual malaria'!I43 -> 0.728 | J74: ='Counterfactual malaria'!J43 -> 0.47873 | K74: ='Counterfactual malaria'!K43 -> 0.78599 | L74: ='Counterfactual malaria'!L43 -> 0.76062 | M74: ='Counterfactual malaria'!M43 -> 0.91107 | N74: ='Counterfactual malaria'!N43 -> 0.96207 | O74: ='Counterfactual malaria'!O43 -> 0.93495 | ... AB74: ='Counterfactual malaria'!AB43 -> 0.90318
E75: =HYPERLINK(buildUrl(CELL("address", 'Counterfactual malaria'!E44)), 'Counterfactual malaria'!E44) -> Adjusted malaria incidence among people age 5 to 14 | F75: ='Counterfactual malaria'!F44 -> % | G75: supp | H75: ='Counterfactual malaria'!H44 -> - | I75: ='Counterfactual malaria'!I44 -> 0.30179 | J75: ='Counterfactual malaria'!J44 -> 0.21805 | K75: ='Counterfactual malaria'!K44 -> 0.32926 | L75: ='Counterfactual malaria'!L44 -> 0.31197 | M75: ='Counterfactual malaria'!M44 -> 0.37367 | N75: ='Counterfactual malaria'!N44 -> 0.39459 | O75: ='Counterfactual malaria'!O44 -> 0.38347 | ... AB75: ='Counterfactual malaria'!AB44 -> 0.38439
E76: Expected reduction in malaria incidence among people under 5 | F76: ppt | G76: calc | H76: - | I76: =I47*I56*I74 -> 0.40446697 | J76: =J47*J56*J74 -> 0.26597592 | K76: =K47*K56*K74 -> 0.43668543 | L76: =L47*L56*L74 -> 0.23317924 | M76: =M47*M56*M74 -> 0.27930189 | N76: =N47*N56*N74 -> 0.29493669 | O76: =O47*O56*O74 -> 0.28662266 | P76: =P47*P56*P74 -> 0.25221077 | ... AB76: =AB47*AB56*AB74 -> 0.33333499
E77: Expected reduction in malaria incidence among people age 5 to 14 | F77: ppt | G77: calc | H77: - | I77: =I66*I56*I75 -> 0.022432335 | J77: =J66*J56*J75 -> 0.016207862 | K77: =K66*K56*K75 -> 0.024474206 | L77: =L66*L56*L75 -> 0.012795372 | M77: =M66*M56*M75 -> 0.015325982 | N77: =N66*N56*N75 -> 0.016184011 | O77: =O66*O56*O75 -> 0.015727927 | P77: =P66*P56*P75 -> 0.014182901 | ... AB77: =AB66*AB56*AB75 -> 0.018980018
E78: =HYPERLINK(buildUrl(CELL("address", Inputs!E61)), Inputs!E61) -> National population under 5 | F78: =Inputs!F61 -> # | G78: =Inputs!G61 -> input | H78: =Inputs!H61 -> - | I78: =Inputs!I61 -> 4106465 | J78: =Inputs!J61 -> 3635515 | K78: =Inputs!K61 -> 4354391 | L78: =Inputs!L61 -> 13560740 | M78: =Inputs!M61 -> 13560740 | ... AB78: =Inputs!AB61 -> 7317718
E79: =HYPERLINK(buildUrl(CELL("address", Inputs!E62)), Inputs!E62) -> National population age 5 to 14 | F79: =Inputs!F62 -> # | G79: =Inputs!G62 -> input | H79: =Inputs!H62 -> - | I79: =Inputs!I62 -> 6265702 | J79: =Inputs!J62 -> 5379382 | K79: =Inputs!K62 -> 7217393 | L79: =Inputs!L62 -> 24438179 | M79: =Inputs!M62 -> 24438179 | ... AB79: =Inputs!AB62 -> 12517987
E80: Number of 5-14-year-olds exposed to spillover effects per person targeted to receive SMC | F80: # | G80: calc | H80: - | I80: =I79/I78 -> 1.5258141 | J80: =J79/J78 -> 1.4796754 | K80: =K79/K78 -> 1.6574977 | L80: =L79/L78 -> 1.8021272 | M80: =M79/M78 -> 1.8021272 | N80: =N79/N78 -> 1.8021272 | O80: =O79/O78 -> 1.8021272 | P80: =P79/P78 -> 1.7544722 | ... AB80: =AB79/AB78 -> 1.7106408
E81: Total 5-14-year-olds exposed to spillover effects from SMC | F81: # | G81: calc | H81: - | I81: =I36*I80 -> 0.0024093655 | J81: =J36*J80 -> 0.0021093376 | K81: =K36*K80 -> 0.0014476304 | L81: =L36*L80 -> 0.0024635432 | M81: =M36*M80 -> 0.0024635432 | N81: =N36*N80 -> 0.0024635432 | O81: =O36*O80 -> 0.0024635432 | P81: =P36*P80 -> 4128719.7 | ... AB81: =AB36*AB80 -> 0.0019291725
E82: Malaria cases averted among people under age 5 | F82: # | G82: calc | H82: - | I82: =I36*I76 -> 0.00063868122 | J82: =J36*J76 -> 0.00037915954 | K82: =K36*K76 -> 0.00038139366 | L82: =L36*L76 -> 0.00031876058 | M82: =M36*M76 -> 0.00038181115 | N82: =N36*N76 -> 0.00040318423 | O82: =O36*O76 -> 0.00039181878 | P82: =P36*P76 -> 593516.17 | ... AB82: =AB36*AB76 -> 0.00037591803
E83: Malaria cases averted among people age 5 to 14 | F83: # | G83: calc | H83: - | I83: =I77*I81 -> 5.4047695e-05 | J83: =J77*J81 -> 3.4187853e-05 | K83: =K77*K81 -> 3.5429605e-05 | L83: =L77*L81 -> 3.1521952e-05 | M83: =M77*M81 -> 3.7756219e-05 | N83: =N77*N81 -> 3.987001e-05 | O83: =O77*O81 -> 3.8746427e-05 | P83: =P77*P81 -> 58557.224 | ... AB83: =AB77*AB81 -> 3.661573e-05
C85: Long-term income increases for people under age 15
E86: =HYPERLINK(buildUrl(CELL("address", Inputs!E65)), Inputs!E65) -> Increase in annual income per malaria case averted among people under age 15 | F86: =Inputs!F65 -> % | G86: =Inputs!G65 -> input | H86: =Inputs!H65 -> 0.0064543 | I86: =Inputs!I65 -> - | J86: =Inputs!J65 -> - | K86: =Inputs!K65 -> - | L86: =Inputs!L65 -> - | M86: =Inputs!M65 -> - | ... AB86: =Inputs!AB65 -> -
E87: Adjusted increase in ln(income) per malaria case averted among people under age 15 | F87: ln($) | G87: calc | H87: =(ln(1+H86)-ln(1)) -> 0.0064335602 | I87: - | J87: - | K87: - | L87: - | M87: - | N87: - | O87: - | P87: - | Q87: - | R87: - | S87: - | T87: - | U87: - | V87: - | W87: - | X87: - | Y87: - | Z87: - | AA87: - | AB87: -
E88: =HYPERLINK(buildUrl(CELL("address", Inputs!E66)), Inputs!E66) -> Average number of years between receiving SMC and the beginning of long-term benefits | F88: =Inputs!F66 -> # | G88: =Inputs!G66 -> input | H88: =Inputs!H66 -> 12.5 | I88: =Inputs!I66 -> - | J88: =Inputs!J66 -> - | K88: =Inputs!K66 -> - | L88: =Inputs!L66 -> - | M88: =Inputs!M66 -> - | ... AB88: =Inputs!AB66 -> -
E89: =HYPERLINK(buildUrl(CELL("address", Inputs!E67)), Inputs!E67) -> Discount rate for future benefits | F89: =Inputs!F67 -> % | G89: =Inputs!G67 -> input | H89: =Inputs!H67 -> 0.04 | I89: =Inputs!I67 -> - | J89: =Inputs!J67 -> - | K89: =Inputs!K67 -> - | L89: =Inputs!L67 -> - | M89: =Inputs!M67 -> - | ... AB89: =Inputs!AB67 -> -
E90: Discounted increase in ln(income) per malaria case averted among people under age 15 | F90: ln($) | G90: calc | H90: =H87/(1+H89)^H88 -> 0.0039403484 | I90: - | J90: - | K90: - | L90: - | M90: - | N90: - | O90: - | P90: - | Q90: - | R90: - | S90: - | T90: - | U90: - | V90: - | W90: - | X90: - | Y90: - | Z90: - | AA90: - | AB90: -
E91: =HYPERLINK(buildUrl(CELL("address", Inputs!E68)), Inputs!E68) -> Expected number of years the long-term benefits of receiving SMC will last | F91: =Inputs!F68 -> # | G91: =Inputs!G68 -> input | H91: =Inputs!H68 -> 40 | I91: =Inputs!I68 -> - | J91: =Inputs!J68 -> - | K91: =Inputs!K68 -> - | L91: =Inputs!L68 -> - | M91: =Inputs!M68 -> - | ... AB91: =Inputs!AB68 -> -
E92: Present value of individual lifetime benefits per malaria case averted among people under age 15 | F92: ln($) | G92: calc | H92: =pv(H89,H91,-H90,,1) -> 0.081110043 | I92: - | J92: - | K92: - | L92: - | M92: - | N92: - | O92: - | P92: - | Q92: - | R92: - | S92: - | T92: - | U92: - | V92: - | W92: - | X92: - | Y92: - | Z92: - | AA92: - | AB92: -
E93: =HYPERLINK(buildUrl(CELL("address", Inputs!E69)), Inputs!E69) -> Multiplier for resource sharing within households | F93: =Inputs!F69 -> # | G93: =Inputs!G69 -> input | H93: =Inputs!H69 -> 2 | I93: =Inputs!I69 -> - | J93: =Inputs!J69 -> - | K93: =Inputs!K69 -> - | L93: =Inputs!L69 -> - | M93: =Inputs!M69 -> - | ... AB93: =Inputs!AB69 -> -
E94: Present value of total lifetime benefits per malaria case averted among people under age 15 | F94: ln($) | G94: calc | H94: =H92*H93 -> 0.16222009 | I94: - | J94: - | K94: - | L94: - | M94: - | N94: - | O94: - | P94: - | Q94: - | R94: - | S94: - | T94: - | U94: - | V94: - | W94: - | X94: - | Y94: - | Z94: - | AA94: - | AB94: -
E95: Present value of increase in units of annual ln(income) among people under age 5 | F95: ln($) | G95: calc | H95: - | I95: =I82*$H94 -> 0.00010360692 | J95: =J82*$H94 -> 6.1507293e-05 | K95: =K82*$H94 -> 6.1869713e-05 | L95: =L82*$H94 -> 5.1709368e-05 | M95: =M82*$H94 -> 6.1937437e-05 | N95: =N82*$H94 -> 6.540458e-05 | O95: =O82*$H94 -> 6.3560876e-05 | P95: =P82*$H94 -> 96280.244 | ... AB95: =AB82*$H94 -> 6.0981454e-05
E96: Present value of increase in units of annual ln(income) among people age 5 to 14 | F96: ln($) | G96: calc | H96: - | I96: =I83*$H94 -> 8.7676217e-06 | J96: =J83*$H94 -> 5.5459564e-06 | K96: =K83*$H94 -> 5.7473935e-06 | L96: =L83*$H94 -> 5.1134937e-06 | M96: =M83*$H94 -> 6.1248171e-06 | N96: =N83*$H94 -> 6.4677164e-06 | O96: =O83*$H94 -> 6.2854487e-06 | P96: =P83*$H94 -> 9499.1579 | ... AB96: =AB83*$H94 -> 5.9398069e-06
E97: Total present value of units of increase in units of annual ln(income) among people under age 15 | F97: ln($) | G97: calc | H97: - | I97: =SUM(I95:I96) -> 0.00011237454 | J97: =SUM(J95:J96) -> 6.7053249e-05 | K97: =SUM(K95:K96) -> 6.7617106e-05 | L97: =SUM(L95:L96) -> 5.6822861e-05 | M97: =SUM(M95:M96) -> 6.8062255e-05 | N97: =SUM(N95:N96) -> 7.1872296e-05 | O97: =SUM(O95:O96) -> 6.9846325e-05 | P97: =SUM(P95:P96) -> 105779.4 | ... AB97: =SUM(AB95:AB96) -> 6.6921261e-05
A99: Value of outcomes
C101: Units of value from mortality reduction among people under age 5
E102: =HYPERLINK(buildUrl(CELL("address", Inputs!E74)), Inputs!E74) -> Value assigned to averting a malaria-attributable death of a person under age 5 | F102: =Inputs!F74 -> UoV | G102: =Inputs!G74 -> input | H102: =Inputs!H74 -> 116.25262 | I102: =Inputs!I74 -> - | J102: =Inputs!J74 -> - | K102: =Inputs!K74 -> - | L102: =Inputs!L74 -> - | M102: =Inputs!M74 -> - | ... AB102: =Inputs!AB74 -> -
E103: Units of value from under-5 deaths averted (before accounting for leverage and funging) | F103: UoV | G103: calc | H103: - | I103: =I58*$H102 -> 0.00048427952 | J103: =J58*$H102 -> 0.00044091506 | K103: =K58*$H102 -> 0.00023817081 | L103: =L58*$H102 -> 0.00026215766 | M103: =M58*$H102 -> 0.00028160306 | N103: =N58*$H102 -> 0.00031068643 | O103: =O58*$H102 -> 0.00033542532 | P103: =P58*$H102 -> 392036.17 | ... AB103: =AB58*$H102 -> 0.00015784871
C105: Units of value from mortality reduction among people age 5 and older
E106: =HYPERLINK(buildUrl(CELL("address", Inputs!E75)), Inputs!E75) -> Value assigned to averting a malaria-attributable death of a person age 5 or older | F106: =Inputs!F75 -> UoV | G106: =Inputs!G75 -> input | H106: =Inputs!H75 -> 73.1914 | I106: =Inputs!I75 -> - | J106: =Inputs!J75 -> - | K106: =Inputs!K75 -> - | L106: =Inputs!L75 -> - | M106: =Inputs!M75 -> - | ... AB106: =Inputs!AB75 -> -
E107: Units of value from 5-and-over deaths averted (before accounting for leverage and funging) | F107: UoV | G107: calc | H107: - | I107: =I71*$H106 -> 3.320759e-05 | J107: =J71*$H106 -> 2.4246717e-05 | K107: =K71*$H106 -> 2.4921043e-05 | L107: =L71*$H106 -> 7.7528672e-06 | M107: =M71*$H106 -> 8.3239282e-06 | N107: =N71*$H106 -> 9.1848264e-06 | O107: =O71*$H106 -> 9.9230443e-06 | P107: =P71*$H106 -> 58179.505 | ... AB107: =AB71*$H106 -> 5.2436176e-06
C109: Units of value from long-term income increases for people under age 15
E110: =HYPERLINK(buildUrl(CELL("address", Inputs!E77)), Inputs!E77) -> Value assigned to increasing ln(consumption) by one unit for one person for one year | F110: =Inputs!F77 -> UoV | G110: =Inputs!G77 -> input | H110: =Inputs!H77 -> 1.442695 | I110: =Inputs!I77 -> - | J110: =Inputs!J77 -> - | K110: =Inputs!K77 -> - | L110: =Inputs!L77 -> - | M110: =Inputs!M77 -> - | ... AB110: =Inputs!AB77 -> -
E111: Units of value from long-term income increases (before accounting for leverage and funging) | F111: UoV | G111: calc | H111: - | I111: =I97*$H110 -> 0.0001621222 | J111: =J97*$H110 -> 9.673739e-05 | K111: =K97*$H110 -> 9.7550864e-05 | L111: =L97*$H110 -> 8.197806e-05 | M111: =M97*$H110 -> 9.8193077e-05 | N111: =N97*$H110 -> 0.00010368981 | O111: =O97*$H110 -> 0.00010076695 | P111: =P97*$H110 -> 152607.42 | ... AB111: =AB97*$H110 -> 9.6546972e-05
E112: Units of value generated from long-term income increases per year of SMC treatment | F112: UoV | G112: calc | H112: - | I112: =I111/I36 -> 0.10266949 | J112: =J111/J36 -> 0.067860133 | K112: =K111/K36 -> 0.1116931 | L112: =L111/L36 -> 0.059968462 | M112: =M111/M36 -> 0.071830046 | N112: =N111/N36 -> 0.075851004 | O112: =O111/O36 -> 0.073712879 | P112: =P111/P36 -> 0.064849514 | ... AB112: =AB111/AB36 -> 0.085610378
A114: Summary of outcomes and initial cost-effectiveness (before final adjustments)
C116: Summary of outcomes
E117: =HYPERLINK(buildUrl(CELL("address", E58)), E58) -> Total deaths averted among people under age 5 | F117: =F58 -> # | G117: feed | H117: =H58 -> - | I117: =I58 -> 4.1657515e-06 | J117: =J58 -> 3.7927323e-06 | K117: =K58 -> 2.048735e-06 | L117: =L58 -> 2.2550688e-06 | M117: =M58 -> 2.4223373e-06 | N117: =N58 -> 2.6725112e-06 | O117: =O58 -> 2.885314e-06 | ... AB117: =AB58 -> 1.3578078e-06
E118: =HYPERLINK(buildUrl(CELL("address", E71)), E71) -> Total deaths averted among people age 5 and older | F118: =F71 -> # | G118: feed | H118: =H71 -> - | I118: =I71 -> 4.5370891e-07 | J118: =J71 -> 3.3127822e-07 | K118: =K71 -> 3.4049141e-07 | L118: =L71 -> 1.0592593e-07 | M118: =M71 -> 1.1372823e-07 | N118: =N71 -> 1.2549051e-07 | O118: =O71 -> 1.3557664e-07 | ... AB118: =AB71 -> 7.1642537e-08
E119: Total malaria cases averted among people under age 15 | F119: # | G119: calc | H119: - | I119: =SUM(I82:I83) -> 0.00069272892 | J119: =SUM(J82:J83) -> 0.00041334739 | K119: =SUM(K82:K83) -> 0.00041682327 | L119: =SUM(L82:L83) -> 0.00035028253 | M119: =SUM(M82:M83) -> 0.00041956737 | N119: =SUM(N82:N83) -> 0.00044305424 | O119: =SUM(O82:O83) -> 0.00043056521 | P119: =SUM(P82:P83) -> 652073.4 | ... AB119: =SUM(AB82:AB83) -> 0.00041253376
...

Sheet Counterfactual malaria
I1: Malaria Consortium | S1: Malaria Consortium
I2: Burkina Faso | J2: Chad | K2: Côte d'Ivoire | L2: DRC | M2: DRC | N2: DRC | O2: DRC | P2: Mozambique | Q2: Nigeria | R2: Nigeria | S2: Nigeria | T2: Nigeria | U2: Nigeria | V2: Nigeria | W2: Nigeria | X2: Nigeria | Y2: Nigeria | Z2: South Sudan | AA2: Togo | AB2: Uganda
A3: Supplemental calculations for counterfactual malaria mortality and incidence rates | H3: Overall | L3: Haut-Katanga | M3: Haut-Lomami | N3: Lualaba | O3: Tanganyika | P3: Nampula | Q3: Bauchi | R3: Borno | S3: FCT (Abuja) | T3: Kebbi | U3: Kogi | V3: Nasarawa | W3: Oyo | X3: Plateau | Y3: Sokoto | Z3: Northern Bahr El Ghazal | AB3: Karamoja
E4: Final cost-effectiveness estimate (pulled from "Main calcs" sheet for visibility) | F4: ='Main CEA'!F193 -> xcash | G4: main | H4: ='Main CEA'!H193 -> - | I4: ='Main CEA'!I193 -> 13.310868 | J4: ='Main CEA'!J193 -> 14.65303 | K4: ='Main CEA'!K193 -> 8.5184856 | L4: ='Main CEA'!L193 -> 10.227025 | M4: ='Main CEA'!M193 -> 11.22453 | N4: ='Main CEA'!N193 -> 12.200271 | O4: ='Main CEA'!O193 -> 12.821222 | ... AB4: ='Main CEA'!AB193 -> 6.7780673
A5: Malaria mortality among the SMC-eligible population
C7: Malaria mortalities per year among people under age 5
E8: =HYPERLINK(buildUrl(CELL("address", Inputs!E22)), Inputs!E22) -> Malaria mortalities per year among people under age 5 | F8: =Inputs!F22 -> # | G8: =Inputs!G22 -> input | H8: =Inputs!H22 -> - | I8: =Inputs!I22 -> 6910 | J8: =Inputs!J22 -> 582 | K8: =Inputs!K22 -> 2780 | L8: =Inputs!L22 -> 2766 | M8: =Inputs!M22 -> 2408 | ... AB8: =Inputs!AB22 -> 4689
E9: =HYPERLINK(buildUrl(CELL("address", Inputs!E23)), Inputs!E23) -> Early neonatal malaria mortalities per year (babies under 7 days old) | F9: =Inputs!F23 -> # | G9: =Inputs!G23 -> input | H9: =Inputs!H23 -> - | I9: =Inputs!I23 -> 0 | J9: =Inputs!J23 -> 0 | K9: =Inputs!K23 -> 0 | L9: =Inputs!L23 -> 0 | M9: =Inputs!M23 -> 0 | ... AB9: =Inputs!AB23 -> 0
E10: =HYPERLINK(buildUrl(CELL("address", Inputs!E24)), Inputs!E24) -> Late neonatal malaria mortalities per year (babies between 7 and 27 days old) | F10: =Inputs!F24 -> # | G10: =Inputs!G24 -> input | H10: =Inputs!H24 -> - | I10: =Inputs!I24 -> 315 | J10: =Inputs!J24 -> 24 | K10: =Inputs!K24 -> 135 | L10: =Inputs!L24 -> 165 | M10: =Inputs!M24 -> 143 | ... AB10: =Inputs!AB24 -> 281
E11: =HYPERLINK(buildUrl(CELL("address", Inputs!E25)), Inputs!E25) -> Post-neonatal malaria mortalities per year (babies between 28 and 364 days old) | F11: =Inputs!F25 -> # | G11: =Inputs!G25 -> input | H11: =Inputs!H25 -> - | I11: =Inputs!I25 -> 2269 | J11: =Inputs!J25 -> 171 | K11: =Inputs!K25 -> 1048 | L11: =Inputs!L25 -> 1131 | M11: =Inputs!M25 -> 985 | ... AB11: =Inputs!AB25 -> 2056
C13: Estimated malaria mortalities per year among the SMC-eligible population
E14: =HYPERLINK(buildUrl(CELL("address", Inputs!E26)), Inputs!E26) -> Number of post-neonatal months of life in which children are under 1 year old | F14: =Inputs!F26 -> # | G14: =Inputs!G26 -> input | H14: =Inputs!H26 -> 11 | I14: =Inputs!I26 -> - | J14: =Inputs!J26 -> - | K14: =Inputs!K26 -> - | L14: =Inputs!L26 -> - | M14: =Inputs!M26 -> - | ... AB14: =Inputs!AB26 -> -
E15: =HYPERLINK(buildUrl(CELL("address", Inputs!E27)), Inputs!E27) -> Number of post-neonatal months of life in which children are under 3 months old | F15: =Inputs!F27 -> # | G15: =Inputs!G27 -> input | H15: =Inputs!H27 -> 2 | I15: =Inputs!I27 -> - | J15: =Inputs!J27 -> - | K15: =Inputs!K27 -> - | L15: =Inputs!L27 -> - | M15: =Inputs!M27 -> - | ... AB15: =Inputs!AB27 -> -
E16: Proportion of post-neonatal malaria mortalities that are among 1-2-month-olds | F16: % | G16: calc | H16: =H15/H14 -> 0.18181818 | I16: - | J16: - | K16: - | L16: - | M16: - | N16: - | O16: - | P16: - | Q16: - | R16: - | S16: - | T16: - | U16: - | V16: - | W16: - | X16: - | Y16: - | Z16: - | AA16: - | AB16: -
E17: Estimated malaria mortalities per year among 1-2-month-olds | F17: # | G17: calc | H17: - | I17: =I11*$H16 -> 412.54545 | J17: =J11*$H16 -> 31.090909 | K17: =K11*$H16 -> 190.54545 | L17: =L11*$H16 -> 205.63636 | M17: =M11*$H16 -> 179.09091 | N17: =N11*$H16 -> 130.36364 | O17: =O11*$H16 -> 186.54545 | P17: =P11*$H16 -> 316.54545 | ... AB17: =AB11*$H16 -> 373.81818
E18: Total malaria mortalities per year among 3-59-month-olds | F18: # | G18: calc | H18: - | I18: =I8-SUM(I9:I10,I17) -> 6182.4545 | J18: =J8-SUM(J9:J10,J17) -> 526.90909 | K18: =K8-SUM(K9:K10,K17) -> 2454.4545 | L18: =L8-SUM(L9:L10,L17) -> 2395.3636 | M18: =M8-SUM(M9:M10,M17) -> 2085.9091 | N18: =N8-SUM(N9:N10,N17) -> 1518.6364 | O18: =O8-SUM(O9:O10,O17) -> 2172.4545 | P18: =P8-SUM(P9:P10,P17) -> 3245.4545 | ... AB18: =AB8-SUM(AB9:AB10,AB17) -> 4034.1818
E19: Proportion of malaria mortalities among people under age 5 that occur among 3-59-month-olds | F19: % | G19: calc | H19: - | I19: =I18/I8 -> 0.89471122 | J19: =J18/J8 -> 0.90534208 | K19: =K18/K8 -> 0.88289732 | L19: =L18/L8 -> 0.86600276 | M19: =M18/M8 -> 0.86624132 | N19: =N18/N8 -> 0.86630711 | O19: =O18/O8 -> 0.86586471 | P19: =P18/P8 -> 0.87102913 | ... AB19: =AB18/AB8 -> 0.86035014
C21: Annual malaria mortality rate among the SMC-eligible population
E22: =HYPERLINK(buildUrl(CELL("address", Inputs!E30)), Inputs!E30) -> Annual malaria mortality rate among people under age 5 | F22: =Inputs!F30 -> per 100k | G22: =Inputs!G30 -> input | H22: =Inputs!H30 -> - | I22: =Inputs!I30 -> 335 | J22: =Inputs!J30 -> 293 | K22: =Inputs!K30 -> 295 | L22: =Inputs!L30 -> 379 | M22: =Inputs!M30 -> 407 | ... AB22: =Inputs!AB30 -> 248
E23: Implied population of people under age 5 | F23: # | G23: calc | H23: - | I23: =I8/I22*100000 -> 2062686.6 | J23: =J8/J22*100000 -> 198634.81 | K23: =K8/K22*100000 -> 942372.88 | L23: =L8/L22*100000 -> 729815.3 | M23: =M8/M22*100000 -> 591646.19 | N23: =N8/N22*100000 -> 390423.16 | O23: =O8/O22*100000 -> 517319.59 | P23: =P8/P22*100000 -> 1061538.5 | ... AB23: =AB8/AB22*100000 -> 1890725.8
E24: =HYPERLINK(buildUrl(CELL("address", Inputs!E31)), Inputs!E31) -> Total number of months of life in which children are under 5 years old | F24: =Inputs!F31 -> # | G24: =Inputs!G31 -> input | H24: =Inputs!H31 -> 60 | I24: =Inputs!I31 -> - | J24: =Inputs!J31 -> - | K24: =Inputs!K31 -> - | L24: =Inputs!L31 -> - | M24: =Inputs!M31 -> - | ... AB24: =Inputs!AB31 -> -
E25: =HYPERLINK(buildUrl(CELL("address", Inputs!E32)), Inputs!E32) -> Number of months of life in which children are under 3 months old | F25: =Inputs!F32 -> # | G25: =Inputs!G32 -> input | H25: =Inputs!H32 -> 3 | I25: =Inputs!I32 -> - | J25: =Inputs!J32 -> - | K25: =Inputs!K32 -> - | L25: =Inputs!L32 -> - | M25: =Inputs!M32 -> - | ... AB25: =Inputs!AB32 -> -
E26: Proportion of people under age 5 who are 3-59-month-olds | F26: % | G26: calc | H26: =(H24-H25)/H24 -> 0.95 | I26: - | J26: - | K26: - | L26: - | M26: - | N26: - | O26: - | P26: - | Q26: - | R26: - | S26: - | T26: - | U26: - | V26: - | W26: - | X26: - | Y26: - | Z26: - | AA26: - | AB26: -
E27: Estimated population of 3-59-month olds | F27: # | G27: calc | H27: - | I27: =I23*$H26 -> 1959552.2 | J27: =J23*$H26 -> 188703.07 | K27: =K23*$H26 -> 895254.24 | L27: =L23*$H26 -> 693324.54 | M27: =M23*$H26 -> 562063.88 | N27: =N23*$H26 -> 370902 | O27: =O23*$H26 -> 491453.61 | P27: =P23*$H26 -> 1008461.5 | ... AB27: =AB23*$H26 -> 1796189.5
E28: Unadjusted annual malaria mortality rate among 3-59-month-olds | F28: % | G28: calc | H28: - | I28: =I18/I27 -> 0.0031550343 | J28: =J18/J27 -> 0.0027922656 | K28: =K18/K27 -> 0.0027416285 | L28: =L18/L27 -> 0.0034548952 | M28: =M18/M27 -> 0.0037111602 | N28: =N18/N27 -> 0.004094441 | O28: =O18/O27 -> 0.0044204672 | P28: =P18/P27 -> 0.0032182234 | ... AB28: =AB18/AB27 -> 0.0022459667
E29: =HYPERLINK(buildUrl(CELL("address", Inputs!E33)), Inputs!E33) -> Adjustment for malaria averted by ITN distributions not accounted for in GBD 2019 | F29: =Inputs!F33 -> % | G29: =Inputs!G33 -> input | H29: =Inputs!H33 -> - | I29: =Inputs!I33 -> 0 | J29: =Inputs!J33 -> 0 | K29: =Inputs!K33 -> 0 | L29: =Inputs!L33 -> 0 | M29: =Inputs!M33 -> 0 | ... AB29: =Inputs!AB33 -> 0
E30: Annual malaria mortality rate among 3-59-month-olds | F30: % | G30: calc | H30: - | I30: =I28*(1+I29) -> 0.0031550343 | J30: =J28*(1+J29) -> 0.0027922656 | K30: =K28*(1+K29) -> 0.0027416285 | L30: =L28*(1+L29) -> 0.0034548952 | M30: =M28*(1+M29) -> 0.0037111602 | N30: =N28*(1+N29) -> 0.004094441 | O30: =O28*(1+O29) -> 0.0044204672 | P30: =P28*(1+P29) -> 0.0032182234 | ... AB30: =AB28*(1+AB29) -> 0.0022459667
C32: Proportion of malaria mortalities that are among the SMC-eligible population
E33: =HYPERLINK(buildUrl(CELL("address", Inputs!E36)), Inputs!E36) -> Total malaria mortalities per year | F33: =Inputs!F36 -> # | G33: =Inputs!G36 -> input | H33: =Inputs!H36 -> - | I33: =Inputs!I36 -> 11943 | J33: =Inputs!J36 -> 926 | K33: =Inputs!K36 -> 5829 | L33: =Inputs!L36 -> 3607 | M33: =Inputs!M36 -> 3140 | ... AB33: =Inputs!AB36 -> 6280
E34: Malaria mortalities per year among people age 5 and older | F34: # | G34: calc | H34: - | I34: =I33-I8 -> 5033 | J34: =J33-J8 -> 344 | K34: =K33-K8 -> 3049 | L34: =L33-L8 -> 841 | M34: =M33-M8 -> 732 | N34: =N33-N8 -> 533 | O34: =O33-O8 -> 763 | P34: =P33-P8 -> 5718 | ... AB34: =AB33-AB8 -> 1591
E35: Malaria mortalities among people age 5 and older per malaria mortality among 3-59-month-olds | F35: # | G35: calc | H35: - | I35: =I34/I18 -> 0.81407796 | J35: =J34/J18 -> 0.65286404 | K35: =K34/K18 -> 1.2422312 | L35: =L34/L18 -> 0.35109492 | M35: =M34/M18 -> 0.35092613 | N35: =N34/N18 -> 0.35097276 | O35: =O34/O18 -> 0.35121563 | P35: =P34/P18 -> 1.7618487 | ... AB35: =AB34/AB18 -> 0.39437985
A37: Malaria incidence among the SMC-eligible population
C39: Malaria incidence among people under age 15
E40: =HYPERLINK(buildUrl(CELL("address", Inputs!E39)), Inputs!E39) -> Malaria incidence among people under 5 | F40: =Inputs!F39 -> per 100k | G40: =Inputs!G39 -> input | H40: =Inputs!H39 -> - | I40: =Inputs!I39 -> 72800 | J40: =Inputs!J39 -> 47873 | K40: =Inputs!K39 -> 78599 | L40: =Inputs!L39 -> 76062 | M40: =Inputs!M39 -> 91107 | ... AB40: =Inputs!AB39 -> 90318
E41: =HYPERLINK(buildUrl(CELL("address", Inputs!E40)), Inputs!E40) -> Malaria incidence among people age 5 to 14 | F41: =Inputs!F40 -> per 100k | G41: =Inputs!G40 -> input | H41: =Inputs!H40 -> - | I41: =Inputs!I40 -> 30179 | J41: =Inputs!J40 -> 21805 | K41: =Inputs!K40 -> 32926 | L41: =Inputs!L40 -> 31197 | M41: =Inputs!M40 -> 37367 | ... AB41: =Inputs!AB40 -> 38439
E42: =HYPERLINK(buildUrl(CELL("address", Inputs!E33)), Inputs!E33) -> Adjustment for malaria averted by ITN distributions not accounted for in GBD 2019 | F42: =Inputs!F33 -> % | G42: =Inputs!G33 -> input | H42: =Inputs!H33 -> - | I42: =Inputs!I33 -> 0 | J42: =Inputs!J33 -> 0 | K42: =Inputs!K33 -> 0 | L42: =Inputs!L33 -> 0 | M42: =Inputs!M33 -> 0 | ... AB42: =Inputs!AB33 -> 0
E43: Adjusted malaria incidence among people under 5 | F43: % | G43: calc | H43: - | I43: =(I40/100000)*(1+I42) -> 0.728 | J43: =(J40/100000)*(1+J42) -> 0.47873 | K43: =(K40/100000)*(1+K42) -> 0.78599 | L43: =(L40/100000)*(1+L42) -> 0.76062 | M43: =(M40/100000)*(1+M42) -> 0.91107 | N43: =(N40/100000)*(1+N42) -> 0.96207 | O43: =(O40/100000)*(1+O42) -> 0.93495 | P43: =(P40/100000)*(1+P42) -> 0.8227 | ... AB43: =(AB40/100000)*(1+AB42) -> 0.90318
E44: Adjusted malaria incidence among people age 5 to 14 | F44: % | G44: calc | H44: - | I44: =(I41/100000)*(1+I42) -> 0.30179 | J44: =(J41/100000)*(1+J42) -> 0.21805 | K44: =(K41/100000)*(1+K42) -> 0.32926 | L44: =(L41/100000)*(1+L42) -> 0.31197 | M44: =(M41/100000)*(1+M42) -> 0.37367 | N44: =(N41/100000)*(1+N42) -> 0.39459 | O44: =(O41/100000)*(1+O42) -> 0.38347 | P44: =(P41/100000)*(1+P42) -> 0.3458 | ... AB44: =(AB41/100000)*(1+AB42) -> 0.38439

Sheet LeverageFunging
I1: Malaria Consortium | S1: Malaria Consortium
I2: Burkina Faso | J2: Chad | K2: Côte d'Ivoire | L2: DRC | M2: DRC | N2: DRC | O2: DRC | P2: Mozambique | Q2: Nigeria | R2: Nigeria | S2: Nigeria | T2: Nigeria | U2: Nigeria | V2: Nigeria | W2: Nigeria | X2: Nigeria | Y2: Nigeria | Z2: South Sudan | AA2: Togo | AB2: Uganda
A3: Supplemental calculations for the leverage/funging adjustment | F3: unit | G3: type | H3: Overall | L3: Haut-Katanga | M3: Haut-Lomami | N3: Lualaba | O3: Tanganyika | P3: Nampula | Q3: Bauchi | R3: Borno | S3: FCT (Abuja) | T3: Kebbi | U3: Kogi | V3: Nasarawa | W3: Oyo | X3: Plateau | Y3: Sokoto | Z3: Northern Bahr El Ghazal | AB3: Karamoja
E4: Final cost-effectiveness estimate (pulled from "Main calcs" sheet for visibility) | F4: ='Main CEA'!F193 -> xcash | G4: main | H4: ='Main CEA'!H193 -> - | I4: ='Main CEA'!I193 -> 13.310868 | J4: ='Main CEA'!J193 -> 14.65303 | K4: ='Main CEA'!K193 -> 8.5184856 | L4: ='Main CEA'!L193 -> 10.227025 | M4: ='Main CEA'!M193 -> 11.22453 | N4: ='Main CEA'!N193 -> 12.200271 | O4: ='Main CEA'!O193 -> 12.821222 | ... AB4: ='Main CEA'!AB193 -> 6.7780673
A5: Costs
C7: GiveWell costs
E8: =HYPERLINK(buildUrl(CELL("address", Inputs!E8)), Inputs!E8) -> Grant size | F8: =Inputs!F8 -> $ | G8: =Inputs!G8 -> input | H8: =Inputs!H8 -> - | I8: =Inputs!I8 -> 0.01 | J8: =Inputs!J8 -> 0.01 | K8: =Inputs!K8 -> 0.01 | L8: =Inputs!L8 -> 0.01 | M8: =Inputs!M8 -> 0.01 | ... AB8: =Inputs!AB8 -> 0.01
C10: Cost breakdown
E11: =HYPERLINK(buildUrl(CELL("address", Inputs!E11)), Inputs!E11) -> Percentage of total costs covered by the grantee | F11: =Inputs!F11 -> % | G11: =Inputs!G11 -> input | H11: =Inputs!H11 -> - | I11: =Inputs!I11 -> 0.8944838 | J11: =Inputs!J11 -> 0.90224903 | K11: =Inputs!K11 -> 0.906659 | L11: =Inputs!L11 -> 0.50149962 | M11: =Inputs!M11 -> 0.50149962 | ... AB11: =Inputs!AB11 -> 0.89331272
E12: =HYPERLINK(buildUrl(CELL("address", Inputs!E12)), Inputs!E12) -> Percentage of total costs covered by other philanthropic actors | F12: =Inputs!F12 -> % | G12: =Inputs!G12 -> input | H12: =Inputs!H12 -> - | I12: =Inputs!I12 -> 0 | J12: =Inputs!J12 -> 0 | K12: =Inputs!K12 -> 0 | L12: =Inputs!L12 -> 0.43937414 | M12: =Inputs!M12 -> 0.43937414 | ... AB12: =Inputs!AB12 -> 0
E13: =HYPERLINK(buildUrl(CELL("address", Inputs!E13)), Inputs!E13) -> Percentage of total costs covered by domestic governments | F13: =Inputs!F13 -> % | G13: =Inputs!G13 -> input | H13: =Inputs!H13 -> - | I13: =Inputs!I13 -> 0.1055162 | J13: =Inputs!J13 -> 0.09775097 | K13: =Inputs!K13 -> 0.093341 | L13: =Inputs!L13 -> 0.05912624 | M13: =Inputs!M13 -> 0.05912624 | ... AB13: =Inputs!AB13 -> 0.10668728
C15: Total costs
E16: =HYPERLINK(buildUrl(CELL("address", 'Main CEA'!E16)), 'Main CEA'!E16) -> Total spending by all contributors | F16: ='Main CEA'!F16 -> $ | G16: main | H16: ='Main CEA'!H16 -> - | I16: ='Main CEA'!I16 -> 0.011179632 | J16: ='Main CEA'!J16 -> 0.011083415 | K16: ='Main CEA'!K16 -> 0.011029505 | L16: ='Main CEA'!L16 -> 0.019940195 | M16: ='Main CEA'!M16 -> 0.019940195 | N16: ='Main CEA'!N16 -> 0.019940195 | O16: ='Main CEA'!O16 -> 0.019940195 | ... AB16: ='Main CEA'!AB16 -> 0.011194288
C18: Total spending attributable to different actors
E19: =HYPERLINK(buildUrl(CELL("address", 'Main CEA'!E19)), 'Main CEA'!E19) -> Total spending contributed by grantee | F19: ='Main CEA'!F19 -> $ | G19: main | H19: ='Main CEA'!H19 -> - | I19: ='Main CEA'!I19 -> 0.01 | J19: ='Main CEA'!J19 -> 0.01 | K19: ='Main CEA'!K19 -> 0.01 | L19: ='Main CEA'!L19 -> 0.01 | M19: ='Main CEA'!M19 -> 0.01 | N19: ='Main CEA'!N19 -> 0.01 | O19: ='Main CEA'!O19 -> 0.01 | ... AB19: ='Main CEA'!AB19 -> 0.01
E20: =HYPERLINK(buildUrl(CELL("address", 'Main CEA'!E20)), 'Main CEA'!E20) -> Total spending contributed by other philanthropic actors | F20: ='Main CEA'!F20 -> $ | G20: main | H20: ='Main CEA'!H20 -> - | I20: ='Main CEA'!I20 -> 0 | J20: ='Main CEA'!J20 -> 0 | K20: ='Main CEA'!K20 -> 0 | L20: ='Main CEA'!L20 -> 0.0087612059 | M20: ='Main CEA'!M20 -> 0.0087612059 | N20: ='Main CEA'!N20 -> 0.0087612059 | O20: ='Main CEA'!O20 -> 0.0087612059 | ... AB20: ='Main CEA'!AB20 -> 0
E21: =HYPERLINK(buildUrl(CELL("address", 'Main CEA'!E21)), 'Main CEA'!E21) -> Total spending contributed by domestic governments | F21: ='Main CEA'!F21 -> $ | G21: main | H21: ='Main CEA'!H21 -> - | I21: ='Main CEA'!I21 -> 0.0011796323 | J21: ='Main CEA'!J21 -> 0.0010834145 | K21: ='Main CEA'!K21 -> 0.001029505 | L21: ='Main CEA'!L21 -> 0.0011789887 | M21: ='Main CEA'!M21 -> 0.0011789887 | N21: ='Main CEA'!N21 -> 0.0011789887 | O21: ='Main CEA'!O21 -> 0.0011789887 | ... AB21: ='Main CEA'!AB21 -> 0.0011942882
C23: Upstream / downstream spending
E24: =HYPERLINK(buildUrl(CELL("address", 'Main CEA'!E24)), 'Main CEA'!E24) -> Total spending causally upstream of donations to grantee | F24: ='Main CEA'!F24 -> $ | G24: main | H24: ='Main CEA'!H24 -> - | I24: ='Main CEA'!I24 -> 0.01 | J24: ='Main CEA'!J24 -> 0.01 | K24: ='Main CEA'!K24 -> 0.01 | L24: ='Main CEA'!L24 -> 0.018761206 | M24: ='Main CEA'!M24 -> 0.018761206 | N24: ='Main CEA'!N24 -> 0.018761206 | O24: ='Main CEA'!O24 -> 0.018761206 | ... AB24: ='Main CEA'!AB24 -> 0.01
E25: =HYPERLINK(buildUrl(CELL("address", 'Main CEA'!E25)), 'Main CEA'!E25) -> Total spending causally downstream of donations to grantee | F25: ='Main CEA'!F25 -> $ | G25: main | H25: ='Main CEA'!H25 -> - | I25: ='Main CEA'!I25 -> 0.0011796323 | J25: ='Main CEA'!J25 -> 0.0010834145 | K25: ='Main CEA'!K25 -> 0.001029505 | L25: ='Main CEA'!L25 -> 0.0011789887 | M25: ='Main CEA'!M25 -> 0.0011789887 | N25: ='Main CEA'!N25 -> 0.0011789887 | O25: ='Main CEA'!O25 -> 0.0011789887 | ... AB25: ='Main CEA'!AB25 -> 0.0011942882
A27: Counterfactual funding scenarios
C29: Probability of scenarios in the absence of philanthropic funding
E30: =HYPERLINK(buildUrl(CELL("address", Inputs!E114)), Inputs!E114) -> Scenario 1: Domestic governments would replace the grantee's costs | F30: =Inputs!F114 -> % | G30: =Inputs!G114 -> input | H30: =Inputs!H114 -> - | I30: =Inputs!I114 -> 0 | J30: =Inputs!J114 -> 0 | K30: =Inputs!K114 -> 0 | L30: =Inputs!L114 -> 0 | M30: =Inputs!M114 -> 0 | ... AB30: =Inputs!AB114 -> 0
E31: =HYPERLINK(buildUrl(CELL("address", Inputs!E115)), Inputs!E115) -> Scenario 2: Global Fund and/or PMI would replace the grantee's costs | F31: =Inputs!F115 -> % | G31: =Inputs!G115 -> input | H31: =Inputs!H115 -> - | I31: =Inputs!I115 -> 0.5 | J31: =Inputs!J115 -> 0.3 | K31: =Inputs!K115 -> 0.4 | L31: =Inputs!L115 -> 0.15 | M31: =Inputs!M115 -> 0.15 | ... AB31: =Inputs!AB115 -> 0.4
E32: =HYPERLINK(buildUrl(CELL("address", Inputs!E116)), Inputs!E116) -> Scenario 3: Other actors' upstream costs would stay the same (downstream costs would shrink in proportion to the total size of the program) | F32: =Inputs!F116 -> % | G32: =Inputs!G116 -> input | H32: =Inputs!H116 -> - | I32: =Inputs!I116 -> 0 | J32: =Inputs!J116 -> 0 | K32: =Inputs!K116 -> 0 | L32: =Inputs!L116 -> 0 | M32: =Inputs!M116 -> 0 | ... AB32: =Inputs!AB116 -> 0
E33: Scenario 4: Distributions would go unfunded | F33: % | G33: calc | H33: - | I33: =1-SUM(I30:I32) -> 0.5 | J33: =1-SUM(J30:J32) -> 0.7 | K33: =1-SUM(K30:K32) -> 0.6 | L33: =1-SUM(L30:L32) -> 0.85 | M33: =1-SUM(M30:M32) -> 0.85 | N33: =1-SUM(N30:N32) -> 0.85 | O33: =1-SUM(O30:O32) -> 0.85 | P33: =1-SUM(P30:P32) -> 0.65 | ... AB33: =1-SUM(AB30:AB32) -> 0.6
C35: Proportion of the program that would still occur in each scenario
E36: =HYPERLINK(buildUrl(CELL("address", Inputs!E119)), Inputs!E119) -> Scenario 1: Domestic governments would replace the grantee's costs | F36: =Inputs!F119 -> % | G36: =Inputs!G119 -> input | H36: =Inputs!H119 -> 1 | I36: =Inputs!I119 -> - | J36: =Inputs!J119 -> - | K36: =Inputs!K119 -> - | L36: =Inputs!L119 -> - | M36: =Inputs!M119 -> - | ... AB36: =Inputs!AB119 -> -
E37: =HYPERLINK(buildUrl(CELL("address", Inputs!E120)), Inputs!E120) -> Scenario 2: Global Fund and/or PMI would replace the grantee's costs | F37: =Inputs!F120 -> % | G37: =Inputs!G120 -> input | H37: =Inputs!H120 -> 1 | I37: =Inputs!I120 -> - | J37: =Inputs!J120 -> - | K37: =Inputs!K120 -> - | L37: =Inputs!L120 -> - | M37: =Inputs!M120 -> - | ... AB37: =Inputs!AB120 -> -
E38: Scenario 3: Other actors' upstream costs would stay the same (downstream costs would shrink in proportion to the total size of the program) | F38: % | G38: calc | H38: - | I38: =I20/I24 -> 0 | J38: =J20/J24 -> 0 | K38: =K20/K24 -> 0 | L38: =L20/L24 -> 0.46698522 | M38: =M20/M24 -> 0.46698522 | N38: =N20/N24 -> 0.46698522 | O38: =O20/O24 -> 0.46698522 | P38: =P20/P24 -> 0 | ... AB38: =AB20/AB24 -> 0
E39: =HYPERLINK(buildUrl(CELL("address", Inputs!E121)), Inputs!E121) -> Scenario 4: Distributions would go unfunded | F39: =Inputs!F121 -> % | G39: =Inputs!G121 -> input | H39: =Inputs!H121 -> 0 | I39: =Inputs!I121 -> - | J39: =Inputs!J121 -> - | K39: =Inputs!K121 -> - | L39: =Inputs!L121 -> - | M39: =Inputs!M121 -> - | ... AB39: =Inputs!AB121 -> -
A41: Value of spending
C43: Cost-effectiveness of the program (before leverage and funging)
E44: =HYPERLINK(buildUrl(CELL("address", 'Main CEA'!E134)), 'Main CEA'!E134) -> Units of value generated per dollar (before final adjustments) | F44: ='Main CEA'!F134 -> UoV | G44: main | H44: ='Main CEA'!H134 -> - | I44: ='Main CEA'!I134 -> 0.067960931 | J44: ='Main CEA'!J134 -> 0.056189917 | K44: ='Main CEA'!K134 -> 0.036064272 | L44: ='Main CEA'!L134 -> 0.035188858 | M44: ='Main CEA'!M134 -> 0.038812006 | N44: ='Main CEA'!N134 -> 0.042356106 | O44: ='Main CEA'!O134 -> 0.044611531 | ... AB44: ='Main CEA'!AB134 -> 0.02596393
E45: =HYPERLINK(buildUrl(CELL("address", 'Main CEA'!D163)), 'Main CEA'!D163) -> Total supplemental grantee-level adjustment | F45: ='Main CEA'!F163 -> % | G45: main | H45: ='Main CEA'!H163 -> -0.08 | I45: ='Main CEA'!I163 -> - | J45: ='Main CEA'!J163 -> - | K45: ='Main CEA'!K163 | L45: ='Main CEA'!L163 -> - | M45: ='Main CEA'!M163 -> - | N45: ='Main CEA'!N163 -> - | O45: ='Main CEA'!O163 -> - | ... AB45: ='Main CEA'!AB163 -> -
E46: =HYPERLINK(buildUrl(CELL("address", 'Main CEA'!D179)), 'Main CEA'!D179) -> Total supplemental intervention-level adjustment | F46: ='Main CEA'!F179 -> % | G46: main | H46: ='Main CEA'!H179 -> - | I46: ='Main CEA'!I179 -> 0.191 | J46: ='Main CEA'!J179 -> 0.241 | K46: ='Main CEA'!K179 -> 0.141 | L46: ='Main CEA'!L179 -> 0.181 | M46: ='Main CEA'!M179 -> 0.181 | N46: ='Main CEA'!N179 -> 0.181 | O46: ='Main CEA'!O179 -> 0.181 | ... AB46: ='Main CEA'!AB179 -> 0.181
E47: Units of value generated per dollar donated to grantee (after supplemental adjustments) | F47: UoV | G47: calc | H47: - | I47: =I44*(1+$H45)*(1+I46) -> 0.074466151 | J47: =J44*(1+$H45)*(1+J46) -> 0.064153152 | K47: =K44*(1+$H45)*(1+K46) -> 0.037857387 | L47: =L44*(1+$H45)*(1+L46) -> 0.038233399 | M47: =M44*(1+$H45)*(1+M46) -> 0.042170021 | N47: =N44*(1+$H45)*(1+N46) -> 0.046020756 | O47: =O44*(1+$H45)*(1+O46) -> 0.04847132 | P47: =P44*(1+$H45)*(1+P46) -> 0.037519782 | ... AB47: =AB44*(1+$H45)*(1+AB46) -> 0.028210329
C49: Lives saved by the program (before leverage and funging)
E50: =HYPERLINK(buildUrl(CELL("address", 'Main CEA'!E145)), 'Main CEA'!E145) -> Total lives saved (before final adjustments) | F50: ='Main CEA'!F145 -> # | G50: main | H50: ='Main CEA'!H145 -> - | I50: ='Main CEA'!I145 -> 4.6194604e-06 | J50: ='Main CEA'!J145 -> 4.1240105e-06 | K50: ='Main CEA'!K145 -> 2.3892264e-06 | L50: ='Main CEA'!L145 -> 2.3609947e-06 | M50: ='Main CEA'!M145 -> 2.5360655e-06 | N50: ='Main CEA'!N145 -> 2.7980017e-06 | O50: ='Main CEA'!O145 -> 3.0208907e-06 | ... AB50: ='Main CEA'!AB145 -> 1.4294503e-06
E51: =HYPERLINK(buildUrl(CELL("address", 'Main CEA'!D163)), 'Main CEA'!D163) -> Total supplemental grantee-level adjustment | F51: ='Main CEA'!F163 -> % | G51: main | H51: ='Main CEA'!H163 -> -0.08 | I51: ='Main CEA'!I163 -> - | J51: ='Main CEA'!J163 -> - | K51: ='Main CEA'!K163 | L51: ='Main CEA'!L163 -> - | M51: ='Main CEA'!M163 -> - | N51: ='Main CEA'!N163 -> - | O51: ='Main CEA'!O163 -> - | ... AB51: ='Main CEA'!AB163 -> -
E52: =HYPERLINK(buildUrl(CELL("address", 'Main CEA'!E204)), 'Main CEA'!E204) -> Total supplemental intervention-level adjustment affecting lives saved | F52: ='Main CEA'!F204 -> % | G52: main | H52: ='Main CEA'!H204 -> - | I52: ='Main CEA'!I204 -> -0.198 | J52: ='Main CEA'!J204 -> -0.148 | K52: ='Main CEA'!K204 -> -0.248 | L52: ='Main CEA'!L204 -> -0.208 | M52: ='Main CEA'!M204 -> -0.208 | N52: ='Main CEA'!N204 -> -0.208 | O52: ='Main CEA'!O204 -> -0.208 | ... AB52: ='Main CEA'!AB204 -> -0.208
E53: Total lives saved (after supplemental adjustments) | F53: # | G53: calc | H53: - | I53: =I50*(1+$H51)*(1+I52) -> 3.4084226e-06 | J53: =J50*(1+$H51)*(1+J52) -> 3.2325644e-06 | K53: =K50*(1+$H51)*(1+K52) -> 1.6529624e-06 | L53: =L50*(1+$H51)*(1+L52) -> 1.7203152e-06 | M53: =M50*(1+$H51)*(1+M52) -> 1.8478788e-06 | N53: =N50*(1+$H51)*(1+N52) -> 2.038736e-06 | O53: =O50*(1+$H51)*(1+O52) -> 2.2011418e-06 | P53: =P50*(1+$H51)*(1+P52) -> 3036.3693 | ... AB53: =AB50*(1+$H51)*(1+AB52) -> 1.0415547e-06
C55: Counterfactual value of spending from non-philanthropic actors
E56: =HYPERLINK(buildUrl(CELL("address", Inputs!E124)), Inputs!E124) -> Counterfactual value per dollar spent by domestic governments on malaria programs | F56: =Inputs!F124 -> UoV | G56: =Inputs!G124 -> input | H56: =Inputs!H124 -> 0.005057 | I56: =Inputs!I124 -> - | J56: =Inputs!J124 -> - | K56: =Inputs!K124 -> - | L56: =Inputs!L124 -> - | M56: =Inputs!M124 -> - | ... AB56: =Inputs!AB124 -> -
E57: =HYPERLINK(buildUrl(CELL("address", Inputs!E125)), Inputs!E125) -> Counterfactual value per dollar spent by the Global Fund or PMI | F57: =Inputs!F125 -> UoV | G57: =Inputs!G125 -> input | H57: =Inputs!H125 -> 0.015433 | I57: =Inputs!I125 -> - | J57: =Inputs!J125 -> - | K57: =Inputs!K125 -> - | L57: =Inputs!L125 -> - | M57: =Inputs!M125 -> - | ... AB57: =Inputs!AB125 -> -
A59: Value generated across different counterfactual scenarios
C61: Scenario 1: Domestic governments would replace philanthropic spending
D62: Hypothetical impact of shifting government spending
E63: Amount of spending domestic governments would shift to the grantee program | F63: $ | G63: calc | H63: - | I63: =I19 -> 0.01 | J63: =J19 -> 0.01 | K63: =K19 -> 0.01 | L63: =L19 -> 0.01 | M63: =M19 -> 0.01 | N63: =N19 -> 0.01 | O63: =O19 -> 0.01 | P63: =P19 -> 17456907 | ... AB63: =AB19 -> 0.01
E64: Value generated by shifting government spending to the grantee program | F64: UoV | G64: calc | H64: - | I64: =I63*I47 -> 0.00074466151 | J64: =J63*J47 -> 0.00064153152 | K64: =K63*K47 -> 0.00037857387 | L64: =L63*L47 -> 0.00038233399 | M64: =M63*M47 -> 0.00042170021 | N64: =N63*N47 -> 0.00046020756 | O64: =O63*O47 -> 0.0004847132 | P64: =P63*P47 -> 654979.35 | ... AB64: =AB63*AB47 -> 0.00028210329
E65: Value lost by shifting spending away from programs domestic governments would otherwise have funded | F65: UoV | G65: calc | H65: - | I65: =I63*$H56 -> 5.057e-05 | J65: =J63*$H56 -> 5.057e-05 | K65: =K63*$H56 -> 5.057e-05 | L65: =L63*$H56 -> 5.057e-05 | M65: =M63*$H56 -> 5.057e-05 | N65: =N63*$H56 -> 5.057e-05 | O65: =O63*$H56 -> 5.057e-05 | P65: =P63*$H56 -> 88279.579 | ... AB65: =AB63*$H56 -> 5.057e-05
E66: Net value generated by shifting government spending to the grantee program | F66: UoV | G66: calc | H66: - | I66: =I64-I65 -> 0.00069409151 | J66: =J64-J65 -> 0.00059096152 | K66: =K64-K65 -> 0.00032800387 | L66: =L64-L65 -> 0.00033176399 | M66: =M64-M65 -> 0.00037113021 | N66: =N64-N65 -> 0.00040963756 | O66: =O64-O65 -> 0.0004341432 | P66: =P64-P65 -> 566699.77 | ... AB66: =AB64-AB65 -> 0.00023153329
E67: Change in value generated by the grantee program if this scenario represented the true counterfactual | F67: UoV | G67: calc | H67: - | I67: =-I66 -> -0.00069409151 | J67: =-J66 -> -0.00059096152 | K67: =-K66 -> -0.00032800387 | L67: =-L66 -> -0.00033176399 | M67: =-M66 -> -0.00037113021 | N67: =-N66 -> -0.00040963756 | O67: =-O66 -> -0.0004341432 | P67: =-P66 -> -566699.77 | ... AB67: =-AB66 -> -0.00023153329
E68: Probability of this scenario representing the true counterfactual | F68: =F30 -> % | G68: feed | H68: =H30 -> - | I68: =I30 -> 0 | J68: =J30 -> 0 | K68: =K30 -> 0 | L68: =L30 -> 0 | M68: =M30 -> 0 | N68: =N30 -> 0 | O68: =O30 -> 0 | ... AB68: =AB30 -> 0
E69: Expected change in value generated by the grantee program | F69: UoV | G69: calc | H69: - | I69: =I67*I68 -> 0 | J69: =J67*J68 -> 0 | K69: =K67*K68 -> 0 | L69: =L67*L68 -> 0 | M69: =M67*M68 -> 0 | N69: =N67*N68 -> 0 | O69: =O67*O68 -> 0 | P69: =P67*P68 -> 0 | ... AB69: =AB67*AB68 -> 0
C71: Scenario 2: The Global Fund and/or PMI would replace philanthropic spending
D72: Hypothetical impact of shifting Global Fund and/or PMI spending
E73: Amount of spending Global Fund and/or PMI would shift to the grantee program | F73: $ | G73: calc | H73: - | I73: =I19 -> 0.01 | J73: =J19 -> 0.01 | K73: =K19 -> 0.01 | L73: =L19 -> 0.01 | M73: =M19 -> 0.01 | N73: =N19 -> 0.01 | O73: =O19 -> 0.01 | P73: =P19 -> 17456907 | ... AB73: =AB19 -> 0.01
E74: Value generated by shifting Global Fund and/or PMI spending to the grantee program | F74: UoV | G74: calc | H74: - | I74: =I73*I47 -> 0.00074466151 | J74: =J73*J47 -> 0.00064153152 | K74: =K73*K47 -> 0.00037857387 | L74: =L73*L47 -> 0.00038233399 | M74: =M73*M47 -> 0.00042170021 | N74: =N73*N47 -> 0.00046020756 | O74: =O73*O47 -> 0.0004847132 | P74: =P73*P47 -> 654979.35 | ... AB74: =AB73*AB47 -> 0.00028210329
E75: Value lost by shifting spending away from programs the Global Fund and/or PMI would otherwise have funded | F75: UoV | G75: calc | H75: - | I75: =I73*$H57 -> 0.00015433 | J75: =J73*$H57 -> 0.00015433 | K75: =K73*$H57 -> 0.00015433 | L75: =L73*$H57 -> 0.00015433 | M75: =M73*$H57 -> 0.00015433 | N75: =N73*$H57 -> 0.00015433 | O75: =O73*$H57 -> 0.00015433 | P75: =P73*$H57 -> 269412.45 | ... AB75: =AB73*$H57 -> 0.00015433
E76: Net value generated by shifting Global Fund and/or PMI spending to the grantee program | F76: UoV | G76: calc | H76: - | I76: =I74-I75 -> 0.00059033151 | J76: =J74-J75 -> 0.00048720152 | K76: =K74-K75 -> 0.00022424387 | L76: =L74-L75 -> 0.00022800399 | M76: =M74-M75 -> 0.00026737021 | N76: =N74-N75 -> 0.00030587756 | O76: =O74-O75 -> 0.0003303832 | P76: =P74-P75 -> 385566.91 | ... AB76: =AB74-AB75 -> 0.00012777329
E77: Change in value generated by the grantee program if this scenario represented the true counterfactual | F77: UoV | G77: calc | H77: - | I77: =-I76 -> -0.00059033151 | J77: =-J76 -> -0.00048720152 | K77: =-K76 -> -0.00022424387 | L77: =-L76 -> -0.00022800399 | M77: =-M76 -> -0.00026737021 | N77: =-N76 -> -0.00030587756 | O77: =-O76 -> -0.0003303832 | P77: =-P76 -> -385566.91 | ... AB77: =-AB76 -> -0.00012777329
E78: Probability of this scenario representing the true counterfactual | F78: =F31 -> % | G78: feed | H78: =H31 -> - | I78: =I31 -> 0.5 | J78: =J31 -> 0.3 | K78: =K31 -> 0.4 | L78: =L31 -> 0.15 | M78: =M31 -> 0.15 | N78: =N31 -> 0.15 | O78: =O31 -> 0.15 | ... AB78: =AB31 -> 0.4
E79: Expected change in value generated by the grantee program | F79: UoV | G79: calc | H79: - | I79: =I77*I78 -> -0.00029516576 | J79: =J77*J78 -> -0.00014616046 | K79: =K77*K78 -> -8.9697549e-05 | L79: =L77*L78 -> -3.4200598e-05 | M79: =M77*M78 -> -4.0105531e-05 | N79: =N77*N78 -> -4.5881634e-05 | O79: =O77*O78 -> -4.955748e-05 | P79: =P77*P78 -> -134948.42 | ... AB79: =AB77*AB78 -> -5.1109317e-05
C81: Scenario 3: The government would spend the same amount and the program would be smaller
D82: Hypothetical impact of shifting government spending
E83: Amount of spending domestic governments would shift away from the grantee program | F83: $ | G83: calc | H83: - | I83: =I21*(1-I38) -> 0.0011796323 | J83: =J21*(1-J38) -> 0.0010834145 | K83: =K21*(1-K38) -> 0.001029505 | L83: =L21*(1-L38) -> 0.00062841842 | M83: =M21*(1-M38) -> 0.00062841842 | N83: =N21*(1-N38) -> 0.00062841842 | O83: =O21*(1-O38) -> 0.00062841842 | P83: =P21*(1-P38) -> 2059273.2 | ... AB83: =AB21*(1-AB38) -> 0.0011942882
E84: Value generated by shifting spending toward programs domestic governments would otherwise have supported | F84: UoV | G84: calc | H84: - | I84: =I83*$H56 -> 5.9654006e-06 | J84: =J83*$H56 -> 5.4788272e-06 | K84: =K83*$H56 -> 5.2062069e-06 | L84: =L83*$H56 -> 3.177912e-06 | M84: =M83*$H56 -> 3.177912e-06 | N84: =N83*$H56 -> 3.177912e-06 | O84: =O83*$H56 -> 3.177912e-06 | P84: =P83*$H56 -> 10413.745 | ... AB84: =AB83*$H56 -> 6.0395152e-06
E85: Value lost by shifting government spending away from the grantee program | F85: UoV | G85: calc | H85: - | I85: 0 | J85: 0 | K85: 0 | L85: 0 | M85: 0 | N85: 0 | O85: 0 | P85: 0 | Q85: 0 | R85: 0 | S85: 0 | T85: 0 | U85: 0 | V85: 0 | W85: 0 | X85: 0 | Y85: 0 | Z85: 0 | AA85: 0 | AB85: 0
E86: Net value generated by shifting government spending away from the grantee program | F86: UoV | G86: calc | H86: - | I86: =I84-I85 -> 5.9654006e-06 | J86: =J84-J85 -> 5.4788272e-06 | K86: =K84-K85 -> 5.2062069e-06 | L86: =L84-L85 -> 3.177912e-06 | M86: =M84-M85 -> 3.177912e-06 | N86: =N84-N85 -> 3.177912e-06 | O86: =O84-O85 -> 3.177912e-06 | P86: =P84-P85 -> 10413.745 | ... AB86: =AB84-AB85 -> 6.0395152e-06
E87: Change in value generated by the grantee program if this scenario represented the true counterfactual | F87: UoV | G87: calc | H87: - | I87: =-I86 -> -5.9654006e-06 | J87: =-J86 -> -5.4788272e-06 | K87: =-K86 -> -5.2062069e-06 | L87: =-L86 -> -3.177912e-06 | M87: =-M86 -> -3.177912e-06 | N87: =-N86 -> -3.177912e-06 | O87: =-O86 -> -3.177912e-06 | P87: =-P86 -> -10413.745 | ... AB87: =-AB86 -> -6.0395152e-06
E88: Probability of this scenario representing the true counterfactual | F88: =F32 -> % | G88: feed | H88: =H32 -> - | I88: =I32 -> 0 | J88: =J32 -> 0 | K88: =K32 -> 0 | L88: =L32 -> 0 | M88: =M32 -> 0 | N88: =N32 -> 0 | O88: =O32 -> 0 | ... AB88: =AB32 -> 0
E89: Expected change in value generated by the program | F89: UoV | G89: calc | H89: - | I89: =I87*I88 -> 0 | J89: =J87*J88 -> 0 | K89: =K87*K88 -> 0 | L89: =L87*L88 -> 0 | M89: =M87*M88 -> 0 | N89: =N87*N88 -> 0 | O89: =O87*O88 -> 0 | P89: =P87*P88 -> 0 | ... AB89: =AB87*AB88 -> 0
C91: Scenario 4: The grantee program would go unfunded
D92: Hypothetical impact of shifting government spending
E93: Amount of spending domestic governments would shift away from the grantee program | F93: $ | G93: calc | H93: - | I93: =I21 -> 0.0011796323 | J93: =J21 -> 0.0010834145 | K93: =K21 -> 0.001029505 | L93: =L21 -> 0.0011789887 | M93: =M21 -> 0.0011789887 | N93: =N21 -> 0.0011789887 | O93: =O21 -> 0.0011789887 | P93: =P21 -> 2059273.2 | ... AB93: =AB21 -> 0.0011942882
E94: Value generated by shifting spending to programs domestic governments would otherwise have funded | F94: UoV | G94: calc | H94: - | I94: =I93*$H56 -> 5.9654006e-06 | J94: =J93*$H56 -> 5.4788272e-06 | K94: =K93*$H56 -> 5.2062069e-06 | L94: =L93*$H56 -> 5.9621461e-06 | M94: =M93*$H56 -> 5.9621461e-06 | N94: =N93*$H56 -> 5.9621461e-06 | O94: =O93*$H56 -> 5.9621461e-06 | P94: =P93*$H56 -> 10413.745 | ... AB94: =AB93*$H56 -> 6.0395152e-06
E95: Value lost by shifting government spending away from the grantee program | F95: UoV | G95: calc | H95: - | I95: 0 | J95: 0 | K95: 0 | L95: 0 | M95: 0 | N95: 0 | O95: 0 | P95: 0 | Q95: 0 | R95: 0 | S95: 0 | T95: 0 | U95: 0 | V95: 0 | W95: 0 | X95: 0 | Y95: 0 | Z95: 0 | AA95: 0 | AB95: 0
E96: Net value generated by shifting government spending away from the grantee program | F96: UoV | G96: calc | H96: - | I96: =I94-I95 -> 5.9654006e-06 | J96: =J94-J95 -> 5.4788272e-06 | K96: =K94-K95 -> 5.2062069e-06 | L96: =L94-L95 -> 5.9621461e-06 | M96: =M94-M95 -> 5.9621461e-06 | N96: =N94-N95 -> 5.9621461e-06 | O96: =O94-O95 -> 5.9621461e-06 | P96: =P94-P95 -> 10413.745 | ... AB96: =AB94-AB95 -> 6.0395152e-06
E97: Change in value generated by the grantee program if this scenario represented the true counterfactual | F97: UoV | G97: calc | H97: - | I97: =-I96 -> -5.9654006e-06 | J97: =-J96 -> -5.4788272e-06 | K97: =-K96 -> -5.2062069e-06 | L97: =-L96 -> -5.9621461e-06 | M97: =-M96 -> -5.9621461e-06 | N97: =-N96 -> -5.9621461e-06 | O97: =-O96 -> -5.9621461e-06 | P97: =-P96 -> -10413.745 | ... AB97: =-AB96 -> -6.0395152e-06
E98: Probability of this scenario representing the true counterfactual | F98: =F33 -> % | G98: feed | H98: =H33 -> - | I98: =I33 -> 0.5 | J98: =J33 -> 0.7 | K98: =K33 -> 0.6 | L98: =L33 -> 0.85 | M98: =M33 -> 0.85 | N98: =N33 -> 0.85 | O98: =O33 -> 0.85 | ... AB98: =AB33 -> 0.6
E99: Expected change in value generated by the program | F99: UoV | G99: calc | H99: - | I99: =I97*I98 -> -2.9827003e-06 | J99: =J97*J98 -> -3.8351791e-06 | K99: =K97*K98 -> -3.1237242e-06 | L99: =L97*L98 -> -5.0678242e-06 | M99: =M97*M98 -> -5.0678242e-06 | N99: =N97*N98 -> -5.0678242e-06 | O99: =O97*O98 -> -5.0678242e-06 | P99: =P97*P98 -> -6768.9339 | ... AB99: =AB97*AB98 -> -3.6237091e-06
A101: Final leverage and funging adjustment
C103: Change in value generated as a result of leverage and funging
E104: Total value generated by grantee spending before adjusting for leverage and funging | F104: UoV | G104: calc | H104: - | I104: =I19*I47 -> 0.00074466151 | J104: =J19*J47 -> 0.00064153152 | K104: =K19*K47 -> 0.00037857387 | L104: =L19*L47 -> 0.00038233399 | M104: =M19*M47 -> 0.00042170021 | N104: =N19*N47 -> 0.00046020756 | O104: =O19*O47 -> 0.0004847132 | P104: =P19*P47 -> 654979.35 | ... AB104: =AB19*AB47 -> 0.00028210329
E105: Change in value generated as a result of crowding funding into the program (leverage) | F105: UoV | G105: calc | H105: - | I105: =SUM(I89,I99) -> -2.9827003e-06 | J105: =SUM(J89,J99) -> -3.8351791e-06 | K105: =SUM(K89,K99) -> -3.1237242e-06 | L105: =SUM(L89,L99) -> -5.0678242e-06 | M105: =SUM(M89,M99) -> -5.0678242e-06 | N105: =SUM(N89,N99) -> -5.0678242e-06 | O105: =SUM(O89,O99) -> -5.0678242e-06 | P105: =SUM(P89,P99) -> -6768.9339 | ... AB105: =SUM(AB89,AB99) -> -3.6237091e-06
E106: Change in value generated as a result of crowding funding out of the program (funging) | F106: UoV | G106: calc | H106: - | I106: =SUM(I69,I79) -> -0.00029516576 | J106: =SUM(J69,J79) -> -0.00014616046 | K106: =SUM(K69,K79) -> -8.9697549e-05 | L106: =SUM(L69,L79) -> -3.4200598e-05 | M106: =SUM(M69,M79) -> -4.0105531e-05 | N106: =SUM(N69,N79) -> -4.5881634e-05 | O106: =SUM(O69,O79) -> -4.955748e-05 | P106: =SUM(P69,P79) -> -134948.42 | ... AB106: =SUM(AB69,AB79) -> -5.1109317e-05
E107: Total expected change in value generated as a result of leverage and funging | F107: UoV | G107: calc | H107: - | I107: =SUM(I69,I79,I89,I99) -> -0.00029814846 | J107: =SUM(J69,J79,J89,J99) -> -0.00014999564 | K107: =SUM(K69,K79,K89,K99) -> -9.2821273e-05 | L107: =SUM(L69,L79,L89,L99) -> -3.9268422e-05 | M107: =SUM(M69,M79,M89,M99) -> -4.5173356e-05 | N107: =SUM(N69,N79,N89,N99) -> -5.0949458e-05 | O107: =SUM(O69,O79,O89,O99) -> -5.4625304e-05 | P107: =SUM(P69,P79,P89,P99) -> -141717.35 | ... AB107: =SUM(AB69,AB79,AB89,AB99) -> -5.4733027e-05
E108: Total value generated by grantee spending after adjusting for leverage and funging | F108: UOV | G108: calc | H108: - | I108: =SUM(I104,I107) -> 0.00044651306 | J108: =SUM(J104,J107) -> 0.00049153589 | K108: =SUM(K104,K107) -> 0.0002857526 | L108: =SUM(L104,L107) -> 0.00034306556 | M108: =SUM(M104,M107) -> 0.00037652685 | N108: =SUM(N104,N107) -> 0.0004092581 | O108: =SUM(O104,O107) -> 0.0004300879 | P108: =SUM(P104,P107) -> 513262 | ... AB108: =SUM(AB104,AB107) -> 0.00022737027
C110: Final leverage and funging adjustment
E111: Adjustment for the possibility of crowding funding into the program (leverage) | F111: % | G111: calc | H111: - | I111: =I105/I104 -> -0.0040054445 | J111: =J105/J104 -> -0.0059781615 | K111: =K105/K104 -> -0.0082512936 | L111: =L105/L104 -> -0.013254966 | M111: =M105/M104 -> -0.012017599 | N111: =N105/N104 -> -0.01101204 | O111: =O105/O104 -> -0.010455305 | P111: =P105/P104 -> -0.010334576 | ... AB111: =AB105/AB104 -> -0.012845327
E112: Adjustment for the possibility of crowding funding out of the program (funging) | F112: % | G112: calc | H112: - | I112: =I106/I104 -> -0.39637574 | J112: =J106/J104 -> -0.22783051 | K112: =K106/K104 -> -0.23693539 | L112: =L106/L104 -> -0.089452152 | M112: =M106/M104 -> -0.095104367 | N112: =N106/N104 -> -0.099697697 | O112: =O106/O104 -> -0.10224083 | P112: =P106/P104 -> -0.20603461 | ... AB112: =AB106/AB104 -> -0.18117235
E113: Adjustment for leverage and funging | F113: % | G113: calc | H113: - | I113: =I107/I104 -> -0.40038118 | J113: =J107/J104 -> -0.23380868 | K113: =K107/K104 -> -0.24518669 | L113: =L107/L104 -> -0.10270712 | M113: =M107/M104 -> -0.10712197 | N113: =N107/N104 -> -0.11070974 | O113: =O107/O104 -> -0.11269614 | P113: =P107/P104 -> -0.21636919 | ... AB113: =AB107/AB104 -> -0.19401768
C115: Leverage and funging adjustment for counterfactual impact estimates
E116: Leverage and funging adjustment for counterfactual impact estimates | F116: % | G116: calc | H116: - | I116: =((MIN(I67,0)*I68)+(MIN(I77,0)*I78)+I105)/I104 -> -0.40038118 | J116: =((MIN(J67,0)*J68)+(MIN(J77,0)*J78)+J105)/J104 -> -0.23380868 | K116: =((MIN(K67,0)*K68)+(MIN(K77,0)*K78)+K105)/K104 -> -0.24518669 | L116: =((MIN(L67,0)*L68)+(MIN(L77,0)*L78)+L105)/L104 -> -0.10270712 | M116: =((MIN(M67,0)*M68)+(MIN(M77,0)*M78)+M105)/M104 -> -0.10712197 | N116: =((MIN(N67,0)*N68)+(MIN(N77,0)*N78)+N105)/N104 -> -0.11070974 | O116: =((MIN(O67,0)*O68)+(MIN(O77,0)*O78)+O105)/O104 -> -0.11269614 | P116: =((MIN(P67,0)*P68)+(MIN(P77,0)*P78)+P105)/P104 -> -0.21636919 | ... AB116: =((MIN(AB67,0)*AB68)+(MIN(AB77,0)*AB78)+AB105)/AB104 -> -0.19401768

Sheet Inputs
I1: Malaria Consortium | S1: Malaria Consortium
I2: Burkina Faso | J2: Chad | K2: Côte d'Ivoire | L2: DRC | M2: DRC | N2: DRC | O2: DRC | P2: Mozambique | Q2: Nigeria | R2: Nigeria | S2: Nigeria | T2: Nigeria | U2: Nigeria | V2: Nigeria | W2: Nigeria | X2: Nigeria | Y2: Nigeria | Z2: South Sudan | AA2: Togo | AB2: Uganda
A3: Inputs | F3: unit | G3: type | H3: Overall | L3: Haut-Katanga | M3: Haut-Lomami | N3: Lualaba | O3: Tanganyika | P3: Nampula | Q3: Bauchi | R3: Borno | S3: FCT (Abuja) | T3: Kebbi | U3: Kogi | V3: Nasarawa | W3: Oyo | X3: Plateau | Y3: Sokoto | Z3: Northern Bahr El Ghazal | AB3: Karamoja | AD3: Source | AE3: GW analysis and discussion
E4: Final cost-effectiveness estimate (pulled from "Main calcs" sheet for visibility) | F4: ='Main CEA'!F193 -> xcash | G4: main | H4: ='Main CEA'!H193 -> - | I4: ='Main CEA'!I193 -> 13.310868 | J4: ='Main CEA'!J193 -> 14.65303 | K4: ='Main CEA'!K193 -> 8.5184856 | L4: ='Main CEA'!L193 -> 10.227025 | M4: ='Main CEA'!M193 -> 11.22453 | N4: ='Main CEA'!N193 -> 12.200271 | O4: ='Main CEA'!O193 -> 12.821222 | ... AB4: ='Main CEA'!AB193 -> 6.7780673
A5: Costs
C7: GiveWell costs
E8: Grant size | F8: $ | G8: input | H8: - | I8: 0.01 | J8: 0.01 | K8: 0.01 | L8: 0.01 | M8: 0.01 | N8: 0.01 | O8: 0.01 | P8: 17456907 | Q8: 0.01 | R8: 0.01 | S8: 0.01 | T8: 0.01 | U8: 0.01 | V8: 0.01 | W8: 0.01 | X8: 0.01 | Y8: 0.01 | Z8: 0.01 | AA8: 0.01 | AB8: 0.01 | AD8: Arbitrary value
C10: Cost breakdown
E11: Percentage of total costs covered by the grantee | F11: % | G11: input | H11: - | I11: 0.8944838 | J11: 0.90224903 | K11: 0.906659 | L11: =$AA11 -> 0.50149962 | M11: =$AA11 -> 0.50149962 | N11: =$AA11 -> 0.50149962 | O11: =$AA11 -> 0.50149962 | P11: 0.8944838 | Q11: 0.81586554 | R11: 0.8944838 | S11: 0.8944838 | T11: 0.8944838 | U11: 0.8944838 | V11: 0.8944838 | W11: 0.8944838 | X11: 0.8944838 | Y11: 0.8944838 | Z11: 0.91399685 | AA11: 0.50149962 | AB11: 0.89331272 | AD11: GW analysis | AE11: GW's analysis of Malaria Consortium's cost per SMC cycle administration
E12: Percentage of total costs covered by other philanthropic actors | F12: % | G12: input | H12: - | I12: 0 | J12: 0 | K12: 0 | L12: =$AA12 -> 0.43937414 | M12: =$AA12 -> 0.43937414 | N12: =$AA12 -> 0.43937414 | O12: =$AA12 -> 0.43937414 | P12: 0 | Q12: 0.08789232 | R12: 0 | S12: 0 | T12: 0 | U12: 0 | V12: 0 | W12: 0 | X12: 0 | Y12: 0 | Z12: 0 | AA12: 0.43937414 | AB12: 0 | AD12: GW analysis | AE12: GW's analysis of Malaria Consortium's cost per SMC cycle administration
E13: Percentage of total costs covered by domestic governments | F13: % | G13: input | H13: - | I13: 0.1055162 | J13: 0.09775097 | K13: 0.093341 | L13: =$AA13 -> 0.05912624 | M13: =$AA13 -> 0.05912624 | N13: =$AA13 -> 0.05912624 | O13: =$AA13 -> 0.05912624 | P13: 0.1055162 | Q13: 0.09624214 | R13: 0.1055162 | S13: 0.1055162 | T13: 0.1055162 | U13: 0.1055162 | V13: 0.1055162 | W13: 0.1055162 | X13: 0.1055162 | Y13: 0.1055162 | Z13: 0.08600315 | AA13: 0.05912624 | AB13: 0.10668728 | AD13: GW analysis | AE13: GW's analysis of Malaria Consortium's cost per SMC cycle administration
C15: Cost per child covered
E16: Cost per seasonal malaria chemoprevention (SMC) cycle administered | F16: $ | G16: input | H16: - | I16: 1.641799 | J16: =2.15969*0.9 -> 1.943721 | K16: =2.80633*0.9 -> 2.525697 | L16: =max($I$16:$J$16,$Q$16:$Y$16,$AA$16) -> 1.943721 | M16: =max($I$16:$J$16,$Q$16:$Y$16,$AA$16) -> 1.943721 | N16: =max($I$16:$J$16,$Q$16:$Y$16,$AA$16) -> 1.943721 | O16: =max($I$16:$J$16,$Q$16:$Y$16,$AA$16) -> 1.943721 | P16: =2.3036866*0.9 -> 2.0733179 | Q16: 0.884114 | R16: 0.738607 | S16: 1.517807 | T16: 1.128167 | U16: 1.361817 | V16: 1.151538 | W16: 1.808616 | X16: 1.246252 | Y16: 0.991878 | Z16: =5.155467*0.9 -> 4.6399203 | AA16: 1.9326022 | AB16: =2.2058284*0.9 -> 1.9852456 | AD16: GW analysis | AE16: GW's analysis of Malaria Consortium's cost per SMC cycle administration
E17: Number of SMC cycles per year | F17: # | G17: input | H17: - | I17: 4.312275 | J17: 4 | K17: 5 | L17: 4 | M17: 4 | N17: 4 | O17: 4 | P17: 4 | Q17: 5 | R17: 4 | S17: 5 | T17: 4 | U17: 5 | V17: 5 | W17: 5 | X17: 5 | Y17: 4 | Z17: 5 | AA17: 4 | AB17: 5 | AD17: GW analysis | AE17: GW's analysis of Malaria Consortium's cost per SMC cycle administration
A19: Counterfactual malaria
C21: Malaria mortalities among the SMC-eligible population
E22: Malaria mortalities per year among people under age 5 | F22: # | G22: input | H22: - | I22: 6910 | J22: 582 | K22: 2780 | L22: 2766 | M22: 2408 | N22: 1753 | O22: 2509 | P22: 3726 | Q22: =IFERROR(__xludf.DUMMYFUNCTION("FILTER('GBD estimates'!$BA$4:$BA$258,'GBD estimates'!$AV$4:$AV$258=Q$3,'GBD estimates'!$AU$4:$AU$258=""Under 5"")"),6310.369098) -> 6310.3691 | R22: =IFERROR(__xludf.DUMMYFUNCTION("FILTER('GBD estimates'!$BA$4:$BA$258,'GBD estimates'!$AV$4:$AV$258=R$3,'GBD estimates'!$AU$4:$AU$258=""Under 5"")"),1946.768516) -> 1946.7685 | S22: =IFERROR(__xludf.DUMMYFUNCTION("FILTER('GBD estimates'!$BA$4:$BA$258,'GBD estimates'!$AV$4:$AV$258=S$3,'GBD estimates'!$AU$4:$AU$258=""Under 5"")"),2525.95462) -> 2525.9546 | T22: =IFERROR(__xludf.DUMMYFUNCTION("FILTER('GBD estimates'!$BA$4:$BA$258,'GBD estimates'!$AV$4:$AV$258=T$3,'GBD estimates'!$AU$4:$AU$258=""Under 5"")"),3863.160124) -> 3863.1601 | U22: =IFERROR(__xludf.DUMMYFUNCTION("FILTER('GBD estimates'!$BA$4:$BA$258,'GBD estimates'!$AV$4:$AV$258=U$3,'GBD estimates'!$AU$4:$AU$258=""Under 5"")"),1159.106488) -> 1159.1065 | V22: =IFERROR(__xludf.DUMMYFUNCTION("FILTER('GBD estimates'!$BA$4:$BA$258,'GBD estimates'!$AV$4:$AV$258=V$3,'GBD estimates'!$AU$4:$AU$258=""Under 5"")"),2235.297195) -> 2235.2972 | W22: =IFERROR(__xludf.DUMMYFUNCTION("FILTER('GBD estimates'!$BA$4:$BA$258,'GBD estimates'!$AV$4:$AV$258=W$3,'GBD estimates'!$AU$4:$AU$258=""Under 5"")"),2153.286251) -> 2153.2863 | X22: =IFERROR(__xludf.DUMMYFUNCTION("FILTER('GBD estimates'!$BA$4:$BA$258,'GBD estimates'!$AV$4:$AV$258=X$3,'GBD estimates'!$AU$4:$AU$258=""Under 5"")"),4770.056621) -> 4770.0566 | Y22: =IFERROR(__xludf.DUMMYFUNCTION("FILTER('GBD estimates'!$BA$4:$BA$258,'GBD estimates'!$AV$4:$AV$258=Y$3,'GBD estimates'!$AU$4:$AU$258=""Under 5"")"),5952.332882) -> 5952.3329 | Z22: 99 | AA22: =IFERROR(__xludf.DUMMYFUNCTION("FILTER('GBD estimates'!$S$4:$S$309,'GBD estimates'!$M$4:$M$309=AA$2,'GBD estimates'!$O$4:$O$309=""<5 years"")"),2278.182123) -> 2278.1821 | AB22: 4689 | AD22: GW analysis | AE22: GW's analysis of malaria burden in SMC-eligible countries
E23: Early neonatal malaria mortalities per year (babies under 7 days old) | F23: # | G23: input | H23: - | I23: 0 | J23: 0 | K23: 0 | L23: 0 | M23: 0 | N23: 0 | O23: 0 | P23: 0 | Q23: 0 | R23: 0 | S23: 0 | T23: 0 | U23: 0 | V23: 0 | W23: 0 | X23: 0 | Y23: 0 | Z23: 0 | AA23: =IFERROR(__xludf.DUMMYFUNCTION("FILTER('GBD estimates'!$S$4:$S$309,'GBD estimates'!$M$4:$M$309=AA$2,'GBD estimates'!$O$4:$O$309=""0-6 days"")"),0.0) -> 0 | AB23: 0 | AD23: GW analysis | AE23: GW's analysis of malaria burden in SMC-eligible countries
E24: Late neonatal malaria mortalities per year (babies between 7 and 27 days old) | F24: # | G24: input | H24: - | I24: 315 | J24: 24 | K24: 135 | L24: 165 | M24: 143 | N24: 104 | O24: 150 | P24: 164 | Q24: =IFERROR(__xludf.DUMMYFUNCTION("FILTER('GBD estimates'!$BA$4:$BA$258,'GBD estimates'!$AV$4:$AV$258=Q$3,'GBD estimates'!$AU$4:$AU$258=""7 to 27 days (late neonatal)"")"),159.3470041) -> 159.347 | R24: =IFERROR(__xludf.DUMMYFUNCTION("FILTER('GBD estimates'!$BA$4:$BA$258,'GBD estimates'!$AV$4:$AV$258=R$3,'GBD estimates'!$AU$4:$AU$258=""7 to 27 days (late neonatal)"")"),95.61855998) -> 95.61856 | S24: =IFERROR(__xludf.DUMMYFUNCTION("FILTER('GBD estimates'!$BA$4:$BA$258,'GBD estimates'!$AV$4:$AV$258=S$3,'GBD estimates'!$AU$4:$AU$258=""7 to 27 days (late neonatal)"")"),143.5773073) -> 143.57731 | T24: =IFERROR(__xludf.DUMMYFUNCTION("FILTER('GBD estimates'!$BA$4:$BA$258,'GBD estimates'!$AV$4:$AV$258=T$3,'GBD estimates'!$AU$4:$AU$258=""7 to 27 days (late neonatal)"")"),129.0610436) -> 129.06104 | U24: =IFERROR(__xludf.DUMMYFUNCTION("FILTER('GBD estimates'!$BA$4:$BA$258,'GBD estimates'!$AV$4:$AV$258=U$3,'GBD estimates'!$AU$4:$AU$258=""7 to 27 days (late neonatal)"")"),69.97392707) -> 69.973927 | V24: =IFERROR(__xludf.DUMMYFUNCTION("FILTER('GBD estimates'!$BA$4:$BA$258,'GBD estimates'!$AV$4:$AV$258=V$3,'GBD estimates'!$AU$4:$AU$258=""7 to 27 days (late neonatal)"")"),102.3979599) -> 102.39796 | W24: =IFERROR(__xludf.DUMMYFUNCTION("FILTER('GBD estimates'!$BA$4:$BA$258,'GBD estimates'!$AV$4:$AV$258=W$3,'GBD estimates'!$AU$4:$AU$258=""7 to 27 days (late neonatal)"")"),117.5898727) -> 117.58987 | X24: =IFERROR(__xludf.DUMMYFUNCTION("FILTER('GBD estimates'!$BA$4:$BA$258,'GBD estimates'!$AV$4:$AV$258=X$3,'GBD estimates'!$AU$4:$AU$258=""7 to 27 days (late neonatal)"")"),256.0142374) -> 256.01424 | Y24: =IFERROR(__xludf.DUMMYFUNCTION("FILTER('GBD estimates'!$BA$4:$BA$258,'GBD estimates'!$AV$4:$AV$258=Y$3,'GBD estimates'!$AU$4:$AU$258=""7 to 27 days (late neonatal)"")"),152.644696) -> 152.6447 | Z24: 7 | AA24: =IFERROR(__xludf.DUMMYFUNCTION("FILTER('GBD estimates'!$S$4:$S$309,'GBD estimates'!$M$4:$M$309=AA$2,'GBD estimates'!$O$4:$O$309=""7-27 days"")"),96.25746212) -> 96.257462 | AB24: 281 | AD24: GW analysis | AE24: GW's analysis of malaria burden in SMC-eligible countries
E25: Post-neonatal malaria mortalities per year (babies between 28 and 364 days old) | F25: # | G25: input | H25: - | I25: 2269 | J25: 171 | K25: 1048 | L25: 1131 | M25: 985 | N25: 717 | O25: 1026 | P25: 1741 | Q25: =IFERROR(__xludf.DUMMYFUNCTION("FILTER('GBD estimates'!$BA$4:$BA$258,'GBD estimates'!$AV$4:$AV$258=Q$3,'GBD estimates'!$AU$4:$AU$258=""28 to 364 days (post neonatal)"")"),1316.323721) -> 1316.3237 | R25: =IFERROR(__xludf.DUMMYFUNCTION("FILTER('GBD estimates'!$BA$4:$BA$258,'GBD estimates'!$AV$4:$AV$258=R$3,'GBD estimates'!$AU$4:$AU$258=""28 to 364 days (post neonatal)"")"),579.8918146) -> 579.89181 | S25: =IFERROR(__xludf.DUMMYFUNCTION("FILTER('GBD estimates'!$BA$4:$BA$258,'GBD estimates'!$AV$4:$AV$258=S$3,'GBD estimates'!$AU$4:$AU$258=""28 to 364 days (post neonatal)"")"),967.3492147) -> 967.34921 | T25: =IFERROR(__xludf.DUMMYFUNCTION("FILTER('GBD estimates'!$BA$4:$BA$258,'GBD estimates'!$AV$4:$AV$258=T$3,'GBD estimates'!$AU$4:$AU$258=""28 to 364 days (post neonatal)"")"),912.8296952) -> 912.8297 | U25: =IFERROR(__xludf.DUMMYFUNCTION("FILTER('GBD estimates'!$BA$4:$BA$258,'GBD estimates'!$AV$4:$AV$258=U$3,'GBD estimates'!$AU$4:$AU$258=""28 to 364 days (post neonatal)"")"),391.0566835) -> 391.05668 | V25: =IFERROR(__xludf.DUMMYFUNCTION("FILTER('GBD estimates'!$BA$4:$BA$258,'GBD estimates'!$AV$4:$AV$258=V$3,'GBD estimates'!$AU$4:$AU$258=""28 to 364 days (post neonatal)"")"),739.9298848) -> 739.92988 | W25: =IFERROR(__xludf.DUMMYFUNCTION("FILTER('GBD estimates'!$BA$4:$BA$258,'GBD estimates'!$AV$4:$AV$258=W$3,'GBD estimates'!$AU$4:$AU$258=""28 to 364 days (post neonatal)"")"),751.4804856) -> 751.48049 | X25: =IFERROR(__xludf.DUMMYFUNCTION("FILTER('GBD estimates'!$BA$4:$BA$258,'GBD estimates'!$AV$4:$AV$258=X$3,'GBD estimates'!$AU$4:$AU$258=""28 to 364 days (post neonatal)"")"),1789.39109) -> 1789.3911 | Y25: =IFERROR(__xludf.DUMMYFUNCTION("FILTER('GBD estimates'!$BA$4:$BA$258,'GBD estimates'!$AV$4:$AV$258=Y$3,'GBD estimates'!$AU$4:$AU$258=""28 to 364 days (post neonatal)"")"),1280.356355) -> 1280.3564 | Z25: 48 | AA25: =IFERROR(__xludf.DUMMYFUNCTION("FILTER('GBD estimates'!$S$4:$S$309,'GBD estimates'!$M$4:$M$309=AA$2,'GBD estimates'!$O$4:$O$309=""<1 year"")-FILTER('GBD estimates'!$S$4:$S$309,'GBD estimates'!$M$4:$M$309=AA$2,'GBD estimates'!$O$4:$O$309=""<28 days"")"),691.27791708) -> 691.27792 | AB25: 2056 | AD25: GW analysis | AE25: GW's analysis of malaria burden in SMC-eligible countries
E26: Number of post-neonatal months of life in which children are under 1 year old | F26: # | G26: input | H26: 11 | I26: - | J26: - | K26: - | L26: - | M26: - | N26: - | O26: - | P26: - | Q26: - | R26: - | S26: - | T26: - | U26: - | V26: - | W26: - | X26: - | Y26: - | Z26: - | AA26: - | AB26: -
E27: Number of post-neonatal months of life in which children are under 3 months old | F27: # | G27: input | H27: 2 | I27: - | J27: - | K27: - | L27: - | M27: - | N27: - | O27: - | P27: - | Q27: - | R27: - | S27: - | T27: - | U27: - | V27: - | W27: - | X27: - | Y27: - | Z27: - | AA27: - | AB27: -
C29: Malaria mortality rate among the SMC-eligible population
E30: Annual malaria mortality rate among people under age 5 | F30: per 100k | G30: input | H30: - | I30: 335 | J30: 293 | K30: 295 | L30: 379 | M30: 407 | N30: 449 | O30: 485 | P30: 351 | Q30: 554 | R30: 357 | S30: 333 | T30: 716 | U30: 373 | V30: 361 | W30: 289 | X30: 366 | Y30: 588 | Z30: 280 | AA30: =IFERROR(__xludf.DUMMYFUNCTION("FILTER('GBD estimates'!$AD$4:$AD$54,'GBD estimates'!$X$4:$X$54=AA$2)"),194.2996635) -> 194.29966 | AB30: 248 | AD30: GW analysis | AE30: GW's analysis of malaria burden in SMC-eligible countries
E31: Total number of months of life in which children are under 5 years old | F31: # | G31: input | H31: 60 | I31: - | J31: - | K31: - | L31: - | M31: - | N31: - | O31: - | P31: - | Q31: - | R31: - | S31: - | T31: - | U31: - | V31: - | W31: - | X31: - | Y31: - | Z31: - | AA31: - | AB31: -
E32: Number of months of life in which children are under 3 months old | F32: # | G32: input | H32: 3 | I32: - | J32: - | K32: - | L32: - | M32: - | N32: - | O32: - | P32: - | Q32: - | R32: - | S32: - | T32: - | U32: - | V32: - | W32: - | X32: - | Y32: - | Z32: - | AA32: - | AB32: -
E33: Adjustment for malaria averted by ITN distributions not accounted for in GBD 2019 | F33: % | G33: input | H33: - | I33: 0 | J33: 0 | K33: 0 | L33: 0 | M33: 0 | N33: 0 | O33: 0 | P33: 0 | Q33: -0.05 | R33: -0.05 | S33: -0.3512063 | T33: -0.05 | U33: -0.05 | V33: -0.05 | W33: -0.05 | X33: -0.05 | Y33: -0.05 | Z33: 0 | AA33: 0 | AB33: 0 | AD33: GW guesstimate
C35: Proportion of malaria mortalities that are among the SMC-eligible population
E36: Total malaria mortalities per year | F36: # | G36: input | H36: - | I36: 11943 | J36: 926 | K36: 5829 | L36: 3607 | M36: 3140 | N36: 2286 | O36: 3272 | P36: 9444 | Q36: =IFERROR(__xludf.DUMMYFUNCTION("FILTER('GBD estimates'!$BA$4:$BA$258,'GBD estimates'!$AV$4:$AV$258=Q$3,'GBD estimates'!$AU$4:$AU$258=""All ages"")"),8241.349008) -> 8241.349 | R36: =IFERROR(__xludf.DUMMYFUNCTION("FILTER('GBD estimates'!$BA$4:$BA$258,'GBD estimates'!$AV$4:$AV$258=R$3,'GBD estimates'!$AU$4:$AU$258=""All ages"")"),3790.634534) -> 3790.6345 | S36: =IFERROR(__xludf.DUMMYFUNCTION("FILTER('GBD estimates'!$BA$4:$BA$258,'GBD estimates'!$AV$4:$AV$258=S$3,'GBD estimates'!$AU$4:$AU$258=""All ages"")"),5429.375255) -> 5429.3753 | T36: =IFERROR(__xludf.DUMMYFUNCTION("FILTER('GBD estimates'!$BA$4:$BA$258,'GBD estimates'!$AV$4:$AV$258=T$3,'GBD estimates'!$AU$4:$AU$258=""All ages"")"),6060.643259) -> 6060.6433 | U36: =IFERROR(__xludf.DUMMYFUNCTION("FILTER('GBD estimates'!$BA$4:$BA$258,'GBD estimates'!$AV$4:$AV$258=U$3,'GBD estimates'!$AU$4:$AU$258=""All ages"")"),3106.693896) -> 3106.6939 | V36: =IFERROR(__xludf.DUMMYFUNCTION("FILTER('GBD estimates'!$BA$4:$BA$258,'GBD estimates'!$AV$4:$AV$258=V$3,'GBD estimates'!$AU$4:$AU$258=""All ages"")"),4403.622657) -> 4403.6227 | W36: =IFERROR(__xludf.DUMMYFUNCTION("FILTER('GBD estimates'!$BA$4:$BA$258,'GBD estimates'!$AV$4:$AV$258=W$3,'GBD estimates'!$AU$4:$AU$258=""All ages"")"),6495.373611) -> 6495.3736 | X36: =IFERROR(__xludf.DUMMYFUNCTION("FILTER('GBD estimates'!$BA$4:$BA$258,'GBD estimates'!$AV$4:$AV$258=X$3,'GBD estimates'!$AU$4:$AU$258=""All ages"")"),9889.762202) -> 9889.7622 | Y36: =IFERROR(__xludf.DUMMYFUNCTION("FILTER('GBD estimates'!$BA$4:$BA$258,'GBD estimates'!$AV$4:$AV$258=Y$3,'GBD estimates'!$AU$4:$AU$258=""All ages"")"),8078.866903) -> 8078.8669 | Z36: 135 | AA36: =IFERROR(__xludf.DUMMYFUNCTION("FILTER('GBD estimates'!$S$4:$S$309,'GBD estimates'!$M$4:$M$309=AA$2,'GBD estimates'!$O$4:$O$309=""All ages"")"),5776.359003) -> 5776.359 | AB36: 6280 | AD36: GW analysis | AE36: GW's analysis of malaria burden in SMC-eligible countries
C38: Malaria incidence among people under age 15
E39: Malaria incidence among people under 5 | F39: per 100k | G39: input | H39: - | I39: 72800 | J39: 47873 | K39: 78599 | L39: 76062 | M39: 91107 | N39: 96207 | O39: 93495 | P39: 82270 | Q39: =IFERROR(__xludf.DUMMYFUNCTION("FILTER('GBD estimates'!$CA$4:$CA$105,'GBD estimates'!$BV$4:$BV$105=Q$3,'GBD estimates'!$BU$4:$BU$105=""Under 5"")"),92549.9) -> 92549.9 | R39: =IFERROR(__xludf.DUMMYFUNCTION("FILTER('GBD estimates'!$CA$4:$CA$105,'GBD estimates'!$BV$4:$BV$105=R$3,'GBD estimates'!$BU$4:$BU$105=""Under 5"")"),66346.67) -> 66346.67 | S39: =IFERROR(__xludf.DUMMYFUNCTION("FILTER('GBD estimates'!$CA$4:$CA$105,'GBD estimates'!$BV$4:$BV$105=S$3,'GBD estimates'!$BU$4:$BU$105=""Under 5"")"),77203.83) -> 77203.83 | T39: =IFERROR(__xludf.DUMMYFUNCTION("FILTER('GBD estimates'!$CA$4:$CA$105,'GBD estimates'!$BV$4:$BV$105=T$3,'GBD estimates'!$BU$4:$BU$105=""Under 5"")"),98746.64) -> 98746.64 | U39: =IFERROR(__xludf.DUMMYFUNCTION("FILTER('GBD estimates'!$CA$4:$CA$105,'GBD estimates'!$BV$4:$BV$105=U$3,'GBD estimates'!$BU$4:$BU$105=""Under 5"")"),90253.5) -> 90253.5 | V39: =IFERROR(__xludf.DUMMYFUNCTION("FILTER('GBD estimates'!$CA$4:$CA$105,'GBD estimates'!$BV$4:$BV$105=V$3,'GBD estimates'!$BU$4:$BU$105=""Under 5"")"),72018.194) -> 72018.194 | W39: =IFERROR(__xludf.DUMMYFUNCTION("FILTER('GBD estimates'!$CA$4:$CA$105,'GBD estimates'!$BV$4:$BV$105=W$3,'GBD estimates'!$BU$4:$BU$105=""Under 5"")"),93840.62) -> 93840.62 | X39: =IFERROR(__xludf.DUMMYFUNCTION("FILTER('GBD estimates'!$CA$4:$CA$105,'GBD estimates'!$BV$4:$BV$105=X$3,'GBD estimates'!$BU$4:$BU$105=""Under 5"")"),77809.67) -> 77809.67 | Y39: =IFERROR(__xludf.DUMMYFUNCTION("FILTER('GBD estimates'!$CA$4:$CA$105,'GBD estimates'!$BV$4:$BV$105=Y$3,'GBD estimates'!$BU$4:$BU$105=""Under 5"")"),69826.126) -> 69826.126 | Z39: 46489 | AA39: =IFERROR(__xludf.DUMMYFUNCTION("FILTER('GBD estimates'!$AO$4:$AO$156,'GBD estimates'!$AI$4:$AI$156=AA$2,'GBD estimates'!$AK$4:$AK$156=""<5 years"")"),63337.56905) -> 63337.569 | AB39: 90318 | AD39: GW analysis | AE39: GW's analysis of malaria burden in SMC-eligible countries
E40: Malaria incidence among people age 5 to 14 | F40: per 100k | G40: input | H40: - | I40: 30179 | J40: 21805 | K40: 32926 | L40: 31197 | M40: 37367 | N40: 39459 | O40: 38347 | P40: 34580 | Q40: =IFERROR(__xludf.DUMMYFUNCTION("FILTER('GBD estimates'!$CA$4:$CA$105,'GBD estimates'!$BV$4:$BV$105=Q$3,'GBD estimates'!$BU$4:$BU$105=""5 to 14"")"),39110.878) -> 39110.878 | R40: =IFERROR(__xludf.DUMMYFUNCTION("FILTER('GBD estimates'!$CA$4:$CA$105,'GBD estimates'!$BV$4:$BV$105=R$3,'GBD estimates'!$BU$4:$BU$105=""5 to 14"")"),29057.47) -> 29057.47 | S40: =IFERROR(__xludf.DUMMYFUNCTION("FILTER('GBD estimates'!$CA$4:$CA$105,'GBD estimates'!$BV$4:$BV$105=S$3,'GBD estimates'!$BU$4:$BU$105=""5 to 14"")"),32687.145) -> 32687.145 | T40: =IFERROR(__xludf.DUMMYFUNCTION("FILTER('GBD estimates'!$CA$4:$CA$105,'GBD estimates'!$BV$4:$BV$105=T$3,'GBD estimates'!$BU$4:$BU$105=""5 to 14"")"),40692.243) -> 40692.243 | U40: =IFERROR(__xludf.DUMMYFUNCTION("FILTER('GBD estimates'!$CA$4:$CA$105,'GBD estimates'!$BV$4:$BV$105=U$3,'GBD estimates'!$BU$4:$BU$105=""5 to 14"")"),36989.745) -> 36989.745 | V40: =IFERROR(__xludf.DUMMYFUNCTION("FILTER('GBD estimates'!$CA$4:$CA$105,'GBD estimates'!$BV$4:$BV$105=V$3,'GBD estimates'!$BU$4:$BU$105=""5 to 14"")"),30377.278) -> 30377.278 | W40: =IFERROR(__xludf.DUMMYFUNCTION("FILTER('GBD estimates'!$CA$4:$CA$105,'GBD estimates'!$BV$4:$BV$105=W$3,'GBD estimates'!$BU$4:$BU$105=""5 to 14"")"),38318.27) -> 38318.27 | X40: =IFERROR(__xludf.DUMMYFUNCTION("FILTER('GBD estimates'!$CA$4:$CA$105,'GBD estimates'!$BV$4:$BV$105=X$3,'GBD estimates'!$BU$4:$BU$105=""5 to 14"")"),33155.254) -> 33155.254 | Y40: =IFERROR(__xludf.DUMMYFUNCTION("FILTER('GBD estimates'!$CA$4:$CA$105,'GBD estimates'!$BV$4:$BV$105=Y$3,'GBD estimates'!$BU$4:$BU$105=""5 to 14"")"),30076.665) -> 30076.665 | Z40: 19498 | AA40: =IFERROR(__xludf.DUMMYFUNCTION("FILTER('GBD estimates'!$AO$4:$AO$156,'GBD estimates'!$AI$4:$AI$156=AA$2,'GBD estimates'!$AK$4:$AK$156=""5-14 years"")"),26979.99336) -> 26979.993 | AB40: 38439 | AD40: GW analysis | AE40: GW's analysis of malaria burden in SMC-eligible countries
A42: Outcomes
C44: Mortality reduction among people under age 5
E45: Reduction in malaria incidence for children under age 5 targeted for SMC found in GiveWell's adjusted version of the Meremikwu et al. 2012 meta-analysis | F45: % | G45: input | H45: 0.75 | I45: - | J45: - | K45: - | L45: - | M45: - | N45: - | O45: - | P45: - | Q45: - | R45: - | S45: - | T45: - | U45: - | V45: - | W45: - | X45: - | Y45: - | Z45: - | AA45: - | AB45: - | AD45: GW analysis | AE45: GW's report on seasonal malaria chemoprevention (SMC)
E46: Estimated proportion of children targeted for SMC in trials that received SMC | F46: % | G46: input | H46: 0.8977 | I46: - | J46: - | K46: - | L46: - | M46: - | N46: - | O46: - | P46: - | Q46: - | R46: - | S46: - | T46: - | U46: - | V46: - | W46: - | X46: - | Y46: - | Z46: - | AA46: - | AB46: - | AD46: GW analysis | AE46: GW's analysis of SMC coverage in trials
E47: Internal validity adjustment | F47: % | G47: input | H47: -0.05 | I47: - | J47: - | K47: - | L47: - | M47: - | N47: - | O47: - | P47: - | Q47: - | R47: - | S47: - | T47: - | U47: - | V47: - | W47: - | X47: - | Y47: - | Z47: - | AA47: - | AB47: - | AD47: GW guesstimate
E48: External validity adjustment | F48: % | G48: input | H48: 0 | I48: - | J48: - | K48: - | L48: - | M48: - | N48: - | O48: - | P48: - | Q48: - | R48: - | S48: - | T48: - | U48: - | V48: - | W48: - | X48: - | Y48: - | Z48: - | AA48: - | AB48: - | AD48: GW guesstimate
E49: Adjustment for lower effectiveness outside the Sahel region of Africa | F49: % | G49: input | H49: - | I49: 0 | J49: 0 | K49: 0 | L49: -0.25 | M49: -0.25 | N49: -0.25 | O49: -0.25 | P49: -0.25 | Q49: 0 | R49: 0 | S49: 0 | T49: 0 | U49: 0 | V49: 0 | W49: 0 | X49: 0 | Y49: 0 | Z49: 0 | AA49: 0 | AB49: -0.25 | AD49: GW analysis
E50: Ratio of the reduction in malaria mortality to the reduction in malaria incidence | F50: % | G50: input | H50: 1 | I50: - | J50: - | K50: - | L50: - | M50: - | N50: - | O50: - | P50: - | Q50: - | R50: - | S50: - | T50: - | U50: - | V50: - | W50: - | X50: - | Y50: - | Z50: - | AA50: - | AB50: - | AD50: GW guesstimate
E51: Relative reduction in mortality rate due to vaccine rollout | F51: % | G51: input | H51: - | I51: -0.14 | J51: -0.02 | K51: -0.12 | L51: -0.11 | M51: -0.11 | N51: -0.11 | O51: -0.11 | P51: -0.17 | Q51: -0.11 | R51: -0.11 | S51: -0.11 | T51: -0.11 | U51: -0.11 | V51: -0.11 | W51: -0.11 | X51: -0.11 | Y51: -0.11 | Z51: -0.14 | AA51: -0.13 | AB51: -0.17 | AD51: GW analysis | AE51: GW's analysis of malaria mortality averted due to vaccine rollout
E52: Indirect malaria deaths per direct malaria death | F52: # | G52: input | H52: 0.75 | I52: - | J52: - | K52: - | L52: - | M52: - | N52: - | O52: - | P52: - | Q52: - | R52: - | S52: - | T52: - | U52: - | V52: - | W52: - | X52: - | Y52: - | Z52: - | AA52: - | AB52: - | AD52: GW guesstimate
E53: Proportion of annual malaria mortality that occurs during the SMC season | F53: % | G53: input | H53: - | I53: 0.7 | J53: 0.7 | K53: 0.7 | L53: =AVERAGE(33%, 70%) -> 0.515 | M53: =AVERAGE(33%, 70%) -> 0.515 | N53: =AVERAGE(33%, 70%) -> 0.515 | O53: =AVERAGE(33%, 70%) -> 0.515 | P53: =AVERAGE(33%, 70%) -> 0.515 | Q53: 0.7 | R53: 0.7 | S53: 0.7 | T53: 0.7 | U53: 0.7 | V53: 0.7 | W53: 0.7 | X53: 0.7 | Y53: 0.7 | Z53: 0.7 | AA53: 0.7 | AB53: 0.62 | AD53: GW guesstimate
C55: Mortality reduction among people over age 5
E56: Reduction in malaria incidence among the SMC-eligible population found in Cisse et al. 2016 | F56: % | G56: input | H56: 0.6 | I56: - | J56: - | K56: - | L56: - | M56: - | N56: - | O56: - | P56: - | Q56: - | R56: - | S56: - | T56: - | U56: - | V56: - | W56: - | X56: - | Y56: - | Z56: - | AA56: - | AB56: - | AD56: Cisse et al. 2016
E57: Reduction in malaria incidence among the population too old to be eligible for SMC found in Cisse et al. 2016 | F57: % | G57: input | H57: 0.26 | I57: - | J57: - | K57: - | L57: - | M57: - | N57: - | O57: - | P57: - | Q57: - | R57: - | S57: - | T57: - | U57: - | V57: - | W57: - | X57: - | Y57: - | Z57: - | AA57: - | AB57: - | AD57: Cisse et al. 2016
E58: Adjustment for differences in program coverage and transmission intensity in the populations studied by the Cisse et al. 2016 trial and the populations targeted by grantee programs | F58: % | G58: input | H58: -0.6912579 | I58: - | J58: - | K58: - | L58: - | M58: - | N58: - | O58: - | P58: - | Q58: - | R58: - | S58: - | T58: - | U58: - | V58: - | W58: - | X58: - | Y58: - | Z58: - | AA58: - | AB58: - | AD58: GW analysis | AE58: GW's analysis of the indirect effects of Malaria Consortium's SMC programs relative to Cisse et al. 2016
C60: Malaria prevalence reduction among people under age 15
E61: National population under 5 | F61: # | G61: input | H61: - | I61: =IFERROR(__xludf.DUMMYFUNCTION("FILTER('GBD estimates'!$H$4:$H$1992,'GBD estimates'!$B$4:$B$1992=I$2,'GBD estimates'!$D$4:$D$1992=""<5 years"")"),4106465.0) -> 4106465 | J61: =IFERROR(__xludf.DUMMYFUNCTION("FILTER('GBD estimates'!$H$4:$H$1992,'GBD estimates'!$B$4:$B$1992=J$2,'GBD estimates'!$D$4:$D$1992=""<5 years"")"),3635515.0) -> 3635515 | K61: =IFERROR(__xludf.DUMMYFUNCTION("FILTER('GBD estimates'!$H$4:$H$1992,'GBD estimates'!$B$4:$B$1992=K$2,'GBD estimates'!$D$4:$D$1992=""<5 years"")"),4354391.0) -> 4354391 | L61: =IFERROR(__xludf.DUMMYFUNCTION("FILTER('GBD estimates'!$H$4:$H$1992,'GBD estimates'!$B$4:$B$1992=L$2,'GBD estimates'!$D$4:$D$1992=""<5 years"")"),1.356074E7) -> 13560740 | M61: =IFERROR(__xludf.DUMMYFUNCTION("FILTER('GBD estimates'!$H$4:$H$1992,'GBD estimates'!$B$4:$B$1992=M$2,'GBD estimates'!$D$4:$D$1992=""<5 years"")"),1.356074E7) -> 13560740 | N61: =IFERROR(__xludf.DUMMYFUNCTION("FILTER('GBD estimates'!$H$4:$H$1992,'GBD estimates'!$B$4:$B$1992=N$2,'GBD estimates'!$D$4:$D$1992=""<5 years"")"),1.356074E7) -> 13560740 | O61: =IFERROR(__xludf.DUMMYFUNCTION("FILTER('GBD estimates'!$H$4:$H$1992,'GBD estimates'!$B$4:$B$1992=O$2,'GBD estimates'!$D$4:$D$1992=""<5 years"")"),1.356074E7) -> 13560740 | P61: =IFERROR(__xludf.DUMMYFUNCTION("FILTER('GBD estimates'!$H$4:$H$1992,'GBD estimates'!$B$4:$B$1992=P$2,'GBD estimates'!$D$4:$D$1992=""<5 years"")"),5179217.0) -> 5179217 | Q61: =IFERROR(__xludf.DUMMYFUNCTION("FILTER('GBD estimates'!$H$4:$H$1992,'GBD estimates'!$B$4:$B$1992=Q$2,'GBD estimates'!$D$4:$D$1992=""<5 years"")"),3.7117842E7) -> 37117842 | R61: =IFERROR(__xludf.DUMMYFUNCTION("FILTER('GBD estimates'!$H$4:$H$1992,'GBD estimates'!$B$4:$B$1992=R$2,'GBD estimates'!$D$4:$D$1992=""<5 years"")"),3.7117842E7) -> 37117842 | S61: =IFERROR(__xludf.DUMMYFUNCTION("FILTER('GBD estimates'!$H$4:$H$1992,'GBD estimates'!$B$4:$B$1992=S$2,'GBD estimates'!$D$4:$D$1992=""<5 years"")"),3.7117842E7) -> 37117842 | T61: =IFERROR(__xludf.DUMMYFUNCTION("FILTER('GBD estimates'!$H$4:$H$1992,'GBD estimates'!$B$4:$B$1992=T$2,'GBD estimates'!$D$4:$D$1992=""<5 years"")"),3.7117842E7) -> 37117842 | U61: =IFERROR(__xludf.DUMMYFUNCTION("FILTER('GBD estimates'!$H$4:$H$1992,'GBD estimates'!$B$4:$B$1992=U$2,'GBD estimates'!$D$4:$D$1992=""<5 years"")"),3.7117842E7) -> 37117842 | V61: =IFERROR(__xludf.DUMMYFUNCTION("FILTER('GBD estimates'!$H$4:$H$1992,'GBD estimates'!$B$4:$B$1992=V$2,'GBD estimates'!$D$4:$D$1992=""<5 years"")"),3.7117842E7) -> 37117842 | W61: =IFERROR(__xludf.DUMMYFUNCTION("FILTER('GBD estimates'!$H$4:$H$1992,'GBD estimates'!$B$4:$B$1992=W$2,'GBD estimates'!$D$4:$D$1992=""<5 years"")"),3.7117842E7) -> 37117842 | X61: =IFERROR(__xludf.DUMMYFUNCTION("FILTER('GBD estimates'!$H$4:$H$1992,'GBD estimates'!$B$4:$B$1992=X$2,'GBD estimates'!$D$4:$D$1992=""<5 years"")"),3.7117842E7) -> 37117842 | Y61: =IFERROR(__xludf.DUMMYFUNCTION("FILTER('GBD estimates'!$H$4:$H$1992,'GBD estimates'!$B$4:$B$1992=Y$2,'GBD estimates'!$D$4:$D$1992=""<5 years"")"),3.7117842E7) -> 37117842 | Z61: =IFERROR(__xludf.DUMMYFUNCTION("FILTER('GBD estimates'!$H$4:$H$1992,'GBD estimates'!$B$4:$B$1992=Z$2,'GBD estimates'!$D$4:$D$1992=""<5 years"")"),1562334.0) -> 1562334 | AA61: =IFERROR(__xludf.DUMMYFUNCTION("FILTER('GBD estimates'!$H$4:$H$1992,'GBD estimates'!$B$4:$B$1992=AA$2,'GBD estimates'!$D$4:$D$1992=""<5 years"")"),1172510.0) -> 1172510 | AB61: =IFERROR(__xludf.DUMMYFUNCTION("FILTER('GBD estimates'!$H$4:$H$1992,'GBD estimates'!$B$4:$B$1992=AB$2,'GBD estimates'!$D$4:$D$1992=""<5 years"")"),7317718.0) -> 7317718 | AD61: GBD 2021
E62: National population age 5 to 14 | F62: # | G62: input | H62: - | I62: =IFERROR(__xludf.DUMMYFUNCTION("FILTER('GBD estimates'!$H$4:$H$1992,'GBD estimates'!$B$4:$B$1992=I$2,'GBD estimates'!$D$4:$D$1992=""5-14 years"")"),6265702.0) -> 6265702 | J62: =IFERROR(__xludf.DUMMYFUNCTION("FILTER('GBD estimates'!$H$4:$H$1992,'GBD estimates'!$B$4:$B$1992=J$2,'GBD estimates'!$D$4:$D$1992=""5-14 years"")"),5379382.0) -> 5379382 | K62: =IFERROR(__xludf.DUMMYFUNCTION("FILTER('GBD estimates'!$H$4:$H$1992,'GBD estimates'!$B$4:$B$1992=K$2,'GBD estimates'!$D$4:$D$1992=""5-14 years"")"),7217393.0) -> 7217393 | L62: =IFERROR(__xludf.DUMMYFUNCTION("FILTER('GBD estimates'!$H$4:$H$1992,'GBD estimates'!$B$4:$B$1992=L$2,'GBD estimates'!$D$4:$D$1992=""5-14 years"")"),2.4438179E7) -> 24438179 | M62: =IFERROR(__xludf.DUMMYFUNCTION("FILTER('GBD estimates'!$H$4:$H$1992,'GBD estimates'!$B$4:$B$1992=M$2,'GBD estimates'!$D$4:$D$1992=""5-14 years"")"),2.4438179E7) -> 24438179 | N62: =IFERROR(__xludf.DUMMYFUNCTION("FILTER('GBD estimates'!$H$4:$H$1992,'GBD estimates'!$B$4:$B$1992=N$2,'GBD estimates'!$D$4:$D$1992=""5-14 years"")"),2.4438179E7) -> 24438179 | O62: =IFERROR(__xludf.DUMMYFUNCTION("FILTER('GBD estimates'!$H$4:$H$1992,'GBD estimates'!$B$4:$B$1992=O$2,'GBD estimates'!$D$4:$D$1992=""5-14 years"")"),2.4438179E7) -> 24438179 | P62: =IFERROR(__xludf.DUMMYFUNCTION("FILTER('GBD estimates'!$H$4:$H$1992,'GBD estimates'!$B$4:$B$1992=P$2,'GBD estimates'!$D$4:$D$1992=""5-14 years"")"),9086792.0) -> 9086792 | Q62: =IFERROR(__xludf.DUMMYFUNCTION("FILTER('GBD estimates'!$H$4:$H$1992,'GBD estimates'!$B$4:$B$1992=Q$2,'GBD estimates'!$D$4:$D$1992=""5-14 years"")"),6.447122E7) -> 64471220 | R62: =IFERROR(__xludf.DUMMYFUNCTION("FILTER('GBD estimates'!$H$4:$H$1992,'GBD estimates'!$B$4:$B$1992=R$2,'GBD estimates'!$D$4:$D$1992=""5-14 years"")"),6.447122E7) -> 64471220 | S62: =IFERROR(__xludf.DUMMYFUNCTION("FILTER('GBD estimates'!$H$4:$H$1992,'GBD estimates'!$B$4:$B$1992=S$2,'GBD estimates'!$D$4:$D$1992=""5-14 years"")"),6.447122E7) -> 64471220 | T62: =IFERROR(__xludf.DUMMYFUNCTION("FILTER('GBD estimates'!$H$4:$H$1992,'GBD estimates'!$B$4:$B$1992=T$2,'GBD estimates'!$D$4:$D$1992=""5-14 years"")"),6.447122E7) -> 64471220 | U62: =IFERROR(__xludf.DUMMYFUNCTION("FILTER('GBD estimates'!$H$4:$H$1992,'GBD estimates'!$B$4:$B$1992=U$2,'GBD estimates'!$D$4:$D$1992=""5-14 years"")"),6.447122E7) -> 64471220 | V62: =IFERROR(__xludf.DUMMYFUNCTION("FILTER('GBD estimates'!$H$4:$H$1992,'GBD estimates'!$B$4:$B$1992=V$2,'GBD estimates'!$D$4:$D$1992=""5-14 years"")"),6.447122E7) -> 64471220 | W62: =IFERROR(__xludf.DUMMYFUNCTION("FILTER('GBD estimates'!$H$4:$H$1992,'GBD estimates'!$B$4:$B$1992=W$2,'GBD estimates'!$D$4:$D$1992=""5-14 years"")"),6.447122E7) -> 64471220 | X62: =IFERROR(__xludf.DUMMYFUNCTION("FILTER('GBD estimates'!$H$4:$H$1992,'GBD estimates'!$B$4:$B$1992=X$2,'GBD estimates'!$D$4:$D$1992=""5-14 years"")"),6.447122E7) -> 64471220 | Y62: =IFERROR(__xludf.DUMMYFUNCTION("FILTER('GBD estimates'!$H$4:$H$1992,'GBD estimates'!$B$4:$B$1992=Y$2,'GBD estimates'!$D$4:$D$1992=""5-14 years"")"),6.447122E7) -> 64471220 | Z62: =IFERROR(__xludf.DUMMYFUNCTION("FILTER('GBD estimates'!$H$4:$H$1992,'GBD estimates'!$B$4:$B$1992=Z$2,'GBD estimates'!$D$4:$D$1992=""5-14 years"")"),2732617.0) -> 2732617 | AA62: =IFERROR(__xludf.DUMMYFUNCTION("FILTER('GBD estimates'!$H$4:$H$1992,'GBD estimates'!$B$4:$B$1992=AA$2,'GBD estimates'!$D$4:$D$1992=""5-14 years"")"),2136532.0) -> 2136532 | AB62: =IFERROR(__xludf.DUMMYFUNCTION("FILTER('GBD estimates'!$H$4:$H$1992,'GBD estimates'!$B$4:$B$1992=AB$2,'GBD estimates'!$D$4:$D$1992=""5-14 years"")"),1.2517987E7) -> 12517987 | AD62: GBD 2021
C64: Long-term income increases for people under age 15
E65: Increase in annual income per malaria case averted among people under age 15 | F65: % | G65: input | H65: 0.0064543 | I65: - | J65: - | K65: - | L65: - | M65: - | N65: - | O65: - | P65: - | Q65: - | R65: - | S65: - | T65: - | U65: - | V65: - | W65: - | X65: - | Y65: - | Z65: - | AA65: - | AB65: - | AD65: GW guesstimate | AE65: GW's analysis of malaria income effect size
E66: Average number of years between receiving SMC and the beginning of long-term benefits | F66: # | G66: input | H66: 12.5 | I66: - | J66: - | K66: - | L66: - | M66: - | N66: - | O66: - | P66: - | Q66: - | R66: - | S66: - | T66: - | U66: - | V66: - | W66: - | X66: - | Y66: - | Z66: - | AA66: - | AB66: - | AD66: GW guesstimate
E67: Discount rate for future benefits | F67: % | G67: input | H67: 0.04 | I67: - | J67: - | K67: - | L67: - | M67: - | N67: - | O67: - | P67: - | Q67: - | R67: - | S67: - | T67: - | U67: - | V67: - | W67: - | X67: - | Y67: - | Z67: - | AA67: - | AB67: - | AD67: GW analysis | AE67: GW's moral weights and discount rate
E68: Expected number of years the long-term benefits of receiving SMC will last | F68: # | G68: input | H68: 40 | I68: - | J68: - | K68: - | L68: - | M68: - | N68: - | O68: - | P68: - | Q68: - | R68: - | S68: - | T68: - | U68: - | V68: - | W68: - | X68: - | Y68: - | Z68: - | AA68: - | AB68: - | AD68: GW guesstimate
E69: Multiplier for resource sharing within households | F69: # | G69: input | H69: 2 | I69: - | J69: - | K69: - | L69: - | M69: - | N69: - | O69: - | P69: - | Q69: - | R69: - | S69: - | T69: - | U69: - | V69: - | W69: - | X69: - | Y69: - | Z69: - | AA69: - | AB69: - | AD69: GW analysis | AE69: GW's analysis on estimating multiplier for benefits experienced by other household members
A71: Value of outcomes
C73: Value of outcomes
E74: Value assigned to averting a malaria-attributable death of a person under age 5 | F74: UoV | G74: input | H74: 116.25262 | I74: - | J74: - | K74: - | L74: - | M74: - | N74: - | O74: - | P74: - | Q74: - | R74: - | S74: - | T74: - | U74: - | V74: - | W74: - | X74: - | Y74: - | Z74: - | AA74: - | AB74: - | AD74: GW value judgment | AE74: GW's moral weights and discount rate
E75: Value assigned to averting a malaria-attributable death of a person age 5 or older | F75: UoV | G75: input | H75: 73.1914 | I75: - | J75: - | K75: - | L75: - | M75: - | N75: - | O75: - | P75: - | Q75: - | R75: - | S75: - | T75: - | U75: - | V75: - | W75: - | X75: - | Y75: - | Z75: - | AA75: - | AB75: - | AD75: GW value judgment | AE75: GW's moral weights and discount rate
E76: Value assigned to doubling consumption for one person for one year | F76: UoV | G76: input | H76: 1 | I76: - | J76: - | K76: - | L76: - | M76: - | N76: - | O76: - | P76: - | Q76: - | R76: - | S76: - | T76: - | U76: - | V76: - | W76: - | X76: - | Y76: - | Z76: - | AA76: - | AB76: - | AD76: GW value judgment | AE76: GW's moral weights and discount rate
E77: Value assigned to increasing ln(consumption) by one unit for one person for one year | F77: UoV | G77: input | H77: =H76/ln(2) -> 1.442695 | I77: - | J77: - | K77: - | L77: - | M77: - | N77: - | O77: - | P77: - | Q77: - | R77: - | S77: - | T77: - | U77: - | V77: - | W77: - | X77: - | Y77: - | Z77: - | AA77: - | AB77: - | AD77: GW value judgment | AE77: GW's moral weights and discount rate
A79: Summary of outcomes and initial cost-effectiveness (before final adjustments)
C81: Cost-effectiveness of GiveDirectly
E82: Value generated per dollar donated to GiveDirectly's unconditional cash transfer program | F82: UoV | G82: input | H82: 0.0033545 | I82: - | J82: - | K82: - | L82: - | M82: - | N82: - | O82: - | P82: - | Q82: - | R82: - | S82: - | T82: - | U82: - | V82: - | W82: - | X82: - | Y82: - | Z82: - | AA82: - | AB82: - | AD82: GW analysis | AE82: GW's CEA for GiveDirectly's unconditional cash transfers
A84: Adjustments
C86: Supplemental grantee-level adjustments
D87: Risk of wastage
E88: Double treatment | F88: % | G88: input | H88: 0 | I88: - | J88: - | K88: - | L88: - | M88: - | N88: - | O88: - | P88: - | Q88: - | R88: - | S88: - | T88: - | U88: - | V88: - | W88: - | X88: - | Y88: - | Z88: - | AA88: - | AB88: - | AD88: GW guesstimate
E89: Ineffective goods | F89: % | G89: input | H89: 0 | I89: - | J89: - | K89: - | L89: - | M89: - | N89: - | O89: - | P89: - | Q89: - | R89: - | S89: - | T89: - | U89: - | V89: - | W89: - | X89: - | Y89: - | Z89: - | AA89: - | AB89: - | AD89: GW guesstimate
E90: Goods purchased and left in storage until they expire / cash doesn't receive recipients or is taken back from them inappropriately | F90: % | G90: input | H90: 0 | I90: - | J90: - | K90: - | L90: - | M90: - | N90: - | O90: - | P90: - | Q90: - | R90: - | S90: - | T90: - | U90: - | V90: - | W90: - | X90: - | Y90: - | Z90: - | AA90: - | AB90: - | AD90: GW guesstimate
D91: Quality of monitoring and evaluation
E92: Incomplete or unrepresentative monitoring results | F92: % | G92: input | H92: 0 | I92: - | J92: - | K92: - | L92: - | M92: - | N92: - | O92: - | P92: - | Q92: - | R92: - | S92: - | T92: - | U92: - | V92: - | W92: - | X92: - | Y92: - | Z92: - | AA92: - | AB92: - | AD92: GW guesstimate
E93: Biased monitoring results | F93: % | G93: input | H93: -0.02 | I93: - | J93: - | K93: - | L93: - | M93: - | N93: - | O93: - | P93: - | Q93: - | R93: - | S93: - | T93: - | U93: - | V93: - | W93: - | X93: - | Y93: - | Z93: - | AA93: - | AB93: - | AD93: GW guesstimate
D94: Confidence in funds being used for intended purpose
E95: Change of priorities | F95: % | G95: input | H95: -0.01 | I95: - | J95: - | K95: - | L95: - | M95: - | N95: - | O95: - | P95: - | Q95: - | R95: - | S95: - | T95: - | U95: - | V95: - | W95: - | X95: - | Y95: - | Z95: - | AA95: - | AB95: - | AD95: GW guesstimate
E96: Non-funding bottlenecks | F96: % | G96: input | H96: 0 | I96: - | J96: - | K96: - | L96: - | M96: - | N96: - | O96: - | P96: - | Q96: - | R96: - | S96: - | T96: - | U96: - | V96: - | W96: - | X96: - | Y96: - | Z96: - | AA96: - | AB96: - | AD96: GW guesstimate
E97: Within-org fungibility | F97: % | G97: input | H97: -0.05 | I97: - | J97: - | K97: - | L97: - | M97: - | N97: - | O97: - | P97: - | Q97: - | R97: - | S97: - | T97: - | U97: - | V97: - | W97: - | X97: - | Y97: - | Z97: - | AA97: - | AB97: - | AD97: GW guesstimate
C99: Supplemental intervention-level adjustments
E100: Malaria morbidity | F100: % | G100: input | H100: 0.09 | I100: - | J100: - | K100: - | L100: - | M100: - | N100: - | O100: - | P100: - | Q100: - | R100: - | S100: - | T100: - | U100: - | V100: - | W100: - | X100: - | Y100: - | Z100: - | AA100: - | AB100: - | AD100: GW guesstimate | AE100: GW's supplemental intervention-level adjustments
E101: Short-term anemia effects | F101: % | G101: input | H101: 0.09 | I101: - | J101: - | K101: - | L101: - | M101: - | N101: - | O101: - | P101: - | Q101: - | R101: - | S101: - | T101: - | U101: - | V101: - | W101: - | X101: - | Y101: - | Z101: - | AA101: - | AB101: - | AD101: GW guesstimate | AE101: GW's supplemental intervention-level adjustments
E102: Investment of income increases | F102: % | G102: input | H102: 0.05 | I102: - | J102: - | K102: - | L102: - | M102: - | N102: - | O102: - | P102: - | Q102: - | R102: - | S102: - | T102: - | U102: - | V102: - | W102: - | X102: - | Y102: - | Z102: - | AA102: - | AB102: - | AD102: GW guesstimate | AE102: GW's supplemental intervention-level adjustments
E103: Treatment costs averted from prevention | F103: % | G103: input | H103: 0.2 | I103: - | J103: - | K103: - | L103: - | M103: - | N103: - | O103: - | P103: - | Q103: - | R103: - | S103: - | T103: - | U103: - | V103: - | W103: - | X103: - | Y103: - | Z103: - | AA103: - | AB103: - | AD103: GW guesstimate | AE103: GW's write-up on treatment costs averted by health-improving interventions
E104: Serious adverse events due to side effects of treatment | F104: % | G104: input | H104: -0.006 | I104: - | J104: - | K104: - | L104: - | M104: - | N104: - | O104: - | P104: - | Q104: - | R104: - | S104: - | T104: - | U104: - | V104: - | W104: - | X104: - | Y104: - | Z104: - | AA104: - | AB104: - | AD104: GW guesstimate | AE104: GW's supplemental intervention-level adjustments
E105: Failure to ingest first day of treatment of SMC | F105: % | G105: input | H105: -0.035 | I105: - | J105: - | K105: - | L105: - | M105: - | N105: - | O105: - | P105: - | Q105: - | R105: - | S105: - | T105: - | U105: - | V105: - | W105: - | X105: - | Y105: - | Z105: - | AA105: - | AB105: - | AD105: GW guesstimate | AE105: GW's supplemental intervention-level adjustments
E106: Rebound effects / decreased immunity development | F106: % | G106: input | H106: -0.04 | I106: - | J106: - | K106: - | L106: - | M106: - | N106: - | O106: - | P106: - | Q106: - | R106: - | S106: - | T106: - | U106: - | V106: - | W106: - | X106: - | Y106: - | Z106: - | AA106: - | AB106: - | AD106: GW guesstimate | AE106: GW's supplemental intervention-level adjustments
E107: Drug resistance | F107: % | G107: input | H107: - | I107: -0.04 | J107: -0.04 | K107: -0.04 | L107: -0.2 | M107: -0.2 | N107: -0.2 | O107: -0.2 | P107: -0.2 | Q107: -0.04 | R107: -0.04 | S107: -0.04 | T107: -0.04 | U107: -0.04 | V107: -0.04 | W107: -0.04 | X107: -0.04 | Y107: -0.04 | Z107: -0.04 | AA107: -0.04 | AB107: -0.2 | AD107: GW guesstimate | AE107: GW's supplemental intervention-level adjustments
E108: Subnational adjustments | F108: % | G108: input | H108: 0.032 | I108: - | J108: - | K108: - | L108: - | M108: - | N108: - | O108: - | P108: - | Q108: - | R108: - | S108: - | T108: - | U108: - | V108: - | W108: - | X108: - | Y108: - | Z108: - | AA108: - | AB108: - | AD108: GW guesstimate | AE108: GW's supplemental intervention-level adjustments
E109: Marginal funding goes to lower priority areas | F109: % | G109: input | H109: - | I109: -0.15 | J109: -0.1 | K109: -0.2 | L109: 0 | M109: 0 | N109: 0 | O109: 0 | P109: 0 | Q109: 0 | R109: 0 | S109: 0 | T109: 0 | U109: 0 | V109: 0 | W109: 0 | X109: 0 | Y109: 0 | Z109: 0 | AA109: -0.05 | AB109: 0 | AD109: GW guesstimate | AE109: GW's supplemental intervention-level adjustments
A111: Leverage and funging adjustment
C113: Probability of scenarios in the absence of philanthropic funding
E114: Scenario 1: Domestic governments would replace the grantee's costs | F114: % | G114: input | H114: - | I114: 0 | J114: 0 | K114: 0 | L114: 0 | M114: 0 | N114: 0 | O114: 0 | P114: 0 | Q114: 0 | R114: 0 | S114: 0 | T114: 0 | U114: 0 | V114: 0 | W114: 0 | X114: 0 | Y114: 0 | Z114: 0 | AA114: 0 | AB114: 0 | AD114: GW analysis | AE114: GW's analysis of leverage and funging risk for SMC
E115: Scenario 2: Global Fund and/or PMI would replace the grantee's costs | F115: % | G115: input | H115: - | I115: 0.5 | J115: 0.3 | K115: 0.4 | L115: 0.15 | M115: 0.15 | N115: 0.15 | O115: 0.15 | P115: 0.35 | Q115: 0.2 | R115: 0.1 | S115: 0.1 | T115: 0.2 | U115: 0.1 | V115: 0.2 | W115: 0.2 | X115: 0.2 | Y115: 0.2 | Z115: 0.15 | AA115: 0.65 | AB115: 0.4 | AD115: GW analysis | AE115: GW's analysis of leverage and funging risk for SMC
E116: Scenario 3: Other actors' upstream costs would stay the same (downstream costs would shrink in proportion to the total size of the program) | F116: % | G116: input | H116: - | I116: 0 | J116: 0 | K116: 0 | L116: 0 | M116: 0 | N116: 0 | O116: 0 | P116: 0 | Q116: 0 | R116: 0 | S116: 0 | T116: 0 | U116: 0 | V116: 0 | W116: 0 | X116: 0 | Y116: 0 | Z116: 0 | AA116: 0 | AB116: 0 | AD116: GW analysis | AE116: GW's analysis of leverage and funging risk for SMC
C118: Proportion of the program that would still occur in each scenario
E119: Scenario 1: Domestic governments would replace the grantee's costs | F119: % | G119: input | H119: 1 | I119: - | J119: - | K119: - | L119: - | M119: - | N119: - | O119: - | P119: - | Q119: - | R119: - | S119: - | T119: - | U119: - | V119: - | W119: - | X119: - | Y119: - | Z119: - | AA119: - | AB119: - | AD119: GW analysis
E120: Scenario 2: Global Fund and/or PMI would replace the grantee's costs | F120: % | G120: input | H120: 1 | I120: - | J120: - | K120: - | L120: - | M120: - | N120: - | O120: - | P120: - | Q120: - | R120: - | S120: - | T120: - | U120: - | V120: - | W120: - | X120: - | Y120: - | Z120: - | AA120: - | AB120: - | AD120: GW analysis
E121: Scenario 4: Distributions would go unfunded | F121: % | G121: input | H121: 0 | I121: - | J121: - | K121: - | L121: - | M121: - | N121: - | O121: - | P121: - | Q121: - | R121: - | S121: - | T121: - | U121: - | V121: - | W121: - | X121: - | Y121: - | Z121: - | AA121: - | AB121: - | AD121: GW analysis
C123: Counterfactual value of spending from non-philanthropic actors
E124: Counterfactual value per dollar spent by domestic governments on malaria programs | F124: UoV | G124: input | H124: 0.005057 | I124: - | J124: - | K124: - | L124: - | M124: - | N124: - | O124: - | P124: - | Q124: - | R124: - | S124: - | T124: - | U124: - | V124: - | W124: - | X124: - | Y124: - | Z124: - | AA124: - | AB124: - | AD124: GW analysis | AE124: GW's analysis of the counterfactual value of other actors' spending
...

Sheet GBD estimates
B2: GBD 2021 Results Tool: Population estimates (2021) | L2: GBD 2021 Results Tool: Malaria mortalities (2021) | W2: GBD 2021 Results Tool: Malaria mortality rate among people under age 5 | AH2: GBD 2021 Results Tool: Malaria incidence (2021) | AS2: GBD 2021: Malaria mortalities among people under age 5 (Nigerian states) | BF2: GBD 2021: Malaria mortality rate among people under age 5 (Nigerian states) | BS2: GBD 2021: Malaria incidence rate among people under age 5 (Nigerian states)
B3: Location | C3: Sex | D3: Age group | E3: Year | F3: Measure | G3: Metric | H3: val | I3: upper | J3: lower | L3: measure | M3: location | N3: sex | O3: age | P3: cause | Q3: metric | R3: year | S3: val | T3: upper | U3: lower | W3: measure | X3: location | Y3: sex | Z3: age | AA3: cause | AB3: metric | AC3: year | AD3: val | AE3: upper | AF3: lower | AH3: measure | AI3: location | AJ3: sex | AK3: age | AL3: cause | AM3: metric | AN3: year | AO3: val | AP3: upper | AQ3: lower | AS3: Condition | AT3: Sex | AU3: Age | AV3: Location | AW3: Measure | AX3: Unit | AY3: Forecast Scenario | AZ3: Year | BA3: Value | BB3: Lower | BC3: Upper | BD3: Data Suite | BF3: Condition | BG3: Sex | BH3: Age | BI3: Location | BJ3: Measure | BK3: Unit | BL3: Forecast Scenario | BM3: Year | BN3: Value | BO3: Lower | BP3: Upper | BQ3: Data Suite | BS3: Condition | BT3: Sex | BU3: Age | BV3: Location | BW3: Measure | BX3: Unit | BY3: Forecast Scenario | BZ3: Year | CA3: Value | CB3: Lower | CC3: Upper | CD3: Data Suite
B4: Angola | C4: both | D4: <1 year | E4: 2021 | F4: Population | G4: Number | H4: 1158989 | I4: 1291610 | J4: 1029607 | L4: Deaths | M4: Angola | N4: Both | O4: <5 years | P4: Malaria | Q4: Number | R4: 2021 | S4: 10110.231 | T4: 19641.927 | U4: 4425.1904 | W4: Deaths | X4: Angola | Y4: Both | Z4: <5 years | AA4: Malaria | AB4: Rate | AC4: 2021 | AD4: 179.47586 | AE4: 348.68162 | AF4: 78.555559 | AH4: Incidence | AI4: Angola | AJ4: Both | AK4: <5 years | AL4: Malaria | AM4: Rate | AN4: 2021 | AO4: 60006.247 | AP4: 93328.677 | AQ4: 32968.94 | AS4: Malaria | AT4: Both | AU4: Under 5 | AV4: Abia | AW4: Deaths | AX4: Number | AY4: Past estimate | AZ4: 2021 | BA4: 2593.7447 | BB4: 1165.1769 | BC4: 4203.044 | BD4: GBD | BF4: Malaria | BG4: Both | BH4: Under 5 | BI4: Abia | BJ4: Deaths | BK4: Rate (per 100,000) | BL4: Past estimate | BM4: 2021 | BN4: 374.46585 | BO4: 168.21969 | BP4: 606.80468 | BQ4: GBD | BS4: Malaria | BT4: Both | BU4: Under 5 | BV4: Abia | BW4: Incidence | BX4: Rate (per 100,000) | BY4: Past estimate | BZ4: 2021 | CA4: 88566.28 | CB4: 29136.607 | CC4: 145462.94 | CD4: GBD
B5: Angola | C5: both | D5: <20 years | E5: 2021 | F5: Population | G5: Number | H5: 18675719 | I5: 20812746 | J5: 16590888 | L5: Deaths | M5: Angola | N5: Both | O5: 0-6 days | P5: Malaria | Q5: Number | R5: 2021 | S5: 0 | T5: 0 | U5: 0 | W5: Deaths | X5: Bangladesh | Y5: Both | Z5: <5 years | AA5: Malaria | AB5: Rate | AC5: 2021 | AD5: 0.001006205 | AE5: 0.002170408 | AF5: 0.000189584 | AH5: Incidence | AI5: Angola | AJ5: Both | AK5: 5-14 years | AL5: Malaria | AM5: Rate | AN5: 2021 | AO5: 25729.449 | AP5: 44511.304 | AQ5: 13280.044 | AS5: Malaria | AT5: Both | AU5: 7 to 27 days (late neonatal) | AV5: Abia | AW5: Deaths | AX5: Number | AY5: Past estimate | AZ5: 2021 | BA5: 133.61541 | BB5: 45.761707 | BC5: 254.08422 | BD5: GBD | BF5: Malaria | BG5: Both | BH5: Under 5 | BI5: Adamawa | BJ5: Deaths | BK5: Rate (per 100,000) | BL5: Past estimate | BM5: 2021 | BN5: 389.27364 | BO5: 120.69699 | BP5: 778.13505 | BQ5: GBD | BS5: Malaria | BT5: Both | BU5: 5 to 14 | BV5: Abia | BW5: Incidence | BX5: Rate (per 100,000) | BY5: Past estimate | BZ5: 2021 | CA5: 36712.77 | CB5: 15750.63 | CC5: 73253.81 | CD5: GBD
B6: Angola | C6: both | D6: <28 days | E6: 2021 | F6: Population | G6: Number | H6: 91094 | I6: 101517 | J6: 80924 | L6: Deaths | M6: Angola | N6: Both | O6: 7-27 days | P6: Malaria | Q6: Number | R6: 2021 | S6: 487.13705 | T6: 1044.59 | U6: 156.18637 | W6: Deaths | X6: Benin | Y6: Both | Z6: <5 years | AA6: Malaria | AB6: Rate | AC6: 2021 | AD6: 387.48473 | AE6: 666.49752 | AF6: 195.73088 | AH6: Incidence | AI6: Angola | AJ6: Both | AK6: <1 year | AL6: Malaria | AM6: Rate | AN6: 2021 | AO6: 42363.513 | AP6: 65885.905 | AQ6: 23276.067 | AS6: Malaria | AT6: Both | AU6: 28 to 364 days (post neonatal) | AV6: Abia | AW6: Deaths | AX6: Number | AY6: Past estimate | AZ6: 2021 | BA6: 1034.766 | BB6: 451.80127 | BC6: 1726.3941 | BD6: GBD | BF6: Malaria | BG6: Both | BH6: Under 5 | BI6: Akwa Ibom | BJ6: Deaths | BK6: Rate (per 100,000) | BL6: Past estimate | BM6: 2021 | BN6: 351.11114 | BO6: 150.19717 | BP6: 589.8658 | BQ6: GBD | BS6: Malaria | BT6: Both | BU6: Under 5 | BV6: Adamawa | BW6: Incidence | BX6: Rate (per 100,000) | BY6: Past estimate | BZ6: 2021 | CA6: 67908.436 | CB6: 26816.18 | CC6: 123921.64 | CD6: GBD
B7: Angola | C7: both | D7: <5 years | E7: 2021 | F7: Population | G7: Number | H7: 5633198 | I7: 6277794 | J7: 5004346 | L7: Deaths | M7: Angola | N7: Both | O7: All ages | P7: Malaria | Q7: Number | R7: 2021 | S7: 18396.462 | T7: 38747.948 | U7: 7261.1323 | W7: Deaths | X7: Bhutan | Y7: Both | Z7: <5 years | AA7: Malaria | AB7: Rate | AC7: 2021 | AD7: 0.059899422 | AE7: 0.11976977 | AF7: 0.032095781 | AH7: Incidence | AI7: Bangladesh | AJ7: Both | AK7: <5 years | AL7: Malaria | AM7: Rate | AN7: 2021 | AO7: 10.482573 | AP7: 11.882007 | AQ7: 9.2279558 | AS7: Malaria | AT7: Both | AU7: All Ages | AV7: Abia | AW7: Deaths | AX7: Number | AY7: Past estimate | AZ7: 2021 | BA7: 5451.2006 | BB7: 2172.7527 | BC7: 9547.9412 | BD7: GBD | BF7: Malaria | BG7: Both | BH7: Under 5 | BI7: Anambra | BJ7: Deaths | BK7: Rate (per 100,000) | BL7: Past estimate | BM7: 2021 | BN7: 256.76752 | BO7: 102.0906 | BP7: 447.8644 | BQ7: GBD | BS7: Malaria | BT7: Both | BU7: 5 to 14 | BV7: Adamawa | BW7: Incidence | BX7: Rate (per 100,000) | BY7: Past estimate | BZ7: 2021 | CA7: 29532.757 | CB7: 14830.467 | CC7: 62959.13 | CD7: GBD
B8: Angola | C8: both | D8: 0-14 years | E8: 2021 | F8: Population | G8: Number | H8: 15245471 | I8: 16989980 | J8: 13543569 | L8: Deaths | M8: Angola | N8: Both | O8: <1 year | P8: Malaria | Q8: Number | R8: 2021 | S8: 4423.8699 | T8: 8778.2976 | U8: 2030.1867 | W8: Deaths | X8: Botswana | Y8: Both | Z8: <5 years | AA8: Malaria | AB8: Rate | AC8: 2021 | AD8: 1.2863331 | AE8: 2.7710629 | AF8: 0.60321668 | AH8: Incidence | AI8: Bangladesh | AJ8: Both | AK8: 5-14 years | AL8: Malaria | AM8: Rate | AN8: 2021 | AO8: 20.837518 | AP8: 23.585864 | AQ8: 18.360918 | AS8: Malaria | AT8: Both | AU8: Under 5 | AV8: Adamawa | AW8: Deaths | AX8: Number | AY8: Past estimate | AZ8: 2021 | BA8: 2186.2062 | BB8: 677.84835 | BC8: 4370.0972 | BD8: GBD | BF8: Malaria | BG8: Both | BH8: Under 5 | BI8: Bauchi | BJ8: Deaths | BK8: Rate (per 100,000) | BL8: Past estimate | BM8: 2021 | BN8: 450.21681 | BO8: 141.1198 | BP8: 1018.9843 | BQ8: GBD | BS8: Malaria | BT8: Both | BU8: Under 5 | BV8: Akwa Ibom | BW8: Incidence | BX8: Rate (per 100,000) | BY8: Past estimate | BZ8: 2021 | CA8: 94265.46 | CB8: 32449.567 | CC8: 155934.23 | CD8: GBD
B9: Angola | C9: both | D9: 0-6 days | E9: 2021 | F9: Population | G9: Number | H9: 22970 | I9: 25598 | J9: 20406 | L9: Deaths | M9: Angola | N9: Both | O9: <28 days | P9: Malaria | Q9: Number | R9: 2021 | S9: 487.13705 | T9: 1044.59 | U9: 156.18637 | W9: Deaths | X9: Burkina Faso | Y9: Both | Z9: <5 years | AA9: Malaria | AB9: Rate | AC9: 2021 | AD9: 506.69241 | AE9: 843.71129 | AF9: 239.58111 | AH9: Incidence | AI9: Bangladesh | AJ9: Both | AK9: <1 year | AL9: Malaria | AM9: Rate | AN9: 2021 | AO9: 6.0576901 | AP9: 6.8726657 | AQ9: 5.3296534 | AS9: Malaria | AT9: Both | AU9: 7 to 27 days (late neonatal) | AV9: Adamawa | AW9: Deaths | AX9: Number | AY9: Past estimate | AZ9: 2021 | BA9: 77.469869 | BB9: 18.348604 | BC9: 188.4138 | BD9: GBD | BF9: Malaria | BG9: Both | BH9: Under 5 | BI9: Bayelsa | BJ9: Deaths | BK9: Rate (per 100,000) | BL9: Past estimate | BM9: 2021 | BN9: 243.11061 | BO9: 64.153939 | BP9: 480.41205 | BQ9: GBD | BS9: Malaria | BT9: Both | BU9: 5 to 14 | BV9: Akwa Ibom | BW9: Incidence | BX9: Rate (per 100,000) | BY9: Past estimate | BZ9: 2021 | CA9: 38425.42 | CB9: 16095.942 | CC9: 78601.664 | CD9: GBD
B10: Angola | C10: both | D10: 10-14 years | E10: 2021 | F10: Population | G10: Number | H10: 4380601 | I10: 4881865 | J10: 3891581 | L10: Deaths | M10: Bangladesh | N10: Both | O10: <5 years | P10: Malaria | Q10: Number | R10: 2021 | S10: 0.14453196 | T10: 0.31175876 | U10: 0.027232028 | W10: Deaths | X10: Burundi | Y10: Both | Z10: <5 years | AA10: Malaria | AB10: Rate | AC10: 2021 | AD10: 468.1229 | AE10: 811.05516 | AF10: 215.3454 | AH10: Incidence | AI10: Benin | AJ10: Both | AK10: <5 years | AL10: Malaria | AM10: Rate | AN10: 2021 | AO10: 103355.33 | AP10: 143353.5 | AQ10: 59122.69 | AS10: Malaria | AT10: Both | AU10: 28 to 364 days (post neonatal) | AV10: Adamawa | AW10: Deaths | AX10: Number | AY10: Past estimate | AZ10: 2021 | BA10: 637.45243 | BB10: 180.15466 | BC10: 1412.948 | BD10: GBD | BF10: Malaria | BG10: Both | BH10: Under 5 | BI10: Benue | BJ10: Deaths | BK10: Rate (per 100,000) | BL10: Past estimate | BM10: 2021 | BN10: 253.75267 | BO10: 90.155252 | BP10: 529.98694 | BQ10: GBD | BS10: Malaria | BT10: Both | BU10: Under 5 | BV10: Anambra | BW10: Incidence | BX10: Rate (per 100,000) | BY10: Past estimate | BZ10: 2021 | CA10: 52168.65 | CB10: 16077.502 | CC10: 119193.27 | CD10: GBD
B11: Angola | C11: both | D11: 10-19 years | E11: 2021 | F11: Population | G11: Number | H11: 7810850 | I11: 8704631 | J11: 6938899 | L11: Deaths | M11: Bangladesh | N11: Both | O11: 0-6 days | P11: Malaria | Q11: Number | R11: 2021 | S11: 0 | T11: 0 | U11: 0 | W11: Deaths | X11: Côte d'Ivoire | Y11: Both | Z11: <5 years | AA11: Malaria | AB11: Rate | AC11: 2021 | AD11: 304.01767 | AE11: 515.71516 | AF11: 133.69601 | AH11: Incidence | AI11: Benin | AJ11: Both | AK11: 5-14 years | AL11: Malaria | AM11: Rate | AN11: 2021 | AO11: 42052.85 | AP11: 83958.503 | AQ11: 24410.31 | AS11: Malaria | AT11: Both | AU11: All Ages | AV11: Adamawa | AW11: Deaths | AX11: Number | AY11: Past estimate | AZ11: 2021 | BA11: 3533.5374 | BB11: 999.00514 | BC11: 7224.2863 | BD11: GBD | BF11: Malaria | BG11: Both | BH11: Under 5 | BI11: Borno | BJ11: Deaths | BK11: Rate (per 100,000) | BL11: Past estimate | BM11: 2021 | BN11: 234.08157 | BO11: 54.95883 | BP11: 519.31173 | BQ11: GBD | BS11: Malaria | BT11: Both | BU11: 5 to 14 | BV11: Anambra | BW11: Incidence | BX11: Rate (per 100,000) | BY11: Past estimate | BZ11: 2021 | CA11: 22726.376 | CB11: 9114.0114 | CC11: 47103.268 | CD11: GBD
B12: Angola | C12: both | D12: 10-24 years | E12: 2021 | F12: Population | G12: Number | H12: 10558881 | I12: 11767114 | J12: 9380159 | L12: Deaths | M12: Bangladesh | N12: Both | O12: 7-27 days | P12: Malaria | Q12: Number | R12: 2021 | S12: 0.003476564 | T12: 0.006295218 | U12: 0.000705775 | W12: Deaths | X12: Cabo Verde | Y12: Both | Z12: <5 years | AA12: Malaria | AB12: Rate | AC12: 2021 | AD12: 0.079934864 | AE12: 0.38001815 | AF12: 0.003576038 | AH12: Incidence | AI12: Benin | AJ12: Both | AK12: <1 year | AL12: Malaria | AM12: Rate | AN12: 2021 | AO12: 73208.318 | AP12: 101542.59 | AQ12: 41878.79 | AS12: Malaria | AT12: Both | AU12: Under 5 | AV12: Akwa Ibom | AW12: Deaths | AX12: Number | AY12: Past estimate | AZ12: 2021 | BA12: 1052.5279 | BB12: 450.24695 | BC12: 1768.2441 | BD12: GBD | BF12: Malaria | BG12: Both | BH12: Under 5 | BI12: Cross River | BJ12: Deaths | BK12: Rate (per 100,000) | BL12: Past estimate | BM12: 2021 | BN12: 278.46423 | BO12: 114.91863 | BP12: 494.02924 | BQ12: GBD | BS12: Malaria | BT12: Both | BU12: Under 5 | BV12: Bauchi | BW12: Incidence | BX12: Rate (per 100,000) | BY12: Past estimate | BZ12: 2021 | CA12: 92549.9 | CB12: 47740.695 | CC12: 143085.46 | CD12: GBD
B13: Angola | C13: both | D13: 12-23 months | E13: 2021 | F13: Population | G13: Number | H13: 1137175 | I13: 1267300 | J13: 1010228 | L13: Deaths | M13: Bangladesh | N13: Both | O13: All ages | P13: Malaria | Q13: Number | R13: 2021 | S13: 603.33174 | T13: 1210.7822 | U13: 146.96593 | W13: Deaths | X13: Cameroon | Y13: Both | Z13: <5 years | AA13: Malaria | AB13: Rate | AC13: 2021 | AD13: 277.72238 | AE13: 515.62298 | AF13: 107.75909 | AH13: Incidence | AI13: Bhutan | AJ13: Both | AK13: <5 years | AL13: Malaria | AM13: Rate | AN13: 2021 | AO13: 2.4977218 | AP13: 2.8911396 | AQ13: 2.1795604 | AS13: Malaria | AT13: Both | AU13: 7 to 27 days (late neonatal) | AV13: Akwa Ibom | AW13: Deaths | AX13: Number | AY13: Past estimate | AZ13: 2021 | BA13: 69.627705 | BB13: 21.784973 | BC13: 138.31288 | BD13: GBD | BF13: Malaria | BG13: Both | BH13: Under 5 | BI13: Delta | BJ13: Deaths | BK13: Rate (per 100,000) | BL13: Past estimate | BM13: 2021 | BN13: 312.00412 | BO13: 90.150937 | BP13: 605.56283 | BQ13: GBD | BS13: Malaria | BT13: Both | BU13: 5 to 14 | BV13: Bauchi | BW13: Incidence | BX13: Rate (per 100,000) | BY13: Past estimate | BZ13: 2021 | CA13: 39110.878 | CB13: 23023.334 | CC13: 78855.38 | CD13: GBD
B14: Angola | C14: both | D14: 1-5 months | E14: 2021 | F14: Population | G14: Number | H14: 496653 | I14: 553484 | J14: 441210 | L14: Deaths | M14: Bangladesh | N14: Both | O14: <1 year | P14: Malaria | Q14: Number | R14: 2021 | S14: 0.083706608 | T14: 0.18566253 | U14: 0.014568372 | W14: Deaths | X14: Central African Republic | Y14: Both | Z14: <5 years | AA14: Malaria | AB14: Rate | AC14: 2021 | AD14: 325.46154 | AE14: 724.79338 | AF14: 129.63886 | AH14: Incidence | AI14: Bhutan | AJ14: Both | AK14: 5-14 years | AL14: Malaria | AM14: Rate | AN14: 2021 | AO14: 4.9885478 | AP14: 5.7728152 | AQ14: 4.3546221 | AS14: Malaria | AT14: Both | AU14: 28 to 364 days (post neonatal) | AV14: Akwa Ibom | AW14: Deaths | AX14: Number | AY14: Past estimate | AZ14: 2021 | BA14: 389.33304 | BB14: 151.4585 | BC14: 665.34862 | BD14: GBD | BF14: Malaria | BG14: Both | BH14: Under 5 | BI14: Ebonyi | BJ14: Deaths | BK14: Rate (per 100,000) | BL14: Past estimate | BM14: 2021 | BN14: 334.76612 | BO14: 122.839 | BP14: 671.77168 | BQ14: GBD | BS14: Malaria | BT14: Both | BU14: Under 5 | BV14: Bayelsa | BW14: Incidence | BX14: Rate (per 100,000) | BY14: Past estimate | BZ14: 2021 | CA14: 71829.134 | CB14: 17317.624 | CC14: 144481.64 | CD14: GBD
B15: Angola | C15: both | D15: 15-19 years | E15: 2021 | F15: Population | G15: Number | H15: 3430249 | I15: 3822765 | J15: 3047319 | L15: Deaths | M15: Bangladesh | N15: Both | O15: <28 days | P15: Malaria | Q15: Number | R15: 2021 | S15: 0.003476564 | T15: 0.006295218 | U15: 0.000705775 | W15: Deaths | X15: Chad | Y15: Both | Z15: <5 years | AA15: Malaria | AB15: Rate | AC15: 2021 | AD15: 152.13561 | AE15: 325.43775 | AF15: 46.117725 | AH15: Incidence | AI15: Bhutan | AJ15: Both | AK15: <1 year | AL15: Malaria | AM15: Rate | AN15: 2021 | AO15: 1.4512935 | AP15: 1.6801903 | AQ15: 1.2661425 | AS15: Malaria | AT15: Both | AU15: All Ages | AV15: Akwa Ibom | AW15: Deaths | AX15: Number | AY15: Past estimate | AZ15: 2021 | BA15: 2671.7285 | BB15: 980.04552 | BC15: 4933.8621 | BD15: GBD | BF15: Malaria | BG15: Both | BH15: Under 5 | BI15: Edo | BJ15: Deaths | BK15: Rate (per 100,000) | BL15: Past estimate | BM15: 2021 | BN15: 314.09544 | BO15: 99.684758 | BP15: 612.82032 | BQ15: GBD | BS15: Malaria | BT15: Both | BU15: 5 to 14 | BV15: Bayelsa | BW15: Incidence | BX15: Rate (per 100,000) | BY15: Past estimate | BZ15: 2021 | CA15: 30618.73 | CB15: 8337.102 | CC15: 66854.954 | CD15: GBD
... B40: Angola | C40: both | D40: 90-94 years | E40: 2021 | F40: Population | G40: Number | H40: 5347 | I40: 5959 | J40: 4750 | L40: Deaths | M40: Burundi | N40: Both | O40: <5 years | P40: Malaria | Q40: Number | R40: 2021 | S40: 10113.265 | T40: 17521.928 | U40: 4652.2935 | W40: Deaths | X40: Niger | Y40: Both | Z40: <5 years | AA40: Malaria | AB40: Rate | AC40: 2021 | AD40: 440.61425 | AE40: 765.13653 | AF40: 164.93558 | AH40: Incidence | AI40: Comoros | AJ40: Both | AK40: <5 years | AL40: Malaria | AM40: Rate | AN40: 2021 | AO40: 888.60395 | AP40: 1152.9525 | AQ40: 679.56027 | AS40: Malaria | AT40: Both | AU40: Under 5 | AV40: Delta | AW40: Deaths | AX40: Number | AY40: Past estimate | AZ40: 2021 | BA40: 1869.0145 | BB40: 540.03586 | BC40: 3627.5346 | BD40: GBD | BF40: Malaria | BG40: Both | BH40: Under 5 | BI40: Zamfara | BJ40: Deaths | BK40: Rate (per 100,000) | BL40: Past estimate | BM40: 2021 | BN40: 362.60904 | BO40: 90.565082 | BP40: 864.42252 | BQ40: GBD | BS40: Malaria | BT40: Both | BU40: Under 5 | BV40: Kaduna | BW40: Incidence | BX40: Rate (per 100,000) | BY40: Past estimate | BZ40: 2021 | CA40: 98888.13 | CB40: 46155.638 | CC40: 148274.56 | CD40: GBD
B41: Angola | C41: both | D41: 95+ years | E41: 2021 | F41: Population | G41: Number | H41: 1095 | I41: 1220 | J41: 973 | L41: Deaths | M41: Burundi | N41: Both | O41: 0-6 days | P41: Malaria | Q41: Number | R41: 2021 | S41: 0 | T41: 0 | U41: 0 | W41: Deaths | X41: Nigeria | Y41: Both | Z41: <5 years | AA41: Malaria | AB41: Rate | AC41: 2021 | AD41: 338.64025 | AE41: 656.71914 | AF41: 118.40981 | AH41: Incidence | AI41: Comoros | AJ41: Both | AK41: 5-14 years | AL41: Malaria | AM41: Rate | AN41: 2021 | AO41: 1151.4163 | AP41: 1416.2865 | AQ41: 931.57764 | AS41: Malaria | AT41: Both | AU41: 7 to 27 days (late neonatal) | AV41: Delta | AW41: Deaths | AX41: Number | AY41: Past estimate | AZ41: 2021 | BA41: 104.64796 | BB41: 20.310917 | BC41: 279.74138 | BD41: GBD | BS41: Malaria | BT41: Both | BU41: 5 to 14 | BV41: Kaduna | BW41: Incidence | BX41: Rate (per 100,000) | BY41: Past estimate | BZ41: 2021 | CA41: 40574.977 | CB41: 19975.06 | CC41: 78311.71 | CD41: GBD
B42: Angola | C42: both | D42: All ages | E42: 2021 | F42: Population | G42: Number | H42: 32706452 | I42: 36448988 | J42: 29055324 | L42: Deaths | M42: Burundi | N42: Both | O42: 7-27 days | P42: Malaria | Q42: Number | R42: 2021 | S42: 752.70826 | T42: 1584.1831 | U42: 269.78897 | W42: Deaths | X42: Pakistan | Y42: Both | Z42: <5 years | AA42: Malaria | AB42: Rate | AC42: 2021 | AD42: 5.461937 | AE42: 17.206501 | AF42: 0.27129181 | AH42: Incidence | AI42: Comoros | AJ42: Both | AK42: <1 year | AL42: Malaria | AM42: Rate | AN42: 2021 | AO42: 611.89667 | AP42: 795.55083 | AQ42: 466.90587 | AS42: Malaria | AT42: Both | AU42: 28 to 364 days (post neonatal) | AV42: Delta | AW42: Deaths | AX42: Number | AY42: Past estimate | AZ42: 2021 | BA42: 688.33224 | BB42: 167.19279 | BC42: 1449.4198 | BD42: GBD | BS42: Malaria | BT42: Both | BU42: Under 5 | BV42: Kano | BW42: Incidence | BX42: Rate (per 100,000) | BY42: Past estimate | BZ42: 2021 | CA42: 94880.84 | CB42: 36542.162 | CC42: 166354.88 | CD42: GBD
B43: Bangladesh | C43: both | D43: <1 year | E43: 2021 | F43: Population | G43: Number | H43: 2769278 | I43: 3124589 | J43: 2404338 | L43: Deaths | M43: Burundi | N43: Both | O43: All ages | P43: Malaria | Q43: Number | R43: 2021 | S43: 13547.099 | T43: 26039.349 | U43: 5803.4297 | W43: Deaths | X43: Rwanda | Y43: Both | Z43: <5 years | AA43: Malaria | AB43: Rate | AC43: 2021 | AD43: 101.24475 | AE43: 163.4384 | AF43: 58.492526 | AH43: Incidence | AI43: Congo | AJ43: Both | AK43: <5 years | AL43: Malaria | AM43: Rate | AN43: 2021 | AO43: 63029.1 | AP43: 108337.06 | AQ43: 31219.976 | AS43: Malaria | AT43: Both | AU43: All Ages | AV43: Delta | AW43: Deaths | AX43: Number | AY43: Past estimate | AZ43: 2021 | BA43: 3714.1484 | BB43: 962.56462 | BC43: 7999.3693 | BD43: GBD | BS43: Malaria | BT43: Both | BU43: 5 to 14 | BV43: Kano | BW43: Incidence | BX43: Rate (per 100,000) | BY43: Past estimate | BZ43: 2021 | CA43: 40314.21 | CB43: 16800.79 | CC43: 84448.224 | CD43: GBD
B44: Bangladesh | C44: both | D44: <20 years | E44: 2021 | F44: Population | G44: Number | H44: 60989067 | I44: 68814257 | J44: 52951833 | L44: Deaths | M44: Burundi | N44: Both | O44: <1 year | P44: Malaria | Q44: Number | R44: 2021 | S44: 5215.7435 | T44: 9250.5251 | U44: 2223.1968 | W44: Deaths | X44: Sao Tome and Principe | Y44: Both | Z44: <5 years | AA44: Malaria | AB44: Rate | AC44: 2021 | AD44: 19.687032 | AE44: 32.312568 | AF44: 6.999413 | AH44: Incidence | AI44: Congo | AJ44: Both | AK44: 5-14 years | AL44: Malaria | AM44: Rate | AN44: 2021 | AO44: 26419.339 | AP44: 50002.193 | AQ44: 13584.171 | AS44: Malaria | AT44: Both | AU44: Under 5 | AV44: Ebonyi | AW44: Deaths | AX44: Number | AY44: Past estimate | AZ44: 2021 | BA44: 1739.3407 | BB44: 638.23327 | BC44: 3490.3169 | BD44: GBD | BS44: Malaria | BT44: Both | BU44: Under 5 | BV44: Katsina | BW44: Incidence | BX44: Rate (per 100,000) | BY44: Past estimate | BZ44: 2021 | CA44: 78589.98 | CB44: 28015.086 | CC44: 143559.5 | CD44: GBD
B45: Bangladesh | C45: both | D45: <28 days | E45: 2021 | F45: Population | G45: Number | H45: 211307 | I45: 238419 | J45: 183461 | L45: Deaths | M45: Burundi | N45: Both | O45: <28 days | P45: Malaria | Q45: Number | R45: 2021 | S45: 752.70826 | T45: 1584.1831 | U45: 269.78897 | W45: Deaths | X45: Senegal | Y45: Both | Z45: <5 years | AA45: Malaria | AB45: Rate | AC45: 2021 | AD45: 72.955935 | AE45: 110.56836 | AF45: 27.443672 | AH45: Incidence | AI45: Congo | AJ45: Both | AK45: <1 year | AL45: Malaria | AM45: Rate | AN45: 2021 | AO45: 44405.484 | AP45: 76331.113 | AQ45: 21996.679 | AS45: Malaria | AT45: Both | AU45: 7 to 27 days (late neonatal) | AV45: Ebonyi | AW45: Deaths | AX45: Number | AY45: Past estimate | AZ45: 2021 | BA45: 94.699804 | BB45: 24.806013 | BC45: 259.18828 | BD45: GBD | BS45: Malaria | BT45: Both | BU45: 5 to 14 | BV45: Katsina | BW45: Incidence | BX45: Rate (per 100,000) | BY45: Past estimate | BZ45: 2021 | CA45: 34047.428 | CB45: 13441.722 | CC45: 74786.98 | CD45: GBD
B46: Bangladesh | C46: both | D46: <5 years | E46: 2021 | F46: Population | G46: Number | H46: 14364063 | I46: 16207041 | J46: 12471144 | L46: Deaths | M46: Côte d'Ivoire | N46: Both | O46: <5 years | P46: Malaria | Q46: Number | R46: 2021 | S46: 13238.119 | T46: 22456.256 | U46: 5821.6474 | W46: Deaths | X46: Sierra Leone | Y46: Both | Z46: <5 years | AA46: Malaria | AB46: Rate | AC46: 2021 | AD46: 472.18941 | AE46: 894.03463 | AF46: 165.73546 | AH46: Incidence | AI46: Democratic Republic of the Congo | AJ46: Both | AK46: <5 years | AL46: Malaria | AM46: Rate | AN46: 2021 | AO46: 83305.679 | AP46: 120816.79 | AQ46: 52568.779 | AS46: Malaria | AT46: Both | AU46: 28 to 364 days (post neonatal) | AV46: Ebonyi | AW46: Deaths | AX46: Number | AY46: Past estimate | AZ46: 2021 | BA46: 689.49137 | BB46: 246.45745 | BC46: 1525.4555 | BD46: GBD | BS46: Malaria | BT46: Both | BU46: Under 5 | BV46: Kebbi | BW46: Incidence | BX46: Rate (per 100,000) | BY46: Past estimate | BZ46: 2021 | CA46: 98746.64 | CB46: 35277.06 | CC46: 158329.99 | CD46: GBD
B47: Bangladesh | C47: both | D47: 0-14 years | E47: 2021 | F47: Population | G47: Number | H47: 45765985 | I47: 51637980 | J47: 39734872 | L47: Deaths | M47: Côte d'Ivoire | N47: Both | O47: 0-6 days | P47: Malaria | Q47: Number | R47: 2021 | S47: 0 | T47: 0 | U47: 0 | W47: Deaths | X47: Somalia | Y47: Both | Z47: <5 years | AA47: Malaria | AB47: Rate | AC47: 2021 | AD47: 29.210553 | AE47: 69.168411 | AF47: 10.0261 | AH47: Incidence | AI47: Democratic Republic of the Congo | AJ47: Both | AK47: 5-14 years | AL47: Malaria | AM47: Rate | AN47: 2021 | AO47: 34167.688 | AP47: 64393.895 | AQ47: 18899.966 | AS47: Malaria | AT47: Both | AU47: All Ages | AV47: Ebonyi | AW47: Deaths | AX47: Number | AY47: Past estimate | AZ47: 2021 | BA47: 3496.1378 | BB47: 1234.2588 | BC47: 7888.067 | BD47: GBD | BS47: Malaria | BT47: Both | BU47: 5 to 14 | BV47: Kebbi | BW47: Incidence | BX47: Rate (per 100,000) | BY47: Past estimate | BZ47: 2021 | CA47: 40692.243 | CB47: 18281.454 | CC47: 78292.453 | CD47: GBD
B48: Bangladesh | C48: both | D48: 0-6 days | E48: 2021 | F48: Population | G48: Number | H48: 53178 | I48: 60001 | J48: 46170 | L48: Deaths | M48: Côte d'Ivoire | N48: Both | O48: 7-27 days | P48: Malaria | Q48: Number | R48: 2021 | S48: 645.20212 | T48: 1303.6871 | U48: 216.08652 | W48: Deaths | X48: South Africa | Y48: Both | Z48: <5 years | AA48: Malaria | AB48: Rate | AC48: 2021 | AD48: 0.12287172 | AE48: 0.55324495 | AF48: 0.026255054 | AH48: Incidence | AI48: Democratic Republic of the Congo | AJ48: Both | AK48: <1 year | AL48: Malaria | AM48: Rate | AN48: 2021 | AO48: 58790.158 | AP48: 85265.855 | AQ48: 37100.156 | AS48: Malaria | AT48: Both | AU48: Under 5 | AV48: Edo | AW48: Deaths | AX48: Number | AY48: Past estimate | AZ48: 2021 | BA48: 1590.3616 | BB48: 504.7345 | BC48: 3102.8972 | BD48: GBD | BS48: Malaria | BT48: Both | BU48: Under 5 | BV48: Kogi | BW48: Incidence | BX48: Rate (per 100,000) | BY48: Past estimate | BZ48: 2021 | CA48: 90253.5 | CB48: 37416.062 | CC48: 156479.5 | CD48: GBD
B49: Bangladesh | C49: both | D49: 10-14 years | E49: 2021 | F49: Population | G49: Number | H49: 15880776 | I49: 17918355 | J49: 13787982 | L49: Deaths | M49: Côte d'Ivoire | N49: Both | O49: All ages | P49: Malaria | Q49: Number | R49: 2021 | S49: 27762.932 | T49: 52331.201 | U49: 11228.682 | W49: Deaths | X49: South Sudan | Y49: Both | Z49: <5 years | AA49: Malaria | AB49: Rate | AC49: 2021 | AD49: 351.39331 | AE49: 671.89044 | AF49: 151.61289 | AH49: Incidence | AI49: Djibouti | AJ49: Both | AK49: <5 years | AL49: Malaria | AM49: Rate | AN49: 2021 | AO49: 10292.603 | AP49: 11809.744 | AQ49: 8972.5509 | AS49: Malaria | AT49: Both | AU49: 7 to 27 days (late neonatal) | AV49: Edo | AW49: Deaths | AX49: Number | AY49: Past estimate | AZ49: 2021 | BA49: 87.969716 | BB49: 19.70013 | BC49: 212.44456 | BD49: GBD | BS49: Malaria | BT49: Both | BU49: 5 to 14 | BV49: Kogi | BW49: Incidence | BX49: Rate (per 100,000) | BY49: Past estimate | BZ49: 2021 | CA49: 36989.745 | CB49: 16910.844 | CC49: 76788.17 | CD49: GBD
B50: Bangladesh | C50: both | D50: 10-19 years | E50: 2021 | F50: Population | G50: Number | H50: 31103858 | I50: 35094632 | J50: 27004943 | L50: Deaths | M50: Côte d'Ivoire | N50: Both | O50: <1 year | P50: Malaria | Q50: Number | R50: 2021 | S50: 5638.9001 | T50: 10018.384 | U50: 2340.9554 | W50: Deaths | X50: Togo | Y50: Both | Z50: <5 years | AA50: Malaria | AB50: Rate | AC50: 2021 | AD50: 194.29966 | AE50: 338.44478 | AF50: 63.690164 | AH50: Incidence | AI50: Djibouti | AJ50: Both | AK50: 5-14 years | AL50: Malaria | AM50: Rate | AN50: 2021 | AO50: 8688.326 | AP50: 9661.1247 | AQ50: 7844.5005 | AS50: Malaria | AT50: Both | AU50: 28 to 364 days (post neonatal) | AV50: Edo | AW50: Deaths | AX50: Number | AY50: Past estimate | AZ50: 2021 | BA50: 518.55835 | BB50: 147.06159 | BC50: 1018.1519 | BD50: GBD | BS50: Malaria | BT50: Both | BU50: Under 5 | BV50: Kwara | BW50: Incidence | BX50: Rate (per 100,000) | BY50: Past estimate | BZ50: 2021 | CA50: 91406.107 | CB50: 39503.232 | CC50: 154655.2 | CD50: GBD
B51: Bangladesh | C51: both | D51: 10-24 years | E51: 2021 | F51: Population | G51: Number | H51: 45795079 | I51: 51670807 | J51: 39760132 | L51: Deaths | M51: Côte d'Ivoire | N51: Both | O51: <28 days | P51: Malaria | Q51: Number | R51: 2021 | S51: 645.20212 | T51: 1303.6871 | U51: 216.08652 | W51: Deaths | X51: Uganda | Y51: Both | Z51: <5 years | AA51: Malaria | AB51: Rate | AC51: 2021 | AD51: 454.74017 | AE51: 771.72271 | AF51: 157.46062 | AH51: Incidence | AI51: Djibouti | AJ51: Both | AK51: <1 year | AL51: Malaria | AM51: Rate | AN51: 2021 | AO51: 7200.3781 | AP51: 8271.0887 | AQ51: 6270.1738 | AS51: Malaria | AT51: Both | AU51: All Ages | AV51: Edo | AW51: Deaths | AX51: Number | AY51: Past estimate | AZ51: 2021 | BA51: 3539.2549 | BB51: 989.70043 | BC51: 7362.3641 | BD51: GBD | BS51: Malaria | BT51: Both | BU51: 5 to 14 | BV51: Kwara | BW51: Incidence | BX51: Rate (per 100,000) | BY51: Past estimate | BZ51: 2021 | CA51: 37886.384 | CB51: 18801.087 | CC51: 86080.26 | CD51: GBD
B52: Bangladesh | C52: both | D52: 12-23 months | E52: 2021 | F52: Population | G52: Number | H52: 2820063 | I52: 3181891 | J52: 2448431 | L52: Deaths | M52: Cabo Verde | N52: Both | O52: <5 years | P52: Malaria | Q52: Number | R52: 2021 | S52: 0.035218716 | T52: 0.16743321 | U52: 0.001575576 | W52: Deaths | X52: United Republic of Tanzania | Y52: Both | Z52: <5 years | AA52: Malaria | AB52: Rate | AC52: 2021 | AD52: 129.42077 | AE52: 257.6676 | AF52: 42.140558 | AH52: Incidence | AI52: Equatorial Guinea | AJ52: Both | AK52: <5 years | AL52: Malaria | AM52: Rate | AN52: 2021 | AO52: 64636.334 | AP52: 114403.02 | AQ52: 16330.978 | AS52: Malaria | AT52: Both | AU52: Under 5 | AV52: Ekiti | AW52: Deaths | AX52: Number | AY52: Past estimate | AZ52: 2021 | BA52: 848.82425 | BB52: 425.14916 | BC52: 1409.4598 | BD52: GBD | BS52: Malaria | BT52: Both | BU52: Under 5 | BV52: Lagos | BW52: Incidence | BX52: Rate (per 100,000) | BY52: Past estimate | BZ52: 2021 | CA52: 45418.07 | CB52: 13202.894 | CC52: 111729.62 | CD52: GBD
... B54: Bangladesh | C54: both | D54: 15-19 years | E54: 2021 | F54: Population | G54: Number | H54: 15223082 | I54: 17176277 | J54: 13216961 | L54: Deaths | M54: Cabo Verde | N54: Both | O54: 7-27 days | P54: Malaria | Q54: Number | R54: 2021 | S54: 0.00129358 | T54: 0.006135171 | U54: 6.6e-05 | W54: Deaths | X54: Zimbabwe | Y54: Both | Z54: <5 years | AA54: Malaria | AB54: Rate | AC54: 2021 | AD54: 46.192341 | AE54: 92.686886 | AF54: 20.122691 | AH54: Incidence | AI54: Equatorial Guinea | AJ54: Both | AK54: <1 year | AL54: Malaria | AM54: Rate | AN54: 2021 | AO54: 45445.916 | AP54: 80437.607 | AQ54: 11334.842 | AS54: Malaria | AT54: Both | AU54: 28 to 364 days (post neonatal) | AV54: Ekiti | AW54: Deaths | AX54: Number | AY54: Past estimate | AZ54: 2021 | BA54: 317.89805 | BB54: 157.04184 | BC54: 536.18412 | BD54: GBD | BS54: Malaria | BT54: Both | BU54: Under 5 | BV54: Nasarawa | BW54: Incidence | BX54: Rate (per 100,000) | BY54: Past estimate | BZ54: 2021 | CA54: 72018.194 | CB54: 26455.316 | CC54: 135790.56 | CD54: GBD
B55: Bangladesh | C55: both | D55: 15-49 years | E55: 2021 | F55: Population | G55: Number | H55: 87962646 | I55: 99248676 | J55: 76370792 | L55: Deaths | M55: Cabo Verde | N55: Both | O55: All ages | P55: Malaria | Q55: Number | R55: 2021 | S55: 0.046077629 | T55: 0.21653453 | U55: 0.002223319 | AH55: Incidence | AI55: Eritrea | AJ55: Both | AK55: <5 years | AL55: Malaria | AM55: Rate | AN55: 2021 | AO55: 269.36692 | AP55: 290.43386 | AQ55: 250.15279 | AS55: Malaria | AT55: Both | AU55: All Ages | AV55: Ekiti | AW55: Deaths | AX55: Number | AY55: Past estimate | AZ55: 2021 | BA55: 2040.2552 | BB55: 912.15544 | BC55: 3646.0083 | BD55: GBD | BS55: Malaria | BT55: Both | BU55: 5 to 14 | BV55: Nasarawa | BW55: Incidence | BX55: Rate (per 100,000) | BY55: Past estimate | BZ55: 2021 | CA55: 30377.278 | CB55: 13783.501 | CC55: 51881.25 | CD55: GBD
B56: Bangladesh | C56: both | D56: 20-24 years | E56: 2021 | F56: Population | G56: Number | H56: 14691221 | I56: 16576175 | J56: 12755189 | L56: Deaths | M56: Cabo Verde | N56: Both | O56: <1 year | P56: Malaria | Q56: Number | R56: 2021 | S56: 0.021702421 | T56: 0.10795701 | U56: 0.000927823 | AH56: Incidence | AI56: Eritrea | AJ56: Both | AK56: 5-14 years | AL56: Malaria | AM56: Rate | AN56: 2021 | AO56: 449.9864 | AP56: 479.62189 | AQ56: 422.41622 | AS56: Malaria | AT56: Both | AU56: Under 5 | AV56: Enugu | AW56: Deaths | AX56: Number | AY56: Past estimate | AZ56: 2021 | BA56: 1391.5795 | BB56: 570.92214 | BC56: 2564.5546 | BD56: GBD | BS56: Malaria | BT56: Both | BU56: Under 5 | BV56: Niger | BW56: Incidence | BX56: Rate (per 100,000) | BY56: Past estimate | BZ56: 2021 | CA56: 90486.72 | CB56: 41157.883 | CC56: 152768.29 | CD56: GBD
B57: Bangladesh | C57: both | D57: 2-4 years | E57: 2021 | F57: Population | G57: Number | H57: 8774722 | I57: 9900561 | J57: 7618375 | L57: Deaths | M57: Cabo Verde | N57: Both | O57: <28 days | P57: Malaria | Q57: Number | R57: 2021 | S57: 0.00129358 | T57: 0.006135171 | U57: 6.6e-05 | AH57: Incidence | AI57: Eritrea | AJ57: Both | AK57: <1 year | AL57: Malaria | AM57: Rate | AN57: 2021 | AO57: 171.6766 | AP57: 186.10461 | AQ57: 158.44351 | AS57: Malaria | AT57: Both | AU57: 7 to 27 days (late neonatal) | AV57: Enugu | AW57: Deaths | AX57: Number | AY57: Past estimate | AZ57: 2021 | BA57: 103.43504 | BB57: 32.485422 | BC57: 263.55372 | BD57: GBD | BS57: Malaria | BT57: Both | BU57: 5 to 14 | BV57: Niger | BW57: Incidence | BX57: Rate (per 100,000) | BY57: Past estimate | BZ57: 2021 | CA57: 37631.333 | CB57: 18929.213 | CC57: 72336.47 | CD57: GBD
B58: Bangladesh | C58: both | D58: 25+ years | E58: 2021 | F58: Population | G58: Number | H58: 88955828 | I58: 100369288 | J58: 77233091 | L58: Deaths | M58: Cameroon | N58: Both | O58: <5 years | P58: Malaria | Q58: Number | R58: 2021 | S58: 13507.62 | T58: 25078.423 | U58: 5241.093 | AH58: Incidence | AI58: Eswatini | AJ58: Both | AK58: <5 years | AL58: Malaria | AM58: Rate | AN58: 2021 | AO58: 38.846254 | AP58: 48.736611 | AQ58: 30.210094 | AS58: Malaria | AT58: Both | AU58: 28 to 364 days (post neonatal) | AV58: Enugu | AW58: Deaths | AX58: Number | AY58: Past estimate | AZ58: 2021 | BA58: 556.87336 | BB58: 208.81741 | BC58: 1029.754 | BD58: GBD | BS58: Malaria | BT58: Both | BU58: Under 5 | BV58: Ogun | BW58: Incidence | BX58: Rate (per 100,000) | BY58: Past estimate | BZ58: 2021 | CA58: 83240.736 | CB58: 34830.073 | CC58: 141478.9 | CD58: GBD
B59: Bangladesh | C59: both | D59: 25-29 years | E59: 2021 | F59: Population | G59: Number | H59: 14108716 | I59: 15918932 | J59: 12249447 | L59: Deaths | M59: Cameroon | N59: Both | O59: 0-6 days | P59: Malaria | Q59: Number | R59: 2021 | S59: 0 | T59: 0 | U59: 0 | AH59: Incidence | AI59: Eswatini | AJ59: Both | AK59: 5-14 years | AL59: Malaria | AM59: Rate | AN59: 2021 | AO59: 74.216357 | AP59: 92.207366 | AQ59: 58.293886 | AS59: Malaria | AT59: Both | AU59: All Ages | AV59: Enugu | AW59: Deaths | AX59: Number | AY59: Past estimate | AZ59: 2021 | BA59: 3812.9564 | BB59: 1366.4503 | BC59: 8368.9011 | BD59: GBD | BS59: Malaria | BT59: Both | BU59: 5 to 14 | BV59: Ogun | BW59: Incidence | BX59: Rate (per 100,000) | BY59: Past estimate | BZ59: 2021 | CA59: 34523.973 | CB59: 18356.518 | CC59: 62573.39 | CD59: GBD
B60: Bangladesh | C60: both | D60: 30-34 years | E60: 2021 | F60: Population | G60: Number | H60: 13187642 | I60: 14879680 | J60: 11449754 | L60: Deaths | M60: Cameroon | N60: Both | O60: 7-27 days | P60: Malaria | Q60: Number | R60: 2021 | S60: 595.34613 | T60: 1215.2277 | U60: 171.64994 | AH60: Incidence | AI60: Eswatini | AJ60: Both | AK60: <1 year | AL60: Malaria | AM60: Rate | AN60: 2021 | AO60: 23.060991 | AP60: 29.101726 | AQ60: 17.826156 | AS60: Malaria | AT60: Both | AU60: Under 5 | AV60: FCT (Abuja) | AW60: Deaths | AX60: Number | AY60: Past estimate | AZ60: 2021 | BA60: 2525.9546 | BB60: 851.87568 | BC60: 4588.0293 | BD60: GBD | BS60: Malaria | BT60: Both | BU60: Under 5 | BV60: Ondo | BW60: Incidence | BX60: Rate (per 100,000) | BY60: Past estimate | BZ60: 2021 | CA60: 92528.385 | CB60: 36280.528 | CC60: 160501.78 | CD60: GBD
B61: Bangladesh | C61: both | D61: 35-39 years | E61: 2021 | F61: Population | G61: Number | H61: 11603427 | I61: 13092202 | J61: 10074309 | L61: Deaths | M61: Cameroon | N61: Both | O61: All ages | P61: Malaria | Q61: Number | R61: 2021 | S61: 28945.613 | T61: 58505.865 | U61: 11324.327 | AH61: Incidence | AI61: Ethiopia | AJ61: Both | AK61: <5 years | AL61: Malaria | AM61: Rate | AN61: 2021 | AO61: 1936.5057 | AP61: 2470.6758 | AQ61: 1443.0547 | AS61: Malaria | AT61: Both | AU61: 7 to 27 days (late neonatal) | AV61: FCT (Abuja) | AW61: Deaths | AX61: Number | AY61: Past estimate | AZ61: 2021 | BA61: 143.57731 | BB61: 32.363758 | BC61: 354.11337 | BD61: GBD | BS61: Malaria | BT61: Both | BU61: 5 to 14 | BV61: Ondo | BW61: Incidence | BX61: Rate (per 100,000) | BY61: Past estimate | BZ61: 2021 | CA61: 37997.198 | CB61: 16739.279 | CC61: 73710.257 | CD61: GBD
B62: Bangladesh | C62: both | D62: 40-44 years | E62: 2021 | F62: Population | G62: Number | H62: 10202770 | I62: 11511834 | J62: 8858233 | L62: Deaths | M62: Cameroon | N62: Both | O62: <1 year | P62: Malaria | Q62: Number | R62: 2021 | S62: 5166.7965 | T62: 10242.923 | U62: 1859.787 | AH62: Incidence | AI62: Ethiopia | AJ62: Both | AK62: 5-14 years | AL62: Malaria | AM62: Rate | AN62: 2021 | AO62: 2149.4006 | AP62: 2592.1466 | AQ62: 1774.282 | AS62: Malaria | AT62: Both | AU62: 28 to 364 days (post neonatal) | AV62: FCT (Abuja) | AW62: Deaths | AX62: Number | AY62: Past estimate | AZ62: 2021 | BA62: 967.34921 | BB62: 294.91016 | BC62: 1873.7836 | BD62: GBD | BS62: Malaria | BT62: Both | BU62: Under 5 | BV62: Osun | BW62: Incidence | BX62: Rate (per 100,000) | BY62: Past estimate | BZ62: 2021 | CA62: 101932.72 | CB62: 48638.964 | CC62: 166441.06 | CD62: GBD
B63: Bangladesh | C63: both | D63: 45-49 years | E63: 2021 | F63: Population | G63: Number | H63: 8945788 | I63: 10093576 | J63: 7766898 | L63: Deaths | M63: Cameroon | N63: Both | O63: <28 days | P63: Malaria | Q63: Number | R63: 2021 | S63: 595.34613 | T63: 1215.2277 | U63: 171.64994 | AH63: Incidence | AI63: Ethiopia | AJ63: Both | AK63: <1 year | AL63: Malaria | AM63: Rate | AN63: 2021 | AO63: 1190.2988 | AP63: 1602.9238 | AQ63: 823.31788 | AS63: Malaria | AT63: Both | AU63: All Ages | AV63: FCT (Abuja) | AW63: Deaths | AX63: Number | AY63: Past estimate | AZ63: 2021 | BA63: 5429.3753 | BB63: 1742.9138 | BC63: 10493.673 | BD63: GBD | BS63: Malaria | BT63: Both | BU63: 5 to 14 | BV63: Osun | BW63: Incidence | BX63: Rate (per 100,000) | BY63: Past estimate | BZ63: 2021 | CA63: 41577.712 | CB63: 21247.976 | CC63: 86982.26 | CD63: GBD
B64: Bangladesh | C64: both | D64: 50-54 years | E64: 2021 | F64: Population | G64: Number | H64: 7541338 | I64: 8508928 | J64: 6547529 | L64: Deaths | M64: Central African Republic | N64: Both | O64: <5 years | P64: Malaria | Q64: Number | R64: 2021 | S64: 2730.1096 | T64: 6079.8746 | U64: 1087.4658 | AH64: Incidence | AI64: Gabon | AJ64: Both | AK64: <5 years | AL64: Malaria | AM64: Rate | AN64: 2021 | AO64: 67263.479 | AP64: 122358.64 | AQ64: 15398.688 | AS64: Malaria | AT64: Both | AU64: Under 5 | AV64: Gombe | AW64: Deaths | AX64: Number | AY64: Past estimate | AZ64: 2021 | BA64: 2553.6855 | BB64: 981.67776 | BC64: 5372.5436 | BD64: GBD | BS64: Malaria | BT64: Both | BU64: Under 5 | BV64: Oyo | BW64: Incidence | BX64: Rate (per 100,000) | BY64: Past estimate | BZ64: 2021 | CA64: 93840.62 | CB64: 40285.04 | CC64: 158974.86 | CD64: GBD
B65: Bangladesh | C65: both | D65: 50-69 years | E65: 2021 | F65: Population | G65: Number | H65: 23537833 | I65: 26557850 | J65: 20435981 | L65: Deaths | M65: Central African Republic | N65: Both | O65: 0-6 days | P65: Malaria | Q65: Number | R65: 2021 | S65: 0 | T65: 0 | U65: 0 | AH65: Incidence | AI65: Gabon | AJ65: Both | AK65: 5-14 years | AL65: Malaria | AM65: Rate | AN65: 2021 | AO65: 27897.474 | AP65: 62349.85 | AQ65: 12783.679 | AS65: Malaria | AT65: Both | AU65: 7 to 27 days (late neonatal) | AV65: Gombe | AW65: Deaths | AX65: Number | AY65: Past estimate | AZ65: 2021 | BA65: 81.955725 | BB65: 22.572061 | BC65: 212.09584 | BD65: GBD | BS65: Malaria | BT65: Both | BU65: 5 to 14 | BV65: Oyo | BW65: Incidence | BX65: Rate (per 100,000) | BY65: Past estimate | BZ65: 2021 | CA65: 38318.27 | CB65: 20152.485 | CC65: 83289.534 | CD65: GBD
B66: Bangladesh | C66: both | D66: 5-14 years | E66: 2021 | F66: Population | G66: Number | H66: 31401922 | I66: 35430939 | J66: 27263728 | L66: Deaths | M66: Central African Republic | N66: Both | O66: 7-27 days | P66: Malaria | Q66: Number | R66: 2021 | S66: 190.10461 | T66: 450.0638 | U66: 66.919839 | AH66: Incidence | AI66: Gabon | AJ66: Both | AK66: <1 year | AL66: Malaria | AM66: Rate | AN66: 2021 | AO66: 47391.826 | AP66: 86238.47 | AQ66: 10433.717 | AS66: Malaria | AT66: Both | AU66: 28 to 364 days (post neonatal) | AV66: Gombe | AW66: Deaths | AX66: Number | AY66: Past estimate | AZ66: 2021 | BA66: 602.95458 | BB66: 208.19235 | BC66: 1402.9654 | BD66: GBD | BS66: Malaria | BT66: Both | BU66: Under 5 | BV66: Plateau | BW66: Incidence | BX66: Rate (per 100,000) | BY66: Past estimate | BZ66: 2021 | CA66: 77809.67 | CB66: 36044.65 | CC66: 144067.28 | CD66: GBD
... B77: Bangladesh | C77: both | D77: 80-84 years | E77: 2021 | F77: Population | G77: Number | H77: 1230806 | I77: 1388725 | J77: 1068609 | L77: Deaths | M77: Comoros | N77: Both | O77: 0-6 days | P77: Malaria | Q77: Number | R77: 2021 | S77: 0 | T77: 0 | U77: 0 | AH77: Incidence | AI77: Guinea-Bissau | AJ77: Both | AK77: 5-14 years | AL77: Malaria | AM77: Rate | AN77: 2021 | AO77: 10676.421 | AP77: 29877.187 | AQ77: 3278.4237 | AS77: Malaria | AT77: Both | AU77: 7 to 27 days (late neonatal) | AV77: Kaduna | AW77: Deaths | AX77: Number | AY77: Past estimate | AZ77: 2021 | BA77: 300.82159 | BB77: 74.441912 | BC77: 743.87725 | BD77: GBD | BS77: Malaria | BT77: Both | BU77: 5 to 14 | BV77: Zamfara | BW77: Incidence | BX77: Rate (per 100,000) | BY77: Past estimate | BZ77: 2021 | CA77: 30568.558 | CB77: 13890.761 | CC77: 54403.87 | CD77: GBD
B78: Bangladesh | C78: both | D78: 85-89 years | E78: 2021 | F78: Population | G78: Number | H78: 534438 | I78: 603009 | J78: 464009 | L78: Deaths | M78: Comoros | N78: Both | O78: 7-27 days | P78: Malaria | Q78: Number | R78: 2021 | S78: 0.0449732 | T78: 0.076371979 | U78: 0.020080347 | AH78: Incidence | AI78: Guinea-Bissau | AJ78: Both | AK78: <1 year | AL78: Malaria | AM78: Rate | AN78: 2021 | AO78: 15395.507 | AP78: 41410.791 | AQ78: 3110.3564 | AS78: Malaria | AT78: Both | AU78: 28 to 364 days (post neonatal) | AV78: Kaduna | AW78: Deaths | AX78: Number | AY78: Past estimate | AZ78: 2021 | BA78: 2247.0723 | BB78: 662.28306 | BC78: 4778.9001 | BD78: GBD
B79: Bangladesh | C79: both | D79: 90-94 years | E79: 2021 | F79: Population | G79: Number | H79: 164527 | I79: 185636 | J79: 142845 | L79: Deaths | M79: Comoros | N79: Both | O79: All ages | P79: Malaria | Q79: Number | R79: 2021 | S79: 29.658595 | T79: 50.209602 | U79: 13.317853 | AH79: Incidence | AI79: India | AJ79: Both | AK79: <5 years | AL79: Malaria | AM79: Rate | AN79: 2021 | AO79: 154.31003 | AP79: 607.47884 | AQ79: 38.152104 | AS79: Malaria | AT79: Both | AU79: All Ages | AV79: Kaduna | AW79: Deaths | AX79: Number | AY79: Past estimate | AZ79: 2021 | BA79: 11930.936 | BB79: 3825.4427 | BC79: 23628.249 | BD79: GBD
B80: Bangladesh | C80: both | D80: 95+ years | E80: 2021 | F80: Population | G80: Number | H80: 25053 | I80: 28268 | J80: 21752 | L80: Deaths | M80: Comoros | N80: Both | O80: <1 year | P80: Malaria | Q80: Number | R80: 2021 | S80: 0.95129242 | T80: 1.555544 | U80: 0.40137286 | AH80: Incidence | AI80: India | AJ80: Both | AK80: 5-14 years | AL80: Malaria | AM80: Rate | AN80: 2021 | AO80: 204.79825 | AP80: 608.71512 | AQ80: 69.459742 | AS80: Malaria | AT80: Both | AU80: Under 5 | AV80: Kano | AW80: Deaths | AX80: Number | AY80: Past estimate | AZ80: 2021 | BA80: 19224.005 | BB80: 5181.4987 | BC80: 39993.976 | BD80: GBD
B81: Bangladesh | C81: both | D81: All ages | E81: 2021 | F81: Population | G81: Number | H81: 164636116 | I81: 185759720 | J81: 142940113 | L81: Deaths | M81: Comoros | N81: Both | O81: <28 days | P81: Malaria | Q81: Number | R81: 2021 | S81: 0.0449732 | T81: 0.076371979 | U81: 0.020080347 | AH81: Incidence | AI81: India | AJ81: Both | AK81: <1 year | AL81: Malaria | AM81: Rate | AN81: 2021 | AO81: 101.78518 | AP81: 414.99096 | AQ81: 23.317729 | AS81: Malaria | AT81: Both | AU81: 7 to 27 days (late neonatal) | AV81: Kano | AW81: Deaths | AX81: Number | AY81: Past estimate | AZ81: 2021 | BA81: 621.87826 | BB81: 112.1054 | BC81: 1661.2888 | BD81: GBD
B82: Benin | C82: both | D82: <1 year | E82: 2021 | F82: Population | G82: Number | H82: 499223 | I82: 559969 | J82: 438016 | L82: Deaths | M82: Congo | N82: Both | O82: <5 years | P82: Malaria | Q82: Number | R82: 2021 | S82: 919.02513 | T82: 1565.9228 | U82: 350.56304 | AH82: Incidence | AI82: Kenya | AJ82: Both | AK82: <5 years | AL82: Malaria | AM82: Rate | AN82: 2021 | AO82: 14491.629 | AP82: 23613.302 | AQ82: 5461.3197 | AS82: Malaria | AT82: Both | AU82: 28 to 364 days (post neonatal) | AV82: Kano | AW82: Deaths | AX82: Number | AY82: Past estimate | AZ82: 2021 | BA82: 4286.4314 | BB82: 846.00985 | BC82: 10202.922 | BD82: GBD
B83: Benin | C83: both | D83: <20 years | E83: 2021 | F83: Population | G83: Number | H83: 7516302 | I83: 8430890 | J83: 6594772 | L83: Deaths | M83: Congo | N83: Both | O83: 0-6 days | P83: Malaria | Q83: Number | R83: 2021 | S83: 0 | T83: 0 | U83: 0 | AH83: Incidence | AI83: Kenya | AJ83: Both | AK83: 5-14 years | AL83: Malaria | AM83: Rate | AN83: 2021 | AO83: 6839.6777 | AP83: 11966.866 | AQ83: 4472.7247 | AS83: Malaria | AT83: Both | AU83: All Ages | AV83: Kano | AW83: Deaths | AX83: Number | AY83: Past estimate | AZ83: 2021 | BA83: 25832.691 | BB83: 6680.4563 | BC83: 54167.496 | BD83: GBD
B84: Benin | C84: both | D84: <28 days | E84: 2021 | F84: Population | G84: Number | H84: 39293 | I84: 44074 | J84: 34475 | L84: Deaths | M84: Congo | N84: Both | O84: 7-27 days | P84: Malaria | Q84: Number | R84: 2021 | S84: 55.486838 | T84: 112.56366 | U84: 19.305563 | AH84: Incidence | AI84: Kenya | AJ84: Both | AK84: <1 year | AL84: Malaria | AM84: Rate | AN84: 2021 | AO84: 10263.748 | AP84: 16760.27 | AQ84: 3584.1471 | AS84: Malaria | AT84: Both | AU84: Under 5 | AV84: Katsina | AW84: Deaths | AX84: Number | AY84: Past estimate | AZ84: 2021 | BA84: 8099.5279 | BB84: 1673.3138 | BC84: 18128.753 | BD84: GBD
B85: Benin | C85: both | D85: <5 years | E85: 2021 | F85: Population | G85: Number | H85: 2342363 | I85: 2627383 | J85: 2055180 | L85: Deaths | M85: Congo | N85: Both | O85: All ages | P85: Malaria | Q85: Number | R85: 2021 | S85: 2439.2762 | T85: 4789.9464 | U85: 893.29478 | AH85: Incidence | AI85: Lesotho | AJ85: Both | AK85: <5 years | AL85: Malaria | AM85: Rate | AN85: 2021 | AO85: 0 | AP85: 0 | AQ85: 0 | AS85: Malaria | AT85: Both | AU85: 7 to 27 days (late neonatal) | AV85: Katsina | AW85: Deaths | AX85: Number | AY85: Past estimate | AZ85: 2021 | BA85: 236.46922 | BB85: 34.626745 | BC85: 677.3675 | BD85: GBD
B86: Benin | C86: both | D86: 0-14 years | E86: 2021 | F86: Population | G86: Number | H86: 6080396 | I86: 6820262 | J86: 5334914 | L86: Deaths | M86: Congo | N86: Both | O86: <1 year | P86: Malaria | Q86: Number | R86: 2021 | S86: 396.35355 | T86: 736.82331 | U86: 143.15813 | AH86: Incidence | AI86: Lesotho | AJ86: Both | AK86: 5-14 years | AL86: Malaria | AM86: Rate | AN86: 2021 | AO86: 0 | AP86: 0 | AQ86: 0 | AS86: Malaria | AT86: Both | AU86: 28 to 364 days (post neonatal) | AV86: Katsina | AW86: Deaths | AX86: Number | AY86: Past estimate | AZ86: 2021 | BA86: 1815.5461 | BB86: 306.97929 | BC86: 4663.5993 | BD86: GBD
B87: Benin | C87: both | D87: 0-6 days | E87: 2021 | F87: Population | G87: Number | H87: 9940 | I87: 11150 | J87: 8721 | L87: Deaths | M87: Congo | N87: Both | O87: <28 days | P87: Malaria | Q87: Number | R87: 2021 | S87: 55.486838 | T87: 112.56366 | U87: 19.305563 | AH87: Incidence | AI87: Lesotho | AJ87: Both | AK87: <1 year | AL87: Malaria | AM87: Rate | AN87: 2021 | AO87: 0 | AP87: 0 | AQ87: 0 | AS87: Malaria | AT87: Both | AU87: All Ages | AV87: Katsina | AW87: Deaths | AX87: Number | AY87: Past estimate | AZ87: 2021 | BA87: 11187.131 | BB87: 2138.5501 | BC87: 26220.104 | BD87: GBD
B88: Benin | C88: both | D88: 10-14 years | E88: 2021 | F88: Population | G88: Number | H88: 1707799 | I88: 1915605 | J88: 1498416 | L88: Deaths | M88: Democratic Republic of the Congo | N88: Both | O88: <5 years | P88: Malaria | Q88: Number | R88: 2021 | S88: 47816.384 | T88: 78261.881 | U88: 23079.834 | AH88: Incidence | AI88: Liberia | AJ88: Both | AK88: <5 years | AL88: Malaria | AM88: Rate | AN88: 2021 | AO88: 105234.35 | AP88: 156927.31 | AQ88: 39616.686 | AS88: Malaria | AT88: Both | AU88: Under 5 | AV88: Kebbi | AW88: Deaths | AX88: Number | AY88: Past estimate | AZ88: 2021 | BA88: 3863.1601 | BB88: 1172.7835 | BC88: 8220.5479 | BD88: GBD
B89: Benin | C89: both | D89: 10-19 years | E89: 2021 | F89: Population | G89: Number | H89: 3143705 | I89: 3526233 | J89: 2758274 | L89: Deaths | M89: Democratic Republic of the Congo | N89: Both | O89: 0-6 days | P89: Malaria | Q89: Number | R89: 2021 | S89: 0 | T89: 0 | U89: 0 | AH89: Incidence | AI89: Liberia | AJ89: Both | AK89: 5-14 years | AL89: Malaria | AM89: Rate | AN89: 2021 | AO89: 43093.531 | AP89: 83457.466 | AQ89: 19197.831 | AS89: Malaria | AT89: Both | AU89: 7 to 27 days (late neonatal) | AV89: Kebbi | AW89: Deaths | AX89: Number | AY89: Past estimate | AZ89: 2021 | BA89: 129.06104 | BB89: 29.333663 | BC89: 296.80069 | BD89: GBD
... B151: Bhutan | C151: both | D151: 70-74 years | E151: 2021 | F151: Population | G151: Number | H151: 13125 | I151: 14270 | J151: 11879 | L151: Deaths | M151: Guinea-Bissau | N151: Both | O151: All ages | P151: Malaria | Q151: Number | R151: 2021 | S151: 578.67764 | T151: 1309.2042 | U151: 127.19152 | AH151: Incidence | AI151: Zambia | AJ151: Both | AK151: <5 years | AL151: Malaria | AM151: Rate | AN151: 2021 | AO151: 43799.873 | AP151: 69558.648 | AQ151: 22322.199 | AS151: Malaria | AT151: Both | AU151: All Ages | AV151: Zamfara | AW151: Deaths | AX151: Number | AY151: Past estimate | AZ151: 2021 | BA151: 3907.9812 | BB151: 919.87239 | BC151: 9250.9905 | BD151: GBD
B152: Bhutan | C152: both | D152: 7-27 days | E152: 2021 | F152: Population | G152: Number | H152: 705 | I152: 766 | J152: 638 | L152: Deaths | M152: Guinea-Bissau | N152: Both | O152: <1 year | P152: Malaria | Q152: Number | R152: 2021 | S152: 145.88524 | T152: 317.32806 | U152: 28.802321 | AH152: Incidence | AI152: Zambia | AJ152: Both | AK152: 5-14 years | AL152: Malaria | AM152: Rate | AN152: 2021 | AO152: 19439.571 | AP152: 34075.852 | AQ152: 10623.191
B153: Bhutan | C153: both | D153: 75-79 years | E153: 2021 | F153: Population | G153: Number | H153: 9144 | I153: 9942 | J153: 8277 | L153: Deaths | M153: Guinea-Bissau | N153: Both | O153: <28 days | P153: Malaria | Q153: Number | R153: 2021 | S153: 24.638812 | T153: 55.521628 | U153: 3.9664171 | AH153: Incidence | AI153: Zambia | AJ153: Both | AK153: <1 year | AL153: Malaria | AM153: Rate | AN153: 2021 | AO153: 30911.066 | AP153: 49090.735 | AQ153: 15753.802
B154: Bhutan | C154: both | D154: 80+ years | E154: 2021 | F154: Population | G154: Number | H154: 9968 | I154: 10838 | J154: 9022 | L154: Deaths | M154: India | N154: Both | O154: <5 years | P154: Malaria | Q154: Number | R154: 2021 | S154: 5014.1977 | T154: 17096.135 | U154: 0 | AH154: Incidence | AI154: Zimbabwe | AJ154: Both | AK154: <5 years | AL154: Malaria | AM154: Rate | AN154: 2021 | AO154: 3038.471 | AP154: 4540.471 | AQ154: 1961.2286
B155: Bhutan | C155: both | D155: 80-84 years | E155: 2021 | F155: Population | G155: Number | H155: 5725 | I155: 6225 | J155: 5182 | L155: Deaths | M155: India | N155: Both | O155: 0-6 days | P155: Malaria | Q155: Number | R155: 2021 | S155: 0 | T155: 0 | U155: 0 | AH155: Incidence | AI155: Zimbabwe | AJ155: Both | AK155: 5-14 years | AL155: Malaria | AM155: Rate | AN155: 2021 | AO155: 2995.7048 | AP155: 4110.9986 | AQ155: 2141.5243
B156: Bhutan | C156: both | D156: 85-89 years | E156: 2021 | F156: Population | G156: Number | H156: 3043 | I156: 3309 | J156: 2754 | L156: Deaths | M156: India | N156: Both | O156: 7-27 days | P156: Malaria | Q156: Number | R156: 2021 | S156: 111.93725 | T156: 471.71433 | U156: 0 | AH156: Incidence | AI156: Zimbabwe | AJ156: Both | AK156: <1 year | AL156: Malaria | AM156: Rate | AN156: 2021 | AO156: 2114.7046 | AP156: 3169.2813 | AQ156: 1359.9129
B157: Bhutan | C157: both | D157: 90-94 years | E157: 2021 | F157: Population | G157: Number | H157: 952 | I157: 1035 | J157: 862 | L157: Deaths | M157: India | N157: Both | O157: All ages | P157: Malaria | Q157: Number | R157: 2021 | S157: 16917.065 | T157: 66855.928 | U157: 0
B158: Bhutan | C158: both | D158: 95+ years | E158: 2021 | F158: Population | G158: Number | H158: 247 | I158: 269 | J158: 224 | L158: Deaths | M158: India | N158: Both | O158: <1 year | P158: Malaria | Q158: Number | R158: 2021 | S158: 2277.3633 | T158: 7646.9713 | U158: 0
B159: Bhutan | C159: both | D159: All ages | E159: 2021 | F159: Population | G159: Number | H159: 756900 | I159: 822956 | J159: 685067 | L159: Deaths | M159: India | N159: Both | O159: <28 days | P159: Malaria | Q159: Number | R159: 2021 | S159: 111.93725 | T159: 471.71433 | U159: 0
B160: Botswana | C160: both | D160: <1 year | E160: 2021 | F160: Population | G160: Number | H160: 47304 | I160: 53564 | J160: 41087 | L160: Deaths | M160: Kenya | N160: Both | O160: <5 years | P160: Malaria | Q160: Number | R160: 2021 | S160: 4582.5126 | T160: 7109.2896 | U160: 2724.6918
B161: Botswana | C161: both | D161: <20 years | E161: 2021 | F161: Population | G161: Number | H161: 917006 | I161: 1038356 | J161: 796487 | L161: Deaths | M161: Kenya | N161: Both | O161: 0-6 days | P161: Malaria | Q161: Number | R161: 2021 | S161: 0 | T161: 0 | U161: 0
B162: Botswana | C162: both | D162: <28 days | E162: 2021 | F162: Population | G162: Number | H162: 3661 | I162: 4146 | J162: 3180 | L162: Deaths | M162: Kenya | N162: Both | O162: 7-27 days | P162: Malaria | Q162: Number | R162: 2021 | S162: 484.645 | T162: 796.82876 | U162: 282.38671
B163: Botswana | C163: both | D163: <5 years | E163: 2021 | F163: Population | G163: Number | H163: 235498 | I163: 266662 | J163: 204547 | L163: Deaths | M163: Kenya | N163: Both | O163: All ages | P163: Malaria | Q163: Number | R163: 2021 | S163: 7550.5717 | T163: 11989.857 | U163: 4492.5449
B164: Botswana | C164: both | D164: 0-14 years | E164: 2021 | F164: Population | G164: Number | H164: 698277 | I164: 790683 | J164: 606505 | L164: Deaths | M164: Kenya | N164: Both | O164: <1 year | P164: Malaria | Q164: Number | R164: 2021 | S164: 2513.7883 | T164: 3921.4418 | U164: 1436.9793
B165: Botswana | C165: both | D165: 0-6 days | E165: 2021 | F165: Population | G165: Number | H165: 922 | I165: 1044 | J165: 801 | L165: Deaths | M165: Kenya | N165: Both | O165: <28 days | P165: Malaria | Q165: Number | R165: 2021 | S165: 484.645 | T165: 796.82876 | U165: 282.38671
B166: Botswana | C166: both | D166: 10-14 years | E166: 2021 | F166: Population | G166: Number | H166: 229138 | I166: 259460 | J166: 199023 | L166: Deaths | M166: Lesotho | N166: Both | O166: All ages | P166: Malaria | Q166: Number | R166: 2021 | S166: 0 | T166: 0 | U166: 0
B167: Botswana | C167: both | D167: 10-19 years | E167: 2021 | F167: Population | G167: Number | H167: 447866 | I167: 507134 | J167: 389005 | L167: Deaths | M167: Lesotho | N167: Both | O167: <1 year | P167: Malaria | Q167: Number | R167: 2021 | S167: 0 | T167: 0 | U167: 0
B168: Botswana | C168: both | D168: 10-24 years | E168: 2021 | F168: Population | G168: Number | H168: 653793 | I168: 740311 | J168: 567867 | L168: Deaths | M168: Lesotho | N168: Both | O168: <28 days | P168: Malaria | Q168: Number | R168: 2021 | S168: 0 | T168: 0 | U168: 0
... B309: Côte d'Ivoire | C309: both | D309: 75-79 years | E309: 2021 | F309: Population | G309: Number | H309: 120580 | I309: 134795 | J309: 107576 | L309: Deaths | M309: Zimbabwe | N309: Both | O309: <28 days | P309: Malaria | Q309: Number | R309: 2021 | S309: 17.720023 | T309: 39.981892 | U309: 5.1298447
B310: Côte d'Ivoire | C310: both | D310: 80+ years | E310: 2021 | F310: Population | G310: Number | H310: 97898 | I310: 109440 | J310: 87340
B311: Côte d'Ivoire | C311: both | D311: 80-84 years | E311: 2021 | F311: Population | G311: Number | H311: 61550 | I311: 68806 | J311: 54912
B312: Côte d'Ivoire | C312: both | D312: 85-89 years | E312: 2021 | F312: Population | G312: Number | H312: 26507 | I312: 29632 | J312: 23648
B313: Côte d'Ivoire | C313: both | D313: 90-94 years | E313: 2021 | F313: Population | G313: Number | H313: 8082 | I313: 9034 | J313: 7210
B314: Côte d'Ivoire | C314: both | D314: 95+ years | E314: 2021 | F314: Population | G314: Number | H314: 1759 | I314: 1967 | J314: 1570
B315: CÃ´te d'Ivoire | C315: both | D315: All ages | E315: 2021 | F315: Population | G315: Number | H315: 27861876 | I315: 31146597 | J315: 24857066
B316: Cabo Verde | C316: both | D316: <1 year | E316: 2021 | F316: Population | G316: Number | H316: 8444 | I316: 9574 | J316: 7358
B317: Cabo Verde | C317: both | D317: <20 years | E317: 2021 | F317: Population | G317: Number | H317: 192746 | I317: 218534 | J317: 167951
B318: Cabo Verde | C318: both | D318: <28 days | E318: 2021 | F318: Population | G318: Number | H318: 644 | I318: 730 | J318: 561
B319: Cabo Verde | C319: both | D319: <5 years | E319: 2021 | F319: Population | G319: Number | H319: 44059 | I319: 49954 | J319: 38391
B320: Cabo Verde | C320: both | D320: 0-14 years | E320: 2021 | F320: Population | G320: Number | H320: 143202 | I320: 162362 | J320: 124780
B321: Cabo Verde | C321: both | D321: 0-6 days | E321: 2021 | F321: Population | G321: Number | H321: 161 | I321: 183 | J321: 141
... B1992: Zimbabwe | C1992: both | D1992: All ages | E1992: 2021 | F1992: Population | G1992: Number | H1992: 15595374 | I1992: 17465381 | J1992: 13802194

Sheet Simple CEA
I1: Malaria Consortium | S1: Malaria Consortium
I2: Burkina Faso | J2: Chad | K2: Côte d'Ivoire | L2: DRC | M2: DRC | N2: DRC | O2: DRC | P2: Mozambique | Q2: Nigeria | R2: Nigeria | S2: Nigeria | T2: Nigeria | U2: Nigeria | V2: Nigeria | W2: Nigeria | X2: Nigeria | Y2: Nigeria | Z2: South Sudan | AA2: Togo | AB2: Uganda
F3: unit | G3: type | H3: Overall | L3: Haut-Katanga | M3: Haut-Lomami | N3: Lualaba | O3: Tanganyika | P3: Nampula | Q3: Bauchi | R3: Borno | S3: FCT (Abuja) | T3: Kebbi | U3: Kogi | V3: Nasarawa | W3: Oyo | X3: Plateau | Y3: Sokoto | Z3: Northern Bahr El Ghazal | AB3: Karamoja
A4: Simple CEA
C6: Grant
E7: Grant size | F7: $ | G7: input | H7: =Inputs!H8 -> - | I7: =Inputs!I8 -> 0.01 | J7: =Inputs!J8 -> 0.01 | K7: =Inputs!K8 -> 0.01 | L7: =Inputs!L8 -> 0.01 | M7: =Inputs!M8 -> 0.01 | N7: =Inputs!N8 -> 0.01 | O7: =Inputs!O8 -> 0.01 | ... AB7: =Inputs!AB8 -> 0.01
C9: Under-five mortality benefits
E10: Cost per person under age five reached | F10: $ | G10: input | H10: - | I10: ='Main CEA'!I31 -> 6.3328458 | J10: ='Main CEA'!J31 -> 7.0148815 | K10: ='Main CEA'!K31 -> 11.44973 | L10: ='Main CEA'!L31 -> 7.3151843 | M10: ='Main CEA'!M31 -> 7.3151843 | N10: ='Main CEA'!N31 -> 7.3151843 | O10: ='Main CEA'!O31 -> 7.3151843 | P10: ='Main CEA'!P31 -> 7.4181972 | ... AB10: ='Main CEA'!AB31 -> 8.8672256
E11: Number of people under age five reached | F11: # | G11: calc | H11: - | I11: =IF(I7="-",$H7/I10,I7/I10) -> 0.0015790689 | J11: =IF(J7="-",$H7/J10,J7/J10) -> 0.0014255408 | K11: =IF(K7="-",$H7/K10,K7/K10) -> 0.00087338307 | L11: =IF(L7="-",$H7/L10,L7/L10) -> 0.0013670195 | M11: =IF(M7="-",$H7/M10,M7/M10) -> 0.0013670195 | N11: =IF(N7="-",$H7/N10,N7/N10) -> 0.0013670195 | O11: =IF(O7="-",$H7/O10,O7/O10) -> 0.0013670195 | P11: =IF(P7="-",$H7/P10,P7/P10) -> 2353254.6 | ... AB11: =IF(AB7="-",$H7/AB10,AB7/AB10) -> 0.0011277485
E12: Proportion of reached children who would have received SMC in the absence of the program | F12: % | G12: input | H12: - | I12: 0 | J12: 0 | K12: 0 | L12: 0 | M12: 0 | N12: 0 | O12: 0 | P12: 0 | Q12: 0 | R12: 0 | S12: 0 | T12: 0 | U12: 0 | V12: 0 | W12: 0 | X12: 0 | Y12: 0 | Z12: 0 | AA12: 0 | AB12: 0
E13: Number of additional children receiving SMC as a result of the program | F13: # | G13: calc | H13: - | I13: =I11*(1-I12) -> 0.0015790689 | J13: =J11*(1-J12) -> 0.0014255408 | K13: =K11*(1-K12) -> 0.00087338307 | L13: =L11*(1-L12) -> 0.0013670195 | M13: =M11*(1-M12) -> 0.0013670195 | N13: =N11*(1-N12) -> 0.0013670195 | O13: =O11*(1-O12) -> 0.0013670195 | P13: =P11*(1-P12) -> 2353254.6 | ... AB13: =AB11*(1-AB12) -> 0.0011277485
E14: Malaria-attributable mortality rate among people under age five | F14: % | G14: input | H14: - | I14: ='Main CEA'!I54 -> 0.0047483266 | J14: ='Main CEA'!J54 -> 0.0047887355 | K14: ='Main CEA'!K54 -> 0.0042221079 | L14: ='Main CEA'!L54 -> 0.0053809993 | M14: ='Main CEA'!M54 -> 0.005780132 | N14: ='Main CEA'!N54 -> 0.0063770918 | O14: ='Main CEA'!O54 -> 0.0068848776 | P14: ='Main CEA'!P54 -> 0.0046744695 | ... AB14: ='Main CEA'!AB54 -> 0.0032622666
E15: Proportion of malaria mortality occurring during the SMC season | F15: % | G15: input | H15: - | I15: ='Main CEA'!I56 -> 0.7 | J15: ='Main CEA'!J56 -> 0.7 | K15: ='Main CEA'!K56 -> 0.7 | L15: ='Main CEA'!L56 -> 0.515 | M15: ='Main CEA'!M56 -> 0.515 | N15: ='Main CEA'!N56 -> 0.515 | O15: ='Main CEA'!O56 -> 0.515 | P15: ='Main CEA'!P56 -> 0.515 | ... AB15: ='Main CEA'!AB56 -> 0.62
E16: Effect of SMC on under-five deaths related to malaria | F16: % | G16: input | H16: - | I16: ='Main CEA'!I49 -> 0.793695 | J16: ='Main CEA'!J49 -> 0.793695 | K16: ='Main CEA'!K49 -> 0.793695 | L16: ='Main CEA'!L49 -> 0.59527125 | M16: ='Main CEA'!M49 -> 0.59527125 | N16: ='Main CEA'!N49 -> 0.59527125 | O16: ='Main CEA'!O49 -> 0.59527125 | P16: ='Main CEA'!P49 -> 0.59527125 | ... AB16: ='Main CEA'!AB49 -> 0.59527125
E17: Number of deaths averted among people under age five | F17: # | G17: calc | H17: - | I17: =I11*I14*I15*I16 -> 4.1657515e-06 | J17: =J11*J14*J15*J16 -> 3.7927323e-06 | K17: =K11*K14*K15*K16 -> 2.048735e-06 | L17: =L11*L14*L15*L16 -> 2.2550688e-06 | M17: =M11*M14*M15*M16 -> 2.4223373e-06 | N17: =N11*N14*N15*N16 -> 2.6725112e-06 | O17: =O11*O14*O15*O16 -> 2.885314e-06 | P17: =P11*P14*P15*P16 -> 3372.2782 | ... AB17: =AB11*AB14*AB15*AB16 -> 1.3578078e-06
C19: Initial cost-effectiveness estimate
E20: Cost per under-five death averted (before adjustments) | F20: $ | G20: calc | H20: - | I20: =IF(I7="-",$H7/I17,I7/I17) -> 2400.5273 | J20: =IF(J7="-",$H7/J17,J7/J17) -> 2636.6216 | K20: =IF(K7="-",$H7/K17,K7/K17) -> 4881.0608 | L20: =IF(L7="-",$H7/L17,L7/L17) -> 4434.4545 | M20: =IF(M7="-",$H7/M17,M7/M17) -> 4128.2443 | N20: =IF(N7="-",$H7/N17,N7/N17) -> 3741.7991 | O20: =IF(O7="-",$H7/O17,O7/O17) -> 3465.8273 | P20: =IF(P7="-",$H7/P17,P7/P17) -> 5176.5917 | ... AB20: =IF(AB7="-",$H7/AB17,AB7/AB17) -> 7364.8127
E21: Moral value of averting the death of a person under age five | F21: UoV | G21: input | H21: ='Main CEA'!H$102 -> 116.25262 | I21: ='Main CEA'!I$102 -> - | J21: ='Main CEA'!J$102 -> - | K21: ='Main CEA'!K$102 -> - | L21: ='Main CEA'!L$102 -> - | M21: ='Main CEA'!M$102 -> - | N21: ='Main CEA'!N$102 -> - | O21: ='Main CEA'!O$102 -> - | ... AB21: ='Main CEA'!AB$102 -> -
E22: Initial cost-effectiveness in terms of multiples of GiveDirectly's unconditional cash transfer program | F22: xcash | G22: calc | H22: - | I22: =IF(I7="-",((I17*$H21)/$H7)/'Main CEA'!$H$135,((I17*$H21)/I7)/'Main CEA'!$H$135) -> 14.436713 | J22: =IF(J7="-",((J17*$H21)/$H7)/'Main CEA'!$H$135,((J17*$H21)/J7)/'Main CEA'!$H$135) -> 13.143988 | K22: =IF(K7="-",((K17*$H21)/$H7)/'Main CEA'!$H$135,((K17*$H21)/K7)/'Main CEA'!$H$135) -> 7.100039 | L22: =IF(L7="-",((L17*$H21)/$H7)/'Main CEA'!$H$135,((L17*$H21)/L7)/'Main CEA'!$H$135) -> 7.8151038 | M22: =IF(M7="-",((M17*$H21)/$H7)/'Main CEA'!$H$135,((M17*$H21)/M7)/'Main CEA'!$H$135) -> 8.3947848 | N22: =IF(N7="-",((N17*$H21)/$H7)/'Main CEA'!$H$135,((N17*$H21)/N7)/'Main CEA'!$H$135) -> 9.2617805 | O22: =IF(O7="-",((O17*$H21)/$H7)/'Main CEA'!$H$135,((O17*$H21)/O7)/'Main CEA'!$H$135) -> 9.9992641 | P22: =IF(P7="-",((P17*$H21)/$H7)/'Main CEA'!$H$135,((P17*$H21)/P7)/'Main CEA'!$H$135) -> 6.6946988 | ... AB22: =IF(AB7="-",((AB17*$H21)/$H7)/'Main CEA'!$H$135,((AB17*$H21)/AB7)/'Main CEA'!$H$135) -> 4.7055809
C24: Adjustments for other benefits
E25: Adjustment to account for mortalities averted among people age 5 and older | F25: % | G25: input | H25: - | I25: ='Main CEA'!I128/'Main CEA'!I127 -> 0.068571122 | J25: ='Main CEA'!J128/'Main CEA'!J127 -> 0.054991809 | K25: ='Main CEA'!K128/'Main CEA'!K127 -> 0.10463517 | L25: ='Main CEA'!L128/'Main CEA'!L127 -> 0.029573301 | M25: ='Main CEA'!M128/'Main CEA'!M127 -> 0.029559083 | N25: ='Main CEA'!N128/'Main CEA'!N127 -> 0.029563011 | O25: ='Main CEA'!O128/'Main CEA'!O127 -> 0.029583469 | P25: ='Main CEA'!P128/'Main CEA'!P127 -> 0.14840341 | ... AB25: ='Main CEA'!AB128/'Main CEA'!AB127 -> 0.033219261
E26: Adjustment to account for developmental benefits (long-term income increases) | F26: % | G26: input | H26: - | I26: ='Main CEA'!I129/SUM('Main CEA'!I127:I128) -> 0.31328741 | J26: ='Main CEA'!J129/SUM('Main CEA'!J127:J128) -> 0.20796504 | K26: ='Main CEA'!K129/SUM('Main CEA'!K127:K128) -> 0.37078634 | L26: ='Main CEA'!L129/SUM('Main CEA'!L127:L128) -> 0.3037231 | M26: ='Main CEA'!M129/SUM('Main CEA'!M127:M128) -> 0.33868209 | N26: ='Main CEA'!N129/SUM('Main CEA'!N127:N128) -> 0.32416106 | O26: ='Main CEA'!O129/SUM('Main CEA'!O127:O128) -> 0.29178348 | P26: ='Main CEA'!P129/SUM('Main CEA'!P127:P128) -> 0.33896514 | ... AB26: ='Main CEA'!AB129/SUM('Main CEA'!AB127:AB128) -> 0.59197739
C28: Percentage of program impact coming from different benefits
E29: Mortalities averted for people under age five | F29: % | G29: calc | H29: - | I29: =1-SUM(I30:I31) -> 0.71258518 | J29: =1-SUM(J30:J31) -> 0.78468716 | K29: =1-SUM(K30:K31) -> 0.66040654 | L29: =1-SUM(L30:L31) -> 0.74500188 | M29: =1-SUM(M30:M31) -> 0.72555656 | N29: =1-SUM(N30:N31) -> 0.73351037 | O29: =1-SUM(O30:O31) -> 0.75188031 | P29: =1-SUM(P30:P31) -> 0.6503337 | ... AB29: =1-SUM(AB30:AB31) -> 0.60795385
E30: Mortalities averted for people over age five | F30: % | G30: calc | H30: - | I30: =I25/(1*(1+I25)*(1+I26)) -> 0.048862765 | J30: =J25/(1*(1+J25)*(1+J26)) -> 0.043151366 | K30: =K25/(1*(1+K25)*(1+K26)) -> 0.069101751 | L30: =L25/(1*(1+L25)*(1+L26)) -> 0.022032165 | M30: =M25/(1*(1+M25)*(1+M26)) -> 0.021446787 | N30: =N25/(1*(1+N25)*(1+N26)) -> 0.021684775 | O30: =O25/(1*(1+O25)*(1+O26)) -> 0.022243228 | P30: =P25/(1*(1+P25)*(1+P26)) -> 0.096511738 | ... AB30: =AB25/(1*(1+AB25)*(1+AB26)) -> 0.020195778
E31: Developmental benefits (long-term income increases) | F31: % | G31: calc | H31: - | I31: =I26/(1*(1+I26)) -> 0.23855206 | J31: =J26/(1*(1+J26)) -> 0.17216147 | K31: =K26/(1*(1+K26)) -> 0.27049171 | L31: =L26/(1*(1+L26)) -> 0.23296596 | M31: =M26/(1*(1+M26)) -> 0.25299665 | N31: =N26/(1*(1+N26)) -> 0.24480486 | O31: =O26/(1*(1+O26)) -> 0.22587646 | P31: =P26/(1*(1+P26)) -> 0.25315456 | ... AB31: =AB26/(1*(1+AB26)) -> 0.37185038
C33: Additional adjustments
E34: Adjustment for additional program benefits and downsides | F34: % | G34: input | H34: - | I34: ='Main CEA'!I179 -> 0.191 | J34: ='Main CEA'!J179 -> 0.241 | K34: ='Main CEA'!K179 -> 0.141 | L34: ='Main CEA'!L179 -> 0.181 | M34: ='Main CEA'!M179 -> 0.181 | N34: ='Main CEA'!N179 -> 0.181 | O34: ='Main CEA'!O179 -> 0.181 | P34: ='Main CEA'!P179 -> 0.181 | ... AB34: ='Main CEA'!AB179 -> 0.181
E35: Adjustment for grantee-level factors | F35: % | G35: input | H35: - | I35: ='Main CEA'!$H163 -> -0.08 | J35: ='Main CEA'!$H163 -> -0.08 | K35: ='Main CEA'!$H163 -> -0.08 | L35: ='Main CEA'!$H163 -> -0.08 | M35: ='Main CEA'!$H163 -> -0.08 | N35: ='Main CEA'!$H163 -> -0.08 | O35: ='Main CEA'!$H163 -> -0.08 | P35: ='Main CEA'!$H163 -> -0.08 | ... AB35: ='Main CEA'!$H163 -> -0.08
E36: Adjustment for leverage | F36: % | G36: input | H36: - | I36: ='Main CEA'!I182 -> -0.0040054445 | J36: ='Main CEA'!J182 -> -0.0059781615 | K36: ='Main CEA'!K182 -> -0.0082512936 | L36: ='Main CEA'!L182 -> -0.013254966 | M36: ='Main CEA'!M182 -> -0.012017599 | N36: ='Main CEA'!N182 -> -0.01101204 | O36: ='Main CEA'!O182 -> -0.010455305 | P36: ='Main CEA'!P182 -> -0.010334576 | ... AB36: ='Main CEA'!AB182 -> -0.012845327
E37: Adjustment for funging | F37: % | G37: input | H37: ='Main CEA'!H$185 -> - | I37: ='Main CEA'!I183 -> -0.39637574 | J37: ='Main CEA'!J183 -> -0.22783051 | K37: ='Main CEA'!K183 -> -0.23693539 | L37: ='Main CEA'!L183 -> -0.089452152 | M37: ='Main CEA'!M183 -> -0.095104367 | N37: ='Main CEA'!N183 -> -0.099697697 | O37: ='Main CEA'!O183 -> -0.10224083 | P37: ='Main CEA'!P183 -> -0.20603461 | ... AB37: ='Main CEA'!AB183 -> -0.18117235
C39: Final cost-effectiveness estimate
E40: Final cost-effectiveness in terms of multiples of GiveDirectly's unconditional cash transfer program | F40: xcash | G40: calc | H40: - | I40: =I22/I29*(1+I34)*(1+I35)*(1+SUM(I36:I37)) -> 13.310868 | J40: =J22/J29*(1+J34)*(1+J35)*(1+SUM(J36:J37)) -> 14.65303 | K40: =K22/K29*(1+K34)*(1+K35)*(1+SUM(K36:K37)) -> 8.5184856 | L40: =L22/L29*(1+L34)*(1+L35)*(1+SUM(L36:L37)) -> 10.227025 | M40: =M22/M29*(1+M34)*(1+M35)*(1+SUM(M36:M37)) -> 11.22453 | N40: =N22/N29*(1+N34)*(1+N35)*(1+SUM(N36:N37)) -> 12.200271 | O40: =O22/O29*(1+O34)*(1+O35)*(1+SUM(O36:O37)) -> 12.821222 | P40: =P22/P29*(1+P34)*(1+P35)*(1+SUM(P36:P37)) -> 8.7648405 | ... AB40: =AB22/AB29*(1+AB34)*(1+AB35)*(1+SUM(AB36:AB37)) -> 6.7780673
E41: Final cost per life saved | F41: $ | G41: calc | H41: - | I41: =I20*('Main CEA'!I58/SUM('Main CEA'!I58,'Main CEA'!I71))/(1+'Main CEA'!I206) -> 4892.9559 | J41: =J20*('Main CEA'!J58/SUM('Main CEA'!J58,'Main CEA'!J71))/(1+'Main CEA'!J206) -> 4037.5284 | K41: =K20*('Main CEA'!K58/SUM('Main CEA'!K58,'Main CEA'!K71))/(1+'Main CEA'!K206) -> 8014.8883 | L41: =L20*('Main CEA'!L58/SUM('Main CEA'!L58,'Main CEA'!L71))/(1+'Main CEA'!L206) -> 6478.2507 | M41: =M20*('Main CEA'!M58/SUM('Main CEA'!M58,'Main CEA'!M71))/(1+'Main CEA'!M206) -> 6060.8618 | N41: =N20*('Main CEA'!N58/SUM('Main CEA'!N58,'Main CEA'!N71))/(1+'Main CEA'!N206) -> 5515.6345 | O41: =O20*('Main CEA'!O58/SUM('Main CEA'!O58,'Main CEA'!O71))/(1+'Main CEA'!O206) -> 5120.1138 | P41: =P20*('Main CEA'!P58/SUM('Main CEA'!P58,'Main CEA'!P71))/(1+'Main CEA'!P206) -> 7336.7074 | ... AB41: =AB20*('Main CEA'!AB58/SUM('Main CEA'!AB58,'Main CEA'!AB71))/(1+'Main CEA'!AB206) -> 11912.212

Sheet Confidence intervals
F1: Malaria Consortium
F2: Burkina Faso | I2: Chad | L2: Côte d'Ivoire | O2: DRC | R2: DRC | U2: DRC | X2: DRC | AA2: Mozambique | AD2: Nigeria | AG2: Nigeria | AJ2: Nigeria | AM2: Nigeria | AP2: Nigeria | AS2: Nigeria | AV2: Nigeria | AY2: Nigeria | BB2: Nigeria | BE2: South Sudan | BH2: Togo | BK2: Uganda
A3: Simple CEA | O3: Haut-Katanga | R3: Haut-Lomami | U3: Lualaba | X3: Tanganyika | AA3: Nampula | AD3: Bauchi | AG3: Borno | AJ3: FCT (Abuja) | AM3: Kebbi | AP3: Kogi | AS3: Nasarawa | AV3: Oyo | AY3: Plateau | BB3: Sokoto | BE3: Northern Bahr El Ghazal | BK3: Karamoja
F4: 25th | G4: Best guess | H4: 75th | I4: 25th | J4: Best guess | K4: 75th | L4: 25th | M4: Best guess | N4: 75th | O4: 25th | P4: Best guess | Q4: 75th | R4: 25th | S4: Best guess | T4: 75th | U4: 25th | V4: Best guess | W4: 75th | X4: 25th | Y4: Best guess | Z4: 75th | AA4: 25th | AB4: Best guess | AC4: 75th | AD4: 25th | AE4: Best guess | AF4: 75th | AG4: 25th | AH4: Best guess | AI4: 75th | AJ4: 25th | AK4: Best guess | AL4: 75th | AM4: 25th | AN4: Best guess | AO4: 75th | AP4: 25th | AQ4: Best guess | AR4: 75th | AS4: 25th | AT4: Best guess | AU4: 75th | AV4: 25th | AW4: Best guess | AX4: 75th | AY4: 25th | AZ4: Best guess | BA4: 75th | BB4: 25th | BC4: Best guess | BD4: 75th | BE4: 25th | BF4: Best guess | BG4: 75th | BH4: 25th | BI4: Best guess | BJ4: 75th | BK4: 25th | BL4: Best guess | BM4: 75th
A5: Final cost-effectiveness estimate (pulled from "Main calcs" sheet) | F5: ='Main CEA'!I193 -> 13.310868 | I5: ='Main CEA'!J193 -> 14.65303 | L5: ='Main CEA'!K193 -> 8.5184856 | O5: ='Main CEA'!L193 -> 10.227025 | R5: ='Main CEA'!M193 -> 11.22453 | U5: ='Main CEA'!N193 -> 12.200271 | X5: ='Main CEA'!O193 -> 12.821222 | AA5: ='Main CEA'!P193 -> 8.7648405 | AD5: ='Main CEA'!Q193 -> 49.532027 | AG5: ='Main CEA'!R193 -> 55.534568 | AJ5: ='Main CEA'!S193 -> 14.612786 | AM5: ='Main CEA'!T193 -> 61.527366 | AP5: ='Main CEA'!U193 -> 27.73213 | AS5: ='Main CEA'!V193 -> 26.601019 | AV5: ='Main CEA'!W193 -> 16.516711 | AY5: ='Main CEA'!X193 -> 25.177662 | BB5: ='Main CEA'!Y193 -> 55.984468 | BE5: ='Main CEA'!Z193 -> 5.2303819 | BH5: ='Main CEA'!AA193 -> 8.0132386 | BK5: ='Main CEA'!AB193 -> 6.7780673
A6: Uncertainty level about each input
C8: Under-five mortality benefits
E9: Cost per person under age five reached | F9: -0.1 | G9: - | H9: 0.1 | I9: -0.2 | J9: - | K9: 0.2 | L9: -0.4 | M9: - | N9: 0.4 | O9: - | P9: - | Q9: - | R9: - | S9: - | T9: - | U9: - | V9: - | W9: - | X9: - | Y9: - | Z9: - | AA9: -0.3 | AB9: - | AC9: 0.3 | AD9: -0.3 | AE9: - | AF9: 0.3 | AG9: -0.3 | AH9: - | AI9: 0.3 | AJ9: -0.3 | AK9: - | AL9: 0.3 | AM9: -0.3 | AN9: - | AO9: 0.3 | AP9: -0.3 | AQ9: - | AR9: 0.3 | AS9: -0.3 | AT9: - | AU9: 0.3 | AV9: -0.3 | AW9: - | AX9: 0.3 | AY9: -0.3 | AZ9: - | BA9: 0.3 | BB9: -0.3 | BC9: - | BD9: 0.3 | BE9: -0.25 | BF9: - | BG9: 0.25 | BH9: -0.2 | BI9: - | BJ9: 0.2 | BK9: -0.35 | BL9: - | BM9: 0.35
E10: Malaria-attributable mortality rate among people under five | F10: -0.5 | G10: - | H10: 0.5 | I10: -0.7 | J10: - | K10: 0.7 | L10: -0.6 | M10: - | N10: 0.6 | O10: - | P10: - | Q10: - | R10: - | S10: - | T10: - | U10: - | V10: - | W10: - | X10: - | Y10: - | Z10: - | AA10: -0.5 | AB10: - | AC10: 0.5 | AD10: -0.65 | AE10: - | AF10: 0.65 | AG10: -0.5 | AH10: - | AI10: 0.5 | AJ10: -0.5 | AK10: - | AL10: 0.5 | AM10: -0.5 | AN10: - | AO10: 0.5 | AP10: -0.5 | AQ10: - | AR10: 0.5 | AS10: -0.5 | AT10: - | AU10: 0.5 | AV10: -0.5 | AW10: - | AX10: 0.5 | AY10: -0.5 | AZ10: - | BA10: 0.5 | BB10: -0.5 | BC10: - | BD10: 0.5 | BE10: -0.75 | BF10: - | BG10: 0.75 | BH10: -0.5 | BI10: - | BJ10: 0.5 | BK10: -0.6 | BL10: - | BM10: 0.6
