Workbook

Sheet Key
A1: Guide to interpreting this cost-effectiveness analysis
A2: Sheet descriptions
E4: Main CEA | F4: This sheet contains the primary calculations that result in final cost-effectiveness estimates. This sheet draws on inputs from the "Inputs" sheet and inputs calculated in the other supplemental sheets listed below.
E5: Aggregation across vaccines | F5: This sheet contains our calculations for pulling CEA parameters from other supplementary sheets and aggregating them across vaccines before entering them in the "Main CEA" sheet.
E6: Treatment effect | F6: This sheet contains our calculations of the effect of New Incentives' program on vaccine uptake.
E7: Disease burden | F7: This sheet contains our calculations of vaccine-preventable disease burden among New Incentives' target population.
E8: Vaccine coverage | F8: This sheet contains our calculations of baseline vaccination coverage among New Incentives' target population, as well as vaccination coverage among populations represented by GBD disease burden estimates.
E9: Vaccine efficacy | F9: This sheet contains our calculations of the effect of vaccination on disease incidence for each vaccine incentivized by New Incentives' program.
E10: Leverage/Funging | F10: This sheet contains our calculations of the impact that crowding in and crowding out funding by other contributors has on the benefits of the program.
E11: Inputs | F11: This sheet contains all of the manually entered input values informing the CEA, along with the sources and reasoning supporting them. This sheet also contains inputs sourced from the "GBD estimates" sheet.
E12: GBD estimates | F12: This sheet contains disease burden and population datasets downloaded from the Institute of Health Metrics (IHME)'s Global Burden of Disease (GBD) project.
E13: Simple CEA | F13: This sheet contains a simplified version of the CEA that is designed to be comparable to our CEAs of other programs.
E14: Confidence intervals | F14: This sheet contains our best guesses of the 25th and 75th percentile values for each of the parameters of our simple CEA.
E15: Sensitivity analysis | F15: This sheet contains the outputs of our sensitivity analysis that tests the cost-effectiveness ranges that would result from updating certain inputs to their 25th or 75th percentile values.
A17: Terminology key
C19: Terms specific to this CEA
E20: BCG vaccine | F20: The Bacillus Calmette-Guerin (BCG) vaccine is designed to prevent tuberculosis and other mycobacterial infections. BCG is one of the vaccines directly incentivized by New Incentives' program.
E21: Penta vaccine | F21: The pentavalent vaccine (referred to as Penta in this CEA) is a 5-in-1 vaccine that is designed to prevent diphtheria, pertussis, tetanus, hepatitis B, and H. influenza type B infections. Penta is one of the vaccines directly incentivized by New Incentives' program.
E22: DTP vaccine | F22: The DTP vaccine is designed to prevent diphtheria, pertussis, and tetanus. In Nigeria, the DTP vaccine is typically delivered as part of the Penta vaccine, which is one of the vaccines directly incentivized by New Incentives' program.
E23: Hib vaccine | F23: The HiB vaccine is designed to prevent H. influenzae type B (Hib) infections. In Nigeria, the Hib vaccine is typically delivered as part of the Penta vaccine, which is one of the vaccines directly incentivized by New Incentives' program.
E24: PCV vaccine | F24: The pneumococcal conjugate vaccine (PCV) is designed to prevent pneumococcal infections. PCV is one of the vaccines directly incentivized by New Incentives' program.
E25: Vaccine efficacy | F25: The efficacy rate of a vaccine refers to the reduction in vaccine-targeted disease incidence among people who receive the vaccine compared to those who do not receive the vaccine.
E26: Vaccine-preventable causes | F26: In this CEA, we use "vaccine-preventable causes" to refer to causes of disease incidence and mortality that are addressable by the specific set of vaccines directly incentivized by New Incentives' program.
E27: Vaccine-preventable mortalities | F27: In this CEA, we use "vaccine-preventable mortalities" to refer to mortalities that we expect would be averted if all children were fully vaccinated with the set of vaccines directly incentivized by New Incentives' program. Because vaccines are not 100% effective, the number of "vaccine-preventable mortalities" will always represent a subset of "mortalities from vaccine-preventable causes."
E28: MICS survey | F28: Multiple Indicator Cluster Surveys (MICS) are standardized household surveys implemented in many countries to collect data on a variety of indicators, including child vaccination rates.
C30: Terms used across GiveWell's CEAs
E31: Internal validity | F31: Describes an adjustment we make to the treatment effect of an intervention to account for the possibility that the treatment effects found in studies may not represent the true effect the intervention had on the populations studied.
E32: External validity | F32: Describes an adjustment we make to the treatment effect of an intervention to account for differences in the program implementation or populations treated in studies from the program implementation or populations treated by grantee programs.
E33: Leverage | F33: Describes a situation where a grantee's spending on a program causes other organizations or governments to contribute more to the program than they otherwise would have. In most cases, accounting for leverage increases cost-effectiveness
E34: Funging | F34: Describes a situation where a grantee's spending on a program causes other organizations or governments to contribute less to the program than they otherwise would have. In most cases, accounting for funging decreases cost-effectiveness.
E35: Counterfactual | F35: In most cases, describes the state of the world that would exist if we did not provide funding to a grantee for a program. When discussing the "counterfactual value of other actors' spending," we are referring to how much benefit another organization's or government's spending would generate if it were spent on something other than the grantee program.
E36: Moral weights | F36: To compare cost-effectiveness across different programs, we use ‘moral weights’ to quantify the benefits of different program impacts (e.g. increased income vs reduced deaths). We benchmark the value of each benefit to a value of 1, which we define as the value of doubling someone’s consumption for one year.
E37: Philanthropic actors | F37: Non-governmental organizations (NGOs) providing funding to philanthropic programs.
A39: Unit and source key
C41: Unit labels used in the CEA
E42: # | F42: Number
E43: per 1k | F43: Rate per 1,000
E44: per 100k | F44: Rate per 100,000
E45: $ | F45: U.S. dollars
E46: ln($) | F46: The natural logarithm of a monetary value
E47: % | F47: Percentage
E48: ppt | F48: Percentage points
E49: UoV | F49: Units of value: an arbitrary unit GiveWell uses to compare the moral value of different types of outcomes, such as saving lives or increasing income
E50: xbenchmark | F50: Cost-effectiveness in terms of multiples of GiveWell's benchmark
C52: Source labels used in the CEA
E54: Input | F54: A value pulled from the "Inputs" sheet
E55: Calc | F55: A value calculated using other values in the same sheet
E56: Supp | F56: A value pulled from one of the sheets hosting supplemental calculations
E57: Main | F57: A value pulled from the "Main CEA" sheet
E58: Feed | F58: A value pulled from an earlier section within the same sheet
A60: GiveWell analyses informing this model
C62: Analyses specific to this CEA
E63: GW's analysis of New Incentives cost per infant immunized
E64: GW's analysis of the biomarkers pilot results for Nigeria
E65: GW's analysis of self-report bias in vaccine coverage sources for New Incentives
E66: GW's analysis of disease etiology for lower respiratory infections and meningitis
E67: GW's analysis of average household size in Northwest Nigeria
E68: GW's analysis of post-program effects for New Incentives
E69: GW's analysis of vaccination coverage found in New Incentives' rapid assessments
C71: Analyses referenced across GiveWell's CEAs
E72: GW's moral weights and discount rate
E73: GW's supplemental intervention-level adjustments
E74: GW's write-up on treatment costs averted by health-improving interventions
E75: GWs benchmark for evaluating cost effectiveness
E76: GW's analysis of the counterfactual value of other actors' spending
E77: GW's analysis of the counterfactual value of Global Fund spending

Sheet Main CEA
I1: New Incentives – current states of operation | R1: New Incentives – prospective states | AF1: New Incentives – prospective states
I2: Nigeria | J2: Nigeria | K2: Nigeria | L2: Nigeria | M2: Nigeria | N2: Nigeria | O2: Nigeria | P2: Nigeria | Q2: Nigeria | R2: Nigeria | S2: Nigeria | T2: Nigeria | U2: Nigeria | V2: Nigeria | W2: Nigeria | X2: Nigeria | Y2: Nigeria | Z2: Nigeria | AA2: Nigeria | AB2: Nigeria | AC2: Nigeria | AD2: Nigeria | AE2: Nigeria | AF2: Nigeria | AG2: Nigeria | AH2: Nigeria | AI2: Nigeria | AJ2: Nigeria | AK2: Nigeria | AL2: Nigeria | AM2: Nigeria | AN2: Nigeria | AO2: Nigeria | AP2: Nigeria | AQ2: Nigeria | AR2: Nigeria | AS2: Nigeria | AT2: Nigeria | AU2: Nigeria | AV2: Nigeria
A3: Main calculations | F3: unit | G3: type | H3: Overall | I3: Bauchi | J3: Gombe | K3: Jigawa | L3: Kaduna - cohort 17 | M3: Kano | N3: Katsina | O3: Kebbi | P3: Sokoto | Q3: Zamfara | R3: Abia | S3: Adamawa | T3: Akwa Ibom | U3: Anambra | V3: Bayelsa | W3: Benue | X3: Borno | Y3: Cross River | Z3: Delta | AA3: Ebonyi | AB3: Edo | AC3: Ekiti | AD3: Enugu | AE3: FCT | AF3: Imo | AG3: Kaduna | AH3: Kogi | AI3: Kwara | AJ3: Lagos | AK3: Nasarawa | AL3: Niger | AM3: Niger - cohorts 32 & 36 | AN3: Niger - cohort 34 | AO3: Ogun | AP3: Ondo | AQ3: Osun | AR3: Oyo | AS3: Plateau | AT3: Rivers | AU3: Taraba | AV3: Yobe
E4: Final cost-effectiveness estimate (pulled from below for visibility) | F4: =F242 -> xbenchmark | G4: feed | H4: =H242 -> - | I4: =I242 -> 20.039606 | J4: =J242 -> 10.020838 | K4: =K242 -> 18.177505 | L4: =L242 -> 9.0027672 | M4: =M242 -> 12.612827 | N4: =N242 -> 16.809734 | O4: =O242 -> 29.037013 | ... AV4: =AV242 -> 11.471963
A5: Grantee costs
C7: GiveWell costs
E8: Grant size | F8: =Inputs!F8 -> $ | G8: =Inputs!G8 -> input | H8: =Inputs!H8 -> 1000000 | I8: =Inputs!I8 -> - | J8: =Inputs!J8 -> - | K8: =Inputs!K8 -> - | L8: =Inputs!L8 -> - | M8: =Inputs!M8 -> - | ... AV8: =Inputs!AV8 -> -
C10: Spending attributable to grantee
E11: Total spending contributed by grantee | F11: $ | G11: calc | H11: - | I11: =IF(I8="-",$H8,I8) -> 1000000 | J11: =IF(J8="-",$H8,J8) -> 1000000 | K11: =IF(K8="-",$H8,K8) -> 1000000 | L11: =IF(L8="-",$H8,L8) -> 1000000 | M11: =IF(M8="-",$H8,M8) -> 1000000 | N11: =IF(N8="-",$H8,N8) -> 1000000 | O11: =IF(O8="-",$H8,O8) -> 1000000 | P11: =IF(P8="-",$H8,P8) -> 1000000 | ... AV11: =IF(AV8="-",$H8,AV8) -> 1000000
C13: Cost per child enrolled
E14: Cost per infant enrolled in the program | F14: $ | G14: input | H14: =Inputs!H11 -> 16.26
E15: Adjustment for repeat enrollments | F15: % | G15: input | H15: =Inputs!H12 -> 0.107211
E16: Adjusted cost per infant enrolled in the program | F16: $ | G16: calc | H16: =H14/(1-H15) -> 18.21259 | I16: =Inputs!I11 -> - | J16: =Inputs!J11 -> - | K16: =Inputs!K11 -> - | L16: =Inputs!L11 -> - | M16: =Inputs!M11 -> - | N16: =Inputs!N11 -> - | O16: =Inputs!O11 -> - | P16: =Inputs!P11 -> - | ... AV16: =Inputs!AV11 -> -
A18: Outputs
C20: Total children enrolled
E21: Total children enrolled in the program | F21: # | G21: calc | H21: - | I21: =I11/$H16 -> 54907.073 | J21: =J11/$H16 -> 54907.073 | K21: =K11/$H16 -> 54907.073 | L21: =L11/$H16 -> 54907.073 | M21: =M11/$H16 -> 54907.073 | N21: =N11/$H16 -> 54907.073 | O21: =O11/$H16 -> 54907.073 | P21: =P11/$H16 -> 54907.073 | ... AV21: =AV11/$H16 -> 54907.073
C23: Counterfactual vaccination coverage
E24: Proportion of children in the target population who would be vaccinated in the absence of the program, aggregated across vaccines | F24: ='Aggregation across vaccines'!F36 -> % | G24: supp | H24: ='Aggregation across vaccines'!H36 -> - | I24: ='Aggregation across vaccines'!I42 -> 0.56315632 | J24: ='Aggregation across vaccines'!J42 -> 0.68255102 | K24: ='Aggregation across vaccines'!K42 -> 0.63869041 | L24: ='Aggregation across vaccines'!L42 -> 0.61022684 | M24: ='Aggregation across vaccines'!M42 -> 0.5925868 | N24: ='Aggregation across vaccines'!N42 -> 0.55620425 | O24: ='Aggregation across vaccines'!O42 -> 0.42892733 | P24: ='Aggregation across vaccines'!P42 -> 0.38889499 | ... AV24: ='Aggregation across vaccines'!AV42 -> 0.62035872
E25: Corresponding proportion of children who would not be vaccinated in the absence of the program, aggregated across incentivized vaccines | F25: % | G25: calc | H25: - | I25: =1-I24 -> 0.43684368 | J25: =1-J24 -> 0.31744898 | K25: =1-K24 -> 0.36130959 | L25: =1-L24 -> 0.38977316 | M25: =1-M24 -> 0.4074132 | N25: =1-N24 -> 0.44379575 | O25: =1-O24 -> 0.57107267 | P25: =1-P24 -> 0.61110501 | ... AV25: =1-AV24 -> 0.37964128
C27: Effect of the program on vaccination coverage
E28: Reduction in the proportion of children who are unvaccinated as a result of New Incentives' program, based on GW's analysis of the New Incentives RCT, aggregated across vaccines | F28: ='Treatment effect'!F71 -> % | G28: supp | H28: ='Treatment effect'!H84 -> 0.33303026 | I28: ='Treatment effect'!I71 -> - | J28: ='Treatment effect'!J71 -> - | K28: ='Treatment effect'!K71 -> - | L28: ='Treatment effect'!L71 -> - | M28: ='Treatment effect'!M71 -> - | N28: ='Treatment effect'!N71 -> - | O28: ='Treatment effect'!O71 -> - | P28: ='Treatment effect'!P71 -> - | ... AV28: ='Treatment effect'!AV71 -> -
E29: Internal validity adjustment | F29: =Inputs!F236 -> % | G29: =Inputs!G236 -> input | H29: =Inputs!H236 -> -0.12 | I29: =Inputs!I236 -> - | J29: =Inputs!J236 -> - | K29: =Inputs!K236 -> - | L29: =Inputs!L236 -> - | M29: =Inputs!M236 -> - | ... AV29: =Inputs!AV236 -> -
E30: Reduction in the proportion of children who are unvaccinated as a result of New Incentives' program | F30: % | G30: calc | H30: =H28*(1+H29) -> 0.29306663 | I30: - | J30: - | K30: - | L30: - | M30: - | N30: - | O30: - | P30: - | R30: - | S30: - | T30: - | U30: - | V30: - | W30: - | X30: - | Y30: - | Z30: - | AA30: - | AB30: - | AC30: - | AD30: - | AE30: - | AF30: - | AG30: - | AH30: - | AI30: - | AJ30: - | AK30: - | AL30: - | AM30: - | AN30: - | AO30: - | AP30: - | AQ30: - | AR30: - | AS30: - | AT30: - | AU30: - | AV30: -
E31: Corresponding increase in the proportion of children who are vaccinated as a result of New Incentives' program | F31: ppt | G31: calc | H31: - | I31: =I25*$H30 -> 0.12802431 | J31: =J25*$H30 -> 0.093033702 | K31: =K25*$H30 -> 0.10588779 | L31: =L25*$H30 -> 0.11422951 | M31: =M25*$H30 -> 0.11939921 | N31: =N25*$H30 -> 0.13006173 | O31: =O25*$H30 -> 0.16736235 | P31: =P25*$H30 -> 0.17909449 | ... AV31: =AV25*$H30 -> 0.11126019
E32: Total proportion of children in the target population who are vaccinated | F32: % | G32: calc | H32: - | I32: =I24+I31 -> 0.69118063 | J32: =J24+J31 -> 0.77558473 | K32: =K24+K31 -> 0.74457819 | L32: =L24+L31 -> 0.72445635 | M32: =M24+M31 -> 0.71198602 | N32: =N24+N31 -> 0.68626598 | O32: =O24+O31 -> 0.59628967 | P32: =P24+P31 -> 0.56798948 | ... AV32: =AV24+AV31 -> 0.73161891
C34: Number of children vaccinated as a result of New Incentives' program
E35: Children in the target population | F35: # | G35: calc | H35: - | I35: =I21/I32 -> 79439.542 | J35: =J21/J32 -> 70794.422 | K35: =K21/K32 -> 73742.52 | L35: =L21/L32 -> 75790.726 | M35: =M21/M32 -> 77118.189 | N35: =N21/N32 -> 80008.444 | O35: =O21/O32 -> 92081.207 | P35: =P21/P32 -> 96669.172 | ... AV35: =AV21/AV32 -> 75048.733
E36: Children counterfactually vaccinated | F36: # | G36: calc | H36: - | I36: =I35*I31 -> 10170.192 | J36: =J35*J31 -> 6586.2672 | K36: =K35*K31 -> 7808.4321 | L36: =L35*L31 -> 8657.5374 | M36: =M35*M31 -> 9207.8511 | N36: =N35*N31 -> 10406.036 | O36: =O35*O31 -> 15410.927 | P36: =P35*P31 -> 17312.916 | ... AV36: =AV35*AV31 -> 8349.9364
A38: Outcomes
C40: Mortality reduction among people under age 5
E41: Probability that a person will die of a vaccine-preventable cause before reaching age 5, adjusted for deaths occurring before the age of vaccination | F41: ='Disease burden'!F184 -> % | G41: supp | H41: ='Disease burden'!H184 -> - | I41: ='Disease burden'!I184 -> 0.027625565 | J41: ='Disease burden'!J184 -> 0.01953192 | K41: ='Disease burden'!K184 -> 0.027236652 | L41: ='Disease burden'!L184 -> 0.011660475 | M41: ='Disease burden'!M184 -> 0.018680701 | N41: ='Disease burden'!N184 -> 0.020226729 | O41: ='Disease burden'!O184 -> 0.021982759 | ... AV41: ='Disease burden'!AV184 -> 0.014629881
E42: Proportion of people under age 5 represented in GBD 2021 disease burden estimates who were vaccinated, aggregated across vaccines | F42: ='Aggregation across vaccines'!F74 -> % | G42: supp | H42: ='Aggregation across vaccines'!H74 -> - | I42: ='Aggregation across vaccines'!I74 -> 0.27723536 | J42: ='Aggregation across vaccines'!J74 -> 0.35272184 | K42: ='Aggregation across vaccines'!K74 -> 0.44729281 | L42: ='Aggregation across vaccines'!L74 -> 0.51957609 | M42: ='Aggregation across vaccines'!M74 -> 0.35511405 | N42: ='Aggregation across vaccines'!N74 -> 0.35528503 | O42: ='Aggregation across vaccines'!O74 -> 0.44566539 | ... AV42: ='Aggregation across vaccines'!AV74 -> 0.55188809
E43: Proportion of vaccine-preventable disease incidence averted by full vaccination among people under age 5, aggregated across vaccines | F43: ='Aggregation across vaccines'!F63 -> % | G43: supp | H43: ='Aggregation across vaccines'!H63 -> - | I43: ='Aggregation across vaccines'!I63 -> 0.52255605 | J43: ='Aggregation across vaccines'!J63 -> 0.52738394 | K43: ='Aggregation across vaccines'!K63 -> 0.5508425 | L43: ='Aggregation across vaccines'!L63 -> 0.54371205 | M43: ='Aggregation across vaccines'!M63 -> 0.51595309 | N43: ='Aggregation across vaccines'!N63 -> 0.54582208 | O43: ='Aggregation across vaccines'!O63 -> 0.55824395 | ... AV43: ='Aggregation across vaccines'!AV63 -> 0.57218524
E44: Probability that an unvaccinated person will die of a vaccine-preventable cause before reaching age 5, adjusted for deaths occurring before the age of vaccination | F44: ='Disease burden'!F209 -> % | G44: calc | H44: ='Disease burden'!H209 -> - | I44: =I41/((1-I42)+(I42*(1-I43))) -> 0.032305729 | J44: =J41/((1-J42)+(J42*(1-J43))) -> 0.023995572 | K44: =K41/((1-K42)+(K42*(1-K43))) -> 0.036141473 | L44: =L41/((1-L42)+(L42*(1-L43))) -> 0.016251528 | M44: =M41/((1-M42)+(M42*(1-M43))) -> 0.022871215 | N44: =N41/((1-N42)+(N42*(1-N43))) -> 0.025092782 | O44: =O41/((1-O42)+(O42*(1-O43))) -> 0.029263135 | P44: =P41/((1-P42)+(P42*(1-P43))) -> 0.036347232 | ... AV44: =AV41/((1-AV42)+(AV42*(1-AV43))) -> 0.021381907
E45: Mortalities indirectly attributable to vaccine-preventable disease per mortality directly caused by vaccine-preventable disease | F45: =Inputs!F241 -> % | G45: =Inputs!G241 -> input | H45: =Inputs!H241 -> 0.75 | I45: =Inputs!I241 -> - | J45: =Inputs!J241 -> - | K45: =Inputs!K241 -> - | L45: =Inputs!L241 -> - | M45: =Inputs!M241 -> - | ... AV45: =Inputs!AV241 -> -
E46: Probability that an unvaccinated person will die of a vaccine-preventable cause before reaching age 5, including mortalities indirectly attributable to vaccine-preventable disease | F46: % | G46: calc | H46: - | I46: =I44*(1+$H45) -> 0.056535025 | J46: =J44*(1+$H45) -> 0.041992252 | K46: =K44*(1+$H45) -> 0.063247578 | L46: =L44*(1+$H45) -> 0.028440174 | M46: =M44*(1+$H45) -> 0.040024626 | N46: =N44*(1+$H45) -> 0.043912369 | O46: =O44*(1+$H45) -> 0.051210486 | P46: =P44*(1+$H45) -> 0.063607657 | ... AV46: =AV44*(1+$H45) -> 0.037418337
E47: Ratio of the reduction in vaccine-preventable disease mortality to the reduction in vaccine-preventable disease incidence | F47: =Inputs!F242 -> % | G47: =Inputs!G242 -> input | H47: =Inputs!H242 -> 1 | I47: =Inputs!I242 -> - | J47: =Inputs!J242 -> - | K47: =Inputs!K242 -> - | L47: =Inputs!L242 -> - | M47: =Inputs!M242 -> - | ... AV47: =Inputs!AV242 -> -
E48: Total deaths averted among people under age 5 | F48: # | G48: calc | H48: - | I48: =I36*I43*I46*$H47 -> 300.45514 | J48: =J36*J43*J46*$H47 -> 145.85973 | K48: =K36*K43*K46*$H47 -> 272.04151 | L48: =L36*L43*L46*$H47 -> 133.8738 | M48: =M36*M43*M46*$H47 -> 190.14977 | N48: =N36*N43*N46*$H47 -> 249.41542 | O48: =O36*O43*O46*$H47 -> 440.56671 | P48: =P36*P43*P46*$H47 -> 583.66726 | ... AV48: =AV36*AV43*AV46*$H47 -> 178.77398
C50: Mortality reduction among people age 5 through age 14
E51: Probability that a 5-year-old will die of a vaccine-preventable cause before reaching age 15 | F51: ='Disease burden'!F229 -> % | G51: supp | H51: ='Disease burden'!H229 -> - | I51: ='Disease burden'!I229 -> 0.0022627988 | J51: ='Disease burden'!J229 -> 0.0015769754 | K51: ='Disease burden'!K229 -> 0.0022646562 | L51: ='Disease burden'!L229 -> 0.0010096079 | M51: ='Disease burden'!M229 -> 0.0015299464 | N51: ='Disease burden'!N229 -> 0.0018337091 | O51: ='Disease burden'!O229 -> 0.0020464817 | ... AV51: ='Disease burden'!AV229 -> 0.0016231791
E52: Proportion of 5-14-year-olds represented in GBD 2021 disease burden estimates who were vaccinated, aggregated across vaccines | F52: ='Aggregation across vaccines'!F107 -> % | G52: supp | H52: ='Aggregation across vaccines'!H107 -> - | I52: ='Aggregation across vaccines'!I107 -> 0.16095182 | J52: ='Aggregation across vaccines'!J107 -> 0.20467257 | K52: ='Aggregation across vaccines'!K107 -> 0.25310031 | L52: ='Aggregation across vaccines'!L107 -> 0.29641914 | M52: ='Aggregation across vaccines'!M107 -> 0.21515189 | N52: ='Aggregation across vaccines'!N107 -> 0.2046454 | O52: ='Aggregation across vaccines'!O107 -> 0.25298993 | ... AV52: ='Aggregation across vaccines'!AV107 -> 0.29552562
E53: Proportion of vaccine-preventable disease incidence averted by full vaccination among 5-14-year-olds, aggregated across vaccines | F53: ='Aggregation across vaccines'!F95 -> % | G53: supp | H53: ='Aggregation across vaccines'!H95 -> - | I53: ='Aggregation across vaccines'!I95 -> 0.51002221 | J53: ='Aggregation across vaccines'!J95 -> 0.51145525 | K53: ='Aggregation across vaccines'!K95 -> 0.53288509 | L53: ='Aggregation across vaccines'!L95 -> 0.52861066 | M53: ='Aggregation across vaccines'!M95 -> 0.499694 | N53: ='Aggregation across vaccines'!N95 -> 0.52907241 | O53: ='Aggregation across vaccines'!O95 -> 0.53788474 | ... AV53: ='Aggregation across vaccines'!AV95 -> 0.5210026
E54: Probability that an unvaccinated 5-year-old will die of a vaccine-preventable cause before reaching age 15 | F54: ='Disease burden'!F255 -> % | G54: calc | H54: ='Disease burden'!H255 -> - | I54: =I51/((1-I52)+(I52*(1-I53))) -> 0.0024651615 | J54: =J51/((1-J52)+(J52*(1-J53))) -> 0.0017613556 | K54: =K51/((1-K52)+(K52*(1-K53))) -> 0.0026177165 | L54: =L51/((1-L52)+(L52*(1-L53))) -> 0.0011971971 | M54: =M51/((1-M52)+(M52*(1-M53))) -> 0.0017142451 | N54: =N51/((1-N52)+(N52*(1-N53))) -> 0.0020563553 | O54: =O51/((1-O52)+(O52*(1-O53))) -> 0.0023688308 | P54: =P51/((1-P52)+(P52*(1-P53))) -> 0.002922449 | ... AV54: =AV51/((1-AV52)+(AV52*(1-AV53))) -> 0.0019185825
E55: Mortalities indirectly attributable to vaccine-preventable disease per mortality directly caused by vaccine-preventable disease | F55: =Inputs!F241 -> % | G55: =Inputs!G241 -> input | H55: =Inputs!H241 -> 0.75 | I55: =Inputs!I241 -> - | J55: =Inputs!J241 -> - | K55: =Inputs!K241 -> - | L55: =Inputs!L241 -> - | M55: =Inputs!M241 -> - | ... AV55: =Inputs!AV241 -> -
E56: Probability that an unvaccinated 5-year-old will die of a vaccine-preventable cause before reaching age 15, including mortalities indirectly attributable to vaccine-preventable disease | F56: % | G56: calc | H56: - | I56: =I54*(1+$H55) -> 0.0043140326 | J56: =J54*(1+$H55) -> 0.0030823723 | K56: =K54*(1+$H55) -> 0.0045810038 | L56: =L54*(1+$H55) -> 0.002095095 | M56: =M54*(1+$H55) -> 0.0029999288 | N56: =N54*(1+$H55) -> 0.0035986218 | O56: =O54*(1+$H55) -> 0.004145454 | P56: =P54*(1+$H55) -> 0.0051142857 | ... AV56: =AV54*(1+$H55) -> 0.0033575194
E57: Ratio of the reduction in vaccine-preventable disease mortality to the reduction in vaccine-preventable disease incidence | F57: =Inputs!F242 -> % | G57: =Inputs!G242 -> input | H57: =Inputs!H242 -> 1 | I57: =Inputs!I242 -> - | J57: =Inputs!J242 -> - | K57: =Inputs!K242 -> - | L57: =Inputs!L242 -> - | M57: =Inputs!M242 -> - | ... AV57: =Inputs!AV242 -> -
E58: Deaths averted among people age 5 through 14 | F58: # | G58: calc | H58: - | I58: =I$36*I53*I56*$H57 -> 22.37699 | J58: =J$36*J53*J56*$H57 -> 10.38322 | K58: =K$36*K53*K56*$H57 -> 19.061543 | L58: =L$36*L53*L56*$H57 -> 9.5881321 | M58: =M$36*M53*M56*$H57 -> 13.802997 | N58: =N$36*N53*N56*$H57 -> 19.81238 | O58: =O$36*O53*O56*$H57 -> 34.362921 | P58: =P$36*P53*P56*$H57 -> 46.963983 | ... AV58: =AV$36*AV53*AV56*$H57 -> 14.606346
E59: Discount rate for deaths averted in the future | F59: =Inputs!F$245 -> % | G59: =Inputs!G$245 -> input | H59: =Inputs!H$245 -> 0.005 | I59: =Inputs!I$245 -> - | J59: =Inputs!J$245 -> - | K59: =Inputs!K$245 -> - | L59: =Inputs!L$245 -> - | M59: =Inputs!M$245 -> - | ... AV59: =Inputs!AV$245 -> -
E60: Average years between vaccination and a mortality occuring among 5-15-year-olds | F60: =Inputs!F246 -> # | G60: =Inputs!G246 -> input | H60: =Inputs!H246 -> 10 | I60: =Inputs!I246 -> - | J60: =Inputs!J246 -> - | K60: =Inputs!K246 -> - | L60: =Inputs!L246 -> - | M60: =Inputs!M246 -> - | ... AW60: =Inputs!AW246
E61: Discounted deaths averted among people age 5 through age 14 | F61: # | G61: calc | H61: - | I61: =I58*((1/(1+$H59))^$H60) -> 21.288304 | J61: =J58*((1/(1+$H59))^$H60) -> 9.8780553 | K61: =K58*((1/(1+$H59))^$H60) -> 18.13416 | L61: =L58*((1/(1+$H59))^$H60) -> 9.1216498 | M61: =M58*((1/(1+$H59))^$H60) -> 13.131452 | N61: =N58*((1/(1+$H59))^$H60) -> 18.848467 | O61: =O58*((1/(1+$H59))^$H60) -> 32.691094 | P61: =P58*((1/(1+$H59))^$H60) -> 44.679088 | ... AV61: =AV58*((1/(1+$H59))^$H60) -> 13.895717
C63: Mortality reduction among people age 15 through age 49
E64: Probability that a 15-year-old will die of a vaccine-preventable cause before reaching age 50 | F64: ='Disease burden'!F273 -> % | G64: supp | H64: ='Disease burden'!H273 -> - | I64: ='Disease burden'!I273 -> 0.0076770019 | J64: ='Disease burden'!J273 -> 0.0045563964 | K64: ='Disease burden'!K273 -> 0.0087317319 | L64: ='Disease burden'!L273 -> 0.0033256077 | M64: ='Disease burden'!M273 -> 0.0042720825 | N64: ='Disease burden'!N273 -> 0.0071748789 | O64: ='Disease burden'!O273 -> 0.0076864641 | ... AV64: ='Disease burden'!AV273 -> 0.0072054259
E65: Proportion of 15-49-year-olds represented in GBD 2021 disease burden estimates who were vaccinated, aggregated across vaccines | F65: ='Aggregation across vaccines'!F138 -> % | G65: supp | H65: ='Aggregation across vaccines'!H138 -> - | I65: ='Aggregation across vaccines'!I138 -> 0.063412936 | J65: ='Aggregation across vaccines'!J138 -> 0.079364607 | K65: ='Aggregation across vaccines'!K138 -> 0.095190965 | L65: ='Aggregation across vaccines'!L138 -> 0.11521307 | M65: ='Aggregation across vaccines'!M138 -> 0.084170302 | N65: ='Aggregation across vaccines'!N138 -> 0.07821503 | O65: ='Aggregation across vaccines'!O138 -> 0.090792531 | ... AV65: ='Aggregation across vaccines'!AV138 -> 0.10622635
E66: Proportion of vaccine-preventable disease incidence averted by full vaccination among 15-49-year-olds, aggregated across vaccines | F66: ='Aggregation across vaccines'!F126 -> % | G66: supp | H66: ='Aggregation across vaccines'!H126 -> - | I66: ='Aggregation across vaccines'!I126 -> 0.17297722 | J66: ='Aggregation across vaccines'!J126 -> 0.18022572 | K66: ='Aggregation across vaccines'!K126 -> 0.16854546 | L66: ='Aggregation across vaccines'!L126 -> 0.18462628 | M66: ='Aggregation across vaccines'!M126 -> 0.17820576 | N66: ='Aggregation across vaccines'!N126 -> 0.17127971 | O66: ='Aggregation across vaccines'!O126 -> 0.17276553 | ... AV66: ='Aggregation across vaccines'!AV126 -> 0.1740227
E67: Probability that an unvaccinated 15-year-old will die of a vaccine-preventable cause before reaching age 50 | F67: ='Disease burden'!F300 -> % | G67: calc | H67: ='Disease burden'!H300 -> - | I67: =I64/((1-I65)+(I65*(1-I66))) -> 0.0077621448 | J67: =J64/((1-J65)+(J65*(1-J66))) -> 0.0046225148 | K67: =K64/((1-K65)+(K65*(1-K66))) -> 0.0088741081 | L67: =L64/((1-L65)+(L65*(1-L66))) -> 0.0033978854 | M67: =M64/((1-M65)+(M65*(1-M66))) -> 0.004337138 | N67: =N64/((1-N65)+(N65*(1-N66))) -> 0.0072723034 | O67: =O64/((1-O65)+(O65*(1-O66))) -> 0.0078089539 | P67: =P64/((1-P65)+(P65*(1-P66))) -> 0.010530841 | ... AV67: =AV64/((1-AV65)+(AV65*(1-AV66))) -> 0.0073411326
E68: Mortalities indirectly attributable to vaccine-preventable disease per mortality directly caused by vaccine-preventable disease | F68: =Inputs!F241 -> % | G68: =Inputs!G241 -> input | H68: =Inputs!H241 -> 0.75 | I68: =Inputs!I241 -> - | J68: =Inputs!J241 -> - | K68: =Inputs!K241 -> - | L68: =Inputs!L241 -> - | M68: =Inputs!M241 -> - | ... AV68: =Inputs!AV241 -> -
E69: Probability that an unvaccinated 15-year-old will die of a vaccine-preventable cause before reaching age 50, including mortalities indirectly attributable to vaccine-preventable disease | F69: % | G69: calc | H69: - | I69: =I67*(1+$H68) -> 0.013583753 | J69: =J67*(1+$H68) -> 0.0080894009 | K69: =K67*(1+$H68) -> 0.015529689 | L69: =L67*(1+$H68) -> 0.0059462994 | M69: =M67*(1+$H68) -> 0.0075899915 | N69: =N67*(1+$H68) -> 0.012726531 | O69: =O67*(1+$H68) -> 0.013665669 | P69: =P67*(1+$H68) -> 0.018428971 | ... AV69: =AV67*(1+$H68) -> 0.012846982
E70: Ratio of the reduction in vaccine-preventable disease mortality to the reduction in vaccine-preventable disease incidence | F70: =Inputs!F242 -> % | G70: =Inputs!G242 -> input | H70: =Inputs!H242 -> 1 | I70: =Inputs!I242 -> - | J70: =Inputs!J242 -> - | K70: =Inputs!K242 -> - | L70: =Inputs!L242 -> - | M70: =Inputs!M242 -> - | ... AV70: =Inputs!AV242 -> -
E71: Deaths averted among people age 15 through 49 | F71: # | G71: calc | H71: - | I71: =I$36*I66*I69*$H70 -> 23.896697 | J71: =J$36*J66*J69*$H70 -> 9.6022383 | K71: =K$36*K66*K69*$H70 -> 20.438248 | L71: =L$36*L66*L69*$H70 -> 9.504618 | M71: =M$36*M66*M69*$H70 -> 12.454357 | N71: =N$36*N66*N69*$H70 -> 22.683041 | O71: =O$36*O66*O69*$H70 -> 36.384529 | P71: =P$36*P66*P69*$H70 -> 54.912895 | ... AV71: =AV$36*AV66*AV69*$H70 -> 18.667673
E72: Discount rate for deaths averted in the future | F72: =Inputs!F$245 -> % | G72: =Inputs!G$245 -> input | H72: =Inputs!H$245 -> 0.005 | I72: =Inputs!I$245 -> - | J72: =Inputs!J$245 -> - | K72: =Inputs!K$245 -> - | L72: =Inputs!L$245 -> - | M72: =Inputs!M$245 -> - | ... AV72: =Inputs!AV$245 -> -
E73: Average years between vaccination and a mortality occuring among 15-49-year-olds | F73: =Inputs!F247 -> # | G73: =Inputs!G247 -> input | H73: =Inputs!H247 -> 32.5 | I73: =Inputs!I247 -> - | J73: =Inputs!J247 -> - | K73: =Inputs!K247 -> - | L73: =Inputs!L247 -> - | M73: =Inputs!M247 -> - | ... AV73: =Inputs!AV247 -> -
E74: Discounted deaths averted among people age 15 through age 49 | F74: # | G74: calc | H74: - | I74: =I71*((1/(1+$H72))^$H73) -> 20.320803 | J74: =J71*((1/(1+$H72))^$H73) -> 8.1653626 | K74: =K71*((1/(1+$H72))^$H73) -> 17.379875 | L74: =L71*((1/(1+$H72))^$H73) -> 8.0823501 | M74: =M71*((1/(1+$H72))^$H73) -> 10.590691 | N74: =N71*((1/(1+$H72))^$H73) -> 19.288758 | O74: =O71*((1/(1+$H72))^$H73) -> 30.93996 | P74: =P71*((1/(1+$H72))^$H73) -> 46.695748 | ... AV74: =AV71*((1/(1+$H72))^$H73) -> 15.874248
C76: Mortality reduction among people age 50 through age 74
E77: Probability that a 50-year-old will die of a vaccine-preventable cause before reaching age 75 | F77: ='Disease burden'!F318 -> % | G77: supp | H77: ='Disease burden'!H318 -> - | I77: ='Disease burden'!I318 -> 0.030453122 | J77: ='Disease burden'!J318 -> 0.021070266 | K77: ='Disease burden'!K318 -> 0.029971369 | L77: ='Disease burden'!L318 -> 0.011857912 | M77: ='Disease burden'!M318 -> 0.015928611 | N77: ='Disease burden'!N318 -> 0.025887607 | O77: ='Disease burden'!O318 -> 0.032083285 | ... AV77: ='Disease burden'!AV318 -> 0.026943216
E78: Proportion of 50-74-year-olds represented in GBD 2021 disease burden estimates who were vaccinated, aggregated across vaccines | F78: ='Aggregation across vaccines'!F169 -> % | G78: supp | H78: ='Aggregation across vaccines'!H169 -> - | I78: ='Aggregation across vaccines'!I169 -> 0.030777325 | J78: ='Aggregation across vaccines'!J169 -> 0.037001506 | K78: ='Aggregation across vaccines'!K169 -> 0.045948837 | L78: ='Aggregation across vaccines'!L169 -> 0.056359847 | M78: ='Aggregation across vaccines'!M169 -> 0.040889242 | N78: ='Aggregation across vaccines'!N169 -> 0.037726383 | O78: ='Aggregation across vaccines'!O169 -> 0.042933084 | ... AV78: ='Aggregation across vaccines'!AV169 -> 0.050794819
E79: Proportion of vaccine-preventable disease incidence averted by full vaccination among 50-74-year-olds, aggregated across vaccines | F79: ='Aggregation across vaccines'!F157 -> % | G79: supp | H79: ='Aggregation across vaccines'!H157 -> - | I79: ='Aggregation across vaccines'!I157 -> 0.084921182 | J79: ='Aggregation across vaccines'!J157 -> 0.09081765 | K79: ='Aggregation across vaccines'!K157 -> 0.081752874 | L79: ='Aggregation across vaccines'!L157 -> 0.090519237 | M79: ='Aggregation across vaccines'!M157 -> 0.087900618 | N79: ='Aggregation across vaccines'!N157 -> 0.083869208 | O79: ='Aggregation across vaccines'!O157 -> 0.084496535 | ... AV79: ='Aggregation across vaccines'!AV157 -> 0.08494775
E80: Probability that an unvaccinated 50-year-old will die of a vaccine-preventable cause before reaching age 75 | F80: ='Disease burden'!F345 -> % | G80: calc | H80: ='Disease burden'!H345 -> - | I80: =I77/((1-I78)+(I78*(1-I79))) -> 0.030532924 | J80: =J77/((1-J78)+(J78*(1-J79))) -> 0.02114131 | K80: =K77/((1-K78)+(K78*(1-K79))) -> 0.03008438 | L80: =L77/((1-L78)+(L78*(1-L79))) -> 0.011918717 | M80: =M77/((1-M78)+(M78*(1-M79))) -> 0.015986068 | N80: =N77/((1-N78)+(N78*(1-N79))) -> 0.025969777 | O80: =O77/((1-O78)+(O78*(1-O79))) -> 0.032200097 | P80: =P77/((1-P78)+(P78*(1-P79))) -> 0.03301705 | ... AV80: =AV77/((1-AV78)+(AV78*(1-AV79))) -> 0.027059978
E81: Mortalities indirectly attributable to vaccine-preventable disease per mortality directly caused by vaccine-preventable disease | F81: =Inputs!F241 -> % | G81: =Inputs!G241 -> input | H81: =Inputs!H241 -> 0.75 | I81: =Inputs!I241 -> - | J81: =Inputs!J241 -> - | K81: =Inputs!K241 -> - | L81: =Inputs!L241 -> - | M81: =Inputs!M241 -> - | ... AV81: =Inputs!AV241 -> -
E82: Probability that an unvaccinated 50-year-old will die of a vaccine-preventable cause before reaching age 75, including mortalities indirectly attributable to vaccine-preventable disease | F82: % | G82: calc | H82: - | I82: =I80*(1+$H81) -> 0.053432617 | J82: =J80*(1+$H81) -> 0.036997292 | K82: =K80*(1+$H81) -> 0.052647665 | L82: =L80*(1+$H81) -> 0.020857754 | M82: =M80*(1+$H81) -> 0.027975618 | N82: =N80*(1+$H81) -> 0.04544711 | O82: =O80*(1+$H81) -> 0.05635017 | P82: =P80*(1+$H81) -> 0.057779837 | ... AV82: =AV80*(1+$H81) -> 0.047354961
E83: Ratio of the reduction in vaccine-preventable disease mortality to the reduction in vaccine-preventable disease incidence | F83: =Inputs!F242 -> % | G83: =Inputs!G242 -> input | H83: =Inputs!H242 -> 1 | I83: =Inputs!I242 -> - | J83: =Inputs!J242 -> - | K83: =Inputs!K242 -> - | L83: =Inputs!L242 -> - | M83: =Inputs!M242 -> - | ... AV83: =Inputs!AV242 -> -
E84: Deaths averted among people age 50 through 74 | F84: # | G84: calc | H84: - | I84: =I$36*I79*I82*$H83 -> 46.147868 | J84: =J$36*J79*J82*$H83 -> 22.129905 | K84: =K$36*K79*K82*$H83 -> 33.608256 | L84: =L$36*L79*L82*$H83 -> 16.345673 | M84: =M$36*M79*M82*$H83 -> 22.642789 | N84: =N$36*N79*N82*$H83 -> 39.663785 | O84: =O$36*O79*O82*$H83 -> 73.377496 | P84: =P$36*P79*P82*$H83 -> 83.318231 | ... AV84: =AV$36*AV79*AV82*$H83 -> 33.589267
E85: Discount rate for deaths averted in the future | F85: =Inputs!F$245 -> % | G85: =Inputs!G$245 -> input | H85: =Inputs!H$245 -> 0.005 | I85: =Inputs!I$245 -> - | J85: =Inputs!J$245 -> - | K85: =Inputs!K$245 -> - | L85: =Inputs!L$245 -> - | M85: =Inputs!M$245 -> - | ... AV85: =Inputs!AV$245 -> -
E86: Average years between vaccination and a mortality occuring among 50-74-year-olds | F86: =Inputs!F248 -> # | G86: =Inputs!G248 -> input | H86: =Inputs!H248 -> 62.5 | I86: =Inputs!I248 -> - | J86: =Inputs!J248 -> - | K86: =Inputs!K248 -> - | L86: =Inputs!L248 -> - | M86: =Inputs!M248 -> - | ... AV86: =Inputs!AV248 -> -
E87: Discounted deaths averted among people age 50 through age 74 | F87: # | G87: calc | H87: - | I87: =I84*((1/(1+$H85))^$H86) -> 33.788801 | J87: =J84*((1/(1+$H85))^$H86) -> 16.203196 | K87: =K84*((1/(1+$H85))^$H86) -> 24.607479 | L87: =L84*((1/(1+$H85))^$H86) -> 11.968065 | M87: =M84*((1/(1+$H85))^$H86) -> 16.578722 | N87: =N84*((1/(1+$H85))^$H86) -> 29.041249 | O87: =O84*((1/(1+$H85))^$H86) -> 53.725941 | P87: =P84*((1/(1+$H85))^$H86) -> 61.004403 | ... AV87: =AV84*((1/(1+$H85))^$H86) -> 24.593575
C89: Long-term income increases
E90: Ratio of value generated from income increases to value generated from mortalities averted among people under age 15 by seasonal malaria chemoprevention (SMC) | F90: =Inputs!F251 -> # | G90: =Inputs!G251 -> input | H90: =Inputs!H251 -> 0.30647 | I90: =Inputs!I251 -> - | J90: =Inputs!J251 -> - | K90: =Inputs!K251 -> - | L90: =Inputs!L251 -> - | M90: =Inputs!M251 -> - | ... AV90: =Inputs!AV251 -> -
E91: Adjustment for income increases generated by New Incentives' program compared to SMC | F91: =Inputs!F252 -> % | G91: =Inputs!G252 -> input | H91: =Inputs!H252 -> 0 | I91: =Inputs!I252 -> - | J91: =Inputs!J252 -> - | K91: =Inputs!K252 -> - | L91: =Inputs!L252 -> - | M91: =Inputs!M252 -> - | ... AV91: =Inputs!AV252 -> -
E92: Ratio of value generated from income increases to value generated from mortalities averted among people under age 15 by New Incentives' program | F92: # | G92: calc | H92: =H90*(1+H91) -> 0.30647 | I92: - | J92: - | K92: - | L92: - | M92: - | N92: - | O92: - | P92: - | Q92: - | R92: - | S92: - | T92: - | U92: - | V92: - | W92: - | X92: - | Y92: - | Z92: - | AA92: - | AB92: - | AC92: - | AD92: - | AE92: - | AF92: - | AG92: - | AH92: - | AI92: - | AJ92: - | AK92: - | AL92: - | AM92: - | AN92: - | AO92: - | AP92: - | AQ92: - | AR92: - | AS92: - | AT92: - | AU92: - | AV92: -
E93: Value assigned to averting a death from vaccine-preventable disease of a person under age 5 | F93: =Inputs!F272 -> UoV | G93: =Inputs!G272 -> input | H93: =Inputs!H272 -> 116.25262 | I93: =Inputs!I272 -> - | J93: =Inputs!J272 -> - | K93: =Inputs!K272 -> - | L93: =Inputs!L272 -> - | M93: =Inputs!M272 -> - | ... AV93: =Inputs!AV272 -> -
E94: Value assigned to averting a death from vaccine-preventable disease of a person age 5-14 | F94: =Inputs!F273 -> UoV | G94: =Inputs!G273 -> input | H94: =Inputs!H273 -> 133.7 | I94: =Inputs!I273 -> - | J94: =Inputs!J273 -> - | K94: =Inputs!K273 -> - | L94: =Inputs!L273 -> - | M94: =Inputs!M273 -> - | ... AV94: =Inputs!AV273 -> -
E95: Units of value generated from deaths averted among people under age 15 | F95: UoV | G95: calc | H95: - | I95: =(I48*$H93)+(I61*$H94) -> 37774.943 | J95: =(J48*$H93)+(J61*$H94) -> 18277.272 | K95: =(K48*$H93)+(K61*$H94) -> 34050.076 | L95: =(L48*$H93)+(L61*$H94) -> 16782.744 | M95: =(M48*$H93)+(M61*$H94) -> 23861.084 | N95: =(N48*$H93)+(N61*$H94) -> 31515.236 | O95: =(O48*$H93)+(O61*$H94) -> 55587.834 | P95: =(P48*$H93)+(P61*$H94) -> 73826.442 | ... AV95: =(AV48*$H93)+(AV61*$H94) -> 22640.801
E96: Units of value generated from long-term income increases | F96: UoV | G96: calc | H96: - | I96: =I95*$H92 -> 11576.887 | J96: =J95*$H92 -> 5601.4355 | K96: =K95*$H92 -> 10435.327 | L96: =L95*$H92 -> 5143.4076 | M96: =M95*$H92 -> 7312.7063 | N96: =N95*$H92 -> 9658.4745 | O96: =O95*$H92 -> 17036.003 | P96: =P95*$H92 -> 22625.59 | ... AV96: =AV95*$H92 -> 6938.7263
C98: Consumption increases
E99: Travel cost of bringing a child to a health clinic for vaccination (when travel is not free) | F99: =Inputs!F255 -> ₦ | G99: =Inputs!G255 -> input | H99: =Inputs!H255 -> 298 | I99: =Inputs!I255 -> - | J99: =Inputs!J255 -> - | K99: =Inputs!K255 -> - | L99: =Inputs!L255 -> - | M99: =Inputs!M255 -> - | ... AV99: =Inputs!AV255 -> -
E100: Percentage of disbursements where a caregiver reported no transportation cost | F100: =Inputs!F256 -> % | G100: =Inputs!G256 -> input | H100: =Inputs!H256 -> 0.6772
E101: Number of routine vaccination visits incentivized by New Incentives' program | F101: =Inputs!F257 -> # | G101: =Inputs!G257 -> input | H101: =Inputs!H257 -> 6 | I101: =Inputs!I257 -> - | J101: =Inputs!J257 -> - | K101: =Inputs!K257 -> - | L101: =Inputs!L257 -> - | M101: =Inputs!M257 -> - | ... AV101: =Inputs!AV257 -> -
E102: Total travel costs of bringing a child to all incentivized vaccination visits | F102: =Inputs!F258 -> ₦ | G102: calc | H102: =(H99*H101)*(1-H100) -> 577.1664 | I102: =Inputs!I258 -> - | J102: =Inputs!J258 -> - | K102: =Inputs!K258 -> - | L102: =Inputs!L258 -> - | M102: =Inputs!M258 -> - | N102: =Inputs!N258 -> - | O102: =Inputs!O258 -> - | P102: =Inputs!P258 -> - | ... AV102: =Inputs!AV258 -> -
E103: Size of cash transfer disbursed for the routine vaccination visit at birth | F103: =Inputs!F258 -> ₦ | G103: =Inputs!G258 -> input | H103: =Inputs!H258 -> 1000 | I103: =Inputs!I258 -> - | J103: =Inputs!J258 -> - | K103: =Inputs!K258 -> - | L103: =Inputs!L259 -> - | M103: =Inputs!M258 -> - | N103: =Inputs!N258 -> - | O103: =Inputs!O258 -> - | P103: =Inputs!P258 -> - | Q103: =Inputs!Q258 -> - | R103: =Inputs!R258 -> - | S103: =Inputs!S258 -> - | T103: =Inputs!T258 -> - | ... AV103: =Inputs!AV258 -> -
E104: Size of cash transfer disbursed for the routine vaccination visit at 6 weeks | F104: =Inputs!F259 -> ₦ | G104: =Inputs!G259 -> input | H104: =Inputs!H259 -> 1000 | I104: =Inputs!I259 -> - | J104: =Inputs!J259 -> - | K104: =Inputs!K259 -> - | L104: =Inputs!L260 -> - | M104: =Inputs!M259 -> - | N104: =Inputs!N259 -> - | O104: =Inputs!O259 -> - | P104: =Inputs!P259 -> - | Q104: =Inputs!Q259 -> - | R104: =Inputs!R259 -> - | S104: =Inputs!S259 -> - | T104: =Inputs!T259 -> - | ... AV104: =Inputs!AV259 -> -
E105: Size of cash transfer disbursed for the routine vaccination visit at 10 weeks | F105: =Inputs!F260 -> ₦ | G105: =Inputs!G260 -> input | H105: =Inputs!H260 -> 1000 | I105: =Inputs!I260 -> - | J105: =Inputs!J260 -> - | K105: =Inputs!K260 -> - | L105: =Inputs!L261 -> - | M105: =Inputs!M260 -> - | N105: =Inputs!N260 -> - | O105: =Inputs!O260 -> - | P105: =Inputs!P260 -> - | Q105: =Inputs!Q260 -> - | R105: =Inputs!R260 -> - | S105: =Inputs!S260 -> - | T105: =Inputs!T260 -> - | ... AV105: =Inputs!AV260 -> -
E106: Size of cash transfer disbursed for the routine vaccination visit at 14 weeks | F106: =Inputs!F261 -> ₦ | G106: =Inputs!G261 -> input | H106: =Inputs!H261 -> 1000 | I106: =Inputs!I261 -> - | J106: =Inputs!J261 -> - | K106: =Inputs!K261 -> - | L106: =Inputs!L262 -> - | M106: =Inputs!M261 -> - | N106: =Inputs!N261 -> - | O106: =Inputs!O261 -> - | P106: =Inputs!P261 -> - | Q106: =Inputs!Q261 -> - | R106: =Inputs!R261 -> - | S106: =Inputs!S261 -> - | T106: =Inputs!T261 -> - | ... AV106: =Inputs!AV261 -> -
E107: Size of cash transfer disbursed for the routine vaccination visit at 9 months | F107: =Inputs!F262 -> ₦ | G107: =Inputs!G262 -> input | H107: =Inputs!H262 -> 1000 | I107: =Inputs!I262 -> - | J107: =Inputs!J262 -> - | K107: =Inputs!K262 -> - | L107: =Inputs!L265 -> - | M107: =Inputs!M262 -> - | N107: =Inputs!N262 -> - | O107: =Inputs!O262 -> - | P107: =Inputs!P262 -> - | Q107: =Inputs!Q262 -> - | R107: =Inputs!R262 -> - | S107: =Inputs!S262 -> - | T107: =Inputs!T262 -> - | ... AV107: =Inputs!AV262 -> -
E108: Size of cash transfer disbursed for the routine vaccination visit at 15 months | F108: =Inputs!F263 -> ₦ | G108: =Inputs!G263 -> input | H108: =Inputs!H263 -> 1000
E109: Size of cash transfer for completion of the full routine immunization schedule | F109: =Inputs!F264 -> ₦ | G109: =Inputs!G264 -> input | H109: =Inputs!H264 -> 5000
E110: Total cash transfer disbursed across the full routine immunization schedule | F110: ₦ | G110: calc | H110: =SUM(H103:H109) -> 11000 | I110: - | J110: - | K110: - | L110: - | M110: - | N110: - | O110: - | P110: - | Q110: - | R110: - | S110: - | T110: - | U110: - | V110: - | W110: - | X110: - | Y110: - | Z110: - | AA110: - | AB110: - | AC110: - | AD110: - | AE110: - | AF110: - | AG110: - | AH110: - | AI110: - | AJ110: - | AK110: - | AL110: - | AM110: - | AN110: - | AO110: - | AP110: - | AQ110: - | AR110: - | AS110: - | AT110: - | AU110: - | AV110: -
E111: Nigerian naira per U.S. dollar | F111: =Inputs!F265 -> ₦ | G111: =Inputs!G265 -> input | H111: =Inputs!H265 -> 1165 | I111: =Inputs!I265 -> - | J111: =Inputs!J265 -> - | K111: =Inputs!K265 -> - | L111: =Inputs!L265 -> - | M111: =Inputs!M265 -> - | ... AV111: =Inputs!AV265 -> -
E112: Total travel costs of bringing a child to all incentivized vaccination visits (in U.S. dollars) | F112: $ | G112: calc | H112: =H102/H111 -> 0.4954218 | I112: - | J112: - | K112: - | L112: - | M112: - | N112: - | O112: - | P112: - | Q112: - | R112: - | S112: - | T112: - | U112: - | V112: - | W112: - | X112: - | Y112: - | Z112: - | AA112: - | AB112: - | AC112: - | AD112: - | AE112: - | AF112: - | AG112: - | AH112: - | AI112: - | AJ112: - | AK112: - | AL112: =Inputs!AL266 -> - | AM112: =Inputs!AM266 -> - | AN112: =Inputs!AN266 -> - | AO112: - | AP112: - | AQ112: - | AR112: - | AS112: - | AT112: - | AU112: - | AV112: -
E113: Total cash transfer disbursed across the full routine immunization schedule (in U.S. dollars) | F113: $ | G113: calc | H113: =H110/H111 -> 9.4420601 | I113: - | J113: - | K113: - | L113: - | M113: - | N113: - | O113: - | P113: - | Q113: - | R113: - | S113: - | T113: - | U113: - | V113: - | W113: - | X113: - | Y113: - | Z113: - | AA113: - | AB113: - | AC113: - | AD113: - | AE113: - | AF113: - | AG113: - | AH113: - | AI113: - | AJ113: - | AK113: - | AL113: =Inputs!AL267 -> - | AM113: =Inputs!AM267 -> - | AN113: =Inputs!AN267 -> - | AO113: - | AP113: - | AQ113: - | AR113: - | AS113: - | AT113: - | AU113: - | AV113: -
E114: Net increase in household consumption from bringing a child to all incentivized vaccination visits | F114: $ | G114: calc | H114: =H113-H112 -> 8.9466383 | I114: - | J114: - | K114: - | L114: - | M114: - | N114: - | O114: - | P114: - | Q114: - | R114: - | S114: - | T114: - | U114: - | V114: - | W114: - | X114: - | Y114: - | Z114: - | AA114: - | AB114: - | AC114: - | AD114: - | AE114: - | AF114: - | AG114: - | AH114: - | AI114: - | AJ114: - | AK114: - | AL114: - | AM114: - | AN114: - | AO114: - | AP114: - | AQ114: - | AR114: - | AS114: - | AT114: - | AU114: - | AV114: -
E115: Average number of people per household | F115: =Inputs!F266 -> # | G115: =Inputs!G266 -> input | H115: =Inputs!H266 -> 6.7 | I115: =Inputs!I266 -> - | J115: =Inputs!J266 -> - | K115: =Inputs!K266 -> - | L115: =Inputs!L266 -> - | M115: =Inputs!M266 -> - | ... AV115: =Inputs!AV266 -> -
...

Sheet Aggregation across vaccines
I1: New Incentives – current states of operation | R1: New Incentives – prospective states | AF1: New Incentives – prospective states
I2: Nigeria | J2: Nigeria | K2: Nigeria | L2: Nigeria | M2: Nigeria | N2: Nigeria | O2: Nigeria | P2: Nigeria | Q2: Nigeria | R2: Nigeria | S2: Nigeria | T2: Nigeria | U2: Nigeria | V2: Nigeria | W2: Nigeria | X2: Nigeria | Y2: Nigeria | Z2: Nigeria | AA2: Nigeria | AB2: Nigeria | AC2: Nigeria | AD2: Nigeria | AE2: Nigeria | AF2: Nigeria | AG2: Nigeria | AH2: Nigeria | AI2: Nigeria | AJ2: Nigeria | AK2: Nigeria | AL2: Nigeria | AM2: Nigeria | AN2: Nigeria | AO2: Nigeria | AP2: Nigeria | AQ2: Nigeria | AR2: Nigeria | AS2: Nigeria | AT2: Nigeria | AU2: Nigeria | AV2: Nigeria
A3: Main calculations | F3: unit | G3: type | H3: Overall | I3: Bauchi | J3: Gombe | K3: Jigawa | L3: Kaduna - cohort 17 | M3: Kano | N3: Katsina | O3: Kebbi | P3: Sokoto | Q3: Zamfara | R3: Abia | S3: Adamawa | T3: Akwa Ibom | U3: Anambra | V3: Bayelsa | W3: Benue | X3: Borno | Y3: Cross River | Z3: Delta | AA3: Ebonyi | AB3: Edo | AC3: Ekiti | AD3: Enugu | AE3: FCT | AF3: Imo | AG3: Kaduna | AH3: Kogi | AI3: Kwara | AJ3: Lagos | AK3: Nasarawa | AL3: Niger | AM3: Niger - cohorts 32 & 36 | AN3: Niger - cohort 34 | AO3: Ogun | AP3: Ondo | AQ3: Osun | AR3: Oyo | AS3: Plateau | AT3: Rivers | AU3: Taraba | AV3: Yobe
E4: Final cost-effectiveness estimate (pulled from "Main calcs" sheet for visibility) | F4: ='Main CEA'!F242 -> xbenchmark | G4: ='Main CEA'!G242 -> calc | H4: ='Main CEA'!H242 -> - | I4: ='Main CEA'!I242 -> 20.039606 | J4: ='Main CEA'!J242 -> 10.020838 | K4: ='Main CEA'!K242 -> 18.177505 | L4: ='Main CEA'!L242 -> 9.0027672 | M4: ='Main CEA'!M242 -> 12.612827 | ... AV4: ='Main CEA'!AV242 -> 11.471963
A5: Baseline coverage for the target population
C7: Baseline vaccination coverage for the target population
E8: Baseline proportion of children in the target population who receive the BCG vaccine | F8: ='Vaccine coverage'!F96 -> % | G8: supp | H8: ='Vaccine coverage'!H96 -> - | I8: ='Vaccine coverage'!I96 -> 0.55242574 | J8: ='Vaccine coverage'!J96 -> 0.72882976 | K8: ='Vaccine coverage'!K96 -> 0.60775837 | L8: ='Vaccine coverage'!L96 -> 0.63807624 | M8: ='Vaccine coverage'!M96 -> 0.61526279 | N8: ='Vaccine coverage'!N96 -> 0.49219015 | O8: ='Vaccine coverage'!O96 -> 0.40063624 | ... AV8: ='Vaccine coverage'!AV96 -> 0.64274993
E9: Baseline proportion of children in the target population who receive the 1st dose of the Penta vaccine | F9: ='Vaccine coverage'!F97 -> % | G9: supp | H9: ='Vaccine coverage'!H97 -> - | I9: ='Vaccine coverage'!I97 -> 0.49339093 | J9: ='Vaccine coverage'!J97 -> 0.67679908 | K9: ='Vaccine coverage'!K97 -> 0.57233748 | L9: ='Vaccine coverage'!L97 -> 0.59765241 | M9: ='Vaccine coverage'!M97 -> 0.56243164 | N9: ='Vaccine coverage'!N97 -> 0.45688369 | O9: ='Vaccine coverage'!O97 -> 0.33809936 | ... AV9: ='Vaccine coverage'!AV97 -> 0.60764175
E10: Baseline proportion of children in the target population who receive the 2nd dose of the Penta vaccine | F10: ='Vaccine coverage'!F98 -> % | G10: supp | H10: ='Vaccine coverage'!H98 -> - | I10: ='Vaccine coverage'!I98 -> 0.44736379 | J10: ='Vaccine coverage'!J98 -> 0.63357359 | K10: ='Vaccine coverage'!K98 -> 0.51570409 | L10: ='Vaccine coverage'!L98 -> 0.50729913 | M10: ='Vaccine coverage'!M98 -> 0.48268462 | N10: ='Vaccine coverage'!N98 -> 0.41743904 | O10: ='Vaccine coverage'!O98 -> 0.24294325 | ... AV10: ='Vaccine coverage'!AV98 -> 0.50552412
E11: Baseline proportion of children in the target population who receive the 3rd dose of the Penta vaccine | F11: ='Vaccine coverage'!F99 -> % | G11: supp | H11: ='Vaccine coverage'!H99 -> - | I11: ='Vaccine coverage'!I99 -> 0.35420886 | J11: ='Vaccine coverage'!J99 -> 0.50179589 | K11: ='Vaccine coverage'!K99 -> 0.39683399 | L11: ='Vaccine coverage'!L99 -> 0.40964155 | M11: ='Vaccine coverage'!M99 -> 0.36891753 | N11: ='Vaccine coverage'!N99 -> 0.35086445 | O11: ='Vaccine coverage'!O99 -> 0.15439104 | ... AV11: ='Vaccine coverage'!AV99 -> 0.41023644
E12: Baseline proportion of children in the target population who receive the 1st dose of the PCV vaccine | F12: ='Vaccine coverage'!F108 -> % | G12: supp | H12: ='Vaccine coverage'!H108 -> - | I12: ='Vaccine coverage'!I108 -> 0.49161614 | J12: ='Vaccine coverage'!J108 -> 0.64092967 | K12: ='Vaccine coverage'!K108 -> 0.5647796 | L12: ='Vaccine coverage'!L108 -> 0.58656257 | M12: ='Vaccine coverage'!M108 -> 0.54917961 | N12: ='Vaccine coverage'!N108 -> 0.44239613 | O12: ='Vaccine coverage'!O108 -> 0.3330181 | ... AV12: ='Vaccine coverage'!AV108 -> 0.59058673
E13: Baseline proportion of children in the target population who receive the 2nd dose of the PCV vaccine | F13: ='Vaccine coverage'!F109 -> % | G13: supp | H13: ='Vaccine coverage'!H109 -> - | I13: ='Vaccine coverage'!I109 -> 0.44575457 | J13: ='Vaccine coverage'!J109 -> 0.59999507 | K13: ='Vaccine coverage'!K109 -> 0.50889407 | L13: ='Vaccine coverage'!L109 -> 0.49788586 | M13: ='Vaccine coverage'!M109 -> 0.47131159 | N13: ='Vaccine coverage'!N109 -> 0.39628905 | O13: ='Vaccine coverage'!O109 -> 0.23929208 | ... AV13: ='Vaccine coverage'!AV109 -> 0.48978056
E14: Baseline proportion of children in the target population who receive the 3rd dose of the PCV vaccine | F14: ='Vaccine coverage'!F110 -> % | G14: supp | H14: ='Vaccine coverage'!H110 -> - | I14: ='Vaccine coverage'!I110 -> 0.35293473 | J14: ='Vaccine coverage'!J110 -> 0.4752014 | K14: ='Vaccine coverage'!K110 -> 0.39159369 | L14: ='Vaccine coverage'!L110 -> 0.40204037 | M14: ='Vaccine coverage'!M110 -> 0.36022509 | N14: ='Vaccine coverage'!N110 -> 0.33429231 | O14: ='Vaccine coverage'!O110 -> 0.15207071 | ... AV14: ='Vaccine coverage'!AV110 -> 0.39934281
E15: Baseline proportion of children in the target population who receive the 1st dose of the rotavirus vaccine | F15: ='Vaccine coverage'!F115 -> % | G15: supp | H15: ='Vaccine coverage'!H115 -> - | I15: ='Vaccine coverage'!I115 -> 0.49250354 | J15: ='Vaccine coverage'!J115 -> 0.65886437 | K15: ='Vaccine coverage'!K115 -> 0.56855854 | L15: ='Vaccine coverage'!L115 -> 0.59210749 | M15: ='Vaccine coverage'!M115 -> 0.55580563 | N15: ='Vaccine coverage'!N115 -> 0.44963991 | O15: ='Vaccine coverage'!O115 -> 0.33555873 | ... AV15: ='Vaccine coverage'!AV115 -> 0.59911424
E16: Baseline proportion of children in the target population who receive the 2nd dose of the rotavirus vaccine | F16: ='Vaccine coverage'!F116 -> % | G16: supp | H16: ='Vaccine coverage'!H116 -> - | I16: ='Vaccine coverage'!I116 -> 0.44655918 | J16: ='Vaccine coverage'!J116 -> 0.61678433 | K16: ='Vaccine coverage'!K116 -> 0.51229908 | L16: ='Vaccine coverage'!L116 -> 0.50259249 | M16: ='Vaccine coverage'!M116 -> 0.4769981 | N16: ='Vaccine coverage'!N116 -> 0.40686404 | O16: ='Vaccine coverage'!O116 -> 0.24111767 | ... AV16: ='Vaccine coverage'!AV116 -> 0.49765234
E17: Baseline proportion of children in the target population who receive the 3rd dose of the rotavirus vaccine | F17: ='Vaccine coverage'!F117 -> % | G17: supp | H17: ='Vaccine coverage'!H117 -> - | I17: ='Vaccine coverage'!I117 -> 0.35357179 | J17: ='Vaccine coverage'!J117 -> 0.48849864 | K17: ='Vaccine coverage'!K117 -> 0.39421384 | L17: ='Vaccine coverage'!L117 -> 0.40584096 | M17: ='Vaccine coverage'!M117 -> 0.36457131 | N17: ='Vaccine coverage'!N117 -> 0.34257838 | O17: ='Vaccine coverage'!O117 -> 0.15323087 | ... AV17: ='Vaccine coverage'!AV117 -> 0.40478963
E18: Baseline proportion of children in the target population who receive the 1st dose of the measles vaccine | F18: ='Vaccine coverage'!F124 -> % | G18: supp | H18: ='Vaccine coverage'!H124 -> - | I18: ='Vaccine coverage'!I124 -> 0.30803947 | J18: ='Vaccine coverage'!J124 -> 0.36704703 | K18: ='Vaccine coverage'!K124 -> 0.55907163 | L18: ='Vaccine coverage'!L124 -> 0.56707265 | M18: ='Vaccine coverage'!M124 -> 0.40505189 | N18: ='Vaccine coverage'!N124 -> 0.43705599 | O18: ='Vaccine coverage'!O124 -> 0.63208098 | ... AV18: ='Vaccine coverage'!AV124 -> 0.71309136
E19: Baseline proportion of children in the target population who receive the 2nd dose of the measles vaccine | F19: ='Vaccine coverage'!F125 -> % | G19: supp | H19: ='Vaccine coverage'!H125 -> - | I19: ='Vaccine coverage'!I125 -> 0.10801384 | J19: ='Vaccine coverage'!J125 -> 0.17802281 | K19: ='Vaccine coverage'!K125 -> 0.3270419 | L19: ='Vaccine coverage'!L125 -> 0.30903959 | M19: ='Vaccine coverage'!M125 -> 0.1420182 | N19: ='Vaccine coverage'!N125 -> 0.24703165 | O19: ='Vaccine coverage'!O125 -> 0.54907035 | ... AV19: ='Vaccine coverage'!AV125 -> 0.48406202
C21: Proportion of vaccine-preventable mortalities that could be prevented by each vaccine dose
E22: Proportion of vaccine-preventable mortalities among people under age 5 that could be prevented by the BCG vaccine | F22: ='Disease burden'!F388 -> % | G22: ='Disease burden'!G388 -> feed | H22: ='Disease burden'!H388 -> - | I22: ='Disease burden'!I388 -> 0.17823491 | J22: ='Disease burden'!J388 -> 0.12033359 | K22: ='Disease burden'!K388 -> 0.20302136 | L22: ='Disease burden'!L388 -> 0.10657065 | M22: ='Disease burden'!M388 -> 0.13277628 | ... AV22: ='Disease burden'!AV388 -> 0.15986442
E23: Proportion of vaccine-preventable mortalities among people under age 5 that could be prevented by the 1st dose of the Penta vaccine | F23: ='Disease burden'!F389 -> % | G23: supp | H23: ='Disease burden'!H389 -> - | I23: ='Disease burden'!I389 -> 0.073644315 | J23: ='Disease burden'!J389 -> 0.09622371 | K23: ='Disease burden'!K389 -> 0.091772594 | L23: ='Disease burden'!L389 -> 0.11232443 | M23: ='Disease burden'!M389 -> 0.085575908 | N23: ='Disease burden'!N389 -> 0.089629168 | O23: ='Disease burden'!O389 -> 0.10466208 | ... AV23: ='Disease burden'!AV389 -> 0.11459606
E24: Proportion of vaccine-preventable mortalities among people under age 5 that could be prevented by the 2nd dose of the Penta vaccine | F24: ='Disease burden'!F390 -> % | G24: supp | H24: ='Disease burden'!H390 -> - | I24: ='Disease burden'!I390 -> 0.11572678 | J24: ='Disease burden'!J390 -> 0.15120869 | K24: ='Disease burden'!K390 -> 0.14421408 | L24: ='Disease burden'!L390 -> 0.17650982 | M24: ='Disease burden'!M390 -> 0.13447643 | N24: ='Disease burden'!N390 -> 0.14084584 | O24: ='Disease burden'!O390 -> 0.16446899 | ... AV24: ='Disease burden'!AV390 -> 0.18007952
E25: Proportion of vaccine-preventable mortalities among people under age 5 that could be prevented by the 3rd dose of the Penta vaccine | F25: ='Disease burden'!F391 -> % | G25: supp | H25: ='Disease burden'!H391 -> - | I25: ='Disease burden'!I391 -> 0.021041233 | J25: ='Disease burden'!J391 -> 0.027492489 | K25: ='Disease burden'!K391 -> 0.026220741 | L25: ='Disease burden'!L391 -> 0.032092695 | M25: ='Disease burden'!M391 -> 0.024450259 | N25: ='Disease burden'!N391 -> 0.025608334 | O25: ='Disease burden'!O391 -> 0.029903452 | ... AV25: ='Disease burden'!AV391 -> 0.032741731
E26: Proportion of vaccine-preventable mortalities among people under age 5 that could be prevented by the 1st dose of the PCV vaccine | F26: ='Disease burden'!F392 -> % | G26: supp | H26: ='Disease burden'!H392 -> - | I26: ='Disease burden'!I392 -> 0.089900525 | J26: ='Disease burden'!J392 -> 0.10135603 | K26: ='Disease burden'!K392 -> 0.085648045 | L26: ='Disease burden'!L392 -> 0.107903 | M26: ='Disease burden'!M392 -> 0.11094009 | N26: ='Disease burden'!N392 -> 0.079775398 | O26: ='Disease burden'!O392 -> 0.076462066 | ... AV26: ='Disease burden'!AV392 -> 0.073761103
E27: Proportion of vaccine-preventable mortalities among people under age 5 that could be prevented by the 2nd dose of the PCV vaccine | F27: ='Disease burden'!F393 -> % | G27: supp | H27: ='Disease burden'!H393 -> - | I27: ='Disease burden'!I393 -> 0.14127225 | J27: ='Disease burden'!J393 -> 0.15927376 | K27: ='Disease burden'!K393 -> 0.13458978 | L27: ='Disease burden'!L393 -> 0.16956186 | M27: ='Disease burden'!M393 -> 0.17433442 | N27: ='Disease burden'!N393 -> 0.12536134 | O27: ='Disease burden'!O393 -> 0.12015467 | ... AV27: ='Disease burden'!AV393 -> 0.1159103
E28: Proportion of vaccine-preventable mortalities among people under age 5 that could be prevented by the 3rd dose of the PCV vaccine | F28: ='Disease burden'!F394 -> % | G28: supp | H28: ='Disease burden'!H394 -> - | I28: ='Disease burden'!I394 -> 0.025685864 | J28: ='Disease burden'!J394 -> 0.028958866 | K28: ='Disease burden'!K394 -> 0.02447087 | L28: ='Disease burden'!L394 -> 0.030829429 | M28: ='Disease burden'!M394 -> 0.031697167 | N28: ='Disease burden'!N394 -> 0.022792971 | O28: ='Disease burden'!O394 -> 0.021846305 | ... AV28: ='Disease burden'!AV394 -> 0.021074601
E29: Proportion of vaccine-preventable mortalities among people under age 5 that could be prevented by the 1st dose of the rotavirus vaccine | F29: ='Disease burden'!F395 -> % | G29: supp | H29: ='Disease burden'!H395 -> - | I29: ='Disease burden'!I395 -> 0.20662453 | J29: ='Disease burden'!J395 -> 0.19100692 | K29: ='Disease burden'!K395 -> 0.14601898 | L29: ='Disease burden'!L395 -> 0.14558025 | M29: ='Disease burden'!M395 -> 0.19432922 | N29: ='Disease burden'!N395 -> 0.17668733 | O29: ='Disease burden'!O395 -> 0.16305604 | ... AV29: ='Disease burden'!AV395 -> 0.14035311
E30: Proportion of vaccine-preventable mortalities among people under age 5 that could be prevented by the 2nd dose of the rotavirus vaccine | F30: ='Disease burden'!F396 -> % | G30: supp | H30: ='Disease burden'!H396 -> - | I30: ='Disease burden'!I396 -> 0.041324906 | J30: ='Disease burden'!J396 -> 0.038201384 | K30: ='Disease burden'!K396 -> 0.029203795 | L30: ='Disease burden'!L396 -> 0.02911605 | M30: ='Disease burden'!M396 -> 0.038865843 | N30: ='Disease burden'!N396 -> 0.035337465 | O30: ='Disease burden'!O396 -> 0.032611208 | ... AV30: ='Disease burden'!AV396 -> 0.028070622
E31: Proportion of vaccine-preventable mortalities among people under age 5 that could be prevented by the 3rd dose of the rotavirus vaccine | F31: ='Disease burden'!F398 -> % | G31: supp | H31: ='Disease burden'!H398 -> - | I31: ='Disease burden'!I397 -> 0.027549937 | J31: ='Disease burden'!J397 -> 0.025467589 | K31: ='Disease burden'!K397 -> 0.019469197 | L31: ='Disease burden'!L397 -> 0.0194107 | M31: ='Disease burden'!M397 -> 0.025910562 | N31: ='Disease burden'!N397 -> 0.02355831 | O31: ='Disease burden'!O397 -> 0.021740806 | P31: ='Disease burden'!P397 -> 0.02699738 | ... AV31: ='Disease burden'!AV397 -> 0.018713748
E32: Proportion of vaccine-preventable mortalities among people under age 5 that could be prevented by the 1st dose of the measles vaccine | F32: ='Disease burden'!F398 -> % | G32: supp | H32: ='Disease burden'!H398 -> - | I32: ='Disease burden'!I398 -> 0.074606151 | J32: ='Disease burden'!J398 -> 0.057117138 | K32: ='Disease burden'!K398 -> 0.090072195 | L32: ='Disease burden'!L398 -> 0.066206609 | M32: ='Disease burden'!M398 -> 0.044052509 | N32: ='Disease burden'!N398 -> 0.10112555 | O32: ='Disease burden'!O398 -> 0.10124241 | ... AV32: ='Disease burden'!AV398 -> 0.10845507
E33: Proportion of vaccine-preventable mortalities among people under age 5 that could be prevented by the 2nd dose of the measles vaccine | F33: ='Disease burden'!F399 -> % | G33: supp | H33: ='Disease burden'!H399 -> - | I33: ='Disease burden'!I399 -> 0.0043885971 | J33: ='Disease burden'!J399 -> 0.0033598316 | K33: ='Disease burden'!K399 -> 0.0052983644 | L33: ='Disease burden'!L399 -> 0.0038945064 | M33: ='Disease burden'!M399 -> 0.0025913241 | N33: ='Disease burden'!N399 -> 0.0059485617 | O33: ='Disease burden'!O399 -> 0.0059554359 | ... AV33: ='Disease burden'!AV399 -> 0.0063797102
C35: Baseline vaccination coverage for the target population, aggregated across vaccines
E36: Proportion of children in the target population who would be vaccinated in the absence of the program, aggregated across vaccines | F36: % | G36: calc | H36: - | I36: =SUMPRODUCT(I8:I19,I22:I33) -> 0.46367056 | J36: =SUMPRODUCT(J8:J19,J22:J33) -> 0.62012448 | K36: =SUMPRODUCT(K8:K19,K22:K33) -> 0.54488278 | L36: =SUMPRODUCT(L8:L19,L22:L33) -> 0.54538777 | M36: =SUMPRODUCT(M8:M19,M22:M33) -> 0.51246873 | N36: =SUMPRODUCT(N8:N19,N22:N33) -> 0.43419286 | O36: =SUMPRODUCT(O8:O19,O22:O33) -> 0.33392894 | P36: =SUMPRODUCT(P8:P19,P22:P33) -> 0.24636944 | ... AV36: =SUMPRODUCT(AV8:AV19,AV22:AV33) -> 0.57166016
E37: Proportion of children in the target population who would not be vaccinated in the absence of the program, aggregated across vaccines - in year of baseline measurement | F37: % | G37: calc | I37: =1-I36 -> 0.53632944 | J37: =1-J36 -> 0.37987552 | K37: =1-K36 -> 0.45511722 | L37: =1-L36 -> 0.45461223 | M37: =1-M36 -> 0.48753127 | N37: =1-N36 -> 0.56580714 | O37: =1-O36 -> 0.66607106 | P37: =1-P36 -> 0.75363056 | ... AV37: =1-AV36 -> 0.42833984
E38: Effective year of baseline measurement | F38: # | G38: supp | I38: ='Vaccine coverage'!I15 -> 2022 | J38: ='Vaccine coverage'!J15 -> 2022.5 | K38: ='Vaccine coverage'!K15 -> 2021.5 | L38: ='Vaccine coverage'!L15 -> 2023 | M38: ='Vaccine coverage'!M15 -> 2022.5 | N38: ='Vaccine coverage'!N15 -> 2021.2647 | O38: ='Vaccine coverage'!O15 -> 2023 | P38: ='Vaccine coverage'!P15 -> 2021.913 | ... AV38: ='Vaccine coverage'!AV15 -> 2023.6471
E39: Counterfactual change in the proportion of unvaccinated children per year in the absence of New Incentives | F39: % | G39: input | H39: =Inputs!H80 -> -0.05 | I39: - | J39: - | K39: - | L39: - | M39: - | N39: - | O39: - | P39: - | Q39: - | R39: - | S39: - | T39: - | U39: - | V39: - | W39: - | X39: - | Y39: - | Z39: - | AA39: - | AB39: - | AC39: - | AD39: - | AE39: - | AF39: - | AG39: - | AH39: - | AI39: - | AJ39: - | AK39: - | AL39: - | AM39: - | AN39: - | AO39: - | AP39: - | AQ39: - | AR39: - | AS39: - | AT39: - | AU39: - | AV39: -
E40: Middle year of grant period | F40: # | G40: input | H40: 2026
E41: Proportion of children in the target population who would not be vaccinated in the absence of the program, aggregated across vaccines - in middle year of grant period | F41: % | G41: calc | I41: =I37*(1+$H$39)^($H$40-I38) -> 0.43684368 | J41: =J37*(1+$H$39)^($H$40-J38) -> 0.31744898 | K41: =K37*(1+$H$39)^($H$40-K38) -> 0.36130959 | L41: =L37*(1+$H$39)^($H$40-L38) -> 0.38977316 | M41: =M37*(1+$H$39)^($H$40-M38) -> 0.4074132 | N41: =N37*(1+$H$39)^($H$40-N38) -> 0.44379575 | O41: =O37*(1+$H$39)^($H$40-O38) -> 0.57107267 | P41: =P37*(1+$H$39)^($H$40-P38) -> 0.61110501 | ... AV41: =AV37*(1+$H$39)^($H$40-AV38) -> 0.37964128
E42: Proportion of children in the target population who would be vaccinated in the absence of the program, aggregated across vaccines - in middle year of grant period | F42: % | G42: calc | I42: =1-I41 -> 0.56315632 | J42: =1-J41 -> 0.68255102 | K42: =1-K41 -> 0.63869041 | L42: =1-L41 -> 0.61022684 | M42: =1-M41 -> 0.5925868 | N42: =1-N41 -> 0.55620425 | O42: =1-O41 -> 0.42892733 | P42: =1-P41 -> 0.38889499 | ... AV42: =1-AV41 -> 0.62035872
A44: Vaccine efficacy and coverage for people under age 5, aggregated across vaccines
C46: Vaccine efficacy with universal coverage
E47: BCG vaccine efficacy rate with universal coverage | F47: ='Vaccine efficacy'!F50 -> % | G47: supp | H47: ='Vaccine efficacy'!H50 -> 0.59746964 | I47: ='Vaccine efficacy'!I50 -> - | J47: ='Vaccine efficacy'!J50 -> - | K47: ='Vaccine efficacy'!K50 -> - | L47: ='Vaccine efficacy'!L50 -> - | M47: ='Vaccine efficacy'!M50 -> - | N47: ='Vaccine efficacy'!N50 -> - | O47: ='Vaccine efficacy'!O50 -> - | ... AW47: ='Vaccine efficacy'!AW50
E48: DTP vaccine efficacy rate with universal coverage (part of the Penta vaccine) | F48: ='Vaccine efficacy'!F51 -> % | G48: supp | H48: ='Vaccine efficacy'!H51 -> 0.85094161 | I48: ='Vaccine efficacy'!I51 -> - | J48: ='Vaccine efficacy'!J51 -> - | K48: ='Vaccine efficacy'!K51 -> - | L48: ='Vaccine efficacy'!L51 -> - | M48: ='Vaccine efficacy'!M51 -> - | N48: ='Vaccine efficacy'!N51 -> - | O48: ='Vaccine efficacy'!O51 -> - | ... AW48: ='Vaccine efficacy'!AW51
E49: Hib vaccine efficacy rate with universal coverage (part of the Penta vaccine) | F49: ='Vaccine efficacy'!F52 -> % | G49: supp | H49: ='Vaccine efficacy'!H52 -> 0.74231077 | I49: ='Vaccine efficacy'!I52 -> - | J49: ='Vaccine efficacy'!J52 -> - | K49: ='Vaccine efficacy'!K52 -> - | L49: ='Vaccine efficacy'!L52 -> - | M49: ='Vaccine efficacy'!M52 -> - | N49: ='Vaccine efficacy'!N52 -> - | O49: ='Vaccine efficacy'!O52 -> - | ... AW49: ='Vaccine efficacy'!AW52
E50: PCV vaccine efficacy rate with universal coverage | F50: ='Vaccine efficacy'!F53 -> % | G50: supp | H50: ='Vaccine efficacy'!H53 -> 0.42999709 | I50: ='Vaccine efficacy'!I53 -> - | J50: ='Vaccine efficacy'!J53 -> - | K50: ='Vaccine efficacy'!K53 -> - | L50: ='Vaccine efficacy'!L53 -> - | M50: ='Vaccine efficacy'!M53 -> - | N50: ='Vaccine efficacy'!N53 -> - | O50: ='Vaccine efficacy'!O53 -> - | ... AW50: ='Vaccine efficacy'!AW53
E51: Rotavirus vaccine efficacy rate with universal coverage | F51: ='Vaccine efficacy'!F54 -> % | G51: supp | H51: ='Vaccine efficacy'!H54 -> 0.41641824 | I51: ='Vaccine efficacy'!I54 -> - | J51: ='Vaccine efficacy'!J54 -> - | K51: ='Vaccine efficacy'!K54 -> - | L51: ='Vaccine efficacy'!L54 -> - | M51: ='Vaccine efficacy'!M54 -> - | N51: ='Vaccine efficacy'!N54 -> - | O51: ='Vaccine efficacy'!O54 -> - | ... AW51: ='Vaccine efficacy'!AW54
E52: Measles vaccine efficacy rate with universal coverage | F52: ='Vaccine efficacy'!F55 -> % | G52: supp | H52: ='Vaccine efficacy'!H55 -> 0.77051897 | I52: ='Vaccine efficacy'!I55 -> - | J52: ='Vaccine efficacy'!J55 -> - | K52: ='Vaccine efficacy'!K55 -> - | L52: ='Vaccine efficacy'!L55 -> - | M52: ='Vaccine efficacy'!M55 -> - | N52: ='Vaccine efficacy'!N55 -> - | O52: ='Vaccine efficacy'!O55 -> - | ... AW52: ='Vaccine efficacy'!AW55
C54: Proportion of deaths from vaccine-preventable causes among unvaccinated people under age 5 that are addressable by each vaccine, adjusted for deaths occurring before the age of vaccination
E55: Proportion of deaths from vaccine-preventable causes among unvaccinated people under age 5 that are addressable by the BCG vaccine, adjusted for deaths occurring before the age of vaccination | F55: ='Disease burden'!F212 -> % | G55: supp | H55: ='Disease burden'!H212 -> - | I55: ='Disease burden'!I212 -> 0.15588696 | J55: ='Disease burden'!J212 -> 0.10621795 | K55: ='Disease burden'!K212 -> 0.18717737 | L55: ='Disease burden'!L212 -> 0.096981906 | M55: ='Disease burden'!M212 -> 0.11466077 | N55: ='Disease burden'!N212 -> 0.15834646 | O55: ='Disease burden'!O212 -> 0.14753015 | ... AV55: ='Disease burden'!AV212 -> 0.1530991
E56: Proportion of deaths from vaccine-preventable causes among unvaccinated people under age 5 that are addressable by the DTP vaccine, adjusted for deaths occurring before the age of vaccination | F56: ='Disease burden'!F213 -> % | G56: supp | H56: ='Disease burden'!H213 -> - | I56: ='Disease burden'!I213 -> 0.1055741 | J56: ='Disease burden'!J213 -> 0.1411213 | K56: ='Disease burden'!K213 -> 0.14318646 | L56: ='Disease burden'!L213 -> 0.16934014 | M56: ='Disease burden'!M213 -> 0.11761382 | N56: ='Disease burden'!N213 -> 0.14084371 | O56: ='Disease burden'!O213 -> 0.17188315 | ... AV56: ='Disease burden'!AV213 -> 0.19356387
E57: Proportion of deaths from vaccine-preventable causes among unvaccinated people under age 5 that are addressable by the Hib vaccine, adjusted for deaths occurring before the age of vaccination | F57: ='Disease burden'!F214 -> % | G57: supp | H57: ='Disease burden'!H214 -> - | I57: ='Disease burden'!I214 -> 0.027097599 | J57: ='Disease burden'!J214 -> 0.03355061 | K57: ='Disease burden'!K214 -> 0.030434251 | L57: ='Disease burden'!L214 -> 0.040944145 | M57: ='Disease burden'!M214 -> 0.035119218 | N57: ='Disease burden'!N214 -> 0.026843428 | O57: ='Disease burden'!O214 -> 0.027847759 | ... Q57: ='Disease burden'!Q214 -> 0.021407212 | R57: ='Disease burden'!I214 -> 0.027097599 | S57: ='Disease burden'!S214 -> 0.040871689 | T57: ='Disease burden'!T214 -> 0.050608269 | U57: ='Disease burden'!U214 -> 0.052389417 | V57: ='Disease burden'!V214 -> 0.037124832 | W57: ='Disease burden'!W214 -> 0.039437974 | X57: ='Disease burden'!X214 -> 0.024616039 | Y57: ='Disease burden'!Y214 -> 0.05139913 | Z57: ='Disease burden'!Z214 -> 0.049333035 | ... AV57: ='Disease burden'!AV214 -> 0.030488306
E58: Proportion of deaths from vaccine-preventable causes among unvaccinated people under age 5 that are addressable by the PCV vaccine, adjusted for deaths occurring before the age of vaccination | F58: ='Disease burden'!F215 -> % | G58: supp | H58: ='Disease burden'!H215 -> - | I58: ='Disease burden'!I215 -> 0.31214871 | J58: ='Disease burden'!J215 -> 0.35517544 | K58: ='Disease burden'!K215 -> 0.31348108 | L58: ='Disease burden'!L215 -> 0.38982431 | M58: ='Disease burden'!M215 -> 0.38033401 | N58: ='Disease burden'!N215 -> 0.28932537 | O58: ='Disease burden'!O215 -> 0.28361976 | ... AV58: ='Disease burden'!AV215 -> 0.28043389
E59: Proportion of deaths from vaccine-preventable causes among unvaccinated people under age 5 that are addressable by the rotavirus vaccine, adjusted for deaths occurring before the age of vaccination | F59: ='Disease burden'!F216 -> % | G59: supp | H59: ='Disease burden'!H216 -> - | I59: ='Disease burden'!I216 -> 0.3457194 | J59: ='Disease burden'!J216 -> 0.32254105 | K59: ='Disease burden'!K216 -> 0.25754062 | L59: ='Disease burden'!L216 -> 0.25344307 | M59: ='Disease burden'!M216 -> 0.32103865 | N59: ='Disease burden'!N216 -> 0.30879162 | O59: ='Disease burden'!O216 -> 0.29145393 | ... AV59: ='Disease burden'!AV216 -> 0.25713884
E60: Proportion of deaths from vaccine-preventable causes among unvaccinated people under age 5 that are addressable by the measles vaccine, adjusted for deaths occurring before the age of vaccination | F60: ='Disease burden'!F217 -> % | G60: supp | H60: ='Disease burden'!H217 -> - | I60: ='Disease burden'!I217 -> 0.053573222 | J60: ='Disease burden'!J217 -> 0.041393637 | K60: ='Disease burden'!K217 -> 0.068180226 | L60: ='Disease burden'!L217 -> 0.049466428 | M60: ='Disease burden'!M217 -> 0.031233534 | N60: ='Disease burden'!N217 -> 0.075849417 | O60: ='Disease burden'!O217 -> 0.077665252 | ... AV60: ='Disease burden'!AV217 -> 0.085275992
C62: Vaccine efficacy for people under age 5, aggregated across vaccines
E63: Proportion of vaccine-preventable disease incidence averted by full vaccination among people under age 5, aggregated across vaccines | F63: % | G63: calc | H63: - | I63: =SUMPRODUCT($H$47:$H$52,I55:I60) -> 0.52255605 | J63: =SUMPRODUCT($H$47:$H$52,J55:J60) -> 0.52738394 | K63: =SUMPRODUCT($H$47:$H$52,K55:K60) -> 0.5508425 | L63: =SUMPRODUCT($H$47:$H$52,L55:L60) -> 0.54371205 | M63: =SUMPRODUCT($H$47:$H$52,M55:M60) -> 0.51595309 | N63: =SUMPRODUCT($H$47:$H$52,N55:N60) -> 0.54582208 | O63: =SUMPRODUCT($H$47:$H$52,O55:O60) -> 0.55824395 | P63: =SUMPRODUCT($H$47:$H$52,P55:P60) -> 0.53001202 | ... AV63: =SUMPRODUCT($H$47:$H$52,AV55:AV60) -> 0.57218524
C65: Vaccine coverage for populations under age 5 represented by GBD 2021, aggregated across doses
E66: Proportion of people under age 5 represented in GBD 2021 disease burden estimates who received the BCG vaccine | F66: ='Vaccine coverage'!F163 -> % | G66: supp | H66: ='Vaccine coverage'!H163 -> - | I66: ='Vaccine coverage'!I163 -> 0.46737589 | J66: ='Vaccine coverage'!J163 -> 0.56161257 | K66: ='Vaccine coverage'!K163 -> 0.60444743 | L66: ='Vaccine coverage'!L163 -> 0.74342274 | M66: ='Vaccine coverage'!M163 -> 0.57398709 | N66: ='Vaccine coverage'!N163 -> 0.54162297 | O66: ='Vaccine coverage'!O163 -> 0.60539931 | ... AV66: ='Vaccine coverage'!AV163 -> 0.71581806
E67: Proportion of people under age 5 represented in GBD 2021 disease burden estimates who received the DTP vaccine, aggregated across doses | F67: ='Vaccine coverage'!F164 -> % | G67: supp | H67: ='Vaccine coverage'!H164 -> - | I67: ='Vaccine coverage'!I164 -> 0.36757067 | J67: ='Vaccine coverage'!J164 -> 0.48479539 | K67: ='Vaccine coverage'!K164 -> 0.54628721 | L67: ='Vaccine coverage'!L164 -> 0.64742507 | M67: ='Vaccine coverage'!M164 -> 0.46932725 | N67: ='Vaccine coverage'!N164 -> 0.4597608 | O67: ='Vaccine coverage'!O164 -> 0.55642479 | ... AV67: ='Vaccine coverage'!AV164 -> 0.67974159
E68: Proportion of people under age 5 represented in GBD 2021 disease burden estimates who received the Hib vaccine, aggregated across doses | F68: ='Vaccine coverage'!F165 -> % | G68: supp | H68: ='Vaccine coverage'!H165 -> - | I68: ='Vaccine coverage'!I165 -> 0.36757067 | J68: ='Vaccine coverage'!J165 -> 0.48479539 | K68: ='Vaccine coverage'!K165 -> 0.54628721 | L68: ='Vaccine coverage'!L165 -> 0.64742507 | M68: ='Vaccine coverage'!M165 -> 0.46932725 | N68: ='Vaccine coverage'!N165 -> 0.4597608 | O68: ='Vaccine coverage'!O165 -> 0.55642479 | ... AV68: ='Vaccine coverage'!AV165 -> 0.67974159
E69: Proportion of people under age 5 represented in GBD 2021 disease burden estimates who received the PCV vaccine, aggregated across doses | F69: ='Vaccine coverage'!F166 -> % | G69: supp | H69: ='Vaccine coverage'!H166 -> - | I69: ='Vaccine coverage'!I166 -> 0.36699954 | J69: ='Vaccine coverage'!J166 -> 0.45352595 | K69: ='Vaccine coverage'!K166 -> 0.53843415 | L69: ='Vaccine coverage'!L166 -> 0.63476499 | M69: ='Vaccine coverage'!M166 -> 0.46318759 | N69: ='Vaccine coverage'!N166 -> 0.43962842 | O69: ='Vaccine coverage'!O166 -> 0.54776263 | ... AV69: ='Vaccine coverage'!AV166 -> 0.65646798
E70: Proportion of people under age 5 represented in GBD 2021 disease burden estimates who received the rotavirus vaccine, aggregated across doses | F70: ='Vaccine coverage'!F167 -> % | G70: supp | H70: ='Vaccine coverage'!H167 -> - | I70: ='Vaccine coverage'!I167 -> 0 | J70: ='Vaccine coverage'!J167 -> 0 | K70: ='Vaccine coverage'!K167 -> 0 | L70: ='Vaccine coverage'!L167 -> 0 | M70: ='Vaccine coverage'!M167 -> 0 | N70: ='Vaccine coverage'!N167 -> 0 | O70: ='Vaccine coverage'!O167 -> 0 | ... AV70: ='Vaccine coverage'!AV167 -> 0
E71: Proportion of people under age 5 represented in GBD 2021 disease burden estimates who received the measles vaccine | F71: ='Vaccine coverage'!F168 -> % | G71: supp | H71: ='Vaccine coverage'!H168 -> - | I71: ='Vaccine coverage'!I168 -> 0.28260429 | J71: ='Vaccine coverage'!J168 -> 0.33934726 | K71: ='Vaccine coverage'!K168 -> 0.51983537 | L71: ='Vaccine coverage'!L168 -> 0.5260755 | M71: ='Vaccine coverage'!M168 -> 0.37160561 | N71: ='Vaccine coverage'!N168 -> 0.40592637 | O71: ='Vaccine coverage'!O168 -> 0.59720252 | ... AV71: ='Vaccine coverage'!AV168 -> 0.66658441
C73: Vaccine coverage for populations under age 5 represented by GBD 2021, aggregated across vaccines
E74: Proportion of people under age 5 represented in GBD 2021 disease burden estimates who were vaccinated, aggregated across vaccines | F74: % | G74: calc | H74: - | I74: =SUMPRODUCT($H47:$H52,I55:I60,I66:I71)/I63 -> 0.27723536 | J74: =SUMPRODUCT($H47:$H52,J55:J60,J66:J71)/J63 -> 0.35272184 | K74: =SUMPRODUCT($H47:$H52,K55:K60,K66:K71)/K63 -> 0.44729281 | L74: =SUMPRODUCT($H47:$H52,L55:L60,L66:L71)/L63 -> 0.51957609 | M74: =SUMPRODUCT($H47:$H52,M55:M60,M66:M71)/M63 -> 0.35511405 | N74: =SUMPRODUCT($H47:$H52,N55:N60,N66:N71)/N63 -> 0.35528503 | O74: =SUMPRODUCT($H47:$H52,O55:O60,O66:O71)/O63 -> 0.44566539 | P74: =SUMPRODUCT($H47:$H52,P55:P60,P66:P71)/P63 -> 0.15656944 | ... AV74: =SUMPRODUCT($H47:$H52,AV55:AV60,AV66:AV71)/AV63 -> 0.55188809
A76: Vaccine efficacy and coverage for older age groups, aggregated across vaccines
C78: Effect of vaccination on disease incidence among 5-14-year-olds
E79: Proportion of vaccine-preventable disease incidence averted by BCG vaccination among 5-14-year-olds | F79: ='Disease burden'!F241 -> % | G79: supp | H79: ='Disease burden'!H241 -> 0.53772268 | I79: ='Disease burden'!I241 -> - | J79: ='Disease burden'!J241 -> - | K79: ='Disease burden'!K241 -> - | L79: ='Disease burden'!L241 -> - | M79: ='Disease burden'!M241 -> - | N79: ='Disease burden'!N241 -> - | O79: ='Disease burden'!O241 -> - | ... AV79: ='Disease burden'!AV241 -> -
E80: Proportion of vaccine-preventable disease incidence averted by DTP vaccination among 5-14-year-olds | F80: ='Disease burden'!F242 -> % | G80: supp | H80: ='Disease burden'!H242 -> 0.76584745 | I80: ='Disease burden'!I242 -> - | J80: ='Disease burden'!J242 -> - | K80: ='Disease burden'!K242 -> - | L80: ='Disease burden'!L242 -> - | M80: ='Disease burden'!M242 -> - | N80: ='Disease burden'!N242 -> - | O80: ='Disease burden'!O242 -> - | ... AV80: ='Disease burden'!AV242 -> - | AW80: ='Vaccine efficacy'!AW91
E81: Proportion of vaccine-preventable disease incidence averted by Hib vaccination among 5-14-year-olds | F81: ='Disease burden'!F243 -> % | G81: supp | H81: ='Disease burden'!H243 -> 0.66807969 | I81: ='Disease burden'!I243 -> - | J81: ='Disease burden'!J243 -> - | K81: ='Disease burden'!K243 -> - | L81: ='Disease burden'!L243 -> - | M81: ='Disease burden'!M243 -> - | N81: ='Disease burden'!N243 -> - | O81: ='Disease burden'!O243 -> - | ... AV81: ='Disease burden'!AV243 -> - | AW81: ='Vaccine efficacy'!AW92
E82: Proportion of vaccine-preventable disease incidence averted by PCV vaccination among 5-14-year-olds | F82: ='Disease burden'!F244 -> % | G82: supp | H82: ='Disease burden'!H244 -> 0.38699738 | I82: ='Disease burden'!I244 -> - | J82: ='Disease burden'!J244 -> - | K82: ='Disease burden'!K244 -> - | L82: ='Disease burden'!L244 -> - | M82: ='Disease burden'!M244 -> - | N82: ='Disease burden'!N244 -> - | O82: ='Disease burden'!O244 -> - | ... AV82: ='Disease burden'!AV244 -> - | AW82: ='Vaccine efficacy'!AW93
E83: Proportion of vaccine-preventable disease incidence averted by rotavirus vaccination among 5-14-year-olds | F83: ='Disease burden'!F245 -> % | G83: supp | H83: ='Disease burden'!H245 -> 0.37477641 | I83: ='Disease burden'!I245 -> - | J83: ='Disease burden'!J245 -> - | K83: ='Disease burden'!K245 -> - | L83: ='Disease burden'!L245 -> - | M83: ='Disease burden'!M245 -> - | N83: ='Disease burden'!N245 -> - | O83: ='Disease burden'!O245 -> - | ... AV83: ='Disease burden'!AV245 -> - | AW83: ='Vaccine efficacy'!AW94
E84: Proportion of vaccine-preventable disease incidence averted by measles vaccination among 5-14-year-olds | F84: ='Disease burden'!F246 -> % | G84: supp | H84: ='Disease burden'!H246 -> 0.69346707 | I84: ='Disease burden'!I246 -> - | J84: ='Disease burden'!J246 -> - | K84: ='Disease burden'!K246 -> - | L84: ='Disease burden'!L246 -> - | M84: ='Disease burden'!M246 -> - | N84: ='Disease burden'!N246 -> - | O84: ='Disease burden'!O246 -> - | ... AV84: ='Disease burden'!AV246 -> - | AW84: ='Vaccine efficacy'!AW95
C86: Proportion of deaths from vaccine-preventable causes among unvaccinated 5-14-year-olds that are addressable by each vaccine
E87: Proportion of deaths from vaccine-preventable causes among unvaccinated 5-14-year-olds that are addressable by the BCG vaccine | F87: ='Disease burden'!F258 -> % | G87: supp | H87: ='Disease burden'!H258 -> - | I87: ='Disease burden'!I258 -> 0.22178408 | J87: ='Disease burden'!J258 -> 0.15698863 | K87: ='Disease burden'!K258 -> 0.24595035 | L87: ='Disease burden'!L258 -> 0.13109275 | M87: ='Disease burden'!M258 -> 0.17569366 | N87: ='Disease burden'!N258 -> 0.2107788 | O87: ='Disease burden'!O258 -> 0.20256377 | ... AV87: ='Disease burden'!AV258 -> 0.2257499
E88: Proportion of deaths from vaccine-preventable causes among unvaccinated 5-14-year-olds that are addressable by the DTP vaccine | F88: ='Disease burden'!F259 -> % | G88: supp | H88: ='Disease burden'!H259 -> - | I88: ='Disease burden'!I259 -> 0.14031797 | J88: ='Disease burden'!J259 -> 0.1835698 | K88: ='Disease burden'!K259 -> 0.17333424 | L88: ='Disease burden'!L259 -> 0.21734168 | M88: ='Disease burden'!M259 -> 0.15530838 | N88: ='Disease burden'!N259 -> 0.17135793 | O88: ='Disease burden'!O259 -> 0.2098095 | ... AV88: ='Disease burden'!AV259 -> 0.16565003
E89: Proportion of deaths from vaccine-preventable causes among unvaccinated 5-14-year-olds that are addressable by the Hib vaccine | F89: ='Disease burden'!F260 -> % | G89: supp | H89: ='Disease burden'!H260 -> - | I89: ='Disease burden'!I260 -> 0.024664851 | J89: ='Disease burden'!J260 -> 0.03129199 | K89: ='Disease burden'!K260 -> 0.026218315 | L89: ='Disease burden'!L260 -> 0.035770965 | M89: ='Disease burden'!M260 -> 0.036344747 | N89: ='Disease burden'!N260 -> 0.024817496 | O89: ='Disease burden'!O260 -> 0.024006143 | ... AV89: ='Disease burden'!AV260 -> 0.025907705
E90: Proportion of deaths from vaccine-preventable causes among unvaccinated 5-14-year-olds that are addressable by the PCV vaccine | F90: ='Disease burden'!F261 -> % | G90: supp | H90: ='Disease burden'!H261 -> - | I90: ='Disease burden'!I261 -> 0.29834256 | J90: ='Disease burden'!J261 -> 0.36886761 | K90: ='Disease burden'!K261 -> 0.30625822 | L90: ='Disease burden'!L261 -> 0.41180935 | M90: ='Disease burden'!M261 -> 0.43364213 | N90: ='Disease burden'!N261 -> 0.29413777 | O90: ='Disease burden'!O261 -> 0.27839123 | ... AV90: ='Disease burden'!AV261 -> 0.29319644
E91: Proportion of deaths from vaccine-preventable causes among unvaccinated 5-14-year-olds that are addressable by the rotavirus vaccine | F91: ='Disease burden'!F262 -> % | G91: supp | H91: ='Disease burden'!H262 -> - | I91: ='Disease burden'!I262 -> 0.21023639 | J91: ='Disease burden'!J262 -> 0.17888008 | K91: ='Disease burden'!K262 -> 0.12644902 | L91: ='Disease burden'!L262 -> 0.10372287 | M91: ='Disease burden'!M262 -> 0.13753205 | N91: ='Disease burden'!N262 -> 0.16691934 | O91: ='Disease burden'!O262 -> 0.16722274 | ... AV91: ='Disease burden'!AV262 -> 0.18444673
E92: Proportion of deaths from vaccine-preventable causes among unvaccinated 5-14-year-olds that are addressable by the measles vaccine | F92: ='Disease burden'!F263 -> % | G92: supp | H92: ='Disease burden'!H263 -> - | I92: ='Disease burden'!I263 -> 0.10465414 | J92: ='Disease burden'!J263 -> 0.080401886 | K92: ='Disease burden'!K263 -> 0.12178987 | L92: ='Disease burden'!L263 -> 0.10026238 | M92: ='Disease burden'!M263 -> 0.061479028 | N92: ='Disease burden'!N263 -> 0.13198866 | O92: ='Disease burden'!O263 -> 0.11800662 | ... AV92: ='Disease burden'!AV263 -> 0.1050492
C94: Vaccine efficacy, aggregated across vaccines
E95: Proportion of vaccine-preventable disease incidence averted by full vaccination among 5-14-year-olds, aggregated across vaccines | F95: % | G95: calc | H95: - | I95: =SUMPRODUCT($H79:$H84,I87:I92) -> 0.51002221 | J95: =SUMPRODUCT($H79:$H84,J87:J92) -> 0.51145525 | K95: =SUMPRODUCT($H79:$H84,K87:K92) -> 0.53288509 | L95: =SUMPRODUCT($H79:$H84,L87:L92) -> 0.52861066 | M95: =SUMPRODUCT($H79:$H84,M87:M92) -> 0.499694 | N95: =SUMPRODUCT($H79:$H84,N87:N92) -> 0.52907241 | O95: =SUMPRODUCT($H79:$H84,O87:O92) -> 0.53788474 | P95: =SUMPRODUCT($H79:$H84,P87:P92) -> 0.53040758 | ... AV95: =SUMPRODUCT($H79:$H84,AV87:AV92) -> 0.5210026
C97: Vaccine coverage for 5-14-year-old populations represented by GBD 2021, aggregated across doses
E98: Adjustment for lower vaccine coverage among 5-14-year-olds represented in GBD 2021 disease burden estimates | F98: =Inputs!F193 -> % | G98: =Inputs!G193 -> input | H98: =Inputs!H193 -> -0.5 | I98: =Inputs!I193 -> - | J98: =Inputs!J193 -> - | K98: =Inputs!K193 -> - | L98: =Inputs!L193 -> - | M98: =Inputs!M193 -> - | ... AV98: =Inputs!AV193 -> -
E99: Proportion of 5-14-year-olds represented in GBD 2021 disease burden estimates who received the BCG vaccine | F99: % | G99: calc | H99: - | I99: =I66*(1+$H$98) -> 0.23368794 | J99: =J66*(1+$H$98) -> 0.28080629 | K99: =K66*(1+$H$98) -> 0.30222371 | L99: =L66*(1+$H$98) -> 0.37171137 | M99: =M66*(1+$H$98) -> 0.28699354 | N99: =N66*(1+$H$98) -> 0.27081149 | O99: =O66*(1+$H$98) -> 0.30269966 | P99: =P66*(1+$H$98) -> 0.16039274 | ... AV99: =AV66*(1+$H$98) -> 0.35790903
E100: Proportion of 5-14-year-olds represented in GBD 2021 disease burden estimates who received the DTP vaccine, aggregated across doses | F100: % | G100: calc | H100: - | I100: =I67*(1+$H$98) -> 0.18378533 | J100: =J67*(1+$H$98) -> 0.2423977 | K100: =K67*(1+$H$98) -> 0.27314361 | L100: =L67*(1+$H$98) -> 0.32371253 | M100: =M67*(1+$H$98) -> 0.23466363 | N100: =N67*(1+$H$98) -> 0.2298804 | O100: =O67*(1+$H$98) -> 0.2782124 | P100: =P67*(1+$H$98) -> 0.1016138 | ... AV100: =AV67*(1+$H$98) -> 0.33987079
E101: Proportion of 5-14-year-olds represented in GBD 2021 disease burden estimates who received the Hib vaccine, aggregated across doses | F101: % | G101: calc | H101: - | I101: =I68*(1+$H$98) -> 0.18378533 | J101: =J68*(1+$H$98) -> 0.2423977 | K101: =K68*(1+$H$98) -> 0.27314361 | L101: =L68*(1+$H$98) -> 0.32371253 | M101: =M68*(1+$H$98) -> 0.23466363 | N101: =N68*(1+$H$98) -> 0.2298804 | O101: =O68*(1+$H$98) -> 0.2782124 | P101: =P68*(1+$H$98) -> 0.1016138 | ... AV101: =AV68*(1+$H$98) -> 0.33987079
E102: Proportion of 5-14-year-olds represented in GBD 2021 disease burden estimates who received the PCV vaccine, aggregated across doses | F102: % | G102: calc | H102: - | I102: =I69*(1+$H$98) -> 0.18349977 | J102: =J69*(1+$H$98) -> 0.22676297 | K102: =K69*(1+$H$98) -> 0.26921708 | L102: =L69*(1+$H$98) -> 0.31738249 | M102: =M69*(1+$H$98) -> 0.23159379 | N102: =N69*(1+$H$98) -> 0.21981421 | O102: =O69*(1+$H$98) -> 0.27388132 | P102: =P69*(1+$H$98) -> 0.078245006 | ... AV102: =AV69*(1+$H$98) -> 0.32823399
E103: Proportion of 5-14-year-olds represented in GBD 2021 disease burden estimates who received the rotavirus vaccine, aggregated across doses | F103: % | G103: calc | H103: - | I103: =I70*(1+$H$98) -> 0 | J103: =J70*(1+$H$98) -> 0 | K103: =K70*(1+$H$98) -> 0 | L103: =L70*(1+$H$98) -> 0 | M103: =M70*(1+$H$98) -> 0 | N103: =N70*(1+$H$98) -> 0 | O103: =O70*(1+$H$98) -> 0 | P103: =P70*(1+$H$98) -> 0 | ... AV103: =AV70*(1+$H$98) -> 0
E104: Proportion of 5-14-year-olds represented in GBD 2021 disease burden estimates who received the measles vaccine | F104: % | G104: calc | H104: - | I104: =I71*(1+$H$98) -> 0.14130215 | J104: =J71*(1+$H$98) -> 0.16967363 | K104: =K71*(1+$H$98) -> 0.25991768 | L104: =L71*(1+$H$98) -> 0.26303775 | M104: =M71*(1+$H$98) -> 0.1858028 | N104: =N71*(1+$H$98) -> 0.20296319 | O104: =O71*(1+$H$98) -> 0.29860126 | P104: =P71*(1+$H$98) -> 0.090746438 | ... AV104: =AV71*(1+$H$98) -> 0.33329221
C106: Vaccine coverage for 5-14-year-old populations represented by GBD 2021, aggregated across vaccines
E107: Proportion of 5-14-year-olds represented in GBD 2021 disease burden estimates who were vaccinated, aggregated across vaccines | F107: % | G107: calc | H107: - | I107: =SUMPRODUCT($H79:$H84,I87:I92,I99:I104)/I95 -> 0.16095182 | J107: =SUMPRODUCT($H79:$H84,J87:J92,J99:J104)/J95 -> 0.20467257 | K107: =SUMPRODUCT($H79:$H84,K87:K92,K99:K104)/K95 -> 0.25310031 | L107: =SUMPRODUCT($H79:$H84,L87:L92,L99:L104)/L95 -> 0.29641914 | M107: =SUMPRODUCT($H79:$H84,M87:M92,M99:M104)/M95 -> 0.21515189 | N107: =SUMPRODUCT($H79:$H84,N87:N92,N99:N104)/N95 -> 0.2046454 | O107: =SUMPRODUCT($H79:$H84,O87:O92,O99:O104)/O95 -> 0.25298993 | P107: =SUMPRODUCT($H79:$H84,P87:P92,P99:P104)/P95 -> 0.09641527 | ... AV107: =SUMPRODUCT($H79:$H84,AV87:AV92,AV99:AV104)/AV95 -> 0.29552562
C109: Effect of vaccination on disease incidence among 15-49-year-olds
E110: Proportion of vaccine-preventable disease incidence averted by BCG vaccination among 15-49-year-olds | F110: ='Disease burden'!F286 -> % | G110: supp | H110: ='Disease burden'!H286 -> 0.11949393 | I110: ='Disease burden'!I286 -> - | J110: ='Disease burden'!J286 -> - | K110: ='Disease burden'!K286 -> - | L110: ='Disease burden'!L286 -> - | M110: ='Disease burden'!M286 -> - | N110: ='Disease burden'!N286 -> - | O110: ='Disease burden'!O286 -> - | ... AV110: ='Disease burden'!AV286 -> -
E111: Proportion of vaccine-preventable disease incidence averted by DTP vaccination among 15-49-year-olds | F111: ='Disease burden'!F287 -> % | G111: supp | H111: ='Disease burden'!H287 -> 0.51056497 | I111: ='Disease burden'!I287 -> - | J111: ='Disease burden'!J287 -> - | K111: ='Disease burden'!K287 -> - | L111: ='Disease burden'!L287 -> - | M111: ='Disease burden'!M287 -> - | N111: ='Disease burden'!N287 -> - | O111: ='Disease burden'!O287 -> - | ... AV111: ='Disease burden'!AV287 -> -
E112: Proportion of vaccine-preventable disease incidence averted by Hib vaccination among 15-49-year-olds | F112: ='Disease burden'!F288 -> % | G112: supp | H112: ='Disease burden'!H288 -> 0.44538646 | I112: ='Disease burden'!I288 -> - | J112: ='Disease burden'!J288 -> - | K112: ='Disease burden'!K288 -> - | L112: ='Disease burden'!L288 -> - | M112: ='Disease burden'!M288 -> - | N112: ='Disease burden'!N288 -> - | O112: ='Disease burden'!O288 -> - | ... AV112: ='Disease burden'!AV288 -> -
E113: Proportion of vaccine-preventable disease incidence averted by PCV vaccination among 15-49-year-olds | F113: ='Disease burden'!F289 -> % | G113: supp | H113: ='Disease burden'!H289 -> 0.25799825 | I113: ='Disease burden'!I289 -> - | J113: ='Disease burden'!J289 -> - | K113: ='Disease burden'!K289 -> - | L113: ='Disease burden'!L289 -> - | M113: ='Disease burden'!M289 -> - | N113: ='Disease burden'!N289 -> - | O113: ='Disease burden'!O289 -> - | ... AV113: ='Disease burden'!AV289 -> -
E114: Proportion of vaccine-preventable disease incidence averted by rotavirus vaccination among 15-49-year-olds | F114: ='Disease burden'!F290 -> % | G114: supp | H114: ='Disease burden'!H290 -> 0.24985094 | I114: ='Disease burden'!I290 -> - | J114: ='Disease burden'!J290 -> - | K114: ='Disease burden'!K290 -> - | L114: ='Disease burden'!L290 -> - | M114: ='Disease burden'!M290 -> - | N114: ='Disease burden'!N290 -> - | O114: ='Disease burden'!O290 -> - | ... AV114: ='Disease burden'!AV290 -> -
E115: Proportion of vaccine-preventable disease incidence averted by measles vaccination among 15-49-year-olds | F115: ='Disease burden'!F291 -> % | G115: supp | H115: ='Disease burden'!H291 -> 0.46231138 | I115: ='Disease burden'!I291 -> - | J115: ='Disease burden'!J291 -> - | K115: ='Disease burden'!K291 -> - | L115: ='Disease burden'!L291 -> - | M115: ='Disease burden'!M291 -> - | N115: ='Disease burden'!N291 -> - | O115: ='Disease burden'!O291 -> - | ... AV115: ='Disease burden'!AV291 -> -
C117: Proportion of deaths from vaccine-preventable causes among unvaccinated 15-49-year-olds that are addressable by each vaccine
...

Sheet Treatment effect
I1: New Incentives – current states of operation | R1: New Incentives – prospective states | AF1: New Incentives – prospective states
I2: Nigeria | J2: Nigeria | K2: Nigeria | L2: Nigeria | M2: Nigeria | N2: Nigeria | O2: Nigeria | P2: Nigeria | Q2: Nigeria | R2: Nigeria | S2: Nigeria | T2: Nigeria | U2: Nigeria | V2: Nigeria | W2: Nigeria | X2: Nigeria | Y2: Nigeria | Z2: Nigeria | AA2: Nigeria | AB2: Nigeria | AC2: Nigeria | AD2: Nigeria | AE2: Nigeria | AF2: Nigeria | AG2: Nigeria | AH2: Nigeria | AI2: Nigeria | AJ2: Nigeria | AK2: Nigeria | AL2: Nigeria | AM2: Nigeria | AN2: Nigeria | AO2: Nigeria | AP2: Nigeria | AQ2: Nigeria | AR2: Nigeria | AS2: Nigeria | AT2: Nigeria | AU2: Nigeria | AV2: Nigeria
A3: Main calculations | F3: unit | G3: type | H3: Overall | I3: Bauchi | J3: Gombe | K3: Jigawa | L3: Kaduna - cohort 17 | M3: Kano | N3: Katsina | O3: Kebbi | P3: Sokoto | Q3: Zamfara | R3: Abia | S3: Adamawa | T3: Akwa Ibom | U3: Anambra | V3: Bayelsa | W3: Benue | X3: Borno | Y3: Cross River | Z3: Delta | AA3: Ebonyi | AB3: Edo | AC3: Ekiti | AD3: Enugu | AE3: FCT | AF3: Imo | AG3: Kaduna | AH3: Kogi | AI3: Kwara | AJ3: Lagos | AK3: Nasarawa | AL3: Niger | AM3: Niger - cohorts 32 & 36 | AN3: Niger - cohort 34 | AO3: Ogun | AP3: Ondo | AQ3: Osun | AR3: Oyo | AS3: Plateau | AT3: Rivers | AU3: Taraba | AV3: Yobe
E4: Final cost-effectiveness estimate (pulled from "Main calcs" sheet for visibility) | F4: ='Main CEA'!F242 -> xbenchmark | G4: ='Main CEA'!G242 -> calc | H4: ='Main CEA'!H242 -> - | I4: ='Main CEA'!I242 -> 20.039606 | J4: ='Main CEA'!J242 -> 10.020838 | K4: ='Main CEA'!K242 -> 18.177505 | L4: ='Main CEA'!L242 -> 9.0027672 | M4: ='Main CEA'!M242 -> 12.612827 | ... AV4: ='Main CEA'!AV242 -> 11.471963
A5: Vaccination coverage rates for the control group of the New Incentives RCT
C7: Vaccination coverage rates for the control group of the New Incentives RCT
E8: Proportion of children in the New Incentives RCT control group who reported receiving the BCG vaccine | F8: =Inputs!F208 -> % | G8: =Inputs!G208 -> input | H8: =Inputs!H208 -> 0.63 | I8: =Inputs!I208 -> - | J8: =Inputs!J208 -> - | K8: =Inputs!K208 -> - | L8: =Inputs!L208 -> - | M8: =Inputs!M208 -> - | ... AV8: =Inputs!AV208 -> -
E9: Proportion of children in the New Incentives RCT control group who reported receiving the 1st dose of the Penta vaccine | F9: =Inputs!F209 -> % | G9: =Inputs!G209 -> input | H9: =Inputs!H209 -> 0.5419 | I9: =Inputs!I209 -> - | J9: =Inputs!J209 -> - | K9: =Inputs!K209 -> - | L9: =Inputs!L209 -> - | M9: =Inputs!M209 -> - | ... AV9: =Inputs!AV209 -> -
E10: Proportion of children in the New Incentives RCT control group who reported receiving the 2nd dose of the Penta vaccine | F10: =Inputs!F210 -> % | G10: =Inputs!G210 -> input | H10: =Inputs!H210 -> 0.3961 | I10: =Inputs!I210 -> - | J10: =Inputs!J210 -> - | K10: =Inputs!K210 -> - | L10: =Inputs!L210 -> - | M10: =Inputs!M210 -> - | ... AV10: =Inputs!AV210 -> -
E11: Proportion of children in the New Incentives RCT control group who reported receiving the 3rd dose of the Penta vaccine | F11: =Inputs!F211 -> % | G11: =Inputs!G211 -> input | H11: =Inputs!H211 -> 0.2978 | I11: =Inputs!I211 -> - | J11: =Inputs!J211 -> - | K11: =Inputs!K211 -> - | L11: =Inputs!L211 -> - | M11: =Inputs!M211 -> - | ... AV11: =Inputs!AV211 -> -
E12: Proportion of children in the New Incentives RCT control group who reported receiving the 1st dose of the PCV vaccine | F12: =Inputs!F212 -> % | G12: =Inputs!G212 -> input | H12: =Inputs!H212 -> 0.4954 | I12: =Inputs!I212 -> - | J12: =Inputs!J212 -> - | K12: =Inputs!K212 -> - | L12: =Inputs!L212 -> - | M12: =Inputs!M212 -> - | ... AV12: =Inputs!AV212 -> -
E13: Proportion of children in the New Incentives RCT control group who reported receiving the 2nd dose of the PCV vaccine | F13: =Inputs!F213 -> % | G13: =Inputs!G213 -> input | H13: =Inputs!H213 -> 0.3554 | I13: =Inputs!I213 -> - | J13: =Inputs!J213 -> - | K13: =Inputs!K213 -> - | L13: =Inputs!L213 -> - | M13: =Inputs!M213 -> - | ... AV13: =Inputs!AV213 -> -
E14: Proportion of children in the New Incentives RCT control group who reported receiving the 3rd dose of the PCV vaccine | F14: =Inputs!F214 -> % | G14: =Inputs!G214 -> input | H14: =Inputs!H214 -> 0.266 | I14: =Inputs!I214 -> - | J14: =Inputs!J214 -> - | K14: =Inputs!K214 -> - | L14: =Inputs!L214 -> - | M14: =Inputs!M214 -> - | ... AV14: =Inputs!AV214 -> -
E15: Proportion of children in the New Incentives RCT control group who reported receiving the measles vaccine | F15: =Inputs!F215 -> % | G15: =Inputs!G215 -> input | H15: =Inputs!H215 -> 0.5894 | I15: =Inputs!I215 -> - | J15: =Inputs!J215 -> - | K15: =Inputs!K215 -> - | L15: =Inputs!L215 -> - | M15: =Inputs!M215 -> - | ... AV15: =Inputs!AV215 -> -
C17: Adjustment for self-report bias
E18: Adjustment for self-report bias in the New Incentives RCT | F18: =Inputs!F218 -> % | G18: =Inputs!G218 -> input | H18: =Inputs!H218 -> -0.2768959 | I18: =Inputs!I218 -> - | J18: =Inputs!J218 -> - | K18: =Inputs!K218 -> - | L18: =Inputs!L218 -> - | M18: =Inputs!M218 -> - | ... AV18: =Inputs!AV218 -> -
C20: Vaccination coverage rates for the control group of the New Incentives RCT, adjusted for self-report bias
E21: Proportion of children in the New Incentives RCT control group who received the BCG vaccine | F21: % | G21: calc | H21: =H8*(1+H$18) -> 0.45555558 | I21: - | J21: - | K21: - | L21: - | M21: - | N21: - | O21: - | P21: - | Q21: - | R21: - | S21: - | T21: - | U21: - | V21: - | W21: - | X21: - | Y21: - | Z21: - | AA21: - | AB21: - | AC21: - | AD21: - | AE21: - | AF21: - | AG21: - | AH21: - | AI21: - | AJ21: - | AK21: - | AL21: - | AM21: - | AN21: - | AO21: - | AP21: - | AQ21: - | AR21: - | AS21: - | AT21: - | AU21: - | AV21: -
E22: Proportion of children in the New Incentives RCT control group who received the 1st dose of the Penta vaccine | F22: % | G22: calc | H22: =H9*(1+H$18) -> 0.39185011 | I22: - | J22: - | K22: - | L22: - | M22: - | N22: - | O22: - | P22: - | Q22: - | R22: - | S22: - | T22: - | U22: - | V22: - | W22: - | X22: - | Y22: - | Z22: - | AA22: - | AB22: - | AC22: - | AD22: - | AE22: - | AF22: - | AG22: - | AH22: - | AI22: - | AJ22: - | AK22: - | AL22: - | AM22: - | AN22: - | AO22: - | AP22: - | AQ22: - | AR22: - | AS22: - | AT22: - | AU22: - | AV22: -
E23: Proportion of children in the New Incentives RCT control group who received the 2nd dose of the Penta vaccine | F23: % | G23: calc | H23: =H10*(1+H$18) -> 0.28642153 | I23: - | J23: - | K23: - | L23: - | M23: - | N23: - | O23: - | P23: - | Q23: - | R23: - | S23: - | T23: - | U23: - | V23: - | W23: - | X23: - | Y23: - | Z23: - | AA23: - | AB23: - | AC23: - | AD23: - | AE23: - | AF23: - | AG23: - | AH23: - | AI23: - | AJ23: - | AK23: - | AL23: - | AM23: - | AN23: - | AO23: - | AP23: - | AQ23: - | AR23: - | AS23: - | AT23: - | AU23: - | AV23: -
E24: Proportion of children in the New Incentives RCT control group who received the 3rd dose of the Penta vaccine | F24: % | G24: calc | H24: =H11*(1+H$18) -> 0.2153404 | I24: - | J24: - | K24: - | L24: - | M24: - | N24: - | O24: - | P24: - | Q24: - | R24: - | S24: - | T24: - | U24: - | V24: - | W24: - | X24: - | Y24: - | Z24: - | AA24: - | AB24: - | AC24: - | AD24: - | AE24: - | AF24: - | AG24: - | AH24: - | AI24: - | AJ24: - | AK24: - | AL24: - | AM24: - | AN24: - | AO24: - | AP24: - | AQ24: - | AR24: - | AS24: - | AT24: - | AU24: - | AV24: -
E25: Proportion of children in the New Incentives RCT control group who received the 1st dose of the PCV vaccine | F25: % | G25: calc | H25: =H12*(1+H$18) -> 0.35822577 | I25: - | J25: - | K25: - | L25: - | M25: - | N25: - | O25: - | P25: - | Q25: - | R25: - | S25: - | T25: - | U25: - | V25: - | W25: - | X25: - | Y25: - | Z25: - | AA25: - | AB25: - | AC25: - | AD25: - | AE25: - | AF25: - | AG25: - | AH25: - | AI25: - | AJ25: - | AK25: - | AL25: - | AM25: - | AN25: - | AO25: - | AP25: - | AQ25: - | AR25: - | AS25: - | AT25: - | AU25: - | AV25: -
E26: Proportion of children in the New Incentives RCT control group who received the 2nd dose of the PCV vaccine | F26: % | G26: calc | H26: =H13*(1+H$18) -> 0.2569912 | I26: - | J26: - | K26: - | L26: - | M26: - | N26: - | O26: - | P26: - | Q26: - | R26: - | S26: - | T26: - | U26: - | V26: - | W26: - | X26: - | Y26: - | Z26: - | AA26: - | AB26: - | AC26: - | AD26: - | AE26: - | AF26: - | AG26: - | AH26: - | AI26: - | AJ26: - | AK26: - | AL26: - | AM26: - | AN26: - | AO26: - | AP26: - | AQ26: - | AR26: - | AS26: - | AT26: - | AU26: - | AV26: -
E27: Proportion of children in the New Incentives RCT control group who received the 3rd dose of the PCV vaccine | F27: % | G27: calc | H27: =H14*(1+H$18) -> 0.19234569 | I27: - | J27: - | K27: - | L27: - | M27: - | N27: - | O27: - | P27: - | Q27: - | R27: - | S27: - | T27: - | U27: - | V27: - | W27: - | X27: - | Y27: - | Z27: - | AA27: - | AB27: - | AC27: - | AD27: - | AE27: - | AF27: - | AG27: - | AH27: - | AI27: - | AJ27: - | AK27: - | AL27: - | AM27: - | AN27: - | AO27: - | AP27: - | AQ27: - | AR27: - | AS27: - | AT27: - | AU27: - | AV27: -
E28: Proportion of children in the New Incentives RCT control group who received the measles vaccine | F28: % | G28: calc | H28: =H15*(1+H$18) -> 0.42619756 | I28: - | J28: - | K28: - | L28: - | M28: - | N28: - | O28: - | P28: - | Q28: - | R28: - | S28: - | T28: - | U28: - | V28: - | W28: - | X28: - | Y28: - | Z28: - | AA28: - | AB28: - | AC28: - | AD28: - | AE28: - | AF28: - | AG28: - | AH28: - | AI28: - | AJ28: - | AK28: - | AL28: - | AM28: - | AN28: - | AO28: - | AP28: - | AQ28: - | AR28: - | AS28: - | AT28: - | AU28: - | AV28: -
C30: Proportion of vaccine-preventable mortalities that could be prevented by each vaccine dose
E31: Proportion of vaccine-preventable mortalities among people under age 5 that could be prevented by the BCG vaccine | F31: ='Disease burden'!F388 -> % | G31: supp | H31: ='Disease burden'!H388 -> - | I31: ='Disease burden'!I388 -> 0.17823491 | J31: ='Disease burden'!J388 -> 0.12033359 | K31: ='Disease burden'!K388 -> 0.20302136 | L31: ='Disease burden'!L388 -> 0.10657065 | M31: ='Disease burden'!M388 -> 0.13277628 | N31: ='Disease burden'!N388 -> 0.17332974 | O31: ='Disease burden'!O388 -> 0.15789653 | ... AV31: ='Disease burden'!AV388 -> 0.15986442
E32: Proportion of vaccine-preventable mortalities among people under age 5 that could be prevented by the 1st dose of the Penta vaccine | F32: ='Disease burden'!F389 -> % | G32: supp | H32: ='Disease burden'!H389 -> - | I32: ='Disease burden'!I389 -> 0.073644315 | J32: ='Disease burden'!J389 -> 0.09622371 | K32: ='Disease burden'!K389 -> 0.091772594 | L32: ='Disease burden'!L389 -> 0.11232443 | M32: ='Disease burden'!M389 -> 0.085575908 | N32: ='Disease burden'!N389 -> 0.089629168 | O32: ='Disease burden'!O389 -> 0.10466208 | ... AV32: ='Disease burden'!AV389 -> 0.11459606
E33: Proportion of vaccine-preventable mortalities among people under age 5 that could be prevented by the 2nd dose of the Penta vaccine | F33: ='Disease burden'!F390 -> % | G33: supp | H33: ='Disease burden'!H390 -> - | I33: ='Disease burden'!I390 -> 0.11572678 | J33: ='Disease burden'!J390 -> 0.15120869 | K33: ='Disease burden'!K390 -> 0.14421408 | L33: ='Disease burden'!L390 -> 0.17650982 | M33: ='Disease burden'!M390 -> 0.13447643 | N33: ='Disease burden'!N390 -> 0.14084584 | O33: ='Disease burden'!O390 -> 0.16446899 | ... AV33: ='Disease burden'!AV390 -> 0.18007952
E34: Proportion of vaccine-preventable mortalities among people under age 5 that could be prevented by the 3rd dose of the Penta vaccine | F34: ='Disease burden'!F391 -> % | G34: supp | H34: ='Disease burden'!H391 -> - | I34: ='Disease burden'!I391 -> 0.021041233 | J34: ='Disease burden'!J391 -> 0.027492489 | K34: ='Disease burden'!K391 -> 0.026220741 | L34: ='Disease burden'!L391 -> 0.032092695 | M34: ='Disease burden'!M391 -> 0.024450259 | N34: ='Disease burden'!N391 -> 0.025608334 | O34: ='Disease burden'!O391 -> 0.029903452 | ... AV34: ='Disease burden'!AV391 -> 0.032741731
E35: Proportion of vaccine-preventable mortalities among people under age 5 that could be prevented by the 1st dose of the PCV vaccine | F35: ='Disease burden'!F392 -> % | G35: supp | H35: ='Disease burden'!H392 -> - | I35: ='Disease burden'!I392 -> 0.089900525 | J35: ='Disease burden'!J392 -> 0.10135603 | K35: ='Disease burden'!K392 -> 0.085648045 | L35: ='Disease burden'!L392 -> 0.107903 | M35: ='Disease burden'!M392 -> 0.11094009 | N35: ='Disease burden'!N392 -> 0.079775398 | O35: ='Disease burden'!O392 -> 0.076462066 | ... AV35: ='Disease burden'!AV392 -> 0.073761103
E36: Proportion of vaccine-preventable mortalities among people under age 5 that could be prevented by the 2nd dose of the PCV vaccine | F36: ='Disease burden'!F393 -> % | G36: supp | H36: ='Disease burden'!H393 -> - | I36: ='Disease burden'!I393 -> 0.14127225 | J36: ='Disease burden'!J393 -> 0.15927376 | K36: ='Disease burden'!K393 -> 0.13458978 | L36: ='Disease burden'!L393 -> 0.16956186 | M36: ='Disease burden'!M393 -> 0.17433442 | N36: ='Disease burden'!N393 -> 0.12536134 | O36: ='Disease burden'!O393 -> 0.12015467 | ... AV36: ='Disease burden'!AV393 -> 0.1159103
E37: Proportion of vaccine-preventable mortalities among people under age 5 that could be prevented by the 3rd dose of the PCV vaccine | F37: ='Disease burden'!F394 -> % | G37: supp | H37: ='Disease burden'!H394 -> - | I37: ='Disease burden'!I394 -> 0.025685864 | J37: ='Disease burden'!J394 -> 0.028958866 | K37: ='Disease burden'!K394 -> 0.02447087 | L37: ='Disease burden'!L394 -> 0.030829429 | M37: ='Disease burden'!M394 -> 0.031697167 | N37: ='Disease burden'!N394 -> 0.022792971 | O37: ='Disease burden'!O394 -> 0.021846305 | ... AV37: ='Disease burden'!AV394 -> 0.021074601
E38: Proportion of vaccine-preventable mortalities among people under age 5 that could be prevented by the 1st dose of the measles vaccine | F38: ='Disease burden'!F398 -> % | G38: supp | H38: ='Disease burden'!H398 -> - | I38: ='Disease burden'!I398 -> 0.074606151 | J38: ='Disease burden'!J398 -> 0.057117138 | K38: ='Disease burden'!K398 -> 0.090072195 | L38: ='Disease burden'!L395 -> 0.14558025 | M38: ='Disease burden'!M398 -> 0.044052509 | N38: ='Disease burden'!N398 -> 0.10112555 | O38: ='Disease burden'!O398 -> 0.10124241 | P38: ='Disease burden'!P398 -> 0.077921789 | Q38: ='Disease burden'!Q398 -> 0.092018777 | R38: ='Disease burden'!R398 -> 0.035524554 | S38: ='Disease burden'!S398 -> 0.045762037 | T38: ='Disease burden'!T398 -> 0.068727418 | ... AV38: ='Disease burden'!AV398 -> 0.10845507
E39: Proportion of vaccine-preventable mortalities among people under age 5 that could be prevented by the 2nd dose of the measles vaccine | F39: ='Disease burden'!F399 -> % | G39: supp | H39: ='Disease burden'!H399 -> - | I39: ='Disease burden'!I399 -> 0.0043885971 | J39: ='Disease burden'!J399 -> 0.0033598316 | K39: ='Disease burden'!K399 -> 0.0052983644 | L39: ='Disease burden'!L396 -> 0.02911605 | M39: ='Disease burden'!M399 -> 0.0025913241 | N39: ='Disease burden'!N399 -> 0.0059485617 | O39: ='Disease burden'!O399 -> 0.0059554359 | P39: ='Disease burden'!P399 -> 0.0045836346 | Q39: ='Disease burden'!Q399 -> 0.0054128692 | R39: ='Disease burden'!R399 -> 0.0020896796 | S39: ='Disease burden'!S399 -> 0.0026918845 | T39: ='Disease burden'!T399 -> 0.0040427893 | ... AV39: ='Disease burden'!AV399 -> 0.0063797102
C41: Average proportion of vaccine-preventable mortalities that could be prevented by each vaccine dose in RCT states (Jigawa, Katsina, Zamfara)
E42: Proportion of vaccine-preventable mortalities among people under age 5 that could be prevented by the BCG vaccine in RCT states | F42: % | G42: calc | H42: =AVERAGE(K31,N31,Q31) -> 0.1939556 | I42: - | J42: - | K42: - | L42: - | M42: - | N42: - | O42: - | P42: - | Q42: - | R42: - | S42: - | T42: - | U42: - | V42: - | W42: - | X42: - | Y42: - | Z42: - | AA42: - | AB42: - | AC42: - | AD42: - | AE42: - | AF42: - | AG42: - | AH42: - | AI42: - | AJ42: - | AK42: - | AL42: - | AM42: - | AN42: - | AO42: - | AP42: - | AQ42: - | AR42: - | AS42: - | AT42: - | AU42: - | AV42: -
E43: Proportion of vaccine-preventable mortalities among people under age 5 that could be prevented by the 1st dose of the Penta vaccine in RCT states | F43: % | G43: calc | H43: =AVERAGE(K32,N32,Q32) -> 0.088879196 | I43: - | J43: - | K43: - | L43: - | M43: - | N43: - | O43: - | P43: - | Q43: - | R43: - | S43: - | T43: - | U43: - | V43: - | W43: - | X43: - | Y43: - | Z43: - | AA43: - | AB43: - | AC43: - | AD43: - | AE43: - | AF43: - | AG43: - | AH43: - | AI43: - | AJ43: - | AK43: - | AL43: - | AM43: - | AN43: - | AO43: - | AP43: - | AQ43: - | AR43: - | AS43: - | AT43: - | AU43: - | AV43: -
E44: Proportion of vaccine-preventable mortalities among people under age 5 that could be prevented by the 2nd dose of the Penta vaccine in RCT states | F44: % | G44: calc | H44: =AVERAGE(K33,N33,Q33) -> 0.13966731 | I44: - | J44: - | K44: - | L44: - | M44: - | N44: - | O44: - | P44: - | Q44: - | R44: - | S44: - | T44: - | U44: - | V44: - | W44: - | X44: - | Y44: - | Z44: - | AA44: - | AB44: - | AC44: - | AD44: - | AE44: - | AF44: - | AG44: - | AH44: - | AI44: - | AJ44: - | AK44: - | AL44: - | AM44: - | AN44: - | AO44: - | AP44: - | AQ44: - | AR44: - | AS44: - | AT44: - | AU44: - | AV44: -
E45: Proportion of vaccine-preventable mortalities among people under age 5 that could be prevented by the 3rd dose of the Penta vaccine in RCT states | F45: % | G45: calc | H45: =AVERAGE(K34,N34,Q34) -> 0.025394056 | I45: - | J45: - | K45: - | L45: - | M45: - | N45: - | O45: - | P45: - | Q45: - | R45: - | S45: - | T45: - | U45: - | V45: - | W45: - | X45: - | Y45: - | Z45: - | AA45: - | AB45: - | AC45: - | AD45: - | AE45: - | AF45: - | AG45: - | AH45: - | AI45: - | AJ45: - | AK45: - | AL45: - | AM45: - | AN45: - | AO45: - | AP45: - | AQ45: - | AR45: - | AS45: - | AT45: - | AU45: - | AV45: -
E46: Proportion of vaccine-preventable mortalities among people under age 5 that could be prevented by the 1st dose of the PCV vaccine in RCT states | F46: % | G46: calc | H46: =AVERAGE(K35,N35,Q35) -> 0.077576567 | I46: - | J46: - | K46: - | L46: - | M46: - | N46: - | O46: - | P46: - | Q46: - | R46: - | S46: - | T46: - | U46: - | V46: - | W46: - | X46: - | Y46: - | Z46: - | AA46: - | AB46: - | AC46: - | AD46: - | AE46: - | AF46: - | AG46: - | AH46: - | AI46: - | AJ46: - | AK46: - | AL46: - | AM46: - | AN46: - | AO46: - | AP46: - | AQ46: - | AR46: - | AS46: - | AT46: - | AU46: - | AV46: -
E47: Proportion of vaccine-preventable mortalities among people under age 5 that could be prevented by the 2nd dose of the PCV vaccine in RCT states | F47: % | G47: calc | H47: =AVERAGE(K36,N36,Q36) -> 0.12190603 | I47: - | J47: - | K47: - | L47: - | M47: - | N47: - | O47: - | P47: - | Q47: - | R47: - | S47: - | T47: - | U47: - | V47: - | W47: - | X47: - | Y47: - | Z47: - | AA47: - | AB47: - | AC47: - | AD47: - | AE47: - | AF47: - | AG47: - | AH47: - | AI47: - | AJ47: - | AK47: - | AL47: - | AM47: - | AN47: - | AO47: - | AP47: - | AQ47: - | AR47: - | AS47: - | AT47: - | AU47: - | AV47: -
E48: Proportion of vaccine-preventable mortalities among people under age 5 that could be prevented by the 3rd dose of the PCV vaccine in RCT states | F48: % | G48: calc | H48: =AVERAGE(K37,N37,Q37) -> 0.022164734 | I48: - | J48: - | K48: - | L48: - | M48: - | N48: - | O48: - | P48: - | Q48: - | R48: - | S48: - | T48: - | U48: - | V48: - | W48: - | X48: - | Y48: - | Z48: - | AA48: - | AB48: - | AC48: - | AD48: - | AE48: - | AF48: - | AG48: - | AH48: - | AI48: - | AJ48: - | AK48: - | AL48: - | AM48: - | AN48: - | AO48: - | AP48: - | AQ48: - | AR48: - | AS48: - | AT48: - | AU48: - | AV48: -
E49: Proportion of vaccine-preventable mortalities among people under age 5 that could be prevented by the 1st dose of the measles vaccine in RCT states | F49: % | G49: calc | H49: =AVERAGE(K38,N38,Q38) -> 0.094405507 | I49: - | J49: - | K49: - | L49: - | M49: - | N49: - | O49: - | P49: - | Q49: - | R49: - | S49: - | T49: - | U49: - | V49: - | W49: - | X49: - | Y49: - | Z49: - | AA49: - | AB49: - | AC49: - | AD49: - | AE49: - | AF49: - | AG49: - | AH49: - | AI49: - | AJ49: - | AK49: - | AL49: - | AM49: - | AN49: - | AO49: - | AP49: - | AQ49: - | AR49: - | AS49: - | AT49: - | AU49: - | AV49: -
C51: Vaccination coverage rates for the control group of the New Incentives RCT, adjusted for self-report bias, aggregated across vaccines
E52: Proportion of children in the New Incentives RCT control group who were vaccinated, aggregated across vaccines | F52: % | G52: calc | H52: =SUMPRODUCT(H21:H28,H42:H49)/SUM(H42:H49) -> 0.35640384 | I52: - | J52: - | K52: - | L52: - | M52: - | N52: - | O52: - | P52: - | Q52: - | R52: - | S52: - | T52: - | U52: - | V52: - | W52: - | X52: - | Y52: - | Z52: - | AA52: - | AB52: - | AC52: - | AD52: - | AE52: - | AF52: - | AG52: - | AH52: - | AI52: - | AJ52: - | AK52: - | AL52: - | AM52: - | AN52: - | AO52: - | AP52: - | AQ52: - | AR52: - | AS52: - | AT52: - | AU52: - | AV52: -
E53: Corresponding proportion of children in the New Incentives RCT control group who were not vaccinated, aggregated across vaccines | F53: % | G53: calc | H53: =1-H52 -> 0.64359616 | I53: - | J53: - | K53: - | L53: - | M53: - | N53: - | O53: - | P53: - | Q53: - | R53: - | S53: - | T53: - | U53: - | V53: - | W53: - | X53: - | Y53: - | Z53: - | AA53: - | AB53: - | AC53: - | AD53: - | AE53: - | AF53: - | AG53: - | AH53: - | AI53: - | AJ53: - | AK53: - | AL53: - | AM53: - | AN53: - | AO53: - | AP53: - | AQ53: - | AR53: - | AS53: - | AT53: - | AU53: - | AV53: -
A55: Treatment effects found by the New Incentives' RCT
C57: Treatment effects found by the New Incentives' RCT
E58: Increase in the proportion of children receiving the BCG vaccine | F58: =Inputs!F221 -> % | G58: =Inputs!G221 -> input | H58: =Inputs!H221 -> 0.1642 | I58: =Inputs!I221 -> - | J58: =Inputs!J221 -> - | K58: =Inputs!K221 -> - | L58: =Inputs!L221 -> - | M58: =Inputs!M221 -> - | ... AV58: =Inputs!AV221 -> -
E59: Increase in the proportion of children receiving the 1st dose of the Penta vaccine | F59: =Inputs!F222 -> % | G59: =Inputs!G222 -> input | H59: =Inputs!H222 -> 0.2093 | I59: =Inputs!I222 -> - | J59: =Inputs!J222 -> - | K59: =Inputs!K222 -> - | L59: =Inputs!L222 -> - | M59: =Inputs!M222 -> - | ... AV59: =Inputs!AV222 -> -
E60: Increase in the proportion of children receiving the 2nd dose of the Penta vaccine | F60: =Inputs!F223 -> % | G60: =Inputs!G223 -> input | H60: =Inputs!H223 -> 0.2659 | I60: =Inputs!I223 -> - | J60: =Inputs!J223 -> - | K60: =Inputs!K223 -> - | L60: =Inputs!L223 -> - | M60: =Inputs!M223 -> - | ... AV60: =Inputs!AV223 -> -
E61: Increase in the proportion of children receiving the 3rd dose of the Penta vaccine | F61: =Inputs!F224 -> % | G61: =Inputs!G224 -> input | H61: =Inputs!H224 -> 0.275 | I61: =Inputs!I224 -> - | J61: =Inputs!J224 -> - | K61: =Inputs!K224 -> - | L61: =Inputs!L224 -> - | M61: =Inputs!M224 -> - | ... AV61: =Inputs!AV224 -> -
E62: Increase in the proportion of children receiving the 1st dose of the PCV vaccine | F62: =Inputs!F225 -> % | G62: =Inputs!G225 -> input | H62: =Inputs!H225 -> 0.2227 | I62: =Inputs!I225 -> - | J62: =Inputs!J225 -> - | K62: =Inputs!K225 -> - | L62: =Inputs!L225 -> - | M62: =Inputs!M225 -> - | ... AV62: =Inputs!AV225 -> -
E63: Increase in the proportion of children receiving the 2nd dose of the PCV vaccine | F63: =Inputs!F226 -> % | G63: =Inputs!G226 -> input | H63: =Inputs!H226 -> 0.2726 | I63: =Inputs!I226 -> - | J63: =Inputs!J226 -> - | K63: =Inputs!K226 -> - | L63: =Inputs!L226 -> - | M63: =Inputs!M226 -> - | ... AV63: =Inputs!AV226 -> -
E64: Increase in the proportion of children receiving the 3rd dose of the PCV vaccine | F64: =Inputs!F227 -> % | G64: =Inputs!G227 -> input | H64: =Inputs!H227 -> 0.2471 | I64: =Inputs!I227 -> - | J64: =Inputs!J227 -> - | K64: =Inputs!K227 -> - | L64: =Inputs!L227 -> - | M64: =Inputs!M227 -> - | ... AV64: =Inputs!AV227 -> -
E65: Increase in the proportion of children receiving the 1st dose of the measles vaccine | F65: =Inputs!F228 -> % | G65: =Inputs!G228 -> input | H65: =Inputs!H228 -> 0.1432 | I65: =Inputs!I228 -> - | J65: =Inputs!J228 -> - | K65: =Inputs!K228 -> - | L65: =Inputs!L228 -> - | M65: =Inputs!M228 -> - | ... AV65: =Inputs!AV228 -> -
C67: Treatment effect found by the New Incentives RCT, aggregated across vaccines
E68: Increase in proportion of children who are vaccinated, aggregated across vaccines | F68: % | G68: calc | H68: =SUMPRODUCT(H42:H49,H58:H65)/SUM(H42:H49) -> 0.21477152 | I68: - | J68: - | K68: - | L68: - | M68: - | N68: - | O68: - | P68: - | Q68: - | R68: - | S68: - | T68: - | U68: - | V68: - | W68: - | X68: - | Y68: - | Z68: - | AA68: - | AB68: - | AC68: - | AD68: - | AE68: - | AF68: - | AG68: - | AH68: - | AI68: - | AJ68: - | AK68: - | AL68: - | AM68: - | AN68: - | AO68: - | AP68: - | AQ68: - | AR68: - | AS68: - | AT68: - | AU68: - | AV68: -
C70: Implied reduction in the proportion of children who are unvaccinated as a result of New Incentives program
E71: Reduction in the proportion of children who are unvaccinated as a result of New Incentives' program, based on GW's analysis of the New Incentives RCT, aggregated across vaccines | F71: % | G71: calc | H71: =H68/H53 -> 0.33370541 | I71: - | J71: - | K71: - | L71: - | M71: - | N71: - | O71: - | P71: - | Q71: - | R71: - | S71: - | T71: - | U71: - | V71: - | W71: - | X71: - | Y71: - | Z71: - | AA71: - | AB71: - | AC71: - | AD71: - | AE71: - | AF71: - | AG71: - | AH71: - | AI71: - | AJ71: - | AK71: - | AL71: - | AM71: - | AN71: - | AO71: - | AP71: - | AQ71: - | AR71: - | AS71: - | AT71: - | AU71: - | AV71: -
A73: Treatment effects, adjusted for second measles dose
C75: Treatment effect
E76: Reduction in the proportion of children who do not receive the second dose of the measles vaccine as a result of New Incentives' program, relative to the program's impact on the first dose | F76: =Inputs!F241 -> % | G76: input | H76: 0.85 | I76: =Inputs!I241 -> - | J76: =Inputs!J241 -> - | K76: =Inputs!K241 -> - | L76: =Inputs!L241 -> - | M76: =Inputs!M241 -> - | N76: =Inputs!N241 -> - | O76: =Inputs!O241 -> - | P76: =Inputs!P241 -> - | ... AV76: =Inputs!AV241 -> -
E77: Reduction in the proportion of children who do not receive the second dose of the measles vaccine as a result of New Incentives' program | F77: =Inputs!F242 -> % | G77: calc | H77: =(H65/(1-H28))*H76 -> 0.21212876 | I77: =Inputs!I242 -> - | J77: =Inputs!J242 -> - | K77: =Inputs!K242 -> - | L77: =Inputs!L242 -> - | M77: =Inputs!M242 -> - | N77: =Inputs!N242 -> - | O77: =Inputs!O242 -> - | P77: =Inputs!P242 -> - | ... AV77: =Inputs!AV242 -> -
C79: Average proportion of vaccine-preventable mortalities that could be prevented by each vaccine in RCT states (Jigawa, Katsina, Zamfara)
E80: Average proportion of vaccine-preventable mortalities that could be prevented by the second dose of the vaccine in RCT states | F80: % | G80: calc | H80: =AVERAGE(K39,N39,Q39) -> 0.0055532651 | I80: - | J80: - | K80: - | L80: - | M80: - | N80: - | O80: - | P80: - | Q80: - | R80: - | S80: - | T80: - | U80: - | V80: - | W80: - | X80: - | Y80: - | Z80: - | AA80: - | AB80: - | AC80: - | AD80: - | AE80: - | AF80: - | AG80: - | AH80: - | AI80: - | AJ80: - | AK80: - | AL80: - | AM80: - | AN80: - | AO80: - | AP80: - | AQ80: - | AR80: - | AS80: - | AT80: - | AU80: - | AV80: -
E81: Average proportion of vaccine-preventable mortalities that could be prevented by all other doses of the vaccine in RCT states | F81: % | G81: calc | H81: =1-H80 -> 0.99444673 | I81: - | J81: - | K81: - | L81: - | M81: - | N81: - | O81: - | P81: - | Q81: - | R81: - | S81: - | T81: - | U81: - | V81: - | W81: - | X81: - | Y81: - | Z81: - | AA81: - | AB81: - | AC81: - | AD81: - | AE81: - | AF81: - | AG81: - | AH81: - | AI81: - | AJ81: - | AK81: - | AL81: - | AM81: - | AN81: - | AO81: - | AP81: - | AQ81: - | AR81: - | AS81: - | AT81: - | AU81: - | AV81: -
C83: Implied reduction in the proportion of children who are unvaccinated as a result of New Incentives program
E84: Reduction in the proportion of children who are unvaccinated as a result of New Incentives' program, based on GW's analysis of the New Incentives RCT, aggregated across vaccines | F84: % | G84: calc | H84: =H77*H80+H71*H81 -> 0.33303026 | I84: - | J84: - | K84: - | L84: - | M84: - | N84: - | O84: - | P84: - | Q84: - | R84: - | S84: - | T84: - | U84: - | V84: - | W84: - | X84: - | Y84: - | Z84: - | AA84: - | AB84: - | AC84: - | AD84: - | AE84: - | AF84: - | AG84: - | AH84: - | AI84: - | AJ84: - | AK84: - | AL84: - | AM84: - | AN84: - | AO84: - | AP84: - | AQ84: - | AR84: - | AS84: - | AT84: - | AU84: - | AV84: -

Sheet Disease burden
I1: New Incentives – current states of operation | R1: New Incentives – prospective states | AF1: New Incentives – prospective states
I2: Nigeria | J2: Nigeria | K2: Nigeria | L2: Nigeria | M2: Nigeria | N2: Nigeria | O2: Nigeria | P2: Nigeria | Q2: Nigeria | R2: Nigeria | S2: Nigeria | T2: Nigeria | U2: Nigeria | V2: Nigeria | W2: Nigeria | X2: Nigeria | Y2: Nigeria | Z2: Nigeria | AA2: Nigeria | AB2: Nigeria | AC2: Nigeria | AD2: Nigeria | AE2: Nigeria | AF2: Nigeria | AG2: Nigeria | AH2: Nigeria | AI2: Nigeria | AJ2: Nigeria | AK2: Nigeria | AL2: Nigeria | AM2: Nigeria | AN2: Nigeria | AO2: Nigeria | AP2: Nigeria | AQ2: Nigeria | AR2: Nigeria | AS2: Nigeria | AT2: Nigeria | AU2: Nigeria | AV2: Nigeria
A3: Main calculations | F3: unit | G3: type | H3: Overall | I3: Bauchi | J3: Gombe | K3: Jigawa | L3: Kaduna - cohort 17 | M3: Kano | N3: Katsina | O3: Kebbi | P3: Sokoto | Q3: Zamfara | R3: Abia | S3: Adamawa | T3: Akwa Ibom | U3: Anambra | V3: Bayelsa | W3: Benue | X3: Borno | Y3: Cross River | Z3: Delta | AA3: Ebonyi | AB3: Edo | AC3: Ekiti | AD3: Enugu | AE3: FCT | AF3: Imo | AG3: Kaduna | AH3: Kogi | AI3: Kwara | AJ3: Lagos | AK3: Nasarawa | AL3: Niger | AM3: Niger - cohorts 32 & 36 | AN3: Niger - cohort 34 | AO3: Ogun | AP3: Ondo | AQ3: Osun | AR3: Oyo | AS3: Plateau | AT3: Rivers | AU3: Taraba | AV3: Yobe
E4: Final cost-effectiveness estimate (pulled from "Main calcs" sheet for visibility) | F4: ='Main CEA'!F242 -> xbenchmark | G4: ='Main CEA'!G242 -> calc | H4: ='Main CEA'!H242 -> - | I4: ='Main CEA'!I242 -> 20.039606 | J4: ='Main CEA'!J242 -> 10.020838 | K4: ='Main CEA'!K242 -> 18.177505 | L4: ='Main CEA'!L242 -> 9.0027672 | M4: ='Main CEA'!M242 -> 12.612827 | ... AV4: ='Main CEA'!AV242 -> 11.471963
A5: Tuberculosis
C7: Probability of dying of tuberculosis
E8: Probability that a person will die of tuberculosis before reaching age 5 | F8: =Inputs!F111 -> % | G8: =Inputs!G111 -> input | H8: =Inputs!H111 -> - | I8: =Inputs!I111 -> 0.003629763 | J8: =Inputs!J111 -> 0.001693533 | K8: =Inputs!K111 -> 0.004321809 | L8: =Inputs!L111 -> 0.000876042 | M8: =Inputs!M111 -> 0.001723095 | ... AV8: =Inputs!AV111 -> 0.00187352
E9: Probability that a 5-year-old will die of tuberculosis before reaching age 15 | F9: =Inputs!F112 -> % | G9: =Inputs!G112 -> input | H9: =Inputs!H112 -> - | I9: =Inputs!I112 -> 0.000531146 | J9: =Inputs!J112 -> 0.000260845 | K9: =Inputs!K112 -> 0.000599109 | L9: =Inputs!L112 -> 0.000139527 | M9: =Inputs!M112 -> 0.000283003 | ... AV9: =Inputs!AV112 -> 0.000388626
E10: Probability that a 15-year-old will die of tuberculosis before reaching age 50 | F10: =Inputs!F113 -> % | G10: =Inputs!G113 -> input | H10: =Inputs!H113 -> - | I10: =Inputs!I113 -> 0.007150253 | J10: =Inputs!J113 -> 0.004007767 | K10: =Inputs!K113 -> 0.008685948 | L10: =Inputs!L113 -> 0.002843472 | M10: =Inputs!M113 -> 0.003815045 | ... AV10: =Inputs!AV113 -> 0.006708114
E11: Probability that a 50-year-old will die of tuberculosis before reaching age 75 | F11: =Inputs!F114 -> % | G11: =Inputs!G114 -> input | H11: =Inputs!H114 -> - | I11: =Inputs!I114 -> 0.049361812 | J11: =Inputs!J114 -> 0.030242318 | K11: =Inputs!K114 -> 0.052337352 | L11: =Inputs!L114 -> 0.017468647 | M11: =Inputs!M114 -> 0.024547523 | ... AV11: =Inputs!AV114 -> 0.043770944
C13: Tuberculosis mortalities occurring before the age of vaccination
E14: Proportion of tuberculosis mortalities among people under age 5 that occur prior to the age of BCG vaccination (birth) | F14: % | G14: input | H14: =Inputs!H115 -> 0 | I14: =Inputs!I115 -> - | J14: =Inputs!J115 -> - | K14: =Inputs!K115 -> - | L14: =Inputs!L115 -> - | M14: =Inputs!M115 -> - | N14: =Inputs!N115 -> - | O14: =Inputs!O115 -> - | ... AV14: =Inputs!AV115 -> -
E15: Probability that a person will die of tuberculosis before reaching age 5, adjusted for deaths occurring before the age of vaccination | F15: % | G15: calc | H15: - | I15: =I8*(1-$H14) -> 0.003629763 | J15: =J8*(1-$H14) -> 0.001693533 | K15: =K8*(1-$H14) -> 0.004321809 | L15: =L8*(1-$H14) -> 0.000876042 | M15: =M8*(1-$H14) -> 0.001723095 | N15: =N8*(1-$H14) -> 0.002687563 | O15: =O8*(1-$H14) -> 0.002755632 | P15: =P8*(1-$H14) -> 0.004692335 | ... AV15: =AV8*(1-$H14) -> 0.00187352
A17: Diphtheria
C19: Probability of dying of diphtheria
E20: Probability that a person will die of diphtheria before reaching age 5 | F20: % | G20: input | H20: =Inputs!H118 -> - | I20: =Inputs!I118 -> 0.000501357 | J20: =Inputs!J118 -> 0.000347103 | K20: =Inputs!K118 -> 0.000579052 | L20: =Inputs!L118 -> 0.000105863 | M20: =Inputs!M118 -> 0.000247733 | N20: =Inputs!N118 -> 0.000380731 | O20: =Inputs!O118 -> 0.000728763 | ... AV20: =Inputs!AV118 -> 0.000257334
E21: Probability that a 5-year-old will die of diphtheria before reaching age 15 | F21: % | G21: input | H21: =Inputs!H119 -> - | I21: =Inputs!I119 -> 5.88e-05 | J21: =Inputs!J119 -> 4.39e-05 | K21: =Inputs!K119 -> 6.71e-05 | L21: =Inputs!L119 -> 1.99e-05 | M21: =Inputs!M119 -> 3.53e-05 | N21: =Inputs!N119 -> 4.59e-05 | O21: =Inputs!O119 -> 0.000109744 | ... AV21: =Inputs!AV119 -> 4.46e-05
E22: Probability that a 15-year-old will die of diphtheria before reaching age 50 | F22: % | G22: input | H22: =Inputs!H120 -> - | I22: =Inputs!I120 -> 2.77e-05 | J22: =Inputs!J120 -> 2.01e-05 | K22: =Inputs!K120 -> 3.52e-05 | L22: =Inputs!L120 -> 1.12e-05 | M22: =Inputs!M120 -> 1.33e-05 | N22: =Inputs!N120 -> 2.68e-05 | O22: =Inputs!O120 -> 5.9e-05 | ... AV22: =Inputs!AV120 -> 3.04e-05
E23: Probability that a 50-year-old will die of diphtheria before reaching age 75 | F23: % | G23: input | H23: =Inputs!H121 -> - | I23: =Inputs!I121 -> 4.12e-05 | J23: =Inputs!J121 -> 3.15e-05 | K23: =Inputs!K121 -> 4.55e-05 | L23: =Inputs!L121 -> 1.6e-05 | M23: =Inputs!M121 -> 2.15e-05 | N23: =Inputs!N121 -> 3.93e-05 | O23: =Inputs!O121 -> 8.1e-05 | ... AV23: =Inputs!AV121 -> 4.25e-05
C25: Diphtheria mortalities occurring before the age of vaccination
E26: Diphtheria mortalities per year among people under age 5 | F26: # | G26: input | H26: =Inputs!H122 -> - | I26: =Inputs!I122 -> 140.59257 | J26: =Inputs!J122 -> 45.34226 | K26: =Inputs!K122 -> 133.20073 | L26: =Inputs!L122 -> 41.327866 | M26: =Inputs!M122 -> 169.10401 | N26: =Inputs!N122 -> 160.20219 | O26: =Inputs!O122 -> 145.30193 | ... AV26: =Inputs!AV122 -> 43.778357
E27: Diphtheria mortalities per year among people under age 1 | F27: # | G27: input | H27: =Inputs!H123 -> - | I27: =Inputs!I123 -> 17.735934 | J27: =Inputs!J123 -> 7.3454386 | K27: =Inputs!K123 -> 17.622697 | L27: =Inputs!L123 -> 10.456793 | M27: =Inputs!M123 -> 24.367067 | N27: =Inputs!N123 -> 29.171431 | O27: =Inputs!O123 -> 26.006764 | ... AV27: =Inputs!AV123 -> 7.8200449
E28: Proportion of diphtheria mortalities among people under age 5 that occur before age 1 | F28: % | G28: calc | H28: - | I28: =I27/I26 -> 0.12615129 | J28: =J27/J26 -> 0.16199983 | K28: =K27/K26 -> 0.1323018 | L28: =L27/L26 -> 0.25302039 | M28: =M27/M26 -> 0.14409515 | N28: =N27/N26 -> 0.18209133 | O28: =O27/O26 -> 0.1789843 | P28: =P27/P26 -> 0.14956457 | ... AV28: =AV27/AV26 -> 0.1786281
E29: Assumed proportion of diphtheria mortalities among people under age 1 occurring before the age of Penta vaccination (6 weeks) | F29: % | G29: input | H29: =Inputs!H124 -> 0.15 | I29: =Inputs!I124 -> - | J29: =Inputs!J124 -> - | K29: =Inputs!K124 -> - | L29: =Inputs!L124 -> - | M29: =Inputs!M124 -> - | N29: =Inputs!N124 -> - | O29: =Inputs!O124 -> - | ... AV29: =Inputs!AV124 -> -
E30: Proportion of diphtheria mortalities among people under age 5 that occur before the age of Penta vaccination (6 weeks) | F30: % | G30: calc | H30: - | I30: =I28*$H29 -> 0.018922694 | J30: =J28*$H29 -> 0.024299975 | K30: =K28*$H29 -> 0.019845271 | L30: =L28*$H29 -> 0.037953058 | M30: =M28*$H29 -> 0.021614272 | N30: =N28*$H29 -> 0.0273137 | O30: =O28*$H29 -> 0.026847644 | P30: =P28*$H29 -> 0.022434685 | ... AV30: =AV28*$H29 -> 0.026794216
E31: Probability that a person will die of diphtheria before reaching age 5, adjusted for deaths occurring before the age of vaccination | F31: % | G31: calc | H31: - | I31: =I20*(1-I30) -> 0.00049186998 | J31: =J20*(1-J30) -> 0.00033866841 | K31: =K20*(1-K30) -> 0.00056756056 | L31: =L20*(1-L30) -> 0.00010184518 | M31: =M20*(1-M30) -> 0.00024237843 | N31: =N20*(1-N30) -> 0.00037033183 | O31: =O20*(1-O30) -> 0.00070919743 | P31: =P20*(1-P30) -> 0.0013868309 | ... AV31: =AV20*(1-AV30) -> 0.00025043894
A33: Pertussis
C35: Probability of dying of pertussis
E36: Probability that a person will die of pertussis before reaching age 5 | F36: % | G36: input | H36: =Inputs!H127 -> - | I36: =Inputs!I127 -> 0.001926586 | J36: =Inputs!J127 -> 0.001715755 | K36: =Inputs!K127 -> 0.002305103 | L36: =Inputs!L127 -> 0.001196296 | M36: =Inputs!M127 -> 0.001434608 | N36: =Inputs!N127 -> 0.001871217 | O36: =Inputs!O127 -> 0.002022091 | ... AV36: =Inputs!AV127 -> 0.001569238
E37: Probability that a 5-year-old will die of pertussis before reaching age 15 | F37: % | G37: input | H37: =Inputs!H128 -> - | I37: =Inputs!I128 -> 0.000230744 | J37: =Inputs!J128 -> 0.000206465 | K37: =Inputs!K128 -> 0.000290793 | L37: =Inputs!L128 -> 0.000172137 | M37: =Inputs!M128 -> 0.000177755 | N37: =Inputs!N128 -> 0.000245196 | O37: =Inputs!O128 -> 0.00027482 | ... AV37: =Inputs!AV128 -> 0.000187811
E38: Probability that a 15-year-old will die of pertussis before reaching age 50 | F38: % | G38: input | H38: =Inputs!H129 -> - | I38: =Inputs!I129 -> 4.74e-05 | J38: =Inputs!J129 -> 3.78e-05 | K38: =Inputs!K129 -> 6.91e-05 | L38: =Inputs!L129 -> 3.12e-05 | M38: =Inputs!M129 -> 3.37e-05 | N38: =Inputs!N129 -> 5.12e-05 | O38: =Inputs!O129 -> 5.8e-05 | ... AV38: =Inputs!AV129 -> 5.25e-05
E39: Probability that a 50-year-old will die of pertussis before reaching age 75 | F39: % | G39: input | H39: =Inputs!H130 -> - | I39: =Inputs!I130 -> 4.66e-05 | J39: =Inputs!J130 -> 3.85e-05 | K39: =Inputs!K130 -> 5.41e-05 | L39: =Inputs!L130 -> 2.93e-05 | M39: =Inputs!M130 -> 3.67e-05 | N39: =Inputs!N130 -> 4.68e-05 | O39: =Inputs!O130 -> 5.17e-05 | ... AV39: =Inputs!AV130 -> 4.43e-05
C41: Pertussis mortalities occurring before the age of vaccination
E42: Pertussis mortalities per year among people under age 5 | F42: # | G42: input | H42: =Inputs!H131 -> - | I42: =Inputs!I131 -> 540.80112 | J42: =Inputs!J131 -> 224.34515 | K42: =Inputs!K131 -> 530.89059 | L42: =Inputs!L131 -> 467.37802 | M42: =Inputs!M131 -> 980.08608 | N42: =Inputs!N131 -> 788.18415 | O42: =Inputs!O131 -> 403.53311 | ... AV42: =Inputs!AV131 -> 267.20856
E43: Pertussis mortalities per year among people under age 1 | F43: # | G43: input | H43: =Inputs!H132 -> - | I43: =Inputs!I132 -> 189.83394 | J43: =Inputs!J132 -> 81.000224 | K43: =Inputs!K132 -> 199.56906 | L43: =Inputs!L132 -> 197.55097 | M43: =Inputs!M132 -> 363.12604 | N43: =Inputs!N132 -> 306.15867 | O43: =Inputs!O132 -> 151.45647 | ... AV43: =Inputs!AV132 -> 102.6045
E44: Proportion of pertussis mortalities among people under age 5 that occur before age 1 | F44: % | G44: calc | H44: - | I44: =I43/I42 -> 0.35102357 | J44: =J43/J42 -> 0.36105182 | K44: =K43/K42 -> 0.37591373 | L44: =L43/L42 -> 0.42267921 | M44: =M43/M42 -> 0.37050423 | N44: =N43/N42 -> 0.38843546 | O44: =O43/O42 -> 0.37532601 | P44: =P43/P42 -> 0.36234088 | ... AV44: =AV43/AV42 -> 0.38398658
E45: Assumed proportion of pertussis mortalities among people under age 1 occurring before the age of Penta vaccination (6 weeks) | F45: % | G45: input | H45: =Inputs!H133 -> 0.15 | I45: =Inputs!I133 -> - | J45: =Inputs!J133 -> - | K45: =Inputs!K133 -> - | L45: =Inputs!L133 -> - | M45: =Inputs!M133 -> - | N45: =Inputs!N133 -> - | O45: =Inputs!O133 -> - | ... AV45: =Inputs!AV133 -> -
E46: Proportion of pertussis mortalities among people under age 5 that occur before the age of Penta vaccination (6 weeks) | F46: % | G46: calc | H46: - | I46: =I44*$H45 -> 0.052653535 | J46: =J44*$H45 -> 0.054157773 | K46: =K44*$H45 -> 0.05638706 | L46: =L44*$H45 -> 0.063401881 | M46: =M44*$H45 -> 0.055575635 | N46: =N44*$H45 -> 0.058265318 | O46: =O44*$H45 -> 0.056298901 | P46: =P44*$H45 -> 0.054351132 | ... AV46: =AV44*$H45 -> 0.057597988
E47: Probability that a person will die of pertussis before reaching age 5, adjusted for deaths occurring before the age of vaccination | F47: % | G47: calc | H47: - | I47: =I36*(1-I46) -> 0.0018251444 | J47: =J36*(1-J46) -> 0.0016228335 | K47: =K36*(1-K46) -> 0.002175125 | L47: =L36*(1-L46) -> 0.0011204486 | M47: =M36*(1-M46) -> 0.0013548787 | N47: =N36*(1-N46) -> 0.0017621899 | O47: =O36*(1-O46) -> 0.0019082495 | P47: =P36*(1-P46) -> 0.0022006705 | ... AV47: =AV36*(1-AV46) -> 0.001478853
A49: Tetanus
C51: Probability of dying of tetanus
E52: Probability that a person will die of tetanus before reaching age 5 | F52: % | G52: input | H52: =Inputs!H136 -> - | I52: =Inputs!I136 -> 0.000194494 | J52: =Inputs!J136 -> 0.000165483 | K52: =Inputs!K136 -> 0.000136302 | L52: =Inputs!L136 -> 0.0001208 | M52: =Inputs!M136 -> 0.000125013 | N52: =Inputs!N136 -> 0.000144148 | O52: =Inputs!O136 -> 0.000289399 | ... AV52: =Inputs!AV136 -> 0.000133492
E53: Probability that a 5-year-old will die of tetanus before reaching age 15 | F53: % | G53: input | H53: =Inputs!H137 -> - | I53: =Inputs!I137 -> 4.07e-05 | J53: =Inputs!J137 -> 4.22e-05 | K53: =Inputs!K137 -> 4.08e-05 | L53: =Inputs!L137 -> 2.54e-05 | M53: =Inputs!M137 -> 2.96e-05 | N53: =Inputs!N137 -> 3.15e-05 | O53: =Inputs!O137 -> 5e-05 | ... AV53: =Inputs!AV137 -> 2.88e-05
E54: Probability that a 15-year-old will die of tetanus before reaching age 50 | F54: % | G54: input | H54: =Inputs!H138 -> - | I54: =Inputs!I138 -> 7.96e-05 | J54: =Inputs!J138 -> 7.32e-05 | K54: =Inputs!K138 -> 9.69e-05 | L54: =Inputs!L138 -> 5.84e-05 | M54: =Inputs!M138 -> 4.9e-05 | N54: =Inputs!N138 -> 7.43e-05 | O54: =Inputs!O138 -> 0.000110427 | ... AV54: =Inputs!AV138 -> 7.93e-05
E55: Probability that a 50-year-old will die of tetanus before reaching age 75 | F55: % | G55: input | H55: =Inputs!H139 -> - | I55: =Inputs!I139 -> 0.000285466 | J55: =Inputs!J139 -> 0.000340228 | K55: =Inputs!K139 -> 0.000269698 | L55: =Inputs!L139 -> 0.00019924 | M55: =Inputs!M139 -> 0.000175487 | N55: =Inputs!N139 -> 0.000234563 | O55: =Inputs!O139 -> 0.000414794 | ... AV55: =Inputs!AV139 -> 0.000243663
C57: Tetanus mortalities occurring before the age of vaccination
E58: Tetanus mortalities per year among people under age 5 | F58: # | G58: input | H58: =Inputs!H140 -> - | I58: =Inputs!I140 -> 54.529057 | J58: =Inputs!J140 -> 21.614357 | K58: =Inputs!K140 -> 31.344077 | L58: =Inputs!L140 -> 47.159682 | M58: =Inputs!M140 -> 85.327054 | N58: =Inputs!N140 -> 60.643753 | O58: =Inputs!O140 -> 57.683113 | ... AV58: =Inputs!AV140 -> 22.708009
E59: Early neonatal tetanus mortalities per year (babies under 7 days old) | F59: # | G59: input | H59: =Inputs!H141 -> - | I59: =Inputs!I141 -> 30.478887 | J59: =Inputs!J141 -> 10.964286 | K59: =Inputs!K141 -> 15.563906 | L59: =Inputs!L141 -> 23.683078 | M59: =Inputs!M141 -> 43.12276 | N59: =Inputs!N141 -> 28.61758 | O59: =Inputs!O141 -> 31.957012 | ... AV59: =Inputs!AV141 -> 13.357209
E60: Late neonatal tetanus mortalities per year (babies between 7 and 27 days old) | F60: # | G60: input | H60: =Inputs!H142 -> - | I60: =Inputs!I142 -> 13.788224 | J60: =Inputs!J142 -> 5.840665 | K60: =Inputs!K142 -> 7.8627662 | L60: =Inputs!L142 -> 14.891264 | M60: =Inputs!M142 -> 25.744596 | N60: =Inputs!N142 -> 21.068592 | O60: =Inputs!O142 -> 16.169646 | ... AV60: =Inputs!AV142 -> 5.701252
E61: Tetanus mortalities per year among people under age 1 | F61: # | G61: input | H61: =Inputs!H143 -> - | I61: =Inputs!I143 -> 47.002054 | J61: =Inputs!J143 -> 17.979237 | K61: =Inputs!K143 -> 25.214423 | L61: =Inputs!L143 -> 41.855 | M61: =Inputs!M143 -> 72.754659 | N61: =Inputs!N143 -> 52.662731 | O61: =Inputs!O143 -> 51.536258 | ... AV61: =Inputs!AV143 -> 20.066783
E62: Proportion of tetanus mortalities among people under age 5 that occur during the neonatal period (babies between 0 and 27 days old) | F62: % | G62: calc | H62: - | I62: =SUM(I59:I60)/I58 -> 0.81180775 | J62: =SUM(J59:J60)/J58 -> 0.77749021 | K62: =SUM(K59:K60)/K58 -> 0.74740349 | L62: =SUM(L59:L60)/L58 -> 0.81795169 | M62: =SUM(M59:M60)/M58 -> 0.80709872 | N62: =SUM(N59:N60)/N58 -> 0.81931229 | O62: =SUM(O59:O60)/O58 -> 0.83432839 | P62: =SUM(P59:P60)/P58 -> 0.79893461 | ... AV62: =SUM(AV59:AV60)/AV58 -> 0.83928366
E63: Assumed ratio of tetanus mortalities among people under age 5 occurring after the neonatal period but before the age of Penta vaccination (6 weeks) to tetanus mortalities occurring in the neonatal period | F63: % | G63: input | H63: =Inputs!H144 -> 0.1 | I63: =Inputs!I144 -> - | J63: =Inputs!J144 -> - | K63: =Inputs!K144 -> - | L63: =Inputs!L144 -> - | M63: =Inputs!M144 -> - | N63: =Inputs!N144 -> - | O63: =Inputs!O144 -> - | ... AV63: =Inputs!AV144 -> -
E64: Proportion of tetanus mortalities among people under age 5 that occur before age 1 | F64: % | G64: calc | H64: - | I64: =I61/I58 -> 0.86196344 | J64: =J61/J58 -> 0.83181919 | K64: =K61/K58 -> 0.80443981 | L64: =L61/L58 -> 0.88751659 | M64: =M61/M58 -> 0.8526564 | N64: =N61/N58 -> 0.86839498 | O64: =O61/O58 -> 0.89343754 | P64: =P61/P58 -> 0.85734153 | ... AV64: =AV61/AV58 -> 0.88368746
E65: Proportion of tetanus mortalities among people under age 5 that occur before the age of Penta vaccination (6 weeks) | F65: % | G65: calc | H65: - | I65: =MIN(I64,I62*(1+$H63)) -> 0.86196344 | J65: =MIN(J64,J62*(1+$H63)) -> 0.83181919 | K65: =MIN(K64,K62*(1+$H63)) -> 0.80443981 | L65: =MIN(L64,L62*(1+$H63)) -> 0.88751659 | M65: =MIN(M64,M62*(1+$H63)) -> 0.8526564 | N65: =MIN(N64,N62*(1+$H63)) -> 0.86839498 | O65: =MIN(O64,O62*(1+$H63)) -> 0.89343754 | P65: =MIN(P64,P62*(1+$H63)) -> 0.85734153 | ... AV65: =MIN(AV64,AV62*(1+$H63)) -> 0.88368746
E66: Probability that a person will die of tetanus before reaching age 5, adjusted for deaths occurring before the age of vaccination | F66: % | G66: calc | H66: - | I66: =I52*(1-I65) -> 2.6847282e-05 | J66: =J52*(1-J65) -> 2.7831065e-05 | K66: =K52*(1-K65) -> 2.6655245e-05 | L66: =L52*(1-L65) -> 1.3587996e-05 | M66: =M52*(1-M65) -> 1.8419865e-05 | N66: =N52*(1-N65) -> 1.8970601e-05 | O66: =O52*(1-O65) -> 3.0839069e-05 | P66: =P52*(1-P65) -> 5.4654314e-05 | ... AV66: =AV52*(1-AV65) -> 1.5526793e-05
A68: Lower respiratory infections
C70: Probability of dying of a lower respiratory infection
E71: Probability that a person will die of a lower respiratory infection before reaching age 5 | F71: % | G71: input | H71: =Inputs!H147 -> - | I71: =Inputs!I147 -> 0.023390685 | J71: =Inputs!J147 -> 0.018787823 | K71: =Inputs!K147 -> 0.023068706 | L71: =Inputs!L147 -> 0.01387223 | M71: =Inputs!M147 -> 0.021079399 | N71: =Inputs!N147 -> 0.01695616 | O71: =Inputs!O147 -> 0.018438313 | ... AV71: =Inputs!AV147 -> 0.013456401
E72: Probability that a 5-year-old will die of a lower respiratory infection before reaching age 15 | F72: % | G72: input | H72: =Inputs!H148 -> - | I72: =Inputs!I148 -> 0.001298445 | J72: =Inputs!J148 -> 0.001136902 | K72: =Inputs!K148 -> 0.001358999 | L72: =Inputs!L148 -> 0.000848418 | M72: =Inputs!M148 -> 0.001325756 | N72: =Inputs!N148 -> 0.001052452 | O72: =Inputs!O148 -> 0.001083798 | ... AV72: =Inputs!AV148 -> 0.000921898
E73: Probability that a 15-year-old will die of a lower respiratory infection before reaching age 50 | F73: % | G73: input | H73: =Inputs!H149 -> - | I73: =Inputs!I149 -> 0.002586005 | J73: =Inputs!J149 -> 0.00203186 | K73: =Inputs!K149 -> 0.003081885 | L73: =Inputs!L149 -> 0.002004393 | M73: =Inputs!M149 -> 0.002148469 | N73: =Inputs!N149 -> 0.002520287 | O73: =Inputs!O149 -> 0.002528167 | ... AV73: =Inputs!AV149 -> 0.002595537
E74: Probability that a 50-year-old will die of a lower respiratory infection before reaching age 75 | F74: % | G74: input | H74: =Inputs!H150 -> - | I74: =Inputs!I150 -> 0.023849512 | J74: =Inputs!J150 -> 0.02352892 | K74: =Inputs!K150 -> 0.024494371 | L74: =Inputs!L150 -> 0.016803436 | M74: =Inputs!M150 -> 0.018501934 | N74: =Inputs!N150 -> 0.02109105 | O74: =Inputs!O150 -> 0.025109776 | ... AV74: =Inputs!AV150 -> 0.022438887
C76: Lower respiratory infection mortalities occurring before the age of vaccination
E77: Lower respiratory infection mortalities per year among people under age 5 | F77: # | G77: input | H77: =Inputs!H151 -> - | I77: =Inputs!I151 -> 6666.1604 | J77: =Inputs!J151 -> 2486.3679 | K77: =Inputs!K151 -> 5391.4653 | L77: =Inputs!L151 -> 5468.2709 | M77: =Inputs!M151 -> 14601.878 | N77: =Inputs!N151 -> 7218.5082 | O77: =Inputs!O151 -> 3722.4286 | ... AV77: =Inputs!AV151 -> 2310.5925
E78: Early neonatal lower respiratory infection mortalities per year (babies under 7 days old) | F78: # | G78: input | H78: =Inputs!H152 -> - | I78: =Inputs!I152 -> 1061.4675 | J78: =Inputs!J152 -> 381.06813 | K78: =Inputs!K152 -> 750.41368 | L78: =Inputs!L152 -> 981.21336 | M78: =Inputs!M152 -> 2779.113 | N78: =Inputs!N152 -> 1075.5619 | O78: =Inputs!O152 -> 697.04728 | ... AV78: =Inputs!AV152 -> 517.09376
E79: Late neonatal lower respiratory infection mortalities per year (babies between 7 and 27 days old) | F79: # | G79: input | H79: =Inputs!H153 -> - | I79: =Inputs!I153 -> 404.60418 | J79: =Inputs!J153 -> 172.49652 | K79: =Inputs!K153 -> 322.76861 | L79: =Inputs!L153 -> 560.45741 | M79: =Inputs!M153 -> 1432.3301 | N79: =Inputs!N153 -> 842.4771 | O79: =Inputs!O153 -> 317.37145 | ... AV79: =Inputs!AV153 -> 188.41491
E80: Proportion of lower respiratory infection mortalities among people under age 5 that occur during the neonatal period (babies between 0 and 27 days old) | F80: % | G80: calc | H80: - | I80: =SUM(I78:I79)/I77 -> 0.21992745 | J80: =SUM(J78:J79)/J77 -> 0.22263988 | K80: =SUM(K78:K79)/K77 -> 0.19905206 | L80: =SUM(L78:L79)/L77 -> 0.28193021 | M80: =SUM(M78:M79)/M77 -> 0.2884179 | N80: =SUM(N78:N79)/N77 -> 0.26571127 | O80: =SUM(O78:O79)/O77 -> 0.27251529 | P80: =SUM(P78:P79)/P77 -> 0.22209998 | ... AV80: =SUM(AV78:AV79)/AV77 -> 0.30533669
E81: Assumed ratio of lower respiratory infection mortalities among people under age 5 occurring after the neonatal period but before the age of Penta and PCV vaccination (6 weeks) to lower respiratory infection mortalities occurring in the neonatal period | F81: % | G81: input | H81: =Inputs!H154 -> 0.1 | I81: =Inputs!I154 -> - | J81: =Inputs!J154 -> - | K81: =Inputs!K154 -> - | L81: =Inputs!L154 -> - | M81: =Inputs!M154 -> - | N81: =Inputs!N154 -> - | O81: =Inputs!O154 -> - | ... AV81: =Inputs!AV154 -> -
E82: Proportion of lower respiratory infection mortalities among people under age 5 that occur before the age of Penta and PCV vaccination (6 weeks) | F82: % | G82: calc | H82: - | I82: =I80*(1+$H81) -> 0.24192019 | J82: =J80*(1+$H81) -> 0.24490387 | K82: =K80*(1+$H81) -> 0.21895727 | L82: =L80*(1+$H81) -> 0.31012323 | M82: =M80*(1+$H81) -> 0.31725969 | N82: =N80*(1+$H81) -> 0.29228239 | O82: =O80*(1+$H81) -> 0.29976682 | P82: =P80*(1+$H81) -> 0.24430998 | ... AV82: =AV80*(1+$H81) -> 0.33587036
E83: Probability that a person will die of a lower respiratory infection before reaching age 5, adjusted for deaths occurring before the age of vaccination | F83: % | G83: calc | H83: - | I83: =I71*(1-I82) -> 0.017732006 | J83: =J71*(1-J82) -> 0.014186612 | K83: =K71*(1-K82) -> 0.018017645 | L83: =L71*(1-L82) -> 0.0095701292 | M83: =M71*(1-M82) -> 0.014391755 | N83: =N71*(1-N82) -> 0.012000173 | O83: =O71*(1-O82) -> 0.012911118 | P83: =P71*(1-P82) -> 0.020371852 | ... AV83: =AV71*(1-AV82) -> 0.0089367948
C85: Disease etiology for lower respiratory infections
D86: Pathogens addressed by the Penta vaccine (H. influenzae type B)
E87: Proportion of lower respiratory infection deaths caused by pathogens addressed by the Penta vaccine (H. influenzae type B) | F87: % | G87: input | H87: =Inputs!H155 -> 0.0281715 | I87: =Inputs!I155 -> - | J87: =Inputs!J155 -> - | K87: =Inputs!K155 -> - | L87: =Inputs!L155 -> - | M87: =Inputs!M155 -> - | N87: =Inputs!N155 -> - | O87: =Inputs!O155 -> - | ... AV87: =Inputs!AV155 -> -
E88: Probability that a person will die of a lower respiratory infection caused by H. influenzae type B before reaching age 5, adjusted for deaths occuring before the age of vaccination | F88: % | G88: calc | H88: - | I88: =I83*$H$87 -> 0.00049953721 | J88: =J83*$H$87 -> 0.00039965815 | K88: =K83*$H$87 -> 0.00050758409 | L88: =L83*$H$87 -> 0.0002696049 | M88: =M83*$H$87 -> 0.00040543734 | N88: =N83*$H$87 -> 0.00033806287 | O88: =O83*$H$87 -> 0.00036372557 | P88: =P83*$H$87 -> 0.00057390564 | ... AV88: =AV83*$H$87 -> 0.00025176291
E89: Probability that a 5-year-old will die of a lower respiratory infection caused by H. influenzae type B before reaching age 15 | F89: % | G89: calc | H89: - | I89: =I72*$H$87 -> 3.6579143e-05 | J89: =J72*$H$87 -> 3.2028235e-05 | K89: =K72*$H$87 -> 3.828504e-05 | L89: =L72*$H$87 -> 2.3901208e-05 | M89: =M72*$H$87 -> 3.7348535e-05 | N89: =N72*$H$87 -> 2.9649152e-05 | O89: =O72*$H$87 -> 3.0532215e-05 | P89: =P72*$H$87 -> 4.1895641e-05 | ... AV89: =AV72*$H$87 -> 2.597125e-05
E90: Probability that a 15-year-old will die of a lower respiratory infection caused by H. influenzae type B before reaching age 50 | F90: % | G90: calc | H90: - | I90: =I73*$H$87 -> 7.285164e-05 | J90: =J73*$H$87 -> 5.7240544e-05 | K90: =K73*$H$87 -> 8.6821323e-05 | L90: =L73*$H$87 -> 5.6466757e-05 | M90: =M73*$H$87 -> 6.0525594e-05 | N90: =N73*$H$87 -> 7.1000265e-05 | O90: =O73*$H$87 -> 7.1222257e-05 | P90: =P73*$H$87 -> 9.3151572e-05 | ... AV90: =AV73*$H$87 -> 7.3120171e-05
E91: Probability that a 50-year-old will die of a lower respiratory infection caused by H. influenzae type B before reaching age 75 | F91: % | G91: calc | H91: - | I91: =I74*$H$87 -> 0.00067187653 | J91: =J74*$H$87 -> 0.00066284497 | K91: =K74*$H$87 -> 0.00069004317 | L91: =L74*$H$87 -> 0.000473378 | M91: =M74*$H$87 -> 0.00052122723 | N91: =N74*$H$87 -> 0.00059416652 | O91: =O74*$H$87 -> 0.00070738005 | P91: =P74*$H$87 -> 0.00068035068 | ... AV91: =AV74*$H$87 -> 0.00063213711
D92: Pathogens addressed by the PCV vaccine (S. pneumoniae)
E93: Proportion of lower respiratory infection deaths caused by pathogens addressed by the PCV vaccine (S. pneumoniae) | F93: % | G93: input | H93: =Inputs!H156 -> 0.395126 | I93: =Inputs!I156 -> - | J93: =Inputs!J156 -> - | K93: =Inputs!K156 -> - | L93: =Inputs!L156 -> - | M93: =Inputs!M156 -> - | N93: =Inputs!N156 -> - | O93: =Inputs!O156 -> - | ... AV93: =Inputs!AV156 -> -
E94: Probability that a person will die of a lower respiratory infection caused by S. pneumoniae before reaching age 5, adjusted for deaths occuring before the age of vaccination | F94: % | G94: calc | H94: - | I94: =I83*$H$93 -> 0.0070063766 | J94: =J83*$H$93 -> 0.0056054994 | K94: =K83*$H$93 -> 0.0071192401 | L94: =L83*$H$93 -> 0.0037814069 | M94: =M83*$H$93 -> 0.0056865568 | N94: =N83*$H$93 -> 0.0047415804 | O94: =O83*$H$93 -> 0.0051015186 | P94: =P83*$H$93 -> 0.0080494485 | ... AV94: =AV83*$H$93 -> 0.00353116
E95: Probability that a 5-year-old will die of a lower respiratory infection caused by S. pneumoniae before reaching age 15 | F95: % | G95: calc | H95: - | I95: =I72*$H$93 -> 0.00051304938 | J95: =J72*$H$93 -> 0.00044921954 | K95: =K72*$H$93 -> 0.00053697584 | L95: =L72*$H$93 -> 0.00033523201 | M95: =M72*$H$93 -> 0.00052384067 | N95: =N72*$H$93 -> 0.00041585115 | O95: =O72*$H$93 -> 0.00042823677 | P95: =P72*$H$93 -> 0.00058761717 | ... AV95: =AV72*$H$93 -> 0.00036426587
E96: Probability that a 15-year-old will die of a lower respiratory infection caused by S. pneumoniae before reaching age 50 | F96: % | G96: calc | H96: - | I96: =I73*$H$93 -> 0.0010217978 | J96: =J73*$H$93 -> 0.00080284072 | K96: =K73*$H$93 -> 0.0012177329 | L96: =L73*$H$93 -> 0.00079198779 | M96: =M73*$H$93 -> 0.00084891597 | N96: =N73*$H$93 -> 0.00099583093 | O96: =O73*$H$93 -> 0.00099894452 | P96: =P73*$H$93 -> 0.0013065193 | ... AV96: =AV73*$H$93 -> 0.0010255642
E97: Probability that a 50-year-old will die of a lower respiratory infection caused by S. pneumoniae before reaching age 75 | F97: % | G97: calc | H97: - | I97: =I74*$H$93 -> 0.0094235623 | J97: =J74*$H$93 -> 0.0092968881 | K97: =K74*$H$93 -> 0.0096783629 | L97: =L74*$H$93 -> 0.0066394745 | M97: =M74*$H$93 -> 0.0073105952 | N97: =N74*$H$93 -> 0.0083336223 | O97: =O74*$H$93 -> 0.0099215254 | P97: =P74*$H$93 -> 0.0095424186 | ... AV97: =AV74*$H$93 -> 0.0088661877
A99: Meningitis
C101: Probability of dying of meningitis
E102: Probability that a person will die of meningitis before reaching age 5 | F102: % | G102: input | H102: =Inputs!H159 -> - | I102: =Inputs!I159 -> 0.006177361 | J102: =Inputs!J159 -> 0.005211418 | K102: =Inputs!K159 -> 0.006472392 | L102: =Inputs!L159 -> 0.003542222 | M102: =Inputs!M159 -> 0.005411087 | N102: =Inputs!N159 -> 0.004841311 | O102: =Inputs!O159 -> 0.005304934 | ... AV102: =Inputs!AV159 -> 0.003392061
E103: Probability that a 5-year-old will die of meningitis before reaching age 15 | F103: % | G103: input | H103: =Inputs!H160 -> - | I103: =Inputs!I160 -> 0.000920251 | J103: =Inputs!J160 -> 0.00078274 | K103: =Inputs!K160 -> 0.000975938 | L103: =Inputs!L160 -> 0.000543254 | M103: =Inputs!M160 -> 0.00085293 | N103: =Inputs!N160 -> 0.000744263 | O103: =Inputs!O160 -> 0.000848212 | ... AV103: =Inputs!AV160 -> 0.000678181
E104: Probability that a 15-year-old will die of meningitis before reaching age 50 | F104: % | G104: input | H104: =Inputs!H161 -> - | I104: =Inputs!I161 -> 0.001870641 | J104: =Inputs!J161 -> 0.001396704 | K104: =Inputs!K161 -> 0.002364602 | L104: =Inputs!L161 -> 0.001256075 | M104: =Inputs!M161 -> 0.001435015 | N104: =Inputs!N161 -> 0.001813177 | O104: =Inputs!O161 -> 0.001952634 | ... AV104: =Inputs!AV161 -> 0.001933221
E105: Probability that a 50-year-old will die of meningitis before reaching age 75 | F105: % | G105: input | H105: =Inputs!H162 -> - | I105: =Inputs!I162 -> 0.004939422 | J105: =Inputs!J162 -> 0.00469284 | K105: =Inputs!K162 -> 0.005174821 | L105: =Inputs!L162 -> 0.003177413 | M105: =Inputs!M162 -> 0.003663199 | N105: =Inputs!N162 -> 0.004443934 | O105: =Inputs!O162 -> 0.005659515 | ... AV105: =Inputs!AV162 -> 0.004682851
C107: Meningitis mortalities occurring before the age of vaccination
E108: Meningitis mortalities per year among people under age 5 | F108: # | G108: input | H108: =Inputs!H163 -> - | I108: =Inputs!I163 -> 1739.1942 | J108: =Inputs!J163 -> 683.0973 | K108: =Inputs!K163 -> 1495.0313 | L108: =Inputs!L163 -> 1386.1806 | M108: =Inputs!M163 -> 3707.0388 | N108: =Inputs!N163 -> 2043.4856 | O108: =Inputs!O163 -> 1061.1067 | ... AV108: =Inputs!AV163 -> 578.33614
E109: Early neonatal meningitis mortalities per year (babies under 7 days old) | F109: # | G109: input | H109: =Inputs!H164 -> - | I109: =Inputs!I164 -> 106.41412 | J109: =Inputs!J164 -> 39.269078 | K109: =Inputs!K164 -> 72.158886 | L109: =Inputs!L164 -> 94.853912 | M109: =Inputs!M164 -> 232.53891 | N109: =Inputs!N164 -> 108.23066 | O109: =Inputs!O164 -> 74.780463 | ... AV109: =Inputs!AV164 -> 53.6266
E110: Late neonatal meningitis mortalities per year (babies between 7 and 27 days old) | F110: # | G110: input | H110: =Inputs!H165 -> - | I110: =Inputs!I165 -> 52.032348 | J110: =Inputs!J165 -> 22.478349 | K110: =Inputs!K165 -> 40.572531 | L110: =Inputs!L165 -> 68.290076 | M110: =Inputs!M165 -> 157.41032 | N110: =Inputs!N165 -> 105.15979 | O110: =Inputs!O165 -> 44.52236 | ... AV110: =Inputs!AV165 -> 24.434616
E111: Proportion of meningitis mortalities among people under age 5 that occur during the neonatal period (babies between 0 and 27 days old) | F111: % | G111: calc | H111: - | I111: =SUM(I109:I110)/I108 -> 0.09110338 | J111: =SUM(J109:J110)/J108 -> 0.090393311 | K111: =SUM(K109:K110)/K108 -> 0.075404054 | L111: =SUM(L109:L110)/L108 -> 0.11769317 | M111: =SUM(M109:M110)/M108 -> 0.10519157 | N111: =SUM(N109:N110)/N108 -> 0.10442474 | O111: =SUM(O109:O110)/O108 -> 0.11243245 | P111: =SUM(P109:P110)/P108 -> 0.091013481 | ... AV111: =SUM(AV109:AV110)/AV108 -> 0.13497551
E112: Assumed ratio of meningitis mortalities among people under age 5 occurring after the neonatal period but before the age of Penta and PCV vaccination (6 weeks) to meningitis mortalities occurring in the neonatal period | F112: % | G112: input | H112: =Inputs!H166 -> 0.1 | I112: =Inputs!I166 -> - | J112: =Inputs!J166 -> - | K112: =Inputs!K166 -> - | L112: =Inputs!L166 -> - | M112: =Inputs!M166 -> - | N112: =Inputs!N166 -> - | O112: =Inputs!O166 -> - | ... AV112: =Inputs!AV166 -> -
E113: Proportion of meningitis mortalities among people under age 5 that occur before the age of Penta and PCV vaccination (6 weeks) | F113: % | G113: calc | H113: - | I113: =I111*(1+$H112) -> 0.10021372 | J113: =J111*(1+$H112) -> 0.099432642 | K113: =K111*(1+$H112) -> 0.082944459 | L113: =L111*(1+$H112) -> 0.12946248 | M113: =M111*(1+$H112) -> 0.11571073 | N113: =N111*(1+$H112) -> 0.11486721 | O113: =O111*(1+$H112) -> 0.12367569 | P113: =P111*(1+$H112) -> 0.10011483 | ... AV113: =AV111*(1+$H112) -> 0.14847306
E114: Probability that a person will die of meningitis before reaching age 5, adjusted for deaths occurring before the age of vaccination | F114: % | G114: calc | H114: - | I114: =I102*(1-I113) -> 0.0055583047 | J114: =J102*(1-J113) -> 0.0046932329 | K114: =K102*(1-K113) -> 0.0059355429 | L114: =L102*(1-L113) -> 0.0030836371 | M114: =M102*(1-M113) -> 0.0047849662 | N114: =N102*(1-N113) -> 0.0042852031 | O114: =O102*(1-O113) -> 0.0046488426 | P114: =P102*(1-P113) -> 0.0072214453 | ... AV114: =AV102*(1-AV113) -> 0.0028884313
C116: Disease etiology for meningitis
D117: Pathogens addressed by the Penta vaccine (H. influenzae type B)
E118: Proportion of meningitis deaths caused by pathogens addressed by the Penta vaccine (H. influenzae type B) according to GBD 2019 | F118: % | G118: input | H118: =Inputs!H167 -> 0.2189 | I118: =Inputs!I167 -> - | J118: =Inputs!J167 -> - | K118: =Inputs!K167 -> - | L118: =Inputs!L167 -> - | M118: =Inputs!M167 -> - | N118: =Inputs!N167 -> - | O118: =Inputs!O167 -> - | ... AV118: =Inputs!AV167 -> -
E119: Adjustment for alignment with Hib meningitis burden estimates from View-Hub | F119: =Inputs!F168 -> % | G119: =Inputs!G168 -> input | H119: =Inputs!H168 -> 0.11261 | I119: =Inputs!I168 -> - | J119: =Inputs!J168 -> - | K119: =Inputs!K168 -> - | L119: =Inputs!L168 -> - | M119: =Inputs!M168 -> - | ... AV119: =Inputs!AV168 -> -
...

Sheet Vaccine coverage
I1: New Incentives – current states of operation | R1: New Incentives – prospective states | AF1: New Incentives – prospective states
I2: Nigeria | J2: Nigeria | K2: Nigeria | L2: Nigeria | M2: Nigeria | N2: Nigeria | O2: Nigeria | P2: Nigeria | Q2: Nigeria | R2: Nigeria | S2: Nigeria | T2: Nigeria | U2: Nigeria | V2: Nigeria | W2: Nigeria | X2: Nigeria | Y2: Nigeria | Z2: Nigeria | AA2: Nigeria | AB2: Nigeria | AC2: Nigeria | AD2: Nigeria | AE2: Nigeria | AF2: Nigeria | AG2: Nigeria | AH2: Nigeria | AI2: Nigeria | AJ2: Nigeria | AK2: Nigeria | AL2: Nigeria | AM2: Nigeria | AN2: Nigeria | AO2: Nigeria | AP2: Nigeria | AQ2: Nigeria | AR2: Nigeria | AS2: Nigeria | AT2: Nigeria | AU2: Nigeria | AV2: Nigeria
A3: Main calculations | F3: unit | G3: type | H3: Overall | I3: Bauchi | J3: Gombe | K3: Jigawa | L3: Kaduna - cohort 17 | M3: Kano | N3: Katsina | O3: Kebbi | P3: Sokoto | Q3: Zamfara | R3: Abia | S3: Adamawa | T3: Akwa Ibom | U3: Anambra | V3: Bayelsa | W3: Benue | X3: Borno | Y3: Cross River | Z3: Delta | AA3: Ebonyi | AB3: Edo | AC3: Ekiti | AD3: Enugu | AE3: FCT | AF3: Imo | AG3: Kaduna | AH3: Kogi | AI3: Kwara | AJ3: Lagos | AK3: Nasarawa | AL3: Niger | AM3: Niger - cohorts 32 & 36 | AN3: Niger - cohort 34 | AO3: Ogun | AP3: Ondo | AQ3: Osun | AR3: Oyo | AS3: Plateau | AT3: Rivers | AU3: Taraba | AV3: Yobe
E4: Final cost-effectiveness estimate (pulled from "Main calcs" sheet for visibility) | F4: ='Main CEA'!F242 -> xbenchmark | G4: ='Main CEA'!G242 -> calc | H4: ='Main CEA'!H242 -> - | I4: ='Main CEA'!I242 -> 20.039606 | J4: ='Main CEA'!J242 -> 10.020838 | K4: ='Main CEA'!K242 -> 18.177505 | L4: ='Main CEA'!L242 -> 9.0027672 | M4: ='Main CEA'!M242 -> 12.612827 | ... AV4: ='Main CEA'!AV242 -> 11.471963
A5: Baseline vaccination coverage among the target population according to New Incentives' coverage surveys
C7: Populations targeted by New Incentives' coverage surveys
E8: Number of local government areas (LGAs) within the state | F8: # | G8: input | H8: =Inputs!H41 -> - | I8: =Inputs!I41 -> 20 | J8: =Inputs!J41 -> 11 | K8: =Inputs!K41 -> 27 | L8: =Inputs!L41 -> 6 | M8: =Inputs!M41 -> 44 | N8: =Inputs!N41 -> 34 | O8: =Inputs!O41 -> 21 | ... AV8: =Inputs!AV41 -> 17
E9: Number of LGAs surveyed by New Incentives' coverage survey | F9: # | G9: input | H9: =Inputs!H42 -> - | I9: =Inputs!I42 -> 20 | J9: =Inputs!J42 -> 11 | K9: =Inputs!K42 -> 23 | L9: =Inputs!L42 -> 6 | M9: =Inputs!M42 -> 44 | N9: =Inputs!N42 -> 12 | O9: =Inputs!O42 -> 16 | ... AV9: =Inputs!AV42 -> 10
E10: Proportion of LGAs surveyed | F10: % | G10: calc | H10: - | I10: =I9/I8 -> 1 | J10: =J9/J8 -> 1 | K10: =K9/K8 -> 0.85185185 | L10: =L9/L8 -> 1 | M10: =M9/M8 -> 1 | N10: =N9/N8 -> 0.35294118 | O10: =O9/O8 -> 0.76190476 | P10: =P9/P8 -> 0.60869565 | ... AV10: =AV9/AV8 -> 0.58823529
E11: Adjustment for higher confidence in coverage survey results | F11: % | G11: input | H11: =Inputs!H45 -> 0.5 | I11: =Inputs!I45 -> - | J11: =Inputs!J45 -> - | K11: =Inputs!K45 -> - | L11: =Inputs!L45 -> - | M11: =Inputs!M45 -> - | N11: =Inputs!N45 -> - | O11: =Inputs!O45 -> - | ... AV11: =Inputs!AV45 -> -
E12: Weight placed on the results of New Incentives' coverage surveys for estimating BCG, Penta, and PCV coverage | F12: % | G12: calc | H12: - | I12: =IF(I10=0,0,MIN(1,(I10*(1+$H11)))) -> 1 | J12: =IF(J10=0,0,MIN(1,(J10*(1+$H11)))) -> 1 | K12: =IF(K10=0,0,MIN(1,(K10*(1+$H11)))) -> 1 | L12: =IF(L10=0,0,MIN(1,(L10*(1+$H11)))) -> 1 | M12: =IF(M10=0,0,MIN(1,(M10*(1+$H11)))) -> 1 | N12: =IF(N10=0,0,MIN(1,(N10*(1+$H11)))) -> 0.52941176 | O12: =IF(O10=0,0,MIN(1,(O10*(1+$H11)))) -> 1 | P12: =IF(P10=0,0,MIN(1,(P10*(1+$H11)))) -> 0.91304348 | ... AV12: =IF(AV10=0,0,MIN(1,(AV10*(1+$H11)))) -> 0.88235294
E13: Starting year of New Incentives' coverage surveys | F13: # | G13: input | I13: =Inputs!I43 -> 2022 | J13: =Inputs!J43 -> 2022 | K13: =Inputs!K43 -> 2021 | L13: =Inputs!L43 -> 2023 | M13: =Inputs!M43 -> 2022 | N13: =Inputs!N43 -> 2021 | O13: =Inputs!O43 -> 2023 | P13: =Inputs!P43 -> 2022 | ... AV13: =Inputs!AV43 -> 2024
E14: Ending year of New Incentives' coverage surveys | F14: # | G14: input | I14: =Inputs!I44 -> 2022 | J14: =Inputs!J44 -> 2023 | K14: =Inputs!K44 -> 2022 | L14: =Inputs!L44 -> 2023 | M14: =Inputs!M44 -> 2023 | N14: =Inputs!N44 -> 2022 | O14: =Inputs!O44 -> 2023 | P14: =Inputs!P44 -> 2022 | ... AW14: =Inputs!AW44
E15: Effective year of baseline measurement | F15: # | G15: calc | I15: =AVERAGE(I13:I14)*I12+2021*(1-I12) -> 2022 | J15: =AVERAGE(J13:J14)*J12+2021*(1-J12) -> 2022.5 | K15: =AVERAGE(K13:K14)*K12+2021*(1-K12) -> 2021.5 | L15: =AVERAGE(L13:L14)*L12+2021*(1-L12) -> 2023 | M15: =AVERAGE(M13:M14)*M12+2021*(1-M12) -> 2022.5 | N15: =AVERAGE(N13:N14)*N12+2021*(1-N12) -> 2021.2647 | O15: =AVERAGE(O13:O14)*O12+2021*(1-O12) -> 2023 | P15: =AVERAGE(P13:P14)*P12+2021*(1-P12) -> 2021.913 | ... AV15: =AVERAGE(AV13:AV14)*AV12+2021*(1-AV12) -> 2023.6471
C17: Baseline vaccination coverage found in New Incentives' coverage surveys
E18: Proportion of children reported to have received the BCG vaccine in New Incentives' coverage surveys | F18: % | G18: input | H18: =Inputs!H48 -> - | I18: =Inputs!I48 -> 0.5521 | J18: =Inputs!J48 -> 0.7284 | K18: =Inputs!K48 -> 0.6074 | L18: =Inputs!L48 -> 0.6377 | M18: =Inputs!M48 -> 0.6149 | N18: =Inputs!N48 -> 0.4236 | O18: =Inputs!O48 -> 0.4004 | ... AV18: =Inputs!AV48 -> 0.6278
E19: Proportion of children reported to have received the 1st dose of the Penta vaccine in New Incentives' coverage surveys | F19: % | G19: input | H19: =Inputs!H49 -> - | I19: =Inputs!I49 -> 0.4931 | J19: =Inputs!J49 -> 0.6764 | K19: =Inputs!K49 -> 0.572 | L19: =Inputs!L49 -> 0.5973 | M19: =Inputs!M49 -> 0.5621 | N19: =Inputs!N49 -> 0.3916 | O19: =Inputs!O49 -> 0.3379 | ... AV19: =Inputs!AV49 -> 0.5899
E20: Proportion of children reported to have received the 2nd dose of the Penta vaccine in New Incentives' coverage surveys | F20: % | G20: input | H20: =Inputs!H50 -> - | I20: =Inputs!I50 -> 0.4471 | J20: =Inputs!J50 -> 0.6332 | K20: =Inputs!K50 -> 0.5154 | L20: =Inputs!L50 -> 0.507 | M20: =Inputs!M50 -> 0.4824 | N20: =Inputs!N50 -> 0.374 | O20: =Inputs!O50 -> 0.2428 | ... AV20: =Inputs!AV50 -> 0.4777
E21: Proportion of children reported to have received the 3rd dose of the Penta vaccine in New Incentives' coverage surveys | F21: % | G21: input | H21: =Inputs!H51 -> - | I21: =Inputs!I51 -> 0.354 | J21: =Inputs!J51 -> 0.5015 | K21: =Inputs!K51 -> 0.3966 | L21: =Inputs!L51 -> 0.4094 | M21: =Inputs!M51 -> 0.3687 | N21: =Inputs!N51 -> 0.2963 | O21: =Inputs!O51 -> 0.1543 | ... AV21: =Inputs!AV51 -> 0.3791
E22: Proportion of children reported to have received the 1st dose of the measles vaccine in New Incentives' coverage surveys | F22: % | G22: input | H22: =Inputs!H52 -> - | I22: =Inputs!I52 -> 0.3526 | J22: =Inputs!J52 -> 0.4886 | K22: =Inputs!K52 -> 0.3738 | L22: =Inputs!L52 -> 0.323 | M22: =Inputs!M52 -> 0.3228 | N22: =Inputs!N52 -> 0.2629 | O22: =Inputs!O52 -> 0.2326 | ... AV22: =Inputs!AV52 -> 0.3495
C24: Baseline vaccination coverage found in coverage surveys, adjusted for self-report bias
E25: Adjustment for self-report bias in New Incentives' coverage surveys | F25: % | G25: input | H25: =Inputs!H55 -> 0.00059
E26: Estimated proportion of children who receive the BCG vaccine according to New Incentives' coverage surveys | F26: % | G26: calc | H26: - | I26: =IFERROR(I18*(1+$H$25),"-") -> 0.55242574 | J26: =IFERROR(J18*(1+$H$25),"-") -> 0.72882976 | K26: =IFERROR(K18*(1+$H$25),"-") -> 0.60775837 | L26: =IFERROR(L18*(1+$H$25),"-") -> 0.63807624 | M26: =IFERROR(M18*(1+$H$25),"-") -> 0.61526279 | N26: =IFERROR(N18*(1+$H$25),"-") -> 0.42384992 | O26: =IFERROR(O18*(1+$H$25),"-") -> 0.40063624 | P26: =IFERROR(P18*(1+$H$25),"-") -> 0.3497062 | ... AV26: =IFERROR(AV18*(1+$H$25),"-") -> 0.6281704
E27: Estimated proportion of children who receive the 1st dose of the Penta vaccine according to New Incentives' coverage surveys | F27: % | G27: calc | H27: - | I27: =IFERROR(I19*(1+$H$25),"-") -> 0.49339093 | J27: =IFERROR(J19*(1+$H$25),"-") -> 0.67679908 | K27: =IFERROR(K19*(1+$H$25),"-") -> 0.57233748 | L27: =IFERROR(L19*(1+$H$25),"-") -> 0.59765241 | M27: =IFERROR(M19*(1+$H$25),"-") -> 0.56243164 | N27: =IFERROR(N19*(1+$H$25),"-") -> 0.39183104 | O27: =IFERROR(O19*(1+$H$25),"-") -> 0.33809936 | P27: =IFERROR(P19*(1+$H$25),"-") -> 0.27136001 | ... AV27: =IFERROR(AV19*(1+$H$25),"-") -> 0.59024804
E28: Estimated proportion of children who receive the 2nd dose of the Penta vaccine according to New Incentives' coverage surveys | F28: % | G28: calc | H28: - | I28: =IFERROR(I20*(1+$H$25),"-") -> 0.44736379 | J28: =IFERROR(J20*(1+$H$25),"-") -> 0.63357359 | K28: =IFERROR(K20*(1+$H$25),"-") -> 0.51570409 | L28: =IFERROR(L20*(1+$H$25),"-") -> 0.50729913 | M28: =IFERROR(M20*(1+$H$25),"-") -> 0.48268462 | N28: =IFERROR(N20*(1+$H$25),"-") -> 0.37422066 | O28: =IFERROR(O20*(1+$H$25),"-") -> 0.24294325 | P28: =IFERROR(P20*(1+$H$25),"-") -> 0.25995328 | ... AV28: =IFERROR(AV20*(1+$H$25),"-") -> 0.47798184
E29: Estimated proportion of children who receive the 3rd dose of the Penta vaccine according to New Incentives' coverage surveys | F29: % | G29: calc | H29: - | I29: =IFERROR(I21*(1+$H$25),"-") -> 0.35420886 | J29: =IFERROR(J21*(1+$H$25),"-") -> 0.50179589 | K29: =IFERROR(K21*(1+$H$25),"-") -> 0.39683399 | L29: =IFERROR(L21*(1+$H$25),"-") -> 0.40964155 | M29: =IFERROR(M21*(1+$H$25),"-") -> 0.36891753 | N29: =IFERROR(N21*(1+$H$25),"-") -> 0.29647482 | O29: =IFERROR(O21*(1+$H$25),"-") -> 0.15439104 | P29: =IFERROR(P21*(1+$H$25),"-") -> 0.18821098 | ... AV29: =IFERROR(AV21*(1+$H$25),"-") -> 0.37932367
E30: Estimated proportion of children who receive the 1st dose of the measles vaccine according to New Incentives' coverage surveys | F30: % | G30: calc | H30: - | I30: =IFERROR(I22*(1+$H$25),"-") -> 0.35280803 | J30: =IFERROR(J22*(1+$H$25),"-") -> 0.48888827 | K30: =IFERROR(K22*(1+$H$25),"-") -> 0.37402054 | L30: =IFERROR(L22*(1+$H$25),"-") -> 0.32319057 | M30: =IFERROR(M22*(1+$H$25),"-") -> 0.32299045 | N30: =IFERROR(N22*(1+$H$25),"-") -> 0.26305511 | O30: =IFERROR(O22*(1+$H$25),"-") -> 0.23273723 | P30: =IFERROR(P22*(1+$H$25),"-") -> 0.21272543 | ... AV30: =IFERROR(AV22*(1+$H$25),"-") -> 0.3497062
A32: Baseline vaccination coverage among the target population according to the 2021 MICS survey results
C34: Baseline vaccination coverage found in the 2021 MICS coverage survey
E35: Proportion of children reported to have received the BCG vaccine in the 2021 MICS survey | F35: % | G35: input | H35: =Inputs!H58 -> - | I35: =Inputs!I58 -> 0.491 | J35: =Inputs!J58 -> 0.59 | K35: =Inputs!K58 -> 0.635 | L35: =Inputs!L58 -> 0.781 | M35: =Inputs!M58 -> 0.603 | N35: =Inputs!N58 -> 0.569 | O35: =Inputs!O58 -> 0.636 | ... AV35: =Inputs!AV58 -> 0.752
E36: Proportion of children reported to have received the 1st dose of the Penta vaccine in the 2021 MICS survey | F36: % | G36: input | H36: =Inputs!H59 -> - | I36: =Inputs!I59 -> 0.423 | J36: =Inputs!J59 -> 0.542 | K36: =Inputs!K59 -> 0.614 | L36: =Inputs!L59 -> 0.726 | M36: =Inputs!M59 -> 0.549 | N36: =Inputs!N59 -> 0.53 | O36: =Inputs!O59 -> 0.595 | ... AV36: =Inputs!AV59 -> 0.738
E37: Proportion of children reported to have received the 2nd dose of the Penta vaccine in the 2021 MICS survey | F37: % | G37: input | H37: =Inputs!H60 -> - | I37: =Inputs!I60 -> 0.376 | J37: =Inputs!J60 -> 0.512 | K37: =Inputs!K60 -> 0.564 | L37: =Inputs!L60 -> 0.665 | M37: =Inputs!M60 -> 0.47 | N37: =Inputs!N60 -> 0.466 | O37: =Inputs!O60 -> 0.584 | ... AV37: =Inputs!AV60 -> 0.712
E38: Proportion of children reported to have received the 3rd dose of the Penta vaccine in the 2021 MICS survey | F38: % | G38: input | H38: =Inputs!H61 -> - | I38: =Inputs!I61 -> 0.313 | J38: =Inputs!J61 -> 0.38 | K38: =Inputs!K61 -> 0.488 | L38: =Inputs!L61 -> 0.603 | M38: =Inputs!M61 -> 0.424 | N38: =Inputs!N61 -> 0.412 | O38: =Inputs!O61 -> 0.551 | ... AV38: =Inputs!AV61 -> 0.642
E39: Proportion of children reported to have received the 1st dose of the PCV vaccine in the 2021 MICS survey | F39: % | G39: input | H39: =Inputs!H62 -> - | I39: =Inputs!I62 -> 0.415 | J39: =Inputs!J62 -> 0.522 | K39: =Inputs!K62 -> 0.606 | L39: =Inputs!L62 -> 0.72 | M39: =Inputs!M62 -> 0.544 | N39: =Inputs!N62 -> 0.518 | O39: =Inputs!O62 -> 0.596 | ... AV39: =Inputs!AV62 -> 0.72
E40: Proportion of children reported to have received the 2nd dose of the PCV vaccine in the 2021 MICS survey | F40: % | G40: input | H40: =Inputs!H63 -> - | I40: =Inputs!I63 -> 0.38 | J40: =Inputs!J63 -> 0.467 | K40: =Inputs!K63 -> 0.555 | L40: =Inputs!L63 -> 0.647 | M40: =Inputs!M63 -> 0.466 | N40: =Inputs!N63 -> 0.439 | O40: =Inputs!O63 -> 0.569 | ... AV40: =Inputs!AV63 -> 0.681
E41: Proportion of children reported to have received the 3rd dose of the PCV vaccine in the 2021 MICS survey | F41: % | G41: input | H41: =Inputs!H64 -> - | I41: =Inputs!I64 -> 0.313 | J41: =Inputs!J64 -> 0.369 | K41: =Inputs!K64 -> 0.483 | L41: =Inputs!L64 -> 0.59 | M41: =Inputs!M64 -> 0.399 | N41: =Inputs!N64 -> 0.391 | O41: =Inputs!O64 -> 0.539 | ... AV41: =Inputs!AV64 -> 0.631
E42: Proportion of children reported to have received the 1st dose of the measles vaccine in the 2021 MICS survey | F42: % | G42: input | H42: =Inputs!H65 -> - | I42: =Inputs!I65 -> 0.308 | J42: =Inputs!J65 -> 0.367 | K42: =Inputs!K65 -> 0.559 | L42: =Inputs!L65 -> 0.567 | M42: =Inputs!M65 -> 0.405 | N42: =Inputs!N65 -> 0.437 | O42: =Inputs!O65 -> 0.632 | ... AV42: =Inputs!AV65 -> 0.713
E43: Proportion of children reported to have received the 2nd dose of the measles vaccine in the 2021 MICS survey | F43: % | G43: input | H43: =Inputs!H66 -> - | I43: =Inputs!I66 -> 0.108 | J43: =Inputs!J66 -> 0.178 | K43: =Inputs!K66 -> 0.327 | L43: =Inputs!L66 -> 0.309 | M43: =Inputs!M66 -> 0.142 | N43: =Inputs!N66 -> 0.247 | O43: =Inputs!O66 -> 0.549 | ... AV43: =Inputs!AV66 -> 0.484
C45: Baseline vaccination coverage based on the 2021 MICS survey, adjusted for self-report bias
E46: Proportion of positive responses that came from self-report in the 2021 MICS survey | F46: % | G46: input | H46: =Inputs!H76 -> 0.217176 | I46: =Inputs!I76 -> - | J46: =Inputs!J76 -> - | K46: =Inputs!K76 -> - | L46: =Inputs!L76 -> - | M46: =Inputs!M76 -> - | N46: =Inputs!N76 -> - | O46: =Inputs!O76 -> - | ... AV46: =Inputs!AV76 -> -
E47: Adjustment for self-report bias in the 2021 MICS coverage survey | F47: % | G47: calc | H47: =H25*H46 -> 0.00012813384 | I47: - | J47: - | K47: - | L47: - | M47: - | N47: - | O47: - | P47: - | Q47: - | R47: - | S47: - | T47: - | U47: - | V47: - | W47: - | X47: - | Y47: - | Z47: - | AA47: - | AB47: - | AC47: - | AD47: - | AE47: - | AF47: - | AG47: - | AH47: - | AI47: - | AJ47: - | AK47: - | AL47: - | AM47: - | AN47: - | AO47: - | AP47: - | AQ47: - | AR47: - | AS47: - | AT47: - | AU47: - | AV47: -
E48: Estimated proportion of children who receive the BCG vaccine | F48: % | G48: calc | H48: - | I48: =I35*(1+$H$47) -> 0.49106291 | J48: =J35*(1+$H$47) -> 0.5900756 | K48: =K35*(1+$H$47) -> 0.63508137 | L48: =L35*(1+$H$47) -> 0.78110007 | M48: =M35*(1+$H$47) -> 0.60307726 | N48: =N35*(1+$H$47) -> 0.56907291 | O48: =O35*(1+$H$47) -> 0.63608149 | P48: =P35*(1+$H$47) -> 0.33704318 | ... AV48: =AV35*(1+$H$47) -> 0.75209636
E49: Estimated proportion of children who receive the 1st dose of the Penta vaccine according to the 2021 MICS survey | F49: % | G49: calc | H49: - | I49: =I36*(1+$H$47) -> 0.4230542 | J49: =J36*(1+$H$47) -> 0.54206945 | K49: =K36*(1+$H$47) -> 0.61407867 | L49: =L36*(1+$H$47) -> 0.72609303 | M49: =M36*(1+$H$47) -> 0.54907035 | N49: =N36*(1+$H$47) -> 0.53006791 | O49: =O36*(1+$H$47) -> 0.59507624 | P49: =P36*(1+$H$47) -> 0.2880369 | ... AV49: =AV36*(1+$H$47) -> 0.73809456
E50: Estimated proportion of children who receive the 2nd dose of the Penta vaccine according to the 2021 MICS survey | F50: % | G50: calc | H50: - | I50: =I37*(1+$H$47) -> 0.37604818 | J50: =J37*(1+$H$47) -> 0.5120656 | K50: =K37*(1+$H$47) -> 0.56407227 | L50: =L37*(1+$H$47) -> 0.66508521 | M50: =M37*(1+$H$47) -> 0.47006022 | N50: =N37*(1+$H$47) -> 0.46605971 | O50: =O37*(1+$H$47) -> 0.58407483 | P50: =P37*(1+$H$47) -> 0.18402358 | ... AV50: =AV37*(1+$H$47) -> 0.71209123
E51: Estimated proportion of children who receive the 3rd dose of the Penta vaccine according to the 2021 MICS survey | F51: % | G51: calc | H51: - | I51: =I38*(1+$H$47) -> 0.31304011 | J51: =J38*(1+$H$47) -> 0.38004869 | K51: =K38*(1+$H$47) -> 0.48806253 | L51: =L38*(1+$H$47) -> 0.60307726 | M51: =M38*(1+$H$47) -> 0.42405433 | N51: =N38*(1+$H$47) -> 0.41205279 | O51: =O38*(1+$H$47) -> 0.5510706 | P51: =P38*(1+$H$47) -> 0.11501474 | ... AV51: =AV38*(1+$H$47) -> 0.64208226
E52: Estimated proportion of children who receive the 1st dose of the PCV vaccine according to the 2021 MICS survey | F52: % | G52: calc | H52: - | I52: =I39*(1+$H$47) -> 0.41505318 | J52: =J39*(1+$H$47) -> 0.52206689 | K52: =K39*(1+$H$47) -> 0.60607765 | L52: =L39*(1+$H$47) -> 0.72009226 | M52: =M39*(1+$H$47) -> 0.5440697 | N52: =N39*(1+$H$47) -> 0.51806637 | O52: =O39*(1+$H$47) -> 0.59607637 | P52: =P39*(1+$H$47) -> 0.21802793 | ... AV52: =AV39*(1+$H$47) -> 0.72009226
E53: Estimated proportion of children who receive the 2nd dose of the PCV vaccine according to the 2021 MICS survey | F53: % | G53: calc | H53: - | I53: =I40*(1+$H$47) -> 0.38004869 | J53: =J40*(1+$H$47) -> 0.46705984 | K53: =K40*(1+$H$47) -> 0.55507111 | L53: =L40*(1+$H$47) -> 0.6470829 | M53: =M40*(1+$H$47) -> 0.46605971 | N53: =N40*(1+$H$47) -> 0.43905625 | O53: =O40*(1+$H$47) -> 0.56907291 | P53: =P40*(1+$H$47) -> 0.1420182 | ... AV53: =AV40*(1+$H$47) -> 0.68108726
E54: Estimated proportion of children who receive the 3rd dose of the PCV vaccine according to the 2021 MICS survey | F54: % | G54: calc | H54: - | I54: =I41*(1+$H$47) -> 0.31304011 | J54: =J41*(1+$H$47) -> 0.36904728 | K54: =K41*(1+$H$47) -> 0.48306189 | L54: =L41*(1+$H$47) -> 0.5900756 | M54: =M41*(1+$H$47) -> 0.39905113 | N54: =N41*(1+$H$47) -> 0.3910501 | O54: =O41*(1+$H$47) -> 0.53906906 | P54: =P41*(1+$H$47) -> 0.10001281 | ... AV54: =AV41*(1+$H$47) -> 0.63108085
E55: Estimated proportion of children who receive the 1st dose of the measles vaccine according to the 2021 MICS survey | F55: % | G55: calc | H55: - | I55: =I42*(1+$H$47) -> 0.30803947 | J55: =J42*(1+$H$47) -> 0.36704703 | K55: =K42*(1+$H$47) -> 0.55907163 | L55: =L42*(1+$H$47) -> 0.56707265 | M55: =M42*(1+$H$47) -> 0.40505189 | N55: =N42*(1+$H$47) -> 0.43705599 | O55: =O42*(1+$H$47) -> 0.63208098 | P55: =P42*(1+$H$47) -> 0.19102447 | ... AV55: =AV42*(1+$H$47) -> 0.71309136
E56: Estimated proportion of children who receive the 2nd dose of the measles vaccine according to the 2021 MICS survey | F56: % | G56: calc | H56: - | I56: =I43*(1+$H$47) -> 0.10801384 | J56: =J43*(1+$H$47) -> 0.17802281 | K56: =K43*(1+$H$47) -> 0.3270419 | L56: =L43*(1+$H$47) -> 0.30903959 | M56: =M43*(1+$H$47) -> 0.1420182 | N56: =N43*(1+$H$47) -> 0.24703165 | O56: =O43*(1+$H$47) -> 0.54907035 | P56: =P43*(1+$H$47) -> 0.1850237 | ... AV56: =AV43*(1+$H$47) -> 0.48406202
A58: Baseline vaccination coverage among the target population according to the 2017 MICS survey results
C60: Baseline vaccination coverage found in the 2017 MICS coverage survey
E61: Proportion of children reported to have received the BCG vaccine in the 2017 MICS survey | F61: % | G61: input | H61: =Inputs!H72 -> - | I61: =Inputs!I72 -> 0.412 | J61: =Inputs!J72 -> 0.544 | K61: =Inputs!K72 -> 0.256 | L61: =Inputs!L72 -> 0.514 | M61: =Inputs!M72 -> 0.337 | N61: =Inputs!N72 -> 0.285 | O61: =Inputs!O72 -> 0.226 | ... AV61: =Inputs!AV72 -> 0.163
E62: Proportion of children reported to have received the 1st dose of the Penta vaccine in the 2017 MICS survey | F62: % | G62: input | H62: =Inputs!H69 -> - | I62: =Inputs!I69 -> 0.353 | J62: =Inputs!J69 -> 0.447 | K62: =Inputs!K69 -> 0.195 | L62: =Inputs!L69 -> 0.437 | M62: =Inputs!M69 -> 0.279 | N62: =Inputs!N69 -> 0.282 | O62: =Inputs!O69 -> 0.202 | ... AV62: =Inputs!AV69 -> 0.175
E63: Proportion of children reported to have received the 2nd dose of the Penta vaccine in the 2017 MICS survey | F63: % | G63: input | H63: =Inputs!H70 -> - | I63: =Inputs!I70 -> 0.252 | J63: =Inputs!J70 -> 0.291 | K63: =Inputs!K70 -> 0.09 | L63: =Inputs!L70 -> 0.325 | M63: =Inputs!M70 -> 0.209 | N63: =Inputs!N70 -> 0.183 | O63: =Inputs!O70 -> 0.167 | ... AV63: =Inputs!AV70 -> 0.113
E64: Proportion of children reported to have received the 3rd dose of the Penta vaccine in the 2017 MICS survey | F64: % | G64: input | H64: =Inputs!H71 -> - | I64: =Inputs!I71 -> 0.185 | J64: =Inputs!J71 -> 0.25 | K64: =Inputs!K71 -> 0.071 | L64: =Inputs!L71 -> 0.295 | M64: =Inputs!M71 -> 0.159 | N64: =Inputs!N71 -> 0.121 | O64: =Inputs!O71 -> 0.113 | ... AV64: =Inputs!AV71 -> 0.087
E65: Proportion of children reported to have received the 1st dose of the measles vaccine in the 2017 MICS survey | F65: % | G65: input | H65: =Inputs!H73 -> - | I65: =Inputs!I73 -> 0.222 | J65: =Inputs!J73 -> 0.324 | K65: =Inputs!K73 -> 0.104 | L65: =Inputs!L73 -> 0.431 | M65: =Inputs!M73 -> 0.241 | N65: =Inputs!N73 -> 0.211 | O65: =Inputs!O73 -> 0.255 | ... AV65: =Inputs!AV73 -> 0.147
C67: Baseline vaccination coverage based on the 2017 MICS survey, adjusted for self-report bias
E68: Proportion of positive responses that came from self-report in the 2017 MICS survey | F68: % | G68: input | H68: =Inputs!H77 -> 0.4415068 | I68: =Inputs!I77 -> - | J68: =Inputs!J77 -> - | K68: =Inputs!K77 -> - | L68: =Inputs!L77 -> - | M68: =Inputs!M77 -> - | N68: =Inputs!N77 -> - | O68: =Inputs!O77 -> - | ... AV68: =Inputs!AV77 -> -
E69: Adjustment for self-report bias in the 2017 MICS coverage survey | F69: % | G69: calc | H69: =H25*H68 -> 0.00026048901 | I69: - | J69: - | K69: - | L69: - | M69: - | N69: - | O69: - | P69: - | Q69: - | R69: - | S69: - | T69: - | U69: - | V69: - | W69: - | X69: - | Y69: - | Z69: - | AA69: - | AB69: - | AC69: - | AD69: - | AE69: - | AF69: - | AG69: - | AH69: - | AI69: - | AJ69: - | AK69: - | AL69: - | AM69: - | AN69: - | AO69: - | AP69: - | AQ69: - | AR69: - | AS69: - | AT69: - | AU69: - | AV69: -
E70: Estimated proportion of children who receive the BCG vaccine according to the 2017 MICS survey | F70: % | G70: calc | H70: - | I70: =I61*(1+$H$69) -> 0.41210732 | J70: =J61*(1+$H$69) -> 0.54414171 | K70: =K61*(1+$H$69) -> 0.25606669 | L70: =L61*(1+$H$69) -> 0.51413389 | M70: =M61*(1+$H$69) -> 0.33708778 | N70: =N61*(1+$H$69) -> 0.28507424 | O70: =O61*(1+$H$69) -> 0.22605887 | P70: =P61*(1+$H$69) -> 0.16304246 | ... AV70: =AV61*(1+$H$69) -> 0.16304246
E71: Estimated proportion of children who receive the 1st dose of the Penta vaccine according to the 2017 MICS survey | F71: % | G71: calc | H71: - | I71: =I62*(1+$H$69) -> 0.35309195 | J71: =J62*(1+$H$69) -> 0.44711644 | K71: =K62*(1+$H$69) -> 0.1950508 | L71: =L62*(1+$H$69) -> 0.43711383 | M71: =M62*(1+$H$69) -> 0.27907268 | N71: =N62*(1+$H$69) -> 0.28207346 | O71: =O62*(1+$H$69) -> 0.20205262 | P71: =P62*(1+$H$69) -> 0.094024486 | ... AV71: =AV62*(1+$H$69) -> 0.17504559
E72: Estimated proportion of children who receive the 2nd dose of the Penta vaccine according to the 2017 MICS survey | F72: % | G72: calc | H72: - | I72: =I63*(1+$H$69) -> 0.25206564 | J72: =J63*(1+$H$69) -> 0.2910758 | K72: =K63*(1+$H$69) -> 0.090023444 | L72: =L63*(1+$H$69) -> 0.32508466 | M72: =M63*(1+$H$69) -> 0.20905444 | N72: =N63*(1+$H$69) -> 0.18304767 | O72: =O63*(1+$H$69) -> 0.1670435 | P72: =P63*(1+$H$69) -> 0.052013545 | ... AV72: =AV63*(1+$H$69) -> 0.11302944
E73: Estimated proportion of children who receive the 3rd dose of the Penta vaccine according to the 2017 MICS survey | F73: % | G73: calc | H73: - | I73: =I64*(1+$H$69) -> 0.18504819 | J73: =J64*(1+$H$69) -> 0.25006512 | K73: =K64*(1+$H$69) -> 0.071018495 | L73: =L64*(1+$H$69) -> 0.29507684 | M73: =M64*(1+$H$69) -> 0.15904142 | N73: =N64*(1+$H$69) -> 0.12103152 | O73: =O64*(1+$H$69) -> 0.11302944 | P73: =P64*(1+$H$69) -> 0.029007554 | ... AV73: =AV64*(1+$H$69) -> 0.087022663
E74: Estimated proportion of children who receive the 1st dose of the measles vaccine according to the 2017 MICS survey | F74: % | G74: calc | H74: - | I74: =I65*(1+$H$69) -> 0.22205783 | J74: =J65*(1+$H$69) -> 0.3240844 | K74: =K65*(1+$H$69) -> 0.10402709 | L74: =L65*(1+$H$69) -> 0.43111227 | M74: =M65*(1+$H$69) -> 0.24106278 | N74: =N65*(1+$H$69) -> 0.21105496 | O74: =O65*(1+$H$69) -> 0.25506642 | P74: =P65*(1+$H$69) -> 0.098025528 | ... AV74: =AV65*(1+$H$69) -> 0.14703829
C76: Ratio of 2017 MICS coverage results to 2021 MICS coverage results
E77: Ratio of BCG vaccine coverage from the 2017 MICS survey to the 2021 MICS survey | F77: % | G77: calc | H77: - | I77: =I70/I48 -> 0.83921492 | J77: =J70/J48 -> 0.92215592 | K77: =K70/K48 -> 0.40320296 | L77: =L70/L48 -> 0.6582177 | M77: =M70/M48 -> 0.55894627 | N77: =N70/N48 -> 0.50094502 | O77: =O70/O48 -> 0.35539294 | P77: =P70/P48 -> 0.48374353 | ... AV77: =AV70/AV48 -> 0.216784
E78: Ratio of 1st dose Penta vaccine coverage from the 2017 MICS survey to the 2021 MICS survey | F78: % | G78: calc | H78: - | I78: =I71/I49 -> 0.8346258 | J78: =J71/J49 -> 0.82483239 | K78: =K71/K49 -> 0.31763161 | L78: =L71/L49 -> 0.60200803 | M78: =M71/M49 -> 0.50826398 | N78: =N71/N49 -> 0.53214589 | O78: =O71/O49 -> 0.33954073 | P78: =P71/P49 -> 0.32643208 | ... AV78: =AV71/AV49 -> 0.23715875
E79: Ratio of 2nd dose Penta vaccine coverage from the 2017 MICS survey to the 2021 MICS survey | F79: % | G79: calc | H79: - | I79: =I72/I50 -> 0.67030146 | J79: =J72/J50 -> 0.56843459 | K79: =K72/K50 -> 0.15959559 | L79: =L72/L50 -> 0.48878648 | M79: =M72/M50 -> 0.4447397 | N79: =N72/N50 -> 0.39275583 | O79: =O72/O50 -> 0.28599675 | P79: =P72/P50 -> 0.2826461 | ... AV79: =AV72/AV50 -> 0.15872887
E80: Ratio of 3rd dose Penta vaccine coverage from the 2017 MICS survey to the 2021 MICS survey | F80: % | G80: calc | H80: - | I80: =I73/I51 -> 0.59113253 | J80: =J73/J51 -> 0.6579818 | K80: =K73/K51 -> 0.14551106 | L80: =L73/L51 -> 0.48928531 | M80: =M73/M51 -> 0.37504963 | N80: =N73/N51 -> 0.29372819 | O80: =O73/O51 -> 0.20510881 | P80: =P73/P51 -> 0.25220729 | ... AV80: =AV73/AV51 -> 0.13553195
E81: Ratio of measles vaccine coverage from the 2017 MICS survey to the 2021 MICS survey | F81: % | G81: calc | H81: - | I81: =I74/I55 -> 0.72087461 | J81: =J74/J55 -> 0.88295062 | K81: =K74/K55 -> 0.18607113 | L81: =L74/L55 -> 0.76024169 | M81: =M74/M55 -> 0.59514048 | N81: =N74/N55 -> 0.48290143 | O81: =O74/O55 -> 0.40353441 | P81: =P74/P55 -> 0.51315691 | ... AV81: =AV74/AV55 -> 0.20619839
E82: Average ratio across vaccine doses | F82: % | G82: calc | H82: - | I82: =AVERAGE(I77:I81) -> 0.73122986 | J82: =AVERAGE(J77:J81) -> 0.77127106 | K82: =AVERAGE(K77:K81) -> 0.24240247 | L82: =AVERAGE(L77:L81) -> 0.59970784 | M82: =AVERAGE(M77:M81) -> 0.49642801 | N82: =AVERAGE(N77:N81) -> 0.44049527 | O82: =AVERAGE(O77:O81) -> 0.31791473 | P82: =AVERAGE(P77:P81) -> 0.37163718 | ... AV82: =AVERAGE(AV77:AV81) -> 0.19088039
C84: Extrapolated 2017 vaccination coverage for the PCV vaccine
E85: Extrapolated proportion of children who receive the 1st dose of the PCV vaccine based on the 2017 MICS survey | F85: % | G85: calc | H85: - | I85: =I52*I$82 -> 0.30349928 | J85: =J52*J$82 -> 0.40265508 | K85: =K52*K$82 -> 0.14691472 | L85: =L52*L$82 -> 0.43184497 | M85: =M52*M$82 -> 0.27009144 | N85: =N52*N$82 -> 0.22820579 | O85: =O52*O$82 -> 0.18950146 | P85: =P52*P$82 -> 0.081027286 | ... AV85: =AV52*AV$82 -> 0.13745149
E86: Extrapolated proportion of children who receive the 2nd dose of the PCV vaccine based on the 2017 MICS survey | F86: % | G86: calc | H86: - | I86: =I53*I$82 -> 0.27790295 | J86: =J53*J$82 -> 0.36022974 | K86: =K53*K$82 -> 0.13455061 | L86: =L53*L$82 -> 0.38806069 | M86: =M53*M$82 -> 0.23136509 | N86: =N53*N$82 -> 0.1934022 | O86: =O53*O$82 -> 0.18091666 | P86: =P53*P$82 -> 0.052779242 | ... AV86: =AV53*AV$82 -> 0.1300062
E87: Extrapolated proportion of children who receive the 3rd dose of the PCV vaccine based on the 2017 MICS survey | F87: % | G87: calc | H87: - | I87: =I54*I$82 -> 0.22890427 | J87: =J54*J$82 -> 0.28463549 | K87: =K54*K$82 -> 0.11709539 | L87: =L54*L$82 -> 0.35387296 | M87: =M54*M$82 -> 0.19810016 | N87: =N54*N$82 -> 0.17225572 | O87: =O54*O$82 -> 0.17137799 | P87: =P54*P$82 -> 0.03716848 | ... AV87: =AV54*AV$82 -> 0.12046096
A89: Estimated baseline vaccination coverage among target populations for New Incentives program
C91: Weighting of coverage estimates from different sources for the BCG, Penta, and PCV vaccines
E92: Weight placed on the results of New Incentives' coverage surveys for estimating BCG, Penta, and PCV coverage | F92: % | G92: feed | H92: =H12 -> - | I92: =I12 -> 1 | J92: =J12 -> 1 | K92: =K12 -> 1 | L92: =L12 -> 1 | M92: =M12 -> 1 | N92: =N12 -> 0.52941176 | O92: =O12 -> 1 | ... AV92: =AV12 -> 0.88235294
E93: Weight placed on the results of the 2021 MICS survey for estimating BCG, Penta, and PCV coverage | F93: % | G93: calc | H93: - | I93: =1-I92 -> 0 | J93: =1-J92 -> 0 | K93: =1-K92 -> 0 | L93: =1-L92 -> 0 | M93: =1-M92 -> 0 | N93: =1-N92 -> 0.47058824 | O93: =1-O92 -> 0 | P93: =1-P92 -> 0.086956522 | ... AV93: =1-AV92 -> 0.11764706
C95: Estimated baseline coverage for the BCG and Penta vaccines
E96: Baseline proportion of children in the target population who receive the BCG vaccine | F96: % | G96: calc | H96: - | I96: =IF(I26="-",I48,(I26*I92)+(I48*I93)) -> 0.55242574 | J96: =IF(J26="-",J48,(J26*J92)+(J48*J93)) -> 0.72882976 | K96: =IF(K26="-",K48,(K26*K92)+(K48*K93)) -> 0.60775837 | L96: =IF(L26="-",L48,(L26*L92)+(L48*L93)) -> 0.63807624 | M96: =IF(M26="-",M48,(M26*M92)+(M48*M93)) -> 0.61526279 | N96: =IF(N26="-",N48,(N26*N92)+(N48*N93)) -> 0.49219015 | O96: =IF(O26="-",O48,(O26*O92)+(O48*O93)) -> 0.40063624 | P96: =IF(P26="-",P48,(P26*P92)+(P48*P93)) -> 0.34860507 | Q96: =IF(Q26="-",Q48,(Q26*Q92)+(Q48*Q93)) -> 0.47657165 | R96: =IF(R26="-",R48,(R26*R$92)+(R48*R$93)) -> 0.90511596 | S96: =IF(S26="-",S48,(S26*S92)+(S48*S93)) -> 0.89072522 | T96: =IF(T26="-",T48,(T26*T92)+(T48*T93)) -> 0.85610968 | U96: =IF(U26="-",U48,(U26*U92)+(U48*U93)) -> 0.84410814 | V96: =IF(V26="-",V48,(V26*V92)+(V48*V93)) -> 0.7891011 | W96: =IF(W26="-",W48,(W26*W92)+(W48*W93)) -> 0.81710469 | X96: =IF(X26="-",X48,(X26*X92)+(X48*X93)) -> 0.64808303 | Y96: =IF(Y26="-",Y48,(Y26*Y92)+(Y48*Y93)) -> 0.93111929 | Z96: =IF(Z26="-",Z48,(Z26*Z92)+(Z48*Z93)) -> 0.83510699 | ... AV96: =IF(AV26="-",AV48,(AV26*AV92)+(AV48*AV93)) -> 0.64274993
E97: Baseline proportion of children in the target population who receive the 1st dose of the Penta vaccine | F97: % | G97: calc | H97: - | I97: =IF(I27="-",I49,(I27*I$92)+(I49*I$93)) -> 0.49339093 | J97: =IF(J27="-",J49,(J27*J$92)+(J49*J$93)) -> 0.67679908 | K97: =IF(K27="-",K49,(K27*K$92)+(K49*K$93)) -> 0.57233748 | L97: =IF(L27="-",L49,(L27*L$92)+(L49*L$93)) -> 0.59765241 | M97: =IF(M27="-",M49,(M27*M$92)+(M49*M$93)) -> 0.56243164 | N97: =IF(N27="-",N49,(N27*N$92)+(N49*N$93)) -> 0.45688369 | O97: =IF(O27="-",O49,(O27*O$92)+(O49*O$93)) -> 0.33809936 | P97: =IF(P27="-",P49,(P27*P$92)+(P49*P$93)) -> 0.27281017 | ... AV97: =IF(AV27="-",AV49,(AV27*AV$92)+(AV49*AV$93)) -> 0.60764175
E98: Baseline proportion of children in the target population who receive the 2nd dose of the Penta vaccine | F98: % | G98: calc | H98: - | I98: =IF(I28="-",I50,(I28*I$92)+(I50*I$93)) -> 0.44736379 | J98: =IF(J28="-",J50,(J28*J$92)+(J50*J$93)) -> 0.63357359 | K98: =IF(K28="-",K50,(K28*K$92)+(K50*K$93)) -> 0.51570409 | L98: =IF(L28="-",L50,(L28*L$92)+(L50*L$93)) -> 0.50729913 | M98: =IF(M28="-",M50,(M28*M$92)+(M50*M$93)) -> 0.48268462 | N98: =IF(N28="-",N50,(N28*N$92)+(N50*N$93)) -> 0.41743904 | O98: =IF(O28="-",O50,(O28*O$92)+(O50*O$93)) -> 0.24294325 | P98: =IF(P28="-",P50,(P28*P$92)+(P50*P$93)) -> 0.2533507 | ... AV98: =IF(AV28="-",AV50,(AV28*AV$92)+(AV50*AV$93)) -> 0.50552412
E99: Baseline proportion of children in the target population who receive the 3rd dose of the Penta vaccine | F99: % | G99: calc | H99: - | I99: =IF(I29="-",I51,(I29*I$92)+(I51*I$93)) -> 0.35420886 | J99: =IF(J29="-",J51,(J29*J$92)+(J51*J$93)) -> 0.50179589 | K99: =IF(K29="-",K51,(K29*K$92)+(K51*K$93)) -> 0.39683399 | L99: =IF(L29="-",L51,(L29*L$92)+(L51*L$93)) -> 0.40964155 | M99: =IF(M29="-",M51,(M29*M$92)+(M51*M$93)) -> 0.36891753 | N99: =IF(N29="-",N51,(N29*N$92)+(N51*N$93)) -> 0.35086445 | O99: =IF(O29="-",O51,(O29*O$92)+(O51*O$93)) -> 0.15439104 | P99: =IF(P29="-",P51,(P29*P$92)+(P51*P$93)) -> 0.18184609 | ... AV99: =IF(AV29="-",AV51,(AV29*AV$92)+(AV51*AV$93)) -> 0.41023644
C101: Estimated baseline coverage for the PCV vaccine
E102: Average coverage rate for the Penta vaccine across doses from the 2021 MICS survey | F102: % | G102: calc | H102: - | I102: =AVERAGE(I49:I51) -> 0.37071416 | J102: =AVERAGE(J49:J51) -> 0.47806125 | K102: =AVERAGE(K49:K51) -> 0.55540449 | L102: =AVERAGE(L49:L51) -> 0.66475183 | M102: =AVERAGE(M49:M51) -> 0.48106163 | N102: =AVERAGE(N49:N51) -> 0.46939347 | O102: =AVERAGE(O49:O51) -> 0.57674056 | P102: =AVERAGE(P49:P51) -> 0.19569174 | ... AV102: =AVERAGE(AV49:AV51) -> 0.69742269
E103: Average coverage rate for the PCV vaccine across doses from the 2021 MICS survey | F103: % | G103: calc | H103: - | I103: =AVERAGE(I52:I54) -> 0.36938066 | J103: =AVERAGE(J52:J54) -> 0.45272467 | K103: =AVERAGE(K52:K54) -> 0.54807022 | L103: =AVERAGE(L52:L54) -> 0.65241692 | M103: =AVERAGE(M52:M54) -> 0.46972685 | N103: =AVERAGE(N52:N54) -> 0.44939091 | O103: =AVERAGE(O52:O54) -> 0.56807278 | P103: =AVERAGE(P52:P54) -> 0.15335298 | ... AV103: =AVERAGE(AV52:AV54) -> 0.67742012
E104: Estimated difference between PCV vaccine coverage and Penta vaccine coverage | F104: % | G104: calc | H104: - | I104: =(I103-I102)/I102 -> -0.0035971223 | J104: =(J103-J102)/J102 -> -0.052998605 | K104: =(K103-K102)/K102 -> -0.013205282 | L104: =(L103-L102)/L102 -> -0.018555667 | M104: =(M103-M102)/M102 -> -0.023562024 | N104: =(N103-N102)/N102 -> -0.042613636 | O104: =(O103-O102)/O102 -> -0.015028902 | P104: =(P103-P102)/P102 -> -0.21635434 | ... AV104: =(AV103-AV102)/AV102 -> -0.028680688
E105: Extrapolated proportion of children surveyed in New Incentives' coverage surveys who received the 1st dose of the PCV vaccine | F105: % | G105: calc | H105: - | I105: =IF(I27="-","-",I27*(1+I$104)) -> 0.49161614 | J105: =IF(J27="-","-",J27*(1+J$104)) -> 0.64092967 | K105: =IF(K27="-","-",K27*(1+K$104)) -> 0.5647796 | L105: =IF(L27="-","-",L27*(1+L$104)) -> 0.58656257 | M105: =IF(M27="-","-",M27*(1+M$104)) -> 0.54917961 | N105: =IF(N27="-","-",N27*(1+N$104)) -> 0.3751337 | O105: =IF(O27="-","-",O27*(1+O$104)) -> 0.3330181 | P105: =IF(P27="-","-",P27*(1+P$104)) -> 0.21265009 | ... AV105: =IF(AV27="-","-",AV27*(1+AV$104)) -> 0.57331932
E106: Extrapolated proportion of children surveyed in New Incentives' coverage surveys who received the 2nd dose of the PCV vaccine | F106: % | G106: calc | H106: - | I106: =IF(I28="-","-",I28*(1+I$104)) -> 0.44575457 | J106: =IF(J28="-","-",J28*(1+J$104)) -> 0.59999507 | K106: =IF(K28="-","-",K28*(1+K$104)) -> 0.50889407 | L106: =IF(L28="-","-",L28*(1+L$104)) -> 0.49788586 | M106: =IF(M28="-","-",M28*(1+M$104)) -> 0.47131159 | N106: =IF(N28="-","-",N28*(1+N$104)) -> 0.35827376 | O106: =IF(O28="-","-",O28*(1+O$104)) -> 0.23929208 | P106: =IF(P28="-","-",P28*(1+P$104)) -> 0.20371126 | ... AV106: =IF(AV28="-","-",AV28*(1+AV$104)) -> 0.46427299
E107: Extrapolated proportion of children surveyed in New Incentives' coverage surveys who received the 3rd dose of the PCV vaccine | F107: % | G107: calc | H107: - | I107: =IF(I29="-","-",I29*(1+I$104)) -> 0.35293473 | J107: =IF(J29="-","-",J29*(1+J$104)) -> 0.4752014 | K107: =IF(K29="-","-",K29*(1+K$104)) -> 0.39159369 | L107: =IF(L29="-","-",L29*(1+L$104)) -> 0.40204037 | M107: =IF(M29="-","-",M29*(1+M$104)) -> 0.36022509 | N107: =IF(N29="-","-",N29*(1+N$104)) -> 0.28384095 | O107: =IF(O29="-","-",O29*(1+O$104)) -> 0.15207071 | P107: =IF(P29="-","-",P29*(1+P$104)) -> 0.14749072 | ... AV107: =IF(AV29="-","-",AV29*(1+AV$104)) -> 0.36844441
E108: Baseline proportion of children in the target population who receive the 1st dose of the PCV vaccine | F108: % | G108: calc | H108: - | I108: =IF(I105="-",I52,(I105*I$92)+(I52*I$93)) -> 0.49161614 | J108: =IF(J105="-",J52,(J105*J$92)+(J52*J$93)) -> 0.64092967 | K108: =IF(K105="-",K52,(K105*K$92)+(K52*K$93)) -> 0.5647796 | L108: =IF(L105="-",L52,(L105*L$92)+(L52*L$93)) -> 0.58656257 | M108: =IF(M105="-",M52,(M105*M$92)+(M52*M$93)) -> 0.54917961 | N108: =IF(N105="-",N52,(N105*N$92)+(N52*N$93)) -> 0.44239613 | O108: =IF(O105="-",O52,(O105*O$92)+(O52*O$93)) -> 0.3330181 | P108: =IF(P105="-",P52,(P105*P$92)+(P52*P$93)) -> 0.21311773 | ... AV108: =IF(AV105="-",AV52,(AV105*AV$92)+(AV52*AV$93)) -> 0.59058673
E109: Baseline proportion of children in the target population who receive the 2nd dose of the PCV vaccine | F109: % | G109: calc | H109: - | I109: =IF(I106="-",I53,(I106*I$92)+(I53*I$93)) -> 0.44575457 | J109: =IF(J106="-",J53,(J106*J$92)+(J53*J$93)) -> 0.59999507 | K109: =IF(K106="-",K53,(K106*K$92)+(K53*K$93)) -> 0.50889407 | L109: =IF(L106="-",L53,(L106*L$92)+(L53*L$93)) -> 0.49788586 | M109: =IF(M106="-",M53,(M106*M$92)+(M53*M$93)) -> 0.47131159 | N109: =IF(N106="-",N53,(N106*N$92)+(N53*N$93)) -> 0.39628905 | O109: =IF(O106="-",O53,(O106*O$92)+(O53*O$93)) -> 0.23929208 | P109: =IF(P106="-",P53,(P106*P$92)+(P53*P$93)) -> 0.19834665 | ... AV109: =IF(AV106="-",AV53,(AV106*AV$92)+(AV53*AV$93)) -> 0.48978056
E110: Baseline proportion of children in the target population who receive the 3rd dose of the PCV vaccine | F110: % | G110: calc | H110: - | I110: =IF(I107="-",I54,(I107*I$92)+(I54*I$93)) -> 0.35293473 | J110: =IF(J107="-",J54,(J107*J$92)+(J54*J$93)) -> 0.4752014 | K110: =IF(K107="-",K54,(K107*K$92)+(K54*K$93)) -> 0.39159369 | L110: =IF(L107="-",L54,(L107*L$92)+(L54*L$93)) -> 0.40204037 | M110: =IF(M107="-",M54,(M107*M$92)+(M54*M$93)) -> 0.36022509 | N110: =IF(N107="-",N54,(N107*N$92)+(N54*N$93)) -> 0.33429231 | O110: =IF(O107="-",O54,(O107*O$92)+(O54*O$93)) -> 0.15207071 | P110: =IF(P107="-",P54,(P107*P$92)+(P54*P$93)) -> 0.1433622 | ... AV110: =IF(AV107="-",AV54,(AV107*AV$92)+(AV54*AV$93)) -> 0.39934281
C112: Weighting of coverage estimates from different sources for the rotavirus vaccine
E113: Weight placed on estimated coverage for the Penta vaccine for estimating rotavirus vaccine coverage | F113: % | G113: input | H113: =Inputs!H83 -> 0.5 | I113: =Inputs!I83 -> - | J113: =Inputs!J83 -> - | K113: =Inputs!K83 -> - | L113: =Inputs!L83 -> - | M113: =Inputs!M83 -> - | N113: =Inputs!N83 -> - | O113: =Inputs!O83 -> - | ... AV113: =Inputs!AV83 -> -
E114: Weight placed on estimated coverage for the PCV vaccine for estimating rotavirus vaccine coverage | F114: % | G114: input | H114: =Inputs!H84 -> 0.5 | I114: =Inputs!I84 -> - | J114: =Inputs!J84 -> - | K114: =Inputs!K84 -> - | L114: =Inputs!L84 -> - | M114: =Inputs!M84 -> - | N114: =Inputs!N84 -> - | O114: =Inputs!O84 -> - | ... AV114: =Inputs!AV84 -> -
E115: Baseline proportion of children in the target population who receive the 1st dose of the rotavirus vaccine | F115: % | G115: calc | H115: - | I115: =(I97*$H$113)+(I108*$H$114) -> 0.49250354 | J115: =(J97*$H$113)+(J108*$H$114) -> 0.65886437 | K115: =(K97*$H$113)+(K108*$H$114) -> 0.56855854 | L115: =(L97*$H$113)+(L108*$H$114) -> 0.59210749 | M115: =(M97*$H$113)+(M108*$H$114) -> 0.55580563 | N115: =(N97*$H$113)+(N108*$H$114) -> 0.44963991 | O115: =(O97*$H$113)+(O108*$H$114) -> 0.33555873 | P115: =(P97*$H$113)+(P108*$H$114) -> 0.24296395 | ... AV115: =(AV97*$H$113)+(AV108*$H$114) -> 0.59911424
E116: Baseline proportion of children in the target population who receive the 2nd dose of the rotavirus vaccine | F116: % | G116: calc | H116: - | I116: =(I98*$H$113)+(I109*$H$114) -> 0.44655918 | J116: =(J98*$H$113)+(J109*$H$114) -> 0.61678433 | K116: =(K98*$H$113)+(K109*$H$114) -> 0.51229908 | L116: =(L98*$H$113)+(L109*$H$114) -> 0.50259249 | M116: =(M98*$H$113)+(M109*$H$114) -> 0.4769981 | N116: =(N98*$H$113)+(N109*$H$114) -> 0.40686404 | O116: =(O98*$H$113)+(O109*$H$114) -> 0.24111767 | P116: =(P98*$H$113)+(P109*$H$114) -> 0.22584867 | ... AV116: =(AV98*$H$113)+(AV109*$H$114) -> 0.49765234
...

Sheet Vaccine efficacy
I1: New Incentives – current states of operation | R1: New Incentives – prospective states | AF1: New Incentives – prospective states
I2: Nigeria | J2: Nigeria | K2: Nigeria | L2: Nigeria | M2: Nigeria | N2: Nigeria | O2: Nigeria | P2: Nigeria | Q2: Nigeria | R2: Nigeria | S2: Nigeria | T2: Nigeria | U2: Nigeria | V2: Nigeria | W2: Nigeria | X2: Nigeria | Y2: Nigeria | Z2: Nigeria | AA2: Nigeria | AB2: Nigeria | AC2: Nigeria | AD2: Nigeria | AE2: Nigeria | AF2: Nigeria | AG2: Nigeria | AH2: Nigeria | AI2: Nigeria | AJ2: Nigeria | AK2: Nigeria | AL2: Nigeria | AM2: Nigeria | AN2: Nigeria | AO2: Nigeria | AP2: Nigeria | AQ2: Nigeria | AR2: Nigeria | AS2: Nigeria | AT2: Nigeria | AU2: Nigeria | AV2: Nigeria
A3: Main calculations | F3: unit | G3: type | H3: Overall | I3: Bauchi | J3: Gombe | K3: Jigawa | L3: Kaduna - cohort 17 | M3: Kano | N3: Katsina | O3: Kebbi | P3: Sokoto | Q3: Zamfara | R3: Abia | S3: Adamawa | T3: Akwa Ibom | U3: Anambra | V3: Bayelsa | W3: Benue | X3: Borno | Y3: Cross River | Z3: Delta | AA3: Ebonyi | AB3: Edo | AC3: Ekiti | AD3: Enugu | AE3: FCT | AF3: Imo | AG3: Kaduna | AH3: Kogi | AI3: Kwara | AJ3: Lagos | AK3: Nasarawa | AL3: Niger | AM3: Niger - cohorts 32 & 36 | AN3: Niger - cohort 34 | AO3: Ogun | AP3: Ondo | AQ3: Osun | AR3: Oyo | AS3: Plateau | AT3: Rivers | AU3: Taraba | AV3: Yobe
E4: Final cost-effectiveness estimate (pulled from "Main calcs" sheet for visibility) | F4: ='Main CEA'!F242 -> xbenchmark | G4: ='Main CEA'!G242 -> calc | H4: ='Main CEA'!H242 -> - | I4: ='Main CEA'!I242 -> 20.039606 | J4: ='Main CEA'!J242 -> 10.020838 | K4: ='Main CEA'!K242 -> 18.177505 | L4: ='Main CEA'!L242 -> 9.0027672 | M4: ='Main CEA'!M242 -> 12.612827 | ... AV4: ='Main CEA'!AV242 -> 11.471963
A5: Vaccine efficacy
C7: Vaccine efficacy rates from meta-analyses
E8: BCG vaccine efficacy rate from Abubakar et al. 2013 | F8: =Inputs!F17 -> % | G8: =Inputs!G17 -> input | H8: =Inputs!H17 -> 0.66 | I8: =Inputs!I17 -> - | J8: =Inputs!J17 -> - | K8: =Inputs!K17 -> - | L8: =Inputs!L17 -> - | M8: =Inputs!M17 -> - | ... AV8: =Inputs!AV17 -> -
E9: DTP vaccine efficacy rate from the LiST meta-analysis (part of the Penta vaccine) | F9: =Inputs!F18 -> % | G9: =Inputs!G18 -> input | H9: =Inputs!H18 -> 0.94 | I9: =Inputs!I18 -> - | J9: =Inputs!J18 -> - | K9: =Inputs!K18 -> - | L9: =Inputs!L18 -> - | M9: =Inputs!M18 -> - | ... AV9: =Inputs!AV18 -> -
E10: Hib vaccine efficacy rate from Thumburu et al. 2015 (part of the Penta vaccine) | F10: =Inputs!F19 -> % | G10: =Inputs!G19 -> input | H10: =Inputs!H19 -> 0.82 | I10: =Inputs!I19 -> - | J10: =Inputs!J19 -> - | K10: =Inputs!K19 -> - | L10: =Inputs!L19 -> - | M10: =Inputs!M19 -> - | ... AV10: =Inputs!AV19 -> -
E11: PCV vaccine efficacy rate from the LiST meta-analysis | F11: =Inputs!F20 -> % | G11: =Inputs!G20 -> input | H11: =Inputs!H20 -> 0.475 | I11: =Inputs!I20 -> - | J11: =Inputs!J20 -> - | K11: =Inputs!K20 -> - | L11: =Inputs!L20 -> - | M11: =Inputs!M20 -> - | ... AV11: =Inputs!AV20 -> -
